Workbook

Sheet Capex_Summary
B1: LAKESHORE HOSPITAL & RESEARCH CENTRE LIMITED
B2: CAPEX BUDGET FOR THE FY 2026-27 | D2: (Figure in Lakhs )
B5: Asset Category | C5: Asset Sub Category | D5: Amount | E5: Potential Savings | G5: Department | H5: Amount | I5: Potential Savings | K5: Asset Category | L5: Amount | M5: Potential Savings
B6: Asset Category | C6: Asset Sub Category | D6: Sum of Total Cost | E6: (INR) | G6: Row Labels | H6: Sum of Total Cost | I6: (INR) | K6: Row Labels | L6: Sum of Total Cost | M6: (INR)
B7: Buildings | C7: Cutout Strcture | D7: 5200000 | E7: =SUMIF(MIXED_new!D3:D178,"Cutout Strcture",MIXED_new!L3:L178)-SUMIF(MIXED_new!D3:D178,"Cutout Strcture",MIXED_new!AB3:AB178) -> 0 | G7: Admin CEO | H7: 3500000 | I7: =SUMIF(MIXED_new!B3:B178,"Admin CEO",MIXED_new!L3:L178)-SUMIF(MIXED_new!B3:B178,"Admin CEO",MIXED_new!AB3:AB178) -> 0 | K7: Buildings | L7: 183051000 | M7: =SUMIF(MIXED_new!C3:C178,"Buildings",MIXED_new!L3:L178)-SUMIF(MIXED_new!C3:C178,"Buildings",MIXED_new!AB3:AB178) -> 0
C8: DG Platform | D8: 9000000 | E8: =SUMIF(MIXED_new!D3:D178,"DG Platform",MIXED_new!L3:L178)-SUMIF(MIXED_new!D3:D178,"DG Platform",MIXED_new!AB3:AB178) -> 0 | G8: Biochemistry | H8: 6200000 | I8: =SUMIF(MIXED_new!B3:B178,"Biochemistry",MIXED_new!L3:L178)-SUMIF(MIXED_new!B3:B178,"Biochemistry",MIXED_new!AB3:AB178) -> 900000 | K8: Computers & IT Equipment | L8: 43448000 | M8: =SUMIF(MIXED_new!C3:C178,"Computers & IT Equipment",MIXED_new!L3:L178)-SUMIF(MIXED_new!C3:C178,"Computers & IT Equipment",MIXED_new!AB3:AB178) -> 0
C9: Electrical / Mechanical Equipments | D9: 4600000 | E9: =SUMIF(MIXED_new!D3:D178,"Electrical / Mechanical Equipments",MIXED_new!L3:L178)-SUMIF(MIXED_new!D3:D178,"Electrical / Mechanical Equipments",MIXED_new!AB3:AB178) -> 0 | G9: Biomedical | H9: 462305000 | I9: =SUMIF(MIXED_new!B3:B178,"Biomedical",MIXED_new!L3:L178)-SUMIF(MIXED_new!B3:B178,"Biomedical",MIXED_new!AB3:AB178) -> 138385000 | K9: Furniture & Fixtures | L9: 31935200 | M9: =SUMIF(MIXED_new!C3:C178,"Furniture & Fixtures",MIXED_new!L3:L178)-SUMIF(MIXED_new!C3:C178,"Furniture & Fixtures",MIXED_new!AB3:AB178) -> 0
C10: Hospital Building | D10: 142251000 | E10: =SUMIF(MIXED_new!D3:D178,"Hospital Building",MIXED_new!L3:L178)-SUMIF(MIXED_new!D3:D178,"Hospital Building",MIXED_new!AB3:AB178) -> 0 | G10: Clinical Nutrition | H10: 3200000 | I10: =SUMIF(MIXED_new!B3:B178,"Clinical Nutrition",MIXED_new!L3:L178)-SUMIF(MIXED_new!B3:B178,"Clinical Nutrition",MIXED_new!AB3:AB178) -> 0 | K10: Intangible Assets | L10: 5800000 | M10: =SUMIF(MIXED_new!C3:C178,"Intangible Assets",MIXED_new!L3:L178)-SUMIF(MIXED_new!C3:C178,"Intangible Assets",MIXED_new!AB3:AB178) -> 0
C11: Internal Infrastructure | D11: 21500000 | E11: =SUMIF(MIXED_new!D3:D178,"Internal Infrastructure",MIXED_new!L3:L178)-SUMIF(MIXED_new!D3:D178,"Internal Infrastructure",MIXED_new!AB3:AB178) -> 0 | G11: Engeering | H11: 62450000 | I11: =SUMIF(MIXED_new!B3:B178,"Engeering",MIXED_new!L3:L178)-SUMIF(MIXED_new!B3:B178,"Engeering",MIXED_new!AB3:AB178) -> 0 | K11: Office Equipment | L11: 15000 | M11: =SUMIF(MIXED_new!C3:C178,"Office Equipment",MIXED_new!L3:L178)-SUMIF(MIXED_new!C3:C178,"Office Equipment",MIXED_new!AB3:AB178) -> 0
C12: Sanitary & Plumbing Fixtures | D12: 500000 | E12: =SUMIF(MIXED_new!D3:D178,"Sanitary & Plumbing Fixtures",MIXED_new!L3:L178)-SUMIF(MIXED_new!D3:D178,"Sanitary & Plumbing Fixtures",MIXED_new!AB3:AB178) -> 0 | G12: Fire & Safety | H12: 34325000 | I12: =SUMIF(MIXED_new!B3:B178,"Fire & Safety",MIXED_new!L3:L178)-SUMIF(MIXED_new!B3:B178,"Fire & Safety",MIXED_new!AB3:AB178) -> 0 | K12: Plant & Machinery | L12: 551115460 | M12: =SUMIF(MIXED_new!C3:C178,"Plant & Machinery",MIXED_new!L3:L178)-SUMIF(MIXED_new!C3:C178,"Plant & Machinery",MIXED_new!AB3:AB178) -> 144754000
B13: Computers & IT Equipment | C13: CCTV | D13: 525000 | E13: =SUMIF(MIXED_new!D3:D178,"CCTV",MIXED_new!L3:L178)-SUMIF(MIXED_new!D3:D178,"CCTV",MIXED_new!AB3:AB178) -> 0 | G13: Food & Beverage | H13: 3382460 | I13: =SUMIF(MIXED_new!B3:B178,"Food & Beverage",MIXED_new!L3:L178)-SUMIF(MIXED_new!B3:B178,"Food & Beverage",MIXED_new!AB3:AB178) -> 0 | K13: Vehicles | L13: 6700000 | M13: =SUMIF(MIXED_new!C3:C178,"Vehicles",MIXED_new!L3:L178)-SUMIF(MIXED_new!C3:C178,"Vehicles",MIXED_new!AB3:AB178) -> 0
C14: Desktop computers | D14: 6420000 | E14: =SUMIF(MIXED_new!D3:D178,"Desktop computers",MIXED_new!L3:L178)-SUMIF(MIXED_new!D3:D178,"Desktop computers",MIXED_new!AB3:AB178) -> 0 | G14: General Store | H14: 820000 | I14: =SUMIF(MIXED_new!B3:B178,"General Store",MIXED_new!L3:L178)-SUMIF(MIXED_new!B3:B178,"General Store",MIXED_new!AB3:AB178) -> 0 | K14: (blank) | L14: 0 | M14: =(MIXED_new!L179-MIXED_new!AB179)-SUM(M7:M13) -> 0
C15: Digittalization /Automation | D15: 7500000 | E15: =SUMIF(MIXED_new!D3:D178,"Digittalization /Automation",MIXED_new!L3:L178)-SUMIF(MIXED_new!D3:D178,"Digittalization /Automation",MIXED_new!AB3:AB178) -> 0 | G15: Hematology | H15: 8000000 | I15: =SUMIF(MIXED_new!B3:B178,"Hematology",MIXED_new!L3:L178)-SUMIF(MIXED_new!B3:B178,"Hematology",MIXED_new!AB3:AB178) -> 0 | K15: Grand Total | L15: 822064660 | M15: =MIXED_new!L179-MIXED_new!AB179 -> 144754000
C16: Laptops | D16: 1500000 | E16: =SUMIF(MIXED_new!D3:D178,"Laptops",MIXED_new!L3:L178)-SUMIF(MIXED_new!D3:D178,"Laptops",MIXED_new!AB3:AB178) -> 0 | G16: Histopathology | H16: 3600000 | I16: =SUMIF(MIXED_new!B3:B178,"Histopathology",MIXED_new!L3:L178)-SUMIF(MIXED_new!B3:B178,"Histopathology",MIXED_new!AB3:AB178) -> 0
C17: Networking equipment | D17: 25500000 | E17: =SUMIF(MIXED_new!D3:D178,"Networking equipment",MIXED_new!L3:L178)-SUMIF(MIXED_new!D3:D178,"Networking equipment",MIXED_new!AB3:AB178) -> 0 | G17: House Keeping | H17: 1524000 | I17: =SUMIF(MIXED_new!B3:B178,"House Keeping",MIXED_new!L3:L178)-SUMIF(MIXED_new!B3:B178,"House Keeping",MIXED_new!AB3:AB178) -> 0
C18: Other Items | D18: 500000 | E18: =SUMIF(MIXED_new!D3:D178,"Other Items",MIXED_new!L3:L178)-SUMIF(MIXED_new!D3:D178,"Other Items",MIXED_new!AB3:AB178) -> 0 | G18: HRD | H18: 208000 | I18: =SUMIF(MIXED_new!B3:B178,"HRD",MIXED_new!L3:L178)-SUMIF(MIXED_new!B3:B178,"HRD",MIXED_new!AB3:AB178) -> 0
C19: Printers, scanners | D19: 1503000 | E19: =SUMIF(MIXED_new!D3:D178,"Printers, scanners",MIXED_new!L3:L178)-SUMIF(MIXED_new!D3:D178,"Printers, scanners",MIXED_new!AB3:AB178) -> 0 | G19: IT | H19: 47500000 | I19: =SUMIF(MIXED_new!B3:B178,"IT",MIXED_new!L3:L178)-SUMIF(MIXED_new!B3:B178,"IT",MIXED_new!AB3:AB178) -> 0
B20: Furniture & Fixtures | C20: Chairs, tables, cupboards | D20: 1020000 | E20: =SUMIF(MIXED_new!D3:D178,"Chairs, tables, cupboards",MIXED_new!L3:L178)-SUMIF(MIXED_new!D3:D178,"Chairs, tables, cupboards",MIXED_new!AB3:AB178) -> 0 | G20: Pharmacy | H20: 2162200 | I20: =SUMIF(MIXED_new!B3:B178,"Pharmacy",MIXED_new!L3:L178)-SUMIF(MIXED_new!B3:B178,"Pharmacy",MIXED_new!AB3:AB178) -> 0
C21: Curtains, blinds | D21: 27804000 | E21: =SUMIF(MIXED_new!D3:D178,"Curtains, blinds",MIXED_new!L3:L178)-SUMIF(MIXED_new!D3:D178,"Curtains, blinds",MIXED_new!AB3:AB178) -> 0 | G21: PHYSIOTHERAPY | H21: 10938000 | I21: =SUMIF(MIXED_new!B3:B178,"*physiotherapy*",MIXED_new!L3:L178)-SUMIF(MIXED_new!B3:B178,"*physiotherapy*",MIXED_new!AB3:AB178) -> 5469000
C22: Office furniture | D22: 105000 | E22: =SUMIF(MIXED_new!D3:D178,"Office furniture",MIXED_new!L3:L178)-SUMIF(MIXED_new!D3:D178,"Office furniture",MIXED_new!AB3:AB178) -> 0 | G22: Project | H22: 171950000 | I22: =SUMIF(MIXED_new!B3:B178,"Project",MIXED_new!L3:L178)-SUMIF(MIXED_new!B3:B178,"Project",MIXED_new!AB3:AB178) -> 0
C23: Storage Cabinet / Pharmacy Furniture | D23: 1506200 | E23: =SUMIF(MIXED_new!D3:D178,"Storage Cabinet / Pharmacy Furniture",MIXED_new!L3:L178)-SUMIF(MIXED_new!D3:D178,"Storage Cabinet / Pharmacy Furniture",MIXED_new!AB3:AB178) -> 0 | G23: (blank) | H23: 0 | I23: =(MIXED_new!L179-MIXED_new!AB179)-SUM(I7:I22) -> 0
C24: Lab Furniutre | D24: 1500000 | E24: =SUMIF(MIXED_new!D3:D178,"Lab Furniutre",MIXED_new!L3:L178)-SUMIF(MIXED_new!D3:D178,"Lab Furniutre",MIXED_new!AB3:AB178) -> 0 | G24: Grand Total | H24: 822064660 | I24: =MIXED_new!L179-MIXED_new!AB179 -> 144754000
B25: Intangible Assets | C25: Computer software | D25: 5800000 | E25: =SUMIF(MIXED_new!D3:D178,"Computer software",MIXED_new!L3:L178)-SUMIF(MIXED_new!D3:D178,"Computer software",MIXED_new!AB3:AB178) -> 0
B26: Office Equipment | C26: Telephones & EPABX systems | D26: 15000 | E26: =SUMIF(MIXED_new!D3:D178,"Telephones & EPABX systems",MIXED_new!L3:L178)-SUMIF(MIXED_new!D3:D178,"Telephones & EPABX systems",MIXED_new!AB3:AB178) -> 0
B27: Plant & Machinery | C27: Biomedical Equipment | D27: 491943000 | E27: =SUMIF(MIXED_new!D3:D178,"Biomedical Equipment",MIXED_new!L3:L178)-SUMIF(MIXED_new!D3:D178,"Biomedical Equipment",MIXED_new!AB3:AB178) -> 144754000
C28: Electrical / Mechanical Equipments | D28: 46050000 | E28: =SUMIF(MIXED_new!D3:D178,"Electrical / Mechanical Equipments",MIXED_new!L3:L178)-SUMIF(MIXED_new!D3:D178,"Electrical / Mechanical Equipments",MIXED_new!AB3:AB178) -> 0
C29: Electrical Equipments | D29: 700000 | E29: =SUMIF(MIXED_new!D3:D178,"Electrical Equipments",MIXED_new!L3:L178)-SUMIF(MIXED_new!D3:D178,"Electrical Equipments",MIXED_new!AB3:AB178) -> 0
C30: Electrical installations | D30: 3000000 | E30: =SUMIF(MIXED_new!D3:D178,"Electrical installations",MIXED_new!L3:L178)-SUMIF(MIXED_new!D3:D178,"Electrical installations",MIXED_new!AB3:AB178) -> 0
C31: Kitchen / Service Equipment | D31: 2786400 | E31: =SUMIF(MIXED_new!D3:D178,"Kitchen / Service Equipment",MIXED_new!L3:L178)-SUMIF(MIXED_new!D3:D178,"Kitchen / Service Equipment",MIXED_new!AB3:AB178) -> 0
C32: Kitchen utensils | D32: 596060 | E32: =SUMIF(MIXED_new!D3:D178,"Kitchen utensils",MIXED_new!L3:L178)-SUMIF(MIXED_new!D3:D178,"Kitchen utensils",MIXED_new!AB3:AB178) -> 0
C33: Palnt | D33: 5400000 | E33: =SUMIF(MIXED_new!D3:D178,"Palnt",MIXED_new!L3:L178)-SUMIF(MIXED_new!D3:D178,"Palnt",MIXED_new!AB3:AB178) -> 0
C34: Refrigeration Equipment | D34: 640000 | E34: =SUMIF(MIXED_new!D3:D178,"Refrigeration Equipment",MIXED_new!L3:L178)-SUMIF(MIXED_new!D3:D178,"Refrigeration Equipment",MIXED_new!AB3:AB178) -> 0
B35: Vehicles | C35: Ambulances | D35: 3200000 | E35: =SUMIF(MIXED_new!D3:D178,"Ambulances",MIXED_new!L3:L178)-SUMIF(MIXED_new!D3:D178,"Ambulances",MIXED_new!AB3:AB178) -> 0
C36: Passenger | D36: 3500000 | E36: =SUMIF(MIXED_new!D3:D178,"Passenger",MIXED_new!L3:L178)-SUMIF(MIXED_new!D3:D178,"Passenger",MIXED_new!AB3:AB178) -> 0
B37: (blank) | C37: (blank) | D37: 0 | E37: =(MIXED_new!L179-MIXED_new!AB179)-SUM(E7:E36) -> 0
B38: Grand Total | D38: 822064660 | E38: =MIXED_new!L179-MIXED_new!AB179 -> 144754000
B41: ITEMS REDUCED OR REMOVED FROM CAPEX BUDGET — FY 2026-27
B43: SL No | C43: Department | D43: Item Description | E43: Qty | F43: Original Budget (INR) | G43: Final Cost (INR) | H43: Savings (INR) | I43: Type | J43: Status / Notes
B44: 61 | C44: Biomedical | D44: Uretero reno fiber Scope | E44: 4 → 1 | F44: 1600000 | G44: 400000 | H44: 1200000 | I44: Reduced | J44: Approved — Qty reduced
B45: 63 | C45: Biomedical | D45: Dental chair | E45: 4 → 2 | F45: 1600000 | G45: 800000 | H45: 800000 | I45: Reduced | J45: Approved — Qty reduced
B46: 71 | C46: Biomedical | D46: Referal monitor | E46: 4 → 2 | F46: 1200000 | G46: 600000 | H46: 600000 | I46: Reduced | J46: Approved — Qty reduced
B47: 157 | C47: Biomedical | D47: Vascular doppler | E47: 2 → 1 | F47: 120000 | G47: 60000 | H47: 60000 | I47: Reduced | J47: Approved — Qty reduced
B48: 3 | C48: Biomedical | D48: Digital Pathology | E48: 1 | F48: 30000000 | G48: — | H48: 30000000 | I48: Removed | J48: On Hold
B49: 6 | C49: Biomedical | D49: Digital Slide Scanner | E49: 1 | F49: 25000000 | G49: — | H49: 25000000 | I49: Removed | J49: On Hold
B50: 9 | C50: Biomedical | D50: LASER | E50: 1 | F50: 15000000 | G50: — | H50: 15000000 | I50: Removed | J50: On Hold
B51: 1 | C51: Biomedical | D51: Electric bed | E51: 50 | F51: 7500000 | G51: — | H51: 7500000 | I51: Removed | J51: On Hold — Awaiting operations
B52: 18 | C52: Biomedical | D52: Portable DR | E52: 1 | F52: 6000000 | G52: — | H52: 6000000 | I52: Removed | J52: On Hold
B53: 22 | C53: Biomedical | D53: WAB for ultrasound | E53: 1 | F53: 6000000 | G53: — | H53: 6000000 | I53: Removed | J53: On Hold
B54: 24 | C54: Biomedical | D54: Ortho Surgical instruments | E54: 1 | F54: 5000000 | G54: — | H54: 5000000 | I54: Removed | J54: On Hold — Waiting CSSD list
B55: 175 | C55: Biomedical | D55: Rota flow | E55: 1 | F55: 4500000 | G55: — | H55: 4500000 | I55: Removed | J55: No final cost entered
B56: 27 | C56: Biomedical | D56: Anesthesia work station MRI | E56: 1 | F56: 4500000 | G56: — | H56: 4500000 | I56: Removed | J56: Rejected
B57: 32 | C57: Biomedical | D57: Incubator with portable ventilator | E57: 1 | F57: 3500000 | G57: — | H57: 3500000 | I57: Removed | J57: On Hold — Pending discussion
B58: 37 | C58: Biomedical | D58: Surgical instruments | E58: 1 | F58: 3000000 | G58: — | H58: 3000000 | I58: Removed | J58: On Hold — Waiting CSSD list
B59: 55 | C59: Biomedical | D59: Surgical diathermy - Ligasure | E59: 1 | F59: 2000000 | G59: — | H59: 2000000 | I59: Removed | J59: PO Released — No final cost
... B93: 170 | C93: PHYSIOTHERAPY | D93: Blood flow restriction therapy units | E93: 1 | F93: 60000 | G93: — | H93: 60000 | I93: Removed | J93: On Hold
B95: TOTAL SAVINGS — All Reduced + Removed Items (50) | F95: 146614000 | G95: 1860000 | H95: 144754000

Sheet Capex_Details
B1: LAKESHORE HOSPITAL & RESEARCH CENTRE LIMITED
B2: CAPEX REQUIREMENT FOR THE FY 2026-27
B3: SL.No | C3: Department | D3: Asset Category | E3: Asset Sub Category | F3: Project Description /Item Name | G3: QTY | H3: Category of CAPEX | I3: Location/ Area of Implementation | J3: Estimated Cost (INR) | K3: XX | L3: XX | M3: Total Cost | N3: Source of Pricing Information | O3: Proposed Timeline for Investment | P3: XX | Q3: Month (Put to Use) | R3: Purpose of the Investment | S3: Impact of Non-Investment | T3: Specifications/Features Required | U3: Maintenance/ Operational Costs | V3: Justification
J4: Equipment Cost | K4: Installation Cost | L4: Other Costs (Specify) | M4: Total | O4: Start Date | P4: End Date
B5: =B4+1 -> 1 | C5: Project | D5: Buildings | E5: Hospital Building | F5: Casualty | G5: 1 | H5: Renovation | I5: Main block G.F. | J5: 38000000 | K5: 0 | L5: 0 | M5: =SUM(J5:L5) -> 38000000 | N5: Inviting tender | O5: 46204 | P5: 46356 | Q5: November | R5: Facility improvement. | S5: Patient capacity enhancing.
B6: =B5+1 -> 2 | C6: Project | D6: Buildings | E6: Hospital Building | F6: ICU Complex | G6: 1 | H6: Renovation | I6: 1st Floor Main Block | J6: 22500000 | K6: 0 | L6: 0 | M6: =SUM(J6:L6) -> 22500000 | N6: Work awarded | O6: 45981 | P6: 46132 | Q6: April | R6: Combine ICUs in one area. | S6: For reducing staff & electrical Consumption | U6: 200000 | V6: Existing ICU space utilise for another purpose
B7: =B6+1 -> 3 | C7: Project | D7: Buildings | E7: Hospital Building | F7: Regularization purpose (fee) | G7: 1 | H7: Other | I7: Main block | J7: 16400000 | K7: 0 | L7: 0 | M7: =SUM(J7:L7) -> 16400000 | N7: Government Fee & Consultant | O7: 46183 | P7: 46203 | Q7: June | R7: Legal Purpose | V7: Statutory Purpose
B8: =B7+1 -> 4 | C8: Project | D8: Buildings | E8: Hospital Building | F8: Ultrasound & Ortho Dept. Renovation | G8: 1 | H8: Renovation | I8: Main block G.F. | J8: 16000000 | K8: 0 | L8: 0 | M8: =SUM(J8:L8) -> 16000000 | N8: Inviting tender | O8: 46042 | P8: 46162 | Q8: May | R8: More space for smooth opeartion | S8: Patient statisfaction
B9: =B8+1 -> 5 | C9: Project | D9: Buildings | E9: Hospital Building | F9: Renal kidney transplant centre | G9: 1 | H9: Renovation | I9: Main block - 1st floor | J9: 15000000 | K9: 0 | L9: 0 | M9: =SUM(J9:L9) -> 15000000 | N9: Inviting tender | O9: 46208 | P9: 46314 | Q9: October | R9: Combine Rental transplant ICU 1 & 2 one area. | S9: For reducing staff & ele. Consumption reducing.
B10: =B9+1 -> 6 | C10: Project | D10: Buildings | E10: Hospital Building | F10: Paediatric OP construction works | G10: 1 | H10: Renovation | I10: Main block 2nd floor | J10: 15000000 | K10: 0 | L10: 0 | M10: =SUM(J10:L10) -> 15000000 | N10: Inviting tender | O10: 46157 | P10: 46275 | Q10: September | R10: Patient friendly.
B11: =B10+1 -> 7 | C11: Project | D11: Buildings | E11: Internal Infrastructure | F11: Porch & Front area | G11: 1 | H11: Renovation | I11: Main block | J11: 14000000 | K11: 0 | L11: 0 | M11: =SUM(J11:L11) -> 14000000 | N11: Inviting tender | O11: 46091 | P11: 46152 | Q11: May | R11: Beautifications & Smooth traffic | S11: Patient friendly | U11: 50000
B12: =B11+1 -> 8 | C12: Project | D12: Buildings | E12: DG Platform | F12: DG overhead platform strengthening & RECD fixing works | G12: 3 | H12: New requirment | I12: Electrical area (DG) | J12: 9000000 | K12: 0 | L12: 0 | M12: =SUM(J12:L12) -> 9000000 | N12: Inviting tender | O12: 46111 | P12: 46157 | Q12: May | R12: Pollution control board rules. | S12: Statutory government rule. | U12: 50000 | V12: Based on pollution control board order.
B13: =B12+1 -> 9 | C13: Engeering | D13: Plant & Machinery | E13: Palnt | F13: STP renovation | G13: 1 | H13: Renovation | I13: Main block | J13: 3700000 | K13: 0 | L13: 0 | M13: =SUM(J13:L13) -> 3700000 | N13: Inviting tender | O13: 46042 | P13: 46091 | Q13: April | R13: PCB related | S13: Environmental Friendly.
B14: =B13+1 -> 10 | C14: Engeering | D14: Plant & Machinery | E14: Palnt | F14: UF Replacement | G14: 1 | H14: Replacement | I14: Main block | J14: 800000 | K14: 0 | L14: 0 | M14: =SUM(J14:L14) -> 800000 | N14: Inviting tender | O14: 46063 | P14: 46101 | Q14: April | R14: Treated water reusage | S14: Water for Gardening purpose.
B15: =B14+1 -> 11 | C15: Engeering | D15: Plant & Machinery | E15: Palnt | F15: Domestic Line hot water and flush line | G15: 1 | H15: Replacement | I15: Main block | J15: 900000 | K15: 0 | L15: 0 | M15: =SUM(J15:L15) -> 900000 | N15: Inviting tender | O15: 46126 | P15: 46252 | Q15: August | R15: Prevent water leak | S15: Water saving.
B16: =B15+1 -> 12 | C16: Project | D16: Buildings | E16: Hospital Building | F16: Architectural & PMC Fees | J16: 7000000 | K16: 0 | L16: 0 | M16: =SUM(J16:L16) -> 7000000 | N16: Inviting tender | Q16: September | R16: Renovation purpose
B17: =B16+1 -> 13 | C17: Project | D17: Buildings | E17: Hospital Building | F17: Main block rooms renovation & delux room renovation | G17: 104 | H17: Renovation | I17: Main block | J17: 5000000 | K17: 0 | L17: 0 | M17: =SUM(J17:L17) -> 5000000 | N17: Inviting tender | O17: 46023 | P17: 46387 | Q17: December | R17: Beautifications
B18: =B17+1 -> 14 | C18: Project | D18: Buildings | E18: Internal Infrastructure | F18: Road & walkway beautification works | G18: 1 | H18: Renovation | I18: Arch gate to 4th gate & casualty | J18: 4000000 | K18: 0 | L18: 0 | M18: =SUM(J18:L18) -> 4000000 | N18: Inviting tender | O18: 46058 | P18: 46122 | Q18: April | R18: Beautifications | S18: Smooth travelling | U18: 50000
B19: =B18+1 -> 15 | C19: Project | D19: Buildings | E19: Cutout Strcture | F19: Central Cutout renovation work | G19: 1 | H19: Renovation | I19: Main block G.F. | J19: 3400000 | K19: 0 | L19: 0 | M19: =SUM(J19:L19) -> 3400000 | N19: Inviting tender | O19: 45698 | P19: 45805 | Q19: May | R19: Stoppage of water sepage & fungus reducing | S19: Beautifications | U19: 50000
B20: =B19+1 -> 16 | C20: Project | D20: Buildings | E20: Cutout Strcture | F20: Exterior Painting - Main block | G20: 1 | H20: Maintenace | I20: Main block | J20: 1800000 | K20: 0 | L20: 0 | M20: =SUM(J20:L20) -> 1800000 | N20: Inviting tender | O20: 46122 | P20: 46157 | Q20: May | R20: Beautifications | S20: Clealiness
B21: =B20+1 -> 17 | C21: Project | D21: Buildings | E21: Hospital Building | F21: Cold room | G21: 1 | H21: Replacement | I21: Main block 2nd floor | J21: 1500000 | K21: 0 | L21: 0 | M21: =SUM(J21:L21) -> 1500000 | N21: Inviting tender | O21: 46085 | P21: 46110 | Q21: April | R21: Based on the request from Pharmacy
B22: =B21+1 -> 18 | C22: Engeering | D22: Plant & Machinery | E22: Electrical / Mechanical Equipments | F22: Multi Level Parking | G22: 1 | H22: New requirment | I22: Parking Area | J22: 44100000 | K22: 0 | L22: 0 | M22: =SUM(J22:L22) -> 44100000 | N22: Inviting tender | O22: 46023 | P22: 46188 | Q22: June | R22: Facility improvement.
B23: =B22+1 -> 19 | C23: Engeering | D23: Plant & Machinery | E23: Electrical / Mechanical Equipments | F23: Coil, Electrical, Water, Soil testing etc. | G23: 1 | H23: New requirment | I23: Parking Area | J23: 750000 | K23: 0 | L23: 0 | M23: =SUM(J23:L23) -> 750000 | N23: Inviting tender | O23: 46023 | P23: 46042 | Q23: April | R23: Facility improvement.
B24: =B23+1 -> 20 | C24: Engeering | D24: Buildings | E24: Internal Infrastructure | F24: Parking area leveling & inter lock laying | G24: 1 | H24: New requirment | I24: Parking Area | J24: 3500000 | K24: 0 | L24: 0 | M24: =SUM(J24:L24) -> 3500000 | N24: Inviting tender | O24: 46183 | P24: 46223 | Q24: April | R24: Facility improvement.
B25: =B24+1 -> 21 | C25: Project | D25: Buildings | E25: Hospital Building | F25: 8th floor Premium suite renovation | G25: 1 | H25: Renovation | I25: Main block | J25: 1200000 | K25: 0 | L25: 0 | M25: =SUM(J25:L25) -> 1200000 | N25: Inviting tender | O25: 46019 | P25: 46050 | Q25: April | R25: Beautifications
B26: =B25+1 -> 22 | C26: Project | D26: Buildings | E26: Hospital Building | F26: Fire Escape & support painting | G26: 1 | H26: Maintenace | I26: Main block | J26: 900000 | K26: 0 | L26: 0 | M26: =SUM(J26:L26) -> 900000 | N26: Inviting tender | O26: 46037 | P26: 46122 | Q26: April | R26: Prevent corrosion | S26: More life.
B27: =B26+1 -> 23 | C27: Engeering | D27: Buildings | E27: Electrical / Mechanical Equipments | F27: Lowside (New block) BMS activation | G27: 1 | H27: Maintenace | I27: New block | J27: 2000000 | K27: 0 | L27: 0 | M27: =SUM(J27:L27) -> 2000000 | N27: Inviting tender | O27: 46117 | P27: 46171 | Q27: May | R27: Centralizing HVAC controle optimizing building performance.
B28: =B27+1 -> 24 | C28: Engeering | D28: Buildings | E28: Electrical / Mechanical Equipments | F28: AHU coil replacement | G28: 4 | H28: Maintenace | I28: All Blocks | J28: 1000000 | K28: 0 | L28: 0 | M28: =SUM(J28:L28) -> 1000000 | N28: Inviting tender | O28: 46055 | P28: 46127 | Q28: April | R28: HVAC performance improving
B29: =B28+1 -> 25 | C29: Engeering | D29: Buildings | E29: Electrical / Mechanical Equipments | F29: AHU unit replacement | G29: 5 | H29: Maintenace | I29: All Blocks | J29: 1000000 | K29: 0 | L29: 0 | M29: =SUM(J29:L29) -> 1000000 | N29: Inviting tender | O29: 46055 | P29: 46127 | Q29: April | R29: HVAC performance improving
B30: =B29+1 -> 26 | C30: Engeering | D30: Buildings | E30: Hospital Building | F30: Chilled water line replacement (Plastic Surgery, NSICU, OT Recovery) 1 1/2" pipe | G30: 1 | H30: Replacement | I30: All Blocks | J30: 2000000 | K30: 0 | L30: 0 | M30: =SUM(J30:L30) -> 2000000 | N30: Inviting tender | O30: 46054 | P30: 46080 | Q30: April | R30: Performance improving
B31: =B30+1 -> 27 | C31: Engeering | D31: Buildings | E31: Hospital Building | F31: Cooling Tower valve replacement | G31: 1 | H31: Replacement | I31: All Blocks | J31: 500000 | K31: 0 | L31: 0 | M31: =SUM(J31:L31) -> 500000 | N31: Inviting tender | O31: 46082 | P31: 46111 | Q31: April | R31: Performance improving
B32: =B31+1 -> 28 | C32: Engeering | D32: Buildings | E32: Electrical / Mechanical Equipments | F32: HRW recovery wheel replacement | G32: 1 | H32: Replacement | I32: All Blocks | J32: 200000 | K32: 0 | L32: 0 | M32: =SUM(J32:L32) -> 200000 | N32: Inviting tender | O32: 46023 | P32: 46052 | Q32: April | R32: Performance improving
B33: =B32+1 -> 29 | C33: Engeering | D33: Plant & Machinery | E33: Electrical / Mechanical Equipments | F33: Split AC replacement (call centre, drivers cabin, 635, 636 doctor's resting area, Biochemistry) | G33: 1 | H33: Replacement | I33: Main Block | J33: 300000 | K33: 0 | L33: 0 | M33: =SUM(J33:L33) -> 300000 | N33: Inviting tender | O33: 46023 | P33: 46052 | Q33: April | R33: Performance improving
B34: =B33+1 -> 30 | C34: Engeering | D34: Plant & Machinery | E34: Electrical / Mechanical Equipments | F34: 5 TR , 1 Tower AC Spare | G34: 2 | H34: Replacement/Spare | I34: All Blocks | J34: 400000 | K34: 0 | L34: 0 | M34: =SUM(J34:L34) -> 400000 | N34: Inviting tender | O34: 46082 | P34: 45746 | Q34: April | R34: Performance improving
B35: =B34+1 -> 31 | C35: Engeering | D35: Buildings | E35: Hospital Building | F35: Main Lobby Glass fixing | G35: 1 | H35: Maintenace | I35: Main block | J35: 400000 | K35: 0 | L35: 0 | M35: =SUM(J35:L35) -> 400000 | N35: Inviting tender | O35: 46082 | P35: 46111 | Q35: April | R35: HVAC performance
B36: =B35+1 -> 32 | C36: Engeering | D36: Plant & Machinery | E36: Electrical / Mechanical Equipments | F36: Robotic duct cleaning in OT passage | G36: 1 | H36: Maintenace | I36: Main block | J36: 400000 | K36: 0 | L36: 0 | M36: =SUM(J36:L36) -> 400000 | N36: Inviting tender | O36: 46058 | P36: 46080 | Q36: April | R36: Dust removal
B37: =B36+1 -> 33 | C37: Engeering | D37: Plant & Machinery | E37: Electrical / Mechanical Equipments | F37: Microfilter & pre filter changing in OT | G37: 1 | H37: Maintenace | I37: Main block | J37: 100000 | K37: 0 | L37: 0 | M37: =SUM(J37:L37) -> 100000 | N37: Inviting tender | O37: 46026 | P37: 46050 | Q37: April | R37: Mandatory requirement
B38: =B37+1 -> 34 | C38: Engeering | D38: Plant & Machinery | E38: Electrical Equipments | F38: Pharmacy Vaccine Refrigerator | G38: 1 | H38: Replacement | I38: All Blocks | J38: 200000 | K38: 0 | L38: 0 | M38: =SUM(J38:L38) -> 200000 | N38: Inviting tender | O38: 46085 | P38: 46110 | Q38: April | R38: Based on the request from Pharmacy
B39: =B38+1 -> 35 | C39: Engeering | D39: Plant & Machinery | E39: Electrical Equipments | F39: Pharmacy Refrigerator | G39: 2 | H39: Replacement | I39: All Blocks | J39: 200000 | K39: 0 | L39: 0 | M39: =SUM(J39:L39) -> 200000 | N39: Inviting tender | O39: 46085 | P39: 46110 | Q39: April | R39: Based on the request from Pharmacy
B40: =B39+1 -> 36 | C40: Project | D40: Buildings | E40: Sanitary & Plumbing Fixtures | F40: Flush with cistern fixing | G40: 40 | H40: Maintenace | I40: New block - various rooms | J40: 500000 | K40: 0 | L40: 0 | M40: =SUM(J40:L40) -> 500000 | N40: Purchasing | O40: 46047 | P40: 46096 | Q40: April | R40: Unavailiability parts (schell brand fittings) | S40: Smooth Operations
B41: =B40+1 -> 37 | C41: Project | D41: Buildings | E41: Electrical / Mechanical Equipments | F41: Automatic doors installation works | G41: 1 | H41: Maintenace | I41: New Block | J41: 400000 | K41: 0 | L41: 0 | M41: =SUM(J41:L41) -> 400000 | N41: Inviting tender | O41: 46091 | P41: 46109 | Q41: April | R41: Safety & energy saving | S41: Increasing airconditioning efficiency.
B42: =B41+1 -> 38 | C42: Project | D42: Buildings | E42: Hospital Building | F42: Outside noise complaint rectifications | G42: 1 | H42: Maintenace | I42: New block | J42: 350000 | K42: 0 | L42: 0 | M42: =SUM(J42:L42) -> 350000 | N42: Inviting tender | O42: 46160 | P42: 46183 | Q42: June | R42: Avoiding noise complaint from patient (exteranal louver side) | S42: Patient statisfaction
B43: =B42+1 -> 39 | C43: House Keeping | D43: Furniture & Fixtures | E43: Chairs, tables, cupboards | F43: Wheel chairs | G43: 30 | H43: Replacement | I43: Main block | J43: 270000 | K43: 0 | L43: 0 | M43: =SUM(J43:L43) -> 270000 | O43: 46113 | P43: 46203 | Q43: June | V43: Replacement of Old chair
B44: =B43+1 -> 40 | C44: House Keeping | D44: Furniture & Fixtures | E44: Chairs, tables, cupboards | F44: Chairs | G44: 50 | H44: Replacement | I44: Main block | J44: 150000 | K44: 0 | L44: 0 | M44: =SUM(J44:L44) -> 150000 | O44: 46113 | P44: 46203 | Q44: June | V44: Around 50 Nos of Old Visiting & computer chairs to be replaced with new one
B45: =B44+1 -> 41 | C45: House Keeping | D45: Furniture & Fixtures | E45: Chairs, tables, cupboards | F45: Airport Chairs | G45: 50 | H45: Replacement | I45: Radiology & Paediatric / oncology OPDs | J45: 600000 | K45: 0 | L45: 0 | M45: =SUM(J45:L45) -> 600000 | O45: 46143 | P45: 46233 | Q45: July | R45: Airport Chairs of Radiology & Paediatric / oncology OPDs to be replaced & added with new one ( 50 Nos ) | V45: Airport Chairs of Radiology & Paediatric / oncology OPDs to be replaced & added with new one ( 50 Nos )
B46: =B45+1 -> 42 | C46: House Keeping | D46: Furniture & Fixtures | E46: Curtains, blinds | F46: Patient privacy curtains | G46: 56 | H46: New requirment | I46: New Block | J46: 504000 | K46: 0 | L46: 0 | M46: =SUM(J46:L46) -> 504000 | O46: 46113 | P46: 46233 | Q46: July | R46: Patient privacy Curtains to be fixed in All Deluxe rooms ( 56 Nos ) | V46: Patient privacy Curtains to be fixed in All Deluxe rooms ( 56 Nos )
B47: =B46+1 -> 43 | C47: Food & Beverage | D47: Plant & Machinery | E47: Kitchen utensils | F47: Urali Aluminium Big | G47: 2 | H47: Replacement | I47: Kitchen | J47: 46000 | K47: 0 | L47: 0 | M47: =SUM(J47:L47) -> 46000 | Q47: April | V47: For Presently using urali cracked and replace
B48: =B47+1 -> 44 | C48: Food & Beverage | D48: Plant & Machinery | E48: Kitchen / Service Equipment | F48: Grinder Titling Type 20 ltr | G48: 1 | H48: Replacement | I48: Kitchen | J48: 46000 | K48: 0 | L48: 0 | M48: =SUM(J48:L48) -> 46000 | Q48: April | V48: For old Machine Complaint and discarded , Need new one
B49: =B48+1 -> 45 | C49: Food & Beverage | D49: Plant & Machinery | E49: Kitchen / Service Equipment | F49: Sujatha Mixer Grinder | G49: 2 | H49: Replacement | I49: Kitchen | J49: 12000 | K49: 0 | L49: 0 | M49: =SUM(J49:L49) -> 12000 | Q49: April | V49: For Presntly using machine is old and always complaint buy new one
B50: =B49+1 -> 46 | C50: Food & Beverage | D50: Plant & Machinery | E50: Kitchen / Service Equipment | F50: Sujatha Juicer Machine | G50: 2 | H50: Replacement | I50: Kitchen | J50: 13000 | K50: 0 | L50: 0 | M50: =SUM(J50:L50) -> 13000 | Q50: April | V50: For Presently using machine is old and always complaint buy new one
B51: =B50+1 -> 47 | C51: Food & Beverage | D51: Plant & Machinery | E51: Kitchen / Service Equipment | F51: Rice Steamer Boiler Unit | G51: 1 | H51: Replacement | I51: Kitchen | J51: 175000 | K51: 0 | L51: 0 | M51: =SUM(J51:L51) -> 175000 | Q51: May | V51: Presently one Machine is damage and replace new
B52: =B51+1 -> 48 | C52: Food & Beverage | D52: Plant & Machinery | E52: Kitchen / Service Equipment | F52: Dough sheeter for Bakery | G52: 1 | H52: Replacement | I52: Kitchen | J52: 300000 | K52: 0 | L52: 0 | M52: =SUM(J52:L52) -> 300000 | Q52: May | V52: Presently one Machine is damage and replace new
B53: =B52+1 -> 49 | C53: Food & Beverage | D53: Plant & Machinery | E53: Kitchen / Service Equipment | F53: Microwave Oven | G53: 2 | H53: Replacement | I53: Service Restaurant & Coffee Shops | J53: 15000 | K53: 0 | L53: 0 | M53: =SUM(J53:L53) -> 15000 | Q53: May | V53: For Replacement for Coffee shops
B54: =B53+1 -> 50 | C54: Food & Beverage | D54: Plant & Machinery | E54: Kitchen / Service Equipment | F54: Camabro Black Trolly | G54: 4 | H54: New | I54: Service Restaurant & Coffee Shops | J54: 60000 | K54: 0 | L54: 0 | M54: =SUM(J54:L54) -> 60000 | Q54: May | V54: for Coffee shops Snakcs pick up
B55: =B54+1 -> 51 | C55: Food & Beverage | D55: Plant & Machinery | E55: Kitchen / Service Equipment | F55: Sujatha mixer grinder | G55: 1 | H55: New | I55: Service Restaurant & Coffee Shops | J55: 6250 | K55: 0 | L55: 0 | M55: =SUM(J55:L55) -> 6250 | Q55: May | V55: for Coffee shops juice counter
B56: =B55+1 -> 52 | C56: Food & Beverage | D56: Plant & Machinery | E56: Kitchen / Service Equipment | F56: Sujath juicer Machine | G56: 1 | H56: New | I56: Service Restaurant & Coffee Shops | J56: 6500 | K56: 0 | L56: 0 | M56: =SUM(J56:L56) -> 6500 | Q56: May | V56: for Coffee shops juice counter
B57: =B56+1 -> 53 | C57: Food & Beverage | D57: Plant & Machinery | E57: Kitchen / Service Equipment | F57: Clearance Trolly | G57: 2 | H57: New | I57: Service Restaurant & Coffee Shops | J57: 30000 | K57: 0 | L57: 0 | M57: =SUM(J57:L57) -> 30000 | Q57: May | V57: for Gourmet & CB -1 area food clearance
B58: =B57+1 -> 54 | C58: Food & Beverage | D58: Plant & Machinery | E58: Kitchen / Service Equipment | F58: Full Plate warmer | G58: 1 | H58: New | I58: Service Restaurant & Coffee Shops | J58: 70000 | K58: 0 | L58: 0 | M58: =SUM(J58:L58) -> 70000 | Q58: May | V58: for Doctors dining area using Hot Plate
... B103: =B102+1 -> 99 | C103: Food & Beverage | D103: Plant & Machinery | E103: Kitchen / Service Equipment | F103: Steel Trolly wheel | G103: 8 | H103: Replacement | I103: Stores & Purchase | J103: 25000 | K103: 0 | L103: 0 | M103: =SUM(J103:L103) -> 25000 | Q103: July | V103: for Heavy Grocery items pick up and shifted from receving area to stores
B104: =B103+1 -> 100 | C104: HRD | D104: Furniture & Fixtures | E104: Office furniture | F104: File Cabinet ( 4 Rack ) | G104: 2 | H104: New | I104: H R Department | J104: 33000 | K104: 0 | L104: 0 | M104: =SUM(J104:L104) -> 33000 | O104: 46113 | P104: 46142 | Q104: April | R104: Unsafe storage of Personnel files | T104: Steel rack powder quoted with sliding trays | V104: shortage of file rack
B105: =B104+1 -> 101 | C105: HRD | D105: Office Equipment | E105: Telephones & EPABX systems | F105: Mobile Phone | G105: 1 | H105: New | I105: H R Department | J105: 15000 | K105: 0 | L105: 0 | M105: =SUM(J105:L105) -> 15000 | O105: 46113 | P105: 46142 | Q105: April | R105: Recruitment Purpose-Candidate co ordination and Official Communication
B106: =B105+1 -> 102 | C106: HRD | D106: Computers & IT Equipment | E106: Desktop computers | F106: Compter System | G106: 3 | H106: Replacement | I106: H R Department | J106: 120000 | K106: 0 | L106: 0 | M106: =SUM(J106:L106) -> 120000 | N106: IT Dept: | O106: 46113 | P106: 46142 | Q106: April | R106: Replacement required due to frequent slowness and system hanging issues affecting day-to-day operations)
B107: =B106+1 -> 103 | C107: HRD | D107: Computers & IT Equipment | E107: Printers, scanners | F107: Printer (Double Side ) | G107: 2 | H107: Replacement | I107: H R Department | J107: 40000 | K107: 0 | L107: 0 | M107: =SUM(J107:L107) -> 40000 | N107: Purchase Dept: | O107: 46113 | P107: 46142 | Q107: April | R107: Printer required as a replacement for the existing old printer, which is not functioning properly.
B108: =B107+1 -> 104 | C108: Pharmacy | D108: Computers & IT Equipment | E108: Printers, scanners | F108: Telephone connection | G108: 1 | H108: Replacement | I108: OP Pharmacy Main block | J108: 3000 | M108: =SUM(J108:L108) -> 3000 | N108: purchase department | O108: 46143 | P108: 46204 | Q108: July | R108: Replacement
B109: =B108+1 -> 105 | C109: Pharmacy | D109: Plant & Machinery | E109: Refrigeration Equipment | F109: Refrigerator | G109: 1 | H109: Replacement | I109: OP Pharmacy new block 2 | J109: 40000 | M109: =SUM(J109:L109) -> 40000 | N109: purchase department | O109: 46174 | P109: 46266 | Q109: September | R109: Replacement of old refrigerator | S109: low performance & repairs | T109: samsung double door | V109: Replacement to improve the efficiency
B110: =B109+1 -> 106 | C110: Pharmacy | D110: Plant & Machinery | E110: Refrigeration Equipment | F110: Refrigerator | G110: 1 | H110: Replacement | I110: OP Pharmacy Main block | J110: 40000 | M110: =SUM(J110:L110) -> 40000 | N110: purchase department | O110: 46113 | P110: 46143 | Q110: May | R110: Replacement of old refrigerator | S110: low performance & repairs | T110: samsung double door | V110: Replacement to improve the efficiency
B111: =B110+1 -> 107 | C111: Pharmacy | D111: Furniture & Fixtures | E111: Storage Cabinet / Pharmacy Furniture | F111: Shutter Medicine storage cabinet A5-336 & D74 G(36+36) | G111: 4 | H111: Replacement | I111: op pharmacy main block | J111: 480000 | M111: =SUM(J111:L111) -> 480000 | N111: purchase department | O111: 46143 | P111: 46204 | Q111: July | R111: Replacement of damaged bin system | S111: Lack proper storage of medicines | T111: Lack proper storage of medicines | V111: for proper storage of medicines in bins
B112: =B111+1 -> 108 | C112: Pharmacy | D112: Furniture & Fixtures | E112: Storage Cabinet / Pharmacy Furniture | F112: Shutter Medicine storage cabinet A5-336 & D74 G(36+36) | G112: 4 | H112: Replacement | I112: IP Pharmacy | J112: 480000 | M112: =SUM(J112:L112) -> 480000 | N112: purchase department | O112: 46143 | P112: 46204 | Q112: July | R112: Replacement of damaged bin system | S112: Lack proper storage of medicines | T112: Lack proper storage of medicines | V112: for proper storage of medicines in bins
B113: =B112+1 -> 109 | C113: Pharmacy | D113: Furniture & Fixtures | E113: Storage Cabinet / Pharmacy Furniture | F113: Shutter Medicine storage cabinet A5-336 & D74 G(36+36) | G113: 4 | H113: Replacement | I113: OP Pharmacy GF New Block | J113: 480000 | M113: =SUM(J113:L113) -> 480000 | N113: purchase department | O113: 46143 | P113: 46204 | Q113: July | R113: Replacement of damaged bin system | S113: Lack proper storage of medicines | T113: Lack proper storage of medicines | V113: for proper storage of medicines in bins
B114: =B113+1 -> 110 | C114: Pharmacy | D114: Furniture & Fixtures | E114: Office furniture | F114: Medical store main door | G114: 1 | H114: Replacement | I114: Medical store | J114: 15000 | M114: =SUM(J114:L114) -> 15000 | N114: purchase department | O114: 46143 | P114: 46204 | Q114: July | R114: for security puropse | S114: secuirty compromised | T114: fabricated strong door with steel door closure | V114: for proper storage
B115: =B114+1 -> 111 | C115: Pharmacy | D115: Buildings | E115: Hospital Building | F115: Fire exit medical store | G115: 1 | H115: new | I115: Medical store | J115: 501000 | M115: =SUM(J115:L115) -> 501000 | N115: Engineering department | O115: 46143 | P115: 46204 | Q115: July | R115: Fire escape route | S115: safety will be compromised | T115: steel stairs | V115: for life saving purpose
B116: =B115+1 -> 112 | C116: Pharmacy | D116: Furniture & Fixtures | E116: Storage Cabinet / Pharmacy Furniture | F116: slotted angle rack shelves replacement | G116: 30 | H116: Replacement | I116: Medical store | J116: 12000 | M116: =SUM(J116:L116) -> 12000 | N116: purchase department | O116: 46143 | P116: 46204 | Q116: July | R116: Replacement of damaged shelves | S116: Lack proper storage of medicines | T116: steel painted shelves | V116: for proper storage of medicines
B117: =B116+1 -> 113 | C117: Pharmacy | D117: Furniture & Fixtures | E117: Storage Cabinet / Pharmacy Furniture | F117: supply trolley medical store platform type | G117: 1 | H117: Replacement | I117: Medical store | J117: 5000 | M117: =SUM(J117:L117) -> 5000 | N117: purchase department | O117: 46143 | P117: 46204 | Q117: July | R117: Replacement of old trolley | S117: proper transportation will be compromised | T117: platform type steel | V117: for proper transportation
B118: =B117+1 -> 114 | C118: Pharmacy | D118: Furniture & Fixtures | E118: Storage Cabinet / Pharmacy Furniture | F118: steel almirah | G118: 2 | H118: Replacement | I118: IP Pharmacy | J118: 24000 | M118: =SUM(J118:L118) -> 24000 | N118: purchase department | O118: 46143 | P118: 46204 | Q118: July | R118: Replacemnt of old almirah | S118: Lack proper storage | T118: steel painted almirah with shelves | V118: for proper storage of medicines
B119: =B118+1 -> 115 | C119: Pharmacy | D119: Furniture & Fixtures | E119: Storage Cabinet / Pharmacy Furniture | F119: slotted angle rack shelves replacement | G119: 3 | H119: Replacement | I119: IP Pharmacy | J119: 1200 | M119: =SUM(J119:L119) -> 1200 | N119: purchase department | O119: 46143 | P119: 46204 | Q119: July | R119: Replacement of damaged shelves | S119: Lack proper storage of medicines | T119: steel painted shelves | V119: for proper storage of medicines
B120: =B119+1 -> 116 | C120: Pharmacy | D120: Furniture & Fixtures | E120: Storage Cabinet / Pharmacy Furniture | F120: Medicine trolley | G120: 2 | H120: Replacement | I120: IP Pharmacy | J120: 24000 | M120: =SUM(J120:L120) -> 24000 | N120: purchase department | O120: 46113 | P120: 46143 | Q120: May | R120: Replacement of old damaged | S120: Not suitable for use | T120: Stainless steel medciien trolley | V120: to improve th medicine delivery in trolley
... B125: =B124+1 -> 121 | C125: Pharmacy | D125: Furniture & Fixtures | E125: Office furniture | F125: Computer Chairs | G125: 2 | H125: Replacement | I125: OP Pharmacy GF New Block | J125: 7000 | M125: =SUM(J125:L125) -> 7000 | N125: purchase department | O125: 46143 | P125: 46204 | Q125: July | R125: purchase department | S125: Chances of staff fall | T125: Office Chair | V125: Replacemnt of very old chair
B126: =#REF!+1 -> #REF! | C126: Histopathology | D126: Furniture & Fixtures | E126: Lab Furniutre | F126: Block Cabinets | G126: 5 | J126: 1000000 | M126: =SUM(J126:L126) -> 1000000 | Q126: July | V126: Space requirement for storing blocks/avoid rodent issues.
B127: =B126+1 -> #REF! | C127: Histopathology | D127: Furniture & Fixtures | E127: Lab Furniutre | F127: Slide Cabinets | G127: 5 | J127: 500000 | M127: =SUM(J127:L127) -> 500000 | Q127: July | V127: Space requirement for storing blocks/avoid rodent issues.
B128: =B127+1 -> #REF! | C128: Biochemistry | D128: Intangible Assets | E128: Computer software | F128: Interfacing of Microbiology and Biochemistry Instruments | G128: 5 | J128: 350000 | M128: =SUM(J128:L128) -> 350000 | Q128: July | V128: New machines to be connected to middleware/HIS.
B129: =B128+1 -> #REF! | C129: Biochemistry | D129: Intangible Assets | E129: Computer software | F129: Navify software with Features Autoreporting, Integrated QC, Rerun etc. | G129: 1 | J129: 450000 | M129: =SUM(J129:L129) -> 450000 | Q129: July | V129: Roche provided middlware which has unique fetaures like auto reporting, rerun, qc management etc.
B130: =#REF!+1 -> #REF! | C130: Fire & Safety | D130: Vehicles | E130: Ambulances | F130: ACLS Ambulance | G130: 1 | H130: Replacement | I130: transport dept | J130: 2000000 | K130: 1200000 | M130: =SUM(J130:L130) -> 3200000 | N130: Vendor Quote | Q130: August | R130: existing ICU ambulance not fit for an orgamisation of our kind | S130: patient dissatisfaction | T130: FORCE Ambulance with interior fabricated for ICU ambulance with required biomedical equipemnts | U130: as required fuel and servicing | V130: need to replace the ICU ambulance which is 13 years old
B131: =B130+1 -> #REF! | C131: Fire & Safety | D131: Furniture & Fixtures | E131: Curtains, blinds | F131: fire curtains | G131: 3 /Floor | H131: New requirment | I131: throught the hospital | J131: 27300000 | M131: =SUM(J131:L131) -> 27300000 | N131: Vendor Quote | Q131: August | R131: quality improvement in fire protection and several inspecting team has asked about the same | S131: we will fall behind to the major players | T131: fire retardant wire mesh with rolling system | V131: quality improvement in fire protection and several inspecting team has asked about the same
B132: =B131+1 -> #REF! | C132: Fire & Safety | D132: Computers & IT Equipment | E132: CCTV | F132: cctv surveillance in parking areas | G132: 30 | H132: New requirment | I132: parking grounds | J132: 500000 | K132: 25000 | M132: =SUM(J132:L132) -> 525000 | N132: existing price | Q132: August | R132: to cover multilevel parking areas and other areas of parking | S132: inadequate surveillance at sensitive areas | T132: camera,dvr,cable | U132: 1.14 lakhs AMC | V132: wehave over 300 parking slot which needs to be covered
B133: =B132+1 -> #REF! | C133: Fire & Safety | D133: Plant & Machinery | E133: Electrical installations | F133: fire alarm system and sprinkler and other additions | G133: 2 | H133: Replacement | I133: thoroughout the hospital | J133: 3000000 | M133: =SUM(J133:L133) -> 3000000 | Q133: August | V133: fire systems need to be kept operational always
B134: =#REF!+1 -> #REF! | C134: IT | D134: Computers & IT Equipment | E134: Desktop computers | F134: Comuputers/Desktop | G134: 215 | H134: Replacement | J134: 6300000 | M134: =SUM(J134:L134) -> 6300000 | Q134: August
B135: =B134+1 -> #REF! | C135: IT | D135: Computers & IT Equipment | E135: Networking equipment | F135: Network Core Switches and Uplinks | J135: 25000000 | M135: =SUM(J135:L135) -> 25000000 | Q135: August | T135: Nexus 93180YC-EX Switchs and Uplinks
B136: =B135+1 -> #REF! | C136: IT | D136: Computers & IT Equipment | E136: Printers, scanners | F136: Printers | G136: 53 | H136: Replacement | J136: 1200000 | M136: =SUM(J136:L136) -> 1200000 | Q136: August | V136: 50 nos replacement and 03 nos standby
B137: =B136+1 -> #REF! | C137: IT | D137: Computers & IT Equipment | E137: Laptops | F137: Laptop and Tablets | G137: 40 | J137: 1500000 | M137: =SUM(J137:L137) -> 1500000 | Q137: August | V137: 40 nos doctors & nursing stations
B138: =B137+1 -> #REF! | C138: IT | D138: Computers & IT Equipment | E138: Other Items | F138: cadrige,key borad,mouse HDD,SMS etc | J138: 500000 | M138: =SUM(J138:L138) -> 500000 | Q138: September
B139: =B138+1 -> #REF! | C139: IT | D139: Computers & IT Equipment | E139: Networking equipment | F139: Netwok Improvement, network upgrade | J139: 500000 | M139: =SUM(J139:L139) -> 500000 | Q139: September
B140: =B139+1 -> #REF! | C140: IT | D140: Intangible Assets | E140: Computer software | F140: Oracle , volume/ OS/Microsoft-/O365 , Antivirus | G140: 1 | H140: New requirment | J140: 5000000 | M140: =SUM(J140:L140) -> 5000000 | Q140: September
B141: =B140+1 -> #REF! | C141: IT | D141: Computers & IT Equipment | E141: Digittalization /Automation | F141: Digittalization /Automation /Customization /Security /DPDP | G141: 1 | J141: 7500000 | M141: =SUM(J141:L141) -> 7500000 | Q141: September
B142: =B141+1 -> #REF! | C142: General Store | D142: Plant & Machinery | E142: Refrigeration Equipment | F142: WALKING REFERGERATOR | G142: 1 | H142: New requirment | J142: 500000 | K142: 50000 | L142: 10000 | M142: =SUM(J142:L142) -> 560000 | N142: Vendor Quote | O142: 46113 | P142: 46173 | Q142: May | R142: TO KEEP REFERGERATOR ITEMS. | S142: NOW THE REFERGERATOR ITEMS ARE TRANSFERRED AT THE TIME OF DELIVERY | T142: NOW WE ARE NOT STOCKING FRIDGE ITEMS SO WE HAVE NO STOCK CONTROL FOR REFERGERATING ITEMS | V142: WE CAN CONTROLL THE PURCHASE OF REFERGERATION ITEMS
B143: =B142+1 -> #REF! | C143: General Store | D143: Computers & IT Equipment | E143: Printers, scanners | F143: DIGITAL DUPLICATOR | G143: 1 | H143: New requirment | J143: 250000 | K143: 5000 | L143: 5000 | M143: =SUM(J143:L143) -> 260000 | N143: Vendor Quote | O143: 46113 | P143: 46173 | Q143: May | R143: THIS COPPIER WILL REDUCE ALL THE BLACK AND WHITE PRINTOUTS. THE PRINTER HAVING A SPEED OF 120 PAGES PER MINUTE. OUR PRINTING COST WILL REDUCE TO ONE FOURTH. | V143: PRINT COST FOR 1000 PRINTS EXCLUDING PAPER IS 160 - 200ONLY.
B144: =#REF!+1 -> #REF! | C144: Hematology | D144: Plant & Machinery | E144: Biomedical Equipment | F144: Automated Urine Analyzer | G144: 1 | J144: 4000000 | M144: =SUM(J144:L144) -> 4000000 | Q144: July | V144: Automate the current process to improve the tat in clinical pathology, but presently there is limited space available in hematology department.
B145: =#REF!+1 -> #REF! | C145: Biochemistry | D145: Plant & Machinery | E145: Biomedical Equipment | F145: Electrophoresis Instrument | G145: 1 | J145: 1800000 | M145: =SUM(J145:L145) -> 1800000 | Q145: July | V145: Electrophoresis numbers are increasing day by day and presently we are outsourcing the samples.
B146: =#REF!+1 -> #REF! | C146: Clinical Nutrition | D146: Plant & Machinery | E146: Biomedical Equipment | F146: Body composition analyser (InBody) | G146: 1 | H146: New requirment | I146: Clinical Nutrition | J146: 1600000 | M146: =SUM(J146:L146) -> 1600000 | N146: Market Survey | O146: 46113 | P146: 46174 | Q146: August | R146: Biomedical equipment, for nutrition screening/ assessment and also to adapt to newer technologies leading to revenue generation | S146: Will not be able to upgrade the services and attract patient flow and related revenue loss | T146: Need to assess the BCA while sitting/ standing and supine positions | U146: As per the inputs from BME | V146: Improve clinical nutrition services for IP and OP, portable technique for quick and fast body composition analysis, to enhance departmentwise revenue generation
B147: =#REF!+1 -> #REF! | C147: PHYSIOTHERAPY | D147: Plant & Machinery | E147: Biomedical Equipment | F147: Spinal decompression traction unit | G147: 1 | H147: New | I147: Physiotherapy Unit | J147: 1200000 | M147: =SUM(J147:L147) -> 1200000 | N147: Vendor Quote | Q147: September | R147: Non-surgical spinal decompression for conditions like disc herniations and nerve impingements | S147: Fewer non-invasive treatment options for spinal issues, leading to prolonged recovery | T147: Traction Type: Lumbar & cervical Pulling Force:0-100 kg - Modes:Static, intermittent, cyclic Features: Emergency stop, digital control | V147: Effective in treating chronic spinal conditions without surgery, improving patient outcomes and reducing hospital referrals
B148: =#REF!+1 -> #REF! | C148: PHYSIOTHERAPY | D148: Plant & Machinery | E148: Biomedical Equipment | F148: Shock wave therapy | G148: 1 | H148: New | I148: Physiotherapy Unit | J148: 1000000 | M148: =SUM(J148:L148) -> 1000000 | N148: Vendor Quote | Q148: September | R148: Effective for chronic pain conditions like plantar fasciitis, tendinopathies, and calcific shoulder issues | S148: Reduced effectiveness in treating chronic musculoskeletal conditions, leading to longer recovery times | T148: Shockwave Type:Radial/Focused - Frequency: 1-20 Hz - Intensity: Up to 5 bars - Features:Multiple applicator heads, low noise, portable | V148: Proven non-invasive solution for chronic pain, reduces surgical referrals, and enhances patient satisfaction.
...

Sheet MIXED_new
A1: SL. No | B1: Department | C1: Asset Category | D1: Asset Sub Category | E1: Project Description /Item Name | F1: QTY | G1: Category of CAPEX | H1: Location/ Area of Implementation | I1: Estimated Cost (INR) | J1: XX | K1: XX | L1: Total Cost | M1: Source of Pricing Information | N1: Proposed Timeline for Investment | O1: XX | P1: Month (Put to Use) | Q1: Purpose of the Investment | R1: Impact of Non-Investment | S1: Specifications/Features Required | T1: Maintenance/ Operational Costs | U1: Commersial Justification | V1: new or replacements | W1: requested by | X1: curent utilization | Y1: infra structrue | Z1: Approved total quantity | AA1: Quantity to be purchased | AB1: Final cost | AC1: Notes
I2: Equipment Cost | J2: Installation Cost | K2: Other Costs (Specify) | L2: Total | N2: Start Date | O2: End Date
A3: 1 | B3: Biomedical | C3: Plant & Machinery | D3: Biomedical Equipment | E3: Electric bed | F3: 50 | H3: Various department | I3: 150000000 | L3: 7500000 | N3: March | P3: March | Q3: Replacement for the old 76 manual cot for twin sharing rooms as well as executive rooms | R3: For patient comfort and marketing tool | U3: Replacement | V3: Replacements of old cot | W3: Facility Manager | Y3: Nil | AC3: Waiting for operation team reply
A4: 2 | B4: Biomedical | C4: Plant & Machinery | D4: Biomedical Equipment | E4: Digital X Ray | F4: 2 | H4: Radiology | I4: 20000000 | L4: 40000000 | N4: August | P4: August | Q4: Replacement for old machine which was installed in 2002 and 2009 | R4: Advanced technology and reduce the procedure time | T4: After warranty CMC will come | U4: More than 10 years of usage,achieved its life. | V4: Replacements of old machine | W4: Dr Thara | X4: Average of 180 Cases/day (Lowest billing cost 330 rs ) | Y4: Present infracture is accurate | Z4: 2 | AA4: 2 | AB4: 40000000 | AC4: Approved
A5: 3 | B5: Biomedical | C5: Plant & Machinery | D5: Biomedical Equipment | E5: Digital Pathology | F5: 1 | H5: Pathology | I5: 30000000 | L5: 30000000 | N5: November | P5: November | Q5: New requirement | R5: Generate additional income & marketing tool | T5: After warranty CMC will come | U5: New requirement | V5: New requirement | W5: Dr HR,Dr Roy,Dr Chithrathara,Dr Moni | X5: 50 Cases/ month | Y5: Nil | AC5: Hold ,need to discuss with Dr
A6: 4 | B6: Biomedical | C6: Plant & Machinery | D6: Biomedical Equipment | E6: Heart Lung Machine | F6: 1 | H6: Cardiac OT | I6: 25000000 | L6: 25000000 | N6: January | P6: January | Q6: Replacement for old machine installed in 2006 | R6: Supportive for cardiac thoraic surgery | T6: After warranty CMC will come | V6: Replacements of old machine | W6: Dr Sujith,Dr Anand | X6: 5 Cases/month | Y6: Nil | Z6: 1 | AA6: 1 | AB6: 25000000 | AC6: Approved
A7: 5 | B7: Biomedical | C7: Plant & Machinery | D7: Biomedical Equipment | E7: Ventilator(Pead +Adult) | F7: 10 | H7: MDICU | I7: 2250000 | L7: 22500000 | N7: November | P7: November | Q7: Replacement for old machine more than 15 yrs | R7: Patient comfort | T7: After warranty CMC will come | U7: Replacement | V7: Replacements of old machine | W7: Dr Nita | X7: 12-15 Machines/Day | Y7: Nil | Z7: 6+4 | AA7: 10 | AB7: 22500000 | AC7: Approved
A8: 6 | B8: Biomedical | C8: Plant & Machinery | D8: Biomedical Equipment | E8: Digital Slide Scaner | F8: 1 | H8: Histopathology | I8: 25000000 | L8: 25000000 | N8: April | P8: April | Q8: New requirement | R8: Implement advanced technology | T8: After warranty CMC will come | U8: New requirement | V8: New Requirment | W8: Dr. Pushpa | X8: Nil | Y8: Nil | AC8: ON HOLD
A9: 7 | B9: Biomedical | C9: Plant & Machinery | D9: Biomedical Equipment | E9: C -Arm | F9: 1 | H9: Radiology | I9: 20000000 | L9: 20000000 | N9: October | P9: October | Q9: Replacement of old machine more than 10yrs old | R9: Latest technology | T9: After warranty CMC will come | U9: Replacement | V9: Replacements of old machine | W9: Dr Thara | X9: 5 Cases/Day | Z9: 1 | AA9: 1 | AB9: 20000000 | AC9: Approved
A10: 8 | B10: Biomedical | C10: Plant & Machinery | D10: Biomedical Equipment | E10: XI system | F10: 1 | H10: Gastroenterology | I10: 18000000 | L10: 18000000 | N10: September | P10: September | Q10: Replacement for old system | R10: Generate additional income and latest technology | T10: After warranty CMC will come | U10: Replacement | V10: Replacements of old machine | W10: Dr Roy | X10: 25 Cases/Day with 3system Endoscopy 3000/- Colono 9000/- | Y10: Nil | Z10: 1 | AA10: 1 | AB10: 18000000 | AC10: Approved
A11: 9 | B11: Biomedical | C11: Plant & Machinery | D11: Biomedical Equipment | E11: LASER | F11: 1 | H11: Dermatology OPD | I11: 15000000 | L11: 15000000 | N11: May | P11: May | Q11: New technology for laser procedures and treatments | R11: To generate additional income | T11: After warranty CMC will come | U11: New requirment | V11: New requirement | W11: Dr. Abin Abraham Itty | X11: Approx of 10 cases per day (Per patient 10000/ sitting) | Y11: Required | AC11: Checked with vendor for lease bases
A12: 10 | B12: Biomedical | C12: Plant & Machinery | D12: Biomedical Equipment | E12: Surgical Microscope | F12: 1 | H12: Main OT | I12: 10000000 | L12: 10000000 | N12: March | P12: March | Q12: Replacement for old machine installed in 2002 | R12: Latest technology | T12: After warranty CMC will come | U12: Morethan 10 years of usage | V12: Replacement | W12: ENT,Head & Neck,Plastic Surgery | Y12: Nil | Z12: 1 | AA12: 1 | AB12: 10000000 | AC12: Approved
A13: 11 | B13: Biomedical | C13: Plant & Machinery | D13: Biomedical Equipment | E13: Neuro monitoring system | F13: 1 | H13: Neuro OT | I13: 10000000 | L13: 10000000 | N13: April | P13: April | Q13: Replacement for old machine, end of life declared No service support available | T13: After warranty CMC will come | U13: Replacement | V13: Replacement | W13: Dr, SK | X13: 6 Cases/Month 18000/- avg billing | Y13: Nil | Z13: 1 | AA13: 1 | AB13: 10000000 | AC13: Approved
A14: 12 | B14: Biomedical | C14: Plant & Machinery | D14: Biomedical Equipment | E14: PET scan upgradation | F14: 1 | H14: Nuclear medicine | I14: 10000000 | L14: 10000000 | N14: October | P14: October | Q14: Replacement of old machine end of life declared | R14: To generate additional income and latest technology | T14: After warranty CMC will come | U14: Upgrade | V14: Upgrade | W14: Dr Senthil | Y14: Nil | Z14: 1 | AA14: 1 | AB14: 10000000 | AC14: Approved
A15: 13 | B15: Biomedical | C15: Plant & Machinery | D15: Biomedical Equipment | E15: Anesthesia machine | F15: 3 | H15: Main OT | I15: 3000000 | L15: 9000000 | N15: September | P15: September | Q15: Replacement of old machine more than 10yrs old | T15: After warranty CMC will come | U15: Morethan 10 years of usage | V15: Replacement | W15: Dr Mallie | X15: Avargae 22 Cases/Day | Y15: Nil | Z15: 3 | AA15: 3 | AB15: 9000000 | AC15: Approved
A16: 14 | B16: Biomedical | C16: Plant & Machinery | D16: Biomedical Equipment | E16: Monitor | F16: 40 | H16: All ICU,HDU,Ambulance | I16: 600000 | L16: 24000000 | N16: November | P16: November | Q16: Additional ICU bed creating | R16: Additional income generating | U16: New Requirement | V16: New requirement | W16: Dr. Nita | X16: Nil | Y16: Nil | Z16: 40 | AA16: 40 | AB16: 24000000 | AC16: Approved
A17: 15 | B17: Biomedical | C17: Plant & Machinery | D17: Biomedical Equipment | E17: Thulium Laser | F17: 1 | H17: Main OT | I17: 7500000 | L17: 7500000 | N17: November | P17: November | Q17: Additional requirement | R17: Additional income generating | T17: After warranty CMC will come | U17: Additional Requirement | V17: Additional Requirement | W17: Dr Datson | X17: 40 Cases/Month | Y17: Nil | Z17: 1 | AA17: 1 | AB17: 7500000 | AC17: Approved with buyback option
A18: 16 | B18: Biomedical | C18: Plant & Machinery | D18: Biomedical Equipment | E18: Pendent | F18: 15 | H18: MDICU | I18: 500000 | L18: 7500000 | N18: March | P18: March | Q18: New reqirement for new ICU | R18: Latest technology | U18: New requirement | V18: New requirement | W18: Dr Nita | X18: Nil | Y18: Nil | Z18: 15 | AA18: 15 | AB18: 7500000 | AC18: Approved
A19: 17 | B19: Biomedical | C19: Plant & Machinery | D19: Biomedical Equipment | E19: Portable ECHO | F19: 2 | H19: Cardiology OP | I19: 3500000 | L19: 7000000 | N19: April | P19: April | Q19: Replacement of old system more than 10 years old | R19: latest technology | T19: After warranty CMC will come | U19: Frequent complaint | V19: Replacement | W19: Dr Anand | X19: 190 Cases/ Month 2000per case | Y19: Nil | Z19: 2 | AA19: 2 | AB19: 7000000 | AC19: Approved
A20: 18 | B20: Biomedical | C20: Plant & Machinery | D20: Biomedical Equipment | E20: Portable DR | F20: 1 | H20: Radiology | I20: 6000000 | L20: 6000000 | N20: October | P20: October | Q20: Replacement for old machine | R20: To generate additional income and patient comfort | T20: After warranty CMC will come | V20: Replacement | W20: Dr Thara | X20: 80 Cases/Day 450/- per case | Y20: Nil | AC20: ON HOLD
A21: 19 | B21: Biomedical | C21: Plant & Machinery | D21: Biomedical Equipment | E21: Thomsan retractor | F21: 1 | H21: Main OT | I21: 6000000 | L21: 6000000 | N21: December | P21: December | Q21: Replacement for old instrument | R21: Patient saftey | U21: Replacement | V21: Replacement | W21: Dr. HR, Dr Fadal | X21: 8-10 Cases / Month | Y21: Nil | Z21: 1 | AA21: 1 | AB21: 6000000 | AC21: APPROVED
A22: 20 | B22: Biomedical | C22: Plant & Machinery | D22: Biomedical Equipment | E22: Surgical Aspirator - CUSA | F22: 1 | H22: Neuro OT | I22: 6000000 | L22: 6000000 | N22: September | P22: September | Q22: Replacement of ols machine ore than 15 yrs old | R22: Patient saftey | T22: After warranty CMC will come | U22: Morethan 15 years of usage | V22: Replacement | W22: Dr SK | X22: 3 -5 Cases/Month | Y22: Nil | Z22: 1 | AA22: 1 | AB22: 6000000 | AC22: APPROVED ,Need to charge for each case
A23: 21 | B23: Biomedical | C23: Plant & Machinery | D23: Biomedical Equipment | E23: Total body densitometry system | F23: 1 | H23: Radiology | I23: 6000000 | L23: 6000000 | N23: August | P23: August | Q23: Replacement of old system | R23: Additional income generating and latest technolgy | T23: After warranty CMC will come | U23: More than 10 years of usage,achieved its life. | V23: Rreplacement | W23: Dr JV,Dr Vivek | X23: 8 Cases/Day | Y23: Nil | Z23: 1 | AA23: 1 | AB23: 6000000 | AC23: APPROVED
A24: 22 | B24: Biomedical | C24: Plant & Machinery | D24: Biomedical Equipment | E24: WAB for ultrasound | F24: 1 | H24: Radiology | I24: 6000000 | L24: 6000000 | N24: October | P24: October | Q24: New reqirement | R24: Additional income and latest technology | T24: After warranty CMC will come | U24: New requirement | V24: New requirement | W24: Dr Chithratara, Dr Thara | Y24: Nil | AC24: ON HOLD
A25: 23 | B25: Biomedical | C25: Plant & Machinery | D25: Biomedical Equipment | E25: Dialysis machine | F25: 6 | H25: Nephrology | I25: 800000 | L25: 480000 | N25: May | P25: May | Q25: Replacement for old machine | T25: After warranty CMC will come | U25: More than 10 years of usage, needs replacement | V25: Replacement | W25: Dr Abi Abhraham | X25: 60 Cases/Day(26 machine | Y25: Nil | Z25: 6 | AA25: 6 | AB25: 480000 | AC25: APPROVED
A26: 24 | B26: Biomedical | C26: Plant & Machinery | D26: Biomedical Equipment | E26: Ortho Surgical instruments | F26: 1 | H26: Ortho OT | I26: 5000000 | L26: 5000000 | N26: October | P26: October | Q26: Replacement for old instruments | U26: Replacement | V26: Replacement | W26: Dr JV | Y26: Nil | AC26: Waiting for list from CSSD
A27: 25 | B27: Biomedical | C27: Plant & Machinery | D27: Biomedical Equipment | E27: Cardiac workstation with TMT | F27: 2 | H27: Cardiology OP | I27: 250000 | L27: 5000000 | N27: September | P27: September | Q27: Replacement of old system more than 10 years old | T27: After warranty CMC will come | U27: More than 10 years of usage,achieved its life. | V27: Replacement | W27: Dr Anand | X27: 20 Cases/Day (1700/- per case) | Y27: Nil | Z27: 2 | AA27: 2 | AB27: 5000000 | AC27: APPROVED
A28: 26 | B28: Biomedical | C28: Plant & Machinery | D28: Biomedical Equipment | E28: MRI compactable monitor | F28: 1 | H28: Radiology | I28: 5000000 | L28: 5000000 | N28: September | P28: September | Q28: Replacement for old machine more than 10 yrs | U28: More than 10 years of usage,achieved its life. | V28: Replacement | W28: Dr Julio | Y28: Nil | Z28: 1 | AA28: 1 | AB28: 5000000 | AC28: APPROVED
A29: 27 | B29: Biomedical | C29: Plant & Machinery | D29: Biomedical Equipment | E29: Anesthesia work station MRI | F29: 1 | H29: Radiology | I29: 4500000 | L29: 4500000 | N29: September | P29: September | Q29: Replacement of old machine more than 12 years | T29: After warranty CMC will come | U29: More than 10 years of usage,achieved its life. | V29: Replacement | W29: Dr Julio | X29: 10 Cases/Month | Y29: Nil | AC29: Rejected
A30: 28 | B30: Hematology | C30: Plant & Machinery | D30: Biomedical Equipment | E30: Automated Urine Analyzer | F30: 1 | H30: Haematology | I30: 4000000 | L30: 4000000 | P30: July | Q30: An Automated Urine Analyzer is a diagnostic instrument used for rapid and standardized examination of urine samples. In the Hematology setting (or integrated central lab), it supports screening, monitoring, and diagnostic evaluation of various systemic and hematological conditions. | R30: Failure to invest in an Automated Urine Analyzer can significantly affect diagnostic efficiency, patient safety, and laboratory productivity in the Hematology Department. Reliance on manual urine strip reading and microscopy Higher observer variability Increased technician workload Reduced productivity during peak hours | T30: a) Urine Reagent Strips (Major Cost Component) Multi-parameter strips (10–14 parameters depending on model) Cost directly proportional to daily sample volume . Quality Control (QC) Materials Annual Maintenance Contract (AMC) | U30: Automate the current process to improve the tat in clinical pathology, but presently there is limited space available in hematology department. | V30: New requirement | W30: Nishanth | Y30: Nil | Z30: 1 | AA30: 1 | AB30: 4000000 | AC30: APPROVED
A31: 29 | B31: Biomedical | C31: Plant & Machinery | D31: Biomedical Equipment | E31: IABP machine | F31: 1 | H31: Cardiac OT | I31: 4000000 | L31: 4000000 | N31: July | P31: July | Q31: Replacement for old machine installed in 2006 | T31: After warranty CMC will come | U31: Morethan 10 years of usage | V31: Replacement | W31: Dr Sujith | X31: 2cases/month | Y31: Nil | Z31: 1 | AA31: 1 | AB31: 4000000 | AC31: APPROVED
A32: 30 | B32: Biomedical | C32: Plant & Machinery | D32: Biomedical Equipment | E32: Ultrasonic cleaner | F32: 1 | H32: CSSD | I32: 4000000 | L32: 4000000 | N32: February | P32: February | Q32: Replacement for old machine more than 10 years old | T32: After warranty CMC will come | U32: Replacement for old one | V32: Replacement | W32: CSSD ,Manager | X32: Nil | Y32: Nil | Z32: 1 | AA32: 1 | AB32: 4000000 | AC32: APPROVED
A33: 31 | B33: Biomedical | C33: Plant & Machinery | D33: Biomedical Equipment | E33: Reporting Workstation | F33: 4 | H33: Radiology | I33: 1000000 | L33: 4000000 | N33: October | P33: October | Q33: Replacement for old system | U33: More than 10 years of usage,achieved its life. | V33: Replacement | W33: Dr Thara | X33: Nil | Y33: Nil | Z33: 4 | AA33: 4 | AB33: 4000000 | AC33: APPROVED
A34: 32 | B34: Biomedical | C34: Plant & Machinery | D34: Biomedical Equipment | E34: Incubator with portable ventilator | F34: 1 | H34: NICU | I34: 3500000 | L34: 3500000 | N34: January | P34: January | Q34: New requirment for neonatal icu | R34: Additional income generative | T34: After warranty CMC will come | U34: New requirement | V34: New requirement | W34: Dr Navin | X34: Nil | Y34: Nil | AC34: Need to discuss with Dr
A35: 33 | B35: Biomedical | C35: Plant & Machinery | D35: Biomedical Equipment | E35: Electric drill | F35: 1 | H35: Neuro OT | I35: 3200000 | L35: 3200000 | N35: February | P35: February | Q35: Replacement for old machine | U35: Replacement | V35: Replacement | W35: Dr SK | Z35: 1 | AA35: 1 | AB35: 3200000 | AC35: APPROVED
A36: 34 | B36: Biomedical | C36: Plant & Machinery | D36: Biomedical Equipment | E36: Manometry | F36: 1 | H36: Gastroenterology | I36: 3200000 | L36: 3200000 | N36: October | P36: October | Q36: Replacement for old machine | R36: Additional income generative | U36: More than 10 years of usage | V36: Replacement | W36: Dr Roy | X36: 6 Cases/Month 15000/- per case | Y36: Nil | Z36: 1 | AA36: 1 | AB36: 3200000 | AC36: APPROVED
A37: 35 | B37: Biomedical | C37: Plant & Machinery | D37: Biomedical Equipment | E37: OT Table | F37: 1 | H37: Main OT | I37: 1500000 | L37: 1500000 | N37: May | P37: May | Q37: Replacement for old machine more than 10 years old | R37: Patient saftey | U37: Morethan 10 years of usage | V37: Replacement | W37: OT incharge | X37: NIL | Y37: NIL | Z37: 1 | AA37: 1 | AB37: 1500000 | AC37: Approved
A38: 36 | B38: Biomedical | C38: Plant & Machinery | D38: Biomedical Equipment | E38: CO monitor | F38: 1 | H38: Main OT | I38: 3000000 | L38: 3000000 | N38: September | P38: September | Q38: Replacement for old machine more than 10 years old | R38: Latest technology | T38: After warranty CMC will come | U38: Morethan 10 years of usage | V38: Replacement | W38: Dr Mallie | X38: NIL | Y38: NIL | Z38: 1 | AA38: 1 | AB38: 3000000 | AC38: Approved
A39: 37 | B39: Biomedical | C39: Plant & Machinery | D39: Biomedical Equipment | E39: Surgical instruments | F39: 1 | H39: Main OT | I39: 3000000 | L39: 3000000 | N39: December | P39: December | Q39: Replacement for old instruments | R39: Supportive | U39: New requirement | V39: Replacement | W39: Dr HR | X39: Nil | AC39: Waiting for list from CSSD
A40: 38 | B40: Biomedical | C40: Plant & Machinery | D40: Biomedical Equipment | E40: Nasal endoscope | F40: 1 | H40: ENT | I40: 3000000 | L40: 3000000 | N40: June | P40: June | Q40: Replacement of old machine more than 15 yrs old machine | R40: Additional income generative | T40: After warranty CMC will come | U40: More than 10 years of usage, needs replacement | V40: Replacement | W40: Dr Idiculla | X40: 10 Cases/Month | Y40: Nil | Z40: 1 | AA40: 1 | AB40: 3000000 | AC40: Approved
A41: 39 | B41: Biomedical | C41: Plant & Machinery | D41: Biomedical Equipment | E41: ERCP scope | F41: 1 | H41: Gastroenterology | I41: 3000000 | L41: 3000000 | N41: July | P41: July | Q41: Replacement for old system | T41: After warranty CMC will come | U41: More than 10 years of usage,achieved its life. | V41: Replacement | W41: Dr. Roy | X41: 30cases/month | Y41: Nil | Z41: 1 | AA41: 1 | AB41: 3000000 | AC41: Approved
A42: 40 | B42: Biomedical | C42: Plant & Machinery | D42: Biomedical Equipment | E42: Bme tools and other Assets calibrattion | H42: Biomedical | I42: 3000000 | L42: 3000000 | N42: December | P42: December | Q42: New requirement,as per NABH standard we need calibrated tools | R42: Patient saftey | U42: New requirement | V42: New requirement | W42: Biomedical | X42: Nil | Y42: Nil | AB42: 3000000 | AC42: Approved need ROI Calculation
A43: 41 | B43: Biomedical | C43: Plant & Machinery | D43: Biomedical Equipment | E43: Microwave ablation system | F43: 1 | H43: Interventional Radiology | I43: 2800000 | L43: 2800000 | N43: October | P43: October | Q43: New requirement | R43: additional income generative | T43: After warranty CMC will come | U43: New requirement | V43: New requirement | W43: Dr Shahir | X43: 5 Cases/Month (1.5) | Y43: Nil | Z43: 1 | AA43: 1 | AB43: 2800000 | AC43: Approved
A44: 42 | B44: Biomedical | C44: Plant & Machinery | D44: Biomedical Equipment | E44: Video Duodenoscope (Adult) | F44: 1 | H44: Gastroenterology | I44: 2800000 | L44: 2800000 | N44: June | P44: June | Q44: Replacement for old machine | U44: More than 10 years of usage,achieved its life. | V44: Replacement | W44: Dr.Roy | Y44: Nil | Z44: 1 | AA44: 1 | AB44: 2800000 | AC44: Approved
A45: 43 | B45: Biomedical | C45: Plant & Machinery | D45: Biomedical Equipment | E45: CRRT | F45: 1 | H45: Nephrology | I45: 2500000 | L45: 2500000 | N45: July | P45: July | Q45: Replacement of old system | T45: After warranty CMC will come | U45: More than 10 years of usage, needs replacement | V45: Replacement | W45: Dr Abi Abhraham | X45: 190 Cases/ Month 2000per case | Y45: nil | AC45: Rejected
A46: 44 | B46: Biomedical | C46: Plant & Machinery | D46: Biomedical Equipment | E46: Pneumatic drill | F46: 1 | H46: Neuro OT | I46: 2500000 | L46: 2500000 | N46: October | P46: October | Q46: Replacement | R46: Supportive | T46: After warranty CMC will come | U46: Replacement more than 10years old | V46: Replacement | W46: Dr SK | X46: NIL | Y46: NIL | Z46: 1 | AA46: 1 | AB46: 2500000 | AC46: Approved
A47: 45 | B47: Biomedical | C47: Plant & Machinery | D47: Biomedical Equipment | E47: Ultrasound machine | F47: 1 | H47: Nephrology | I47: 2500000 | L47: 2500000 | N47: July | P47: July | Q47: New requirement | R47: Additional income generative | T47: After warranty CMC will come | U47: new requirement | V47: New requirement | W47: Dr Abi Abhraham | X47: NIL | Y47: NIL | AC47: Rejected
A48: 46 | B48: Biomedical | C48: Plant & Machinery | D48: Biomedical Equipment | E48: Ultrasound Machine | F48: 1 | H48: LR | I48: 2500000 | L48: 2500000 | N48: June | P48: June | Q48: Replacement for old machine more than 10years old | T48: After warranty CMC will come | U48: More than 10 years of usage,achived its life | V48: Replacement | W48: Dr Smitha | X48: Nil | Y48: Nil | AC48: Rejected
A49: 47 | B49: Biomedical | C49: Plant & Machinery | D49: Biomedical Equipment | E49: Microscope | F49: 1 | H49: ENT OPD | I49: 2500000 | L49: 2500000 | N49: April | P49: April | Q49: New requirement | R49: Additional income generative | U49: New requirment | V49: New requirement | W49: Dr Idiculla | X49: Nil | Y49: Nil | AC49: Need to discuss with Dr Moni
A50: 48 | B50: Biomedical | C50: Plant & Machinery | D50: Biomedical Equipment | E50: Dye Injector MRI compitable | F50: 1 | H50: Radiology | I50: 2500000 | L50: 2500000 | N50: September | P50: September | Q50: New Requirement for new MRI system | R50: Additional income generative | T50: After warranty CMC will come | U50: New requirement | V50: New requirement | W50: Dr Julio | X50: 250 Cases/Month | Y50: Nil | Z50: 1 | AA50: 1 | AB50: 2500000 | AC50: APPROVED
A51: 49 | B51: Biomedical | C51: Plant & Machinery | D51: Biomedical Equipment | E51: Portable Ultrasound Machine | F51: 1 | H51: Interventional Radiology | I51: 2500000 | J51: 2500000 | K51: 2500000 | L51: 2500000 | N51: October | P51: October | Q51: New requirement | R51: Additional income generative | T51: After warranty CMC will come | U51: New requirement | V51: New requirement | W51: Dr Shahir | X51: Nil | Y51: Nil | AC51: Rejected
A52: 50 | B52: Biomedical | C52: Plant & Machinery | D52: Biomedical Equipment | E52: Versajet Machine | F52: 1 | H52: Foot and Ankle | I52: 2500000 | L52: 2500000 | N52: September | P52: September | Q52: New requirement | R52: Additional income generatrive | U52: New requirement | V52: New requirement | W52: Dr Rajesh Simon | X52: Nil | Y52: Nil | AC52: Rental
A53: 51 | B53: Biomedical | C53: Plant & Machinery | D53: Biomedical Equipment | E53: EEG,EMG | F53: 1 | H53: Neuroscience | I53: 2500000 | L53: 2500000 | N53: September | P53: September | Q53: Replacement | U53: Repalcement | V53: Replacement for old one | W53: Dr Murali | X53: Nil | Y53: Nil | Z53: 1 | AA53: 1 | AB53: 2500000 | AC53: Approved
A54: 52 | B54: Biomedical | C54: Plant & Machinery | D54: Biomedical Equipment | E54: OT Table Ortho | F54: 1 | H54: Ortho OT | I54: 2000000 | L54: 2000000 | N54: December | P54: December | Q54: Additional table for trauma surgery | R54: Pateint saftey | U54: New requirement | V54: New requirement | W54: Dr Jacob | X54: 20cases / month | Y54: Nil | Z54: 1 | AA54: 1 | AB54: 2000000 | AC54: Approved
A55: 53 | B55: Biomedical | C55: Plant & Machinery | D55: Biomedical Equipment | E55: Dye Injector | F55: 1 | H55: Cath-Lab | I55: 2000000 | L55: 2000000 | N55: September | P55: September | Q55: Replacement for old machine more than 10 years old | T55: After warranty CMC will come | U55: More than 10 years of usage,achieved its life. | V55: Replacement | W55: DGM Radiology | X55: Nil | Y55: Nil | Z55: 1 | AA55: 1 | AB55: 2000000 | AC55: Approved
A56: 54 | B56: Biomedical | C56: Plant & Machinery | D56: Biomedical Equipment | E56: Coblator | F56: 1 | H56: Main OT | I56: 2000000 | L56: 2000000 | N56: June | P56: June | Q56: Replacement for old machine more than 10 years old | U56: Morethan 10 years of usage | V56: Replacement | W56: Dr Idiculla | X56: Monthly an average of 25 cases | Y56: Nil | Z56: 1 | AA56: 1 | AB56: 2000000 | AC56: Approved
A57: 55 | B57: Biomedical | C57: Plant & Machinery | D57: Biomedical Equipment | E57: Surgical diathermy - Ligasure | F57: 1 | H57: Main OT | I57: 2000000 | L57: 2000000 | N57: October | P57: October | Q57: New Requirement | T57: After warranty CMC will come | U57: New requirement | V57: New requirement | W57: Dr Moni,Dr HR | X57: NIL | Y57: Nil | AC57: PO Released
A58: 56 | B58: Biomedical | C58: Plant & Machinery | D58: Biomedical Equipment | E58: Refrigerated Centrifuge | F58: 2 | H58: Blood Bank | I58: 1000000 | L58: 2000000 | N58: February | P58: February | Q58: A Refrigerated Centrifuge is a critical component in blood bank operations, used for component separation and preservation of blood products under controlled temperature conditions. Separation of: Packed Red Blood Cells (PRBC) Fresh Frozen Plasma (FFP) Platelet Concentrate Cryoprecipitate | R58: Inability to prepare blood components Dependence on external blood banks Increased cost per unit procurement Delay in emergency transfusions Reduced regulatory compliance | T58: Maintenance AMC/CMC: 8–12% of equipment cost annually Rotor maintenance and balancing Compressor and cooling system servicing | U58: More than 10 years of usage, needs replacement | V58: replacement | W58: DR Don | X58: Mandatory for component preparation in licensed blood banks Required for NABH/NABL and Drug Controller compliance Ensures adherence to transfusion medicine guidelines | Y58: NIL | AC58: Approved on machine condition
A59: 57 | B59: Biomedical | C59: Plant & Machinery | D59: Biomedical Equipment | E59: Dose calibrator | F59: 2 | H59: Nuclear medicine | I59: 100000 | L59: 200000 | N59: November | P59: November | Q59: Replacement for old machine more than 10years | R59: Patient saftey | T59: After warranty CMC will come | U59: More than 10 years of usage,achieved its life. | V59: Replacement | W59: Dr Senthil | X59: nil | Y59: NIL | Z59: 2 | AA59: 2 | AB59: 200000 | AC59: Approved
A60: 58 | B60: Biomedical | C60: Plant & Machinery | D60: Biomedical Equipment | E60: Syringe pump | F60: 50 | H60: MDICU , Various Departments | I60: 40000 | L60: 2000000 | N60: November | P60: November | Q60: New requirement for new ICU | U60: New requirement | V60: New requirement | W60: Dr.Nita | X60: Nil | Y60: Nil | Z60: 50 | AA60: 50 | AB60: 2000000 | AC60: Approved
A61: 59 | B61: Biochemistry | C61: Plant & Machinery | D61: Biomedical Equipment | E61: Electrophoresis Instrument | F61: 1 | H61: Biochemistry | I61: 1800000 | L61: 1800000 | P61: July | Q61: Used for separation and analysis of proteins, hemoglobin, lipoproteins, and other biomolecules . Supports NABL/NABH compliance requirements. Enhances laboratory standards and audit readiness. | R61: Inability to perform essential tests such as Serum Protein Electrophoresis (SPEP) and Hemoglobin electrophoresis. Continuous expenditure on outsourced investigations.Loss of potential revenue from in-house specialized testing | T61: Typically 8–12% of equipment cost per year after warranty period. AMC/CMC a) Consumables b) Quality Control Materials | U61: Electrophoresis numbers are increasing day by day and presently we are outsourcing the samples. | V61: New | W61: nishanth | X61: utilization of the Electrophoresis Machine in the Biochemistry Department can be assessed based on workload, test types, and operational frequency | Z61: 1 | AA61: 1 | AB61: 1800000 | AC61: Approved
A62: 60 | B62: Clinical Nutrition | C62: Plant & Machinery | D62: Biomedical Equipment | E62: Body composition analyser (InBody) | F62: 1 | G62: New requirment | H62: Clinical Nutrition | I62: 1600000 | L62: 1600000 | M62: Market Survey | N62: 46113 | O62: 46174 | P62: August | Q62: Biomedical equipment, for nutrition screening/ assessment and also to adapt to newer technologies leading to revenue generation | R62: Will not be able to upgrade the services and attract patient flow and related revenue loss | S62: Need to assess the BCA while sitting/ standing and supine positions | T62: As per the inputs from BME | U62: Improve clinical nutrition services for IP and OP, portable technique for quick and fast body composition analysis, to enhance departmentwise revenue generation | Z62: 1 | AA62: 1 | AB62: 1600000 | AC62: Approved
A63: 61 | B63: Biomedical | C63: Plant & Machinery | D63: Biomedical Equipment | E63: Uretero reno fiber Scope | F63: 4 | H63: Main OT | I63: 400000 | L63: 1600000 | N63: August | P63: August | Q63: New requirement | T63: After warranty CMC will come | U63: New requirement | V63: new requirement | W63: Dr DATSON | X63: Nil | Y63: Nil | Z63: 4 | AA63: 1 | AB63: 400000 | AC63: Approved
A64: 62 | B64: Biomedical | C64: Plant & Machinery | D64: Biomedical Equipment | E64: Deep Freezer -40 | F64: 2 | H64: Blood Bank | I64: 800000 | L64: 1600000 | N64: December | P64: December | Q64: A Deep Freezer (-40°C) is a critical storage equipment in the Blood Bank for preserving plasma components and temperature-sensitive reagents under controlled conditions. | R64: Inability to Store Fresh Frozen Plasma (FFP) Plasma requires storage at ≤ -30°C Without proper freezing, clotting factors degrade Reduced therapeutic efficacy of plasma transfusion | T64: After warranty CMC will come | U64: More than 10 years of usage, needs replacement | V64: Replacement | W64: nil | X64: Nil | Y64: Nil | Z64: 2 | AA64: 2 | AB64: 1600000 | AC64: Approved on machine condition
A65: 63 | B65: Biomedical | C65: Plant & Machinery | D65: Biomedical Equipment | E65: Dental chair | F65: 4 | H65: Dental OP | I65: 400000 | L65: 1600000 | N65: November | P65: November | Q65: Replacement for old machine | T65: After warranty CMC will come | U65: Frequent complaint | V65: replacement | W65: Dr Jacob Chacko | X65: Nil | Y65: Nil | Z65: 2 | AA65: 2 | AB65: 800000 | AC65: Approved
A66: 64 | B66: Biomedical | C66: Plant & Machinery | D66: Biomedical Equipment | E66: Neuro Navigation Surgical Instruments | F66: 1 | H66: Neuro OT | I66: 1500000 | L66: 1500000 | N66: September | P66: September | Q66: New requirement | U66: New Requirement | V66: new requirement | W66: Dr KK, Dr SK | X66: Nil | Y66: Nil | AC66: Waiting for list from CSSD
A67: 65 | B67: Biomedical | C67: Plant & Machinery | D67: Biomedical Equipment | E67: Patient trolley | F67: 10 | H67: Various department | I67: 125000 | L67: 1250000 | N67: April | P67: April | U67: New requirement | X67: Nil | Y67: Nil | Z67: 10 | AA67: 10 | AB67: 1250000 | AC67: Approved
A68: 66 | B68: Physiotherapy | C68: Plant & Machinery | D68: Biomedical Equipment | E68: Spinal decompression traction unit | F68: 1 | G68: New | H68: Physiotherapy Unit | I68: 1200000 | L68: 1200000 | M68: Vendor Quote | P68: September | Q68: Non-surgical spinal decompression for conditions like disc herniations and nerve impingements | R68: Fewer non-invasive treatment options for spinal issues, leading to prolonged recovery | S68: Traction Type: Lumbar & cervical Pulling Force:0-100 kg - Modes:Static, intermittent, cyclic Features: Emergency stop, digital control | U68: Effective in treating chronic spinal conditions without surgery, improving patient outcomes and reducing hospital referrals | X68: Nil | Y68: Nil | AC68: ON HOLD
A69: 67 | B69: Biomedical | C69: Plant & Machinery | D69: Biomedical Equipment | E69: ENT Surgical instruments | F69: 1 | H69: ENT | I69: 1200000 | L69: 1200000 | N69: September | P69: September | Q69: New requirement | U69: New requirement | V69: new requirement | W69: Dr Idicula | X69: Nil | Y69: Nil | Z69: 1 | AA69: 1 | AB69: 1200000 | AC69: Waiting for list from CSSD
A70: 68 | B70: Biomedical | C70: Plant & Machinery | D70: Biomedical Equipment | E70: Portable ventilator | F70: 1 | H70: LTICU | I70: 1200000 | L70: 1200000 | N70: October | P70: October | Q70: New Requirement | R70: additional income | T70: After warranty CMC will come | U70: New requirement | V70: new requirement | W70: Dr Fadal | X70: Nil | Y70: Nil | Z70: 1 | AA70: 1 | AB70: 1200000 | AC70: Approved
A71: 69 | B71: Biomedical | C71: Plant & Machinery | D71: Biomedical Equipment | E71: Portable ventilator | F71: 1 | H71: Ambulance | I71: 1200000 | L71: 1200000 | N71: November | P71: November | Q71: New requirement for new icu ambulance | R71: additionla income generative | T71: After warranty CMC will come | U71: New requirement | V71: New requirement | W71: Dr Deepthi | X71: Nil | Y71: Nil | Z71: 1 | AA71: 1 | AB71: 1200000 | AC71: Approved
A72: 70 | B72: Biomedical | C72: Plant & Machinery | D72: Biomedical Equipment | E72: Portable ventilator | F72: 1 | H72: Emergency | I72: 1200000 | L72: 1200000 | N72: July | P72: July | Q72: Repacement for old machine more than 10 years | T72: After warranty CMC will come | U72: More than 10 years of usage,achived its life | V72: Replacement | W72: Dr Deepthi | X72: Nil | Y72: Nil | Z72: 1 | AA72: 1 | AB72: 1200000 | AC72: Approved
A73: 71 | B73: Biomedical | C73: Plant & Machinery | D73: Biomedical Equipment | E73: Referal monitor | F73: 4 | H73: Gastroenterology | I73: 300000 | L73: 1200000 | N73: November | P73: November | U73: More than 10 years of usage | X73: Nil | Y73: Nil | Z73: 2 | AA73: 2 | AB73: 600000 | AC73: Approved
A74: 72 | B74: Biomedical | C74: Plant & Machinery | D74: Biomedical Equipment | E74: ECG machine | F74: 6 | H74: Various floors | I74: 200000 | L74: 1200000 | N74: April | P74: April | Q74: Replacement | U74: Replacement | V74: Replacement | W74: Biomedical | X74: Nil | Y74: Nil | Z74: 6 | AA74: 6 | AB74: 1200000 | AC74: Approved
A75: 73 | B75: Biomedical | C75: Plant & Machinery | D75: Biomedical Equipment | E75: Calibration and QA of various equipments | H75: Biomedical | I75: 800000 | L75: 800000 | N75: October | P75: October | Q75: Recalibration of radiology equipments | U75: New requirement | V75: Recalibration | W75: Biomedical | X75: Nil | Y75: Nil | AC75: Approved
A76: 74 | B76: Physiotherapy | C76: Plant & Machinery | D76: Biomedical Equipment | E76: Shock wave therapy | F76: 1 | G76: New | H76: Physiotherapy Unit | I76: 1000000 | J76: Nil | K76: Nil | L76: 1000000 | M76: Vendor Quote | P76: September | Q76: Effective for chronic pain conditions like plantar fasciitis, tendinopathies, and calcific shoulder issues | R76: Reduced effectiveness in treating chronic musculoskeletal conditions, leading to longer recovery times | S76: Shockwave Type:Radial/Focused - Frequency: 1-20 Hz - Intensity: Up to 5 bars - Features:Multiple applicator heads, low noise, portable | U76: Proven non-invasive solution for chronic pain, reduces surgical referrals, and enhances patient satisfaction. | V76: It’s a New Machine , it will generate addition income | W76: Departments Head | X76: Nil | Y76: Nil | AC76: ON HOLD
A77: 75 | B77: Physiotherapy | C77: Plant & Machinery | D77: Biomedical Equipment | E77: Armable Game based Physiotherapy upperlimb rehabilitation device | F77: 1 | G77: New | H77: Physiotherapy Unit | I77: 1000000 | L77: 1000000 | M77: Vendor Quote (Schnell Tech) | P77: September | Q77: to strengthen and modernize the physiotherapy and neuro rehab services by incorporating technology driven, patient centric rehabilitaion for individuals with upperlimb weakness | R77: Limit the department to conventional rehabilitation methods, resulting in lower patient engagement, slower recovery, reduced competitiveness and missed revenue opportunities from advanced neuro rehab services | S77: real time performance feedback and progress monitoring with objective data recording for assessment and reporting. | U77: Technology driven engaging therapy which improves patient compliance and therapist efficiency. Requires minimal space and support revenue generation. | X77: Nil | Y77: Nil | AC77: ON HOLD
A78: 76 | B78: Biomedical | C78: Plant & Machinery | D78: Biomedical Equipment | E78: Cold Room | F78: 1 | H78: Biochemistry | I78: 1200000 | L78: 1200000 | N78: November | P78: November | Q78: A Cold Room (2–8°C Walk-in Refrigeration System) is a centralized temperature-controlled storage facility used in laboratories for safe preservation of reagents, kits, calibrators, controls, and patient samples. | R78: failure to store items in specific temperature | T78: After warranty CMC will come | U78: More than 10 years of usage, needs replacement | V78: Replacement | X78: Nil | Y78: Nil | AC78: ON HOLD
A79: 77 | B79: Biomedical | C79: Plant & Machinery | D79: Biomedical Equipment | E79: Impulse oscillometry | F79: 1 | H79: Pulmanology | I79: 1200000 | L79: 1200000 | N79: July | P79: July | Q79: New requirement | U79: New requirement | V79: New requirement | W79: Dr Mujeeb Rahman | X79: Nil | Y79: Nil | Z79: 1 | AA79: 1 | AB79: 1200000 | AC79: Approved
A80: 78 | B80: Biomedical | C80: Plant & Machinery | D80: Biomedical Equipment | E80: BIPAP | F80: 5 | H80: Pulmanology | I80: 200000 | L80: 1000000 | N80: October | P80: October | U80: New requirement | W80: Dr Mujeeb Rahman | X80: Nil | Y80: Nil | Z80: 5 | AA80: 5 | AB80: 1000000 | AC80: Approved
A81: 79 | B81: Biochemistry | C81: Plant & Machinery | D81: Biomedical Equipment | E81: Tube Labeller Insturment | F81: 3 | H81: Biochemistry | I81: 300000 | L81: 900000 | P81: July | Q81: A Tube Labeller Instrument is an automated device used for accurate labeling of sample collection tubes in the laboratory. It plays a critical role in patient identification, sample tracking, and workflow efficiency in the Biochemistry Department.Essential for high sample volume labs. Improves TAT (Turnaround Time). Supports NABL/NABH compliance. Enhances audit traceability. | R81: Failure to invest in a Laboratory Tube Labeler can significantly affect the pre-analytical phase of laboratory operations, leading to clinical, operational, and financial risks. Manual labeling consumes more time. Slower sample registration and processing. Increased patient waiting time. | T81: Operational (Recurring) Costs a) Label Rolls (Major Recurring Cost) Thermal labels / barcode labels Cost depends on: Number of samples per day Label size and quality Average consumption: Directly proportional to daily sample load | U81: Already had discussed the same. To improve the phlebotomy process and for TAT saving. | V81: new | W81: nishanth | X81: Nil | Y81: Nil | AC81: Rejected
A82: 80 | B82: Histopathology | C82: Plant & Machinery | D82: Biomedical Equipment | E82: Cytospin | F82: 1 | H82: Histopathology | I82: 900000 | L82: 900000 | P82: July | Q82: A Cytospin (Cytocentrifuge) is a specialized laboratory instrument used to concentrate cells from fluid specimens onto a small, defined area of a microscope slide for cytological examination. It plays a crucial role in Histopathology and Cytopathology diagnostics. | R82: Non-investment in a Cytocentrifuge reduces diagnostic accuracy, increases repeat sampling, delays reporting, and impacts institutional reputation. For a hospital handling fluid cytology cases, it is a critical instrument to ensure high-quality and reliable histopathology services | T82: spare parts replacement and amc/cmc cost after warrenty | U82: Instrument is too old. | V82: replacement of old instrument | W82: Dr.Pushpa Mahadevan | X82: Nil | Y82: Nil | Z82: 1 | AA82: 1 | AB82: 900000 | AC82: Approved
A83: 81 | B83: Biomedical | C83: Plant & Machinery | D83: Biomedical Equipment | E83: Flexible Cystoscope | F83: 2 | H83: Urology OPD | I83: 900000 | L83: 900000 | N83: September | P83: September | Q83: Replacement | U83: Replacement | V83: Replacement | W83: Dr. Datson | X83: 100 Cases/ Month | Y83: Nil | Z83: 2 | AA83: 2 | AB83: 900000 | AC83: Approved
A84: 82 | B84: Biomedical | C84: Plant & Machinery | D84: Biomedical Equipment | E84: Surgical diathermy | F84: 1 | H84: Main OT | I84: 500000 | L84: 500000 | N84: October | P84: October | Q84: Replacement | U84: Replacement | V84: Replacement | W84: OT Technician | X84: Nil | Y84: Nil | Z84: 1 | AA84: 1 | AB84: 500000 | AC84: Approved
A85: 83 | B85: Biomedical | C85: Plant & Machinery | D85: Biomedical Equipment | E85: Immuno fluorescence microscope with camera | F85: 1 | H85: Histopathology | I85: 800000 | L85: 800000 | N85: February | P85: February | Q85: An Immunofluorescence Microscope with Camera is an advanced diagnostic instrument used for detecting antigen–antibody reactions in tissue sections using fluorescent-labeled antibodies. It is essential for specialized diagnostic services in Histopathology. | R85: Mandatory for comprehensive renal pathology reporting Detects IgG, IgA, IgM, C3, C1q deposition patterns | T85: After warranty CMC will come and bulb replacement | U85: Immunofluorescence microscopy is a sensitive and critical technique, and aging equipment can impact image quality, reliability, and efficiency. | V85: replacement | X85: Nil | Y85: Nil | Z85: 1 | AA85: 1 | AB85: 800000 | AC85: Approved
A86: 84 | B86: Biomedical | C86: Plant & Machinery | D86: Biomedical Equipment | E86: Deep freezer | F86: 1 | H86: Microbiology | I86: 800000 | L86: 800000 | N86: November | P86: November | Q86: A Deep Freezer (-40°C) is an essential equipment in the Microbiology laboratory for long-term preservation of microbial isolates, control strains, reagents, and sensitive materials. | R86: NABL requires preservation of significant isolates Mandatory documentation for traceability Supports audit compliance and quality assurance | T86: After warranty CMC will come and bulb replacement | U86: More than 10 years of usage, needs replacement | V86: replacement | X86: Nil | Y86: Nil | Z86: 1 | AA86: 1 | AB86: 800000 | AC86: Approved on machine condition
A87: 85 | B87: Biomedical | C87: Plant & Machinery | D87: Biomedical Equipment | E87: Deep Freezer | F87: 1 | H87: Molecular biology | I87: 800000 | L87: 800000 | N87: October | P87: October | Q87: A Deep Freezer (-40°C) is a critical infrastructure component in a Molecular Laboratory for preserving temperature-sensitive reagents, extracted nucleic acids, and control materials required for PCR and other molecular assays. | R87: Reagent degradation Compromised test accuracy Increased repeat testing Loss of expensive molecular kits Audit non-conformities Risk of incorrect diagnostic reports | T87: After warranty CMC will come and bulb replacement | U87: More than 10 years of usage, needs replacement | V87: replacement | X87: Nil | Y87: Nil | Z87: 1 | AA87: 1 | AB87: 800000 | AC87: Approved on machine condition
A88: 86 | B88: Biomedical | C88: Plant & Machinery | D88: Biomedical Equipment | E88: Deep Freezer -80 | F88: 1 | H88: Blood Bank | I88: 800000 | L88: 800000 | N88: April | P88: April | Q88: A Deep Freezer (-80°C) is an advanced ultra-low temperature storage system used in specialized blood banks for long-term preservation of rare and critical blood components. | R88: Inability to store rare plasma long-term Risk of losing rare donor units Increased dependency on external sourcing Delays during emergencies Limited advancement of blood bank services | T88: After warranty CMC will come and bulb replacement | U88: More than 10 years of usage, needs replacement | V88: Replacement | W88: Dr. Don | X88: Nil | Y88: Nil | Z88: 1 | AA88: 1 | AB88: 800000 | AC88: Approved on machine condition
A89: 87 | B89: Biomedical | C89: Plant & Machinery | D89: Biomedical Equipment | E89: Defibrillator | F89: 1 | H89: MDICU | I89: 400000 | L89: 400000 | N89: November | P89: November | Q89: New requirement | U89: New requirement | V89: New requirement | W89: Dr.Nita | X89: Nil | Y89: Nil | Z89: 1 | AA89: 1 | AB89: 400000 | AC89: Approved
A90: 88 | B90: Biomedical | C90: Plant & Machinery | D90: Biomedical Equipment | E90: Syringe holder Tungston | F90: 2 | H90: Nuclear medicine | I90: 400000 | L90: 800000 | N90: November | P90: November | Q90: Replacement for old machine | U90: More than 10 years of usage,achieved its life. | V90: Replacement | W90: Anish | X90: Nil | Y90: Nil | Z90: 2 | AA90: 2 | AB90: 800000 | AC90: Approved
A91: 89 | B91: Biomedical | C91: Plant & Machinery | D91: Biomedical Equipment | E91: Consumables for various equipments | H91: Biomedical | I91: 800000 | L91: 800000 | N91: November | P91: November | U91: New requirement | W91: Biomedical | X91: Nil | Y91: Nil | AB91: 800000 | AC91: Approved
A92: 90 | B92: Biomedical | C92: Plant & Machinery | D92: Biomedical Equipment | E92: Head light | F92: 1 | H92: Main OT | I92: 700000 | L92: 700000 | N92: October | P92: October | Q92: Additional requirement | U92: Additional requirement | V92: Additional requirement | W92: Dr.Datson | X92: Nil | Y92: Nil | Z92: 1 | AA92: 1 | AB92: 700000 | AC92: Approved
A93: 91 | B93: Biomedical | C93: Plant & Machinery | D93: Biomedical Equipment | E93: Cold cabinet | F93: 1 | H93: Medical store | I93: 700000 | L93: 700000 | N93: November | P93: November | Q93: New Requirement | U93: New Requirement | V93: New Requirement | W93: Jacob | X93: Nil | Y93: Nil | AC93: ON HOLD
A94: 92 | B94: Biomedical | C94: Plant & Machinery | D94: Biomedical Equipment | E94: Blood Bank Refrigerator 600L | F94: 1 | H94: Blood Bank | I94: 600000 | L94: 600000 | N94: September | P94: September | Q94: Replacement for old machine | U94: More than 10 years of usage, needs replacement | V94: Replacement | W94: Dr.Don | X94: Nil | Y94: Nil | Z94: 1 | AA94: 1 | AB94: 600000 | AC94: Approved on machine condition
A95: 93 | B95: Biomedical | C95: Plant & Machinery | D95: Biomedical Equipment | E95: Sterile Tubing Welder | F95: 1 | H95: Blood Bank | I95: 700000 | L95: 700000 | N95: December | P95: December | U95: More than 10 years of usage, needs replacement | X95: Nil | Y95: Nil | Z95: 1 | AA95: 1 | AB95: 700000 | AC95: Approved on machine condition
A96: 94 | B96: Biomedical | C96: Plant & Machinery | D96: Biomedical Equipment | E96: Examination couch | F96: 8 | H96: Radiology | I96: 680000 | L96: 680000 | N96: October | P96: October | Q96: New Requirement | U96: New Requirement | V96: New Requirement | W96: Shibu | X96: Nil | Y96: Nil | Z96: 8 | AA96: 8 | AB96: 680000 | AC96: Approved
A97: 95 | B97: Biomedical | C97: Plant & Machinery | D97: Biomedical Equipment | E97: Warm oxygen Therapy unit | F97: 1 | H97: Foot and Ankle | I97: 650000 | L97: 650000 | N97: October | P97: October | Q97: New Requirement | U97: New requirement | V97: New Requirement | W97: Dr.Rajesh Simon | X97: Nil | Y97: Nil | Z97: 1 | AA97: 1 | AB97: 650000 | AC97: Approved
A98: 96 | B98: Biomedical | C98: Plant & Machinery | D98: Biomedical Equipment | E98: Platelet Agitator with Incubator | F98: 1 | H98: Blood Bank | I98: 400000 | L98: 400000 | N98: January | P98: January | Q98: Proper Storage of Platelet Concentrates Maintains temperature at 20–24°C Provides continuous gentle agitation Prevents platelet clumping and preserves viability Preservation of Platelet Function Maintains metabolic activity Ensures optimal pH levels Prevents bacterial proliferation due to improper storage | R98: Inability to store platelets properly Increased dependency on external blood centers High risk of platelet spoilage Delay during dengue season and emergency cases Non-compliance during inspection Possible license suspension for component therapy | T98: AMC (8–12% annually) Motor and agitation mechanism servicing Alarm and temperature sensor validation | U98: More than 10 years of usage, needs replacement | V98: Replacement | W98: Dr.Don | X98: Nil | Y98: Nil | Z98: 1 | AA98: 1 | AB98: 400000 | AC98: Approved on machine condition
A99: 97 | B99: Biomedical | C99: Plant & Machinery | D99: Biomedical Equipment | E99: Contamination monitor | F99: 2 | H99: Nuclear medicine | I99: 300000 | L99: 600000 | N99: November | P99: November | U99: More than 10 years of usage,achieved its life. | X99: Nil | Y99: Nil | Z99: 1 | AA99: 1 | AB99: 600000 | AC99: Approved
A100: 98 | B100: Physiotherapy | C100: Plant & Machinery | D100: Biomedical Equipment | E100: Shoulder continuous passive movement machine | F100: 1 | G100: New | H100: Physiotherapy Unit | I100: 556000 | L100: 556000 | M100: Vendor Quote | P100: September | Q100: Aids in post-surgical shoulder rehabilitation by providing controlled passive motion | R100: Increased risk of post-surgical stiffness and delayed recovery | S100: ROM: 0° to 180° - Speed:Variable - Control: Handheld remote - Features:Soft padding, auto-stop sensor | U100: Essential for early mobilization post-surgery, preventing joint stiffness and improving functional outcomes | X100: Nil | Y100: Nil | AC100: ON HOLD
...

Sheet MonthWise
B2: Asset Category Wise Summary
B3: Asset Category | C3: YTD | D3: Apr | E3: May | F3: Jun | G3: Jul | H3: Aug | I3: Sep | J3: Oct | K3: Nov | L3: Dec | M3: Jan | N3: Feb | O3: Mar
B4: Biomedical Assets | C4: =SUMIFS(Capex_Details!$M$4:$M$353,Capex_Details!$E$4:$E$353,MonthWise!B4)/10^5 -> 0 | D4: =SUMIFS(Capex_Details!$M$4:$M$353,Capex_Details!$E$4:$E$353,MonthWise!$B4,Capex_Details!$O$4:$O$353,MonthWise!D$3)/10^5 -> 0 | E4: =SUMIFS(Capex_Details!$M$4:$M$353,Capex_Details!$E$4:$E$353,MonthWise!$B4,Capex_Details!$O$4:$O$353,MonthWise!E$3)/10^5 -> 0 | F4: =SUMIFS(Capex_Details!$M$4:$M$353,Capex_Details!$E$4:$E$353,MonthWise!$B4,Capex_Details!$O$4:$O$353,MonthWise!F$3)/10^5 -> 0 | G4: =SUMIFS(Capex_Details!$M$4:$M$353,Capex_Details!$E$4:$E$353,MonthWise!$B4,Capex_Details!$O$4:$O$353,MonthWise!G$3)/10^5 -> 0 | H4: =SUMIFS(Capex_Details!$M$4:$M$353,Capex_Details!$E$4:$E$353,MonthWise!$B4,Capex_Details!$O$4:$O$353,MonthWise!H$3)/10^5 -> 0 | I4: =SUMIFS(Capex_Details!$M$4:$M$353,Capex_Details!$E$4:$E$353,MonthWise!$B4,Capex_Details!$O$4:$O$353,MonthWise!I$3)/10^5 -> 0 | J4: =SUMIFS(Capex_Details!$M$4:$M$353,Capex_Details!$E$4:$E$353,MonthWise!$B4,Capex_Details!$O$4:$O$353,MonthWise!J$3)/10^5 -> 0 | K4: =SUMIFS(Capex_Details!$M$4:$M$353,Capex_Details!$E$4:$E$353,MonthWise!$B4,Capex_Details!$O$4:$O$353,MonthWise!K$3)/10^5 -> 0 | ... O4: =SUMIFS(Capex_Details!$M$4:$M$353,Capex_Details!$E$4:$E$353,MonthWise!$B4,Capex_Details!$O$4:$O$353,MonthWise!O$3)/10^5 -> 0 | P4: =SUM(D4:O4)-C4 -> 0
B5: Vehicles | C5: =SUMIFS(Capex_Details!$M$4:$M$353,Capex_Details!$E$4:$E$353,MonthWise!B5)/10^5 -> 0 | D5: =SUMIFS(Capex_Details!$M$4:$M$353,Capex_Details!$E$4:$E$353,MonthWise!$B5,Capex_Details!$O$4:$O$353,MonthWise!D$3)/10^5 -> 0 | E5: =SUMIFS(Capex_Details!$M$4:$M$353,Capex_Details!$E$4:$E$353,MonthWise!$B5,Capex_Details!$O$4:$O$353,MonthWise!E$3)/10^5 -> 0 | F5: =SUMIFS(Capex_Details!$M$4:$M$353,Capex_Details!$E$4:$E$353,MonthWise!$B5,Capex_Details!$O$4:$O$353,MonthWise!F$3)/10^5 -> 0 | G5: =SUMIFS(Capex_Details!$M$4:$M$353,Capex_Details!$E$4:$E$353,MonthWise!$B5,Capex_Details!$O$4:$O$353,MonthWise!G$3)/10^5 -> 0 | H5: =SUMIFS(Capex_Details!$M$4:$M$353,Capex_Details!$E$4:$E$353,MonthWise!$B5,Capex_Details!$O$4:$O$353,MonthWise!H$3)/10^5 -> 0 | I5: =SUMIFS(Capex_Details!$M$4:$M$353,Capex_Details!$E$4:$E$353,MonthWise!$B5,Capex_Details!$O$4:$O$353,MonthWise!I$3)/10^5 -> 0 | J5: =SUMIFS(Capex_Details!$M$4:$M$353,Capex_Details!$E$4:$E$353,MonthWise!$B5,Capex_Details!$O$4:$O$353,MonthWise!J$3)/10^5 -> 0 | K5: =SUMIFS(Capex_Details!$M$4:$M$353,Capex_Details!$E$4:$E$353,MonthWise!$B5,Capex_Details!$O$4:$O$353,MonthWise!K$3)/10^5 -> 0 | ... O5: =SUMIFS(Capex_Details!$M$4:$M$353,Capex_Details!$E$4:$E$353,MonthWise!$B5,Capex_Details!$O$4:$O$353,MonthWise!O$3)/10^5 -> 0 | P5: =SUM(D5:O5)-C5 -> 0
B6: Fire & Safety Assets | C6: =SUMIFS(Capex_Details!$M$4:$M$353,Capex_Details!$E$4:$E$353,MonthWise!B6)/10^5 -> 0 | D6: =SUMIFS(Capex_Details!$M$4:$M$353,Capex_Details!$E$4:$E$353,MonthWise!$B6,Capex_Details!$O$4:$O$353,MonthWise!D$3)/10^5 -> 0 | E6: =SUMIFS(Capex_Details!$M$4:$M$353,Capex_Details!$E$4:$E$353,MonthWise!$B6,Capex_Details!$O$4:$O$353,MonthWise!E$3)/10^5 -> 0 | F6: =SUMIFS(Capex_Details!$M$4:$M$353,Capex_Details!$E$4:$E$353,MonthWise!$B6,Capex_Details!$O$4:$O$353,MonthWise!F$3)/10^5 -> 0 | G6: =SUMIFS(Capex_Details!$M$4:$M$353,Capex_Details!$E$4:$E$353,MonthWise!$B6,Capex_Details!$O$4:$O$353,MonthWise!G$3)/10^5 -> 0 | H6: =SUMIFS(Capex_Details!$M$4:$M$353,Capex_Details!$E$4:$E$353,MonthWise!$B6,Capex_Details!$O$4:$O$353,MonthWise!H$3)/10^5 -> 0 | I6: =SUMIFS(Capex_Details!$M$4:$M$353,Capex_Details!$E$4:$E$353,MonthWise!$B6,Capex_Details!$O$4:$O$353,MonthWise!I$3)/10^5 -> 0 | J6: =SUMIFS(Capex_Details!$M$4:$M$353,Capex_Details!$E$4:$E$353,MonthWise!$B6,Capex_Details!$O$4:$O$353,MonthWise!J$3)/10^5 -> 0 | K6: =SUMIFS(Capex_Details!$M$4:$M$353,Capex_Details!$E$4:$E$353,MonthWise!$B6,Capex_Details!$O$4:$O$353,MonthWise!K$3)/10^5 -> 0 | ... O6: =SUMIFS(Capex_Details!$M$4:$M$353,Capex_Details!$E$4:$E$353,MonthWise!$B6,Capex_Details!$O$4:$O$353,MonthWise!O$3)/10^5 -> 0 | P6: =SUM(D6:O6)-C6 -> 0
B7: IT Assets | C7: =SUMIFS(Capex_Details!$M$4:$M$353,Capex_Details!$E$4:$E$353,MonthWise!B7)/10^5 -> 0 | D7: =SUMIFS(Capex_Details!$M$4:$M$353,Capex_Details!$E$4:$E$353,MonthWise!$B7,Capex_Details!$O$4:$O$353,MonthWise!D$3)/10^5 -> 0 | E7: =SUMIFS(Capex_Details!$M$4:$M$353,Capex_Details!$E$4:$E$353,MonthWise!$B7,Capex_Details!$O$4:$O$353,MonthWise!E$3)/10^5 -> 0 | F7: =SUMIFS(Capex_Details!$M$4:$M$353,Capex_Details!$E$4:$E$353,MonthWise!$B7,Capex_Details!$O$4:$O$353,MonthWise!F$3)/10^5 -> 0 | G7: =SUMIFS(Capex_Details!$M$4:$M$353,Capex_Details!$E$4:$E$353,MonthWise!$B7,Capex_Details!$O$4:$O$353,MonthWise!G$3)/10^5 -> 0 | H7: =SUMIFS(Capex_Details!$M$4:$M$353,Capex_Details!$E$4:$E$353,MonthWise!$B7,Capex_Details!$O$4:$O$353,MonthWise!H$3)/10^5 -> 0 | I7: =SUMIFS(Capex_Details!$M$4:$M$353,Capex_Details!$E$4:$E$353,MonthWise!$B7,Capex_Details!$O$4:$O$353,MonthWise!I$3)/10^5 -> 0 | J7: =SUMIFS(Capex_Details!$M$4:$M$353,Capex_Details!$E$4:$E$353,MonthWise!$B7,Capex_Details!$O$4:$O$353,MonthWise!J$3)/10^5 -> 0 | K7: =SUMIFS(Capex_Details!$M$4:$M$353,Capex_Details!$E$4:$E$353,MonthWise!$B7,Capex_Details!$O$4:$O$353,MonthWise!K$3)/10^5 -> 0 | ... O7: =SUMIFS(Capex_Details!$M$4:$M$353,Capex_Details!$E$4:$E$353,MonthWise!$B7,Capex_Details!$O$4:$O$353,MonthWise!O$3)/10^5 -> 0 | P7: =SUM(D7:O7)-C7 -> 0
B8: Furniture & Fixtures Assets | C8: =SUMIFS(Capex_Details!$M$4:$M$353,Capex_Details!$E$4:$E$353,MonthWise!B8)/10^5 -> 0 | D8: =SUMIFS(Capex_Details!$M$4:$M$353,Capex_Details!$E$4:$E$353,MonthWise!$B8,Capex_Details!$O$4:$O$353,MonthWise!D$3)/10^5 -> 0 | E8: =SUMIFS(Capex_Details!$M$4:$M$353,Capex_Details!$E$4:$E$353,MonthWise!$B8,Capex_Details!$O$4:$O$353,MonthWise!E$3)/10^5 -> 0 | F8: =SUMIFS(Capex_Details!$M$4:$M$353,Capex_Details!$E$4:$E$353,MonthWise!$B8,Capex_Details!$O$4:$O$353,MonthWise!F$3)/10^5 -> 0 | G8: =SUMIFS(Capex_Details!$M$4:$M$353,Capex_Details!$E$4:$E$353,MonthWise!$B8,Capex_Details!$O$4:$O$353,MonthWise!G$3)/10^5 -> 0 | H8: =SUMIFS(Capex_Details!$M$4:$M$353,Capex_Details!$E$4:$E$353,MonthWise!$B8,Capex_Details!$O$4:$O$353,MonthWise!H$3)/10^5 -> 0 | I8: =SUMIFS(Capex_Details!$M$4:$M$353,Capex_Details!$E$4:$E$353,MonthWise!$B8,Capex_Details!$O$4:$O$353,MonthWise!I$3)/10^5 -> 0 | J8: =SUMIFS(Capex_Details!$M$4:$M$353,Capex_Details!$E$4:$E$353,MonthWise!$B8,Capex_Details!$O$4:$O$353,MonthWise!J$3)/10^5 -> 0 | K8: =SUMIFS(Capex_Details!$M$4:$M$353,Capex_Details!$E$4:$E$353,MonthWise!$B8,Capex_Details!$O$4:$O$353,MonthWise!K$3)/10^5 -> 0 | ... O8: =SUMIFS(Capex_Details!$M$4:$M$353,Capex_Details!$E$4:$E$353,MonthWise!$B8,Capex_Details!$O$4:$O$353,MonthWise!O$3)/10^5 -> 0 | P8: =SUM(D8:O8)-C8 -> 0
B9: Electrical Equipments | C9: =SUMIFS(Capex_Details!$M$4:$M$353,Capex_Details!$E$4:$E$353,MonthWise!B9)/10^5 -> 7 | D9: =SUMIFS(Capex_Details!$M$4:$M$353,Capex_Details!$E$4:$E$353,MonthWise!$B9,Capex_Details!$O$4:$O$353,MonthWise!D$3)/10^5 -> 0 | E9: =SUMIFS(Capex_Details!$M$4:$M$353,Capex_Details!$E$4:$E$353,MonthWise!$B9,Capex_Details!$O$4:$O$353,MonthWise!E$3)/10^5 -> 0 | F9: =SUMIFS(Capex_Details!$M$4:$M$353,Capex_Details!$E$4:$E$353,MonthWise!$B9,Capex_Details!$O$4:$O$353,MonthWise!F$3)/10^5 -> 0 | G9: =SUMIFS(Capex_Details!$M$4:$M$353,Capex_Details!$E$4:$E$353,MonthWise!$B9,Capex_Details!$O$4:$O$353,MonthWise!G$3)/10^5 -> 0 | H9: =SUMIFS(Capex_Details!$M$4:$M$353,Capex_Details!$E$4:$E$353,MonthWise!$B9,Capex_Details!$O$4:$O$353,MonthWise!H$3)/10^5 -> 0 | I9: =SUMIFS(Capex_Details!$M$4:$M$353,Capex_Details!$E$4:$E$353,MonthWise!$B9,Capex_Details!$O$4:$O$353,MonthWise!I$3)/10^5 -> 0 | J9: =SUMIFS(Capex_Details!$M$4:$M$353,Capex_Details!$E$4:$E$353,MonthWise!$B9,Capex_Details!$O$4:$O$353,MonthWise!J$3)/10^5 -> 0 | K9: =SUMIFS(Capex_Details!$M$4:$M$353,Capex_Details!$E$4:$E$353,MonthWise!$B9,Capex_Details!$O$4:$O$353,MonthWise!K$3)/10^5 -> 0 | ... O9: =SUMIFS(Capex_Details!$M$4:$M$353,Capex_Details!$E$4:$E$353,MonthWise!$B9,Capex_Details!$O$4:$O$353,MonthWise!O$3)/10^5 -> 0 | P9: =SUM(D9:O9)-C9 -> -7
B10: Project | C10: =SUMIFS(Capex_Details!$M$4:$M$353,Capex_Details!$E$4:$E$353,MonthWise!B10)/10^5 -> 0 | D10: =SUMIFS(Capex_Details!$M$4:$M$353,Capex_Details!$E$4:$E$353,MonthWise!$B10,Capex_Details!$O$4:$O$353,MonthWise!D$3)/10^5 -> 0 | E10: =SUMIFS(Capex_Details!$M$4:$M$353,Capex_Details!$E$4:$E$353,MonthWise!$B10,Capex_Details!$O$4:$O$353,MonthWise!E$3)/10^5 -> 0 | F10: =SUMIFS(Capex_Details!$M$4:$M$353,Capex_Details!$E$4:$E$353,MonthWise!$B10,Capex_Details!$O$4:$O$353,MonthWise!F$3)/10^5 -> 0 | G10: =SUMIFS(Capex_Details!$M$4:$M$353,Capex_Details!$E$4:$E$353,MonthWise!$B10,Capex_Details!$O$4:$O$353,MonthWise!G$3)/10^5 -> 0 | H10: =SUMIFS(Capex_Details!$M$4:$M$353,Capex_Details!$E$4:$E$353,MonthWise!$B10,Capex_Details!$O$4:$O$353,MonthWise!H$3)/10^5 -> 0 | I10: =SUMIFS(Capex_Details!$M$4:$M$353,Capex_Details!$E$4:$E$353,MonthWise!$B10,Capex_Details!$O$4:$O$353,MonthWise!I$3)/10^5 -> 0 | J10: =SUMIFS(Capex_Details!$M$4:$M$353,Capex_Details!$E$4:$E$353,MonthWise!$B10,Capex_Details!$O$4:$O$353,MonthWise!J$3)/10^5 -> 0 | K10: =SUMIFS(Capex_Details!$M$4:$M$353,Capex_Details!$E$4:$E$353,MonthWise!$B10,Capex_Details!$O$4:$O$353,MonthWise!K$3)/10^5 -> 0 | ... O10: =SUMIFS(Capex_Details!$M$4:$M$353,Capex_Details!$E$4:$E$353,MonthWise!$B10,Capex_Details!$O$4:$O$353,MonthWise!O$3)/10^5 -> 0 | P10: =SUM(D10:O10)-C10 -> 0
B11: Land | C11: =SUMIFS(Capex_Details!$M$4:$M$353,Capex_Details!$E$4:$E$353,MonthWise!B11)/10^5 -> 0 | D11: =SUMIFS(Capex_Details!$M$4:$M$353,Capex_Details!$E$4:$E$353,MonthWise!$B11,Capex_Details!$O$4:$O$353,MonthWise!D$3)/10^5 -> 0 | E11: =SUMIFS(Capex_Details!$M$4:$M$353,Capex_Details!$E$4:$E$353,MonthWise!$B11,Capex_Details!$O$4:$O$353,MonthWise!E$3)/10^5 -> 0 | F11: =SUMIFS(Capex_Details!$M$4:$M$353,Capex_Details!$E$4:$E$353,MonthWise!$B11,Capex_Details!$O$4:$O$353,MonthWise!F$3)/10^5 -> 0 | G11: =SUMIFS(Capex_Details!$M$4:$M$353,Capex_Details!$E$4:$E$353,MonthWise!$B11,Capex_Details!$O$4:$O$353,MonthWise!G$3)/10^5 -> 0 | H11: =SUMIFS(Capex_Details!$M$4:$M$353,Capex_Details!$E$4:$E$353,MonthWise!$B11,Capex_Details!$O$4:$O$353,MonthWise!H$3)/10^5 -> 0 | I11: =SUMIFS(Capex_Details!$M$4:$M$353,Capex_Details!$E$4:$E$353,MonthWise!$B11,Capex_Details!$O$4:$O$353,MonthWise!I$3)/10^5 -> 0 | J11: =SUMIFS(Capex_Details!$M$4:$M$353,Capex_Details!$E$4:$E$353,MonthWise!$B11,Capex_Details!$O$4:$O$353,MonthWise!J$3)/10^5 -> 0 | K11: =SUMIFS(Capex_Details!$M$4:$M$353,Capex_Details!$E$4:$E$353,MonthWise!$B11,Capex_Details!$O$4:$O$353,MonthWise!K$3)/10^5 -> 0 | ... O11: =SUMIFS(Capex_Details!$M$4:$M$353,Capex_Details!$E$4:$E$353,MonthWise!$B11,Capex_Details!$O$4:$O$353,MonthWise!O$3)/10^5 -> 0 | P11: =SUM(D11:O11)-C11 -> 0
B12: Building | C12: =SUMIFS(Capex_Details!$M$4:$M$353,Capex_Details!$E$4:$E$353,MonthWise!B12)/10^5 -> 0 | D12: =SUMIFS(Capex_Details!$M$4:$M$353,Capex_Details!$E$4:$E$353,MonthWise!$B12,Capex_Details!$O$4:$O$353,MonthWise!D$3)/10^5 -> 0 | E12: =SUMIFS(Capex_Details!$M$4:$M$353,Capex_Details!$E$4:$E$353,MonthWise!$B12,Capex_Details!$O$4:$O$353,MonthWise!E$3)/10^5 -> 0 | F12: =SUMIFS(Capex_Details!$M$4:$M$353,Capex_Details!$E$4:$E$353,MonthWise!$B12,Capex_Details!$O$4:$O$353,MonthWise!F$3)/10^5 -> 0 | G12: =SUMIFS(Capex_Details!$M$4:$M$353,Capex_Details!$E$4:$E$353,MonthWise!$B12,Capex_Details!$O$4:$O$353,MonthWise!G$3)/10^5 -> 0 | H12: =SUMIFS(Capex_Details!$M$4:$M$353,Capex_Details!$E$4:$E$353,MonthWise!$B12,Capex_Details!$O$4:$O$353,MonthWise!H$3)/10^5 -> 0 | I12: =SUMIFS(Capex_Details!$M$4:$M$353,Capex_Details!$E$4:$E$353,MonthWise!$B12,Capex_Details!$O$4:$O$353,MonthWise!I$3)/10^5 -> 0 | J12: =SUMIFS(Capex_Details!$M$4:$M$353,Capex_Details!$E$4:$E$353,MonthWise!$B12,Capex_Details!$O$4:$O$353,MonthWise!J$3)/10^5 -> 0 | K12: =SUMIFS(Capex_Details!$M$4:$M$353,Capex_Details!$E$4:$E$353,MonthWise!$B12,Capex_Details!$O$4:$O$353,MonthWise!K$3)/10^5 -> 0 | ... O12: =SUMIFS(Capex_Details!$M$4:$M$353,Capex_Details!$E$4:$E$353,MonthWise!$B12,Capex_Details!$O$4:$O$353,MonthWise!O$3)/10^5 -> 0 | P12: =SUM(D12:O12)-C12 -> 0
C13: =SUMIFS(Capex_Details!$M$4:$M$353,Capex_Details!$E$4:$E$353,MonthWise!B13)/10^5 -> 0 | D13: =SUMIFS(Capex_Details!$M$4:$M$353,Capex_Details!$E$4:$E$353,MonthWise!$B13,Capex_Details!$O$4:$O$353,MonthWise!D$3)/10^5 -> 0 | E13: =SUMIFS(Capex_Details!$M$4:$M$353,Capex_Details!$E$4:$E$353,MonthWise!$B13,Capex_Details!$O$4:$O$353,MonthWise!E$3)/10^5 -> 0 | F13: =SUMIFS(Capex_Details!$M$4:$M$353,Capex_Details!$E$4:$E$353,MonthWise!$B13,Capex_Details!$O$4:$O$353,MonthWise!F$3)/10^5 -> 0 | G13: =SUMIFS(Capex_Details!$M$4:$M$353,Capex_Details!$E$4:$E$353,MonthWise!$B13,Capex_Details!$O$4:$O$353,MonthWise!G$3)/10^5 -> 0 | H13: =SUMIFS(Capex_Details!$M$4:$M$353,Capex_Details!$E$4:$E$353,MonthWise!$B13,Capex_Details!$O$4:$O$353,MonthWise!H$3)/10^5 -> 0 | I13: =SUMIFS(Capex_Details!$M$4:$M$353,Capex_Details!$E$4:$E$353,MonthWise!$B13,Capex_Details!$O$4:$O$353,MonthWise!I$3)/10^5 -> 0 | J13: =SUMIFS(Capex_Details!$M$4:$M$353,Capex_Details!$E$4:$E$353,MonthWise!$B13,Capex_Details!$O$4:$O$353,MonthWise!J$3)/10^5 -> 0 | K13: =SUMIFS(Capex_Details!$M$4:$M$353,Capex_Details!$E$4:$E$353,MonthWise!$B13,Capex_Details!$O$4:$O$353,MonthWise!K$3)/10^5 -> 0 | ... O13: =SUMIFS(Capex_Details!$M$4:$M$353,Capex_Details!$E$4:$E$353,MonthWise!$B13,Capex_Details!$O$4:$O$353,MonthWise!O$3)/10^5 -> 0 | P13: =SUM(D13:O13)-C13 -> 0
B14: Total | C14: =SUM(C4:C13) -> 7 | D14: =SUM(D4:D13) -> 0 | E14: =SUM(E4:E13) -> 0 | F14: =SUM(F4:F13) -> 0 | G14: =SUM(G4:G13) -> 0 | H14: =SUM(H4:H13) -> 0 | I14: =SUM(I4:I13) -> 0 | J14: =SUM(J4:J13) -> 0 | ... O14: =SUM(O4:O13) -> 0 | P14: =SUM(D14:O14)-C14 -> -7

Sheet Sheet1
B2: Capex Requirement For FY 26-27
B3: Sl.No. | C3: Department | D3: Status
B4: 1 | C4: Clinical Nutrition | D4: Received
B5: 2 | C5: Safety & Security | D5: Received
B6: 3 | C6: Pharmacy | D6: Received
B7: 4 | C7: Food & Beverage | D7: Received
B8: 5 | C8: House Keeping | D8: Received
B9: 6 | C9: IT | D9: Received
B10: 7 | C10: Physiotherapy | D10: Received
B11: 8 | C11: Store | D11: Pending
B12: 9 | C12: CSSD | D12: Pending
B13: 10 | C13: Operation | D13: Pending
B14: 11 | C14: Radiology | D14: Pending
B15: 12 | C15: MRD | D15: Pending
... B25: 22 | C25: Purchase | D25: Pending
