Workbook

Sheet Performance Tracker
A1: VPS LAKESHORE — MONTHLY PERFORMANCE TRACKER | FY 2026–27
A2: All figures ₹ Lakhs | Plan linked from 'Monthly P&L' | enter Actuals in blue columns | % Rev = line ÷ Total Revenue
B3: FY26 Actual | C3: Growth % | D3: FY27 Plan | E3: FY27 Plan % Rev | F3: YTD Plan | G3: % Ach. vs YTD Plan | H3: YTD FY27 | I3: YTD % Rev | J3: % Achieved | K3: 46138 | O3: 46168 | S3: 46199 | W3: 46229 | AA3: 46260 | AE3: 46291 | AI3: 46321 | AM3: 46352 | AQ3: 46382 | AU3: 46049 | AY3: 46080 | BC3: 46108
K4: Plan | L4: Actual | M4: % Achv | N4: % Rev | O4: Plan | P4: Actual | Q4: % Achv | R4: % Rev | S4: Plan | T4: Actual | U4: % Achv | V4: % Rev | W4: Plan | X4: Actual | Y4: % Achv | Z4: % Rev | AA4: Plan | AB4: Actual | AC4: % Achv | AD4: % Rev | AE4: Plan | AF4: Actual | AG4: % Achv | AH4: % Rev | AI4: Plan | AJ4: Actual | AK4: % Achv | AL4: % Rev | AM4: Plan | AN4: Actual | AO4: % Achv | AP4: % Rev | AQ4: Plan | AR4: Actual | AS4: % Achv | AT4: % Rev | AU4: Plan | AV4: Actual | AW4: % Achv | AX4: % Rev | AY4: Plan | AZ4: Actual | BA4: % Achv | BB4: % Rev | BC4: Plan | BD4: Actual | BE4: % Achv | BF4: % Rev
A5: REVENUE
A6: IP Revenue | B6: ='Monthly P&L'!B5 -> 31154.53 | C6: =IF(OR(B6=0,B6=""),"",D6/B6-1) -> 0.27923931 | D6: ='Monthly P&L'!C5 -> 39854.1 | E6: =IF(D$10=0,"",D6/D$10) -> 0.69285692 | F6: =IF(H6="","",K6*(L6<>"")+O6*(P6<>"")+S6*(T6<>"")+W6*(X6<>"")+AA6*(AB6<>"")+AE6*(AF6<>"")+AI6*(AJ6<>"")+AM6*(AN6<>"")+AQ6*(AR6<>"")+AU6*(AV6<>"")+AY6*(AZ6<>"")+BC6*(BD6<>"")) -> 6102.0628 | G6: =IF(OR(F6=0,F6="",H6=""),"",H6/F6) -> 1.0338463 | H6: =IF(SUM(L6,P6,T6,X6,AB6,AF6,AJ6,AN6,AR6,AV6,AZ6,BD6)=0,"",SUM(L6,P6,T6,X6,AB6,AF6,AJ6,AN6,AR6,AV6,AZ6,BD6)) -> 6308.5948 | I6: =IF(OR(H$10="",H$10=0,H6=""),"",H6/H$10) -> 0.72472349 | J6: =IF(OR(D6=0,H6=""),"",H6/D6) -> 0.15829224 | K6: ='Monthly P&L'!D5 -> 2876.8074 | L6: 3091.941 | M6: =IF(OR(L6="",K6=0),"",L6/K6) -> 1.0747821 | N6: =IF(OR(L6="",L$10="",L$10=0),"",L6/L$10) -> 0.72260511 | O6: ='Monthly P&L'!E5 -> 3225.2555 | P6: 3216.6538 | Q6: =IF(OR(P6="",O6=0),"",P6/O6) -> 0.99733304 | R6: =IF(OR(P6="",P$10="",P$10=0),"",P6/P$10) -> 0.72677148 | S6: ='Monthly P&L'!F5 -> 2894.7614 | U6: =IF(OR(T6="",S6=0),"",T6/S6) | V6: =IF(OR(T6="",T$10="",T$10=0),"",T6/T$10) | W6: ='Monthly P&L'!G5 -> 3395.955 | Y6: =IF(OR(X6="",W6=0),"",X6/W6) | Z6: =IF(OR(X6="",X$10="",X$10=0),"",X6/X$10) | AA6: ='Monthly P&L'!H5 -> 3520.9665 | AC6: =IF(OR(AB6="",AA6=0),"",AB6/AA6) | AD6: =IF(OR(AB6="",AB$10="",AB$10=0),"",AB6/AB$10) | AE6: ='Monthly P&L'!I5 -> 3502.6117 | AG6: =IF(OR(AF6="",AE6=0),"",AF6/AE6) | AH6: =IF(OR(AF6="",AF$10="",AF$10=0),"",AF6/AF$10) | AI6: ='Monthly P&L'!J5 -> 3472.181 | AK6: =IF(OR(AJ6="",AI6=0),"",AJ6/AI6) | AL6: =IF(OR(AJ6="",AJ$10="",AJ$10=0),"",AJ6/AJ$10) | AM6: ='Monthly P&L'!K5 -> 3091.2843 | AO6: =IF(OR(AN6="",AM6=0),"",AN6/AM6) | AP6: =IF(OR(AN6="",AN$10="",AN$10=0),"",AN6/AN$10) | AQ6: ='Monthly P&L'!L5 -> 3298.0825 | AS6: =IF(OR(AR6="",AQ6=0),"",AR6/AQ6) | AT6: =IF(OR(AR6="",AR$10="",AR$10=0),"",AR6/AR$10) | AU6: ='Monthly P&L'!M5 -> 3813.4737 | AW6: =IF(OR(AV6="",AU6=0),"",AV6/AU6) | AX6: =IF(OR(AV6="",AV$10="",AV$10=0),"",AV6/AV$10) | AY6: ='Monthly P&L'!N5 -> 3468.5768 | BA6: =IF(OR(AZ6="",AY6=0),"",AZ6/AY6) | BB6: =IF(OR(AZ6="",AZ$10="",AZ$10=0),"",AZ6/AZ$10) | BC6: ='Monthly P&L'!O5 -> 3294.1442 | BE6: =IF(OR(BD6="",BC6=0),"",BD6/BC6) | BF6: =IF(OR(BD6="",BD$10="",BD$10=0),"",BD6/BD$10)
A7: OP Revenue | B7: ='Monthly P&L'!B6 -> 12160.816 | C7: =IF(OR(B7=0,B7=""),"",D7/B7-1) -> 0.19395774 | D7: ='Monthly P&L'!C6 -> 14519.5 | E7: =IF(D$10=0,"",D7/D$10) -> 0.2524191 | F7: =IF(H7="","",K7*(L7<>"")+O7*(P7<>"")+S7*(T7<>"")+W7*(X7<>"")+AA7*(AB7<>"")+AE7*(AF7<>"")+AI7*(AJ7<>"")+AM7*(AN7<>"")+AQ7*(AR7<>"")+AU7*(AV7<>"")+AY7*(AZ7<>"")+BC7*(BD7<>"")) -> 2348.5126 | G7: =IF(OR(F7=0,F7="",H7=""),"",H7/F7) -> 0.85387823 | H7: =IF(SUM(L7,P7,T7,X7,AB7,AF7,AJ7,AN7,AR7,AV7,AZ7,BD7)=0,"",SUM(L7,P7,T7,X7,AB7,AF7,AJ7,AN7,AR7,AV7,AZ7,BD7)) -> 2005.3438 | I7: =IF(OR(H$10="",H$10=0,H7=""),"",H7/H$10) -> 0.23037139 | J7: =IF(OR(D7=0,H7=""),"",H7/D7) -> 0.13811383 | K7: ='Monthly P&L'!D6 -> 1144.8245 | L7: 980.77008 | M7: =IF(OR(L7="",K7=0),"",L7/K7) -> 0.85669908 | N7: =IF(OR(L7="",L$10="",L$10=0),"",L7/L$10) -> 0.22921184 | O7: ='Monthly P&L'!E6 -> 1203.6881 | P7: 1024.5737 | Q7: =IF(OR(P7="",O7=0),"",P7/O7) -> 0.85119532 | R7: =IF(OR(P7="",P$10="",P$10=0),"",P7/P$10) -> 0.2314924 | S7: ='Monthly P&L'!F6 -> 1086.5151 | U7: =IF(OR(T7="",S7=0),"",T7/S7) | V7: =IF(OR(T7="",T$10="",T$10=0),"",T7/T$10) | W7: ='Monthly P&L'!G6 -> 1302.6032 | Y7: =IF(OR(X7="",W7=0),"",X7/W7) | Z7: =IF(OR(X7="",X$10="",X$10=0),"",X7/X$10) | AA7: ='Monthly P&L'!H6 -> 1314.8005 | AC7: =IF(OR(AB7="",AA7=0),"",AB7/AA7) | AD7: =IF(OR(AB7="",AB$10="",AB$10=0),"",AB7/AB$10) | AE7: ='Monthly P&L'!I6 -> 1244.6991 | AG7: =IF(OR(AF7="",AE7=0),"",AF7/AE7) | AH7: =IF(OR(AF7="",AF$10="",AF$10=0),"",AF7/AF$10) | AI7: ='Monthly P&L'!J6 -> 1242.9217 | AK7: =IF(OR(AJ7="",AI7=0),"",AJ7/AI7) | AL7: =IF(OR(AJ7="",AJ$10="",AJ$10=0),"",AJ7/AJ$10) | AM7: ='Monthly P&L'!K6 -> 1120.6707 | AO7: =IF(OR(AN7="",AM7=0),"",AN7/AM7) | AP7: =IF(OR(AN7="",AN$10="",AN$10=0),"",AN7/AN$10) | AQ7: ='Monthly P&L'!L6 -> 1184.946 | AS7: =IF(OR(AR7="",AQ7=0),"",AR7/AQ7) | AT7: =IF(OR(AR7="",AR$10="",AR$10=0),"",AR7/AR$10) | AU7: ='Monthly P&L'!M6 -> 1326.6257 | AW7: =IF(OR(AV7="",AU7=0),"",AV7/AU7) | AX7: =IF(OR(AV7="",AV$10="",AV$10=0),"",AV7/AV$10) | AY7: ='Monthly P&L'!N6 -> 1191.909 | BA7: =IF(OR(AZ7="",AY7=0),"",AZ7/AY7) | BB7: =IF(OR(AZ7="",AZ$10="",AZ$10=0),"",AZ7/AZ$10) | BC7: ='Monthly P&L'!O6 -> 1155.2967 | BE7: =IF(OR(BD7="",BC7=0),"",BD7/BC7) | BF7: =IF(OR(BD7="",BD$10="",BD$10=0),"",BD7/BD$10)
A8: F&B / VPS Gourmet | B8: ='Monthly P&L'!B7 -> 1718.1767 | C8: =IF(OR(B8=0,B8=""),"",D8/B8-1) -> 0.29363878 | D8: ='Monthly P&L'!C7 -> 2222.7 | E8: =IF(D$10=0,"",D8/D$10) -> 0.038641271 | F8: =IF(H8="","",K8*(L8<>"")+O8*(P8<>"")+S8*(T8<>"")+W8*(X8<>"")+AA8*(AB8<>"")+AE8*(AF8<>"")+AI8*(AJ8<>"")+AM8*(AN8<>"")+AQ8*(AR8<>"")+AU8*(AV8<>"")+AY8*(AZ8<>"")+BC8*(BD8<>"")) -> 355.90897 | G8: =IF(OR(F8=0,F8="",H8=""),"",H8/F8) -> 0.9106661 | H8: =IF(SUM(L8,P8,T8,X8,AB8,AF8,AJ8,AN8,AR8,AV8,AZ8,BD8)=0,"",SUM(L8,P8,T8,X8,AB8,AF8,AJ8,AN8,AR8,AV8,AZ8,BD8)) -> 324.11424 | I8: =IF(OR(H$10="",H$10=0,H8=""),"",H8/H$10) -> 0.037233839 | J8: =IF(OR(D8=0,H8=""),"",H8/D8) -> 0.14582006 | K8: ='Monthly P&L'!D7 -> 172.64272 | L8: 157.02992 | M8: =IF(OR(L8="",K8=0),"",L8/K8) -> 0.90956586 | N8: =IF(OR(L8="",L$10="",L$10=0),"",L8/L$10) -> 0.036698833 | O8: ='Monthly P&L'!E7 -> 183.26626 | P8: 167.08431 | Q8: =IF(OR(P8="",O8=0),"",P8/O8) -> 0.91170256 | R8: =IF(OR(P8="",P$10="",P$10=0),"",P8/P$10) -> 0.037751067 | S8: ='Monthly P&L'!F7 -> 169.6418 | U8: =IF(OR(T8="",S8=0),"",T8/S8) | V8: =IF(OR(T8="",T$10="",T$10=0),"",T8/T$10) | W8: ='Monthly P&L'!G7 -> 198.35485 | Y8: =IF(OR(X8="",W8=0),"",X8/W8) | Z8: =IF(OR(X8="",X$10="",X$10=0),"",X8/X$10) | AA8: ='Monthly P&L'!H7 -> 197.8822 | AC8: =IF(OR(AB8="",AA8=0),"",AB8/AA8) | AD8: =IF(OR(AB8="",AB$10="",AB$10=0),"",AB8/AB$10) | AE8: ='Monthly P&L'!I7 -> 191.14197 | AG8: =IF(OR(AF8="",AE8=0),"",AF8/AE8) | AH8: =IF(OR(AF8="",AF$10="",AF$10=0),"",AF8/AF$10) | AI8: ='Monthly P&L'!J7 -> 190.0075 | AK8: =IF(OR(AJ8="",AI8=0),"",AJ8/AI8) | AL8: =IF(OR(AJ8="",AJ$10="",AJ$10=0),"",AJ8/AJ$10) | AM8: ='Monthly P&L'!K7 -> 177.99094 | AO8: =IF(OR(AN8="",AM8=0),"",AN8/AM8) | AP8: =IF(OR(AN8="",AN$10="",AN$10=0),"",AN8/AN$10) | AQ8: ='Monthly P&L'!L7 -> 183.43362 | AS8: =IF(OR(AR8="",AQ8=0),"",AR8/AQ8) | AT8: =IF(OR(AR8="",AR$10="",AR$10=0),"",AR8/AR$10) | AU8: ='Monthly P&L'!M7 -> 201.12799 | AW8: =IF(OR(AV8="",AU8=0),"",AV8/AU8) | AX8: =IF(OR(AV8="",AV$10="",AV$10=0),"",AV8/AV$10) | AY8: ='Monthly P&L'!N7 -> 183.82706 | BA8: =IF(OR(AZ8="",AY8=0),"",AZ8/AY8) | BB8: =IF(OR(AZ8="",AZ$10="",AZ$10=0),"",AZ8/AZ$10) | BC8: ='Monthly P&L'!O7 -> 173.38309 | BE8: =IF(OR(BD8="",BC8=0),"",BD8/BC8) | BF8: =IF(OR(BD8="",BD$10="",BD$10=0),"",BD8/BD$10)
A9: Other Income | B9: ='Monthly P&L'!B8 -> 875.5977 | C9: =IF(OR(B9=0,B9=""),"",D9/B9-1) -> 0.056535441 | D9: ='Monthly P&L'!C8 -> 925.1 | E9: =IF(D$10=0,"",D9/D$10) -> 0.01608271 | F9: =IF(H9="","",K9*(L9<>"")+O9*(P9<>"")+S9*(T9<>"")+W9*(X9<>"")+AA9*(AB9<>"")+AE9*(AF9<>"")+AI9*(AJ9<>"")+AM9*(AN9<>"")+AQ9*(AR9<>"")+AU9*(AV9<>"")+AY9*(AZ9<>"")+BC9*(BD9<>"")) -> 96.610756 | G9: =IF(OR(F9=0,F9="",H9=""),"",H9/F9) -> 0.6911987 | H9: =IF(SUM(L9,P9,T9,X9,AB9,AF9,AJ9,AN9,AR9,AV9,AZ9,BD9)=0,"",SUM(L9,P9,T9,X9,AB9,AF9,AJ9,AN9,AR9,AV9,AZ9,BD9)) -> 66.777229 | I9: =IF(OR(H$10="",H$10=0,H9=""),"",H9/H$10) -> 0.0076712846 | J9: =IF(OR(D9=0,H9=""),"",H9/D9) -> 0.072183795 | K9: ='Monthly P&L'!D8 -> 23.262151 | L9: 49.139616 | M9: =IF(OR(L9="",K9=0),"",L9/K9) -> 2.1124279 | N9: =IF(OR(L9="",L$10="",L$10=0),"",L9/L$10) -> 0.011484222 | O9: ='Monthly P&L'!E8 -> 73.348605 | P9: 17.637613 | Q9: =IF(OR(P9="",O9=0),"",P9/O9) -> 0.24046283 | R9: =IF(OR(P9="",P$10="",P$10=0),"",P9/P$10) -> 0.0039850462 | S9: ='Monthly P&L'!F8 -> 66.43931 | U9: =IF(OR(T9="",S9=0),"",T9/S9) | V9: =IF(OR(T9="",T$10="",T$10=0),"",T9/T$10) | W9: ='Monthly P&L'!G8 -> 16.323444 | Y9: =IF(OR(X9="",W9=0),"",X9/W9) | Z9: =IF(OR(X9="",X$10="",X$10=0),"",X9/X$10) | AA9: ='Monthly P&L'!H8 -> 23.353976 | AC9: =IF(OR(AB9="",AA9=0),"",AB9/AA9) | AD9: =IF(OR(AB9="",AB$10="",AB$10=0),"",AB9/AB$10) | AE9: ='Monthly P&L'!I8 -> 26.985795 | AG9: =IF(OR(AF9="",AE9=0),"",AF9/AE9) | AH9: =IF(OR(AF9="",AF$10="",AF$10=0),"",AF9/AF$10) | AI9: ='Monthly P&L'!J8 -> 45.125736 | AK9: =IF(OR(AJ9="",AI9=0),"",AJ9/AI9) | AL9: =IF(OR(AJ9="",AJ$10="",AJ$10=0),"",AJ9/AJ$10) | AM9: ='Monthly P&L'!K8 -> 31.312755 | AO9: =IF(OR(AN9="",AM9=0),"",AN9/AM9) | AP9: =IF(OR(AN9="",AN$10="",AN$10=0),"",AN9/AN$10) | AQ9: ='Monthly P&L'!L8 -> 14.044394 | AS9: =IF(OR(AR9="",AQ9=0),"",AR9/AQ9) | AT9: =IF(OR(AR9="",AR$10="",AR$10=0),"",AR9/AR$10) | AU9: ='Monthly P&L'!M8 -> 53.197681 | AW9: =IF(OR(AV9="",AU9=0),"",AV9/AU9) | AX9: =IF(OR(AV9="",AV$10="",AV$10=0),"",AV9/AV$10) | AY9: ='Monthly P&L'!N8 -> 219.67586 | BA9: =IF(OR(AZ9="",AY9=0),"",AZ9/AY9) | BB9: =IF(OR(AZ9="",AZ$10="",AZ$10=0),"",AZ9/AZ$10) | BC9: ='Monthly P&L'!O8 -> 332.04697 | BE9: =IF(OR(BD9="",BC9=0),"",BD9/BC9) | BF9: =IF(OR(BD9="",BD$10="",BD$10=0),"",BD9/BD$10)
A10: Total Revenue | B10: ='Monthly P&L'!B9 -> 45909.12 | C10: =IF(OR(B10=0,B10=""),"",D10/B10-1) -> 0.25294058 | D10: ='Monthly P&L'!C9 -> 57521.4 | E10: =IF(D$10=0,"",D10/D$10) -> 1 | F10: =IF(H10="","",K10*(L10<>"")+O10*(P10<>"")+S10*(T10<>"")+W10*(X10<>"")+AA10*(AB10<>"")+AE10*(AF10<>"")+AI10*(AJ10<>"")+AM10*(AN10<>"")+AQ10*(AR10<>"")+AU10*(AV10<>"")+AY10*(AZ10<>"")+BC10*(BD10<>"")) -> 8903.0952 | G10: =IF(OR(F10=0,F10="",H10=""),"",H10/F10) -> 0.97773077 | H10: =IF(SUM(L10,P10,T10,X10,AB10,AF10,AJ10,AN10,AR10,AV10,AZ10,BD10)=0,"",SUM(L10,P10,T10,X10,AB10,AF10,AJ10,AN10,AR10,AV10,AZ10,BD10)) -> 8704.8301 | I10: =IF(OR(H$10="",H$10=0,H10=""),"",H10/H$10) -> 1 | J10: =IF(OR(D10=0,H10=""),"",H10/D10) -> 0.15133203 | K10: ='Monthly P&L'!D9 -> 4217.5367 | L10: =IF(SUM(L6:L9)=0,"",SUM(L6:L9)) -> 4278.8806 | M10: =IF(OR(L10="",K10=0),"",L10/K10) -> 1.014545 | N10: =IF(OR(L10="",L$10="",L$10=0),"",L10/L$10) -> 1 | O10: ='Monthly P&L'!E9 -> 4685.5584 | P10: =IF(SUM(P6:P9)=0,"",SUM(P6:P9)) -> 4425.9494 | Q10: =IF(OR(P10="",O10=0),"",P10/O10) -> 0.9445938 | R10: =IF(OR(P10="",P$10="",P$10=0),"",P10/P$10) -> 1 | S10: ='Monthly P&L'!F9 -> 4217.3576 | T10: =IF(SUM(T6:T9)=0,"",SUM(T6:T9)) | U10: =IF(OR(T10="",S10=0),"",T10/S10) | V10: =IF(OR(T10="",T$10="",T$10=0),"",T10/T$10) | W10: ='Monthly P&L'!G9 -> 4913.2364 | X10: =IF(SUM(X6:X9)=0,"",SUM(X6:X9)) | Y10: =IF(OR(X10="",W10=0),"",X10/W10) | Z10: =IF(OR(X10="",X$10="",X$10=0),"",X10/X$10) | AA10: ='Monthly P&L'!H9 -> 5057.0032 | AB10: =IF(SUM(AB6:AB9)=0,"",SUM(AB6:AB9)) | AC10: =IF(OR(AB10="",AA10=0),"",AB10/AA10) | AD10: =IF(OR(AB10="",AB$10="",AB$10=0),"",AB10/AB$10) | AE10: ='Monthly P&L'!I9 -> 4965.4385 | AF10: =IF(SUM(AF6:AF9)=0,"",SUM(AF6:AF9)) | AG10: =IF(OR(AF10="",AE10=0),"",AF10/AE10) | AH10: =IF(OR(AF10="",AF$10="",AF$10=0),"",AF10/AF$10) | AI10: ='Monthly P&L'!J9 -> 4950.2359 | AJ10: =IF(SUM(AJ6:AJ9)=0,"",SUM(AJ6:AJ9)) | AK10: =IF(OR(AJ10="",AI10=0),"",AJ10/AI10) | AL10: =IF(OR(AJ10="",AJ$10="",AJ$10=0),"",AJ10/AJ$10) | AM10: ='Monthly P&L'!K9 -> 4421.2587 | AN10: =IF(SUM(AN6:AN9)=0,"",SUM(AN6:AN9)) | AO10: =IF(OR(AN10="",AM10=0),"",AN10/AM10) | AP10: =IF(OR(AN10="",AN$10="",AN$10=0),"",AN10/AN$10) | AQ10: ='Monthly P&L'!L9 -> 4680.5064 | AR10: =IF(SUM(AR6:AR9)=0,"",SUM(AR6:AR9)) | AS10: =IF(OR(AR10="",AQ10=0),"",AR10/AQ10) | AT10: =IF(OR(AR10="",AR$10="",AR$10=0),"",AR10/AR$10) | AU10: ='Monthly P&L'!M9 -> 5394.4251 | AV10: =IF(SUM(AV6:AV9)=0,"",SUM(AV6:AV9)) | AW10: =IF(OR(AV10="",AU10=0),"",AV10/AU10) | AX10: =IF(OR(AV10="",AV$10="",AV$10=0),"",AV10/AV$10) | AY10: ='Monthly P&L'!N9 -> 5063.9887 | AZ10: =IF(SUM(AZ6:AZ9)=0,"",SUM(AZ6:AZ9)) | BA10: =IF(OR(AZ10="",AY10=0),"",AZ10/AY10) | BB10: =IF(OR(AZ10="",AZ$10="",AZ$10=0),"",AZ10/AZ$10) | BC10: ='Monthly P&L'!O9 -> 4954.8709 | BD10: =IF(SUM(BD6:BD9)=0,"",SUM(BD6:BD9)) | BE10: =IF(OR(BD10="",BC10=0),"",BD10/BC10) | BF10: =IF(OR(BD10="",BD$10="",BD$10=0),"",BD10/BD$10)
A11: VARIABLE COSTS
A12: Consumption / Drug & Consumables | B12: ='Monthly P&L'!B12 -> 13709.978 | C12: =IF(OR(B12=0,B12=""),"",D12/B12-1) -> 0.11183076 | D12: ='Monthly P&L'!C12 -> 15243.175 | E12: =IF(D$10=0,"",D12/D$10) -> 0.26500008 | F12: =IF(H12="","",K12*(L12<>"")+O12*(P12<>"")+S12*(T12<>"")+W12*(X12<>"")+AA12*(AB12<>"")+AE12*(AF12<>"")+AI12*(AJ12<>"")+AM12*(AN12<>"")+AQ12*(AR12<>"")+AU12*(AV12<>"")+AY12*(AZ12<>"")+BC12*(BD12<>"")) -> 2235.185 | G12: =IF(OR(F12=0,F12="",H12=""),"",H12/F12) -> 1.1593003 | H12: =IF(SUM(L12,P12,T12,X12,AB12,AF12,AJ12,AN12,AR12,AV12,AZ12,BD12)=0,"",SUM(L12,P12,T12,X12,AB12,AF12,AJ12,AN12,AR12,AV12,AZ12,BD12)) -> 2591.2507 | I12: =IF(OR(H$10="",H$10=0,H12=""),"",H12/H$10) -> 0.29767964 | J12: =IF(OR(D12=0,H12=""),"",H12/D12) -> 0.16999415 | K12: ='Monthly P&L'!D12 -> 960.94761 | L12: 1246.2882 | M12: =IF(OR(L12="",K12=0),"",L12/K12) -> 1.2969366 | N12: =IF(OR(L12="",L$10="",L$10=0),"",L12/L$10) -> 0.291265 | O12: ='Monthly P&L'!E12 -> 1274.2374 | P12: 1344.9625 | Q12: =IF(OR(P12="",O12=0),"",P12/O12) -> 1.0555039 | R12: =IF(OR(P12="",P$10="",P$10=0),"",P12/P$10) -> 0.30388114 | S12: ='Monthly P&L'!F12 -> 1245.8601 | U12: =IF(OR(T12="",S12=0),"",T12/S12) | V12: =IF(OR(T12="",T$10="",T$10=0),"",T12/T$10) | W12: ='Monthly P&L'!G12 -> 1420.1062 | Y12: =IF(OR(X12="",W12=0),"",X12/W12) | Z12: =IF(OR(X12="",X$10="",X$10=0),"",X12/X$10) | AA12: ='Monthly P&L'!H12 -> 1356.5204 | AC12: =IF(OR(AB12="",AA12=0),"",AB12/AA12) | AD12: =IF(OR(AB12="",AB$10="",AB$10=0),"",AB12/AB$10) | AE12: ='Monthly P&L'!I12 -> 1289.868 | AG12: =IF(OR(AF12="",AE12=0),"",AF12/AE12) | AH12: =IF(OR(AF12="",AF$10="",AF$10=0),"",AF12/AF$10) | AI12: ='Monthly P&L'!J12 -> 1366.0106 | AK12: =IF(OR(AJ12="",AI12=0),"",AJ12/AI12) | AL12: =IF(OR(AJ12="",AJ$10="",AJ$10=0),"",AJ12/AJ$10) | AM12: ='Monthly P&L'!K12 -> 1200.5291 | AO12: =IF(OR(AN12="",AM12=0),"",AN12/AM12) | AP12: =IF(OR(AN12="",AN$10="",AN$10=0),"",AN12/AN$10) | AQ12: ='Monthly P&L'!L12 -> 1281.6389 | AS12: =IF(OR(AR12="",AQ12=0),"",AR12/AQ12) | AT12: =IF(OR(AR12="",AR$10="",AR$10=0),"",AR12/AR$10) | AU12: ='Monthly P&L'!M12 -> 1380.4566 | AW12: =IF(OR(AV12="",AU12=0),"",AV12/AU12) | AX12: =IF(OR(AV12="",AV$10="",AV$10=0),"",AV12/AV$10) | AY12: ='Monthly P&L'!N12 -> 1301.0576 | BA12: =IF(OR(AZ12="",AY12=0),"",AZ12/AY12) | BB12: =IF(OR(AZ12="",AZ$10="",AZ$10=0),"",AZ12/AZ$10) | BC12: ='Monthly P&L'!O12 -> 1165.9428 | BE12: =IF(OR(BD12="",BC12=0),"",BD12/BC12) | BF12: =IF(OR(BD12="",BD$10="",BD$10=0),"",BD12/BD$10)
A13: Doctor Cost | B13: ='Monthly P&L'!B13 -> 7978.262 | C13: =IF(OR(B13=0,B13=""),"",D13/B13-1) -> 0.12806411 | D13: ='Monthly P&L'!C13 -> 8999.991 | E13: =IF(D$10=0,"",D13/D$10) -> 0.15646335 | F13: =IF(H13="","",K13*(L13<>"")+O13*(P13<>"")+S13*(T13<>"")+W13*(X13<>"")+AA13*(AB13<>"")+AE13*(AF13<>"")+AI13*(AJ13<>"")+AM13*(AN13<>"")+AQ13*(AR13<>"")+AU13*(AV13<>"")+AY13*(AZ13<>"")+BC13*(BD13<>"")) -> 1499.9985 | G13: =IF(OR(F13=0,F13="",H13=""),"",H13/F13) -> 0.93851002 | H13: =IF(SUM(L13,P13,T13,X13,AB13,AF13,AJ13,AN13,AR13,AV13,AZ13,BD13)=0,"",SUM(L13,P13,T13,X13,AB13,AF13,AJ13,AN13,AR13,AV13,AZ13,BD13)) -> 1407.7636 | I13: =IF(OR(H$10="",H$10=0,H13=""),"",H13/H$10) -> 0.16172213 | J13: =IF(OR(D13=0,H13=""),"",H13/D13) -> 0.15641834 | K13: ='Monthly P&L'!D13 -> 749.99925 | L13: 715.16936 | M13: =IF(OR(L13="",K13=0),"",L13/K13) -> 0.9535601 | N13: =IF(OR(L13="",L$10="",L$10=0),"",L13/L$10) -> 0.16713936 | O13: ='Monthly P&L'!E13 -> 749.99925 | P13: 692.59426 | Q13: =IF(OR(P13="",O13=0),"",P13/O13) -> 0.92345994 | R13: =IF(OR(P13="",P$10="",P$10=0),"",P13/P$10) -> 0.1564849 | S13: ='Monthly P&L'!F13 -> 749.99925 | U13: =IF(OR(T13="",S13=0),"",T13/S13) | V13: =IF(OR(T13="",T$10="",T$10=0),"",T13/T$10) | W13: ='Monthly P&L'!G13 -> 749.99925 | Y13: =IF(OR(X13="",W13=0),"",X13/W13) | Z13: =IF(OR(X13="",X$10="",X$10=0),"",X13/X$10) | AA13: ='Monthly P&L'!H13 -> 749.99925 | AC13: =IF(OR(AB13="",AA13=0),"",AB13/AA13) | AD13: =IF(OR(AB13="",AB$10="",AB$10=0),"",AB13/AB$10) | AE13: ='Monthly P&L'!I13 -> 749.99925 | AG13: =IF(OR(AF13="",AE13=0),"",AF13/AE13) | AH13: =IF(OR(AF13="",AF$10="",AF$10=0),"",AF13/AF$10) | AI13: ='Monthly P&L'!J13 -> 749.99925 | AK13: =IF(OR(AJ13="",AI13=0),"",AJ13/AI13) | AL13: =IF(OR(AJ13="",AJ$10="",AJ$10=0),"",AJ13/AJ$10) | AM13: ='Monthly P&L'!K13 -> 749.99925 | AO13: =IF(OR(AN13="",AM13=0),"",AN13/AM13) | AP13: =IF(OR(AN13="",AN$10="",AN$10=0),"",AN13/AN$10) | AQ13: ='Monthly P&L'!L13 -> 749.99925 | AS13: =IF(OR(AR13="",AQ13=0),"",AR13/AQ13) | AT13: =IF(OR(AR13="",AR$10="",AR$10=0),"",AR13/AR$10) | AU13: ='Monthly P&L'!M13 -> 749.99925 | AW13: =IF(OR(AV13="",AU13=0),"",AV13/AU13) | AX13: =IF(OR(AV13="",AV$10="",AV$10=0),"",AV13/AV$10) | AY13: ='Monthly P&L'!N13 -> 749.99925 | BA13: =IF(OR(AZ13="",AY13=0),"",AZ13/AY13) | BB13: =IF(OR(AZ13="",AZ$10="",AZ$10=0),"",AZ13/AZ$10) | BC13: ='Monthly P&L'!O13 -> 749.99925 | BE13: =IF(OR(BD13="",BC13=0),"",BD13/BC13) | BF13: =IF(OR(BD13="",BD$10="",BD$10=0),"",BD13/BD$10)
A14: Total Variable Cost | B14: ='Monthly P&L'!B14 -> 21688.24 | C14: =IF(OR(B14=0,B14=""),"",D14/B14-1) -> 0.11780238 | D14: ='Monthly P&L'!C14 -> 24243.166 | E14: =IF(D$10=0,"",D14/D$10) -> 0.42146343 | F14: =IF(H14="","",K14*(L14<>"")+O14*(P14<>"")+S14*(T14<>"")+W14*(X14<>"")+AA14*(AB14<>"")+AE14*(AF14<>"")+AI14*(AJ14<>"")+AM14*(AN14<>"")+AQ14*(AR14<>"")+AU14*(AV14<>"")+AY14*(AZ14<>"")+BC14*(BD14<>"")) -> 3735.1835 | G14: =IF(OR(F14=0,F14="",H14=""),"",H14/F14) -> 1.070634 | H14: =IF(SUM(L14,P14,T14,X14,AB14,AF14,AJ14,AN14,AR14,AV14,AZ14,BD14)=0,"",SUM(L14,P14,T14,X14,AB14,AF14,AJ14,AN14,AR14,AV14,AZ14,BD14)) -> 3999.0143 | I14: =IF(OR(H$10="",H$10=0,H14=""),"",H14/H$10) -> 0.45940177 | J14: =IF(OR(D14=0,H14=""),"",H14/D14) -> 0.16495429 | K14: ='Monthly P&L'!D14 -> 1710.9469 | L14: =IF(L$10="","",L12+L13) -> 1961.4575 | M14: =IF(OR(L14="",K14=0),"",L14/K14) -> 1.1464164 | N14: =IF(OR(L14="",L$10="",L$10=0),"",L14/L$10) -> 0.45840436 | O14: ='Monthly P&L'!E14 -> 2024.2366 | P14: =IF(P$10="","",P12+P13) -> 2037.5568 | Q14: =IF(OR(P14="",O14=0),"",P14/O14) -> 1.0065804 | R14: =IF(OR(P14="",P$10="",P$10=0),"",P14/P$10) -> 0.46036604 | S14: ='Monthly P&L'!F14 -> 1995.8594 | T14: =IF(T$10="","",T12+T13) | U14: =IF(OR(T14="",S14=0),"",T14/S14) | V14: =IF(OR(T14="",T$10="",T$10=0),"",T14/T$10) | W14: ='Monthly P&L'!G14 -> 2170.1055 | X14: =IF(X$10="","",X12+X13) | Y14: =IF(OR(X14="",W14=0),"",X14/W14) | Z14: =IF(OR(X14="",X$10="",X$10=0),"",X14/X$10) | AA14: ='Monthly P&L'!H14 -> 2106.5197 | AB14: =IF(AB$10="","",AB12+AB13) | AC14: =IF(OR(AB14="",AA14=0),"",AB14/AA14) | AD14: =IF(OR(AB14="",AB$10="",AB$10=0),"",AB14/AB$10) | AE14: ='Monthly P&L'!I14 -> 2039.8673 | AF14: =IF(AF$10="","",AF12+AF13) | AG14: =IF(OR(AF14="",AE14=0),"",AF14/AE14) | AH14: =IF(OR(AF14="",AF$10="",AF$10=0),"",AF14/AF$10) | AI14: ='Monthly P&L'!J14 -> 2116.0099 | AJ14: =IF(AJ$10="","",AJ12+AJ13) | AK14: =IF(OR(AJ14="",AI14=0),"",AJ14/AI14) | AL14: =IF(OR(AJ14="",AJ$10="",AJ$10=0),"",AJ14/AJ$10) | AM14: ='Monthly P&L'!K14 -> 1950.5283 | AN14: =IF(AN$10="","",AN12+AN13) | AO14: =IF(OR(AN14="",AM14=0),"",AN14/AM14) | AP14: =IF(OR(AN14="",AN$10="",AN$10=0),"",AN14/AN$10) | AQ14: ='Monthly P&L'!L14 -> 2031.6382 | AR14: =IF(AR$10="","",AR12+AR13) | AS14: =IF(OR(AR14="",AQ14=0),"",AR14/AQ14) | AT14: =IF(OR(AR14="",AR$10="",AR$10=0),"",AR14/AR$10) | AU14: ='Monthly P&L'!M14 -> 2130.4558 | AV14: =IF(AV$10="","",AV12+AV13) | AW14: =IF(OR(AV14="",AU14=0),"",AV14/AU14) | AX14: =IF(OR(AV14="",AV$10="",AV$10=0),"",AV14/AV$10) | AY14: ='Monthly P&L'!N14 -> 2051.0569 | AZ14: =IF(AZ$10="","",AZ12+AZ13) | BA14: =IF(OR(AZ14="",AY14=0),"",AZ14/AY14) | BB14: =IF(OR(AZ14="",AZ$10="",AZ$10=0),"",AZ14/AZ$10) | BC14: ='Monthly P&L'!O14 -> 1915.9421 | BD14: =IF(BD$10="","",BD12+BD13) | BE14: =IF(OR(BD14="",BC14=0),"",BD14/BC14) | BF14: =IF(OR(BD14="",BD$10="",BD$10=0),"",BD14/BD$10)
A15: Contribution | B15: ='Monthly P&L'!B15 -> 24220.88 | C15: =IF(OR(B15=0,B15=""),"",D15/B15-1) -> 0.37394815 | D15: ='Monthly P&L'!C15 -> 33278.234 | E15: =IF(D$10=0,"",D15/D$10) -> 0.57853657 | F15: =IF(H15="","",K15*(L15<>"")+O15*(P15<>"")+S15*(T15<>"")+W15*(X15<>"")+AA15*(AB15<>"")+AE15*(AF15<>"")+AI15*(AJ15<>"")+AM15*(AN15<>"")+AQ15*(AR15<>"")+AU15*(AV15<>"")+AY15*(AZ15<>"")+BC15*(BD15<>"")) -> 5167.9117 | G15: =IF(OR(F15=0,F15="",H15=""),"",H15/F15) -> 0.91058362 | H15: =IF(SUM(L15,P15,T15,X15,AB15,AF15,AJ15,AN15,AR15,AV15,AZ15,BD15)=0,"",SUM(L15,P15,T15,X15,AB15,AF15,AJ15,AN15,AR15,AV15,AZ15,BD15)) -> 4705.8157 | I15: =IF(OR(H$10="",H$10=0,H15=""),"",H15/H$10) -> 0.54059823 | J15: =IF(OR(D15=0,H15=""),"",H15/D15) -> 0.14140822 | K15: ='Monthly P&L'!D15 -> 2506.5899 | L15: =IF(L$10="","",L10-L14) -> 2317.4231 | M15: =IF(OR(L15="",K15=0),"",L15/K15) -> 0.92453222 | N15: =IF(OR(L15="",L$10="",L$10=0),"",L15/L$10) -> 0.54159564 | O15: ='Monthly P&L'!E15 -> 2661.3218 | P15: =IF(P$10="","",P10-P14) -> 2388.3926 | Q15: =IF(OR(P15="",O15=0),"",P15/O15) -> 0.89744601 | R15: =IF(OR(P15="",P$10="",P$10=0),"",P15/P$10) -> 0.53963396 | S15: ='Monthly P&L'!F15 -> 2221.4983 | T15: =IF(T$10="","",T10-T14) | U15: =IF(OR(T15="",S15=0),"",T15/S15) | V15: =IF(OR(T15="",T$10="",T$10=0),"",T15/T$10) | W15: ='Monthly P&L'!G15 -> 2743.1309 | X15: =IF(X$10="","",X10-X14) | Y15: =IF(OR(X15="",W15=0),"",X15/W15) | Z15: =IF(OR(X15="",X$10="",X$10=0),"",X15/X$10) | AA15: ='Monthly P&L'!H15 -> 2950.4835 | AB15: =IF(AB$10="","",AB10-AB14) | AC15: =IF(OR(AB15="",AA15=0),"",AB15/AA15) | AD15: =IF(OR(AB15="",AB$10="",AB$10=0),"",AB15/AB$10) | AE15: ='Monthly P&L'!I15 -> 2925.5713 | AF15: =IF(AF$10="","",AF10-AF14) | AG15: =IF(OR(AF15="",AE15=0),"",AF15/AE15) | AH15: =IF(OR(AF15="",AF$10="",AF$10=0),"",AF15/AF$10) | AI15: ='Monthly P&L'!J15 -> 2834.226 | AJ15: =IF(AJ$10="","",AJ10-AJ14) | AK15: =IF(OR(AJ15="",AI15=0),"",AJ15/AI15) | AL15: =IF(OR(AJ15="",AJ$10="",AJ$10=0),"",AJ15/AJ$10) | AM15: ='Monthly P&L'!K15 -> 2470.7304 | AN15: =IF(AN$10="","",AN10-AN14) | AO15: =IF(OR(AN15="",AM15=0),"",AN15/AM15) | AP15: =IF(OR(AN15="",AN$10="",AN$10=0),"",AN15/AN$10) | AQ15: ='Monthly P&L'!L15 -> 2648.8683 | AR15: =IF(AR$10="","",AR10-AR14) | AS15: =IF(OR(AR15="",AQ15=0),"",AR15/AQ15) | AT15: =IF(OR(AR15="",AR$10="",AR$10=0),"",AR15/AR$10) | AU15: ='Monthly P&L'!M15 -> 3263.9693 | AV15: =IF(AV$10="","",AV10-AV14) | AW15: =IF(OR(AV15="",AU15=0),"",AV15/AU15) | AX15: =IF(OR(AV15="",AV$10="",AV$10=0),"",AV15/AV$10) | AY15: ='Monthly P&L'!N15 -> 3012.9318 | AZ15: =IF(AZ$10="","",AZ10-AZ14) | BA15: =IF(OR(AZ15="",AY15=0),"",AZ15/AY15) | BB15: =IF(OR(AZ15="",AZ$10="",AZ$10=0),"",AZ15/AZ$10) | BC15: ='Monthly P&L'!O15 -> 3038.9288 | BD15: =IF(BD$10="","",BD10-BD14) | BE15: =IF(OR(BD15="",BC15=0),"",BD15/BC15) | BF15: =IF(OR(BD15="",BD$10="",BD$10=0),"",BD15/BD$10)
A16: Contribution Margin % | B16: ='Monthly P&L'!B16 -> 0.52758319 | D16: ='Monthly P&L'!C16 -> 0.57853657 | F16: =IF($F$10="","",F15/$F$10) -> 0.58046237 | H16: =IF(H$10="","",H15/H$10) -> 0.54059823 | K16: ='Monthly P&L'!D16 -> 0.59432556 | L16: =IF(L$10="","",L15/L10) -> 0.54159564 | O16: ='Monthly P&L'!E16 -> 0.56798391 | P16: =IF(P$10="","",P15/P10) -> 0.53963396 | S16: ='Monthly P&L'!F16 -> 0.52675122 | T16: =IF(T$10="","",T15/T10) | W16: ='Monthly P&L'!G16 -> 0.55831446 | X16: =IF(X$10="","",X15/X10) | AA16: ='Monthly P&L'!H16 -> 0.58344506 | AB16: =IF(AB$10="","",AB15/AB10) | AE16: ='Monthly P&L'!I16 -> 0.58918689 | AF16: =IF(AF$10="","",AF15/AF10) | AI16: ='Monthly P&L'!J16 -> 0.57254362 | AJ16: =IF(AJ$10="","",AJ15/AJ10) | AM16: ='Monthly P&L'!K16 -> 0.55882963 | AN16: =IF(AN$10="","",AN15/AN10) | AQ16: ='Monthly P&L'!L16 -> 0.56593625 | AR16: =IF(AR$10="","",AR15/AR10) | AU16: ='Monthly P&L'!M16 -> 0.60506342 | AV16: =IF(AV$10="","",AV15/AV10) | AY16: ='Monthly P&L'!N16 -> 0.59497207 | AZ16: =IF(AZ$10="","",AZ15/AZ10) | BC16: ='Monthly P&L'!O16 -> 0.61332149 | BD16: =IF(BD$10="","",BD15/BD10)
A17: FIXED COSTS
A18: Employee Cost | B18: ='Monthly P&L'!B19 -> 7510.1356 | C18: =IF(OR(B18=0,B18=""),"",D18/B18-1) -> 0.22137617 | D18: ='Monthly P&L'!C19 -> 9172.7007 | E18: =IF(D$10=0,"",D18/D$10) -> 0.15946588 | F18: =IF(H18="","",K18*(L18<>"")+O18*(P18<>"")+S18*(T18<>"")+W18*(X18<>"")+AA18*(AB18<>"")+AE18*(AF18<>"")+AI18*(AJ18<>"")+AM18*(AN18<>"")+AQ18*(AR18<>"")+AU18*(AV18<>"")+AY18*(AZ18<>"")+BC18*(BD18<>"")) -> 1528.7834 | G18: =IF(OR(F18=0,F18="",H18=""),"",H18/F18) -> 0.86221677 | H18: =IF(SUM(L18,P18,T18,X18,AB18,AF18,AJ18,AN18,AR18,AV18,AZ18,BD18)=0,"",SUM(L18,P18,T18,X18,AB18,AF18,AJ18,AN18,AR18,AV18,AZ18,BD18)) -> 1318.1427 | I18: =IF(OR(H$10="",H$10=0,H18=""),"",H18/H$10) -> 0.15142659 | J18: =IF(OR(D18=0,H18=""),"",H18/D18) -> 0.14370279 | K18: ='Monthly P&L'!D19 -> 764.39172 | L18: 658.26274 | M18: =IF(OR(L18="",K18=0),"",L18/K18) -> 0.86115891 | N18: =IF(OR(L18="",L$10="",L$10=0),"",L18/L$10) -> 0.15383994 | O18: ='Monthly P&L'!E19 -> 764.39172 | P18: 659.87997 | Q18: =IF(OR(P18="",O18=0),"",P18/O18) -> 0.86327462 | R18: =IF(OR(P18="",P$10="",P$10=0),"",P18/P$10) -> 0.14909343 | S18: ='Monthly P&L'!F19 -> 764.39172 | U18: =IF(OR(T18="",S18=0),"",T18/S18) | V18: =IF(OR(T18="",T$10="",T$10=0),"",T18/T$10) | W18: ='Monthly P&L'!G19 -> 764.39172 | Y18: =IF(OR(X18="",W18=0),"",X18/W18) | Z18: =IF(OR(X18="",X$10="",X$10=0),"",X18/X$10) | AA18: ='Monthly P&L'!H19 -> 764.39172 | AC18: =IF(OR(AB18="",AA18=0),"",AB18/AA18) | AD18: =IF(OR(AB18="",AB$10="",AB$10=0),"",AB18/AB$10) | AE18: ='Monthly P&L'!I19 -> 764.39172 | AG18: =IF(OR(AF18="",AE18=0),"",AF18/AE18) | AH18: =IF(OR(AF18="",AF$10="",AF$10=0),"",AF18/AF$10) | AI18: ='Monthly P&L'!J19 -> 764.39172 | AK18: =IF(OR(AJ18="",AI18=0),"",AJ18/AI18) | AL18: =IF(OR(AJ18="",AJ$10="",AJ$10=0),"",AJ18/AJ$10) | AM18: ='Monthly P&L'!K19 -> 764.39172 | AO18: =IF(OR(AN18="",AM18=0),"",AN18/AM18) | AP18: =IF(OR(AN18="",AN$10="",AN$10=0),"",AN18/AN$10) | AQ18: ='Monthly P&L'!L19 -> 764.39172 | AS18: =IF(OR(AR18="",AQ18=0),"",AR18/AQ18) | AT18: =IF(OR(AR18="",AR$10="",AR$10=0),"",AR18/AR$10) | AU18: ='Monthly P&L'!M19 -> 764.39172 | AW18: =IF(OR(AV18="",AU18=0),"",AV18/AU18) | AX18: =IF(OR(AV18="",AV$10="",AV$10=0),"",AV18/AV$10) | AY18: ='Monthly P&L'!N19 -> 764.39172 | BA18: =IF(OR(AZ18="",AY18=0),"",AZ18/AY18) | BB18: =IF(OR(AZ18="",AZ$10="",AZ$10=0),"",AZ18/AZ$10) | BC18: ='Monthly P&L'!O19 -> 764.39172 | BE18: =IF(OR(BD18="",BC18=0),"",BD18/BC18) | BF18: =IF(OR(BD18="",BD$10="",BD$10=0),"",BD18/BD$10)
A19: Utilities & Power | B19: ='Monthly P&L'!B20 -> 1190.744 | C19: =IF(OR(B19=0,B19=""),"",D19/B19-1) -> 0.19748659 | D19: ='Monthly P&L'!C20 -> 1425.9 | E19: =IF(D$10=0,"",D19/D$10) -> 0.024789035 | F19: =IF(H19="","",K19*(L19<>"")+O19*(P19<>"")+S19*(T19<>"")+W19*(X19<>"")+AA19*(AB19<>"")+AE19*(AF19<>"")+AI19*(AJ19<>"")+AM19*(AN19<>"")+AQ19*(AR19<>"")+AU19*(AV19<>"")+AY19*(AZ19<>"")+BC19*(BD19<>"")) -> 221.00486 | G19: =IF(OR(F19=0,F19="",H19=""),"",H19/F19) -> 0.96621736 | H19: =IF(SUM(L19,P19,T19,X19,AB19,AF19,AJ19,AN19,AR19,AV19,AZ19,BD19)=0,"",SUM(L19,P19,T19,X19,AB19,AF19,AJ19,AN19,AR19,AV19,AZ19,BD19)) -> 213.53873 | I19: =IF(OR(H$10="",H$10=0,H19=""),"",H19/H$10) -> 0.024531062 | J19: =IF(OR(D19=0,H19=""),"",H19/D19) -> 0.14975716 | K19: ='Monthly P&L'!D20 -> 106.51425 | L19: 108.91587 | M19: =IF(OR(L19="",K19=0),"",L19/K19) -> 1.0225474 | N19: =IF(OR(L19="",L$10="",L$10=0),"",L19/L$10) -> 0.02545429 | O19: ='Monthly P&L'!E20 -> 114.4906 | P19: 104.62286 | Q19: =IF(OR(P19="",O19=0),"",P19/O19) -> 0.91381177 | R19: =IF(OR(P19="",P$10="",P$10=0),"",P19/P$10) -> 0.023638512 | S19: ='Monthly P&L'!F20 -> 125.70903 | U19: =IF(OR(T19="",S19=0),"",T19/S19) | V19: =IF(OR(T19="",T$10="",T$10=0),"",T19/T$10) | W19: ='Monthly P&L'!G20 -> 117.11542 | Y19: =IF(OR(X19="",W19=0),"",X19/W19) | Z19: =IF(OR(X19="",X$10="",X$10=0),"",X19/X$10) | AA19: ='Monthly P&L'!H20 -> 108.99724 | AC19: =IF(OR(AB19="",AA19=0),"",AB19/AA19) | AD19: =IF(OR(AB19="",AB$10="",AB$10=0),"",AB19/AB$10) | AE19: ='Monthly P&L'!I20 -> 117.12588 | AG19: =IF(OR(AF19="",AE19=0),"",AF19/AE19) | AH19: =IF(OR(AF19="",AF$10="",AF$10=0),"",AF19/AF$10) | AI19: ='Monthly P&L'!J20 -> 130.7755 | AK19: =IF(OR(AJ19="",AI19=0),"",AJ19/AI19) | AL19: =IF(OR(AJ19="",AJ$10="",AJ$10=0),"",AJ19/AJ$10) | AM19: ='Monthly P&L'!K20 -> 106.15133 | AO19: =IF(OR(AN19="",AM19=0),"",AN19/AM19) | AP19: =IF(OR(AN19="",AN$10="",AN$10=0),"",AN19/AN$10) | AQ19: ='Monthly P&L'!L20 -> 118.14686 | AS19: =IF(OR(AR19="",AQ19=0),"",AR19/AQ19) | AT19: =IF(OR(AR19="",AR$10="",AR$10=0),"",AR19/AR$10) | AU19: ='Monthly P&L'!M20 -> 125.67155 | AW19: =IF(OR(AV19="",AU19=0),"",AV19/AU19) | AX19: =IF(OR(AV19="",AV$10="",AV$10=0),"",AV19/AV$10) | AY19: ='Monthly P&L'!N20 -> 109.14156 | BA19: =IF(OR(AZ19="",AY19=0),"",AZ19/AY19) | BB19: =IF(OR(AZ19="",AZ$10="",AZ$10=0),"",AZ19/AZ$10) | BC19: ='Monthly P&L'!O20 -> 146.06078 | BE19: =IF(OR(BD19="",BC19=0),"",BD19/BC19) | BF19: =IF(OR(BD19="",BD$10="",BD$10=0),"",BD19/BD$10)
A20: Lab Test Charges | B20: ='Monthly P&L'!B21 -> 267.69115 | C20: =IF(OR(B20=0,B20=""),"",D20/B20-1) -> 0.049717187 | D20: ='Monthly P&L'!C21 -> 281 | E20: =IF(D$10=0,"",D20/D$10) -> 0.0048851384 | F20: =IF(H20="","",K20*(L20<>"")+O20*(P20<>"")+S20*(T20<>"")+W20*(X20<>"")+AA20*(AB20<>"")+AE20*(AF20<>"")+AI20*(AJ20<>"")+AM20*(AN20<>"")+AQ20*(AR20<>"")+AU20*(AV20<>"")+AY20*(AZ20<>"")+BC20*(BD20<>"")) -> 37.149869 | G20: =IF(OR(F20=0,F20="",H20=""),"",H20/F20) -> 1.4429022 | H20: =IF(SUM(L20,P20,T20,X20,AB20,AF20,AJ20,AN20,AR20,AV20,AZ20,BD20)=0,"",SUM(L20,P20,T20,X20,AB20,AF20,AJ20,AN20,AR20,AV20,AZ20,BD20)) -> 53.603629 | I20: =IF(OR(H$10="",H$10=0,H20=""),"",H20/H$10) -> 0.006157918 | J20: =IF(OR(D20=0,H20=""),"",H20/D20) -> 0.19076025 | K20: ='Monthly P&L'!D21 -> 17.614643 | L20: 24.101609 | M20: =IF(OR(L20="",K20=0),"",L20/K20) -> 1.3682713 | N20: =IF(OR(L20="",L$10="",L$10=0),"",L20/L$10) -> 0.0056326903 | O20: ='Monthly P&L'!E21 -> 19.535226 | P20: 29.50202 | Q20: =IF(OR(P20="",O20=0),"",P20/O20) -> 1.510196 | R20: =IF(OR(P20="",P$10="",P$10=0),"",P20/P$10) -> 0.0066656929 | S20: ='Monthly P&L'!F21 -> 22.497812 | U20: =IF(OR(T20="",S20=0),"",T20/S20) | V20: =IF(OR(T20="",T$10="",T$10=0),"",T20/T$10) | W20: ='Monthly P&L'!G21 -> 19.284869 | Y20: =IF(OR(X20="",W20=0),"",X20/W20) | Z20: =IF(OR(X20="",X$10="",X$10=0),"",X20/X$10) | AA20: ='Monthly P&L'!H21 -> 27.862517 | AC20: =IF(OR(AB20="",AA20=0),"",AB20/AA20) | AD20: =IF(OR(AB20="",AB$10="",AB$10=0),"",AB20/AB$10) | AE20: ='Monthly P&L'!I21 -> 17.60298 | AG20: =IF(OR(AF20="",AE20=0),"",AF20/AE20) | AH20: =IF(OR(AF20="",AF$10="",AF$10=0),"",AF20/AF$10) | AI20: ='Monthly P&L'!J21 -> 23.917082 | AK20: =IF(OR(AJ20="",AI20=0),"",AJ20/AI20) | AL20: =IF(OR(AJ20="",AJ$10="",AJ$10=0),"",AJ20/AJ$10) | AM20: ='Monthly P&L'!K21 -> 9.6772168 | AO20: =IF(OR(AN20="",AM20=0),"",AN20/AM20) | AP20: =IF(OR(AN20="",AN$10="",AN$10=0),"",AN20/AN$10) | AQ20: ='Monthly P&L'!L21 -> 39.487348 | AS20: =IF(OR(AR20="",AQ20=0),"",AR20/AQ20) | AT20: =IF(OR(AR20="",AR$10="",AR$10=0),"",AR20/AR$10) | AU20: ='Monthly P&L'!M21 -> 31.569099 | AW20: =IF(OR(AV20="",AU20=0),"",AV20/AU20) | AX20: =IF(OR(AV20="",AV$10="",AV$10=0),"",AV20/AV$10) | AY20: ='Monthly P&L'!N21 -> 28.746253 | BA20: =IF(OR(AZ20="",AY20=0),"",AZ20/AY20) | BB20: =IF(OR(AZ20="",AZ$10="",AZ$10=0),"",AZ20/AZ$10) | BC20: ='Monthly P&L'!O21 -> 23.204954 | BE20: =IF(OR(BD20="",BC20=0),"",BD20/BC20) | BF20: =IF(OR(BD20="",BD$10="",BD$10=0),"",BD20/BD$10)
A21: Rent Paid | B21: ='Monthly P&L'!B22 -> 279.27305 | C21: =IF(OR(B21=0,B21=""),"",D21/B21-1) -> -0.25413497 | D21: ='Monthly P&L'!C22 -> 208.3 | E21: =IF(D$10=0,"",D21/D$10) -> 0.003621261 | F21: =IF(H21="","",K21*(L21<>"")+O21*(P21<>"")+S21*(T21<>"")+W21*(X21<>"")+AA21*(AB21<>"")+AE21*(AF21<>"")+AI21*(AJ21<>"")+AM21*(AN21<>"")+AQ21*(AR21<>"")+AU21*(AV21<>"")+AY21*(AZ21<>"")+BC21*(BD21<>"")) -> 32.305533 | G21: =IF(OR(F21=0,F21="",H21=""),"",H21/F21) -> 1.4168109 | H21: =IF(SUM(L21,P21,T21,X21,AB21,AF21,AJ21,AN21,AR21,AV21,AZ21,BD21)=0,"",SUM(L21,P21,T21,X21,AB21,AF21,AJ21,AN21,AR21,AV21,AZ21,BD21)) -> 45.77083 | I21: =IF(OR(H$10="",H$10=0,H21=""),"",H21/H$10) -> 0.0052580957 | J21: =IF(OR(D21=0,H21=""),"",H21/D21) -> 0.21973514 | K21: ='Monthly P&L'!D22 -> 16.634946 | L21: 22.68199 | M21: =IF(OR(L21="",K21=0),"",L21/K21) -> 1.3635145 | N21: =IF(OR(L21="",L$10="",L$10=0),"",L21/L$10) -> 0.0053009167 | O21: ='Monthly P&L'!E22 -> 15.670587 | P21: 23.08884 | Q21: =IF(OR(P21="",O21=0),"",P21/O21) -> 1.4733871 | R21: =IF(OR(P21="",P$10="",P$10=0),"",P21/P$10) -> 0.0052166976 | S21: ='Monthly P&L'!F22 -> 17.61895 | U21: =IF(OR(T21="",S21=0),"",T21/S21) | V21: =IF(OR(T21="",T$10="",T$10=0),"",T21/T$10) | W21: ='Monthly P&L'!G22 -> 12.414811 | Y21: =IF(OR(X21="",W21=0),"",X21/W21) | Z21: =IF(OR(X21="",X$10="",X$10=0),"",X21/X$10) | AA21: ='Monthly P&L'!H22 -> 19.683796 | AC21: =IF(OR(AB21="",AA21=0),"",AB21/AA21) | AD21: =IF(OR(AB21="",AB$10="",AB$10=0),"",AB21/AB$10) | AE21: ='Monthly P&L'!I22 -> 19.513104 | AG21: =IF(OR(AF21="",AE21=0),"",AF21/AE21) | AH21: =IF(OR(AF21="",AF$10="",AF$10=0),"",AF21/AF$10) | AI21: ='Monthly P&L'!J22 -> 15.669426 | AK21: =IF(OR(AJ21="",AI21=0),"",AJ21/AI21) | AL21: =IF(OR(AJ21="",AJ$10="",AJ$10=0),"",AJ21/AJ$10) | AM21: ='Monthly P&L'!K22 -> 15.549287 | AO21: =IF(OR(AN21="",AM21=0),"",AN21/AM21) | AP21: =IF(OR(AN21="",AN$10="",AN$10=0),"",AN21/AN$10) | AQ21: ='Monthly P&L'!L22 -> 18.107216 | AS21: =IF(OR(AR21="",AQ21=0),"",AR21/AQ21) | AT21: =IF(OR(AR21="",AR$10="",AR$10=0),"",AR21/AR$10) | AU21: ='Monthly P&L'!M22 -> 17.154054 | AW21: =IF(OR(AV21="",AU21=0),"",AV21/AU21) | AX21: =IF(OR(AV21="",AV$10="",AV$10=0),"",AV21/AV$10) | AY21: ='Monthly P&L'!N22 -> 17.050806 | BA21: =IF(OR(AZ21="",AY21=0),"",AZ21/AY21) | BB21: =IF(OR(AZ21="",AZ$10="",AZ$10=0),"",AZ21/AZ$10) | BC21: ='Monthly P&L'!O22 -> 23.233017 | BE21: =IF(OR(BD21="",BC21=0),"",BD21/BC21) | BF21: =IF(OR(BD21="",BD$10="",BD$10=0),"",BD21/BD$10)
A22: Repair & Maintenance | B22: ='Monthly P&L'!B23 -> 1559.2231 | C22: =IF(OR(B22=0,B22=""),"",D22/B22-1) -> 0.048849239 | D22: ='Monthly P&L'!C23 -> 1635.39 | E22: =IF(D$10=0,"",D22/D$10) -> 0.028430984 | F22: =IF(H22="","",K22*(L22<>"")+O22*(P22<>"")+S22*(T22<>"")+W22*(X22<>"")+AA22*(AB22<>"")+AE22*(AF22<>"")+AI22*(AJ22<>"")+AM22*(AN22<>"")+AQ22*(AR22<>"")+AU22*(AV22<>"")+AY22*(AZ22<>"")+BC22*(BD22<>"")) -> 184.52 | G22: =IF(OR(F22=0,F22="",H22=""),"",H22/F22) -> 1.051622 | H22: =IF(SUM(L22,P22,T22,X22,AB22,AF22,AJ22,AN22,AR22,AV22,AZ22,BD22)=0,"",SUM(L22,P22,T22,X22,AB22,AF22,AJ22,AN22,AR22,AV22,AZ22,BD22)) -> 194.04528 | I22: =IF(OR(H$10="",H$10=0,H22=""),"",H22/H$10) -> 0.02229168 | J22: =IF(OR(D22=0,H22=""),"",H22/D22) -> 0.11865383 | K22: ='Monthly P&L'!D23 -> 84.96 | L22: 114.68122 | M22: =IF(OR(L22="",K22=0),"",L22/K22) -> 1.349826 | N22: =IF(OR(L22="",L$10="",L$10=0),"",L22/L$10) -> 0.026801687 | O22: ='Monthly P&L'!E23 -> 99.56 | P22: 79.364062 | Q22: =IF(OR(P22="",O22=0),"",P22/O22) -> 0.79714808 | R22: =IF(OR(P22="",P$10="",P$10=0),"",P22/P$10) -> 0.017931534 | S22: ='Monthly P&L'!F23 -> 132.21 | U22: =IF(OR(T22="",S22=0),"",T22/S22) | V22: =IF(OR(T22="",T$10="",T$10=0),"",T22/T$10) | W22: ='Monthly P&L'!G23 -> 132.29 | Y22: =IF(OR(X22="",W22=0),"",X22/W22) | Z22: =IF(OR(X22="",X$10="",X$10=0),"",X22/X$10) | AA22: ='Monthly P&L'!H23 -> 143.62 | AC22: =IF(OR(AB22="",AA22=0),"",AB22/AA22) | AD22: =IF(OR(AB22="",AB$10="",AB$10=0),"",AB22/AB$10) | AE22: ='Monthly P&L'!I23 -> 158.24 | AG22: =IF(OR(AF22="",AE22=0),"",AF22/AE22) | AH22: =IF(OR(AF22="",AF$10="",AF$10=0),"",AF22/AF$10) | AI22: ='Monthly P&L'!J23 -> 163.31 | AK22: =IF(OR(AJ22="",AI22=0),"",AJ22/AI22) | AL22: =IF(OR(AJ22="",AJ$10="",AJ$10=0),"",AJ22/AJ$10) | AM22: ='Monthly P&L'!K23 -> 134.81 | AO22: =IF(OR(AN22="",AM22=0),"",AN22/AM22) | AP22: =IF(OR(AN22="",AN$10="",AN$10=0),"",AN22/AN$10) | AQ22: ='Monthly P&L'!L23 -> 109.05 | AS22: =IF(OR(AR22="",AQ22=0),"",AR22/AQ22) | AT22: =IF(OR(AR22="",AR$10="",AR$10=0),"",AR22/AR$10) | AU22: ='Monthly P&L'!M23 -> 98.93 | AW22: =IF(OR(AV22="",AU22=0),"",AV22/AU22) | AX22: =IF(OR(AV22="",AV$10="",AV$10=0),"",AV22/AV$10) | AY22: ='Monthly P&L'!N23 -> 189.56 | BA22: =IF(OR(AZ22="",AY22=0),"",AZ22/AY22) | BB22: =IF(OR(AZ22="",AZ$10="",AZ$10=0),"",AZ22/AZ$10) | BC22: ='Monthly P&L'!O23 -> 188.85 | BE22: =IF(OR(BD22="",BC22=0),"",BD22/BC22) | BF22: =IF(OR(BD22="",BD$10="",BD$10=0),"",BD22/BD$10)
A23: Housekeeping | B23: ='Monthly P&L'!B24 -> 1011.1753 | C23: =IF(OR(B23=0,B23=""),"",D23/B23-1) -> 0.17091471 | D23: ='Monthly P&L'!C24 -> 1184 | E23: =IF(D$10=0,"",D23/D$10) -> 0.020583644 | F23: =IF(H23="","",K23*(L23<>"")+O23*(P23<>"")+S23*(T23<>"")+W23*(X23<>"")+AA23*(AB23<>"")+AE23*(AF23<>"")+AI23*(AJ23<>"")+AM23*(AN23<>"")+AQ23*(AR23<>"")+AU23*(AV23<>"")+AY23*(AZ23<>"")+BC23*(BD23<>"")) -> 156.93586 | G23: =IF(OR(F23=0,F23="",H23=""),"",H23/F23) -> 1.2959928 | H23: =IF(SUM(L23,P23,T23,X23,AB23,AF23,AJ23,AN23,AR23,AV23,AZ23,BD23)=0,"",SUM(L23,P23,T23,X23,AB23,AF23,AJ23,AN23,AR23,AV23,AZ23,BD23)) -> 203.38774 | I23: =IF(OR(H$10="",H$10=0,H23=""),"",H23/H$10) -> 0.02336493 | J23: =IF(OR(D23=0,H23=""),"",H23/D23) -> 0.17178019 | K23: ='Monthly P&L'!D24 -> 72.842371 | L23: 89.327925 | M23: =IF(OR(L23="",K23=0),"",L23/K23) -> 1.2263182 | N23: =IF(OR(L23="",L$10="",L$10=0),"",L23/L$10) -> 0.02087647 | O23: ='Monthly P&L'!E24 -> 84.093491 | P23: 114.05982 | Q23: =IF(OR(P23="",O23=0),"",P23/O23) -> 1.3563454 | R23: =IF(OR(P23="",P$10="",P$10=0),"",P23/P$10) -> 0.025770701 | S23: ='Monthly P&L'!F24 -> 101.11201 | U23: =IF(OR(T23="",S23=0),"",T23/S23) | V23: =IF(OR(T23="",T$10="",T$10=0),"",T23/T$10) | W23: ='Monthly P&L'!G24 -> 87.15006 | Y23: =IF(OR(X23="",W23=0),"",X23/W23) | Z23: =IF(OR(X23="",X$10="",X$10=0),"",X23/X$10) | AA23: ='Monthly P&L'!H24 -> 79.411635 | AC23: =IF(OR(AB23="",AA23=0),"",AB23/AA23) | AD23: =IF(OR(AB23="",AB$10="",AB$10=0),"",AB23/AB$10) | AE23: ='Monthly P&L'!I24 -> 87.829971 | AG23: =IF(OR(AF23="",AE23=0),"",AF23/AE23) | AH23: =IF(OR(AF23="",AF$10="",AF$10=0),"",AF23/AF$10) | AI23: ='Monthly P&L'!J24 -> 103.13467 | AK23: =IF(OR(AJ23="",AI23=0),"",AJ23/AI23) | AL23: =IF(OR(AJ23="",AJ$10="",AJ$10=0),"",AJ23/AJ$10) | AM23: ='Monthly P&L'!K24 -> 74.265622 | AO23: =IF(OR(AN23="",AM23=0),"",AN23/AM23) | AP23: =IF(OR(AN23="",AN$10="",AN$10=0),"",AN23/AN$10) | AQ23: ='Monthly P&L'!L24 -> 79.782965 | AS23: =IF(OR(AR23="",AQ23=0),"",AR23/AQ23) | AT23: =IF(OR(AR23="",AR$10="",AR$10=0),"",AR23/AR$10) | AU23: ='Monthly P&L'!M24 -> 57.876277 | AW23: =IF(OR(AV23="",AU23=0),"",AV23/AU23) | AX23: =IF(OR(AV23="",AV$10="",AV$10=0),"",AV23/AV$10) | AY23: ='Monthly P&L'!N24 -> 141.54075 | BA23: =IF(OR(AZ23="",AY23=0),"",AZ23/AY23) | BB23: =IF(OR(AZ23="",AZ$10="",AZ$10=0),"",AZ23/AZ$10) | BC23: ='Monthly P&L'!O24 -> 214.96018 | BE23: =IF(OR(BD23="",BC23=0),"",BD23/BC23) | BF23: =IF(OR(BD23="",BD$10="",BD$10=0),"",BD23/BD$10)
A24: Security | B24: ='Monthly P&L'!B25 -> 265.1163 | C24: =IF(OR(B24=0,B24=""),"",D24/B24-1) -> 0.3914648 | D24: ='Monthly P&L'!C25 -> 368.9 | E24: =IF(D$10=0,"",D24/D$10) -> 0.0064132653 | F24: =IF(H24="","",K24*(L24<>"")+O24*(P24<>"")+S24*(T24<>"")+W24*(X24<>"")+AA24*(AB24<>"")+AE24*(AF24<>"")+AI24*(AJ24<>"")+AM24*(AN24<>"")+AQ24*(AR24<>"")+AU24*(AV24<>"")+AY24*(AZ24<>"")+BC24*(BD24<>"")) -> 61.772591 | G24: =IF(OR(F24=0,F24="",H24=""),"",H24/F24) -> 0.6942119 | H24: =IF(SUM(L24,P24,T24,X24,AB24,AF24,AJ24,AN24,AR24,AV24,AZ24,BD24)=0,"",SUM(L24,P24,T24,X24,AB24,AF24,AJ24,AN24,AR24,AV24,AZ24,BD24)) -> 42.883268 | I24: =IF(OR(H$10="",H$10=0,H24=""),"",H24/H$10) -> 0.0049263762 | J24: =IF(OR(D24=0,H24=""),"",H24/D24) -> 0.11624632 | K24: ='Monthly P&L'!D25 -> 28.914527 | L24: 24.095348 | M24: =IF(OR(L24="",K24=0),"",L24/K24) -> 0.83333016 | N24: =IF(OR(L24="",L$10="",L$10=0),"",L24/L$10) -> 0.0056312269 | O24: ='Monthly P&L'!E25 -> 32.858064 | P24: 18.78792 | Q24: =IF(OR(P24="",O24=0),"",P24/O24) -> 0.57179024 | R24: =IF(OR(P24="",P$10="",P$10=0),"",P24/P$10) -> 0.0042449468 | S24: ='Monthly P&L'!F25 -> 32.858064 | U24: =IF(OR(T24="",S24=0),"",T24/S24) | V24: =IF(OR(T24="",T$10="",T$10=0),"",T24/T$10) | W24: ='Monthly P&L'!G25 -> 32.454901 | Y24: =IF(OR(X24="",W24=0),"",X24/W24) | Z24: =IF(OR(X24="",X$10="",X$10=0),"",X24/X$10) | AA24: ='Monthly P&L'!H25 -> 27.57367 | AC24: =IF(OR(AB24="",AA24=0),"",AB24/AA24) | AD24: =IF(OR(AB24="",AB$10="",AB$10=0),"",AB24/AB$10) | AE24: ='Monthly P&L'!I25 -> 26.491382 | AG24: =IF(OR(AF24="",AE24=0),"",AF24/AE24) | AH24: =IF(OR(AF24="",AF$10="",AF$10=0),"",AF24/AF$10) | AI24: ='Monthly P&L'!J25 -> 35.5005 | AK24: =IF(OR(AJ24="",AI24=0),"",AJ24/AI24) | AL24: =IF(OR(AJ24="",AJ$10="",AJ$10=0),"",AJ24/AJ$10) | AM24: ='Monthly P&L'!K25 -> 29.279706 | AO24: =IF(OR(AN24="",AM24=0),"",AN24/AM24) | AP24: =IF(OR(AN24="",AN$10="",AN$10=0),"",AN24/AN$10) | AQ24: ='Monthly P&L'!L25 -> 29.746206 | AS24: =IF(OR(AR24="",AQ24=0),"",AR24/AQ24) | AT24: =IF(OR(AR24="",AR$10="",AR$10=0),"",AR24/AR$10) | AU24: ='Monthly P&L'!M25 -> 31.465653 | AW24: =IF(OR(AV24="",AU24=0),"",AV24/AU24) | AX24: =IF(OR(AV24="",AV$10="",AV$10=0),"",AV24/AV$10) | AY24: ='Monthly P&L'!N25 -> 29.391243 | BA24: =IF(OR(AZ24="",AY24=0),"",AZ24/AY24) | BB24: =IF(OR(AZ24="",AZ$10="",AZ$10=0),"",AZ24/AZ$10) | BC24: ='Monthly P&L'!O25 -> 32.366085 | BE24: =IF(OR(BD24="",BC24=0),"",BD24/BC24) | BF24: =IF(OR(BD24="",BD$10="",BD$10=0),"",BD24/BD$10)
A25: Printing & Stationery | B25: ='Monthly P&L'!B26 -> 182.70992 | C25: =IF(OR(B25=0,B25=""),"",D25/B25-1) -> -0.089814056 | D25: ='Monthly P&L'!C26 -> 166.3 | E25: =IF(D$10=0,"",D25/D$10) -> 0.0028910979 | F25: =IF(H25="","",K25*(L25<>"")+O25*(P25<>"")+S25*(T25<>"")+W25*(X25<>"")+AA25*(AB25<>"")+AE25*(AF25<>"")+AI25*(AJ25<>"")+AM25*(AN25<>"")+AQ25*(AR25<>"")+AU25*(AV25<>"")+AY25*(AZ25<>"")+BC25*(BD25<>"")) -> 26.211723 | G25: =IF(OR(F25=0,F25="",H25=""),"",H25/F25) -> 1.407712 | H25: =IF(SUM(L25,P25,T25,X25,AB25,AF25,AJ25,AN25,AR25,AV25,AZ25,BD25)=0,"",SUM(L25,P25,T25,X25,AB25,AF25,AJ25,AN25,AR25,AV25,AZ25,BD25)) -> 36.898556 | I25: =IF(OR(H$10="",H$10=0,H25=""),"",H25/H$10) -> 0.0042388601 | J25: =IF(OR(D25=0,H25=""),"",H25/D25) -> 0.22187947 | K25: ='Monthly P&L'!D26 -> 10.388101 | L25: 18.924059 | M25: =IF(OR(L25="",K25=0),"",L25/K25) -> 1.8217054 | N25: =IF(OR(L25="",L$10="",L$10=0),"",L25/L$10) -> 0.0044226659 | O25: ='Monthly P&L'!E26 -> 15.823622 | P25: 17.974497 | Q25: =IF(OR(P25="",O25=0),"",P25/O25) -> 1.1359281 | R25: =IF(OR(P25="",P$10="",P$10=0),"",P25/P$10) -> 0.0040611618 | S25: ='Monthly P&L'!F26 -> 12.298557 | U25: =IF(OR(T25="",S25=0),"",T25/S25) | V25: =IF(OR(T25="",T$10="",T$10=0),"",T25/T$10) | W25: ='Monthly P&L'!G26 -> 15.191548 | Y25: =IF(OR(X25="",W25=0),"",X25/W25) | Z25: =IF(OR(X25="",X$10="",X$10=0),"",X25/X$10) | AA25: ='Monthly P&L'!H26 -> 12.674734 | AC25: =IF(OR(AB25="",AA25=0),"",AB25/AA25) | AD25: =IF(OR(AB25="",AB$10="",AB$10=0),"",AB25/AB$10) | AE25: ='Monthly P&L'!I26 -> 13.101131 | AG25: =IF(OR(AF25="",AE25=0),"",AF25/AE25) | AH25: =IF(OR(AF25="",AF$10="",AF$10=0),"",AF25/AF$10) | AI25: ='Monthly P&L'!J26 -> 16.453661 | AK25: =IF(OR(AJ25="",AI25=0),"",AJ25/AI25) | AL25: =IF(OR(AJ25="",AJ$10="",AJ$10=0),"",AJ25/AJ$10) | AM25: ='Monthly P&L'!K26 -> 10.592546 | AO25: =IF(OR(AN25="",AM25=0),"",AN25/AM25) | AP25: =IF(OR(AN25="",AN$10="",AN$10=0),"",AN25/AN$10) | AQ25: ='Monthly P&L'!L26 -> 12.725547 | AS25: =IF(OR(AR25="",AQ25=0),"",AR25/AQ25) | AT25: =IF(OR(AR25="",AR$10="",AR$10=0),"",AR25/AR$10) | AU25: ='Monthly P&L'!M26 -> 12.94168 | AW25: =IF(OR(AV25="",AU25=0),"",AV25/AU25) | AX25: =IF(OR(AV25="",AV$10="",AV$10=0),"",AV25/AV$10) | AY25: ='Monthly P&L'!N26 -> 16.412919 | BA25: =IF(OR(AZ25="",AY25=0),"",AZ25/AY25) | BB25: =IF(OR(AZ25="",AZ$10="",AZ$10=0),"",AZ25/AZ$10) | BC25: ='Monthly P&L'!O26 -> 17.695954 | BE25: =IF(OR(BD25="",BC25=0),"",BD25/BC25) | BF25: =IF(OR(BD25="",BD$10="",BD$10=0),"",BD25/BD$10)
A26: Insurance | B26: ='Monthly P&L'!B27 -> 31.991355 | C26: =IF(OR(B26=0,B26=""),"",D26/B26-1) -> 0.12217815 | D26: ='Monthly P&L'!C27 -> 35.9 | E26: =IF(D$10=0,"",D26/D$10) -> 0.00062411555 | F26: =IF(H26="","",K26*(L26<>"")+O26*(P26<>"")+S26*(T26<>"")+W26*(X26<>"")+AA26*(AB26<>"")+AE26*(AF26<>"")+AI26*(AJ26<>"")+AM26*(AN26<>"")+AQ26*(AR26<>"")+AU26*(AV26<>"")+AY26*(AZ26<>"")+BC26*(BD26<>"")) -> 5.2335674 | G26: =IF(OR(F26=0,F26="",H26=""),"",H26/F26) -> 1.2084354 | H26: =IF(SUM(L26,P26,T26,X26,AB26,AF26,AJ26,AN26,AR26,AV26,AZ26,BD26)=0,"",SUM(L26,P26,T26,X26,AB26,AF26,AJ26,AN26,AR26,AV26,AZ26,BD26)) -> 6.3244283 | I26: =IF(OR(H$10="",H$10=0,H26=""),"",H26/H$10) -> 0.00072654242 | J26: =IF(OR(D26=0,H26=""),"",H26/D26) -> 0.17616792 | K26: ='Monthly P&L'!D27 -> 2.5586521 | L26: 3.0348463 | M26: =IF(OR(L26="",K26=0),"",L26/K26) -> 1.1861113 | N26: =IF(OR(L26="",L$10="",L$10=0),"",L26/L$10) -> 0.00070926175 | O26: ='Monthly P&L'!E27 -> 2.6749153 | P26: 3.289582 | Q26: =IF(OR(P26="",O26=0),"",P26/O26) -> 1.2297892 | R26: =IF(OR(P26="",P$10="",P$10=0),"",P26/P$10) -> 0.00074324889 | S26: ='Monthly P&L'!F27 -> 2.1797664 | U26: =IF(OR(T26="",S26=0),"",T26/S26) | V26: =IF(OR(T26="",T$10="",T$10=0),"",T26/T$10) | W26: ='Monthly P&L'!G27 -> 2.069981 | Y26: =IF(OR(X26="",W26=0),"",X26/W26) | Z26: =IF(OR(X26="",X$10="",X$10=0),"",X26/X$10) | AA26: ='Monthly P&L'!H27 -> 2.9522487 | AC26: =IF(OR(AB26="",AA26=0),"",AB26/AA26) | AD26: =IF(OR(AB26="",AB$10="",AB$10=0),"",AB26/AB$10) | AE26: ='Monthly P&L'!I27 -> 3.8088144 | AG26: =IF(OR(AF26="",AE26=0),"",AF26/AE26) | AH26: =IF(OR(AF26="",AF$10="",AF$10=0),"",AF26/AF$10) | AI26: ='Monthly P&L'!J27 -> 3.0101004 | AK26: =IF(OR(AJ26="",AI26=0),"",AJ26/AI26) | AL26: =IF(OR(AJ26="",AJ$10="",AJ$10=0),"",AJ26/AJ$10) | AM26: ='Monthly P&L'!K27 -> 3.2638714 | AO26: =IF(OR(AN26="",AM26=0),"",AN26/AM26) | AP26: =IF(OR(AN26="",AN$10="",AN$10=0),"",AN26/AN$10) | AQ26: ='Monthly P&L'!L27 -> 3.5089919 | AS26: =IF(OR(AR26="",AQ26=0),"",AR26/AQ26) | AT26: =IF(OR(AR26="",AR$10="",AR$10=0),"",AR26/AR$10) | AU26: ='Monthly P&L'!M27 -> 3.0436151 | AW26: =IF(OR(AV26="",AU26=0),"",AV26/AU26) | AX26: =IF(OR(AV26="",AV$10="",AV$10=0),"",AV26/AV$10) | AY26: ='Monthly P&L'!N27 -> 3.242325 | BA26: =IF(OR(AZ26="",AY26=0),"",AZ26/AY26) | BB26: =IF(OR(AZ26="",AZ$10="",AZ$10=0),"",AZ26/AZ$10) | BC26: ='Monthly P&L'!O27 -> 3.5867181 | BE26: =IF(OR(BD26="",BC26=0),"",BD26/BC26) | BF26: =IF(OR(BD26="",BD$10="",BD$10=0),"",BD26/BD$10)
A27: Rates & Taxes | B27: ='Monthly P&L'!B28 -> 58.321304 | C27: =IF(OR(B27=0,B27=""),"",D27/B27-1) -> 0.12308875 | D27: ='Monthly P&L'!C28 -> 65.5 | E27: =IF(D$10=0,"",D27/D$10) -> 0.0011387066 | F27: =IF(H27="","",K27*(L27<>"")+O27*(P27<>"")+S27*(T27<>"")+W27*(X27<>"")+AA27*(AB27<>"")+AE27*(AF27<>"")+AI27*(AJ27<>"")+AM27*(AN27<>"")+AQ27*(AR27<>"")+AU27*(AV27<>"")+AY27*(AZ27<>"")+BC27*(BD27<>"")) -> 10.442583 | G27: =IF(OR(F27=0,F27="",H27=""),"",H27/F27) -> 0.2529366 | H27: =IF(SUM(L27,P27,T27,X27,AB27,AF27,AJ27,AN27,AR27,AV27,AZ27,BD27)=0,"",SUM(L27,P27,T27,X27,AB27,AF27,AJ27,AN27,AR27,AV27,AZ27,BD27)) -> 2.6413113 | I27: =IF(OR(H$10="",H$10=0,H27=""),"",H27/H$10) -> 0.00030343055 | J27: =IF(OR(D27=0,H27=""),"",H27/D27) -> 0.040325364 | K27: ='Monthly P&L'!D28 -> 3.8349731 | L27: 1.311025 | M27: =IF(OR(L27="",K27=0),"",L27/K27) -> 0.3418603 | N27: =IF(OR(L27="",L$10="",L$10=0),"",L27/L$10) -> 0.00030639439 | O27: ='Monthly P&L'!E28 -> 6.6076095 | P27: 1.3302863 | Q27: =IF(OR(P27="",O27=0),"",P27/O27) -> 0.20132641 | R27: =IF(OR(P27="",P$10="",P$10=0),"",P27/P$10) -> 0.00030056518 | S27: ='Monthly P&L'!F28 -> 4.9727993 | U27: =IF(OR(T27="",S27=0),"",T27/S27) | V27: =IF(OR(T27="",T$10="",T$10=0),"",T27/T$10) | W27: ='Monthly P&L'!G28 -> 6.8288177 | Y27: =IF(OR(X27="",W27=0),"",X27/W27) | Z27: =IF(OR(X27="",X$10="",X$10=0),"",X27/X$10) | AA27: ='Monthly P&L'!H28 -> 3.3504462 | AC27: =IF(OR(AB27="",AA27=0),"",AB27/AA27) | AD27: =IF(OR(AB27="",AB$10="",AB$10=0),"",AB27/AB$10) | AE27: ='Monthly P&L'!I28 -> 1.8130073 | AG27: =IF(OR(AF27="",AE27=0),"",AF27/AE27) | AH27: =IF(OR(AF27="",AF$10="",AF$10=0),"",AF27/AF$10) | AI27: ='Monthly P&L'!J28 -> 10.612213 | AK27: =IF(OR(AJ27="",AI27=0),"",AJ27/AI27) | AL27: =IF(OR(AJ27="",AJ$10="",AJ$10=0),"",AJ27/AJ$10) | AM27: ='Monthly P&L'!K28 -> 1.8985126 | AO27: =IF(OR(AN27="",AM27=0),"",AN27/AM27) | AP27: =IF(OR(AN27="",AN$10="",AN$10=0),"",AN27/AN$10) | AQ27: ='Monthly P&L'!L28 -> 2.4640354 | AS27: =IF(OR(AR27="",AQ27=0),"",AR27/AQ27) | AT27: =IF(OR(AR27="",AR$10="",AR$10=0),"",AR27/AR$10) | AU27: ='Monthly P&L'!M28 -> 5.0194067 | AW27: =IF(OR(AV27="",AU27=0),"",AV27/AU27) | AX27: =IF(OR(AV27="",AV$10="",AV$10=0),"",AV27/AV$10) | AY27: ='Monthly P&L'!N28 -> 2.9702682 | BA27: =IF(OR(AZ27="",AY27=0),"",AZ27/AY27) | BB27: =IF(OR(AZ27="",AZ$10="",AZ$10=0),"",AZ27/AZ$10) | BC27: ='Monthly P&L'!O28 -> 15.127911 | BE27: =IF(OR(BD27="",BC27=0),"",BD27/BC27) | BF27: =IF(OR(BD27="",BD$10="",BD$10=0),"",BD27/BD$10)
A28: Professional Fee | B28: ='Monthly P&L'!B29 -> 201.10741 | C28: =IF(OR(B28=0,B28=""),"",D28/B28-1) -> 2.9779737 | D28: ='Monthly P&L'!C29 -> 800 | E28: =IF(D$10=0,"",D28/D$10) -> 0.013907867 | F28: =IF(H28="","",K28*(L28<>"")+O28*(P28<>"")+S28*(T28<>"")+W28*(X28<>"")+AA28*(AB28<>"")+AE28*(AF28<>"")+AI28*(AJ28<>"")+AM28*(AN28<>"")+AQ28*(AR28<>"")+AU28*(AV28<>"")+AY28*(AZ28<>"")+BC28*(BD28<>"")) -> 145.58 | G28: =IF(OR(F28=0,F28="",H28=""),"",H28/F28) -> 0.19800061 | H28: =IF(SUM(L28,P28,T28,X28,AB28,AF28,AJ28,AN28,AR28,AV28,AZ28,BD28)=0,"",SUM(L28,P28,T28,X28,AB28,AF28,AJ28,AN28,AR28,AV28,AZ28,BD28)) -> 28.824928 | I28: =IF(OR(H$10="",H$10=0,H28=""),"",H28/H$10) -> 0.0033113717 | J28: =IF(OR(D28=0,H28=""),"",H28/D28) -> 0.03603116 | K28: ='Monthly P&L'!D29 -> 69.46 | L28: 14.323616 | M28: =IF(OR(L28="",K28=0),"",L28/K28) -> 0.20621387 | N28: =IF(OR(L28="",L$10="",L$10=0),"",L28/L$10) -> 0.0033475146 | O28: ='Monthly P&L'!E29 -> 76.12 | P28: 14.501313 | Q28: =IF(OR(P28="",O28=0),"",P28/O28) -> 0.19050595 | R28: =IF(OR(P28="",P$10="",P$10=0),"",P28/P$10) -> 0.0032764298 | S28: ='Monthly P&L'!F29 -> 70.61 | U28: =IF(OR(T28="",S28=0),"",T28/S28) | V28: =IF(OR(T28="",T$10="",T$10=0),"",T28/T$10) | W28: ='Monthly P&L'!G29 -> 79.24 | Y28: =IF(OR(X28="",W28=0),"",X28/W28) | Z28: =IF(OR(X28="",X$10="",X$10=0),"",X28/X$10) | AA28: ='Monthly P&L'!H29 -> 62.89 | AC28: =IF(OR(AB28="",AA28=0),"",AB28/AA28) | AD28: =IF(OR(AB28="",AB$10="",AB$10=0),"",AB28/AB$10) | AE28: ='Monthly P&L'!I29 -> 61.45 | AG28: =IF(OR(AF28="",AE28=0),"",AF28/AE28) | AH28: =IF(OR(AF28="",AF$10="",AF$10=0),"",AF28/AF$10) | AI28: ='Monthly P&L'!J29 -> 56.15 | AK28: =IF(OR(AJ28="",AI28=0),"",AJ28/AI28) | AL28: =IF(OR(AJ28="",AJ$10="",AJ$10=0),"",AJ28/AJ$10) | AM28: ='Monthly P&L'!K29 -> 56.78 | AO28: =IF(OR(AN28="",AM28=0),"",AN28/AM28) | AP28: =IF(OR(AN28="",AN$10="",AN$10=0),"",AN28/AN$10) | AQ28: ='Monthly P&L'!L29 -> 49.93 | AS28: =IF(OR(AR28="",AQ28=0),"",AR28/AQ28) | AT28: =IF(OR(AR28="",AR$10="",AR$10=0),"",AR28/AR$10) | AU28: ='Monthly P&L'!M29 -> 59.1 | AW28: =IF(OR(AV28="",AU28=0),"",AV28/AU28) | AX28: =IF(OR(AV28="",AV$10="",AV$10=0),"",AV28/AV$10) | AY28: ='Monthly P&L'!N29 -> 72.08 | BA28: =IF(OR(AZ28="",AY28=0),"",AZ28/AY28) | BB28: =IF(OR(AZ28="",AZ$10="",AZ$10=0),"",AZ28/AZ$10) | BC28: ='Monthly P&L'!O29 -> 86.19 | BE28: =IF(OR(BD28="",BC28=0),"",BD28/BC28) | BF28: =IF(OR(BD28="",BD$10="",BD$10=0),"",BD28/BD$10)
A29: Quality & Infection | B29: ='Monthly P&L'!B30 -> 5.675688 | C29: =IF(OR(B29=0,B29=""),"",D29/B29-1) -> 0.10999759 | D29: ='Monthly P&L'!C30 -> 6.3 | E29: =IF(D$10=0,"",D29/D$10) -> 0.00010952446 | F29: =IF(H29="","",K29*(L29<>"")+O29*(P29<>"")+S29*(T29<>"")+W29*(X29<>"")+AA29*(AB29<>"")+AE29*(AF29<>"")+AI29*(AJ29<>"")+AM29*(AN29<>"")+AQ29*(AR29<>"")+AU29*(AV29<>"")+AY29*(AZ29<>"")+BC29*(BD29<>"")) | G29: =IF(OR(F29=0,F29="",H29=""),"",H29/F29) | H29: =IF(SUM(L29,P29,T29,X29,AB29,AF29,AJ29,AN29,AR29,AV29,AZ29,BD29)=0,"",SUM(L29,P29,T29,X29,AB29,AF29,AJ29,AN29,AR29,AV29,AZ29,BD29)) | I29: =IF(OR(H$10="",H$10=0,H29=""),"",H29/H$10) | J29: =IF(OR(D29=0,H29=""),"",H29/D29) | K29: ='Monthly P&L'!D30 -> 0 | L29: 0 | M29: =IF(OR(L29="",K29=0),"",L29/K29) | N29: =IF(OR(L29="",L$10="",L$10=0),"",L29/L$10) -> 0 | O29: ='Monthly P&L'!E30 -> 0 | P29: 0 | Q29: =IF(OR(P29="",O29=0),"",P29/O29) | R29: =IF(OR(P29="",P$10="",P$10=0),"",P29/P$10) -> 0 | S29: ='Monthly P&L'!F30 -> 0 | U29: =IF(OR(T29="",S29=0),"",T29/S29) | V29: =IF(OR(T29="",T$10="",T$10=0),"",T29/T$10) | W29: ='Monthly P&L'!G30 -> 0 | Y29: =IF(OR(X29="",W29=0),"",X29/W29) | Z29: =IF(OR(X29="",X$10="",X$10=0),"",X29/X$10) | AA29: ='Monthly P&L'!H30 -> 0 | AC29: =IF(OR(AB29="",AA29=0),"",AB29/AA29) | AD29: =IF(OR(AB29="",AB$10="",AB$10=0),"",AB29/AB$10) | AE29: ='Monthly P&L'!I30 -> 3.5221196 | AG29: =IF(OR(AF29="",AE29=0),"",AF29/AE29) | AH29: =IF(OR(AF29="",AF$10="",AF$10=0),"",AF29/AF$10) | AI29: ='Monthly P&L'!J30 -> 0 | AK29: =IF(OR(AJ29="",AI29=0),"",AJ29/AI29) | AL29: =IF(OR(AJ29="",AJ$10="",AJ$10=0),"",AJ29/AJ$10) | AM29: ='Monthly P&L'!K30 -> 2.1438989 | AO29: =IF(OR(AN29="",AM29=0),"",AN29/AM29) | AP29: =IF(OR(AN29="",AN$10="",AN$10=0),"",AN29/AN$10) | AQ29: ='Monthly P&L'!L30 -> 0 | AS29: =IF(OR(AR29="",AQ29=0),"",AR29/AQ29) | AT29: =IF(OR(AR29="",AR$10="",AR$10=0),"",AR29/AR$10) | AU29: ='Monthly P&L'!M30 -> 0 | AW29: =IF(OR(AV29="",AU29=0),"",AV29/AU29) | AX29: =IF(OR(AV29="",AV$10="",AV$10=0),"",AV29/AV$10) | AY29: ='Monthly P&L'!N30 -> 0 | BA29: =IF(OR(AZ29="",AY29=0),"",AZ29/AY29) | BB29: =IF(OR(AZ29="",AZ$10="",AZ$10=0),"",AZ29/AZ$10) | BC29: ='Monthly P&L'!O30 -> 0.63398153 | BE29: =IF(OR(BD29="",BC29=0),"",BD29/BC29) | BF29: =IF(OR(BD29="",BD$10="",BD$10=0),"",BD29/BD$10)
... A35: CSR | B35: ='Monthly P&L'!B36 -> 147.22187 | C35: =IF(OR(B35=0,B35=""),"",D35/B35-1) -> -0.13192245 | D35: ='Monthly P&L'!C36 -> 127.8 | E35: =IF(D$10=0,"",D35/D$10) -> 0.0022217818 | F35: =IF(H35="","",K35*(L35<>"")+O35*(P35<>"")+S35*(T35<>"")+W35*(X35<>"")+AA35*(AB35<>"")+AE35*(AF35<>"")+AI35*(AJ35<>"")+AM35*(AN35<>"")+AQ35*(AR35<>"")+AU35*(AV35<>"")+AY35*(AZ35<>"")+BC35*(BD35<>"")) -> 13.926704 | G35: =IF(OR(F35=0,F35="",H35=""),"",H35/F35) -> 2.1543983 | H35: =IF(SUM(L35,P35,T35,X35,AB35,AF35,AJ35,AN35,AR35,AV35,AZ35,BD35)=0,"",SUM(L35,P35,T35,X35,AB35,AF35,AJ35,AN35,AR35,AV35,AZ35,BD35)) -> 30.003668 | I35: =IF(OR(H$10="",H$10=0,H35=""),"",H35/H$10) -> 0.0034467839 | J35: =IF(OR(D35=0,H35=""),"",H35/D35) -> 0.23477049 | K35: ='Monthly P&L'!D36 -> 6.6176445 | L35: 15.003668 | M35: =IF(OR(L35="",K35=0),"",L35/K35) -> 2.2672218 | N35: =IF(OR(L35="",L$10="",L$10=0),"",L35/L$10) -> 0.003506447 | O35: ='Monthly P&L'!E36 -> 7.3090596 | P35: 15 | Q35: =IF(OR(P35="",O35=0),"",P35/O35) -> 2.0522476 | R35: =IF(OR(P35="",P$10="",P$10=0),"",P35/P$10) -> 0.0033891033 | S35: ='Monthly P&L'!F36 -> 9.1856176 | U35: =IF(OR(T35="",S35=0),"",T35/S35) | V35: =IF(OR(T35="",T$10="",T$10=0),"",T35/T$10) | W35: ='Monthly P&L'!G36 -> 8.7444345 | Y35: =IF(OR(X35="",W35=0),"",X35/W35) | Z35: =IF(OR(X35="",X$10="",X$10=0),"",X35/X$10) | AA35: ='Monthly P&L'!H36 -> 7.6984011 | AC35: =IF(OR(AB35="",AA35=0),"",AB35/AA35) | AD35: =IF(OR(AB35="",AB$10="",AB$10=0),"",AB35/AB$10) | AE35: ='Monthly P&L'!I36 -> 8.8291242 | AG35: =IF(OR(AF35="",AE35=0),"",AF35/AE35) | AH35: =IF(OR(AF35="",AF$10="",AF$10=0),"",AF35/AF$10) | AI35: ='Monthly P&L'!J36 -> 7.8339427 | AK35: =IF(OR(AJ35="",AI35=0),"",AJ35/AI35) | AL35: =IF(OR(AJ35="",AJ$10="",AJ$10=0),"",AJ35/AJ$10) | AM35: ='Monthly P&L'!K36 -> 6.6176445 | AO35: =IF(OR(AN35="",AM35=0),"",AN35/AM35) | AP35: =IF(OR(AN35="",AN$10="",AN$10=0),"",AN35/AN$10) | AQ35: ='Monthly P&L'!L36 -> 26.210858 | AS35: =IF(OR(AR35="",AQ35=0),"",AR35/AQ35) | AT35: =IF(OR(AR35="",AR$10="",AR$10=0),"",AR35/AR$10) | AU35: ='Monthly P&L'!M36 -> 6.6176445 | AW35: =IF(OR(AV35="",AU35=0),"",AV35/AU35) | AX35: =IF(OR(AV35="",AV$10="",AV$10=0),"",AV35/AV$10) | AY35: ='Monthly P&L'!N36 -> 8.3537996 | BA35: =IF(OR(AZ35="",AY35=0),"",AZ35/AY35) | BB35: =IF(OR(AZ35="",AZ$10="",AZ$10=0),"",AZ35/AZ$10) | BC35: ='Monthly P&L'!O36 -> 23.781829 | BE35: =IF(OR(BD35="",BC35=0),"",BD35/BC35) | BF35: =IF(OR(BD35="",BD$10="",BD$10=0),"",BD35/BD$10)
A36: Total Fixed Cost | B36: ='Monthly P&L'!B37 -> 14151.028 | C36: =IF(OR(B36=0,B36=""),"",D36/B36-1) -> 0.30720469 | D36: ='Monthly P&L'!C37 -> 18498.291 | E36: =IF(D$10=0,"",D36/D$10) -> 0.32158972 | F36: =IF(H36="","",K36*(L36<>"")+O36*(P36<>"")+S36*(T36<>"")+W36*(X36<>"")+AA36*(AB36<>"")+AE36*(AF36<>"")+AI36*(AJ36<>"")+AM36*(AN36<>"")+AQ36*(AR36<>"")+AU36*(AV36<>"")+AY36*(AZ36<>"")+BC36*(BD36<>"")) -> 2873.2491 | G36: =IF(OR(F36=0,F36="",H36=""),"",H36/F36) -> 0.82300815 | H36: =IF(SUM(L36,P36,T36,X36,AB36,AF36,AJ36,AN36,AR36,AV36,AZ36,BD36)=0,"",SUM(L36,P36,T36,X36,AB36,AF36,AJ36,AN36,AR36,AV36,AZ36,BD36)) -> 2364.7074 | I36: =IF(OR(H$10="",H$10=0,H36=""),"",H36/H$10) -> 0.27165463 | J36: =IF(OR(D36=0,H36=""),"",H36/D36) -> 0.12783383 | K36: ='Monthly P&L'!D37 -> 1421.1935 | L36: =IF(L$10="","",SUM(L18:L35)) -> 1207.1934 | M36: =IF(OR(L36="",K36=0),"",L36/K36) -> 0.84942227 | N36: =IF(OR(L36="",L$10="",L$10=0),"",L36/L$10) -> 0.28212832 | O36: ='Monthly P&L'!E37 -> 1452.0556 | P36: =IF(P$10="","",SUM(P18:P35)) -> 1157.514 | Q36: =IF(OR(P36="",O36=0),"",P36/O36) -> 0.79715545 | R36: =IF(OR(P36="",P$10="",P$10=0),"",P36/P$10) -> 0.26152897 | S36: ='Monthly P&L'!F37 -> 1502.0205 | T36: =IF(T$10="","",SUM(T18:T35)) | U36: =IF(OR(T36="",S36=0),"",T36/S36) | V36: =IF(OR(T36="",T$10="",T$10=0),"",T36/T$10) | W36: ='Monthly P&L'!G37 -> 1491.9882 | X36: =IF(X$10="","",SUM(X18:X35)) | Y36: =IF(OR(X36="",W36=0),"",X36/W36) | Z36: =IF(OR(X36="",X$10="",X$10=0),"",X36/X$10) | AA36: ='Monthly P&L'!H37 -> 1514.0599 | AB36: =IF(AB$10="","",SUM(AB18:AB35)) | AC36: =IF(OR(AB36="",AA36=0),"",AB36/AA36) | AD36: =IF(OR(AB36="",AB$10="",AB$10=0),"",AB36/AB$10) | AE36: ='Monthly P&L'!I37 -> 1554.9948 | AF36: =IF(AF$10="","",SUM(AF18:AF35)) | AG36: =IF(OR(AF36="",AE36=0),"",AF36/AE36) | AH36: =IF(OR(AF36="",AF$10="",AF$10=0),"",AF36/AF$10) | AI36: ='Monthly P&L'!J37 -> 1599.1013 | AJ36: =IF(AJ$10="","",SUM(AJ18:AJ35)) | AK36: =IF(OR(AJ36="",AI36=0),"",AJ36/AI36) | AL36: =IF(OR(AJ36="",AJ$10="",AJ$10=0),"",AJ36/AJ$10) | AM36: ='Monthly P&L'!K37 -> 1476.7066 | AN36: =IF(AN$10="","",SUM(AN18:AN35)) | AO36: =IF(OR(AN36="",AM36=0),"",AN36/AM36) | AP36: =IF(OR(AN36="",AN$10="",AN$10=0),"",AN36/AN$10) | AQ36: ='Monthly P&L'!L37 -> 1511.7954 | AR36: =IF(AR$10="","",SUM(AR18:AR35)) | AS36: =IF(OR(AR36="",AQ36=0),"",AR36/AQ36) | AT36: =IF(OR(AR36="",AR$10="",AR$10=0),"",AR36/AR$10) | AU36: ='Monthly P&L'!M37 -> 1478.452 | AV36: =IF(AV$10="","",SUM(AV18:AV35)) | AW36: =IF(OR(AV36="",AU36=0),"",AV36/AU36) | AX36: =IF(OR(AV36="",AV$10="",AV$10=0),"",AV36/AV$10) | AY36: ='Monthly P&L'!N37 -> 1697.7097 | AZ36: =IF(AZ$10="","",SUM(AZ18:AZ35)) | BA36: =IF(OR(AZ36="",AY36=0),"",AZ36/AY36) | BB36: =IF(OR(AZ36="",AZ$10="",AZ$10=0),"",AZ36/AZ$10) | BC36: ='Monthly P&L'!O37 -> 1798.2131 | BD36: =IF(BD$10="","",SUM(BD18:BD35)) | BE36: =IF(OR(BD36="",BC36=0),"",BD36/BC36) | BF36: =IF(OR(BD36="",BD$10="",BD$10=0),"",BD36/BD$10)
A37: EBITDA | B37: ='Monthly P&L'!B39 -> 10069.852 | C37: =IF(OR(B37=0,B37=""),"",D37/B37-1) -> 0.46774183 | D37: ='Monthly P&L'!C39 -> 14779.943 | E37: =IF(D$10=0,"",D37/D$10) -> 0.25694686 | F37: =IF(H37="","",K37*(L37<>"")+O37*(P37<>"")+S37*(T37<>"")+W37*(X37<>"")+AA37*(AB37<>"")+AE37*(AF37<>"")+AI37*(AJ37<>"")+AM37*(AN37<>"")+AQ37*(AR37<>"")+AU37*(AV37<>"")+AY37*(AZ37<>"")+BC37*(BD37<>"")) -> 2294.6626 | G37: =IF(OR(F37=0,F37="",H37=""),"",H37/F37) -> 1.0202408 | H37: =IF(SUM(L37,P37,T37,X37,AB37,AF37,AJ37,AN37,AR37,AV37,AZ37,BD37)=0,"",SUM(L37,P37,T37,X37,AB37,AF37,AJ37,AN37,AR37,AV37,AZ37,BD37)) -> 2341.1083 | I37: =IF(OR(H$10="",H$10=0),"",H37/H$10) -> 0.2689436 | J37: =IF(OR(D37=0,H37=""),"",H37/D37) -> 0.15839766 | K37: ='Monthly P&L'!D39 -> 1085.3964 | L37: =IF(L$10="","",L15-L36) -> 1110.2297 | M37: =IF(OR(L37="",K37=0),"",L37/K37) -> 1.0228795 | N37: =IF(OR(L37="",L$10="",L$10=0),"",L37/L$10) -> 0.25946732 | O37: ='Monthly P&L'!E39 -> 1209.2662 | P37: =IF(P$10="","",P15-P36) -> 1230.8786 | Q37: =IF(OR(P37="",O37=0),"",P37/O37) -> 1.0178723 | R37: =IF(OR(P37="",P$10="",P$10=0),"",P37/P$10) -> 0.27810499 | S37: ='Monthly P&L'!F39 -> 719.47777 | T37: =IF(T$10="","",T15-T36) | U37: =IF(OR(T37="",S37=0),"",T37/S37) | V37: =IF(OR(T37="",T$10="",T$10=0),"",T37/T$10) | W37: ='Monthly P&L'!G39 -> 1251.1427 | X37: =IF(X$10="","",X15-X36) | Y37: =IF(OR(X37="",W37=0),"",X37/W37) | Z37: =IF(OR(X37="",X$10="",X$10=0),"",X37/X$10) | AA37: ='Monthly P&L'!H39 -> 1436.4236 | AB37: =IF(AB$10="","",AB15-AB36) | AC37: =IF(OR(AB37="",AA37=0),"",AB37/AA37) | AD37: =IF(OR(AB37="",AB$10="",AB$10=0),"",AB37/AB$10) | AE37: ='Monthly P&L'!I39 -> 1370.5765 | AF37: =IF(AF$10="","",AF15-AF36) | AG37: =IF(OR(AF37="",AE37=0),"",AF37/AE37) | AH37: =IF(OR(AF37="",AF$10="",AF$10=0),"",AF37/AF$10) | AI37: ='Monthly P&L'!J39 -> 1235.1247 | AJ37: =IF(AJ$10="","",AJ15-AJ36) | AK37: =IF(OR(AJ37="",AI37=0),"",AJ37/AI37) | AL37: =IF(OR(AJ37="",AJ$10="",AJ$10=0),"",AJ37/AJ$10) | AM37: ='Monthly P&L'!K39 -> 994.02376 | AN37: =IF(AN$10="","",AN15-AN36) | AO37: =IF(OR(AN37="",AM37=0),"",AN37/AM37) | AP37: =IF(OR(AN37="",AN$10="",AN$10=0),"",AN37/AN$10) | AQ37: ='Monthly P&L'!L39 -> 1137.0728 | AR37: =IF(AR$10="","",AR15-AR36) | AS37: =IF(OR(AR37="",AQ37=0),"",AR37/AQ37) | AT37: =IF(OR(AR37="",AR$10="",AR$10=0),"",AR37/AR$10) | AU37: ='Monthly P&L'!M39 -> 1785.5173 | AV37: =IF(AV$10="","",AV15-AV36) | AW37: =IF(OR(AV37="",AU37=0),"",AV37/AU37) | AX37: =IF(OR(AV37="",AV$10="",AV$10=0),"",AV37/AV$10) | AY37: ='Monthly P&L'!N39 -> 1315.2221 | AZ37: =IF(AZ$10="","",AZ15-AZ36) | BA37: =IF(OR(AZ37="",AY37=0),"",AZ37/AY37) | BB37: =IF(OR(AZ37="",AZ$10="",AZ$10=0),"",AZ37/AZ$10) | BC37: ='Monthly P&L'!O39 -> 1240.7158 | BD37: =IF(BD$10="","",BD15-BD36) | BE37: =IF(OR(BD37="",BC37=0),"",BD37/BC37) | BF37: =IF(OR(BD37="",BD$10="",BD$10=0),"",BD37/BD$10)
A38: EBITDA Margin % | B38: ='Monthly P&L'!B40 -> 0.21934317 | D38: ='Monthly P&L'!C40 -> 0.25694686 | F38: =IF($F$10="","",F37/$F$10) -> 0.25773763 | H38: =IF(H$10="","",H37/H$10) -> 0.2689436 | K38: ='Monthly P&L'!D40 -> 0.25735315 | L38: =IF(L$10="","",L37/L10) -> 0.25946732 | O38: ='Monthly P&L'!E40 -> 0.2580837 | P38: =IF(P$10="","",P37/P10) -> 0.27810499 | S38: ='Monthly P&L'!F40 -> 0.17059918 | T38: =IF(T$10="","",T37/T10) | W38: ='Monthly P&L'!G40 -> 0.25464736 | X38: =IF(X$10="","",X37/X10) | AA38: ='Monthly P&L'!H40 -> 0.28404642 | AB38: =IF(AB$10="","",AB37/AB10) | AE38: ='Monthly P&L'!I40 -> 0.27602325 | AF38: =IF(AF$10="","",AF37/AF10) | AI38: ='Monthly P&L'!J40 -> 0.24950825 | AJ38: =IF(AJ$10="","",AJ37/AJ10) | AM38: ='Monthly P&L'!K40 -> 0.22482823 | AN38: =IF(AN$10="","",AN37/AN10) | AQ38: ='Monthly P&L'!L40 -> 0.24293799 | AR38: =IF(AR$10="","",AR37/AR10) | AU38: ='Monthly P&L'!M40 -> 0.33099307 | AV38: =IF(AV$10="","",AV37/AV10) | AY38: ='Monthly P&L'!N40 -> 0.25972058 | AZ38: =IF(AZ$10="","",AZ37/AZ10) | BC38: ='Monthly P&L'!O40 -> 0.25040325 | BD38: =IF(BD$10="","",BD37/BD10)
A39: (-) Depreciation | B39: ='Monthly P&L'!B41 -> 2728.2069 | C39: =IF(OR(B39=0,B39=""),"",D39/B39-1) -> 0.0048831564 | D39: ='Monthly P&L'!C41 -> 2741.5292 | E39: =IF(D$10=0,"",D39/D$10) -> 0.04766103 | F39: =IF(H39="","",K39*(L39<>"")+O39*(P39<>"")+S39*(T39<>"")+W39*(X39<>"")+AA39*(AB39<>"")+AE39*(AF39<>"")+AI39*(AJ39<>"")+AM39*(AN39<>"")+AQ39*(AR39<>"")+AU39*(AV39<>"")+AY39*(AZ39<>"")+BC39*(BD39<>"")) -> 456.92153 | G39: =IF(OR(F39=0,F39="",H39=""),"",H39/F39) -> 0.86599409 | H39: =IF(SUM(L39,P39,T39,X39,AB39,AF39,AJ39,AN39,AR39,AV39,AZ39,BD39)=0,"",SUM(L39,P39,T39,X39,AB39,AF39,AJ39,AN39,AR39,AV39,AZ39,BD39)) -> 395.69134 | I39: =IF(OR(H$10="",H$10=0,H39=""),"",H39/H$10) -> 0.045456527 | J39: =IF(OR(D39=0,H39=""),"",H39/D39) -> 0.14433235 | K39: ='Monthly P&L'!D41 -> 228.46076 | L39: 198.44871 | M39: =IF(OR(L39="",K39=0),"",L39/K39) -> 0.86863367 | N39: =IF(OR(L39="",L$10="",L$10=0),"",L39/L$10) -> 0.046378651 | O39: ='Monthly P&L'!E41 -> 228.46076 | P39: 197.24263 | Q39: =IF(OR(P39="",O39=0),"",P39/O39) -> 0.86335452 | R39: =IF(OR(P39="",P$10="",P$10=0),"",P39/P$10) -> 0.044565044 | S39: ='Monthly P&L'!F41 -> 228.46076 | U39: =IF(OR(T39="",S39=0),"",T39/S39) | V39: =IF(OR(T39="",T$10="",T$10=0),"",T39/T$10) | W39: ='Monthly P&L'!G41 -> 228.46076 | Y39: =IF(OR(X39="",W39=0),"",X39/W39) | Z39: =IF(OR(X39="",X$10="",X$10=0),"",X39/X$10) | AA39: ='Monthly P&L'!H41 -> 228.46076 | AC39: =IF(OR(AB39="",AA39=0),"",AB39/AA39) | AD39: =IF(OR(AB39="",AB$10="",AB$10=0),"",AB39/AB$10) | AE39: ='Monthly P&L'!I41 -> 228.46076 | AG39: =IF(OR(AF39="",AE39=0),"",AF39/AE39) | AH39: =IF(OR(AF39="",AF$10="",AF$10=0),"",AF39/AF$10) | AI39: ='Monthly P&L'!J41 -> 228.46076 | AK39: =IF(OR(AJ39="",AI39=0),"",AJ39/AI39) | AL39: =IF(OR(AJ39="",AJ$10="",AJ$10=0),"",AJ39/AJ$10) | AM39: ='Monthly P&L'!K41 -> 228.46076 | AO39: =IF(OR(AN39="",AM39=0),"",AN39/AM39) | AP39: =IF(OR(AN39="",AN$10="",AN$10=0),"",AN39/AN$10) | AQ39: ='Monthly P&L'!L41 -> 228.46076 | AS39: =IF(OR(AR39="",AQ39=0),"",AR39/AQ39) | AT39: =IF(OR(AR39="",AR$10="",AR$10=0),"",AR39/AR$10) | AU39: ='Monthly P&L'!M41 -> 228.46076 | AW39: =IF(OR(AV39="",AU39=0),"",AV39/AU39) | AX39: =IF(OR(AV39="",AV$10="",AV$10=0),"",AV39/AV$10) | AY39: ='Monthly P&L'!N41 -> 228.46076 | BA39: =IF(OR(AZ39="",AY39=0),"",AZ39/AY39) | BB39: =IF(OR(AZ39="",AZ$10="",AZ$10=0),"",AZ39/AZ$10) | BC39: ='Monthly P&L'!O41 -> 228.46076 | BE39: =IF(OR(BD39="",BC39=0),"",BD39/BC39) | BF39: =IF(OR(BD39="",BD$10="",BD$10=0),"",BD39/BD$10)
A40: (-) Finance Cost | B40: ='Monthly P&L'!B42 -> 62.065184 | C40: =IF(OR(B40=0,B40=""),"",D40/B40-1) -> -0.033274436 | D40: ='Monthly P&L'!C42 -> 60 | E40: =IF(D$10=0,"",D40/D$10) -> 0.00104309 | F40: =IF(H40="","",K40*(L40<>"")+O40*(P40<>"")+S40*(T40<>"")+W40*(X40<>"")+AA40*(AB40<>"")+AE40*(AF40<>"")+AI40*(AJ40<>"")+AM40*(AN40<>"")+AQ40*(AR40<>"")+AU40*(AV40<>"")+AY40*(AZ40<>"")+BC40*(BD40<>"")) -> 10 | G40: =IF(OR(F40=0,F40="",H40=""),"",H40/F40) -> 0.40220216 | H40: =IF(SUM(L40,P40,T40,X40,AB40,AF40,AJ40,AN40,AR40,AV40,AZ40,BD40)=0,"",SUM(L40,P40,T40,X40,AB40,AF40,AJ40,AN40,AR40,AV40,AZ40,BD40)) -> 4.0220216 | I40: =IF(OR(H$10="",H$10=0,H40=""),"",H40/H$10) -> 0.00046204482 | J40: =IF(OR(D40=0,H40=""),"",H40/D40) -> 0.067033694 | K40: ='Monthly P&L'!D42 -> 5 | L40: 1.8106894 | M40: =IF(OR(L40="",K40=0),"",L40/K40) -> 0.36213789 | N40: =IF(OR(L40="",L$10="",L$10=0),"",L40/L$10) -> 0.00042316895 | O40: ='Monthly P&L'!E42 -> 5 | P40: 2.2113322 | Q40: =IF(OR(P40="",O40=0),"",P40/O40) -> 0.44226644 | R40: =IF(OR(P40="",P$10="",P$10=0),"",P40/P$10) -> 0.00049962889 | S40: ='Monthly P&L'!F42 -> 5 | U40: =IF(OR(T40="",S40=0),"",T40/S40) | V40: =IF(OR(T40="",T$10="",T$10=0),"",T40/T$10) | W40: ='Monthly P&L'!G42 -> 5 | Y40: =IF(OR(X40="",W40=0),"",X40/W40) | Z40: =IF(OR(X40="",X$10="",X$10=0),"",X40/X$10) | AA40: ='Monthly P&L'!H42 -> 5 | AC40: =IF(OR(AB40="",AA40=0),"",AB40/AA40) | AD40: =IF(OR(AB40="",AB$10="",AB$10=0),"",AB40/AB$10) | AE40: ='Monthly P&L'!I42 -> 5 | AG40: =IF(OR(AF40="",AE40=0),"",AF40/AE40) | AH40: =IF(OR(AF40="",AF$10="",AF$10=0),"",AF40/AF$10) | AI40: ='Monthly P&L'!J42 -> 5 | AK40: =IF(OR(AJ40="",AI40=0),"",AJ40/AI40) | AL40: =IF(OR(AJ40="",AJ$10="",AJ$10=0),"",AJ40/AJ$10) | AM40: ='Monthly P&L'!K42 -> 5 | AO40: =IF(OR(AN40="",AM40=0),"",AN40/AM40) | AP40: =IF(OR(AN40="",AN$10="",AN$10=0),"",AN40/AN$10) | AQ40: ='Monthly P&L'!L42 -> 5 | AS40: =IF(OR(AR40="",AQ40=0),"",AR40/AQ40) | AT40: =IF(OR(AR40="",AR$10="",AR$10=0),"",AR40/AR$10) | AU40: ='Monthly P&L'!M42 -> 5 | AW40: =IF(OR(AV40="",AU40=0),"",AV40/AU40) | AX40: =IF(OR(AV40="",AV$10="",AV$10=0),"",AV40/AV$10) | AY40: ='Monthly P&L'!N42 -> 5 | BA40: =IF(OR(AZ40="",AY40=0),"",AZ40/AY40) | BB40: =IF(OR(AZ40="",AZ$10="",AZ$10=0),"",AZ40/AZ$10) | BC40: ='Monthly P&L'!O42 -> 5 | BE40: =IF(OR(BD40="",BC40=0),"",BD40/BC40) | BF40: =IF(OR(BD40="",BD$10="",BD$10=0),"",BD40/BD$10)
A41: PBT | B41: ='Monthly P&L'!B43 -> 7279.5798 | C41: =IF(OR(B41=0,B41=""),"",D41/B41-1) -> 0.64548147 | D41: ='Monthly P&L'!C43 -> 11978.414 | E41: =IF(D$10=0,"",D41/D$10) -> 0.20824274 | F41: =IF(H41="","",K41*(L41<>"")+O41*(P41<>"")+S41*(T41<>"")+W41*(X41<>"")+AA41*(AB41<>"")+AE41*(AF41<>"")+AI41*(AJ41<>"")+AM41*(AN41<>"")+AQ41*(AR41<>"")+AU41*(AV41<>"")+AY41*(AZ41<>"")+BC41*(BD41<>"")) -> 1827.7411 | G41: =IF(OR(F41=0,F41="",H41=""),"",H41/F41) -> 1.0621827 | H41: =IF(SUM(L41,P41,T41,X41,AB41,AF41,AJ41,AN41,AR41,AV41,AZ41,BD41)=0,"",SUM(L41,P41,T41,X41,AB41,AF41,AJ41,AN41,AR41,AV41,AZ41,BD41)) -> 1941.395 | I41: =IF(OR(H$10="",H$10=0,H41=""),"",H41/H$10) -> 0.22302503 | J41: =IF(OR(D41=0,H41=""),"",H41/D41) -> 0.16207446 | K41: ='Monthly P&L'!D43 -> 851.93561 | L41: =IF(L$10="","",L37-L39-L40) -> 909.9703 | M41: =IF(OR(L41="",K41=0),"",L41/K41) -> 1.068121 | N41: =IF(OR(L41="",L$10="",L$10=0),"",L41/L$10) -> 0.2126655 | O41: ='Monthly P&L'!E43 -> 975.80548 | P41: =IF(P$10="","",P37-P39-P40) -> 1031.4247 | Q41: =IF(OR(P41="",O41=0),"",P41/O41) -> 1.0569982 | R41: =IF(OR(P41="",P$10="",P$10=0),"",P41/P$10) -> 0.23304032 | S41: ='Monthly P&L'!F43 -> 486.01701 | T41: =IF(T$10="","",T37-T39-T40) | U41: =IF(OR(T41="",S41=0),"",T41/S41) | V41: =IF(OR(T41="",T$10="",T$10=0),"",T41/T$10) | W41: ='Monthly P&L'!G43 -> 1017.6819 | X41: =IF(X$10="","",X37-X39-X40) | Y41: =IF(OR(X41="",W41=0),"",X41/W41) | Z41: =IF(OR(X41="",X$10="",X$10=0),"",X41/X$10) | AA41: ='Monthly P&L'!H43 -> 1202.9629 | AB41: =IF(AB$10="","",AB37-AB39-AB40) | AC41: =IF(OR(AB41="",AA41=0),"",AB41/AA41) | AD41: =IF(OR(AB41="",AB$10="",AB$10=0),"",AB41/AB$10) | AE41: ='Monthly P&L'!I43 -> 1137.1157 | AF41: =IF(AF$10="","",AF37-AF39-AF40) | AG41: =IF(OR(AF41="",AE41=0),"",AF41/AE41) | AH41: =IF(OR(AF41="",AF$10="",AF$10=0),"",AF41/AF$10) | AI41: ='Monthly P&L'!J43 -> 1001.6639 | AJ41: =IF(AJ$10="","",AJ37-AJ39-AJ40) | AK41: =IF(OR(AJ41="",AI41=0),"",AJ41/AI41) | AL41: =IF(OR(AJ41="",AJ$10="",AJ$10=0),"",AJ41/AJ$10) | AM41: ='Monthly P&L'!K43 -> 760.56299 | AN41: =IF(AN$10="","",AN37-AN39-AN40) | AO41: =IF(OR(AN41="",AM41=0),"",AN41/AM41) | AP41: =IF(OR(AN41="",AN$10="",AN$10=0),"",AN41/AN$10) | AQ41: ='Monthly P&L'!L43 -> 903.61205 | AR41: =IF(AR$10="","",AR37-AR39-AR40) | AS41: =IF(OR(AR41="",AQ41=0),"",AR41/AQ41) | AT41: =IF(OR(AR41="",AR$10="",AR$10=0),"",AR41/AR$10) | AU41: ='Monthly P&L'!M43 -> 1552.0565 | AV41: =IF(AV$10="","",AV37-AV39-AV40) | AW41: =IF(OR(AV41="",AU41=0),"",AV41/AU41) | AX41: =IF(OR(AV41="",AV$10="",AV$10=0),"",AV41/AV$10) | AY41: ='Monthly P&L'!N43 -> 1081.7613 | AZ41: =IF(AZ$10="","",AZ37-AZ39-AZ40) | BA41: =IF(OR(AZ41="",AY41=0),"",AZ41/AY41) | BB41: =IF(OR(AZ41="",AZ$10="",AZ$10=0),"",AZ41/AZ$10) | BC41: ='Monthly P&L'!O43 -> 1007.255 | BD41: =IF(BD$10="","",BD37-BD39-BD40) | BE41: =IF(OR(BD41="",BC41=0),"",BD41/BC41) | BF41: =IF(OR(BD41="",BD$10="",BD$10=0),"",BD41/BD$10)
A42: (-) Tax @ 25.89% | B42: ='Monthly P&L'!B44 -> 1892.6908 | C42: =IF(OR(B42=0,B42=""),"",D42/B42-1) -> 0.53622764 | D42: ='Monthly P&L'!C44 -> 2907.6039 | E42: =IF(D$10=0,"",D42/D$10) -> 0.050548211 | F42: =IF(H42="","",K42*(L42<>"")+O42*(P42<>"")+S42*(T42<>"")+W42*(X42<>"")+AA42*(AB42<>"")+AE42*(AF42<>"")+AI42*(AJ42<>"")+AM42*(AN42<>"")+AQ42*(AR42<>"")+AU42*(AV42<>"")+AY42*(AZ42<>"")+BC42*(BD42<>"")) -> 520.54842 | G42: =IF(OR(F42=0,F42="",H42=""),"",H42/F42) -> 0.96510007 | H42: =IF(SUM(L42,P42,T42,X42,AB42,AF42,AJ42,AN42,AR42,AV42,AZ42,BD42)=0,"",SUM(L42,P42,T42,X42,AB42,AF42,AJ42,AN42,AR42,AV42,AZ42,BD42)) -> 502.38132 | I42: =IF(OR(H$10="",H$10=0,H42=""),"",H42/H$10) -> 0.057712938 | J42: =IF(OR(D42=0,H42=""),"",H42/D42) -> 0.1727819 | K42: ='Monthly P&L'!D44 -> 264.46958 | L42: 235.47608 | M42: =IF(OR(L42="",K42=0),"",L42/K42) -> 0.89037116 | N42: =IF(OR(L42="",L$10="",L$10=0),"",L42/L$10) -> 0.055032169 | O42: ='Monthly P&L'!E44 -> 256.07885 | P42: 266.90524 | Q42: =IF(OR(P42="",O42=0),"",P42/O42) -> 1.0422776 | R42: =IF(OR(P42="",P$10="",P$10=0),"",P42/P$10) -> 0.060304628 | S42: ='Monthly P&L'!F44 -> 106.49541 | U42: =IF(OR(T42="",S42=0),"",T42/S42) | V42: =IF(OR(T42="",T$10="",T$10=0),"",T42/T$10) | W42: ='Monthly P&L'!G44 -> 237.67777 | Y42: =IF(OR(X42="",W42=0),"",X42/W42) | Z42: =IF(OR(X42="",X$10="",X$10=0),"",X42/X$10) | AA42: ='Monthly P&L'!H44 -> 298.09767 | AC42: =IF(OR(AB42="",AA42=0),"",AB42/AA42) | AD42: =IF(OR(AB42="",AB$10="",AB$10=0),"",AB42/AB$10) | AE42: ='Monthly P&L'!I44 -> 257.85514 | AG42: =IF(OR(AF42="",AE42=0),"",AF42/AE42) | AH42: =IF(OR(AF42="",AF$10="",AF$10=0),"",AF42/AF$10) | AI42: ='Monthly P&L'!J44 -> 230.88254 | AK42: =IF(OR(AJ42="",AI42=0),"",AJ42/AI42) | AL42: =IF(OR(AJ42="",AJ$10="",AJ$10=0),"",AJ42/AJ$10) | AM42: ='Monthly P&L'!K44 -> 181.9444 | AO42: =IF(OR(AN42="",AM42=0),"",AN42/AM42) | AP42: =IF(OR(AN42="",AN$10="",AN$10=0),"",AN42/AN$10) | AQ42: ='Monthly P&L'!L44 -> 199.97208 | AS42: =IF(OR(AR42="",AQ42=0),"",AR42/AQ42) | AT42: =IF(OR(AR42="",AR$10="",AR$10=0),"",AR42/AR$10) | AU42: ='Monthly P&L'!M44 -> 406.39467 | AW42: =IF(OR(AV42="",AU42=0),"",AV42/AU42) | AX42: =IF(OR(AV42="",AV$10="",AV$10=0),"",AV42/AV$10) | AY42: ='Monthly P&L'!N44 -> 254.87236 | BA42: =IF(OR(AZ42="",AY42=0),"",AZ42/AY42) | BB42: =IF(OR(AZ42="",AZ$10="",AZ$10=0),"",AZ42/AZ$10) | BC42: ='Monthly P&L'!O44 -> 212.86339 | BE42: =IF(OR(BD42="",BC42=0),"",BD42/BC42) | BF42: =IF(OR(BD42="",BD$10="",BD$10=0),"",BD42/BD$10)
A43: PAT | B43: ='Monthly P&L'!B45 -> 5386.8891 | C43: =IF(OR(B43=0,B43=""),"",D43/B43-1) -> 0.68386796 | D43: ='Monthly P&L'!C45 -> 9070.8099 | E43: =IF(D$10=0,"",D43/D$10) -> 0.15769453 | F43: =IF(H43="","",K43*(L43<>"")+O43*(P43<>"")+S43*(T43<>"")+W43*(X43<>"")+AA43*(AB43<>"")+AE43*(AF43<>"")+AI43*(AJ43<>"")+AM43*(AN43<>"")+AQ43*(AR43<>"")+AU43*(AV43<>"")+AY43*(AZ43<>"")+BC43*(BD43<>"")) -> 1307.1927 | G43: =IF(OR(F43=0,F43="",H43=""),"",H43/F43) -> 1.1008428 | H43: =IF(SUM(L43,P43,T43,X43,AB43,AF43,AJ43,AN43,AR43,AV43,AZ43,BD43)=0,"",SUM(L43,P43,T43,X43,AB43,AF43,AJ43,AN43,AR43,AV43,AZ43,BD43)) -> 1439.0136 | I43: =IF(OR(H$10="",H$10=0,H43=""),"",H43/H$10) -> 0.16531209 | J43: =IF(OR(D43=0,H43=""),"",H43/D43) -> 0.15864224 | K43: ='Monthly P&L'!D45 -> 587.46603 | L43: =IF(L$10="","",L41-L42) -> 674.49422 | M43: =IF(OR(L43="",K43=0),"",L43/K43) -> 1.1481416 | N43: =IF(OR(L43="",L$10="",L$10=0),"",L43/L$10) -> 0.15763333 | O43: ='Monthly P&L'!E45 -> 719.72663 | P43: =IF(P$10="","",P41-P42) -> 764.51942 | Q43: =IF(OR(P43="",O43=0),"",P43/O43) -> 1.0622358 | R43: =IF(OR(P43="",P$10="",P$10=0),"",P43/P$10) -> 0.17273569 | S43: ='Monthly P&L'!F45 -> 379.5216 | T43: =IF(T$10="","",T41-T42) | U43: =IF(OR(T43="",S43=0),"",T43/S43) | V43: =IF(OR(T43="",T$10="",T$10=0),"",T43/T$10) | W43: ='Monthly P&L'!G45 -> 780.00415 | X43: =IF(X$10="","",X41-X42) | Y43: =IF(OR(X43="",W43=0),"",X43/W43) | Z43: =IF(OR(X43="",X$10="",X$10=0),"",X43/X$10) | AA43: ='Monthly P&L'!H45 -> 904.86521 | AB43: =IF(AB$10="","",AB41-AB42) | AC43: =IF(OR(AB43="",AA43=0),"",AB43/AA43) | AD43: =IF(OR(AB43="",AB$10="",AB$10=0),"",AB43/AB$10) | AE43: ='Monthly P&L'!I45 -> 879.26056 | AF43: =IF(AF$10="","",AF41-AF42) | AG43: =IF(OR(AF43="",AE43=0),"",AF43/AE43) | AH43: =IF(OR(AF43="",AF$10="",AF$10=0),"",AF43/AF$10) | AI43: ='Monthly P&L'!J45 -> 770.78137 | AJ43: =IF(AJ$10="","",AJ41-AJ42) | AK43: =IF(OR(AJ43="",AI43=0),"",AJ43/AI43) | AL43: =IF(OR(AJ43="",AJ$10="",AJ$10=0),"",AJ43/AJ$10) | AM43: ='Monthly P&L'!K45 -> 578.6186 | AN43: =IF(AN$10="","",AN41-AN42) | AO43: =IF(OR(AN43="",AM43=0),"",AN43/AM43) | AP43: =IF(OR(AN43="",AN$10="",AN$10=0),"",AN43/AN$10) | AQ43: ='Monthly P&L'!L45 -> 703.63998 | AR43: =IF(AR$10="","",AR41-AR42) | AS43: =IF(OR(AR43="",AQ43=0),"",AR43/AQ43) | AT43: =IF(OR(AR43="",AR$10="",AR$10=0),"",AR43/AR$10) | AU43: ='Monthly P&L'!M45 -> 1145.6619 | AV43: =IF(AV$10="","",AV41-AV42) | AW43: =IF(OR(AV43="",AU43=0),"",AV43/AU43) | AX43: =IF(OR(AV43="",AV$10="",AV$10=0),"",AV43/AV$10) | AY43: ='Monthly P&L'!N45 -> 826.88895 | AZ43: =IF(AZ$10="","",AZ41-AZ42) | BA43: =IF(OR(AZ43="",AY43=0),"",AZ43/AY43) | BB43: =IF(OR(AZ43="",AZ$10="",AZ$10=0),"",AZ43/AZ$10) | BC43: ='Monthly P&L'!O45 -> 794.39163 | BD43: =IF(BD$10="","",BD41-BD42) | BE43: =IF(OR(BD43="",BC43=0),"",BD43/BC43) | BF43: =IF(OR(BD43="",BD$10="",BD$10=0),"",BD43/BD$10)
A44: PAT Margin % | B44: ='Monthly P&L'!B46 -> 0.1173381 | D44: ='Monthly P&L'!C46 -> 0.15769453 | F44: =IF($F$10="","",F43/$F$10) -> 0.14682452 | H44: =IF(H$10="","",H43/H$10) -> 0.16531209 | K44: ='Monthly P&L'!D46 -> 0.13929127 | L44: =IF(L$10="","",L43/L10) -> 0.15763333 | O44: ='Monthly P&L'!E46 -> 0.1536053 | P44: =IF(P$10="","",P43/P10) -> 0.17273569 | S44: ='Monthly P&L'!F46 -> 0.089990377 | T44: =IF(T$10="","",T43/T10) | W44: ='Monthly P&L'!G46 -> 0.15875567 | X44: =IF(X$10="","",X43/X10) | AA44: ='Monthly P&L'!H46 -> 0.17893309 | AB44: =IF(AB$10="","",AB43/AB10) | AE44: ='Monthly P&L'!I46 -> 0.17707611 | AF44: =IF(AF$10="","",AF43/AF10) | AI44: ='Monthly P&L'!J46 -> 0.15570599 | AJ44: =IF(AJ$10="","",AJ43/AJ10) | AM44: ='Monthly P&L'!K46 -> 0.13087192 | AN44: =IF(AN$10="","",AN43/AN10) | AQ44: ='Monthly P&L'!L46 -> 0.15033415 | AR44: =IF(AR$10="","",AR43/AR10) | AU44: ='Monthly P&L'!M46 -> 0.21237886 | AV44: =IF(AV$10="","",AV43/AV10) | AY44: ='Monthly P&L'!N46 -> 0.16328807 | AZ44: =IF(AZ$10="","",AZ43/AZ10) | BC44: ='Monthly P&L'!O46 -> 0.16032539 | BD44: =IF(BD$10="","",BD43/BD10)

Sheet Dashboard
A1: VPS LAKESHORE — PERFORMANCE DASHBOARD | FY 2026–27
A2: All figures ₹ Lakhs | linked from 'Performance Tracker' | YTD = months with actuals entered
B4: TOTAL REVENUE (YTD) | E4: EBITDA (YTD) | H4: PAT (YTD) | K4: CONTRIBUTION (YTD)
B5: ='Performance Tracker'!H10 -> 8704.8301 | E5: ='Performance Tracker'!H37 -> 2341.1083 | H5: ='Performance Tracker'!H43 -> 1439.0136 | K5: ='Performance Tracker'!H15 -> 4705.8157
B6: ="of ₹"&TEXT('Performance Tracker'!D10,"#,##0")&" plan • "&TEXT('Performance Tracker'!J10,"0.0%")&" achieved" -> of ₹57,521 plan • 15.1% achieved | E6: ="Margin "&TEXT('Performance Tracker'!H38,"0.0%")&" • Plan "&TEXT('Performance Tracker'!D38,"0.0%") -> Margin 26.9% • Plan 25.7% | H6: ="Margin "&TEXT('Performance Tracker'!H44,"0.0%")&" • Plan "&TEXT('Performance Tracker'!D44,"0.0%") -> Margin 16.5% • Plan 15.8% | K6: ="Margin "&TEXT('Performance Tracker'!H16,"0.0%")&" • Plan "&TEXT('Performance Tracker'!D16,"0.0%") -> Margin 54.1% • Plan 57.9%
A40: CHART DATA (linked to Performance Tracker)
A41: Month | B41: Revenue Plan | C41: Revenue Actual | E41: Month | F41: EBITDA Plan | G41: EBITDA Actual
A42: =TEXT('Performance Tracker'!K3,"mmm") -> Apr | B42: ='Performance Tracker'!K10 -> 4217.5367 | C42: =IF('Performance Tracker'!L10="",NA(),'Performance Tracker'!L10) -> 4278.8806 | E42: =TEXT('Performance Tracker'!K3,"mmm") -> Apr | F42: ='Performance Tracker'!K37 -> 1085.3964 | G42: =IF('Performance Tracker'!L37="",NA(),'Performance Tracker'!L37) -> 1110.2297
A43: =TEXT('Performance Tracker'!O3,"mmm") -> May | B43: ='Performance Tracker'!O10 -> 4685.5584 | C43: =IF('Performance Tracker'!P10="",NA(),'Performance Tracker'!P10) -> 4425.9494 | E43: =TEXT('Performance Tracker'!O3,"mmm") -> May | F43: ='Performance Tracker'!O37 -> 1209.2662 | G43: =IF('Performance Tracker'!P37="",NA(),'Performance Tracker'!P37) -> 1230.8786
A44: =TEXT('Performance Tracker'!S3,"mmm") -> Jun | B44: ='Performance Tracker'!S10 -> 4217.3576 | C44: =IF('Performance Tracker'!T10="",NA(),'Performance Tracker'!T10) -> #N/A | E44: =TEXT('Performance Tracker'!S3,"mmm") -> Jun | F44: ='Performance Tracker'!S37 -> 719.47777 | G44: =IF('Performance Tracker'!T37="",NA(),'Performance Tracker'!T37) -> #N/A
A45: =TEXT('Performance Tracker'!W3,"mmm") -> Jul | B45: ='Performance Tracker'!W10 -> 4913.2364 | C45: =IF('Performance Tracker'!X10="",NA(),'Performance Tracker'!X10) -> #N/A | E45: =TEXT('Performance Tracker'!W3,"mmm") -> Jul | F45: ='Performance Tracker'!W37 -> 1251.1427 | G45: =IF('Performance Tracker'!X37="",NA(),'Performance Tracker'!X37) -> #N/A
A46: =TEXT('Performance Tracker'!AA3,"mmm") -> Aug | B46: ='Performance Tracker'!AA10 -> 5057.0032 | C46: =IF('Performance Tracker'!AB10="",NA(),'Performance Tracker'!AB10) -> #N/A | E46: =TEXT('Performance Tracker'!AA3,"mmm") -> Aug | F46: ='Performance Tracker'!AA37 -> 1436.4236 | G46: =IF('Performance Tracker'!AB37="",NA(),'Performance Tracker'!AB37) -> #N/A
A47: =TEXT('Performance Tracker'!AE3,"mmm") -> Sep | B47: ='Performance Tracker'!AE10 -> 4965.4385 | C47: =IF('Performance Tracker'!AF10="",NA(),'Performance Tracker'!AF10) -> #N/A | E47: =TEXT('Performance Tracker'!AE3,"mmm") -> Sep | F47: ='Performance Tracker'!AE37 -> 1370.5765 | G47: =IF('Performance Tracker'!AF37="",NA(),'Performance Tracker'!AF37) -> #N/A
A48: =TEXT('Performance Tracker'!AI3,"mmm") -> Oct | B48: ='Performance Tracker'!AI10 -> 4950.2359 | C48: =IF('Performance Tracker'!AJ10="",NA(),'Performance Tracker'!AJ10) -> #N/A | E48: =TEXT('Performance Tracker'!AI3,"mmm") -> Oct | F48: ='Performance Tracker'!AI37 -> 1235.1247 | G48: =IF('Performance Tracker'!AJ37="",NA(),'Performance Tracker'!AJ37) -> #N/A
A49: =TEXT('Performance Tracker'!AM3,"mmm") -> Nov | B49: ='Performance Tracker'!AM10 -> 4421.2587 | C49: =IF('Performance Tracker'!AN10="",NA(),'Performance Tracker'!AN10) -> #N/A | E49: =TEXT('Performance Tracker'!AM3,"mmm") -> Nov | F49: ='Performance Tracker'!AM37 -> 994.02376 | G49: =IF('Performance Tracker'!AN37="",NA(),'Performance Tracker'!AN37) -> #N/A
A50: =TEXT('Performance Tracker'!AQ3,"mmm") -> Dec | B50: ='Performance Tracker'!AQ10 -> 4680.5064 | C50: =IF('Performance Tracker'!AR10="",NA(),'Performance Tracker'!AR10) -> #N/A | E50: =TEXT('Performance Tracker'!AQ3,"mmm") -> Dec | F50: ='Performance Tracker'!AQ37 -> 1137.0728 | G50: =IF('Performance Tracker'!AR37="",NA(),'Performance Tracker'!AR37) -> #N/A
A51: =TEXT('Performance Tracker'!AU3,"mmm") -> Jan | B51: ='Performance Tracker'!AU10 -> 5394.4251 | C51: =IF('Performance Tracker'!AV10="",NA(),'Performance Tracker'!AV10) -> #N/A | E51: =TEXT('Performance Tracker'!AU3,"mmm") -> Jan | F51: ='Performance Tracker'!AU37 -> 1785.5173 | G51: =IF('Performance Tracker'!AV37="",NA(),'Performance Tracker'!AV37) -> #N/A
A52: =TEXT('Performance Tracker'!AY3,"mmm") -> Feb | B52: ='Performance Tracker'!AY10 -> 5063.9887 | C52: =IF('Performance Tracker'!AZ10="",NA(),'Performance Tracker'!AZ10) -> #N/A | E52: =TEXT('Performance Tracker'!AY3,"mmm") -> Feb | F52: ='Performance Tracker'!AY37 -> 1315.2221 | G52: =IF('Performance Tracker'!AZ37="",NA(),'Performance Tracker'!AZ37) -> #N/A
A53: =TEXT('Performance Tracker'!BC3,"mmm") -> Mar | B53: ='Performance Tracker'!BC10 -> 4954.8709 | C53: =IF('Performance Tracker'!BD10="",NA(),'Performance Tracker'!BD10) -> #N/A | E53: =TEXT('Performance Tracker'!BC3,"mmm") -> Mar | F53: ='Performance Tracker'!BC37 -> 1240.7158 | G53: =IF('Performance Tracker'!BD37="",NA(),'Performance Tracker'!BD37) -> #N/A
A55: Revenue Mix (FY27 Plan) | B55: ₹ Lakhs | E55: Revenue Allocation (FY27 Plan) | F55: ₹ Lakhs
A56: ="IP Revenue" -> IP Revenue | B56: ='Performance Tracker'!D6 -> 39854.1 | E56: Variable Cost | F56: ='Performance Tracker'!D14 -> 24243.166
A57: OP Revenue | B57: ='Performance Tracker'!D7 -> 14519.5 | E57: Fixed Cost | F57: ='Performance Tracker'!D36 -> 18498.291
A58: F&B / VPS Gourmet | B58: ='Performance Tracker'!D8 -> 2222.7 | E58: EBITDA | F58: ='Performance Tracker'!D37 -> 14779.943
A59: Other Income | B59: ='Performance Tracker'!D9 -> 925.1
A61: Margins | B61: Plan | C61: YTD Actual
A62: Contribution % | B62: ='Performance Tracker'!D16 -> 0.57853657 | C62: ='Performance Tracker'!H16 -> 0.54059823
A63: EBITDA % | B63: ='Performance Tracker'!D38 -> 0.25694686 | C63: ='Performance Tracker'!H38 -> 0.2689436
A64: PAT % | B64: ='Performance Tracker'!D44 -> 0.15769453 | C64: ='Performance Tracker'!H44 -> 0.16531209

Sheet Monthly P&L
A1: VPS LAKESHORE HOSPITAL — MONTHLY PROFIT & LOSS | FY 2026–27 (Annual Operating Plan — Single Growth Plan)
A2: All figures ₹ Lakhs
A3: P&L Line | B3: FY26 Actual | C3: FY27 Plan | D3: Apr-26 | E3: May-26 | F3: Jun-26 | G3: Jul-26 | H3: Aug-26 | I3: Sep-26 | J3: Oct-26 | K3: Nov-26 | L3: Dec-26 | M3: Jan-27 | N3: Feb-27 | O3: Mar-27 | P3: FY27 Total
A4: REVENUE
A5: IP Revenue | B5: 31154.53 | C5: 39854.1 | D5: 2876.8074 | E5: 3225.2555 | F5: 2894.7614 | G5: 3395.955 | H5: 3520.9665 | I5: 3502.6117 | J5: 3472.181 | K5: 3091.2843 | L5: 3298.0825 | M5: 3813.4737 | N5: 3468.5768 | O5: 3294.1442 | P5: =SUM(D5:O5) -> 39854.1 | Q5: =+C5-P5 -> 0
A6: OP Revenue | B6: 12160.816 | C6: 14519.5 | D6: 1144.8245 | E6: 1203.6881 | F6: 1086.5151 | G6: 1302.6032 | H6: 1314.8005 | I6: 1244.6991 | J6: 1242.9217 | K6: 1120.6707 | L6: 1184.946 | M6: 1326.6257 | N6: 1191.909 | O6: 1155.2967 | P6: =SUM(D6:O6) -> 14519.5 | Q6: =+C6-P6 -> 0
A7: F&B / VPS Gourmet | B7: 1718.1767 | C7: 2222.7 | D7: 172.64272 | E7: 183.26626 | F7: 169.6418 | G7: 198.35485 | H7: 197.8822 | I7: 191.14197 | J7: 190.0075 | K7: 177.99094 | L7: 183.43362 | M7: 201.12799 | N7: 183.82706 | O7: 173.38309 | P7: =SUM(D7:O7) -> 2222.7 | Q7: =+C7-P7 -> 0
A8: Other Income | B8: 875.5977 | C8: 925.1 | D8: 23.262151 | E8: 73.348605 | F8: 66.43931 | G8: 16.323444 | H8: 23.353976 | I8: 26.985795 | J8: 45.125736 | K8: 31.312755 | L8: 14.044394 | M8: 53.197681 | N8: 219.67586 | O8: 332.04697 | P8: =SUM(D8:O8) -> 925.11668 | Q8: =+C8-P8 -> -0.0166762
A9: Total Revenue | B9: =SUM(B5:B8) -> 45909.12 | C9: =SUM(C5:C8) -> 57521.4 | D9: =SUM(D5:D8) -> 4217.5367 | E9: =SUM(E5:E8) -> 4685.5584 | F9: =SUM(F5:F8) -> 4217.3576 | G9: =SUM(G5:G8) -> 4913.2364 | H9: =SUM(H5:H8) -> 5057.0032 | I9: =SUM(I5:I8) -> 4965.4385 | ... P9: =SUM(P5:P8) -> 57521.417
A11: VARIABLE COSTS
A12: (-) Consumption / Drug & Consumables | B12: 13709.978 | C12: =+P12 -> 15243.175 | D12: 960.94761 | E12: 1274.2374 | F12: 1245.8601 | G12: 1420.1062 | H12: 1356.5204 | I12: 1289.868 | J12: 1366.0106 | K12: 1200.5291 | L12: 1281.6389 | M12: 1380.4566 | N12: 1301.0576 | O12: 1165.9428 | P12: =SUM(D12:O12) -> 15243.175 | Q12: =+C12-P12 -> 0 | R12: =+C12/$C$8 -> 16.477327
A13: (-) Doctor Cost | B13: 7978.262 | C13: =+P13 -> 8999.991 | D13: 749.99925 | E13: 749.99925 | F13: 749.99925 | G13: 749.99925 | H13: 749.99925 | I13: 749.99925 | J13: 749.99925 | K13: 749.99925 | L13: 749.99925 | M13: 749.99925 | N13: 749.99925 | O13: 749.99925 | P13: =SUM(D13:O13) -> 8999.991 | Q13: =+C13-P13 -> 0 | R13: =+C13/$C$8 -> 9.7286683
A14: Total Variable Cost | B14: =+B12+B13 -> 21688.24 | C14: =+C12+C13 -> 24243.166 | D14: =+D12+D13 -> 1710.9469 | E14: =+E12+E13 -> 2024.2366 | F14: =+F12+F13 -> 1995.8594 | G14: =+G12+G13 -> 2170.1055 | H14: =+H12+H13 -> 2106.5197 | I14: =+I12+I13 -> 2039.8673 | ... P14: =+P12+P13 -> 24243.166
A15: Contribution | B15: =+B9-B14 -> 24220.88 | C15: =+C9-C14 -> 33278.234 | D15: =+D9-D14 -> 2506.5899 | E15: =+E9-E14 -> 2661.3218 | F15: =+F9-F14 -> 2221.4983 | G15: =+G9-G14 -> 2743.1309 | H15: =+H9-H14 -> 2950.4835 | I15: =+I9-I14 -> 2925.5713 | ... P15: =+P9-P14 -> 33278.25 | Q15: =+C15-P15 -> -0.0166762
A16: Contribution Margin % | B16: =+B15/B9 -> 0.52758319 | C16: =+C15/C9 -> 0.57853657 | D16: =+D15/D9 -> 0.59432556 | E16: =+E15/E9 -> 0.56798391 | F16: =+F15/F9 -> 0.52675122 | G16: =+G15/G9 -> 0.55831446 | H16: =+H15/H9 -> 0.58344506 | I16: =+I15/I9 -> 0.58918689 | ... P16: =+P15/P9 -> 0.57853669
A18: FIXED COSTS
A19: Employee Cost | B19: 7510.1356 | C19: =+P19 -> 9172.7007 | D19: 764.39172 | E19: 764.39172 | F19: 764.39172 | G19: 764.39172 | H19: 764.39172 | I19: 764.39172 | J19: 764.39172 | K19: 764.39172 | L19: 764.39172 | M19: 764.39172 | N19: 764.39172 | O19: 764.39172 | P19: =SUM(D19:O19) -> 9172.7007 | Q19: =+C19-P19 -> 0
A20: Utilities & Power | B20: 1190.744 | C20: =+P20 -> 1425.9 | D20: 106.51425 | E20: 114.4906 | F20: 125.70903 | G20: 117.11542 | H20: 108.99724 | I20: 117.12588 | J20: 130.7755 | K20: 106.15133 | L20: 118.14686 | M20: 125.67155 | N20: 109.14156 | O20: 146.06078 | P20: =SUM(D20:O20) -> 1425.9 | Q20: =+C20-P20 -> 0
A21: Lab Test Charges | B21: 267.69115 | C21: =+P21 -> 281 | D21: 17.614643 | E21: 19.535226 | F21: 22.497812 | G21: 19.284869 | H21: 27.862517 | I21: 17.60298 | J21: 23.917082 | K21: 9.6772168 | L21: 39.487348 | M21: 31.569099 | N21: 28.746253 | O21: 23.204954 | P21: =SUM(D21:O21) -> 281 | Q21: =+C21-P21 -> 0
A22: Rent Paid | B22: 279.27305 | C22: =+P22 -> 208.3 | D22: 16.634946 | E22: 15.670587 | F22: 17.61895 | G22: 12.414811 | H22: 19.683796 | I22: 19.513104 | J22: 15.669426 | K22: 15.549287 | L22: 18.107216 | M22: 17.154054 | N22: 17.050806 | O22: 23.233017 | P22: =SUM(D22:O22) -> 208.3 | Q22: =+C22-P22 -> 0
A23: Repair & Maintenance | B23: 1559.2231 | C23: =+P23 -> 1635.39 | D23: 84.96 | E23: 99.56 | F23: 132.21 | G23: 132.29 | H23: 143.62 | I23: 158.24 | J23: 163.31 | K23: 134.81 | L23: 109.05 | M23: 98.93 | N23: 189.56 | O23: 188.85 | P23: =SUM(D23:O23) -> 1635.39 | Q23: =+C23-P23 -> 0
A24: Housekeeping | B24: 1011.1753 | C24: =+P24 -> 1184 | D24: 72.842371 | E24: 84.093491 | F24: 101.11201 | G24: 87.15006 | H24: 79.411635 | I24: 87.829971 | J24: 103.13467 | K24: 74.265622 | L24: 79.782965 | M24: 57.876277 | N24: 141.54075 | O24: 214.96018 | P24: =SUM(D24:O24) -> 1184 | Q24: =+C24-P24 -> 0
A25: Security | B25: 265.1163 | C25: =+P25 -> 368.9 | D25: 28.914527 | E25: 32.858064 | F25: 32.858064 | G25: 32.454901 | H25: 27.57367 | I25: 26.491382 | J25: 35.5005 | K25: 29.279706 | L25: 29.746206 | M25: 31.465653 | N25: 29.391243 | O25: 32.366085 | P25: =SUM(D25:O25) -> 368.9 | Q25: =+C25-P25 -> 0
A26: Printing & Stationery | B26: 182.70992 | C26: =+P26 -> 166.3 | D26: 10.388101 | E26: 15.823622 | F26: 12.298557 | G26: 15.191548 | H26: 12.674734 | I26: 13.101131 | J26: 16.453661 | K26: 10.592546 | L26: 12.725547 | M26: 12.94168 | N26: 16.412919 | O26: 17.695954 | P26: =SUM(D26:O26) -> 166.3 | Q26: =+C26-P26 -> 0
A27: Insurance | B27: 31.991355 | C27: =+P27 -> 35.9 | D27: 2.5586521 | E27: 2.6749153 | F27: 2.1797664 | G27: 2.069981 | H27: 2.9522487 | I27: 3.8088144 | J27: 3.0101004 | K27: 3.2638714 | L27: 3.5089919 | M27: 3.0436151 | N27: 3.242325 | O27: 3.5867181 | P27: =SUM(D27:O27) -> 35.9 | Q27: =+C27-P27 -> 0
A28: Rates & Taxes | B28: 58.321304 | C28: =+P28 -> 65.5 | D28: 3.8349731 | E28: 6.6076095 | F28: 4.9727993 | G28: 6.8288177 | H28: 3.3504462 | I28: 1.8130073 | J28: 10.612213 | K28: 1.8985126 | L28: 2.4640354 | M28: 5.0194067 | N28: 2.9702682 | O28: 15.127911 | P28: =SUM(D28:O28) -> 65.5 | Q28: =+C28-P28 -> 0
A29: Professional Fee | B29: 201.10741 | C29: =+P29 -> 800 | D29: 69.46 | E29: 76.12 | F29: 70.61 | G29: 79.24 | H29: 62.89 | I29: 61.45 | J29: 56.15 | K29: 56.78 | L29: 49.93 | M29: 59.1 | N29: 72.08 | O29: 86.19 | P29: =SUM(D29:O29) -> 800 | Q29: =+C29-P29 -> 0
A30: Quality & Infection | B30: 5.675688 | C30: =+P30 -> 6.3 | D30: 0 | E30: 0 | F30: 0 | G30: 0 | H30: 0 | I30: 3.5221196 | J30: 0 | K30: 2.1438989 | L30: 0 | M30: 0 | N30: 0 | O30: 0.63398153 | P30: =SUM(D30:O30) -> 6.3 | Q30: =+C30-P30 -> 0
... A36: CSR | B36: 147.22187 | C36: =+P36 -> 127.8 | D36: 6.6176445 | E36: 7.3090596 | F36: 9.1856176 | G36: 8.7444345 | H36: 7.6984011 | I36: 8.8291242 | J36: 7.8339427 | K36: 6.6176445 | L36: 26.210858 | M36: 6.6176445 | N36: 8.3537996 | O36: 23.781829 | P36: =SUM(D36:O36) -> 127.8 | Q36: =+C36-P36 -> 0
A37: Total Fixed Cost | B37: =SUM(B19:B36) -> 14151.028 | C37: =SUM(C19:C36) -> 18498.291 | D37: =SUM(D19:D36) -> 1421.1935 | E37: =SUM(E19:E36) -> 1452.0556 | F37: =SUM(F19:F36) -> 1502.0205 | G37: =SUM(G19:G36) -> 1491.9882 | H37: =SUM(H19:H36) -> 1514.0599 | I37: =SUM(I19:I36) -> 1554.9948 | ... P37: =SUM(P19:P36) -> 18498.291
A39: EBITDA | B39: =+B15-B37 -> 10069.852 | C39: =+C15-C37 -> 14779.943 | D39: =+D15-D37 -> 1085.3964 | E39: =+E15-E37 -> 1209.2662 | F39: =+F15-F37 -> 719.47777 | G39: =+G15-G37 -> 1251.1427 | H39: =+H15-H37 -> 1436.4236 | I39: =+I15-I37 -> 1370.5765 | ... P39: =+P15-P37 -> 14779.96 | Q39: =+C39-P39 -> -0.0166762
A40: EBITDA Margin % | B40: =+B39/B9 -> 0.21934317 | C40: =+C39/C9 -> 0.25694686 | D40: =+D39/D9 -> 0.25735315 | E40: =+E39/E9 -> 0.2580837 | F40: =+F39/F9 -> 0.17059918 | G40: =+G39/G9 -> 0.25464736 | H40: =+H39/H9 -> 0.28404642 | I40: =+I39/I9 -> 0.27602325 | ... P40: =+P39/P9 -> 0.25694707
A41: (-) Depreciation | B41: 2728.2069 | C41: =+P41 -> 2741.5292 | D41: 228.46076 | E41: 228.46076 | F41: 228.46076 | G41: 228.46076 | H41: 228.46076 | I41: 228.46076 | J41: 228.46076 | K41: 228.46076 | L41: 228.46076 | M41: 228.46076 | N41: 228.46076 | O41: 228.46076 | P41: =SUM(D41:O41) -> 2741.5292 | Q41: =+C41-P41 -> 0
A42: (-) Finance Cost | B42: 62.065184 | C42: =+P42 -> 60 | D42: 5 | E42: 5 | F42: 5 | G42: 5 | H42: 5 | I42: 5 | J42: 5 | K42: 5 | L42: 5 | M42: 5 | N42: 5 | O42: 5 | P42: =SUM(D42:O42) -> 60 | Q42: =+C42-P42 -> 0
A43: PBT | B43: =+B39-B41-B42 -> 7279.5798 | C43: =+C39-C41-C42 -> 11978.414 | D43: =+D39-D41-D42 -> 851.93561 | E43: =+E39-E41-E42 -> 975.80548 | F43: =+F39-F41-F42 -> 486.01701 | G43: =+G39-G41-G42 -> 1017.6819 | H43: =+H39-H41-H42 -> 1202.9629 | I43: =+I39-I41-I42 -> 1137.1157 | ... P43: =+P39-P41-P42 -> 11978.43
A44: (-) Tax @ 25.89% | B44: 1892.6908 | C44: =+P44 -> 2907.6039 | D44: 264.46958 | E44: 256.07885 | F44: 106.49541 | G44: 237.67777 | H44: 298.09767 | I44: 257.85514 | J44: 230.88254 | K44: 181.9444 | L44: 199.97208 | M44: 406.39467 | N44: 254.87236 | O44: 212.86339 | P44: =SUM(D44:O44) -> 2907.6039 | Q44: =+C44-P44 -> 0
A45: PAT | B45: =+B43-B44 -> 5386.8891 | C45: =+C43-C44 -> 9070.8099 | D45: =+D43-D44 -> 587.46603 | E45: =+E43-E44 -> 719.72663 | F45: =+F43-F44 -> 379.5216 | G45: =+G43-G44 -> 780.00415 | H45: =+H43-H44 -> 904.86521 | I45: =+I43-I44 -> 879.26056 | ... P45: =+P43-P44 -> 9070.8266
A46: PAT Margin % | B46: =+B45/B9 -> 0.1173381 | C46: =+C45/C9 -> 0.15769453 | D46: =+D45/D9 -> 0.13929127 | E46: =+E45/E9 -> 0.1536053 | F46: =+F45/F9 -> 0.089990377 | G46: =+G45/G9 -> 0.15875567 | H46: =+H45/H9 -> 0.17893309 | I46: =+I45/I9 -> 0.17707611 | ... P46: =+P45/P9 -> 0.15769477
A49: INITIATIVE CONTRIBUTION — Monthly Phased Impact (₹L) | How revenue growth and cost savings are built up month-by-month
A50: Initiative | B50: Type | C50: Full-Year ₹L | D50: Apr-26 | E50: May-26 | F50: Jun-26 | G50: Jul-26 | H50: Aug-26 | I50: Sep-26 | J50: Oct-26 | K50: Nov-26 | L50: Dec-26 | M50: Jan-27 | N50: Feb-27 | O50: Mar-27 | P50: Total ₹L
A51: REVENUE — PRICING & YIELD
A52: R-01 — Annual Rate Revision Policy | B52: Revenue uplift | C52: =+P52 -> 904.97649 | D52: 0 | E52: 80.203977 | F52: 71.754292 | G52: 86.306094 | H52: 84.294263 | I52: 81.970072 | J52: 86.340704 | K52: 77.992912 | L52: 80.061968 | M52: 91.16059 | N52: 85.397087 | O52: 79.494535 | P52: =SUM(D52:O52) -> 904.97649 | Q52: R-01
A53: R-02 — Procedure Contribution Framework | B53: Revenue uplift | C53: =+P53 -> 250 | D53: 0 | E53: 0 | F53: 0 | G53: 7.5 | H53: 12.5 | I53: 17.5 | J53: 22.5 | K53: 27.5 | L53: 32.5 | M53: 37.5 | N53: 42.5 | O53: 50 | P53: =SUM(D53:O53) -> 250 | Q53: R-02
A54: R-03 — Insurance Renegotiation & Empanelment | B54: Revenue uplift | C54: =+P54 -> 900 | D54: 66.419292 | E54: 75.216928 | F54: 73.97683 | G54: 75.272763 | H54: 74.547357 | I54: 81.604123 | J54: 77.345104 | K54: 71.373074 | L54: 74.294749 | M54: 73.00757 | N54: 76.948663 | O54: 79.993546 | P54: =SUM(D54:O54) -> 900 | Q54: R-03
A55: REVENUE — NETWORK EXPANSION
A56: R-04 — Distributed Healthcare Network | B56: Revenue uplift | C56: =+P56 -> 449.12 | D56: 0 | E56: 12 | F56: 20 | G56: 36 | H56: 36 | I56: 36 | J56: 7.04 | K56: 7.04 | L56: 7.04 | M56: 96 | N56: 96 | O56: 96 | P56: =SUM(D56:O56) -> 449.12 | Q56: R-04
A57: R-05 — Corporate Health Programme | B57: Revenue uplift | C57: =+P57 -> 535.12682 | D57: 0 | E57: 0 | F57: 0 | G57: 16.053805 | H57: 26.756341 | I57: 37.458878 | J57: 53.512682 | K57: 58.86395 | L57: 64.215219 | M57: 80.269023 | N57: 90.97156 | O57: 107.02536 | P57: =SUM(D57:O57) -> 535.12682 | Q57: R-05
A58: R-06 — Residential & Community Outreach | B58: Revenue uplift | C58: =+P58 -> 240 | D58: 0 | E58: 0 | F58: 60 | G58: 0 | H58: 0 | I58: 60 | J58: 0 | K58: 0 | L58: 60 | M58: 0 | N58: 0 | O58: 60 | P58: =SUM(D58:O58) -> 240 | Q58: R-06
A59: REVENUE — REFERRAL DEVELOPMENT
A60: R-07 — International Medical Value Travel | B60: Revenue uplift | C60: =+P60 -> 681.92098 | D60: 48.514256 | E60: 50.195491 | F60: 39.696351 | G60: 73.126805 | H60: 101.92517 | I60: 73.146713 | J60: 55.389579 | K60: 52.764143 | L60: 45.298899 | M60: 77.350624 | N60: 48.025133 | O60: 16.487815 | P60: =SUM(D60:O60) -> 681.92098 | Q60: R-07
A61: R-08 — Govt Scheme Empanelment | B61: Revenue uplift | C61: =+P61 -> 150 | D61: 9.7524857 | E61: 11.011735 | F61: 7.6351363 | G61: 14.182578 | H61: 21.713584 | I61: 16.794096 | J61: 12.316723 | K61: 11.732142 | L61: 11.455044 | M61: 17.240553 | N61: 11.752297 | O61: 4.413626 | P61: =SUM(D61:O61) -> 150 | Q61: R-08
A62: R-09 — Scaled BD Organisation & Referral | B62: Revenue uplift | C62: =+P62 -> 2210.4624 | D62: 0 | E62: 103.89631 | F62: 205.49119 | G62: 209.09101 | H62: 207.07599 | I62: 226.67812 | J62: 214.84751 | K62: 198.25854 | L62: 206.3743 | M62: 202.79881 | N62: 213.74629 | O62: 222.20429 | P62: =SUM(D62:O62) -> 2210.4624 | Q62: R-09
A63: R-10 — OP-IP Conversion & Follow-Up | B63: Revenue uplift | C63: =+P63 -> 392.82196 | D63: 0 | E63: 32.437148 | F63: 32.240848 | G63: 38.367325 | H63: 36.651286 | I63: 36.651286 | J63: 36.827255 | K63: 33.596443 | L63: 35.83597 | M63: 39.476666 | N63: 34.608664 | O63: 36.129073 | P63: =SUM(D63:O63) -> 392.82196 | Q63: R-10
A64: REVENUE — HIGH-VALUE SERVICES
A65: R-11 — Dept Organic Growth Initiative | B65: Revenue uplift | C65: =+P65 -> 1098.7518 | D65: 0 | E65: 8.2512934 | F65: 25.017564 | G65: 48.232457 | H65: 62.371814 | I65: 81.261611 | J65: 101.17848 | K65: 108.65263 | L65: 135.97993 | M65: 170.27426 | N65: 168.77335 | O65: 188.75836 | P65: =SUM(D65:O65) -> 1098.7518 | Q65: R-11
A66: R-12 — New Specialties & Packages | B66: Revenue uplift | C66: =+P66 -> 1117.063 | D66: 0 | E66: 8.0918944 | F66: 26.415778 | G66: 47.623312 | H66: 63.530161 | I66: 83.017026 | J66: 102.03503 | K66: 110.26345 | L66: 138.66161 | M66: 174.99412 | N66: 170.09664 | O66: 192.33396 | P66: =SUM(D66:O66) -> 1117.063 | Q66: R-12
A67: R-13 — Clinician Recruitment | B67: Revenue uplift | C67: =+P67 -> 2031.0236 | D67: 0 | E67: 14.712535 | F67: 48.028687 | G67: 86.587839 | H67: 115.50938 | I67: 150.94005 | J67: 185.51823 | K67: 200.47899 | L67: 252.11202 | M67: 318.17113 | N67: 309.26662 | O67: 349.69812 | P67: =SUM(D67:O67) -> 2031.0236 | Q67: R-13
A68: REVENUE — MARKETING
A69: R-14 — Quarterly Health Events | B69: Revenue uplift | C69: =+P69 -> 129.01339 | D69: 0 | E69: 0.22985775 | F69: 17.743059 | G69: 0.99605023 | H69: 25.430594 | I69: 1.7622427 | J69: 2.6333829 | K69: 29.567263 | L69: 3.6993982 | M69: 24.819587 | N69: 3.7014731 | O69: 18.43048 | P69: =SUM(D69:O69) -> 129.01339 | Q69: R-14
A70: R-15 — Patient Acquisition & Digital | B70: Revenue uplift | C70: =+P70 -> 502.05424 | D70: 0 | E70: 1.0161081 | F70: 1.8753426 | G70: 5.131334 | H70: 21.845165 | I70: 31.455407 | J70: 46.722936 | K70: 54.10165 | L70: 71.601737 | M70: 83.126554 | N70: 86.188673 | O70: 98.989333 | P70: =SUM(D70:O70) -> 502.05424 | Q70: R-15
A71: REVENUE —FINANCIAL INCOME
A72: R-16 — Cash Portfolio Optimisation & Treasury Income | B72: Revenue uplift | C72: =+P72 -> 20 | D72: 0 | E72: 0 | F72: 0 | G72: 0.6 | H72: 1 | I72: 1.4 | J72: 1.8 | K72: 2.2 | L72: 2.6 | M72: 3 | N72: 3.4 | O72: 4 | P72: =SUM(D72:O72) -> 20 | Q72: R-16
A73: COST — MATERIALS/COGS
A74: C-01 — Drug Brand Substitution | B74: Cost saving | C74: =+P74 -> 465.01812 | D74: 20.941114 | E74: 28.419554 | F74: 27.802617 | G74: 43.785651 | H74: 45.21913 | I74: 43.108592 | J74: 45.618633 | K74: 39.856502 | L74: 42.369908 | M74: 46.020632 | N74: 43.331723 | O74: 38.544067 | P74: =SUM(D74:O74) -> 465.01812 | Q74: C-01
A75: C-02 — Manufacturer Rate Contract | B75: Cost saving | C75: =+P75 -> 190.58554 | D75: 11.796827 | E75: 16.009682 | F75: 15.662141 | G75: 17.899794 | H75: 16.982296 | I75: 16.189671 | J75: 17.132331 | K75: 14.968331 | L75: 15.912254 | M75: 17.283304 | N75: 16.273469 | O75: 14.475439 | P75: =SUM(D75:O75) -> 190.58554 | Q75: C-02
A76: C-03 — Distributor Consolidation | B76: Cost saving | C76: =+P76 -> 117.28341 | D76: 7.2595861 | E76: 9.8521119 | F76: 9.6382405 | G76: 11.015258 | H76: 10.450643 | I76: 9.9628745 | J76: 10.542973 | K76: 9.2112805 | L76: 9.7921564 | M76: 10.635879 | N76: 10.014443 | O76: 8.9079623 | P76: =SUM(D76:O76) -> 117.28341 | Q76: C-03
A77: C-04 — Surgical BOQ Standardisation | B77: Cost saving | C77: =+P77 -> 84.29745 | D77: 5.2178275 | E77: 7.0812055 | F77: 6.9274853 | G77: 7.9172168 | H77: 7.5114 | I77: 7.1608161 | J77: 7.5777619 | K77: 6.6206079 | L77: 7.0381124 | M77: 7.6445383 | N77: 7.1978806 | O77: 6.4025979 | P77: =SUM(D77:O77) -> 84.29745 | Q77: C-04
A78: C-05 — Inventory & Wastage Control | B78: Cost saving | C78: =+P78 -> 102.62298 | D78: 6.3521378 | E78: 8.620598 | F78: 8.4334604 | G78: 9.6383508 | H78: 9.144313 | I78: 8.7175152 | J78: 9.2251014 | K78: 8.0598705 | L78: 8.5681369 | M78: 9.3063945 | N78: 8.7626373 | O78: 7.794467 | P78: =SUM(D78:O78) -> 102.62298 | Q78: C-05
A79: COST — MISCELLANEOUS
A80: C-06 — Laundry Cost Reduction | B80: Cost saving | C80: =+P80 -> 12.933766 | D80: 1.0778138 | E80: 1.0778138 | F80: 1.0778138 | G80: 1.0778138 | H80: 1.0778138 | I80: 1.0778138 | J80: 1.0778138 | K80: 1.0778138 | L80: 1.0778138 | M80: 1.0778138 | N80: 1.0778138 | O80: 1.0778138 | P80: =SUM(D80:O80) -> 12.933766 | Q80: C-06
A81: C-07 — AMC Renegotiation | B81: Cost saving | C81: =+P81 -> 107.45505 | D81: -6.6868793 | E81: 32.729928 | F81: -2.0288969 | G81: 74.14554 | H81: 68.174847 | I81: 111.48352 | J81: -76.294881 | K81: -160.39326 | L81: 48.216882 | M81: -41.675143 | N81: 139.63255 | O81: -79.849147 | P81: =SUM(D81:O81) -> 107.45505 | Q81: C-07
A82: COST — PAYROLL
A83: C-08 — Nursing Headcount Norm | B83: Cost saving | C83: =+P83 -> 150 | D83: 11.069882 | E83: 12.536155 | F83: 12.329472 | G83: 12.54546 | H83: 12.42456 | I83: 13.600687 | J83: 12.890851 | K83: 11.895512 | L83: 12.382458 | M83: 12.167928 | N83: 12.824777 | O83: 13.332258 | P83: =SUM(D83:O83) -> 150 | Q83: C-08
A84: C-09 — Pharmacy Headcount Auto | B84: Cost saving | C84: =+P84 -> 100 | D84: 7.3799213 | E84: 8.3574364 | F84: 8.2196477 | G84: 8.3636403 | H84: 8.2830397 | I84: 9.0671248 | J84: 8.5939004 | K84: 7.9303416 | L84: 8.2549721 | M84: 8.1119522 | N84: 8.5498515 | O84: 8.8881718 | P84: =SUM(D84:O84) -> 100 | Q84: C-09
A85: C-10 — PCS Reduction via EMR | B85: Cost saving | C85: =+P85 -> 50 | D85: 3.6899607 | E85: 4.1787182 | F85: 4.1098239 | G85: 4.1818202 | H85: 4.1415198 | I85: 4.5335624 | J85: 4.2969502 | K85: 3.9651708 | L85: 4.1274861 | M85: 4.0559761 | N85: 4.2749257 | O85: 4.4440859 | P85: =SUM(D85:O85) -> 50 | Q85: C-10
A86: C-11 — Contract Staff Rebid | B86: Cost saving | C86: =+P86 -> 40 | D86: 0 | E86: 0 | F86: 0 | G86: 1.2 | H86: 2 | I86: 2.8 | J86: 3.6 | K86: 4.4 | L86: 5.2 | M86: 6 | N86: 6.8 | O86: 8 | P86: =SUM(D86:O86) -> 40 | Q86: C-11
A87: COST — MISCELLANEOUS
A88: C-12 — Expense Analysis & Discipline | B88: Cost saving | C88: =+P88 -> 15 | D88: 0 | E88: 0 | F88: 0 | G88: 0.45 | H88: 0.75 | I88: 1.05 | J88: 1.35 | K88: 1.65 | L88: 1.95 | M88: 2.25 | N88: 2.55 | O88: 3 | P88: =SUM(D88:O88) -> 15 | Q88: C-12
A89: CLINICAL EXCELLENCE
A90: CL-01 — Research & Publications | B90: Clinical/Brand | C90: =+P90 -> 0 | P90: 0 | Q90: CL-01
A91: CL-02 — Patient Care & Experience | B91: Clinical/Brand | C91: =+P91 -> 0 | P91: 0 | Q91: CL-02
A92: CL-03 — Academic Excellence & Med Ed | B92: Clinical/Brand | C92: =+P92 -> 0 | P92: 0 | Q92: CL-03
A93: CL-04 — Rare & Complex Care | B93: Clinical/Brand | C93: =+P93 -> 0 | P93: 0 | Q93: CL-04
A94: CL-05 — Awards & Accreditations | B94: Clinical/Brand | C94: =+P94 -> -20 | F94: -20 | P94: =SUM(D94:O94) -> -20 | Q94: CL-05
A95: TOTAL REVENUE INITIATIVE IMPACT (₹L) | C95: =+SUM(C52:C54,C56:C58,C60:C63,C65:C67,C69:C70,C72) -> 11612.335 | D95: =+SUM(D52:D54,D56:D58,D60:D63,D65:D67,D69:D70,D72) -> 124.68603 | E95: =+SUM(E52:E54,E56:E58,E60:E63,E65:E67,E69:E70,E72) -> 397.26327 | F95: =+SUM(F52:F54,F56:F58,F60:F63,F65:F67,F69:F70,F72) -> 629.87508 | G95: =+SUM(G52:G54,G56:G58,G60:G63,G65:G67,G69:G70,G72) -> 745.07137 | H95: =+SUM(H52:H54,H56:H58,H60:H63,H65:H67,H69:H70,H72) -> 891.15111 | I95: =+SUM(I52:I54,I56:I58,I60:I63,I65:I67,I69:I70,I72) -> 1017.6396 | J95: =+SUM(J52:J54,J56:J58,J60:J63,J65:J67,J69:J70,J72) -> 1006.0076 | ... P95: =+SUM(P52:P54,P56:P58,P60:P63,P65:P67,P69:P70,P72) -> 11612.335
A96: TOTAL COST SAVING IMPACT (₹L) | C96: =+SUM(C88:C88,C83:C86,C80:C81,C74:C78)+C94 -> 1415.1963 | D96: =+SUM(D88:D88,D83:D86,D80:D81,D74:D78) -> 68.098191 | E96: =+SUM(E88:E88,E83:E86,E80:E81,E74:E78) -> 128.8632 | F96: =+SUM(F88:F88,F83:F86,F80:F81,F74:F78) -> 92.171804 | G96: =+SUM(G88:G88,G83:G86,G80:G81,G74:G78) -> 192.22055 | H96: =+SUM(H88:H88,H83:H86,H80:H81,H74:H78) -> 186.15956 | I96: =+SUM(I88:I88,I83:I86,I80:I81,I74:I78) -> 228.75217 | J96: =+SUM(J88:J88,J83:J86,J80:J81,J74:J78) -> 45.611435 | K96: =+SUM(K88:K88,K83:K86,K80:K81,K74:K78) -> -50.757834 | ... O96: =+SUM(O88:O88,O83:O86,O80:O81,O74:O78) -> 35.017715 | P96: =+SUM(P88:P88,P83:P86,P80:P81,P74:P78)+P94 -> 1415.1963
A97: GROSS INITIATIVE IMPACT — Revenue + Cost Savings (₹L) | C97: =+C95+C96 -> 13027.531 | D97: =+D95+D96 -> 192.78422 | E97: =+E95+E96 -> 526.12648 | F97: =+F95+F96 -> 722.04689 | G97: =+G95+G96 -> 937.29192 | H97: =+H95+H96 -> 1077.3107 | I97: =+I95+I96 -> 1246.3918 | J97: =+J95+J96 -> 1051.6191 | ... P97: =+P95+P96 -> 13027.531
A99: Additional Cost to create Revenue Impact, the effect of which has to be adjusted in the above to reach the EBITDA
A100: Marketing Cost | D100: 0 | E100: 14.05 | F100: 80.05 | G100: 42.05 | H100: 72.55 | I100: 49.55 | J100: 42.05 | K100: 72.55 | L100: 49.55 | M100: 72.55 | N100: 42.05 | O100: 80.05 | P100: =SUM(D100:O100) -> 617.05
A101: Professional Fee | D101: 0 | E101: 5.5 | F101: 1.5 | G101: 1.5 | H101: 1.5 | I101: 1.5 | J101: 1.5 | K101: 1.5 | L101: 1.5 | M101: 1.5 | N101: 1.5 | O101: 1.5 | P101: =SUM(D101:O101) -> 20.5
A102: Employee Cost | D102: 0 | E102: 4.4 | F102: 3.4 | G102: 3.4 | H102: 3.4 | I102: 3.4 | J102: 3.4 | K102: 3.4 | L102: 3.4 | M102: 3.4 | N102: 3.4 | O102: 3.4 | P102: =SUM(D102:O102) -> 38.4
A103: Doctor Cost | D103: 0 | E103: 29.25 | F103: 29.25 | G103: 29.25 | H103: 29.25 | I103: 29.25 | J103: 29.25 | K103: 29.25 | L103: 29.25 | M103: 29.25 | N103: 29.25 | O103: 29.25 | P103: =SUM(D103:O103) -> 321.75
A104: Repair & Maintenance | D104: 0 | E104: 13 | F104: 0 | G104: 19.5 | H104: 0 | I104: 0 | J104: 19.5 | K104: 0 | L104: 0 | M104: 13 | N104: 0 | O104: 0 | P104: =SUM(D104:O104) -> 65
D106: =SUM(D100:D105) -> 0 | E106: =SUM(E100:E105) -> 66.2 | F106: =SUM(F100:F105) -> 114.2 | G106: =SUM(G100:G105) -> 95.7 | H106: =SUM(H100:H105) -> 106.7 | I106: =SUM(I100:I105) -> 83.7 | J106: =SUM(J100:J105) -> 95.7 | K106: =SUM(K100:K105) -> 106.7 | ... P106: =SUM(P100:P105) -> 1062.7
P107: =+P96-P106 -> 352.49632
