Workbook

Sheet PL_Consol
B1: LAKESHORE HOSPITAL AND RESEARCH CENTRE LIMITED
B2: Consolidated Profit and Loss Statement FY27 (Amount in lakhs)
D4: SMLY | E4: SMLY | O4: PM | S4: PM | T4: CM | U4: Budget | V4: Growth & Ach %
B5: Particulars | C5: Anx | D5: 45748 | E5: 45778 | F5: 45809 | G5: 45839 | H5: 45870 | I5: 45901 | J5: 45931 | K5: 45962 | L5: 45992 | M5: 46023 | N5: 46054 | O5: 46082 | P5: YTD | Q5: Bud | R5: FY25 | S5: 46113 | T5: 46143 | U5: 46143 | V5: YOY Gr. | W5: MOM Gr. | X5: BUD Ach.
B6: Revenue
B7: IP Revenue | C7: 1 | D7: =SUMIFS(PL_Kochi!C:C,PL_Kochi!$B:$B,PL_Consol!$B7)+SUMIFS(PL_Calicut!C:C,PL_Calicut!$B:$B,PL_Consol!$B7)+SUMIFS(PL_FNB!C:C,PL_FNB!$B:$B,PL_Consol!$B7) -> 1288.4786 | E7: =SUMIFS(PL_Kochi!D:D,PL_Kochi!$B:$B,PL_Consol!$B7)+SUMIFS(PL_Calicut!D:D,PL_Calicut!$B:$B,PL_Consol!$B7)+SUMIFS(PL_FNB!D:D,PL_FNB!$B:$B,PL_Consol!$B7) -> 1389.486 | F7: =SUMIFS(PL_Kochi!E:E,PL_Kochi!$B:$B,PL_Consol!$B7)+SUMIFS(PL_Calicut!E:E,PL_Calicut!$B:$B,PL_Consol!$B7)+SUMIFS(PL_FNB!E:E,PL_FNB!$B:$B,PL_Consol!$B7) -> 1243.0957 | G7: =SUMIFS(PL_Kochi!F:F,PL_Kochi!$B:$B,PL_Consol!$B7)+SUMIFS(PL_Calicut!F:F,PL_Calicut!$B:$B,PL_Consol!$B7)+SUMIFS(PL_FNB!F:F,PL_FNB!$B:$B,PL_Consol!$B7) -> 1443.6384 | H7: =SUMIFS(PL_Kochi!G:G,PL_Kochi!$B:$B,PL_Consol!$B7)+SUMIFS(PL_Calicut!G:G,PL_Calicut!$B:$B,PL_Consol!$B7)+SUMIFS(PL_FNB!G:G,PL_FNB!$B:$B,PL_Consol!$B7) -> 1583.9548 | I7: =SUMIFS(PL_Kochi!H:H,PL_Kochi!$B:$B,PL_Consol!$B7)+SUMIFS(PL_Calicut!H:H,PL_Calicut!$B:$B,PL_Consol!$B7)+SUMIFS(PL_FNB!H:H,PL_FNB!$B:$B,PL_Consol!$B7) -> 1505.3154 | J7: =SUMIFS(PL_Kochi!I:I,PL_Kochi!$B:$B,PL_Consol!$B7)+SUMIFS(PL_Calicut!I:I,PL_Calicut!$B:$B,PL_Consol!$B7)+SUMIFS(PL_FNB!I:I,PL_FNB!$B:$B,PL_Consol!$B7) -> 1554.3693 | K7: =SUMIFS(PL_Kochi!J:J,PL_Kochi!$B:$B,PL_Consol!$B7)+SUMIFS(PL_Calicut!J:J,PL_Calicut!$B:$B,PL_Consol!$B7)+SUMIFS(PL_FNB!J:J,PL_FNB!$B:$B,PL_Consol!$B7) -> 1402.5104 | L7: =SUMIFS(PL_Kochi!K:K,PL_Kochi!$B:$B,PL_Consol!$B7)+SUMIFS(PL_Calicut!K:K,PL_Calicut!$B:$B,PL_Consol!$B7)+SUMIFS(PL_FNB!K:K,PL_FNB!$B:$B,PL_Consol!$B7) -> 1476.794 | M7: =SUMIFS(PL_Kochi!L:L,PL_Kochi!$B:$B,PL_Consol!$B7)+SUMIFS(PL_Calicut!L:L,PL_Calicut!$B:$B,PL_Consol!$B7)+SUMIFS(PL_FNB!L:L,PL_FNB!$B:$B,PL_Consol!$B7) -> 1717.568 | N7: =SUMIFS(PL_Kochi!M:M,PL_Kochi!$B:$B,PL_Consol!$B7)+SUMIFS(PL_Calicut!M:M,PL_Calicut!$B:$B,PL_Consol!$B7)+SUMIFS(PL_FNB!M:M,PL_FNB!$B:$B,PL_Consol!$B7) -> 1569.515 | O7: =SUMIFS(PL_Kochi!N:N,PL_Kochi!$B:$B,PL_Consol!$B7)+SUMIFS(PL_Calicut!N:N,PL_Calicut!$B:$B,PL_Consol!$B7)+SUMIFS(PL_FNB!N:N,PL_FNB!$B:$B,PL_Consol!$B7) -> 1386.8843 | P7: =SUM(D7:O7) -> 17561.61 | Q7: 20170.36 | R7: 16277.82 | S7: =SUMIFS(PL_Kochi!R:R,PL_Kochi!$B:$B,PL_Consol!$B7)+SUMIFS(PL_Calicut!R:R,PL_Calicut!$B:$B,PL_Consol!$B7)+SUMIFS(PL_FNB!R:R,PL_FNB!$B:$B,PL_Consol!$B7) -> 1722.7909 | T7: =SUMIFS(PL_Kochi!$S:$S,PL_Kochi!$B:$B,PL_Consol!B7)+SUMIFS(PL_Calicut!$S:$S,PL_Calicut!$B:$B,PL_Consol!B7)+SUMIFS(PL_FNB!$S:$S,PL_FNB!$B:$B,PL_Consol!B7) -> 1795.5768 | U7: =2959.7-1469.5 -> 1490.2 | V7: =IFERROR(T7/E7-1,"-") -> 0.29225966 | W7: =IFERROR(T7/S7-1,"-") -> 0.042248824 | X7: =IFERROR(T7/U7,"-") -> 1.2049233
B8: IP Pharmacy | C8: 2 | D8: =SUMIFS(PL_Kochi!C:C,PL_Kochi!$B:$B,PL_Consol!$B8)+SUMIFS(PL_Calicut!C:C,PL_Calicut!$B:$B,PL_Consol!$B8)+SUMIFS(PL_FNB!C:C,PL_FNB!$B:$B,PL_Consol!$B8) -> 962.09911 | E8: =SUMIFS(PL_Kochi!D:D,PL_Kochi!$B:$B,PL_Consol!$B8)+SUMIFS(PL_Calicut!D:D,PL_Calicut!$B:$B,PL_Consol!$B8)+SUMIFS(PL_FNB!D:D,PL_FNB!$B:$B,PL_Consol!$B8) -> 1132.1552 | F8: =SUMIFS(PL_Kochi!E:E,PL_Kochi!$B:$B,PL_Consol!$B8)+SUMIFS(PL_Calicut!E:E,PL_Calicut!$B:$B,PL_Consol!$B8)+SUMIFS(PL_FNB!E:E,PL_FNB!$B:$B,PL_Consol!$B8) -> 1020.1168 | G8: =SUMIFS(PL_Kochi!F:F,PL_Kochi!$B:$B,PL_Consol!$B8)+SUMIFS(PL_Calicut!F:F,PL_Calicut!$B:$B,PL_Consol!$B8)+SUMIFS(PL_FNB!F:F,PL_FNB!$B:$B,PL_Consol!$B8) -> 1210.9126 | H8: =SUMIFS(PL_Kochi!G:G,PL_Kochi!$B:$B,PL_Consol!$B8)+SUMIFS(PL_Calicut!G:G,PL_Calicut!$B:$B,PL_Consol!$B8)+SUMIFS(PL_FNB!G:G,PL_FNB!$B:$B,PL_Consol!$B8) -> 1170.6095 | I8: =SUMIFS(PL_Kochi!H:H,PL_Kochi!$B:$B,PL_Consol!$B8)+SUMIFS(PL_Calicut!H:H,PL_Calicut!$B:$B,PL_Consol!$B8)+SUMIFS(PL_FNB!H:H,PL_FNB!$B:$B,PL_Consol!$B8) -> 1233.0387 | J8: =SUMIFS(PL_Kochi!I:I,PL_Kochi!$B:$B,PL_Consol!$B8)+SUMIFS(PL_Calicut!I:I,PL_Calicut!$B:$B,PL_Consol!$B8)+SUMIFS(PL_FNB!I:I,PL_FNB!$B:$B,PL_Consol!$B8) -> 1161.8466 | K8: =SUMIFS(PL_Kochi!J:J,PL_Kochi!$B:$B,PL_Consol!$B8)+SUMIFS(PL_Calicut!J:J,PL_Calicut!$B:$B,PL_Consol!$B8)+SUMIFS(PL_FNB!J:J,PL_FNB!$B:$B,PL_Consol!$B8) -> 1016.3118 | L8: =SUMIFS(PL_Kochi!K:K,PL_Kochi!$B:$B,PL_Consol!$B8)+SUMIFS(PL_Calicut!K:K,PL_Calicut!$B:$B,PL_Consol!$B8)+SUMIFS(PL_FNB!K:K,PL_FNB!$B:$B,PL_Consol!$B8) -> 1099.892 | M8: =SUMIFS(PL_Kochi!L:L,PL_Kochi!$B:$B,PL_Consol!$B8)+SUMIFS(PL_Calicut!L:L,PL_Calicut!$B:$B,PL_Consol!$B8)+SUMIFS(PL_FNB!L:L,PL_FNB!$B:$B,PL_Consol!$B8) -> 1265.8426 | N8: =SUMIFS(PL_Kochi!M:M,PL_Kochi!$B:$B,PL_Consol!$B8)+SUMIFS(PL_Calicut!M:M,PL_Calicut!$B:$B,PL_Consol!$B8)+SUMIFS(PL_FNB!M:M,PL_FNB!$B:$B,PL_Consol!$B8) -> 1140.9099 | O8: =SUMIFS(PL_Kochi!N:N,PL_Kochi!$B:$B,PL_Consol!$B8)+SUMIFS(PL_Calicut!N:N,PL_Calicut!$B:$B,PL_Consol!$B8)+SUMIFS(PL_FNB!N:N,PL_FNB!$B:$B,PL_Consol!$B8) -> 1187.7072 | P8: =SUM(D8:O8) -> 13601.442 | Q8: 15621.359 | R8: 12607.149 | S8: =SUMIFS(PL_Kochi!R:R,PL_Kochi!$B:$B,PL_Consol!$B8)+SUMIFS(PL_Calicut!R:R,PL_Calicut!$B:$B,PL_Consol!$B8)+SUMIFS(PL_FNB!R:R,PL_FNB!$B:$B,PL_Consol!$B8) -> 1369.1501 | T8: =SUMIFS(PL_Kochi!$S:$S,PL_Kochi!$B:$B,PL_Consol!B8)+SUMIFS(PL_Calicut!$S:$S,PL_Calicut!$B:$B,PL_Consol!B8)+SUMIFS(PL_FNB!$S:$S,PL_FNB!$B:$B,PL_Consol!B8) -> 1421.0771 | U8: 1469.5434 | V8: =IFERROR(T8/E8-1,"-") -> 0.25519634 | W8: =IFERROR(T8/S8-1,"-") -> 0.037926411 | X8: =IFERROR(T8/U8,"-") -> 0.9670195
B9: OP Revenue | C9: 3 | D9: =SUMIFS(PL_Kochi!C:C,PL_Kochi!$B:$B,PL_Consol!$B9)+SUMIFS(PL_Calicut!C:C,PL_Calicut!$B:$B,PL_Consol!$B9)+SUMIFS(PL_FNB!C:C,PL_FNB!$B:$B,PL_Consol!$B9) -> 637.60032 | E9: =SUMIFS(PL_Kochi!D:D,PL_Kochi!$B:$B,PL_Consol!$B9)+SUMIFS(PL_Calicut!D:D,PL_Calicut!$B:$B,PL_Consol!$B9)+SUMIFS(PL_FNB!D:D,PL_FNB!$B:$B,PL_Consol!$B9) -> 663.57897 | F9: =SUMIFS(PL_Kochi!E:E,PL_Kochi!$B:$B,PL_Consol!$B9)+SUMIFS(PL_Calicut!E:E,PL_Calicut!$B:$B,PL_Consol!$B9)+SUMIFS(PL_FNB!E:E,PL_FNB!$B:$B,PL_Consol!$B9) -> 612.20136 | G9: =SUMIFS(PL_Kochi!F:F,PL_Kochi!$B:$B,PL_Consol!$B9)+SUMIFS(PL_Calicut!F:F,PL_Calicut!$B:$B,PL_Consol!$B9)+SUMIFS(PL_FNB!F:F,PL_FNB!$B:$B,PL_Consol!$B9) -> 743.56545 | H9: =SUMIFS(PL_Kochi!G:G,PL_Kochi!$B:$B,PL_Consol!$B9)+SUMIFS(PL_Calicut!G:G,PL_Calicut!$B:$B,PL_Consol!$B9)+SUMIFS(PL_FNB!G:G,PL_FNB!$B:$B,PL_Consol!$B9) -> 713.72688 | I9: =SUMIFS(PL_Kochi!H:H,PL_Kochi!$B:$B,PL_Consol!$B9)+SUMIFS(PL_Calicut!H:H,PL_Calicut!$B:$B,PL_Consol!$B9)+SUMIFS(PL_FNB!H:H,PL_FNB!$B:$B,PL_Consol!$B9) -> 699.15029 | J9: =SUMIFS(PL_Kochi!I:I,PL_Kochi!$B:$B,PL_Consol!$B9)+SUMIFS(PL_Calicut!I:I,PL_Calicut!$B:$B,PL_Consol!$B9)+SUMIFS(PL_FNB!I:I,PL_FNB!$B:$B,PL_Consol!$B9) -> 692.3888 | K9: =SUMIFS(PL_Kochi!J:J,PL_Kochi!$B:$B,PL_Consol!$B9)+SUMIFS(PL_Calicut!J:J,PL_Calicut!$B:$B,PL_Consol!$B9)+SUMIFS(PL_FNB!J:J,PL_FNB!$B:$B,PL_Consol!$B9) -> 631.3311 | L9: =SUMIFS(PL_Kochi!K:K,PL_Kochi!$B:$B,PL_Consol!$B9)+SUMIFS(PL_Calicut!K:K,PL_Calicut!$B:$B,PL_Consol!$B9)+SUMIFS(PL_FNB!K:K,PL_FNB!$B:$B,PL_Consol!$B9) -> 650.09553 | M9: =SUMIFS(PL_Kochi!L:L,PL_Kochi!$B:$B,PL_Consol!$B9)+SUMIFS(PL_Calicut!L:L,PL_Calicut!$B:$B,PL_Consol!$B9)+SUMIFS(PL_FNB!L:L,PL_FNB!$B:$B,PL_Consol!$B9) -> 742.60137 | N9: =SUMIFS(PL_Kochi!M:M,PL_Kochi!$B:$B,PL_Consol!$B9)+SUMIFS(PL_Calicut!M:M,PL_Calicut!$B:$B,PL_Consol!$B9)+SUMIFS(PL_FNB!M:M,PL_FNB!$B:$B,PL_Consol!$B9) -> 667.29975 | O9: =SUMIFS(PL_Kochi!N:N,PL_Kochi!$B:$B,PL_Consol!$B9)+SUMIFS(PL_Calicut!N:N,PL_Calicut!$B:$B,PL_Consol!$B9)+SUMIFS(PL_FNB!N:N,PL_FNB!$B:$B,PL_Consol!$B9) -> 619.02266 | P9: =SUM(D9:O9) -> 8072.5625 | Q9: 8131.6124 | R9: 6731.8624 | S9: =SUMIFS(PL_Kochi!R:R,PL_Kochi!$B:$B,PL_Consol!$B9)+SUMIFS(PL_Calicut!R:R,PL_Calicut!$B:$B,PL_Consol!$B9)+SUMIFS(PL_FNB!R:R,PL_FNB!$B:$B,PL_Consol!$B9) -> 631.38286 | T9: =SUMIFS(PL_Kochi!$S:$S,PL_Kochi!$B:$B,PL_Consol!B9)+SUMIFS(PL_Calicut!$S:$S,PL_Calicut!$B:$B,PL_Consol!B9)+SUMIFS(PL_FNB!$S:$S,PL_FNB!$B:$B,PL_Consol!B9) -> 681.16854 | U9: =1161.6-431.3 -> 730.3 | V9: =IFERROR(T9/E9-1,"-") -> 0.026507118 | W9: =IFERROR(T9/S9-1,"-") -> 0.078851806 | X9: =IFERROR(T9/U9,"-") -> 0.93272427
B10: OP Pharmacy | C10: 4 | D10: =SUMIFS(PL_Kochi!C:C,PL_Kochi!$B:$B,PL_Consol!$B10)+SUMIFS(PL_Calicut!C:C,PL_Calicut!$B:$B,PL_Consol!$B10)+SUMIFS(PL_FNB!C:C,PL_FNB!$B:$B,PL_Consol!$B10) -> 322.0861 | E10: =SUMIFS(PL_Kochi!D:D,PL_Kochi!$B:$B,PL_Consol!$B10)+SUMIFS(PL_Calicut!D:D,PL_Calicut!$B:$B,PL_Consol!$B10)+SUMIFS(PL_FNB!D:D,PL_FNB!$B:$B,PL_Consol!$B10) -> 344.86247 | F10: =SUMIFS(PL_Kochi!E:E,PL_Kochi!$B:$B,PL_Consol!$B10)+SUMIFS(PL_Calicut!E:E,PL_Calicut!$B:$B,PL_Consol!$B10)+SUMIFS(PL_FNB!E:E,PL_FNB!$B:$B,PL_Consol!$B10) -> 299.17609 | G10: =SUMIFS(PL_Kochi!F:F,PL_Kochi!$B:$B,PL_Consol!$B10)+SUMIFS(PL_Calicut!F:F,PL_Calicut!$B:$B,PL_Consol!$B10)+SUMIFS(PL_FNB!F:F,PL_FNB!$B:$B,PL_Consol!$B10) -> 348.22764 | H10: =SUMIFS(PL_Kochi!G:G,PL_Kochi!$B:$B,PL_Consol!$B10)+SUMIFS(PL_Calicut!G:G,PL_Calicut!$B:$B,PL_Consol!$B10)+SUMIFS(PL_FNB!G:G,PL_FNB!$B:$B,PL_Consol!$B10) -> 384.8945 | I10: =SUMIFS(PL_Kochi!H:H,PL_Kochi!$B:$B,PL_Consol!$B10)+SUMIFS(PL_Calicut!H:H,PL_Calicut!$B:$B,PL_Consol!$B10)+SUMIFS(PL_FNB!H:H,PL_FNB!$B:$B,PL_Consol!$B10) -> 344.28042 | J10: =SUMIFS(PL_Kochi!I:I,PL_Kochi!$B:$B,PL_Consol!$B10)+SUMIFS(PL_Calicut!I:I,PL_Calicut!$B:$B,PL_Consol!$B10)+SUMIFS(PL_FNB!I:I,PL_FNB!$B:$B,PL_Consol!$B10) -> 348.91355 | K10: =SUMIFS(PL_Kochi!J:J,PL_Kochi!$B:$B,PL_Consol!$B10)+SUMIFS(PL_Calicut!J:J,PL_Calicut!$B:$B,PL_Consol!$B10)+SUMIFS(PL_FNB!J:J,PL_FNB!$B:$B,PL_Consol!$B10) -> 308.22255 | L10: =SUMIFS(PL_Kochi!K:K,PL_Kochi!$B:$B,PL_Consol!$B10)+SUMIFS(PL_Calicut!K:K,PL_Calicut!$B:$B,PL_Consol!$B10)+SUMIFS(PL_FNB!K:K,PL_FNB!$B:$B,PL_Consol!$B10) -> 345.34109 | M10: =SUMIFS(PL_Kochi!L:L,PL_Kochi!$B:$B,PL_Consol!$B10)+SUMIFS(PL_Calicut!L:L,PL_Calicut!$B:$B,PL_Consol!$B10)+SUMIFS(PL_FNB!L:L,PL_FNB!$B:$B,PL_Consol!$B10) -> 369.29489 | N10: =SUMIFS(PL_Kochi!M:M,PL_Kochi!$B:$B,PL_Consol!$B10)+SUMIFS(PL_Calicut!M:M,PL_Calicut!$B:$B,PL_Consol!$B10)+SUMIFS(PL_FNB!M:M,PL_FNB!$B:$B,PL_Consol!$B10) -> 335.17451 | O10: =SUMIFS(PL_Kochi!N:N,PL_Kochi!$B:$B,PL_Consol!$B10)+SUMIFS(PL_Calicut!N:N,PL_Calicut!$B:$B,PL_Consol!$B10)+SUMIFS(PL_FNB!N:N,PL_FNB!$B:$B,PL_Consol!$B10) -> 346.93941 | P10: =SUM(D10:O10) -> 4097.4132 | Q10: 4127.4305 | R10: 3416.9103 | S10: =SUMIFS(PL_Kochi!R:R,PL_Kochi!$B:$B,PL_Consol!$B10)+SUMIFS(PL_Calicut!R:R,PL_Calicut!$B:$B,PL_Consol!$B10)+SUMIFS(PL_FNB!R:R,PL_FNB!$B:$B,PL_Consol!$B10) -> 349.32571 | T10: =SUMIFS(PL_Kochi!$S:$S,PL_Kochi!$B:$B,PL_Consol!B10)+SUMIFS(PL_Calicut!$S:$S,PL_Calicut!$B:$B,PL_Consol!B10)+SUMIFS(PL_FNB!$S:$S,PL_FNB!$B:$B,PL_Consol!B10) -> 343.25514 | U10: 431.31397 | V10: =IFERROR(T10/E10-1,"-") -> -0.0046607679 | W10: =IFERROR(T10/S10-1,"-") -> -0.017377953 | X10: =IFERROR(T10/U10,"-") -> 0.7958359
B11: Aurveda | C11: 5 | D11: =SUMIFS(PL_Kochi!C:C,PL_Kochi!$B:$B,PL_Consol!$B11)+SUMIFS(PL_Calicut!C:C,PL_Calicut!$B:$B,PL_Consol!$B11)+SUMIFS(PL_FNB!C:C,PL_FNB!$B:$B,PL_Consol!$B11) -> 0 | E11: =SUMIFS(PL_Kochi!D:D,PL_Kochi!$B:$B,PL_Consol!$B11)+SUMIFS(PL_Calicut!D:D,PL_Calicut!$B:$B,PL_Consol!$B11)+SUMIFS(PL_FNB!D:D,PL_FNB!$B:$B,PL_Consol!$B11) -> 0 | F11: =SUMIFS(PL_Kochi!E:E,PL_Kochi!$B:$B,PL_Consol!$B11)+SUMIFS(PL_Calicut!E:E,PL_Calicut!$B:$B,PL_Consol!$B11)+SUMIFS(PL_FNB!E:E,PL_FNB!$B:$B,PL_Consol!$B11) -> 0 | G11: =SUMIFS(PL_Kochi!F:F,PL_Kochi!$B:$B,PL_Consol!$B11)+SUMIFS(PL_Calicut!F:F,PL_Calicut!$B:$B,PL_Consol!$B11)+SUMIFS(PL_FNB!F:F,PL_FNB!$B:$B,PL_Consol!$B11) -> 1.3048497 | H11: =SUMIFS(PL_Kochi!G:G,PL_Kochi!$B:$B,PL_Consol!$B11)+SUMIFS(PL_Calicut!G:G,PL_Calicut!$B:$B,PL_Consol!$B11)+SUMIFS(PL_FNB!G:G,PL_FNB!$B:$B,PL_Consol!$B11) -> 1.9660111 | I11: =SUMIFS(PL_Kochi!H:H,PL_Kochi!$B:$B,PL_Consol!$B11)+SUMIFS(PL_Calicut!H:H,PL_Calicut!$B:$B,PL_Consol!$B11)+SUMIFS(PL_FNB!H:H,PL_FNB!$B:$B,PL_Consol!$B11) -> 0.28107447 | J11: =SUMIFS(PL_Kochi!I:I,PL_Kochi!$B:$B,PL_Consol!$B11)+SUMIFS(PL_Calicut!I:I,PL_Calicut!$B:$B,PL_Consol!$B11)+SUMIFS(PL_FNB!I:I,PL_FNB!$B:$B,PL_Consol!$B11) -> 0.49013011 | K11: =SUMIFS(PL_Kochi!J:J,PL_Kochi!$B:$B,PL_Consol!$B11)+SUMIFS(PL_Calicut!J:J,PL_Calicut!$B:$B,PL_Consol!$B11)+SUMIFS(PL_FNB!J:J,PL_FNB!$B:$B,PL_Consol!$B11) -> 0.41512359 | L11: =SUMIFS(PL_Kochi!K:K,PL_Kochi!$B:$B,PL_Consol!$B11)+SUMIFS(PL_Calicut!K:K,PL_Calicut!$B:$B,PL_Consol!$B11)+SUMIFS(PL_FNB!K:K,PL_FNB!$B:$B,PL_Consol!$B11) -> 0.46913222 | M11: =SUMIFS(PL_Kochi!L:L,PL_Kochi!$B:$B,PL_Consol!$B11)+SUMIFS(PL_Calicut!L:L,PL_Calicut!$B:$B,PL_Consol!$B11)+SUMIFS(PL_FNB!L:L,PL_FNB!$B:$B,PL_Consol!$B11) -> 0.23805783 | N11: =SUMIFS(PL_Kochi!M:M,PL_Kochi!$B:$B,PL_Consol!$B11)+SUMIFS(PL_Calicut!M:M,PL_Calicut!$B:$B,PL_Consol!$B11)+SUMIFS(PL_FNB!M:M,PL_FNB!$B:$B,PL_Consol!$B11) -> 0.2362908 | O11: =SUMIFS(PL_Kochi!N:N,PL_Kochi!$B:$B,PL_Consol!$B11)+SUMIFS(PL_Calicut!N:N,PL_Calicut!$B:$B,PL_Consol!$B11)+SUMIFS(PL_FNB!N:N,PL_FNB!$B:$B,PL_Consol!$B11) -> 0.62416156 | P11: =SUM(D11:O11) -> 6.0248314 | Q11: 0 | R11: 0 | S11: =SUMIFS(PL_Kochi!R:R,PL_Kochi!$B:$B,PL_Consol!$B11)+SUMIFS(PL_Calicut!R:R,PL_Calicut!$B:$B,PL_Consol!$B11)+SUMIFS(PL_FNB!R:R,PL_FNB!$B:$B,PL_Consol!$B11) -> 0.061515039 | T11: =SUMIFS(PL_Kochi!$S:$S,PL_Kochi!$B:$B,PL_Consol!B11)+SUMIFS(PL_Calicut!$S:$S,PL_Calicut!$B:$B,PL_Consol!B11)+SUMIFS(PL_FNB!$S:$S,PL_FNB!$B:$B,PL_Consol!B11) -> 0.15 | U11: 0 | V11: =IFERROR(T11/E11-1,"-") -> - | W11: =IFERROR(T11/S11-1,"-") -> 1.4384281 | X11: =IFERROR(T11/U11,"-") -> -
B12: F & B Revenue | C12: 6 | D12: =SUMIFS(PL_Kochi!C:C,PL_Kochi!$B:$B,PL_Consol!$B12)+SUMIFS(PL_Calicut!C:C,PL_Calicut!$B:$B,PL_Consol!$B12)+SUMIFS(PL_FNB!C:C,PL_FNB!$B:$B,PL_Consol!$B12) -> 134.45512 | E12: =SUMIFS(PL_Kochi!D:D,PL_Kochi!$B:$B,PL_Consol!$B12)+SUMIFS(PL_Calicut!D:D,PL_Calicut!$B:$B,PL_Consol!$B12)+SUMIFS(PL_FNB!D:D,PL_FNB!$B:$B,PL_Consol!$B12) -> 142.66725 | F12: =SUMIFS(PL_Kochi!E:E,PL_Kochi!$B:$B,PL_Consol!$B12)+SUMIFS(PL_Calicut!E:E,PL_Calicut!$B:$B,PL_Consol!$B12)+SUMIFS(PL_FNB!E:E,PL_FNB!$B:$B,PL_Consol!$B12) -> 132.13448 | G12: =SUMIFS(PL_Kochi!F:F,PL_Kochi!$B:$B,PL_Consol!$B12)+SUMIFS(PL_Calicut!F:F,PL_Calicut!$B:$B,PL_Consol!$B12)+SUMIFS(PL_FNB!F:F,PL_FNB!$B:$B,PL_Consol!$B12) -> 154.33057 | H12: =SUMIFS(PL_Kochi!G:G,PL_Kochi!$B:$B,PL_Consol!$B12)+SUMIFS(PL_Calicut!G:G,PL_Calicut!$B:$B,PL_Consol!$B12)+SUMIFS(PL_FNB!G:G,PL_FNB!$B:$B,PL_Consol!$B12) -> 153.96558 | I12: =SUMIFS(PL_Kochi!H:H,PL_Kochi!$B:$B,PL_Consol!$B12)+SUMIFS(PL_Calicut!H:H,PL_Calicut!$B:$B,PL_Consol!$B12)+SUMIFS(PL_FNB!H:H,PL_FNB!$B:$B,PL_Consol!$B12) -> 148.75409 | J12: =SUMIFS(PL_Kochi!I:I,PL_Kochi!$B:$B,PL_Consol!$B12)+SUMIFS(PL_Calicut!I:I,PL_Calicut!$B:$B,PL_Consol!$B12)+SUMIFS(PL_FNB!I:I,PL_FNB!$B:$B,PL_Consol!$B12) -> 147.87833 | K12: =SUMIFS(PL_Kochi!J:J,PL_Kochi!$B:$B,PL_Consol!$B12)+SUMIFS(PL_Calicut!J:J,PL_Calicut!$B:$B,PL_Consol!$B12)+SUMIFS(PL_FNB!J:J,PL_FNB!$B:$B,PL_Consol!$B12) -> 138.58874 | L12: =SUMIFS(PL_Kochi!K:K,PL_Kochi!$B:$B,PL_Consol!$B12)+SUMIFS(PL_Calicut!K:K,PL_Calicut!$B:$B,PL_Consol!$B12)+SUMIFS(PL_FNB!K:K,PL_FNB!$B:$B,PL_Consol!$B12) -> 142.79663 | M12: =SUMIFS(PL_Kochi!L:L,PL_Kochi!$B:$B,PL_Consol!$B12)+SUMIFS(PL_Calicut!L:L,PL_Calicut!$B:$B,PL_Consol!$B12)+SUMIFS(PL_FNB!L:L,PL_FNB!$B:$B,PL_Consol!$B12) -> 156.47398 | N12: =SUMIFS(PL_Kochi!M:M,PL_Kochi!$B:$B,PL_Consol!$B12)+SUMIFS(PL_Calicut!M:M,PL_Calicut!$B:$B,PL_Consol!$B12)+SUMIFS(PL_FNB!M:M,PL_FNB!$B:$B,PL_Consol!$B12) -> 143.10076 | O12: =SUMIFS(PL_Kochi!N:N,PL_Kochi!$B:$B,PL_Consol!$B12)+SUMIFS(PL_Calicut!N:N,PL_Calicut!$B:$B,PL_Consol!$B12)+SUMIFS(PL_FNB!N:N,PL_FNB!$B:$B,PL_Consol!$B12) -> 135.02678 | P12: =SUM(D12:O12) -> 1730.1723 | Q12: 1853.3035 | R12: 1643.72 | S12: =SUMIFS(PL_Kochi!R:R,PL_Kochi!$B:$B,PL_Consol!$B12)+SUMIFS(PL_Calicut!R:R,PL_Calicut!$B:$B,PL_Consol!$B12)+SUMIFS(PL_FNB!R:R,PL_FNB!$B:$B,PL_Consol!$B12) -> 157.02992 | T12: =SUMIFS(PL_Kochi!$S:$S,PL_Kochi!$B:$B,PL_Consol!B12)+SUMIFS(PL_Calicut!$S:$S,PL_Calicut!$B:$B,PL_Consol!B12)+SUMIFS(PL_FNB!$S:$S,PL_FNB!$B:$B,PL_Consol!B12) -> 167.08431 | U12: 172.6 | V12: =IFERROR(T12/E12-1,"-") -> 0.17114691 | W12: =IFERROR(T12/S12-1,"-") -> 0.064028504 | X12: =IFERROR(T12/U12,"-") -> 0.96804354
B13: Revenue From Operation | D13: =SUM(D7:D12) -> 3344.7193 | E13: =SUM(E7:E12) -> 3672.7499 | F13: =SUM(F7:F12) -> 3306.7245 | G13: =SUM(G7:G12) -> 3901.9795 | H13: =SUM(H7:H12) -> 4009.1172 | I13: =SUM(I7:I12) -> 3930.82 | J13: =SUM(J7:J12) -> 3905.8867 | K13: =SUM(K7:K12) -> 3497.3797 | ... U13: =SUM(U7:U12) -> 4293.9573 | V13: =IFERROR(T13/E13-1,"-") -> 0.20027552 | W13: =IFERROR(T13/S13-1,"-") -> 0.042217911 | X13: =IFERROR(S13/U13,"-") -> 0.98504495
B14: Other Income | C14: 7 | D14: =SUMIFS(PL_Kochi!C:C,PL_Kochi!$B:$B,PL_Consol!$B14)+SUMIFS(PL_Calicut!C:C,PL_Calicut!$B:$B,PL_Consol!$B14)+SUMIFS(PL_FNB!C:C,PL_FNB!$B:$B,PL_Consol!$B14) -> 22.023867 | E14: =SUMIFS(PL_Kochi!D:D,PL_Kochi!$B:$B,PL_Consol!$B14)+SUMIFS(PL_Calicut!D:D,PL_Calicut!$B:$B,PL_Consol!$B14)+SUMIFS(PL_FNB!D:D,PL_FNB!$B:$B,PL_Consol!$B14) -> 69.441876 | F14: =SUMIFS(PL_Kochi!E:E,PL_Kochi!$B:$B,PL_Consol!$B14)+SUMIFS(PL_Calicut!E:E,PL_Calicut!$B:$B,PL_Consol!$B14)+SUMIFS(PL_FNB!E:E,PL_FNB!$B:$B,PL_Consol!$B14) -> 62.903433 | G14: =SUMIFS(PL_Kochi!F:F,PL_Kochi!$B:$B,PL_Consol!$B14)+SUMIFS(PL_Calicut!F:F,PL_Calicut!$B:$B,PL_Consol!$B14)+SUMIFS(PL_FNB!F:F,PL_FNB!$B:$B,PL_Consol!$B14) -> 15.475536 | H14: =SUMIFS(PL_Kochi!G:G,PL_Kochi!$B:$B,PL_Consol!$B14)+SUMIFS(PL_Calicut!G:G,PL_Calicut!$B:$B,PL_Consol!$B14)+SUMIFS(PL_FNB!G:G,PL_FNB!$B:$B,PL_Consol!$B14) -> 22.113476 | I14: =SUMIFS(PL_Kochi!H:H,PL_Kochi!$B:$B,PL_Consol!$B14)+SUMIFS(PL_Calicut!H:H,PL_Calicut!$B:$B,PL_Consol!$B14)+SUMIFS(PL_FNB!H:H,PL_FNB!$B:$B,PL_Consol!$B14) -> 25.552787 | J14: =SUMIFS(PL_Kochi!I:I,PL_Kochi!$B:$B,PL_Consol!$B14)+SUMIFS(PL_Calicut!I:I,PL_Calicut!$B:$B,PL_Consol!$B14)+SUMIFS(PL_FNB!I:I,PL_FNB!$B:$B,PL_Consol!$B14) -> 42.725339 | K14: =SUMIFS(PL_Kochi!J:J,PL_Kochi!$B:$B,PL_Consol!$B14)+SUMIFS(PL_Calicut!J:J,PL_Calicut!$B:$B,PL_Consol!$B14)+SUMIFS(PL_FNB!J:J,PL_FNB!$B:$B,PL_Consol!$B14) -> 29.650772 | L14: =SUMIFS(PL_Kochi!K:K,PL_Kochi!$B:$B,PL_Consol!$B14)+SUMIFS(PL_Calicut!K:K,PL_Calicut!$B:$B,PL_Consol!$B14)+SUMIFS(PL_FNB!K:K,PL_FNB!$B:$B,PL_Consol!$B14) -> 13.299825 | M14: =SUMIFS(PL_Kochi!L:L,PL_Kochi!$B:$B,PL_Consol!$B14)+SUMIFS(PL_Calicut!L:L,PL_Calicut!$B:$B,PL_Consol!$B14)+SUMIFS(PL_FNB!L:L,PL_FNB!$B:$B,PL_Consol!$B14) -> 50.366286 | N14: =SUMIFS(PL_Kochi!M:M,PL_Kochi!$B:$B,PL_Consol!$B14)+SUMIFS(PL_Calicut!M:M,PL_Calicut!$B:$B,PL_Consol!$B14)+SUMIFS(PL_FNB!M:M,PL_FNB!$B:$B,PL_Consol!$B14) -> 207.9737 | O14: =SUMIFS(PL_Kochi!N:N,PL_Kochi!$B:$B,PL_Consol!$B14)+SUMIFS(PL_Calicut!N:N,PL_Calicut!$B:$B,PL_Consol!$B14)+SUMIFS(PL_FNB!N:N,PL_FNB!$B:$B,PL_Consol!$B14) -> 353.06963 | P14: =SUM(D14:O14) -> 914.59653 | Q14: 498.81309 | R14: 897.75892 | S14: =SUMIFS(PL_Kochi!R:R,PL_Kochi!$B:$B,PL_Consol!$B14)+SUMIFS(PL_Calicut!R:R,PL_Calicut!$B:$B,PL_Consol!$B14)+SUMIFS(PL_FNB!R:R,PL_FNB!$B:$B,PL_Consol!$B14) -> 49.139616 | T14: =SUMIFS(PL_Kochi!$S:$S,PL_Kochi!$B:$B,PL_Consol!B14)+SUMIFS(PL_Calicut!$S:$S,PL_Calicut!$B:$B,PL_Consol!B14)+SUMIFS(PL_FNB!$S:$S,PL_FNB!$B:$B,PL_Consol!B14) -> 17.637613 | U14: 75.6 | V14: =IFERROR(T14/E14-1,"-") -> -0.74600898 | W14: =IFERROR(T14/S14-1,"-") -> -0.64107141 | X14: =IFERROR(S14/U14,"-") -> 0.64999492
B15: Total Revenue | D15: =SUM(D13:D14) -> 3366.7431 | E15: =SUM(E13:E14) -> 3742.1918 | F15: =SUM(F13:F14) -> 3369.6279 | G15: =SUM(G13:G14) -> 3917.4551 | H15: =SUM(H13:H14) -> 4031.2307 | I15: =SUM(I13:I14) -> 3956.3728 | J15: =SUM(J13:J14) -> 3948.612 | K15: =SUM(K13:K14) -> 3527.0305 | ... U15: =SUM(U13:U14) -> 4369.5573 | V15: =IFERROR(T15/E15-1,"-") -> 0.18271582 | W15: =IFERROR(T15/S15-1,"-") -> 0.034370864 | X15: =IFERROR(S15/U15,"-") -> 0.97924808
V16: =IFERROR(S16/D16-1,"-") -> - | W16: =IFERROR(S16/O16-1,"-") -> - | X16: =IFERROR(S16/U16,"-") -> -
B17: Material Cost | C17: 8 | D17: =SUMIFS(PL_Kochi!C:C,PL_Kochi!$B:$B,PL_Consol!$B17)+SUMIFS(PL_Calicut!C:C,PL_Calicut!$B:$B,PL_Consol!$B17)+SUMIFS(PL_FNB!C:C,PL_FNB!$B:$B,PL_Consol!$B17) -> 865.38086 | E17: =SUMIFS(PL_Kochi!D:D,PL_Kochi!$B:$B,PL_Consol!$B17)+SUMIFS(PL_Calicut!D:D,PL_Calicut!$B:$B,PL_Consol!$B17)+SUMIFS(PL_FNB!D:D,PL_FNB!$B:$B,PL_Consol!$B17) -> 1147.3681 | F17: =SUMIFS(PL_Kochi!E:E,PL_Kochi!$B:$B,PL_Consol!$B17)+SUMIFS(PL_Calicut!E:E,PL_Calicut!$B:$B,PL_Consol!$B17)+SUMIFS(PL_FNB!E:E,PL_FNB!$B:$B,PL_Consol!$B17) -> 1121.87 | G17: =SUMIFS(PL_Kochi!F:F,PL_Kochi!$B:$B,PL_Consol!$B17)+SUMIFS(PL_Calicut!F:F,PL_Calicut!$B:$B,PL_Consol!$B17)+SUMIFS(PL_FNB!F:F,PL_FNB!$B:$B,PL_Consol!$B17) -> 1278.5375 | H17: =SUMIFS(PL_Kochi!G:G,PL_Kochi!$B:$B,PL_Consol!$B17)+SUMIFS(PL_Calicut!G:G,PL_Calicut!$B:$B,PL_Consol!$B17)+SUMIFS(PL_FNB!G:G,PL_FNB!$B:$B,PL_Consol!$B17) -> 1221.3064 | I17: =SUMIFS(PL_Kochi!H:H,PL_Kochi!$B:$B,PL_Consol!$B17)+SUMIFS(PL_Calicut!H:H,PL_Calicut!$B:$B,PL_Consol!$B17)+SUMIFS(PL_FNB!H:H,PL_FNB!$B:$B,PL_Consol!$B17) -> 1161.3552 | J17: =SUMIFS(PL_Kochi!I:I,PL_Kochi!$B:$B,PL_Consol!$B17)+SUMIFS(PL_Calicut!I:I,PL_Calicut!$B:$B,PL_Consol!$B17)+SUMIFS(PL_FNB!I:I,PL_FNB!$B:$B,PL_Consol!$B17) -> 1229.9506 | K17: =SUMIFS(PL_Kochi!J:J,PL_Kochi!$B:$B,PL_Consol!$B17)+SUMIFS(PL_Calicut!J:J,PL_Calicut!$B:$B,PL_Consol!$B17)+SUMIFS(PL_FNB!J:J,PL_FNB!$B:$B,PL_Consol!$B17) -> 1081.0936 | L17: =SUMIFS(PL_Kochi!K:K,PL_Kochi!$B:$B,PL_Consol!$B17)+SUMIFS(PL_Calicut!K:K,PL_Calicut!$B:$B,PL_Consol!$B17)+SUMIFS(PL_FNB!K:K,PL_FNB!$B:$B,PL_Consol!$B17) -> 1154.1166 | M17: =SUMIFS(PL_Kochi!L:L,PL_Kochi!$B:$B,PL_Consol!$B17)+SUMIFS(PL_Calicut!L:L,PL_Calicut!$B:$B,PL_Consol!$B17)+SUMIFS(PL_FNB!L:L,PL_FNB!$B:$B,PL_Consol!$B17) -> 1242.8874 | N17: =SUMIFS(PL_Kochi!M:M,PL_Kochi!$B:$B,PL_Consol!$B17)+SUMIFS(PL_Calicut!M:M,PL_Calicut!$B:$B,PL_Consol!$B17)+SUMIFS(PL_FNB!M:M,PL_FNB!$B:$B,PL_Consol!$B17) -> 1171.5098 | O17: =SUMIFS(PL_Kochi!N:N,PL_Kochi!$B:$B,PL_Consol!$B17)+SUMIFS(PL_Calicut!N:N,PL_Calicut!$B:$B,PL_Consol!$B17)+SUMIFS(PL_FNB!N:N,PL_FNB!$B:$B,PL_Consol!$B17) -> 1050.0197 | P17: =SUM(D17:O17) -> 13725.396 | Q17: 13960.301 | R17: 12513.66 | S17: =SUMIFS(PL_Kochi!R:R,PL_Kochi!$B:$B,PL_Consol!$B17)+SUMIFS(PL_Calicut!R:R,PL_Calicut!$B:$B,PL_Consol!$B17)+SUMIFS(PL_FNB!R:R,PL_FNB!$B:$B,PL_Consol!$B17) -> 1246.2882 | T17: =SUMIFS(PL_Kochi!S:S,PL_Kochi!$B:$B,PL_Consol!$B17)+SUMIFS(PL_Calicut!S:S,PL_Calicut!$B:$B,PL_Consol!$B17)+SUMIFS(PL_FNB!S:S,PL_FNB!$B:$B,PL_Consol!$B17) -> 1344.9625 | U17: 1179.8 | V17: =IFERROR(T17/E17-1,"-") -> 0.17221537 | W17: =IFERROR(T17/S17-1,"-") -> 0.079174623 | X17: =IFERROR(S17/U17,"-") -> 1.0563554
B18: Doctor Cost | C18: 9 | D18: =SUMIFS(PL_Kochi!C:C,PL_Kochi!$B:$B,PL_Consol!$B18)+SUMIFS(PL_Calicut!C:C,PL_Calicut!$B:$B,PL_Consol!$B18)+SUMIFS(PL_FNB!C:C,PL_FNB!$B:$B,PL_Consol!$B18) -> 625.32472 | E18: =SUMIFS(PL_Kochi!D:D,PL_Kochi!$B:$B,PL_Consol!$B18)+SUMIFS(PL_Calicut!D:D,PL_Calicut!$B:$B,PL_Consol!$B18)+SUMIFS(PL_FNB!D:D,PL_FNB!$B:$B,PL_Consol!$B18) -> 633.17885 | F18: =SUMIFS(PL_Kochi!E:E,PL_Kochi!$B:$B,PL_Consol!$B18)+SUMIFS(PL_Calicut!E:E,PL_Calicut!$B:$B,PL_Consol!$B18)+SUMIFS(PL_FNB!E:E,PL_FNB!$B:$B,PL_Consol!$B18) -> 615.54412 | G18: =SUMIFS(PL_Kochi!F:F,PL_Kochi!$B:$B,PL_Consol!$B18)+SUMIFS(PL_Calicut!F:F,PL_Calicut!$B:$B,PL_Consol!$B18)+SUMIFS(PL_FNB!F:F,PL_FNB!$B:$B,PL_Consol!$B18) -> 671.81447 | H18: =SUMIFS(PL_Kochi!G:G,PL_Kochi!$B:$B,PL_Consol!$B18)+SUMIFS(PL_Calicut!G:G,PL_Calicut!$B:$B,PL_Consol!$B18)+SUMIFS(PL_FNB!G:G,PL_FNB!$B:$B,PL_Consol!$B18) -> 672.78128 | I18: =SUMIFS(PL_Kochi!H:H,PL_Kochi!$B:$B,PL_Consol!$B18)+SUMIFS(PL_Calicut!H:H,PL_Calicut!$B:$B,PL_Consol!$B18)+SUMIFS(PL_FNB!H:H,PL_FNB!$B:$B,PL_Consol!$B18) -> 676.88154 | J18: =SUMIFS(PL_Kochi!I:I,PL_Kochi!$B:$B,PL_Consol!$B18)+SUMIFS(PL_Calicut!I:I,PL_Calicut!$B:$B,PL_Consol!$B18)+SUMIFS(PL_FNB!I:I,PL_FNB!$B:$B,PL_Consol!$B18) -> 654.77264 | K18: =SUMIFS(PL_Kochi!J:J,PL_Kochi!$B:$B,PL_Consol!$B18)+SUMIFS(PL_Calicut!J:J,PL_Calicut!$B:$B,PL_Consol!$B18)+SUMIFS(PL_FNB!J:J,PL_FNB!$B:$B,PL_Consol!$B18) -> 662.30433 | L18: =SUMIFS(PL_Kochi!K:K,PL_Kochi!$B:$B,PL_Consol!$B18)+SUMIFS(PL_Calicut!K:K,PL_Calicut!$B:$B,PL_Consol!$B18)+SUMIFS(PL_FNB!K:K,PL_FNB!$B:$B,PL_Consol!$B18) -> 689.30664 | M18: =SUMIFS(PL_Kochi!L:L,PL_Kochi!$B:$B,PL_Consol!$B18)+SUMIFS(PL_Calicut!L:L,PL_Calicut!$B:$B,PL_Consol!$B18)+SUMIFS(PL_FNB!L:L,PL_FNB!$B:$B,PL_Consol!$B18) -> 699.5981 | N18: =SUMIFS(PL_Kochi!M:M,PL_Kochi!$B:$B,PL_Consol!$B18)+SUMIFS(PL_Calicut!M:M,PL_Calicut!$B:$B,PL_Consol!$B18)+SUMIFS(PL_FNB!M:M,PL_FNB!$B:$B,PL_Consol!$B18) -> 683.83619 | O18: =SUMIFS(PL_Kochi!N:N,PL_Kochi!$B:$B,PL_Consol!$B18)+SUMIFS(PL_Calicut!N:N,PL_Calicut!$B:$B,PL_Consol!$B18)+SUMIFS(PL_FNB!N:N,PL_FNB!$B:$B,PL_Consol!$B18) -> 699.42364 | P18: =SUM(D18:O18) -> 7984.7665 | Q18: 9779.2563 | R18: 7546.99 | S18: =SUMIFS(PL_Kochi!R:R,PL_Kochi!$B:$B,PL_Consol!$B18)+SUMIFS(PL_Calicut!R:R,PL_Calicut!$B:$B,PL_Consol!$B18)+SUMIFS(PL_FNB!R:R,PL_FNB!$B:$B,PL_Consol!$B18) -> 715.16936 | T18: =SUMIFS(PL_Kochi!S:S,PL_Kochi!$B:$B,PL_Consol!$B18)+SUMIFS(PL_Calicut!S:S,PL_Calicut!$B:$B,PL_Consol!$B18)+SUMIFS(PL_FNB!S:S,PL_FNB!$B:$B,PL_Consol!$B18) -> 692.59426 | U18: 736 | V18: =IFERROR(T18/E18-1,"-") -> 0.093836693 | W18: =IFERROR(T18/S18-1,"-") -> -0.031566088 | X18: =IFERROR(S18/U18,"-") -> 0.9716975
B19: Employee Cost | C19: 10 | D19: =SUMIFS(PL_Kochi!C:C,PL_Kochi!$B:$B,PL_Consol!$B19)+SUMIFS(PL_Calicut!C:C,PL_Calicut!$B:$B,PL_Consol!$B19)+SUMIFS(PL_FNB!C:C,PL_FNB!$B:$B,PL_Consol!$B19) -> 554.73431 | E19: =SUMIFS(PL_Kochi!D:D,PL_Kochi!$B:$B,PL_Consol!$B19)+SUMIFS(PL_Calicut!D:D,PL_Calicut!$B:$B,PL_Consol!$B19)+SUMIFS(PL_FNB!D:D,PL_FNB!$B:$B,PL_Consol!$B19) -> 628.21321 | F19: =SUMIFS(PL_Kochi!E:E,PL_Kochi!$B:$B,PL_Consol!$B19)+SUMIFS(PL_Calicut!E:E,PL_Calicut!$B:$B,PL_Consol!$B19)+SUMIFS(PL_FNB!E:E,PL_FNB!$B:$B,PL_Consol!$B19) -> 617.87253 | G19: =SUMIFS(PL_Kochi!F:F,PL_Kochi!$B:$B,PL_Consol!$B19)+SUMIFS(PL_Calicut!F:F,PL_Calicut!$B:$B,PL_Consol!$B19)+SUMIFS(PL_FNB!F:F,PL_FNB!$B:$B,PL_Consol!$B19) -> 628.60267 | H19: =SUMIFS(PL_Kochi!G:G,PL_Kochi!$B:$B,PL_Consol!$B19)+SUMIFS(PL_Calicut!G:G,PL_Calicut!$B:$B,PL_Consol!$B19)+SUMIFS(PL_FNB!G:G,PL_FNB!$B:$B,PL_Consol!$B19) -> 622.55297 | I19: =SUMIFS(PL_Kochi!H:H,PL_Kochi!$B:$B,PL_Consol!$B19)+SUMIFS(PL_Calicut!H:H,PL_Calicut!$B:$B,PL_Consol!$B19)+SUMIFS(PL_FNB!H:H,PL_FNB!$B:$B,PL_Consol!$B19) -> 681.43864 | J19: =SUMIFS(PL_Kochi!I:I,PL_Kochi!$B:$B,PL_Consol!$B19)+SUMIFS(PL_Calicut!I:I,PL_Calicut!$B:$B,PL_Consol!$B19)+SUMIFS(PL_FNB!I:I,PL_FNB!$B:$B,PL_Consol!$B19) -> 645.91964 | K19: =SUMIFS(PL_Kochi!J:J,PL_Kochi!$B:$B,PL_Consol!$B19)+SUMIFS(PL_Calicut!J:J,PL_Calicut!$B:$B,PL_Consol!$B19)+SUMIFS(PL_FNB!J:J,PL_FNB!$B:$B,PL_Consol!$B19) -> 596.10196 | L19: =SUMIFS(PL_Kochi!K:K,PL_Kochi!$B:$B,PL_Consol!$B19)+SUMIFS(PL_Calicut!K:K,PL_Calicut!$B:$B,PL_Consol!$B19)+SUMIFS(PL_FNB!K:K,PL_FNB!$B:$B,PL_Consol!$B19) -> 620.42651 | M19: =SUMIFS(PL_Kochi!L:L,PL_Kochi!$B:$B,PL_Consol!$B19)+SUMIFS(PL_Calicut!L:L,PL_Calicut!$B:$B,PL_Consol!$B19)+SUMIFS(PL_FNB!L:L,PL_FNB!$B:$B,PL_Consol!$B19) -> 609.70921 | N19: =SUMIFS(PL_Kochi!M:M,PL_Kochi!$B:$B,PL_Consol!$B19)+SUMIFS(PL_Calicut!M:M,PL_Calicut!$B:$B,PL_Consol!$B19)+SUMIFS(PL_FNB!M:M,PL_FNB!$B:$B,PL_Consol!$B19) -> 642.58791 | O19: =SUMIFS(PL_Kochi!N:N,PL_Kochi!$B:$B,PL_Consol!$B19)+SUMIFS(PL_Calicut!N:N,PL_Calicut!$B:$B,PL_Consol!$B19)+SUMIFS(PL_FNB!N:N,PL_FNB!$B:$B,PL_Consol!$B19) -> 668.03247 | P19: =SUM(D19:O19) -> 7516.192 | Q19: 10174.401 | R19: 7400.74 | S19: =SUMIFS(PL_Kochi!R:R,PL_Kochi!$B:$B,PL_Consol!$B19)+SUMIFS(PL_Calicut!R:R,PL_Calicut!$B:$B,PL_Consol!$B19)+SUMIFS(PL_FNB!R:R,PL_FNB!$B:$B,PL_Consol!$B19) -> 658.26274 | T19: =SUMIFS(PL_Kochi!S:S,PL_Kochi!$B:$B,PL_Consol!$B19)+SUMIFS(PL_Calicut!S:S,PL_Calicut!$B:$B,PL_Consol!$B19)+SUMIFS(PL_FNB!S:S,PL_FNB!$B:$B,PL_Consol!$B19) -> 659.87997 | U19: 785.9 | V19: =IFERROR(T19/E19-1,"-") -> 0.050407666 | W19: =IFERROR(T19/S19-1,"-") -> 0.0024568175 | X19: =IFERROR(S19/U19,"-") -> 0.83759097
B20: Utilities-Power, fuel & water charges | C20: 11 | D20: =SUMIFS(PL_Kochi!C:C,PL_Kochi!$B:$B,PL_Consol!$B20)+SUMIFS(PL_Calicut!C:C,PL_Calicut!$B:$B,PL_Consol!$B20)+SUMIFS(PL_FNB!C:C,PL_FNB!$B:$B,PL_Consol!$B20) -> 89.079465 | E20: =SUMIFS(PL_Kochi!D:D,PL_Kochi!$B:$B,PL_Consol!$B20)+SUMIFS(PL_Calicut!D:D,PL_Calicut!$B:$B,PL_Consol!$B20)+SUMIFS(PL_FNB!D:D,PL_FNB!$B:$B,PL_Consol!$B20) -> 95.752945 | F20: =SUMIFS(PL_Kochi!E:E,PL_Kochi!$B:$B,PL_Consol!$B20)+SUMIFS(PL_Calicut!E:E,PL_Calicut!$B:$B,PL_Consol!$B20)+SUMIFS(PL_FNB!E:E,PL_FNB!$B:$B,PL_Consol!$B20) -> 105.11128 | G20: =SUMIFS(PL_Kochi!F:F,PL_Kochi!$B:$B,PL_Consol!$B20)+SUMIFS(PL_Calicut!F:F,PL_Calicut!$B:$B,PL_Consol!$B20)+SUMIFS(PL_FNB!F:F,PL_FNB!$B:$B,PL_Consol!$B20) -> 97.919884 | H20: =SUMIFS(PL_Kochi!G:G,PL_Kochi!$B:$B,PL_Consol!$B20)+SUMIFS(PL_Calicut!G:G,PL_Calicut!$B:$B,PL_Consol!$B20)+SUMIFS(PL_FNB!G:G,PL_FNB!$B:$B,PL_Consol!$B20) -> 91.137033 | I20: =SUMIFS(PL_Kochi!H:H,PL_Kochi!$B:$B,PL_Consol!$B20)+SUMIFS(PL_Calicut!H:H,PL_Calicut!$B:$B,PL_Consol!$B20)+SUMIFS(PL_FNB!H:H,PL_FNB!$B:$B,PL_Consol!$B20) -> 97.924134 | J20: =SUMIFS(PL_Kochi!I:I,PL_Kochi!$B:$B,PL_Consol!$B20)+SUMIFS(PL_Calicut!I:I,PL_Calicut!$B:$B,PL_Consol!$B20)+SUMIFS(PL_FNB!I:I,PL_FNB!$B:$B,PL_Consol!$B20) -> 109.33022 | K20: =SUMIFS(PL_Kochi!J:J,PL_Kochi!$B:$B,PL_Consol!$B20)+SUMIFS(PL_Calicut!J:J,PL_Calicut!$B:$B,PL_Consol!$B20)+SUMIFS(PL_FNB!J:J,PL_FNB!$B:$B,PL_Consol!$B20) -> 88.771923 | L20: =SUMIFS(PL_Kochi!K:K,PL_Kochi!$B:$B,PL_Consol!$B20)+SUMIFS(PL_Calicut!K:K,PL_Calicut!$B:$B,PL_Consol!$B20)+SUMIFS(PL_FNB!K:K,PL_FNB!$B:$B,PL_Consol!$B20) -> 98.77479 | M20: =SUMIFS(PL_Kochi!L:L,PL_Kochi!$B:$B,PL_Consol!$B20)+SUMIFS(PL_Calicut!L:L,PL_Calicut!$B:$B,PL_Consol!$B20)+SUMIFS(PL_FNB!L:L,PL_FNB!$B:$B,PL_Consol!$B20) -> 105.06447 | N20: =SUMIFS(PL_Kochi!M:M,PL_Kochi!$B:$B,PL_Consol!$B20)+SUMIFS(PL_Calicut!M:M,PL_Calicut!$B:$B,PL_Consol!$B20)+SUMIFS(PL_FNB!M:M,PL_FNB!$B:$B,PL_Consol!$B20) -> 91.249222 | O20: =SUMIFS(PL_Kochi!N:N,PL_Kochi!$B:$B,PL_Consol!$B20)+SUMIFS(PL_Calicut!N:N,PL_Calicut!$B:$B,PL_Consol!$B20)+SUMIFS(PL_FNB!N:N,PL_FNB!$B:$B,PL_Consol!$B20) -> 122.10168 | P20: =SUM(D20:O20) -> 1192.217 | Q20: 1306.9786 | R20: 1245.62 | S20: =SUMIFS(PL_Kochi!R:R,PL_Kochi!$B:$B,PL_Consol!$B20)+SUMIFS(PL_Calicut!R:R,PL_Calicut!$B:$B,PL_Consol!$B20)+SUMIFS(PL_FNB!R:R,PL_FNB!$B:$B,PL_Consol!$B20) -> 108.91587 | T20: =SUMIFS(PL_Kochi!S:S,PL_Kochi!$B:$B,PL_Consol!$B20)+SUMIFS(PL_Calicut!S:S,PL_Calicut!$B:$B,PL_Consol!$B20)+SUMIFS(PL_FNB!S:S,PL_FNB!$B:$B,PL_Consol!$B20) -> 104.62286 | U20: 119.4 | V20: =IFERROR(T20/E20-1,"-") -> 0.092633348 | W20: =IFERROR(T20/S20-1,"-") -> -0.039415816 | X20: =IFERROR(S20/U20,"-") -> 0.91219321
B21: Repair & Maintenance | C21: 12 | D21: =SUMIFS(PL_Kochi!C:C,PL_Kochi!$B:$B,PL_Consol!$B21)+SUMIFS(PL_Calicut!C:C,PL_Calicut!$B:$B,PL_Consol!$B21)+SUMIFS(PL_FNB!C:C,PL_FNB!$B:$B,PL_Consol!$B21) -> 71.970159 | E21: =SUMIFS(PL_Kochi!D:D,PL_Kochi!$B:$B,PL_Consol!$B21)+SUMIFS(PL_Calicut!D:D,PL_Calicut!$B:$B,PL_Consol!$B21)+SUMIFS(PL_FNB!D:D,PL_FNB!$B:$B,PL_Consol!$B21) -> 88.984337 | F21: =SUMIFS(PL_Kochi!E:E,PL_Kochi!$B:$B,PL_Consol!$B21)+SUMIFS(PL_Calicut!E:E,PL_Calicut!$B:$B,PL_Consol!$B21)+SUMIFS(PL_FNB!E:E,PL_FNB!$B:$B,PL_Consol!$B21) -> 124.64797 | G21: =SUMIFS(PL_Kochi!F:F,PL_Kochi!$B:$B,PL_Consol!$B21)+SUMIFS(PL_Calicut!F:F,PL_Calicut!$B:$B,PL_Consol!$B21)+SUMIFS(PL_FNB!F:F,PL_FNB!$B:$B,PL_Consol!$B21) -> 125.7808 | H21: =SUMIFS(PL_Kochi!G:G,PL_Kochi!$B:$B,PL_Consol!$B21)+SUMIFS(PL_Calicut!G:G,PL_Calicut!$B:$B,PL_Consol!$B21)+SUMIFS(PL_FNB!G:G,PL_FNB!$B:$B,PL_Consol!$B21) -> 138.05387 | I21: =SUMIFS(PL_Kochi!H:H,PL_Kochi!$B:$B,PL_Consol!$B21)+SUMIFS(PL_Calicut!H:H,PL_Calicut!$B:$B,PL_Consol!$B21)+SUMIFS(PL_FNB!H:H,PL_FNB!$B:$B,PL_Consol!$B21) -> 153.57039 | J21: =SUMIFS(PL_Kochi!I:I,PL_Kochi!$B:$B,PL_Consol!$B21)+SUMIFS(PL_Calicut!I:I,PL_Calicut!$B:$B,PL_Consol!$B21)+SUMIFS(PL_FNB!I:I,PL_FNB!$B:$B,PL_Consol!$B21) -> 160.26832 | K21: =SUMIFS(PL_Kochi!J:J,PL_Kochi!$B:$B,PL_Consol!$B21)+SUMIFS(PL_Calicut!J:J,PL_Calicut!$B:$B,PL_Consol!$B21)+SUMIFS(PL_FNB!J:J,PL_FNB!$B:$B,PL_Consol!$B21) -> 129.30591 | L21: =SUMIFS(PL_Kochi!K:K,PL_Kochi!$B:$B,PL_Consol!$B21)+SUMIFS(PL_Calicut!K:K,PL_Calicut!$B:$B,PL_Consol!$B21)+SUMIFS(PL_FNB!K:K,PL_FNB!$B:$B,PL_Consol!$B21) -> 100.64707 | M21: =SUMIFS(PL_Kochi!L:L,PL_Kochi!$B:$B,PL_Consol!$B21)+SUMIFS(PL_Calicut!L:L,PL_Calicut!$B:$B,PL_Consol!$B21)+SUMIFS(PL_FNB!L:L,PL_FNB!$B:$B,PL_Consol!$B21) -> 90.417465 | N21: =SUMIFS(PL_Kochi!M:M,PL_Kochi!$B:$B,PL_Consol!$B21)+SUMIFS(PL_Calicut!M:M,PL_Calicut!$B:$B,PL_Consol!$B21)+SUMIFS(PL_FNB!M:M,PL_FNB!$B:$B,PL_Consol!$B21) -> 190.35786 | O21: =SUMIFS(PL_Kochi!N:N,PL_Kochi!$B:$B,PL_Consol!$B21)+SUMIFS(PL_Calicut!N:N,PL_Calicut!$B:$B,PL_Consol!$B21)+SUMIFS(PL_FNB!N:N,PL_FNB!$B:$B,PL_Consol!$B21) -> 186.61879 | P21: =SUM(D21:O21) -> 1560.623 | Q21: 1275.5024 | R21: 1328.28 | S21: =SUMIFS(PL_Kochi!R:R,PL_Kochi!$B:$B,PL_Consol!$B21)+SUMIFS(PL_Calicut!R:R,PL_Calicut!$B:$B,PL_Consol!$B21)+SUMIFS(PL_FNB!R:R,PL_FNB!$B:$B,PL_Consol!$B21) -> 114.68122 | T21: =SUMIFS(PL_Kochi!S:S,PL_Kochi!$B:$B,PL_Consol!$B21)+SUMIFS(PL_Calicut!S:S,PL_Calicut!$B:$B,PL_Consol!$B21)+SUMIFS(PL_FNB!S:S,PL_FNB!$B:$B,PL_Consol!$B21) -> 79.364062 | U21: 23.4 | V21: =IFERROR(T21/E21-1,"-") -> -0.108112 | W21: =IFERROR(T21/S21-1,"-") -> -0.30795939 | X21: =IFERROR(S21/U21,"-") -> 4.9009069
B22: Marketing Cost | C22: 13 | D22: =SUMIFS(PL_Kochi!C:C,PL_Kochi!$B:$B,PL_Consol!$B22)+SUMIFS(PL_Calicut!C:C,PL_Calicut!$B:$B,PL_Consol!$B22)+SUMIFS(PL_FNB!C:C,PL_FNB!$B:$B,PL_Consol!$B22) -> 79.802357 | E22: =SUMIFS(PL_Kochi!D:D,PL_Kochi!$B:$B,PL_Consol!$B22)+SUMIFS(PL_Calicut!D:D,PL_Calicut!$B:$B,PL_Consol!$B22)+SUMIFS(PL_FNB!D:D,PL_FNB!$B:$B,PL_Consol!$B22) -> 57.816802 | F22: =SUMIFS(PL_Kochi!E:E,PL_Kochi!$B:$B,PL_Consol!$B22)+SUMIFS(PL_Calicut!E:E,PL_Calicut!$B:$B,PL_Consol!$B22)+SUMIFS(PL_FNB!E:E,PL_FNB!$B:$B,PL_Consol!$B22) -> 59.621195 | G22: =SUMIFS(PL_Kochi!F:F,PL_Kochi!$B:$B,PL_Consol!$B22)+SUMIFS(PL_Calicut!F:F,PL_Calicut!$B:$B,PL_Consol!$B22)+SUMIFS(PL_FNB!F:F,PL_FNB!$B:$B,PL_Consol!$B22) -> 50.836791 | H22: =SUMIFS(PL_Kochi!G:G,PL_Kochi!$B:$B,PL_Consol!$B22)+SUMIFS(PL_Calicut!G:G,PL_Calicut!$B:$B,PL_Consol!$B22)+SUMIFS(PL_FNB!G:G,PL_FNB!$B:$B,PL_Consol!$B22) -> 66.430517 | I22: =SUMIFS(PL_Kochi!H:H,PL_Kochi!$B:$B,PL_Consol!$B22)+SUMIFS(PL_Calicut!H:H,PL_Calicut!$B:$B,PL_Consol!$B22)+SUMIFS(PL_FNB!H:H,PL_FNB!$B:$B,PL_Consol!$B22) -> 84.857807 | J22: =SUMIFS(PL_Kochi!I:I,PL_Kochi!$B:$B,PL_Consol!$B22)+SUMIFS(PL_Calicut!I:I,PL_Calicut!$B:$B,PL_Consol!$B22)+SUMIFS(PL_FNB!I:I,PL_FNB!$B:$B,PL_Consol!$B22) -> 81.86046 | K22: =SUMIFS(PL_Kochi!J:J,PL_Kochi!$B:$B,PL_Consol!$B22)+SUMIFS(PL_Calicut!J:J,PL_Calicut!$B:$B,PL_Consol!$B22)+SUMIFS(PL_FNB!J:J,PL_FNB!$B:$B,PL_Consol!$B22) -> 71.772029 | L22: =SUMIFS(PL_Kochi!K:K,PL_Kochi!$B:$B,PL_Consol!$B22)+SUMIFS(PL_Calicut!K:K,PL_Calicut!$B:$B,PL_Consol!$B22)+SUMIFS(PL_FNB!K:K,PL_FNB!$B:$B,PL_Consol!$B22) -> 77.663979 | M22: =SUMIFS(PL_Kochi!L:L,PL_Kochi!$B:$B,PL_Consol!$B22)+SUMIFS(PL_Calicut!L:L,PL_Calicut!$B:$B,PL_Consol!$B22)+SUMIFS(PL_FNB!L:L,PL_FNB!$B:$B,PL_Consol!$B22) -> 74.179736 | N22: =SUMIFS(PL_Kochi!M:M,PL_Kochi!$B:$B,PL_Consol!$B22)+SUMIFS(PL_Calicut!M:M,PL_Calicut!$B:$B,PL_Consol!$B22)+SUMIFS(PL_FNB!M:M,PL_FNB!$B:$B,PL_Consol!$B22) -> 111.7871 | O22: =SUMIFS(PL_Kochi!N:N,PL_Kochi!$B:$B,PL_Consol!$B22)+SUMIFS(PL_Calicut!N:N,PL_Calicut!$B:$B,PL_Consol!$B22)+SUMIFS(PL_FNB!N:N,PL_FNB!$B:$B,PL_Consol!$B22) -> 63.518614 | P22: =SUM(D22:O22) -> 880.14738 | Q22: 1209.9732 | R22: 703.25 | S22: =SUMIFS(PL_Kochi!R:R,PL_Kochi!$B:$B,PL_Consol!$B22)+SUMIFS(PL_Calicut!R:R,PL_Calicut!$B:$B,PL_Consol!$B22)+SUMIFS(PL_FNB!R:R,PL_FNB!$B:$B,PL_Consol!$B22) -> 72.019957 | T22: =SUMIFS(PL_Kochi!S:S,PL_Kochi!$B:$B,PL_Consol!$B22)+SUMIFS(PL_Calicut!S:S,PL_Calicut!$B:$B,PL_Consol!$B22)+SUMIFS(PL_FNB!S:S,PL_FNB!$B:$B,PL_Consol!$B22) -> 51.2846 | U22: 17.4 | V22: =IFERROR(T22/E22-1,"-") -> -0.11298103 | W22: =IFERROR(T22/S22-1,"-") -> -0.28791126 | X22: =IFERROR(S22/U22,"-") -> 4.139078
B23: Lab Test Charges | C23: 14 | D23: =SUMIFS(PL_Kochi!C:C,PL_Kochi!$B:$B,PL_Consol!$B23)+SUMIFS(PL_Calicut!C:C,PL_Calicut!$B:$B,PL_Consol!$B23)+SUMIFS(PL_FNB!C:C,PL_FNB!$B:$B,PL_Consol!$B23) -> 16.785611 | E23: =SUMIFS(PL_Kochi!D:D,PL_Kochi!$B:$B,PL_Consol!$B23)+SUMIFS(PL_Calicut!D:D,PL_Calicut!$B:$B,PL_Consol!$B23)+SUMIFS(PL_FNB!D:D,PL_FNB!$B:$B,PL_Consol!$B23) -> 18.615196 | F23: =SUMIFS(PL_Kochi!E:E,PL_Kochi!$B:$B,PL_Consol!$B23)+SUMIFS(PL_Calicut!E:E,PL_Calicut!$B:$B,PL_Consol!$B23)+SUMIFS(PL_FNB!E:E,PL_FNB!$B:$B,PL_Consol!$B23) -> 21.438936 | G23: =SUMIFS(PL_Kochi!F:F,PL_Kochi!$B:$B,PL_Consol!$B23)+SUMIFS(PL_Calicut!F:F,PL_Calicut!$B:$B,PL_Consol!$B23)+SUMIFS(PL_FNB!F:F,PL_FNB!$B:$B,PL_Consol!$B23) -> 18.376415 | H23: =SUMIFS(PL_Kochi!G:G,PL_Kochi!$B:$B,PL_Consol!$B23)+SUMIFS(PL_Calicut!G:G,PL_Calicut!$B:$B,PL_Consol!$B23)+SUMIFS(PL_FNB!G:G,PL_FNB!$B:$B,PL_Consol!$B23) -> 26.549782 | I23: =SUMIFS(PL_Kochi!H:H,PL_Kochi!$B:$B,PL_Consol!$B23)+SUMIFS(PL_Calicut!H:H,PL_Calicut!$B:$B,PL_Consol!$B23)+SUMIFS(PL_FNB!H:H,PL_FNB!$B:$B,PL_Consol!$B23) -> 16.773704 | J23: =SUMIFS(PL_Kochi!I:I,PL_Kochi!$B:$B,PL_Consol!$B23)+SUMIFS(PL_Calicut!I:I,PL_Calicut!$B:$B,PL_Consol!$B23)+SUMIFS(PL_FNB!I:I,PL_FNB!$B:$B,PL_Consol!$B23) -> 22.79036 | K23: =SUMIFS(PL_Kochi!J:J,PL_Kochi!$B:$B,PL_Consol!$B23)+SUMIFS(PL_Calicut!J:J,PL_Calicut!$B:$B,PL_Consol!$B23)+SUMIFS(PL_FNB!J:J,PL_FNB!$B:$B,PL_Consol!$B23) -> 9.2216255 | L23: =SUMIFS(PL_Kochi!K:K,PL_Kochi!$B:$B,PL_Consol!$B23)+SUMIFS(PL_Calicut!K:K,PL_Calicut!$B:$B,PL_Consol!$B23)+SUMIFS(PL_FNB!K:K,PL_FNB!$B:$B,PL_Consol!$B23) -> 37.627735 | M23: =SUMIFS(PL_Kochi!L:L,PL_Kochi!$B:$B,PL_Consol!$B23)+SUMIFS(PL_Calicut!L:L,PL_Calicut!$B:$B,PL_Consol!$B23)+SUMIFS(PL_FNB!L:L,PL_FNB!$B:$B,PL_Consol!$B23) -> 30.08253 | N23: =SUMIFS(PL_Kochi!M:M,PL_Kochi!$B:$B,PL_Consol!$B23)+SUMIFS(PL_Calicut!M:M,PL_Calicut!$B:$B,PL_Consol!$B23)+SUMIFS(PL_FNB!M:M,PL_FNB!$B:$B,PL_Consol!$B23) -> 27.391808 | O23: =SUMIFS(PL_Kochi!N:N,PL_Kochi!$B:$B,PL_Consol!$B23)+SUMIFS(PL_Calicut!N:N,PL_Calicut!$B:$B,PL_Consol!$B23)+SUMIFS(PL_FNB!N:N,PL_FNB!$B:$B,PL_Consol!$B23) -> 22.111633 | P23: =SUM(D23:O23) -> 267.76534 | Q23: 274.99371 | R23: 237.77 | S23: =SUMIFS(PL_Kochi!R:R,PL_Kochi!$B:$B,PL_Consol!$B23)+SUMIFS(PL_Calicut!R:R,PL_Calicut!$B:$B,PL_Consol!$B23)+SUMIFS(PL_FNB!R:R,PL_FNB!$B:$B,PL_Consol!$B23) -> 24.101609 | T23: =SUMIFS(PL_Kochi!S:S,PL_Kochi!$B:$B,PL_Consol!$B23)+SUMIFS(PL_Calicut!S:S,PL_Calicut!$B:$B,PL_Consol!$B23)+SUMIFS(PL_FNB!S:S,PL_FNB!$B:$B,PL_Consol!$B23) -> 29.50202 | U23: 136.3 | V23: =IFERROR(T23/E23-1,"-") -> 0.58483528 | W23: =IFERROR(T23/S23-1,"-") -> 0.22406847 | X23: =IFERROR(S23/U23,"-") -> 0.17682765
B24: Rent Paid | C24: 15 | D24: =SUMIFS(PL_Kochi!C:C,PL_Kochi!$B:$B,PL_Consol!$B24)+SUMIFS(PL_Calicut!C:C,PL_Calicut!$B:$B,PL_Consol!$B24)+SUMIFS(PL_FNB!C:C,PL_FNB!$B:$B,PL_Consol!$B24) -> 22.641747 | E24: =SUMIFS(PL_Kochi!D:D,PL_Kochi!$B:$B,PL_Consol!$B24)+SUMIFS(PL_Calicut!D:D,PL_Calicut!$B:$B,PL_Consol!$B24)+SUMIFS(PL_FNB!D:D,PL_FNB!$B:$B,PL_Consol!$B24) -> 21.421681 | F24: =SUMIFS(PL_Kochi!E:E,PL_Kochi!$B:$B,PL_Consol!$B24)+SUMIFS(PL_Calicut!E:E,PL_Calicut!$B:$B,PL_Consol!$B24)+SUMIFS(PL_FNB!E:E,PL_FNB!$B:$B,PL_Consol!$B24) -> 24.008923 | G24: =SUMIFS(PL_Kochi!F:F,PL_Kochi!$B:$B,PL_Consol!$B24)+SUMIFS(PL_Calicut!F:F,PL_Calicut!$B:$B,PL_Consol!$B24)+SUMIFS(PL_FNB!F:F,PL_FNB!$B:$B,PL_Consol!$B24) -> 16.951312 | H24: =SUMIFS(PL_Kochi!G:G,PL_Kochi!$B:$B,PL_Consol!$B24)+SUMIFS(PL_Calicut!G:G,PL_Calicut!$B:$B,PL_Consol!$B24)+SUMIFS(PL_FNB!G:G,PL_FNB!$B:$B,PL_Consol!$B24) -> 26.720004 | I24: =SUMIFS(PL_Kochi!H:H,PL_Kochi!$B:$B,PL_Consol!$B24)+SUMIFS(PL_Calicut!H:H,PL_Calicut!$B:$B,PL_Consol!$B24)+SUMIFS(PL_FNB!H:H,PL_FNB!$B:$B,PL_Consol!$B24) -> 26.464045 | J24: =SUMIFS(PL_Kochi!I:I,PL_Kochi!$B:$B,PL_Consol!$B24)+SUMIFS(PL_Calicut!I:I,PL_Calicut!$B:$B,PL_Consol!$B24)+SUMIFS(PL_FNB!I:I,PL_FNB!$B:$B,PL_Consol!$B24) -> 21.325308 | K24: =SUMIFS(PL_Kochi!J:J,PL_Kochi!$B:$B,PL_Consol!$B24)+SUMIFS(PL_Calicut!J:J,PL_Calicut!$B:$B,PL_Consol!$B24)+SUMIFS(PL_FNB!J:J,PL_FNB!$B:$B,PL_Consol!$B24) -> 21.235651 | L24: =SUMIFS(PL_Kochi!K:K,PL_Kochi!$B:$B,PL_Consol!$B24)+SUMIFS(PL_Calicut!K:K,PL_Calicut!$B:$B,PL_Consol!$B24)+SUMIFS(PL_FNB!K:K,PL_FNB!$B:$B,PL_Consol!$B24) -> 24.573338 | M24: =SUMIFS(PL_Kochi!L:L,PL_Kochi!$B:$B,PL_Consol!$B24)+SUMIFS(PL_Calicut!L:L,PL_Calicut!$B:$B,PL_Consol!$B24)+SUMIFS(PL_FNB!L:L,PL_FNB!$B:$B,PL_Consol!$B24) -> 23.386038 | N24: =SUMIFS(PL_Kochi!M:M,PL_Kochi!$B:$B,PL_Consol!$B24)+SUMIFS(PL_Calicut!M:M,PL_Calicut!$B:$B,PL_Consol!$B24)+SUMIFS(PL_FNB!M:M,PL_FNB!$B:$B,PL_Consol!$B24) -> 23.189508 | O24: =SUMIFS(PL_Kochi!N:N,PL_Kochi!$B:$B,PL_Consol!$B24)+SUMIFS(PL_Calicut!N:N,PL_Calicut!$B:$B,PL_Consol!$B24)+SUMIFS(PL_FNB!N:N,PL_FNB!$B:$B,PL_Consol!$B24) -> 31.523178 | P24: =SUM(D24:O24) -> 283.44073 | Q24: 180 | R24: 178.89 | S24: =SUMIFS(PL_Kochi!R:R,PL_Kochi!$B:$B,PL_Consol!$B24)+SUMIFS(PL_Calicut!R:R,PL_Calicut!$B:$B,PL_Consol!$B24)+SUMIFS(PL_FNB!R:R,PL_FNB!$B:$B,PL_Consol!$B24) -> 22.68199 | T24: =SUMIFS(PL_Kochi!S:S,PL_Kochi!$B:$B,PL_Consol!$B24)+SUMIFS(PL_Calicut!S:S,PL_Calicut!$B:$B,PL_Consol!$B24)+SUMIFS(PL_FNB!S:S,PL_FNB!$B:$B,PL_Consol!$B24) -> 23.08884 | U24: 98.7 | V24: =IFERROR(T24/E24-1,"-") -> 0.077825769 | W24: =IFERROR(T24/S24-1,"-") -> 0.017937149 | X24: =IFERROR(S24/U24,"-") -> 0.22980739
B25: House Keeping Expenses | C25: 16 | D25: =SUMIFS(PL_Kochi!C:C,PL_Kochi!$B:$B,PL_Consol!$B25)+SUMIFS(PL_Calicut!C:C,PL_Calicut!$B:$B,PL_Consol!$B25)+SUMIFS(PL_FNB!C:C,PL_FNB!$B:$B,PL_Consol!$B25) -> 66.117028 | E25: =SUMIFS(PL_Kochi!D:D,PL_Kochi!$B:$B,PL_Consol!$B25)+SUMIFS(PL_Calicut!D:D,PL_Calicut!$B:$B,PL_Consol!$B25)+SUMIFS(PL_FNB!D:D,PL_FNB!$B:$B,PL_Consol!$B25) -> 71.893894 | F25: =SUMIFS(PL_Kochi!E:E,PL_Kochi!$B:$B,PL_Consol!$B25)+SUMIFS(PL_Calicut!E:E,PL_Calicut!$B:$B,PL_Consol!$B25)+SUMIFS(PL_FNB!E:E,PL_FNB!$B:$B,PL_Consol!$B25) -> 78.735924 | G25: =SUMIFS(PL_Kochi!F:F,PL_Kochi!$B:$B,PL_Consol!$B25)+SUMIFS(PL_Calicut!F:F,PL_Calicut!$B:$B,PL_Consol!$B25)+SUMIFS(PL_FNB!F:F,PL_FNB!$B:$B,PL_Consol!$B25) -> 74.499295 | H25: =SUMIFS(PL_Kochi!G:G,PL_Kochi!$B:$B,PL_Consol!$B25)+SUMIFS(PL_Calicut!G:G,PL_Calicut!$B:$B,PL_Consol!$B25)+SUMIFS(PL_FNB!G:G,PL_FNB!$B:$B,PL_Consol!$B25) -> 67.888813 | I25: =SUMIFS(PL_Kochi!H:H,PL_Kochi!$B:$B,PL_Consol!$B25)+SUMIFS(PL_Calicut!H:H,PL_Calicut!$B:$B,PL_Consol!$B25)+SUMIFS(PL_FNB!H:H,PL_FNB!$B:$B,PL_Consol!$B25) -> 75.070654 | J25: =SUMIFS(PL_Kochi!I:I,PL_Kochi!$B:$B,PL_Consol!$B25)+SUMIFS(PL_Calicut!I:I,PL_Calicut!$B:$B,PL_Consol!$B25)+SUMIFS(PL_FNB!I:I,PL_FNB!$B:$B,PL_Consol!$B25) -> 88.145987 | K25: =SUMIFS(PL_Kochi!J:J,PL_Kochi!$B:$B,PL_Consol!$B25)+SUMIFS(PL_Calicut!J:J,PL_Calicut!$B:$B,PL_Consol!$B25)+SUMIFS(PL_FNB!J:J,PL_FNB!$B:$B,PL_Consol!$B25) -> 63.493011 | L25: =SUMIFS(PL_Kochi!K:K,PL_Kochi!$B:$B,PL_Consol!$B25)+SUMIFS(PL_Calicut!K:K,PL_Calicut!$B:$B,PL_Consol!$B25)+SUMIFS(PL_FNB!K:K,PL_FNB!$B:$B,PL_Consol!$B25) -> 68.196841 | M25: =SUMIFS(PL_Kochi!L:L,PL_Kochi!$B:$B,PL_Consol!$B25)+SUMIFS(PL_Calicut!L:L,PL_Calicut!$B:$B,PL_Consol!$B25)+SUMIFS(PL_FNB!L:L,PL_FNB!$B:$B,PL_Consol!$B25) -> 49.50565 | N25: =SUMIFS(PL_Kochi!M:M,PL_Kochi!$B:$B,PL_Consol!$B25)+SUMIFS(PL_Calicut!M:M,PL_Calicut!$B:$B,PL_Consol!$B25)+SUMIFS(PL_FNB!M:M,PL_FNB!$B:$B,PL_Consol!$B25) -> 120.95571 | O25: =SUMIFS(PL_Kochi!N:N,PL_Kochi!$B:$B,PL_Consol!$B25)+SUMIFS(PL_Calicut!N:N,PL_Calicut!$B:$B,PL_Consol!$B25)+SUMIFS(PL_FNB!N:N,PL_FNB!$B:$B,PL_Consol!$B25) -> 183.70153 | P25: =SUM(D25:O25) -> 1008.2043 | Q25: 926.03153 | R25: 1028.68 | S25: =SUMIFS(PL_Kochi!R:R,PL_Kochi!$B:$B,PL_Consol!$B25)+SUMIFS(PL_Calicut!R:R,PL_Calicut!$B:$B,PL_Consol!$B25)+SUMIFS(PL_FNB!R:R,PL_FNB!$B:$B,PL_Consol!$B25) -> 89.327925 | T25: =SUMIFS(PL_Kochi!S:S,PL_Kochi!$B:$B,PL_Consol!$B25)+SUMIFS(PL_Calicut!S:S,PL_Calicut!$B:$B,PL_Consol!$B25)+SUMIFS(PL_FNB!S:S,PL_FNB!$B:$B,PL_Consol!$B25) -> 114.05982 | U25: 30.7 | V25: =IFERROR(T25/E25-1,"-") -> 0.58650217 | W25: =IFERROR(T25/S25-1,"-") -> 0.27686632 | X25: =IFERROR(S25/U25,"-") -> 2.9097044
B26: Security Expenses | C26: 17 | D26: =SUMIFS(PL_Kochi!C:C,PL_Kochi!$B:$B,PL_Consol!$B26)+SUMIFS(PL_Calicut!C:C,PL_Calicut!$B:$B,PL_Consol!$B26)+SUMIFS(PL_FNB!C:C,PL_FNB!$B:$B,PL_Consol!$B26) -> 20.799117 | E26: =SUMIFS(PL_Kochi!D:D,PL_Kochi!$B:$B,PL_Consol!$B26)+SUMIFS(PL_Calicut!D:D,PL_Calicut!$B:$B,PL_Consol!$B26)+SUMIFS(PL_FNB!D:D,PL_FNB!$B:$B,PL_Consol!$B26) -> 23.636231 | F26: =SUMIFS(PL_Kochi!E:E,PL_Kochi!$B:$B,PL_Consol!$B26)+SUMIFS(PL_Calicut!E:E,PL_Calicut!$B:$B,PL_Consol!$B26)+SUMIFS(PL_FNB!E:E,PL_FNB!$B:$B,PL_Consol!$B26) -> 23.635804 | G26: =SUMIFS(PL_Kochi!F:F,PL_Kochi!$B:$B,PL_Consol!$B26)+SUMIFS(PL_Calicut!F:F,PL_Calicut!$B:$B,PL_Consol!$B26)+SUMIFS(PL_FNB!F:F,PL_FNB!$B:$B,PL_Consol!$B26) -> 23.342055 | H26: =SUMIFS(PL_Kochi!G:G,PL_Kochi!$B:$B,PL_Consol!$B26)+SUMIFS(PL_Calicut!G:G,PL_Calicut!$B:$B,PL_Consol!$B26)+SUMIFS(PL_FNB!G:G,PL_FNB!$B:$B,PL_Consol!$B26) -> 19.828358 | I26: =SUMIFS(PL_Kochi!H:H,PL_Kochi!$B:$B,PL_Consol!$B26)+SUMIFS(PL_Calicut!H:H,PL_Calicut!$B:$B,PL_Consol!$B26)+SUMIFS(PL_FNB!H:H,PL_FNB!$B:$B,PL_Consol!$B26) -> 19.054742 | J26: =SUMIFS(PL_Kochi!I:I,PL_Kochi!$B:$B,PL_Consol!$B26)+SUMIFS(PL_Calicut!I:I,PL_Calicut!$B:$B,PL_Consol!$B26)+SUMIFS(PL_FNB!I:I,PL_FNB!$B:$B,PL_Consol!$B26) -> 25.530817 | K26: =SUMIFS(PL_Kochi!J:J,PL_Kochi!$B:$B,PL_Consol!$B26)+SUMIFS(PL_Calicut!J:J,PL_Calicut!$B:$B,PL_Consol!$B26)+SUMIFS(PL_FNB!J:J,PL_FNB!$B:$B,PL_Consol!$B26) -> 21.061225 | L26: =SUMIFS(PL_Kochi!K:K,PL_Kochi!$B:$B,PL_Consol!$B26)+SUMIFS(PL_Calicut!K:K,PL_Calicut!$B:$B,PL_Consol!$B26)+SUMIFS(PL_FNB!K:K,PL_FNB!$B:$B,PL_Consol!$B26) -> 21.393371 | M26: =SUMIFS(PL_Kochi!L:L,PL_Kochi!$B:$B,PL_Consol!$B26)+SUMIFS(PL_Calicut!L:L,PL_Calicut!$B:$B,PL_Consol!$B26)+SUMIFS(PL_FNB!L:L,PL_FNB!$B:$B,PL_Consol!$B26) -> 22.631518 | N26: =SUMIFS(PL_Kochi!M:M,PL_Kochi!$B:$B,PL_Consol!$B26)+SUMIFS(PL_Calicut!M:M,PL_Calicut!$B:$B,PL_Consol!$B26)+SUMIFS(PL_FNB!M:M,PL_FNB!$B:$B,PL_Consol!$B26) -> 21.138675 | O26: =SUMIFS(PL_Kochi!N:N,PL_Kochi!$B:$B,PL_Consol!$B26)+SUMIFS(PL_Calicut!N:N,PL_Calicut!$B:$B,PL_Consol!$B26)+SUMIFS(PL_FNB!N:N,PL_FNB!$B:$B,PL_Consol!$B26) -> 23.288502 | P26: =SUM(D26:O26) -> 265.34041 | Q26: 241.48542 | R26: 227.63 | S26: =SUMIFS(PL_Kochi!R:R,PL_Kochi!$B:$B,PL_Consol!$B26)+SUMIFS(PL_Calicut!R:R,PL_Calicut!$B:$B,PL_Consol!$B26)+SUMIFS(PL_FNB!R:R,PL_FNB!$B:$B,PL_Consol!$B26) -> 24.095348 | T26: =SUMIFS(PL_Kochi!S:S,PL_Kochi!$B:$B,PL_Consol!$B26)+SUMIFS(PL_Calicut!S:S,PL_Calicut!$B:$B,PL_Consol!$B26)+SUMIFS(PL_FNB!S:S,PL_FNB!$B:$B,PL_Consol!$B26) -> 18.78792 | U26: 17.2 | V26: =IFERROR(T26/E26-1,"-") -> -0.20512201 | W26: =IFERROR(T26/S26-1,"-") -> -0.22026773 | X26: =IFERROR(S26/U26,"-") -> 1.4008923
B27: Printing & Stationery | C27: 18 | D27: =SUMIFS(PL_Kochi!C:C,PL_Kochi!$B:$B,PL_Consol!$B27)+SUMIFS(PL_Calicut!C:C,PL_Calicut!$B:$B,PL_Consol!$B27)+SUMIFS(PL_FNB!C:C,PL_FNB!$B:$B,PL_Consol!$B27) -> 11.416728 | E27: =SUMIFS(PL_Kochi!D:D,PL_Kochi!$B:$B,PL_Consol!$B27)+SUMIFS(PL_Calicut!D:D,PL_Calicut!$B:$B,PL_Consol!$B27)+SUMIFS(PL_FNB!D:D,PL_FNB!$B:$B,PL_Consol!$B27) -> 17.394012 | F27: =SUMIFS(PL_Kochi!E:E,PL_Kochi!$B:$B,PL_Consol!$B27)+SUMIFS(PL_Calicut!E:E,PL_Calicut!$B:$B,PL_Consol!$B27)+SUMIFS(PL_FNB!E:E,PL_FNB!$B:$B,PL_Consol!$B27) -> 13.518077 | G27: =SUMIFS(PL_Kochi!F:F,PL_Kochi!$B:$B,PL_Consol!$B27)+SUMIFS(PL_Calicut!F:F,PL_Calicut!$B:$B,PL_Consol!$B27)+SUMIFS(PL_FNB!F:F,PL_FNB!$B:$B,PL_Consol!$B27) -> 16.703076 | H27: =SUMIFS(PL_Kochi!G:G,PL_Kochi!$B:$B,PL_Consol!$B27)+SUMIFS(PL_Calicut!G:G,PL_Calicut!$B:$B,PL_Consol!$B27)+SUMIFS(PL_FNB!G:G,PL_FNB!$B:$B,PL_Consol!$B27) -> 13.933211 | I27: =SUMIFS(PL_Kochi!H:H,PL_Kochi!$B:$B,PL_Consol!$B27)+SUMIFS(PL_Calicut!H:H,PL_Calicut!$B:$B,PL_Consol!$B27)+SUMIFS(PL_FNB!H:H,PL_FNB!$B:$B,PL_Consol!$B27) -> 14.397721 | J27: =SUMIFS(PL_Kochi!I:I,PL_Kochi!$B:$B,PL_Consol!$B27)+SUMIFS(PL_Calicut!I:I,PL_Calicut!$B:$B,PL_Consol!$B27)+SUMIFS(PL_FNB!I:I,PL_FNB!$B:$B,PL_Consol!$B27) -> 18.095623 | K27: =SUMIFS(PL_Kochi!J:J,PL_Kochi!$B:$B,PL_Consol!$B27)+SUMIFS(PL_Calicut!J:J,PL_Calicut!$B:$B,PL_Consol!$B27)+SUMIFS(PL_FNB!J:J,PL_FNB!$B:$B,PL_Consol!$B27) -> 11.643462 | L27: =SUMIFS(PL_Kochi!K:K,PL_Kochi!$B:$B,PL_Consol!$B27)+SUMIFS(PL_Calicut!K:K,PL_Calicut!$B:$B,PL_Consol!$B27)+SUMIFS(PL_FNB!K:K,PL_FNB!$B:$B,PL_Consol!$B27) -> 13.987179 | M27: =SUMIFS(PL_Kochi!L:L,PL_Kochi!$B:$B,PL_Consol!$B27)+SUMIFS(PL_Calicut!L:L,PL_Calicut!$B:$B,PL_Consol!$B27)+SUMIFS(PL_FNB!L:L,PL_FNB!$B:$B,PL_Consol!$B27) -> 14.229374 | N27: =SUMIFS(PL_Kochi!M:M,PL_Kochi!$B:$B,PL_Consol!$B27)+SUMIFS(PL_Calicut!M:M,PL_Calicut!$B:$B,PL_Consol!$B27)+SUMIFS(PL_FNB!M:M,PL_FNB!$B:$B,PL_Consol!$B27) -> 18.054122 | O27: =SUMIFS(PL_Kochi!N:N,PL_Kochi!$B:$B,PL_Consol!$B27)+SUMIFS(PL_Calicut!N:N,PL_Calicut!$B:$B,PL_Consol!$B27)+SUMIFS(PL_FNB!N:N,PL_FNB!$B:$B,PL_Consol!$B27) -> 19.449988 | P27: =SUM(D27:O27) -> 182.82258 | Q27: 180 | R27: 167.97 | S27: =SUMIFS(PL_Kochi!R:R,PL_Kochi!$B:$B,PL_Consol!$B27)+SUMIFS(PL_Calicut!R:R,PL_Calicut!$B:$B,PL_Consol!$B27)+SUMIFS(PL_FNB!R:R,PL_FNB!$B:$B,PL_Consol!$B27) -> 18.924059 | T27: =SUMIFS(PL_Kochi!S:S,PL_Kochi!$B:$B,PL_Consol!$B27)+SUMIFS(PL_Calicut!S:S,PL_Calicut!$B:$B,PL_Consol!$B27)+SUMIFS(PL_FNB!S:S,PL_FNB!$B:$B,PL_Consol!$B27) -> 17.974497 | U27: 3 | V27: =IFERROR(T27/E27-1,"-") -> 0.033372677 | W27: =IFERROR(T27/S27-1,"-") -> -0.050177526 | X27: =IFERROR(S27/U27,"-") -> 6.3080198
B28: Insurance | C28: 19 | D28: =SUMIFS(PL_Kochi!C:C,PL_Kochi!$B:$B,PL_Consol!$B28)+SUMIFS(PL_Calicut!C:C,PL_Calicut!$B:$B,PL_Consol!$B28)+SUMIFS(PL_FNB!C:C,PL_FNB!$B:$B,PL_Consol!$B28) -> 2.2859503 | E28: =SUMIFS(PL_Kochi!D:D,PL_Kochi!$B:$B,PL_Consol!$B28)+SUMIFS(PL_Calicut!D:D,PL_Calicut!$B:$B,PL_Consol!$B28)+SUMIFS(PL_FNB!D:D,PL_FNB!$B:$B,PL_Consol!$B28) -> 2.3843484 | F28: =SUMIFS(PL_Kochi!E:E,PL_Kochi!$B:$B,PL_Consol!$B28)+SUMIFS(PL_Calicut!E:E,PL_Calicut!$B:$B,PL_Consol!$B28)+SUMIFS(PL_FNB!E:E,PL_FNB!$B:$B,PL_Consol!$B28) -> 1.9492875 | G28: =SUMIFS(PL_Kochi!F:F,PL_Kochi!$B:$B,PL_Consol!$B28)+SUMIFS(PL_Calicut!F:F,PL_Calicut!$B:$B,PL_Consol!$B28)+SUMIFS(PL_FNB!F:F,PL_FNB!$B:$B,PL_Consol!$B28) -> 1.8451045 | H28: =SUMIFS(PL_Kochi!G:G,PL_Kochi!$B:$B,PL_Consol!$B28)+SUMIFS(PL_Calicut!G:G,PL_Calicut!$B:$B,PL_Consol!$B28)+SUMIFS(PL_FNB!G:G,PL_FNB!$B:$B,PL_Consol!$B28) -> 2.6315041 | I28: =SUMIFS(PL_Kochi!H:H,PL_Kochi!$B:$B,PL_Consol!$B28)+SUMIFS(PL_Calicut!H:H,PL_Calicut!$B:$B,PL_Consol!$B28)+SUMIFS(PL_FNB!H:H,PL_FNB!$B:$B,PL_Consol!$B28) -> 3.41898 | J28: =SUMIFS(PL_Kochi!I:I,PL_Kochi!$B:$B,PL_Consol!$B28)+SUMIFS(PL_Calicut!I:I,PL_Calicut!$B:$B,PL_Consol!$B28)+SUMIFS(PL_FNB!I:I,PL_FNB!$B:$B,PL_Consol!$B28) -> 2.6836979 | K28: =SUMIFS(PL_Kochi!J:J,PL_Kochi!$B:$B,PL_Consol!$B28)+SUMIFS(PL_Calicut!J:J,PL_Calicut!$B:$B,PL_Consol!$B28)+SUMIFS(PL_FNB!J:J,PL_FNB!$B:$B,PL_Consol!$B28) -> 2.9104056 | L28: =SUMIFS(PL_Kochi!K:K,PL_Kochi!$B:$B,PL_Consol!$B28)+SUMIFS(PL_Calicut!K:K,PL_Calicut!$B:$B,PL_Consol!$B28)+SUMIFS(PL_FNB!K:K,PL_FNB!$B:$B,PL_Consol!$B28) -> 3.1283705 | M28: =SUMIFS(PL_Kochi!L:L,PL_Kochi!$B:$B,PL_Consol!$B28)+SUMIFS(PL_Calicut!L:L,PL_Calicut!$B:$B,PL_Consol!$B28)+SUMIFS(PL_FNB!L:L,PL_FNB!$B:$B,PL_Consol!$B28) -> 2.6990206 | N28: =SUMIFS(PL_Kochi!M:M,PL_Kochi!$B:$B,PL_Consol!$B28)+SUMIFS(PL_Calicut!M:M,PL_Calicut!$B:$B,PL_Consol!$B28)+SUMIFS(PL_FNB!M:M,PL_FNB!$B:$B,PL_Consol!$B28) -> 2.8924163 | O28: =SUMIFS(PL_Kochi!N:N,PL_Kochi!$B:$B,PL_Consol!$B28)+SUMIFS(PL_Calicut!N:N,PL_Calicut!$B:$B,PL_Consol!$B28)+SUMIFS(PL_FNB!N:N,PL_FNB!$B:$B,PL_Consol!$B28) -> 3.1997823 | P28: =SUM(D28:O28) -> 32.028868 | Q28: 32 | R28: 22.78 | S28: =SUMIFS(PL_Kochi!R:R,PL_Kochi!$B:$B,PL_Consol!$B28)+SUMIFS(PL_Calicut!R:R,PL_Calicut!$B:$B,PL_Consol!$B28)+SUMIFS(PL_FNB!R:R,PL_FNB!$B:$B,PL_Consol!$B28) -> 3.0348463 | T28: =SUMIFS(PL_Kochi!S:S,PL_Kochi!$B:$B,PL_Consol!$B28)+SUMIFS(PL_Calicut!S:S,PL_Calicut!$B:$B,PL_Consol!$B28)+SUMIFS(PL_FNB!S:S,PL_FNB!$B:$B,PL_Consol!$B28) -> 3.289582 | U28: 4.2 | V28: =IFERROR(T28/E28-1,"-") -> 0.37965662 | W28: =IFERROR(T28/S28-1,"-") -> 0.083936923 | X28: =IFERROR(S28/U28,"-") -> 0.72258246
... B31: Quality & Infection control expense | C31: 22 | D31: =SUMIFS(PL_Kochi!C:C,PL_Kochi!$B:$B,PL_Consol!$B31)+SUMIFS(PL_Calicut!C:C,PL_Calicut!$B:$B,PL_Consol!$B31)+SUMIFS(PL_FNB!C:C,PL_FNB!$B:$B,PL_Consol!$B31) -> 0 | E31: =SUMIFS(PL_Kochi!D:D,PL_Kochi!$B:$B,PL_Consol!$B31)+SUMIFS(PL_Calicut!D:D,PL_Calicut!$B:$B,PL_Consol!$B31)+SUMIFS(PL_FNB!D:D,PL_FNB!$B:$B,PL_Consol!$B31) -> 0 | F31: =SUMIFS(PL_Kochi!E:E,PL_Kochi!$B:$B,PL_Consol!$B31)+SUMIFS(PL_Calicut!E:E,PL_Calicut!$B:$B,PL_Consol!$B31)+SUMIFS(PL_FNB!E:E,PL_FNB!$B:$B,PL_Consol!$B31) -> 0 | G31: =SUMIFS(PL_Kochi!F:F,PL_Kochi!$B:$B,PL_Consol!$B31)+SUMIFS(PL_Calicut!F:F,PL_Calicut!$B:$B,PL_Consol!$B31)+SUMIFS(PL_FNB!F:F,PL_FNB!$B:$B,PL_Consol!$B31) -> 0 | H31: =SUMIFS(PL_Kochi!G:G,PL_Kochi!$B:$B,PL_Consol!$B31)+SUMIFS(PL_Calicut!G:G,PL_Calicut!$B:$B,PL_Consol!$B31)+SUMIFS(PL_FNB!G:G,PL_FNB!$B:$B,PL_Consol!$B31) -> 0.084021841 | I31: =SUMIFS(PL_Kochi!H:H,PL_Kochi!$B:$B,PL_Consol!$B31)+SUMIFS(PL_Calicut!H:H,PL_Calicut!$B:$B,PL_Consol!$B31)+SUMIFS(PL_FNB!H:H,PL_FNB!$B:$B,PL_Consol!$B31) -> 0.59515768 | J31: =SUMIFS(PL_Kochi!I:I,PL_Kochi!$B:$B,PL_Consol!$B31)+SUMIFS(PL_Calicut!I:I,PL_Calicut!$B:$B,PL_Consol!$B31)+SUMIFS(PL_FNB!I:I,PL_FNB!$B:$B,PL_Consol!$B31) -> 0.41771089 | K31: =SUMIFS(PL_Kochi!J:J,PL_Kochi!$B:$B,PL_Consol!$B31)+SUMIFS(PL_Calicut!J:J,PL_Calicut!$B:$B,PL_Consol!$B31)+SUMIFS(PL_FNB!J:J,PL_FNB!$B:$B,PL_Consol!$B31) -> 0.42412627 | L31: =SUMIFS(PL_Kochi!K:K,PL_Kochi!$B:$B,PL_Consol!$B31)+SUMIFS(PL_Calicut!K:K,PL_Calicut!$B:$B,PL_Consol!$B31)+SUMIFS(PL_FNB!K:K,PL_FNB!$B:$B,PL_Consol!$B31) -> 0.88160848 | M31: =SUMIFS(PL_Kochi!L:L,PL_Kochi!$B:$B,PL_Consol!$B31)+SUMIFS(PL_Calicut!L:L,PL_Calicut!$B:$B,PL_Consol!$B31)+SUMIFS(PL_FNB!L:L,PL_FNB!$B:$B,PL_Consol!$B31) -> 0.63415405 | N31: =SUMIFS(PL_Kochi!M:M,PL_Kochi!$B:$B,PL_Consol!$B31)+SUMIFS(PL_Calicut!M:M,PL_Calicut!$B:$B,PL_Consol!$B31)+SUMIFS(PL_FNB!M:M,PL_FNB!$B:$B,PL_Consol!$B31) -> 0.049612765 | O31: =SUMIFS(PL_Kochi!N:N,PL_Kochi!$B:$B,PL_Consol!$B31)+SUMIFS(PL_Calicut!N:N,PL_Calicut!$B:$B,PL_Consol!$B31)+SUMIFS(PL_FNB!N:N,PL_FNB!$B:$B,PL_Consol!$B31) -> 2.5907986 | P31: =SUM(D31:O31) -> 5.6771906 | Q31: 4.4806926 | R31: 6.814546 | S31: =SUMIFS(PL_Kochi!R:R,PL_Kochi!$B:$B,PL_Consol!$B31)+SUMIFS(PL_Calicut!R:R,PL_Calicut!$B:$B,PL_Consol!$B31)+SUMIFS(PL_FNB!R:R,PL_FNB!$B:$B,PL_Consol!$B31) -> 0 | T31: =SUMIFS(PL_Kochi!S:S,PL_Kochi!$B:$B,PL_Consol!$B31)+SUMIFS(PL_Calicut!S:S,PL_Calicut!$B:$B,PL_Consol!$B31)+SUMIFS(PL_FNB!S:S,PL_FNB!$B:$B,PL_Consol!$B31) -> 0 | U31: 88.3 | V31: =IFERROR(T31/E31-1,"-") -> - | W31: =IFERROR(T31/S31-1,"-") -> - | X31: =IFERROR(S31/U31,"-") -> 0
B32: Provission for Bad Debts | C32: 23 | D32: =SUMIFS(PL_Kochi!C:C,PL_Kochi!$B:$B,PL_Consol!$B32)+SUMIFS(PL_Calicut!C:C,PL_Calicut!$B:$B,PL_Consol!$B32)+SUMIFS(PL_FNB!C:C,PL_FNB!$B:$B,PL_Consol!$B32) -> 18.713982 | E32: =SUMIFS(PL_Kochi!D:D,PL_Kochi!$B:$B,PL_Consol!$B32)+SUMIFS(PL_Calicut!D:D,PL_Calicut!$B:$B,PL_Consol!$B32)+SUMIFS(PL_FNB!D:D,PL_FNB!$B:$B,PL_Consol!$B32) -> 1.3771271 | F32: =SUMIFS(PL_Kochi!E:E,PL_Kochi!$B:$B,PL_Consol!$B32)+SUMIFS(PL_Calicut!E:E,PL_Calicut!$B:$B,PL_Consol!$B32)+SUMIFS(PL_FNB!E:E,PL_FNB!$B:$B,PL_Consol!$B32) -> 1.3771708 | G32: =SUMIFS(PL_Kochi!F:F,PL_Kochi!$B:$B,PL_Consol!$B32)+SUMIFS(PL_Calicut!F:F,PL_Calicut!$B:$B,PL_Consol!$B32)+SUMIFS(PL_FNB!F:F,PL_FNB!$B:$B,PL_Consol!$B32) -> 1.3771111 | H32: =SUMIFS(PL_Kochi!G:G,PL_Kochi!$B:$B,PL_Consol!$B32)+SUMIFS(PL_Calicut!G:G,PL_Calicut!$B:$B,PL_Consol!$B32)+SUMIFS(PL_FNB!G:G,PL_FNB!$B:$B,PL_Consol!$B32) -> 1.3771 | I32: =SUMIFS(PL_Kochi!H:H,PL_Kochi!$B:$B,PL_Consol!$B32)+SUMIFS(PL_Calicut!H:H,PL_Calicut!$B:$B,PL_Consol!$B32)+SUMIFS(PL_FNB!H:H,PL_FNB!$B:$B,PL_Consol!$B32) -> 1.3771068 | J32: =SUMIFS(PL_Kochi!I:I,PL_Kochi!$B:$B,PL_Consol!$B32)+SUMIFS(PL_Calicut!I:I,PL_Calicut!$B:$B,PL_Consol!$B32)+SUMIFS(PL_FNB!I:I,PL_FNB!$B:$B,PL_Consol!$B32) -> 1.3771076 | K32: =SUMIFS(PL_Kochi!J:J,PL_Kochi!$B:$B,PL_Consol!$B32)+SUMIFS(PL_Calicut!J:J,PL_Calicut!$B:$B,PL_Consol!$B32)+SUMIFS(PL_FNB!J:J,PL_FNB!$B:$B,PL_Consol!$B32) -> 1.377152 | L32: =SUMIFS(PL_Kochi!K:K,PL_Kochi!$B:$B,PL_Consol!$B32)+SUMIFS(PL_Calicut!K:K,PL_Calicut!$B:$B,PL_Consol!$B32)+SUMIFS(PL_FNB!K:K,PL_FNB!$B:$B,PL_Consol!$B32) -> 1.3771301 | M32: =SUMIFS(PL_Kochi!L:L,PL_Kochi!$B:$B,PL_Consol!$B32)+SUMIFS(PL_Calicut!L:L,PL_Calicut!$B:$B,PL_Consol!$B32)+SUMIFS(PL_FNB!L:L,PL_FNB!$B:$B,PL_Consol!$B32) -> 1.3770765 | N32: =SUMIFS(PL_Kochi!M:M,PL_Kochi!$B:$B,PL_Consol!$B32)+SUMIFS(PL_Calicut!M:M,PL_Calicut!$B:$B,PL_Consol!$B32)+SUMIFS(PL_FNB!M:M,PL_FNB!$B:$B,PL_Consol!$B32) -> 1.3770963 | O32: =SUMIFS(PL_Kochi!N:N,PL_Kochi!$B:$B,PL_Consol!$B32)+SUMIFS(PL_Calicut!N:N,PL_Calicut!$B:$B,PL_Consol!$B32)+SUMIFS(PL_FNB!N:N,PL_FNB!$B:$B,PL_Consol!$B32) -> 18.712983 | P32: =SUM(D32:O32) -> 51.198143 | Q32: 370 | R32: 243.91 | S32: =ECL!M43 -> 16.520904 | T32: =SUMIFS(PL_Kochi!S:S,PL_Kochi!$B:$B,PL_Consol!$B32)+SUMIFS(PL_Calicut!S:S,PL_Calicut!$B:$B,PL_Consol!$B32)+SUMIFS(PL_FNB!S:S,PL_FNB!$B:$B,PL_Consol!$B32) -> 1.376742 | U32: 118.3 | V32: =IFERROR(T32/E32-1,"-") -> -0.00027968462 | W32: =IFERROR(T32/S32-1,"-") -> -0.91666667 | X32: =IFERROR(S32/U32,"-") -> 0.13965261
B33: Communication Costs | C33: 24 | D33: =SUMIFS(PL_Kochi!C:C,PL_Kochi!$B:$B,PL_Consol!$B33)+SUMIFS(PL_Calicut!C:C,PL_Calicut!$B:$B,PL_Consol!$B33)+SUMIFS(PL_FNB!C:C,PL_FNB!$B:$B,PL_Consol!$B33) -> 0.68185368 | E33: =SUMIFS(PL_Kochi!D:D,PL_Kochi!$B:$B,PL_Consol!$B33)+SUMIFS(PL_Calicut!D:D,PL_Calicut!$B:$B,PL_Consol!$B33)+SUMIFS(PL_FNB!D:D,PL_FNB!$B:$B,PL_Consol!$B33) -> 3.4929729 | F33: =SUMIFS(PL_Kochi!E:E,PL_Kochi!$B:$B,PL_Consol!$B33)+SUMIFS(PL_Calicut!E:E,PL_Calicut!$B:$B,PL_Consol!$B33)+SUMIFS(PL_FNB!E:E,PL_FNB!$B:$B,PL_Consol!$B33) -> 2.4256114 | G33: =SUMIFS(PL_Kochi!F:F,PL_Kochi!$B:$B,PL_Consol!$B33)+SUMIFS(PL_Calicut!F:F,PL_Calicut!$B:$B,PL_Consol!$B33)+SUMIFS(PL_FNB!F:F,PL_FNB!$B:$B,PL_Consol!$B33) -> 4.0467134 | H33: =SUMIFS(PL_Kochi!G:G,PL_Kochi!$B:$B,PL_Consol!$B33)+SUMIFS(PL_Calicut!G:G,PL_Calicut!$B:$B,PL_Consol!$B33)+SUMIFS(PL_FNB!G:G,PL_FNB!$B:$B,PL_Consol!$B33) -> 2.7793287 | I33: =SUMIFS(PL_Kochi!H:H,PL_Kochi!$B:$B,PL_Consol!$B33)+SUMIFS(PL_Calicut!H:H,PL_Calicut!$B:$B,PL_Consol!$B33)+SUMIFS(PL_FNB!H:H,PL_FNB!$B:$B,PL_Consol!$B33) -> 2.9051669 | J33: =SUMIFS(PL_Kochi!I:I,PL_Kochi!$B:$B,PL_Consol!$B33)+SUMIFS(PL_Calicut!I:I,PL_Calicut!$B:$B,PL_Consol!$B33)+SUMIFS(PL_FNB!I:I,PL_FNB!$B:$B,PL_Consol!$B33) -> 3.117634 | K33: =SUMIFS(PL_Kochi!J:J,PL_Kochi!$B:$B,PL_Consol!$B33)+SUMIFS(PL_Calicut!J:J,PL_Calicut!$B:$B,PL_Consol!$B33)+SUMIFS(PL_FNB!J:J,PL_FNB!$B:$B,PL_Consol!$B33) -> 5.0159787 | L33: =SUMIFS(PL_Kochi!K:K,PL_Kochi!$B:$B,PL_Consol!$B33)+SUMIFS(PL_Calicut!K:K,PL_Calicut!$B:$B,PL_Consol!$B33)+SUMIFS(PL_FNB!K:K,PL_FNB!$B:$B,PL_Consol!$B33) -> 2.4340294 | M33: =SUMIFS(PL_Kochi!L:L,PL_Kochi!$B:$B,PL_Consol!$B33)+SUMIFS(PL_Calicut!L:L,PL_Calicut!$B:$B,PL_Consol!$B33)+SUMIFS(PL_FNB!L:L,PL_FNB!$B:$B,PL_Consol!$B33) -> 3.3117412 | N33: =SUMIFS(PL_Kochi!M:M,PL_Kochi!$B:$B,PL_Consol!$B33)+SUMIFS(PL_Calicut!M:M,PL_Calicut!$B:$B,PL_Consol!$B33)+SUMIFS(PL_FNB!M:M,PL_FNB!$B:$B,PL_Consol!$B33) -> 2.0004324 | O33: =SUMIFS(PL_Kochi!N:N,PL_Kochi!$B:$B,PL_Consol!$B33)+SUMIFS(PL_Calicut!N:N,PL_Calicut!$B:$B,PL_Consol!$B33)+SUMIFS(PL_FNB!N:N,PL_FNB!$B:$B,PL_Consol!$B33) -> 5.3502137 | P33: =SUM(D33:O33) -> 37.561676 | Q33: 41.97591 | R33: 34.723635 | S33: =SUMIFS(PL_Kochi!R:R,PL_Kochi!$B:$B,PL_Consol!$B33)+SUMIFS(PL_Calicut!R:R,PL_Calicut!$B:$B,PL_Consol!$B33)+SUMIFS(PL_FNB!R:R,PL_FNB!$B:$B,PL_Consol!$B33) -> 1.1021556 | T33: =SUMIFS(PL_Kochi!S:S,PL_Kochi!$B:$B,PL_Consol!$B33)+SUMIFS(PL_Calicut!S:S,PL_Calicut!$B:$B,PL_Consol!$B33)+SUMIFS(PL_FNB!S:S,PL_FNB!$B:$B,PL_Consol!$B33) -> 2.6738307 | U33: 3.9 | V33: =IFERROR(T33/E33-1,"-") -> -0.23451147 | W33: =IFERROR(T33/S33-1,"-") -> 1.4260011 | X33: =IFERROR(S33/U33,"-") -> 0.282604
B34: Business Travel Cost | C34: 25 | D34: =SUMIFS(PL_Kochi!C:C,PL_Kochi!$B:$B,PL_Consol!$B34)+SUMIFS(PL_Calicut!C:C,PL_Calicut!$B:$B,PL_Consol!$B34)+SUMIFS(PL_FNB!C:C,PL_FNB!$B:$B,PL_Consol!$B34) -> 11.494375 | E34: =SUMIFS(PL_Kochi!D:D,PL_Kochi!$B:$B,PL_Consol!$B34)+SUMIFS(PL_Calicut!D:D,PL_Calicut!$B:$B,PL_Consol!$B34)+SUMIFS(PL_FNB!D:D,PL_FNB!$B:$B,PL_Consol!$B34) -> 13.282296 | F34: =SUMIFS(PL_Kochi!E:E,PL_Kochi!$B:$B,PL_Consol!$B34)+SUMIFS(PL_Calicut!E:E,PL_Calicut!$B:$B,PL_Consol!$B34)+SUMIFS(PL_FNB!E:E,PL_FNB!$B:$B,PL_Consol!$B34) -> 13.151583 | G34: =SUMIFS(PL_Kochi!F:F,PL_Kochi!$B:$B,PL_Consol!$B34)+SUMIFS(PL_Calicut!F:F,PL_Calicut!$B:$B,PL_Consol!$B34)+SUMIFS(PL_FNB!F:F,PL_FNB!$B:$B,PL_Consol!$B34) -> 15.067058 | H34: =SUMIFS(PL_Kochi!G:G,PL_Kochi!$B:$B,PL_Consol!$B34)+SUMIFS(PL_Calicut!G:G,PL_Calicut!$B:$B,PL_Consol!$B34)+SUMIFS(PL_FNB!G:G,PL_FNB!$B:$B,PL_Consol!$B34) -> 18.584653 | I34: =SUMIFS(PL_Kochi!H:H,PL_Kochi!$B:$B,PL_Consol!$B34)+SUMIFS(PL_Calicut!H:H,PL_Calicut!$B:$B,PL_Consol!$B34)+SUMIFS(PL_FNB!H:H,PL_FNB!$B:$B,PL_Consol!$B34) -> 15.298645 | J34: =SUMIFS(PL_Kochi!I:I,PL_Kochi!$B:$B,PL_Consol!$B34)+SUMIFS(PL_Calicut!I:I,PL_Calicut!$B:$B,PL_Consol!$B34)+SUMIFS(PL_FNB!I:I,PL_FNB!$B:$B,PL_Consol!$B34) -> 15.564519 | K34: =SUMIFS(PL_Kochi!J:J,PL_Kochi!$B:$B,PL_Consol!$B34)+SUMIFS(PL_Calicut!J:J,PL_Calicut!$B:$B,PL_Consol!$B34)+SUMIFS(PL_FNB!J:J,PL_FNB!$B:$B,PL_Consol!$B34) -> 12.937513 | L34: =SUMIFS(PL_Kochi!K:K,PL_Kochi!$B:$B,PL_Consol!$B34)+SUMIFS(PL_Calicut!K:K,PL_Calicut!$B:$B,PL_Consol!$B34)+SUMIFS(PL_FNB!K:K,PL_FNB!$B:$B,PL_Consol!$B34) -> 14.60782 | M34: =SUMIFS(PL_Kochi!L:L,PL_Kochi!$B:$B,PL_Consol!$B34)+SUMIFS(PL_Calicut!L:L,PL_Calicut!$B:$B,PL_Consol!$B34)+SUMIFS(PL_FNB!L:L,PL_FNB!$B:$B,PL_Consol!$B34) -> 14.398174 | N34: =SUMIFS(PL_Kochi!M:M,PL_Kochi!$B:$B,PL_Consol!$B34)+SUMIFS(PL_Calicut!M:M,PL_Calicut!$B:$B,PL_Consol!$B34)+SUMIFS(PL_FNB!M:M,PL_FNB!$B:$B,PL_Consol!$B34) -> 16.727479 | O34: =SUMIFS(PL_Kochi!N:N,PL_Kochi!$B:$B,PL_Consol!$B34)+SUMIFS(PL_Calicut!N:N,PL_Calicut!$B:$B,PL_Consol!$B34)+SUMIFS(PL_FNB!N:N,PL_FNB!$B:$B,PL_Consol!$B34) -> 20.709302 | P34: =SUM(D34:O34) -> 181.82342 | Q34: 190 | R34: 157.60583 | S34: =SUMIFS(PL_Kochi!R:R,PL_Kochi!$B:$B,PL_Consol!$B34)+SUMIFS(PL_Calicut!R:R,PL_Calicut!$B:$B,PL_Consol!$B34)+SUMIFS(PL_FNB!R:R,PL_FNB!$B:$B,PL_Consol!$B34) -> 18.05943 | T34: =SUMIFS(PL_Kochi!S:S,PL_Kochi!$B:$B,PL_Consol!$B34)+SUMIFS(PL_Calicut!S:S,PL_Calicut!$B:$B,PL_Consol!$B34)+SUMIFS(PL_FNB!S:S,PL_FNB!$B:$B,PL_Consol!$B34) -> 13.933824 | U34: 16.5 | V34: =IFERROR(T34/E34-1,"-") -> 0.049052399 | W34: =IFERROR(T34/S34-1,"-") -> -0.22844608 | X34: =IFERROR(S34/U34,"-") -> 1.0945109
B35: Miscellaneous expenses | C35: 26 | D35: =SUMIFS(PL_Kochi!C:C,PL_Kochi!$B:$B,PL_Consol!$B35)+SUMIFS(PL_Calicut!C:C,PL_Calicut!$B:$B,PL_Consol!$B35)+SUMIFS(PL_FNB!C:C,PL_FNB!$B:$B,PL_Consol!$B35) -> 2.465909 | E35: =SUMIFS(PL_Kochi!D:D,PL_Kochi!$B:$B,PL_Consol!$B35)+SUMIFS(PL_Calicut!D:D,PL_Calicut!$B:$B,PL_Consol!$B35)+SUMIFS(PL_FNB!D:D,PL_FNB!$B:$B,PL_Consol!$B35) -> 2.4144899 | F35: =SUMIFS(PL_Kochi!E:E,PL_Kochi!$B:$B,PL_Consol!$B35)+SUMIFS(PL_Calicut!E:E,PL_Calicut!$B:$B,PL_Consol!$B35)+SUMIFS(PL_FNB!E:E,PL_FNB!$B:$B,PL_Consol!$B35) -> 3.4030767 | G35: =SUMIFS(PL_Kochi!F:F,PL_Kochi!$B:$B,PL_Consol!$B35)+SUMIFS(PL_Calicut!F:F,PL_Calicut!$B:$B,PL_Consol!$B35)+SUMIFS(PL_FNB!F:F,PL_FNB!$B:$B,PL_Consol!$B35) -> 6.8842077 | H35: =SUMIFS(PL_Kochi!G:G,PL_Kochi!$B:$B,PL_Consol!$B35)+SUMIFS(PL_Calicut!G:G,PL_Calicut!$B:$B,PL_Consol!$B35)+SUMIFS(PL_FNB!G:G,PL_FNB!$B:$B,PL_Consol!$B35) -> 12.573068 | I35: =SUMIFS(PL_Kochi!H:H,PL_Kochi!$B:$B,PL_Consol!$B35)+SUMIFS(PL_Calicut!H:H,PL_Calicut!$B:$B,PL_Consol!$B35)+SUMIFS(PL_FNB!H:H,PL_FNB!$B:$B,PL_Consol!$B35) -> 6.2340995 | J35: =SUMIFS(PL_Kochi!I:I,PL_Kochi!$B:$B,PL_Consol!$B35)+SUMIFS(PL_Calicut!I:I,PL_Calicut!$B:$B,PL_Consol!$B35)+SUMIFS(PL_FNB!I:I,PL_FNB!$B:$B,PL_Consol!$B35) -> 8.1068159 | K35: =SUMIFS(PL_Kochi!J:J,PL_Kochi!$B:$B,PL_Consol!$B35)+SUMIFS(PL_Calicut!J:J,PL_Calicut!$B:$B,PL_Consol!$B35)+SUMIFS(PL_FNB!J:J,PL_FNB!$B:$B,PL_Consol!$B35) -> 25.901765 | L35: =SUMIFS(PL_Kochi!K:K,PL_Kochi!$B:$B,PL_Consol!$B35)+SUMIFS(PL_Calicut!K:K,PL_Calicut!$B:$B,PL_Consol!$B35)+SUMIFS(PL_FNB!K:K,PL_FNB!$B:$B,PL_Consol!$B35) -> 11.309856 | M35: =SUMIFS(PL_Kochi!L:L,PL_Kochi!$B:$B,PL_Consol!$B35)+SUMIFS(PL_Calicut!L:L,PL_Calicut!$B:$B,PL_Consol!$B35)+SUMIFS(PL_FNB!L:L,PL_FNB!$B:$B,PL_Consol!$B35) -> 9.4525364 | N35: =SUMIFS(PL_Kochi!M:M,PL_Kochi!$B:$B,PL_Consol!$B35)+SUMIFS(PL_Calicut!M:M,PL_Calicut!$B:$B,PL_Consol!$B35)+SUMIFS(PL_FNB!M:M,PL_FNB!$B:$B,PL_Consol!$B35) -> 5.6806972 | O35: =SUMIFS(PL_Kochi!N:N,PL_Kochi!$B:$B,PL_Consol!$B35)+SUMIFS(PL_Calicut!N:N,PL_Calicut!$B:$B,PL_Consol!$B35)+SUMIFS(PL_FNB!N:N,PL_FNB!$B:$B,PL_Consol!$B35) -> 23.654033 | P35: =SUM(D35:O35) -> 118.08055 | Q35: 149.72962 | R35: 248.19999 | S35: =SUMIFS(PL_Kochi!R:R,PL_Kochi!$B:$B,PL_Consol!$B35)+SUMIFS(PL_Calicut!R:R,PL_Calicut!$B:$B,PL_Consol!$B35)+SUMIFS(PL_FNB!R:R,PL_FNB!$B:$B,PL_Consol!$B35) -> 4.8270436 | T35: =SUMIFS(PL_Kochi!S:S,PL_Kochi!$B:$B,PL_Consol!$B35)+SUMIFS(PL_Calicut!S:S,PL_Calicut!$B:$B,PL_Consol!$B35)+SUMIFS(PL_FNB!S:S,PL_FNB!$B:$B,PL_Consol!$B35) -> 6.8438395 | U35: 11.7 | V35: =IFERROR(T35/E35-1,"-") -> 1.8344866 | W35: =IFERROR(T35/S35-1,"-") -> 0.41781182 | X35: =IFERROR(S35/U35,"-") -> 0.41256783
B36: CSR Activity | C36: 27 | D36: =SUMIFS(PL_Kochi!C:C,PL_Kochi!$B:$B,PL_Consol!$B36)+SUMIFS(PL_Calicut!C:C,PL_Calicut!$B:$B,PL_Consol!$B36)+SUMIFS(PL_FNB!C:C,PL_FNB!$B:$B,PL_Consol!$B36) -> 7.6257141 | E36: =SUMIFS(PL_Kochi!D:D,PL_Kochi!$B:$B,PL_Consol!$B36)+SUMIFS(PL_Calicut!D:D,PL_Calicut!$B:$B,PL_Consol!$B36)+SUMIFS(PL_FNB!D:D,PL_FNB!$B:$B,PL_Consol!$B36) -> 8.4221789 | F36: =SUMIFS(PL_Kochi!E:E,PL_Kochi!$B:$B,PL_Consol!$B36)+SUMIFS(PL_Calicut!E:E,PL_Calicut!$B:$B,PL_Consol!$B36)+SUMIFS(PL_FNB!E:E,PL_FNB!$B:$B,PL_Consol!$B36) -> 10.584859 | G36: =SUMIFS(PL_Kochi!F:F,PL_Kochi!$B:$B,PL_Consol!$B36)+SUMIFS(PL_Calicut!F:F,PL_Calicut!$B:$B,PL_Consol!$B36)+SUMIFS(PL_FNB!F:F,PL_FNB!$B:$B,PL_Consol!$B36) -> 10.076034 | H36: =SUMIFS(PL_Kochi!G:G,PL_Kochi!$B:$B,PL_Consol!$B36)+SUMIFS(PL_Calicut!G:G,PL_Calicut!$B:$B,PL_Consol!$B36)+SUMIFS(PL_FNB!G:G,PL_FNB!$B:$B,PL_Consol!$B36) -> 8.8706393 | I36: =SUMIFS(PL_Kochi!H:H,PL_Kochi!$B:$B,PL_Consol!$B36)+SUMIFS(PL_Calicut!H:H,PL_Calicut!$B:$B,PL_Consol!$B36)+SUMIFS(PL_FNB!H:H,PL_FNB!$B:$B,PL_Consol!$B36) -> 10.173589 | J36: =SUMIFS(PL_Kochi!I:I,PL_Kochi!$B:$B,PL_Consol!$B36)+SUMIFS(PL_Calicut!I:I,PL_Calicut!$B:$B,PL_Consol!$B36)+SUMIFS(PL_FNB!I:I,PL_FNB!$B:$B,PL_Consol!$B36) -> 9.0268696 | K36: =SUMIFS(PL_Kochi!J:J,PL_Kochi!$B:$B,PL_Consol!$B36)+SUMIFS(PL_Calicut!J:J,PL_Calicut!$B:$B,PL_Consol!$B36)+SUMIFS(PL_FNB!J:J,PL_FNB!$B:$B,PL_Consol!$B36) -> 7.6256037 | L36: =SUMIFS(PL_Kochi!K:K,PL_Kochi!$B:$B,PL_Consol!$B36)+SUMIFS(PL_Calicut!K:K,PL_Calicut!$B:$B,PL_Consol!$B36)+SUMIFS(PL_FNB!K:K,PL_FNB!$B:$B,PL_Consol!$B36) -> 30.202656 | M36: =SUMIFS(PL_Kochi!L:L,PL_Kochi!$B:$B,PL_Consol!$B36)+SUMIFS(PL_Calicut!L:L,PL_Calicut!$B:$B,PL_Consol!$B36)+SUMIFS(PL_FNB!L:L,PL_FNB!$B:$B,PL_Consol!$B36) -> 7.6251857 | N36: =SUMIFS(PL_Kochi!M:M,PL_Kochi!$B:$B,PL_Consol!$B36)+SUMIFS(PL_Calicut!M:M,PL_Calicut!$B:$B,PL_Consol!$B36)+SUMIFS(PL_FNB!M:M,PL_FNB!$B:$B,PL_Consol!$B36) -> 9.62581 | O36: =SUMIFS(PL_Kochi!N:N,PL_Kochi!$B:$B,PL_Consol!$B36)+SUMIFS(PL_Calicut!N:N,PL_Calicut!$B:$B,PL_Consol!$B36)+SUMIFS(PL_FNB!N:N,PL_FNB!$B:$B,PL_Consol!$B36) -> 27.403066 | P36: =SUM(D36:O36) -> 147.26221 | Q36: 110 | R36: 137.25 | S36: =SUMIFS(PL_Kochi!R:R,PL_Kochi!$B:$B,PL_Consol!$B36)+SUMIFS(PL_Calicut!R:R,PL_Calicut!$B:$B,PL_Consol!$B36)+SUMIFS(PL_FNB!R:R,PL_FNB!$B:$B,PL_Consol!$B36) -> 15.003668 | T36: =SUMIFS(PL_Kochi!S:S,PL_Kochi!$B:$B,PL_Consol!$B36)+SUMIFS(PL_Calicut!S:S,PL_Calicut!$B:$B,PL_Consol!$B36)+SUMIFS(PL_FNB!S:S,PL_FNB!$B:$B,PL_Consol!$B36) -> 15 | U36: 10.7 | V36: =IFERROR(T36/E36-1,"-") -> 0.7810118 | W36: =IFERROR(T36/S36-1,"-") -> -0.00024448198 | X36: =IFERROR(S36/U36,"-") -> 1.402212
B37: Total Expenses | D37: =SUM(D17:D36) -> 2473.8739 | E37: =SUM(E17:E36) -> 2852.4474 | F37: =SUM(F17:F36) -> 2854.291 | G37: =SUM(G17:G36) -> 3069.6371 | H37: =SUM(H17:H36) -> 3025.5411 | I37: =SUM(I17:I36) -> 3056.215 | J37: =SUM(J17:J36) -> 3124.1301 | K37: =SUM(K17:K36) -> 2831.0122 | ... U37: =SUM(U17:U36) -> 3416.3 | V37: =IFERROR(T37/E37-1,"-") -> 0.1201156 | W37: =IFERROR(S37/O37-1,"-") -> -0.017926957 | X37: =IFERROR(S37/U37,"-") -> 0.92750956
V38: =IFERROR(S38/D38-1,"-") -> - | W38: =IFERROR(S38/O38-1,"-") -> - | X38: =IFERROR(S38/U38,"-") -> -
B39: EBITDA | D39: =D15-D37 -> 892.86927 | E39: =E15-E37 -> 889.74441 | F39: =F15-F37 -> 515.33685 | G39: =G15-G37 -> 847.81793 | H39: =H15-H37 -> 1005.6896 | I39: =I15-I37 -> 900.1578 | J39: =J15-J37 -> 824.48193 | K39: =K15-K37 -> 696.01832 | ... U39: =U15-U37 -> 953.25733 | V39: =IFERROR(S39/D39-1,"-") -> 0.24344038 | W39: =IFERROR(S39/O39-1,"-") -> 0.38297766 | X39: =IFERROR(S39/U39,"-") -> 1.1646695
B40: Depreciation | C40: 28 | D40: 227.3667 | E40: =SUMIFS(PL_Kochi!D:D,PL_Kochi!$B:$B,PL_Consol!$B40)+SUMIFS(PL_Calicut!D:D,PL_Calicut!$B:$B,PL_Consol!$B40)+SUMIFS(PL_FNB!D:D,PL_FNB!$B:$B,PL_Consol!$B40) -> 16.438299 | F40: =SUMIFS(PL_Kochi!E:E,PL_Kochi!$B:$B,PL_Consol!$B40)+SUMIFS(PL_Calicut!E:E,PL_Calicut!$B:$B,PL_Consol!$B40)+SUMIFS(PL_FNB!E:E,PL_FNB!$B:$B,PL_Consol!$B40) -> 16.438728 | G40: =SUMIFS(PL_Kochi!F:F,PL_Kochi!$B:$B,PL_Consol!$B40)+SUMIFS(PL_Calicut!F:F,PL_Calicut!$B:$B,PL_Consol!$B40)+SUMIFS(PL_FNB!F:F,PL_FNB!$B:$B,PL_Consol!$B40) -> 16.436339 | H40: =SUMIFS(PL_Kochi!G:G,PL_Kochi!$B:$B,PL_Consol!$B40)+SUMIFS(PL_Calicut!G:G,PL_Calicut!$B:$B,PL_Consol!$B40)+SUMIFS(PL_FNB!G:G,PL_FNB!$B:$B,PL_Consol!$B40) -> 16.436477 | I40: =SUMIFS(PL_Kochi!H:H,PL_Kochi!$B:$B,PL_Consol!$B40)+SUMIFS(PL_Calicut!H:H,PL_Calicut!$B:$B,PL_Consol!$B40)+SUMIFS(PL_FNB!H:H,PL_FNB!$B:$B,PL_Consol!$B40) -> 16.436325 | J40: =SUMIFS(PL_Kochi!I:I,PL_Kochi!$B:$B,PL_Consol!$B40)+SUMIFS(PL_Calicut!I:I,PL_Calicut!$B:$B,PL_Consol!$B40)+SUMIFS(PL_FNB!I:I,PL_FNB!$B:$B,PL_Consol!$B40) -> 16.436288 | K40: =SUMIFS(PL_Kochi!J:J,PL_Kochi!$B:$B,PL_Consol!$B40)+SUMIFS(PL_Calicut!J:J,PL_Calicut!$B:$B,PL_Consol!$B40)+SUMIFS(PL_FNB!J:J,PL_FNB!$B:$B,PL_Consol!$B40) -> 16.437642 | L40: =SUMIFS(PL_Kochi!K:K,PL_Kochi!$B:$B,PL_Consol!$B40)+SUMIFS(PL_Calicut!K:K,PL_Calicut!$B:$B,PL_Consol!$B40)+SUMIFS(PL_FNB!K:K,PL_FNB!$B:$B,PL_Consol!$B40) -> 16.436246 | M40: =SUMIFS(PL_Kochi!L:L,PL_Kochi!$B:$B,PL_Consol!$B40)+SUMIFS(PL_Calicut!L:L,PL_Calicut!$B:$B,PL_Consol!$B40)+SUMIFS(PL_FNB!L:L,PL_FNB!$B:$B,PL_Consol!$B40) -> 16.436297 | N40: =SUMIFS(PL_Kochi!M:M,PL_Kochi!$B:$B,PL_Consol!$B40)+SUMIFS(PL_Calicut!M:M,PL_Calicut!$B:$B,PL_Consol!$B40)+SUMIFS(PL_FNB!M:M,PL_FNB!$B:$B,PL_Consol!$B40) -> 16.4362 | O40: 227.35173 | P40: =SUM(D40:O40) -> 619.08728 | Q40: 2741.5292 | R40: 2604.81 | S40: 198.4 | T40: =SUMIFS(PL_Kochi!S:S,PL_Kochi!$B:$B,PL_Consol!$B40)+SUMIFS(PL_Calicut!S:S,PL_Calicut!$B:$B,PL_Consol!$B40)+SUMIFS(PL_FNB!S:S,PL_FNB!$B:$B,PL_Consol!$B40) -> 197.24263 | U40: 250 | V40: =IFERROR(T40/E40-1,"-") -> 10.998969 | W40: =IFERROR(S40/O40-1,"-") -> -0.12734336 | X40: =IFERROR(S40/U40,"-") -> 0.7936
B41: EBIT (Operational Profit) | D41: =D39-D40 -> 665.50257 | E41: =E39-E40 -> 873.30612 | F41: =F39-F40 -> 498.89812 | G41: =G39-G40 -> 831.38159 | H41: =H39-H40 -> 989.25314 | I41: =I39-I40 -> 883.72148 | J41: =J39-J40 -> 808.04564 | K41: =K39-K40 -> 679.58067 | ... U41: =U39-U40 -> 703.25733 | V41: =IFERROR(S41/D41-1,"-") -> 0.37013701 | W41: =IFERROR(S41/O41-1,"-") -> 0.58460479 | X41: =IFERROR(S41/U41,"-") -> 1.2965804
B42: Finance Cost | C42: 29 | D42: =SUMIFS(PL_Kochi!C:C,PL_Kochi!$B:$B,PL_Consol!$B42)+SUMIFS(PL_Calicut!C:C,PL_Calicut!$B:$B,PL_Consol!$B42)+SUMIFS(PL_FNB!C:C,PL_FNB!$B:$B,PL_Consol!$B42) -> 0.36520933 | E42: =SUMIFS(PL_Kochi!D:D,PL_Kochi!$B:$B,PL_Consol!$B42)+SUMIFS(PL_Calicut!D:D,PL_Calicut!$B:$B,PL_Consol!$B42)+SUMIFS(PL_FNB!D:D,PL_FNB!$B:$B,PL_Consol!$B42) -> 5.7342188 | F42: =SUMIFS(PL_Kochi!E:E,PL_Kochi!$B:$B,PL_Consol!$B42)+SUMIFS(PL_Calicut!E:E,PL_Calicut!$B:$B,PL_Consol!$B42)+SUMIFS(PL_FNB!E:E,PL_FNB!$B:$B,PL_Consol!$B42) -> 7.4012506 | G42: =SUMIFS(PL_Kochi!F:F,PL_Kochi!$B:$B,PL_Consol!$B42)+SUMIFS(PL_Calicut!F:F,PL_Calicut!$B:$B,PL_Consol!$B42)+SUMIFS(PL_FNB!F:F,PL_FNB!$B:$B,PL_Consol!$B42) -> 7.3545603 | H42: =SUMIFS(PL_Kochi!G:G,PL_Kochi!$B:$B,PL_Consol!$B42)+SUMIFS(PL_Calicut!G:G,PL_Calicut!$B:$B,PL_Consol!$B42)+SUMIFS(PL_FNB!G:G,PL_FNB!$B:$B,PL_Consol!$B42) -> 7.2443167 | I42: =SUMIFS(PL_Kochi!H:H,PL_Kochi!$B:$B,PL_Consol!$B42)+SUMIFS(PL_Calicut!H:H,PL_Calicut!$B:$B,PL_Consol!$B42)+SUMIFS(PL_FNB!H:H,PL_FNB!$B:$B,PL_Consol!$B42) -> 6.5759747 | J42: =SUMIFS(PL_Kochi!I:I,PL_Kochi!$B:$B,PL_Consol!$B42)+SUMIFS(PL_Calicut!I:I,PL_Calicut!$B:$B,PL_Consol!$B42)+SUMIFS(PL_FNB!I:I,PL_FNB!$B:$B,PL_Consol!$B42) -> 2.6668361 | K42: =SUMIFS(PL_Kochi!J:J,PL_Kochi!$B:$B,PL_Consol!$B42)+SUMIFS(PL_Calicut!J:J,PL_Calicut!$B:$B,PL_Consol!$B42)+SUMIFS(PL_FNB!J:J,PL_FNB!$B:$B,PL_Consol!$B42) -> 3.3780767 | L42: =SUMIFS(PL_Kochi!K:K,PL_Kochi!$B:$B,PL_Consol!$B42)+SUMIFS(PL_Calicut!K:K,PL_Calicut!$B:$B,PL_Consol!$B42)+SUMIFS(PL_FNB!K:K,PL_FNB!$B:$B,PL_Consol!$B42) -> 2.6934718 | M42: =SUMIFS(PL_Kochi!L:L,PL_Kochi!$B:$B,PL_Consol!$B42)+SUMIFS(PL_Calicut!L:L,PL_Calicut!$B:$B,PL_Consol!$B42)+SUMIFS(PL_FNB!L:L,PL_FNB!$B:$B,PL_Consol!$B42) -> 2.7732613 | N42: =SUMIFS(PL_Kochi!M:M,PL_Kochi!$B:$B,PL_Consol!$B42)+SUMIFS(PL_Calicut!M:M,PL_Calicut!$B:$B,PL_Consol!$B42)+SUMIFS(PL_FNB!M:M,PL_FNB!$B:$B,PL_Consol!$B42) -> 2.5378542 | O42: =SUMIFS(PL_Kochi!N:N,PL_Kochi!$B:$B,PL_Consol!$B42)+SUMIFS(PL_Calicut!N:N,PL_Calicut!$B:$B,PL_Consol!$B42)+SUMIFS(PL_FNB!N:N,PL_FNB!$B:$B,PL_Consol!$B42) -> 13.389736 | P42: =SUM(D42:O42) -> 62.114766 | Q42: 60 | R42: 33.23 | S42: =SUMIFS(PL_Kochi!R:R,PL_Kochi!$B:$B,PL_Consol!$B42)+SUMIFS(PL_Calicut!R:R,PL_Calicut!$B:$B,PL_Consol!$B42)+SUMIFS(PL_FNB!R:R,PL_FNB!$B:$B,PL_Consol!$B42) -> 1.8106894 | T42: =SUMIFS(PL_Kochi!S:S,PL_Kochi!$B:$B,PL_Consol!$B42)+SUMIFS(PL_Calicut!S:S,PL_Calicut!$B:$B,PL_Consol!$B42)+SUMIFS(PL_FNB!S:S,PL_FNB!$B:$B,PL_Consol!$B42) -> 2.2113322 | U42: 7.8 | V42: =IFERROR(S42/D42-1,"-") -> 3.9579495 | W42: =IFERROR(S42/O42-1,"-") -> -0.86477034 | X42: =IFERROR(S42/U42,"-") -> 0.23213967
B43: PBT | D43: =D41-D42 -> 665.13736 | E43: =E41-E42 -> 867.5719 | F43: =F41-F42 -> 491.49687 | G43: =G41-G42 -> 824.02703 | H43: =H41-H42 -> 982.00882 | I43: =I41-I42 -> 877.1455 | J43: =J41-J42 -> 805.3788 | K43: =K41-K42 -> 676.2026 | ... U43: =U41-U42 -> 695.45733 | V43: =IFERROR(S43/D43-1,"-") -> 0.36816704 | W43: =IFERROR(S43/O43-1,"-") -> 0.61913388 | X43: =IFERROR(S43/U43,"-") -> 1.3085188
B44: Tax | D44: =IF(D43>0,D43*$R$44/$R$43,0) -> 172.11984 | E44: =IF(E43>0,E43*$R$44/$R$43,0) -> 224.5045 | F44: =IF(F43>0,F43*$R$44/$R$43,0) -> 127.1863 | G44: =IF(G43>0,G43*$R$44/$R$43,0) -> 213.23625 | H44: =IF(H43>0,H43*$R$44/$R$43,0) -> 254.11773 | I44: =IF(I43>0,I43*$R$44/$R$43,0) -> 226.9819 | J44: =IF(J43>0,J43*$R$44/$R$43,0) -> 208.41059 | K44: =IF(K43>0,K43*$R$44/$R$43,0) -> 174.98323 | ... O44: =IF(O43>0,O43*$R$44/$R$43,0) -> 145.44115 | P44: =SUM(D44:O44) -> 2484.8765 | Q44: 1757.974 | R44: 1362.02 | S44: =IF(S43>0,S43*$R$44/$R$43,0) -> 235.48869 | T44: =IF(T43>0,T43*$R$44/$R$43,0) -> 266.90524 | U44: 180 | V44: =IFERROR(S44/D44-1,"-") -> 0.36816704 | W44: =IFERROR(S44/O44-1,"-") -> 0.61913388 | X44: =IFERROR(S44/U44,"-") -> 1.3082705
B45: PAT | D45: =D43-D44 -> 493.01752 | E45: =E43-E44 -> 643.06739 | F45: =F43-F44 -> 364.31056 | G45: =G43-G44 -> 610.79078 | H45: =H43-H44 -> 727.89109 | I45: =I43-I44 -> 650.1636 | J45: =J43-J44 -> 596.96821 | K45: =K43-K44 -> 501.21937 | ... U45: =U43-U44 -> 515.45733 | V45: =IFERROR(S45/D45-1,"-") -> 0.36816704 | W45: =IFERROR(S45/O45-1,"-") -> 0.61913388 | X45: =IFERROR(S45/U45,"-") -> 1.3086056
B52: Common Size Statement
U53: Bud
B54: Particulars | C54: Anx | D54: 45748 | E54: May | F54: Jun | G54: Jul | H54: Aug | I54: Sep | J54: Oct | K54: Nov | L54: Dec | M54: Jan | N54: Feb | O54: 46082 | P54: YTD | Q54: Bud | R54: FY25 | S54: 46113 | T54: 46143 | U54: 46113
B55: Revenue
B56: IP Revenue | C56: 1 | D56: =D7/D$15 -> 0.38270773 | E56: =E7/E$15 -> 0.37130273 | F56: =F7/F$15 -> 0.36891188 | G56: =G7/G$15 -> 0.36851436 | H56: =H7/H$15 -> 0.3929209 | I56: =I7/I$15 -> 0.38047866 | J56: =J7/J$15 -> 0.39364954 | K56: =K7/K$15 -> 0.39764624 | ... R56: =R7/R$15 -> 0.39152697 | S56: =IFERROR(S7/S$15,0) -> 0.40262653 | T56: =IFERROR(T7/T$15,0) -> 0.40569301 | U56: =IFERROR(U7/U$15,0) -> 0.34104141
B57: IP Pharmacy | C57: 2 | D57: =D8/D$15 -> 0.28576552 | E57: =E8/E$15 -> 0.302538 | F57: =F8/F$15 -> 0.30273871 | G57: =G8/G$15 -> 0.30910695 | H57: =H8/H$15 -> 0.29038514 | I57: =I8/I$15 -> 0.31165888 | J57: =J8/J$15 -> 0.29424177 | K57: =K8/K$15 -> 0.28814943 | ... R57: =R8/R$15 -> 0.30323709 | S57: =IFERROR(S8/S$15,0) -> 0.31997858 | T57: =IFERROR(T8/T$15,0) -> 0.32107847 | U57: =IFERROR(U8/U$15,0) -> 0.33631401
B58: OP Revenue | C58: 3 | D58: =D9/D$15 -> 0.18938193 | E58: =E9/E$15 -> 0.17732361 | F58: =F9/F$15 -> 0.18168219 | G58: =G9/G$15 -> 0.18980829 | H58: =H9/H$15 -> 0.17704938 | I58: =I9/I$15 -> 0.17671497 | J58: =J9/J$15 -> 0.17534992 | K58: =K9/K$15 -> 0.17899791 | ... R58: =R9/R$15 -> 0.16192007 | S58: =IFERROR(S9/S$15,0) -> 0.14755795 | T58: =IFERROR(T9/T$15,0) -> 0.15390337 | U58: =IFERROR(U9/U$15,0) -> 0.16713364
B59: OP Pharmacy | C59: 4 | D59: =D10/D$15 -> 0.095666967 | E59: =E10/E$15 -> 0.092155208 | F59: =F10/F$15 -> 0.088786091 | G59: =G10/G$15 -> 0.08889129 | H59: =H10/H$15 -> 0.095478162 | I59: =I10/I$15 -> 0.087019206 | J59: =J10/J$15 -> 0.088363594 | K59: =K10/K$15 -> 0.087388681 | ... R59: =R10/R$15 -> 0.082186223 | S59: =IFERROR(S10/S$15,0) -> 0.081639508 | T59: =IFERROR(T10/T$15,0) -> 0.077555143 | U59: =IFERROR(U10/U$15,0) -> 0.098708849
B60: Aurveda | C60: 5 | D60: =D11/D$15 -> 0 | E60: =E11/E$15 -> 0 | F60: =F11/F$15 -> 0 | G60: =G11/G$15 -> 0.00033308608 | H60: =H11/H$15 -> 0.000487695 | I60: =I11/I$15 -> 7.1043474e-05 | J60: =J11/J$15 -> 0.00012412719 | K60: =K11/K$15 -> 0.00011769776 | ... R60: =R11/R$15 -> 0 | S60: =IFERROR(S11/S$15,0) -> 1.4376433e-05 | T60: =IFERROR(T11/T$15,0) -> 3.3891033e-05 | U60: =IFERROR(U11/U$15,0) -> 0
B61: F & B Revenue | C61: 6 | D61: =D12/D$15 -> 0.039936257 | E61: =E12/E$15 -> 0.038123982 | F61: =F12/F$15 -> 0.039213374 | G61: =G12/G$15 -> 0.039395619 | H61: =H12/H$15 -> 0.038193194 | I61: =I12/I$15 -> 0.037598602 | J61: =J12/J$15 -> 0.037450712 | K61: =K12/K$15 -> 0.039293319 | ... R61: =R12/R$15 -> 0.039536051 | S61: =IFERROR(S12/S$15,0) -> 0.036698833 | T61: =IFERROR(T12/T$15,0) -> 0.037751067 | U61: =IFERROR(U12/U$15,0) -> 0.039500569
B62: Revenue From Operation | D62: =D13/D$15 -> 0.99345841 | E62: =E13/E$15 -> 0.98144353 | F62: =F13/F$15 -> 0.98133223 | G62: =G13/G$15 -> 0.99604959 | H62: =H13/H$15 -> 0.99451446 | I62: =I13/I$15 -> 0.99354136 | J62: =J13/J$15 -> 0.98917966 | K62: =K13/K$15 -> 0.99159328 | ... R62: =R13/R$15 -> 0.97840639 | S62: =IFERROR(S13/S$15,0) -> 0.98851578 | T62: =IFERROR(T13/T$15,0) -> 0.99601495 | U62: =IFERROR(U13/U$15,0) -> 0.98269848
B63: Other Income | C63: 7 | D63: =D14/D$15 -> 0.0065415941 | E63: =E14/E$15 -> 0.018556472 | F63: =F14/F$15 -> 0.018667768 | G63: =G14/G$15 -> 0.0039504055 | H63: =H14/H$15 -> 0.0054855396 | I63: =I14/I$15 -> 0.0064586398 | J63: =J14/J$15 -> 0.010820344 | K63: =K14/K$15 -> 0.0084067239 | ... R63: =R14/R$15 -> 0.021593606 | S63: =IFERROR(S14/S$15,0) -> 0.011484222 | T63: =IFERROR(T14/T$15,0) -> 0.0039850462 | U63: =IFERROR(U14/U$15,0) -> 0.017301524
B64: Total Revenue | D64: =SUM(D62:D63) -> 1 | E64: =SUM(E62:E63) -> 1 | F64: =SUM(F62:F63) -> 1 | G64: =SUM(G62:G63) -> 1 | H64: =SUM(H62:H63) -> 1 | I64: =SUM(I62:I63) -> 1 | J64: =SUM(J62:J63) -> 1 | K64: =SUM(K62:K63) -> 1 | ... R64: =SUM(R62:R63) -> 1 | S64: =IFERROR(S15/S$15,0) -> 1 | T64: =IFERROR(T15/T$15,0) -> 1 | U64: =IFERROR(U15/U$15,0) -> 1
B66: Material Cost | C66: 8 | D66: =D17/D$15 -> 0.25703798 | E66: =E17/E$15 -> 0.30660324 | F66: =F17/F$15 -> 0.33293588 | G66: =G17/G$15 -> 0.32636942 | H66: =H17/H$15 -> 0.30296117 | I66: =I17/I$15 -> 0.2935404 | J66: =J17/J$15 -> 0.31148935 | K66: =K17/K$15 -> 0.30651666 | ... R66: =R17/R$15 -> 0.30098843 | S66: =IFERROR(S17/S$15,0) -> 0.291265 | T66: =IFERROR(T17/T$15,0) -> 0.30388114 | U66: =IFERROR(U17/U$15,0) -> 0.27000447
B67: Doctor Cost | C67: 9 | D67: =D18/D$15 -> 0.1857358 | E67: =E18/E$15 -> 0.1692 | F67: =F18/F$15 -> 0.18267421 | G67: =G18/G$15 -> 0.17149258 | H67: =H18/H$15 -> 0.16689228 | I67: =I18/I$15 -> 0.17108639 | J67: =J18/J$15 -> 0.16582349 | K67: =K18/K$15 -> 0.18777959 | ... R67: =R18/R$15 -> 0.18152616 | S67: =IFERROR(S18/S$15,0) -> 0.16713936 | T67: =IFERROR(T18/T$15,0) -> 0.1564849 | U67: =IFERROR(U18/U$15,0) -> 0.16843812
B68: Employee Cost | C68: 10 | D68: =D19/D$15 -> 0.16476882 | E68: =E19/E$15 -> 0.16787307 | F68: =F19/F$15 -> 0.18336521 | G68: =G19/G$15 -> 0.160462 | H68: =H19/H$15 -> 0.15443248 | I68: =I19/I$15 -> 0.17223823 | J68: =J19/J$15 -> 0.16358144 | K68: =K19/K$15 -> 0.16900958 | ... R68: =R19/R$15 -> 0.17800844 | S68: =IFERROR(S19/S$15,0) -> 0.15383994 | T68: =IFERROR(T19/T$15,0) -> 0.14909343 | U68: =IFERROR(U19/U$15,0) -> 0.17985804
B69: Utilities-Power, fuel & water charges | C69: 11 | D69: =D20/D$15 -> 0.026458646 | E69: =E20/E$15 -> 0.025587396 | F69: =F20/F$15 -> 0.031193734 | G69: =G20/G$15 -> 0.02499579 | H69: =H20/H$15 -> 0.022607744 | I69: =I20/I$15 -> 0.024750988 | J69: =J20/J$15 -> 0.027688266 | K69: =K20/K$15 -> 0.025169026 | ... R69: =R20/R$15 -> 0.029960635 | S69: =IFERROR(S20/S$15,0) -> 0.02545429 | T69: =IFERROR(T20/T$15,0) -> 0.023638512 | U69: =IFERROR(U20/U$15,0) -> 0.027325422
B70: Repair & Maintenance | C70: 12 | D70: =D21/D$15 -> 0.021376789 | E70: =E21/E$15 -> 0.023778668 | F70: =F21/F$15 -> 0.036991613 | G70: =G21/G$15 -> 0.032107785 | H70: =H21/H$15 -> 0.034246086 | I70: =I21/I$15 -> 0.038815954 | J70: =J21/J$15 -> 0.040588521 | K70: =K21/K$15 -> 0.036661409 | ... R70: =R21/R$15 -> 0.031948839 | S70: =IFERROR(S21/S$15,0) -> 0.026801687 | T70: =IFERROR(T21/T$15,0) -> 0.017931534 | U70: =IFERROR(U21/U$15,0) -> 0.0053552335
B71: Marketing Cost | C71: 13 | D71: =D22/D$15 -> 0.023703132 | E71: =E22/E$15 -> 0.015449984 | F71: =F22/F$15 -> 0.017693703 | G71: =G22/G$15 -> 0.012976994 | H71: =H22/H$15 -> 0.016478967 | I71: =I22/I$15 -> 0.021448385 | J71: =J22/J$15 -> 0.020731452 | K71: =K22/K$15 -> 0.020349138 | ... R71: =R22/R$15 -> 0.016915124 | S71: =IFERROR(S22/S$15,0) -> 0.016831495 | T71: =IFERROR(T22/T$15,0) -> 0.011587254 | U71: =IFERROR(U22/U$15,0) -> 0.0039820967
B72: Lab Test Charges | C72: 14 | D72: =D23/D$15 -> 0.0049857117 | E72: =E23/E$15 -> 0.00497441 | F72: =F23/F$15 -> 0.0063624045 | G72: =G23/G$15 -> 0.0046909065 | H72: =H23/H$15 -> 0.0065860238 | I72: =I23/I$15 -> 0.0042396672 | J72: =J23/J$15 -> 0.0057717395 | K72: =K23/K$15 -> 0.0026145579 | ... R72: =R23/R$15 -> 0.0057190317 | S72: =IFERROR(S23/S$15,0) -> 0.0056326903 | T72: =IFERROR(T23/T$15,0) -> 0.0066656929 | U72: =IFERROR(U23/U$15,0) -> 0.031193091
B73: Rent Paid | C73: 15 | D73: =D24/D$15 -> 0.0067251187 | E73: =E24/E$15 -> 0.0057243675 | F73: =F24/F$15 -> 0.0071250962 | G73: =G24/G$15 -> 0.0043271236 | H73: =H24/H$15 -> 0.0066282497 | I73: =I24/I$15 -> 0.0066889665 | J73: =J24/J$15 -> 0.0054007099 | K73: =K24/K$15 -> 0.0060208301 | ... R73: =R24/R$15 -> 0.0043028034 | S73: =IFERROR(S24/S$15,0) -> 0.0053009167 | T73: =IFERROR(T24/T$15,0) -> 0.0052166976 | U73: =IFERROR(U24/U$15,0) -> 0.0225881
B74: House Keeping Expenses | C74: 16 | D74: =D25/D$15 -> 0.019638275 | E74: =E25/E$15 -> 0.019211707 | F74: =F25/F$15 -> 0.023366356 | G74: =G25/G$15 -> 0.019017269 | H74: =H25/H$15 -> 0.016840716 | I74: =I25/I$15 -> 0.018974616 | J74: =J25/J$15 -> 0.022323284 | K74: =K25/K$15 -> 0.018001832 | ... R74: =R25/R$15 -> 0.024742623 | S74: =IFERROR(S25/S$15,0) -> 0.02087647 | T74: =IFERROR(T25/T$15,0) -> 0.025770701 | U74: =IFERROR(U25/U$15,0) -> 0.0070258833
B75: Security Expenses | C75: 17 | D75: =D26/D$15 -> 0.0061778152 | E75: =E26/E$15 -> 0.0063161464 | F75: =F26/F$15 -> 0.0070143662 | G75: =G26/G$15 -> 0.0059584742 | H75: =H26/H$15 -> 0.004918686 | I75: =I26/I$15 -> 0.0048162149 | J75: =J26/J$15 -> 0.00646577 | K75: =K26/K$15 -> 0.0059713758 | ... R75: =R26/R$15 -> 0.0054751364 | S75: =IFERROR(S26/S$15,0) -> 0.0056312269 | T75: =IFERROR(T26/T$15,0) -> 0.0042449468 | U75: =IFERROR(U26/U$15,0) -> 0.0039363255
B76: Printing & Stationery | C76: 18 | D76: =D27/D$15 -> 0.0033910303 | E76: =E27/E$15 -> 0.0046480814 | F76: =F27/F$15 -> 0.0040117419 | G76: =G27/G$15 -> 0.0042637569 | H76: =H27/H$15 -> 0.003456317 | I76: =I27/I$15 -> 0.0036391214 | J76: =J27/J$15 -> 0.0045827808 | K76: =K27/K$15 -> 0.0033012083 | ... R76: =R27/R$15 -> 0.004040147 | S76: =IFERROR(S27/S$15,0) -> 0.0044226659 | T76: =IFERROR(T27/T$15,0) -> 0.0040611618 | U76: =IFERROR(U27/U$15,0) -> 0.0006865684
B77: Insurance | C77: 19 | D77: =D28/D$15 -> 0.00067897972 | E77: =E28/E$15 -> 0.0006371529 | F77: =F28/F$15 -> 0.00057848747 | G77: =G28/G$15 -> 0.00047099571 | H77: =H28/H$15 -> 0.00065277932 | I77: =I28/I$15 -> 0.00086417034 | J77: =J28/J$15 -> 0.00067965602 | K77: =K28/K$15 -> 0.00082517164 | ... R77: =R28/R$15 -> 0.00054792254 | S77: =IFERROR(S28/S$15,0) -> 0.00070926175 | T77: =IFERROR(T28/T$15,0) -> 0.00074324889 | U77: =IFERROR(U28/U$15,0) -> 0.00096119577
... B85: CSR Activity | C85: 27 | D85: =D36/D$15 -> 0.0022650122 | E85: =E36/E$15 -> 0.0022506005 | F85: =F36/F$15 -> 0.0031412547 | G85: =G36/G$15 -> 0.0025720867 | H85: =H36/H$15 -> 0.0022004792 | I85: =I36/I$15 -> 0.0025714434 | J85: =J36/J$15 -> 0.0022860867 | K85: =K36/K$15 -> 0.0021620464 | ... R85: =R36/R$15 -> 0.0033012453 | S85: =IFERROR(S36/S$15,0) -> 0.003506447 | T85: =IFERROR(T36/T$15,0) -> 0.0033891033 | U85: =IFERROR(U36/U$15,0) -> 0.0024487606
B86: Total Expenses | D86: =SUM(D66:D85) -> 0.73479733 | E86: =SUM(E66:E85) -> 0.76223976 | F86: =SUM(F66:F85) -> 0.84706417 | G86: =SUM(G66:G85) -> 0.78357941 | H86: =SUM(H66:H85) -> 0.75052541 | I86: =SUM(I66:I85) -> 0.77247902 | J86: =SUM(J66:J85) -> 0.79119703 | K86: =SUM(K66:K85) -> 0.80266167 | ... R86: =SUM(R66:R85) -> 0.80994905 | S86: =IFERROR(S37/S$15,0) -> 0.74053268 | T86: =IFERROR(T37/T$15,0) -> 0.72189501 | U86: =IFERROR(U37/U$15,0) -> 0.78184121
S87: =IFERROR(S38/S$15,0) -> 0 | U87: =IFERROR(U38/U$15,0) -> 0
B88: EBITDA | D88: =D39/D$15 -> 0.26520267 | E88: =E39/E$15 -> 0.23776024 | F88: =F39/F$15 -> 0.15293583 | G88: =G39/G$15 -> 0.21642059 | H88: =H39/H$15 -> 0.24947459 | I88: =I39/I$15 -> 0.22752098 | J88: =J39/J$15 -> 0.20880297 | K88: =K39/K$15 -> 0.19733833 | ... R88: =R39/R$15 -> 0.19005095 | S88: =IFERROR(S39/S$15,0) -> 0.25946732 | T88: =IFERROR(T39/T$15,0) -> 0.27810499 | U88: =IFERROR(U39/U$15,0) -> 0.21815879
B89: Depreciation | C89: 28 | D89: =D40/D$15 -> 0.06753313 | E89: =E40/E$15 -> 0.0043926927 | F89: =F40/F$15 -> 0.0048784996 | G89: =G40/G$15 -> 0.0041956676 | H89: =H40/H$15 -> 0.004077285 | I89: =I40/I$15 -> 0.0041543923 | J89: =J40/J$15 -> 0.0041625483 | K89: =K40/K$15 -> 0.0046604763 | ... R89: =R40/R$15 -> 0.062652946 | S89: =IFERROR(S40/S$15,0) -> 0.046367267 | T89: =IFERROR(T40/T$15,0) -> 0.044565044 | U89: =IFERROR(U40/U$15,0) -> 0.057214034
B90: EBIT (Operational Profit) | D90: =D41/D$15 -> 0.19766954 | E90: =E41/E$15 -> 0.23336754 | F90: =F41/F$15 -> 0.14805733 | G90: =G41/G$15 -> 0.21222492 | H90: =H41/H$15 -> 0.2453973 | I90: =I41/I$15 -> 0.22336658 | J90: =J41/J$15 -> 0.20464042 | K90: =K41/K$15 -> 0.19267785 | ... R90: =R41/R$15 -> 0.127398 | S90: =IFERROR(S41/S$15,0) -> 0.21310006 | T90: =IFERROR(T41/T$15,0) -> 0.23353995 | U90: =IFERROR(U41/U$15,0) -> 0.16094475
B91: Finance Cost | C91: 29 | D91: =D42/D$15 -> 0.00010847556 | E91: =E42/E$15 -> 0.0015323156 | F91: =F42/F$15 -> 0.0021964593 | G91: =G42/G$15 -> 0.0018773822 | H91: =H42/H$15 -> 0.0017970484 | I91: =I42/I$15 -> 0.0016621221 | J91: =J42/J$15 -> 0.0006753857 | K91: =K42/K$15 -> 0.00095776793 | ... R91: =R42/R$15 -> 0.00079927418 | S91: =IFERROR(S42/S$15,0) -> 0.00042316895 | T91: =IFERROR(T42/T$15,0) -> 0.00049962889 | U91: =IFERROR(U42/U$15,0) -> 0.0017850778
B92: PBT | D92: =D43/D$15 -> 0.19756106 | E92: =E43/E$15 -> 0.23183523 | F92: =F43/F$15 -> 0.14586087 | G92: =G43/G$15 -> 0.21034754 | H92: =H43/H$15 -> 0.24360025 | I92: =I43/I$15 -> 0.22170446 | J92: =J43/J$15 -> 0.20396504 | K92: =K43/K$15 -> 0.19172009 | ... R92: =R43/R$15 -> 0.12659873 | S92: =IFERROR(S43/S$15,0) -> 0.21267689 | T92: =IFERROR(T43/T$15,0) -> 0.23304032 | U92: =IFERROR(U43/U$15,0) -> 0.15915968
B93: Tax | C93: 30 | D93: =D44/D$15 -> 0.051123543 | E93: =E44/E$15 -> 0.059992784 | F93: =F44/F$15 -> 0.03774491 | G93: =G44/G$15 -> 0.054432342 | H93: =H44/H$15 -> 0.063037259 | I93: =I44/I$15 -> 0.057371211 | J93: =J44/J$15 -> 0.052780721 | K93: =K44/K$15 -> 0.049612053 | ... R93: =R44/R$15 -> 0.03276038 | S93: =IFERROR(S44/S$15,0) -> 0.055035115 | T93: =IFERROR(T44/T$15,0) -> 0.060304628 | U93: =IFERROR(U44/U$15,0) -> 0.041194104
B94: PAT | D94: =D45/D$15 -> 0.14643752 | E94: =E45/E$15 -> 0.17184245 | F94: =F45/F$15 -> 0.10811596 | G94: =G45/G$15 -> 0.1559152 | H94: =H45/H$15 -> 0.18056299 | I94: =I45/I$15 -> 0.16433325 | J94: =J45/J$15 -> 0.15118432 | K94: =K45/K$15 -> 0.14210803 | ... R94: =R45/R$15 -> 0.093838349 | S94: =IFERROR(S45/S$15,0) -> 0.15764177 | T94: =IFERROR(T45/T$15,0) -> 0.17273569 | U94: =IFERROR(U45/U$15,0) -> 0.11796557

Sheet Anx_Consl_PL
B2: LAKESHORE HOSPITAL AND RESEARCH CENTRE LIMITED
B3: Annexure to Consolidated Profit and Loss Account | E3: (Amount in Lakhs)
B5: Unit | C5: (All)
B7: Annex | C7: PL_Group | D7: Description | E7: Apr.25 | F7: Mar.26 | G7: Apr.26
B8: 1 | C8: IP Revenue | D8: CONCESSION LABORATORY & DIAG. SERVICES-IP | E8: 5.5394 | F8: 5.922577 | G8: 5.73906
D9: CONCESSION OTHER HEALTHCARE SERVICES - IP | E9: 8.8866 | F9: 12.558061 | G9: 14.722211
D10: CONCESSION VPS GOURMET FOOD COLLECTION | E10: 0.1575 | F10: 0.18438 | G10: 0.16707
D11: CONCESSION-IP BILLING | E11: 0 | F11: 0 | G11: 0
D12: COSMETIC SURGERY COLLECTION-IP | E12: 0 | F12: 0 | G12: -2.573
D13: CREDIT DISCOUNT A/C - ON LINE | E13: 28.5021 | F13: 23.737713 | G13: 36.731416
D14: CREDIT DISPUTE A/C - ON LINE | E14: 1.0371 | F14: 68.676727 | G14: 1.556176
D15: GUEST LAUNDRY SERVICES-IP | E15: -0.5868 | F15: -0.6634576 | G15: -0.8951186
D16: IP BILLING COLLECTION | E16: 0 | F16: 0 | G16: 0
D17: IP EXTRA DISCOUNT ACCOUNT | E17: 26.3499 | F17: 31.08558 | G17: 33.761783
D18: LABORATORY & DIAG. SERVICES-IP | E18: -272.5816 | F18: -337.64713 | G18: -397.53293
D19: OTHER HEALTHCARE SERVICES- IP | E19: -1085.3805 | F19: -1188.0634 | G19: -1412.3968
D20: ROOM RENT TAXABLE | E20: 0 | F20: -2.3164 | G20: -1.6495
B21: 1 Total | E21: -1288.0763 | F21: -1386.5254 | G21: -1722.3697
B22: 2 | C22: IP Pharmacy | D22: CONCESSION-PHARMACY NONTAXABLE | E22: 0.0414 | F22: 0.1460842 | G22: 0.0386901
D23: PHARMACY REVENUE-NON TAXABLE | E23: -961.8401 | F23: -1187.5459 | G23: -1368.8541
B24: 2 Total | E24: -961.7987 | F24: -1187.3998 | G24: -1368.8154
B25: 3 | C25: OP Revenue | D25: ASHWAS HOME CARE -OP | E25: 0 | F25: 0 | G25: 0
D26: BLOOD BANK COLLECTION-OP | E26: 0 | F26: 0 | G26: 0
D27: CONCESSION LABORATORY & DIAG. SERVICES-OP | E27: 8.9977 | F27: 10.98005 | G27: 10.252115
D28: CONCESSION-OP CONSULTATION | E28: 0 | F28: 0 | G28: 0.005
D29: CONCESSION-OTHER HEALTHCARE SERVICES-OP | E29: 16.6504 | F29: 13.703861 | G29: 10.00199
D30: CREDIT DISCOUNT A/C - ONLINE | E30: 0 | F30: 0 | G30: 0
D31: LAB OUSOURCING INCOME | E31: 0 | F31: 1.74799 | G31: 1.893845
D32: LABORATORY & DIAG. SERVICES-OP | E32: -382.4001 | F32: -374.72865 | G32: -372.80802
D33: OP CREDIT A/C - ON LINE | E33: 0 | F33: 0 | G33: 0
D34: OTHER HEALTHCARE SERVICES-OP | E34: -280.232 | F34: -270.24716 | G34: -279.52111
D35: PURCHASE ASSETS CALICUT STORE | E35: 0 | F35: 0.034 | G35: 0
D36: HEALTHCARE SERVICE-CAMP | G36: -0.755
B37: 3 Total | E37: -636.984 | F37: -618.50991 | G37: -630.93118
B38: 4 | C38: OP Pharmacy | D38: CASUALITY PHARMACY - OP | E38: 0.0062 | F38: 0.0550692 | G38: 0.0661579
D39: CONCESSION-PHARMACY NONTAXABLE | E39: 0 | F39: 0.0001395 | G39: 4.5e-05
D40: CONCESSION-PHARMACY TAXABLE | E40: 14.0798 | F40: 16.109361 | G40: 16.335555
D41: PHARMACY REVENUE-NON TAXABLE | E41: -0.0123 | F41: -0.0072 | G41: -0.0009
D42: PHARMACY REVENUE-TAXABLE | E42: -335.4855 | F42: -362.37067 | G42: -364.94838
B43: 4 Total | E43: -321.4118 | F43: -346.2133 | G43: -348.54752
B44: 5 | C44: Aurveda | D44: CONCESSION - AYURVEDA | F44: 0 | G44: 0
D45: OTHER HEALTH SERVICES AYURVEDA | E45: 0 | F45: -0.624 | G45: -0.0615
B46: 5 Total | E46: 0 | F46: -0.624 | G46: -0.0615
B47: 6 | C47: F & B Revenue | D47: AERATED SOFTDRINKS SALES | F47: -0.2562939 | G47: -0.3585993
D48: AERATED SOFTDRINKS SALES (CESS) | E48: -0.3483 | F48: 0 | G48: 0
D49: BAKERY SALES | E49: -6.3488 | F49: -6.6073337 | G49: -6.4669641
D50: BANQUET FUNCTION SALES | E50: -2.1872 | F50: -0.8612845 | G50: -0.14
D51: CALICUT - COFEEBERRY SALES | E51: -0.0004 | F51: 0 | G51: 0
D52: COFFEEBERRY SALES | E52: -13.956 | F52: -12.539301 | G52: -14.528166
D53: FEED REVENUE FROM IP SERVICES | E53: -3.1615 | F53: -3.8569592 | G53: -4.9456552
D54: GOURMET RESTAURANT SALES | E54: -46.8802 | F54: -50.914795 | G54: -56.336823
D55: IP SALES - BYSTANDERS FOOD | E55: -29.4061 | F55: -28.846163 | G55: -35.942488
D56: IP SALES - PATIENT SERVICE CHARGES | E56: -2.7665 | F56: -2.703555 | G56: -3.37089
D57: IP SALES - PATIENTS FOOD | E57: -21.5855 | F57: -20.88905 | G57: -26.93112
D58: MRP SALES @ 28 | E58: 0 | F58: 0 | G58: 0
D59: MRP SALES @0% | E59: -0.0193 | F59: -0.0156651 | G59: -0.026785
... D66: X MAS CAKE SALE | E66: 0 | F66: 0 | G66: 0
B67: 6 Total | E67: -133.4552 | F67: -134.02744 | G67: -156.02992
B68: 7 | C68: OTHER INCOME | D68: ACLS/BLS COURSE FEE FROM STUDENTS | E68: -0.1299 | F68: -1.02524 | G68: -0.0607373
D69: CME PROGRAME INCOME | E69: 0 | F69: 0 | G69: 0
D70: DISCOUNT RECEIVED | E70: 0 | F70: -1.2994 | G70: -0.3299672
D71: DNB TRAINING FEE RECEIVED | E71: -4.025 | F71: -4.05 | G71: -4.4
D72: EM(MEM) TRAINING FEE RECEIVED | F72: 0 | G72: 0
D73: EXCESS CASH RECEIVED | F73: 0 | G73: 0
D74: INCOME FROM CLINICAL STUDIES | E74: 3.75 | F74: 0 | G74: 0
D75: INCOME FROM GOVERNMENT GRANT | E75: 0 | F75: 0 | G75: 0
D76: INTEREST RECEIVED | E76: 0 | F76: -12.3613 | G76: 0
D77: INTEREST RECEIVED ON FD | E77: -1.0395 | F77: -327.43719 | G77: -36.694783
D78: INTEREST RECEIVED ON KSEB | E78: 0 | F78: 0 | G78: 0
D79: MISCELLANEOUS INCOME | E79: -0.0208 | F79: -0.11991 | G79: -0.07966
D80: NOTICE PAY | E80: 0.2584 | F80: -1.58159 | G80: -1.59492
D81: OTHER EXCESS | E81: 0 | F81: 0 | G81: 0
D82: OTHER INCOME | E82: 0 | F82: 0.2342179 | G82: 0
D83: PROFIT ON EXCHANGE FLUCTUATION | E83: 0 | F83: 0 | G83: 0
D84: PROFIT ON SALE OF FIXED ASSETS | E84: 0 | F84: 0 | G84: 0
D85: RENT RECEIVED | E85: -1.3846 | F85: -2.13008 | G85: -1.96716
... D92: VALET PARKING INCOME | E92: -0.4627 | F92: -0.43135 | G92: -0.26525
D93: AGOI FELLOWSHIP FEE
B94: 7 Total | E94: -22.0169 | F94: -352.97441 | G94: -49.125418
B95: 8 | C95: Material Cost | D95: Closing Stock | E95: -1023.3496 | F95: -1043.7733 | G95: -1032.9093
D96: CONSUMABLES & ACCESSORIES | E96: 0 | F96: 0 | G96: 0
D97: DISCOUNTS & ALLOWANCES | E97: -0.0497 | F97: -0.0610189 | G97: -0.0468847
D98: Opening Stock | E98: 864.0326 | F98: 1009.5838 | G98: 1035.7733
D99: PURCHASE - ASSETS | E99: 0 | F99: 0 | G99: 0.3106343
D100: PURCHASE - BEVERAGES | E100: 2.8712 | F100: 2.6682158 | G100: 3.0565979
D101: PURCHASE - BLOCK STOCK | E101: 4.5198 | F101: 0.1154006 | G101: 0.7220192
D102: PURCHASE - CAKE MIXING ITEMS | E102: 0 | F102: 0 | G102: 0
D103: PURCHASE - CROCKERY & CUTLERY | E103: -0.0166 | F103: -0.0174 | G103: -0.10136
D104: PURCHASE - FISH,MEAT & EGG | E104: 12.564 | F104: 13.144751 | G104: 14.839602
D105: PURCHASE - FRUITS & VEGETABLES | E105: 8.0771 | F105: 10.278299 | G105: 10.783128
D106: PURCHASE - FUEL | E106: 5.5756 | F106: 6.9769034 | G106: 7.319997
D107: PURCHASE - MILK,CURD & BUTTER MILK | E107: 8.8909 | F107: 10.696384 | G107: 10.935893
... D111: PURCHASE-ASSETS(GS) | E111: 0 | F111: 0 | G111: 5.3237556
D112: PURCHASE-CHEMICALS(GS) | F112: -0.0103066 | G112: 0
D113: PURCHASE-CONSIGNMENT STORE | E113: 7.1353 | F113: 23.207178 | G113: 18.373715
D114: PURCHASE-CONSUMABLE(GS) | E114: 434.2076 | F114: 439.10318 | G114: 492.71861
D115: PURCHASE-INSTRUMENTS(GS) | E115: 1.0262 | F115: 2.50232 | G115: 7.3642267
D116: PURCHASE-LAB MATERIALSGS) | E116: 0 | F116: 0 | G116: 0
D117: PURCHASE-MEDICAL CONSUMABLE(GS) | E117: 0 | F117: 0.1176036 | G117: 0.10976
D118: PURCHASE-MEDICAL GAS(GS) | E118: 3.8882 | F118: 5.56482 | G118: 5.8336714
...

Sheet PL_Kochi
B1: LAKESHORE HOSPITAL - KOCHI
B2: Profit and Loss Statement (Amount in Lakhs) | E2: (Amount in Lakhs)
C4: SMLY | D4: SMLY | N4: PM | R4: PM | S4: CM | T4: Budget | U4: Growth & Ach %
B5: Particulars | C5: 45748 | D5: 45778 | E5: 45809 | F5: 45839 | G5: 45870 | H5: 45901 | I5: 45931 | J5: 45962 | K5: 45992 | L5: 46023 | M5: 46054 | N5: 46082 | O5: YTD | P5: Bud | Q5: FY25 | R5: 46113 | S5: 46143 | T5: 46143 | U5: YOY Gr. | V5: MOM Gr. | W5: BUD Ach.
B6: Revenue
B7: IP Revenue | C7: =-SUMIFS(TB_Kochi[Apr],TB_Kochi[MIS_Group1],$B7)/10^5 -> 1288.0763 | D7: =-SUMIFS(TB_Kochi[May],TB_Kochi[MIS_Group1],$B7)/10^5 -> 1389.0974 | E7: =-SUMIFS(TB_Kochi[Jun],TB_Kochi[MIS_Group1],$B7)/10^5 -> 1242.7087 | F7: =-SUMIFS(TB_Kochi[Jul],TB_Kochi[MIS_Group1],$B7)/10^5 -> 1443.2515 | G7: =-SUMIFS(TB_Kochi[Aug],TB_Kochi[MIS_Group1],$B7)/10^5 -> 1583.543 | H7: =-SUMIFS(TB_Kochi[Sep],TB_Kochi[MIS_Group1],$B7)/10^5 -> 1504.9166 | I7: =-SUMIFS(TB_Kochi[Oct],TB_Kochi[MIS_Group1],$B7)/10^5 -> 1553.9567 | J7: =-SUMIFS(TB_Kochi[Nov],TB_Kochi[MIS_Group1],$B7)/10^5 -> 1402.0929 | K7: =-SUMIFS(TB_Kochi[Dec],TB_Kochi[MIS_Group1],$B7)/10^5 -> 1476.3778 | L7: =-SUMIFS(TB_Kochi[Jan],TB_Kochi[MIS_Group1],$B7)/10^5 -> 1717.1508 | M7: =-SUMIFS(TB_Kochi[Feb],TB_Kochi[MIS_Group1],$B7)/10^5 -> 1569.1112 | N7: =-SUMIFS(TB_Kochi[Mar],TB_Kochi[MIS_Group1],$B7)/10^5 -> 1386.5254 | O7: =SUM(C7:N7) -> 17556.808 | P7: 20170.76 | R7: =-SUMIFS(TB_Kochi[Apr_26],TB_Kochi[MIS_Group1],$B7)/10^5 -> 1722.3697 | S7: =-SUMIFS(TB_Kochi!AB:AB,TB_Kochi!J:J,$B7)/10^5 -> 1795.5768 | U7: =IFERROR(R7/C7-1,"-") -> 0.33716428 | V7: =IFERROR(R7/N7-1,"-") -> 0.24222009 | W7: =IFERROR(R7/T7,"-") -> - | X7: =S7 -> 1795.5768
B8: IP Pharmacy | C8: =-SUMIFS(TB_Kochi[Apr],TB_Kochi[MIS_Group1],$B8)/10^5 -> 961.79874 | D8: =-SUMIFS(TB_Kochi[May],TB_Kochi[MIS_Group1],$B8)/10^5 -> 1131.8386 | E8: =-SUMIFS(TB_Kochi[Jun],TB_Kochi[MIS_Group1],$B8)/10^5 -> 1019.7991 | F8: =-SUMIFS(TB_Kochi[Jul],TB_Kochi[MIS_Group1],$B8)/10^5 -> 1210.588 | G8: =-SUMIFS(TB_Kochi[Aug],TB_Kochi[MIS_Group1],$B8)/10^5 -> 1170.3052 | H8: =-SUMIFS(TB_Kochi[Sep],TB_Kochi[MIS_Group1],$B8)/10^5 -> 1232.712 | I8: =-SUMIFS(TB_Kochi[Oct],TB_Kochi[MIS_Group1],$B8)/10^5 -> 1161.5382 | J8: =-SUMIFS(TB_Kochi[Nov],TB_Kochi[MIS_Group1],$B8)/10^5 -> 1016.0092 | K8: =-SUMIFS(TB_Kochi[Dec],TB_Kochi[MIS_Group1],$B8)/10^5 -> 1099.582 | L8: =-SUMIFS(TB_Kochi[Jan],TB_Kochi[MIS_Group1],$B8)/10^5 -> 1265.5351 | M8: =-SUMIFS(TB_Kochi[Feb],TB_Kochi[MIS_Group1],$B8)/10^5 -> 1140.6163 | N8: =-SUMIFS(TB_Kochi[Mar],TB_Kochi[MIS_Group1],$B8)/10^5 -> 1187.3998 | O8: =SUM(C8:N8) -> 13597.722 | P8: 15621.669 | R8: =-SUMIFS(TB_Kochi[Apr_26],TB_Kochi[MIS_Group1],$B8)/10^5 -> 1368.8154 | S8: =-SUMIFS(TB_Kochi!AB:AB,TB_Kochi!J:J,$B8)/10^5 -> 1421.0771 | U8: =IFERROR(R8/C8-1,"-") -> 0.42318278 | V8: =IFERROR(R8/N8-1,"-") -> 0.15278395 | W8: =IFERROR(R8/T8,"-") -> - | X8: =S8 -> 1421.0771
B9: OP Revenue | C9: =-SUMIFS(TB_Kochi[Apr],TB_Kochi[MIS_Group1],$B9)/10^5 -> 625.0784 | D9: =-SUMIFS(TB_Kochi[May],TB_Kochi[MIS_Group1],$B9)/10^5 -> 654.08417 | E9: =-SUMIFS(TB_Kochi[Jun],TB_Kochi[MIS_Group1],$B9)/10^5 -> 601.68523 | F9: =-SUMIFS(TB_Kochi[Jul],TB_Kochi[MIS_Group1],$B9)/10^5 -> 730.50899 | G9: =-SUMIFS(TB_Kochi[Aug],TB_Kochi[MIS_Group1],$B9)/10^5 -> 700.55691 | H9: =-SUMIFS(TB_Kochi[Sep],TB_Kochi[MIS_Group1],$B9)/10^5 -> 686.00636 | I9: =-SUMIFS(TB_Kochi[Oct],TB_Kochi[MIS_Group1],$B9)/10^5 -> 679.96522 | J9: =-SUMIFS(TB_Kochi[Nov],TB_Kochi[MIS_Group1],$B9)/10^5 -> 620.32297 | K9: =-SUMIFS(TB_Kochi[Dec],TB_Kochi[MIS_Group1],$B9)/10^5 -> 639.0722 | L9: =-SUMIFS(TB_Kochi[Jan],TB_Kochi[MIS_Group1],$B9)/10^5 -> 731.91998 | M9: =-SUMIFS(TB_Kochi[Feb],TB_Kochi[MIS_Group1],$B9)/10^5 -> 655.11018 | N9: =-SUMIFS(TB_Kochi[Mar],TB_Kochi[MIS_Group1],$B9)/10^5 -> 607.94325 | O9: =SUM(C9:N9) -> 7932.2539 | P9: 7962.6052 | R9: =-SUMIFS(TB_Kochi[Apr_26],TB_Kochi[MIS_Group1],$B9)/10^5 -> 621.77163 | S9: =-SUMIFS(TB_Kochi!AB:AB,TB_Kochi!J:J,$B9)/10^5 -> 670.49782 | U9: =IFERROR(R9/C9-1,"-") -> -0.0052901692 | V9: =IFERROR(R9/N9-1,"-") -> 0.022746156 | W9: =IFERROR(R9/T9,"-") -> - | X9: =S9+PL_Calicut!S7 -> 681.16854
B10: OP Pharmacy | C10: =-SUMIFS(TB_Kochi[Apr],TB_Kochi[MIS_Group1],$B10)/10^5 -> 305.03794 | D10: =-SUMIFS(TB_Kochi[May],TB_Kochi[MIS_Group1],$B10)/10^5 -> 330.0132 | E10: =-SUMIFS(TB_Kochi[Jun],TB_Kochi[MIS_Group1],$B10)/10^5 -> 283.50114 | F10: =-SUMIFS(TB_Kochi[Jul],TB_Kochi[MIS_Group1],$B10)/10^5 -> 329.51464 | G10: =-SUMIFS(TB_Kochi[Aug],TB_Kochi[MIS_Group1],$B10)/10^5 -> 367.53428 | H10: =-SUMIFS(TB_Kochi[Sep],TB_Kochi[MIS_Group1],$B10)/10^5 -> 324.20881 | I10: =-SUMIFS(TB_Kochi[Oct],TB_Kochi[MIS_Group1],$B10)/10^5 -> 327.523 | J10: =-SUMIFS(TB_Kochi[Nov],TB_Kochi[MIS_Group1],$B10)/10^5 -> 289.5593 | K10: =-SUMIFS(TB_Kochi[Dec],TB_Kochi[MIS_Group1],$B10)/10^5 -> 318.32859 | L10: =-SUMIFS(TB_Kochi[Jan],TB_Kochi[MIS_Group1],$B10)/10^5 -> 350.44439 | M10: =-SUMIFS(TB_Kochi[Feb],TB_Kochi[MIS_Group1],$B10)/10^5 -> 312.6858 | N10: =-SUMIFS(TB_Kochi[Mar],TB_Kochi[MIS_Group1],$B10)/10^5 -> 327.14018 | O10: =SUM(C10:N10) -> 3865.4913 | P10: 3844.6809 | R10: =-SUMIFS(TB_Kochi[Apr_26],TB_Kochi[MIS_Group1],$B10)/10^5 -> 327.20468 | S10: =-SUMIFS(TB_Kochi!AB:AB,TB_Kochi!J:J,$B10)/10^5 -> 326.89188 | U10: =IFERROR(R10/C10-1,"-") -> 0.072668807 | V10: =IFERROR(R10/N10-1,"-") -> 0.00019717327 | W10: =IFERROR(R10/T10,"-") -> - | X10: =S10+PL_Calicut!S8 -> 343.25514
B11: Clinical Studies | C11: =-SUMIFS(TB_Kochi[Apr],TB_Kochi[MIS_Group1],$B11)/10^5 -> 0 | D11: =-SUMIFS(TB_Kochi[May],TB_Kochi[MIS_Group1],$B11)/10^5 -> 0 | E11: =-SUMIFS(TB_Kochi[Jun],TB_Kochi[MIS_Group1],$B11)/10^5 -> 0 | F11: =-SUMIFS(TB_Kochi[Jul],TB_Kochi[MIS_Group1],$B11)/10^5 -> 0 | G11: =-SUMIFS(TB_Kochi[Aug],TB_Kochi[MIS_Group1],$B11)/10^5 -> 0 | H11: =-SUMIFS(TB_Kochi[Sep],TB_Kochi[MIS_Group1],$B11)/10^5 -> 0 | I11: =-SUMIFS(TB_Kochi[Oct],TB_Kochi[MIS_Group1],$B11)/10^5 -> 0 | J11: =-SUMIFS(TB_Kochi[Nov],TB_Kochi[MIS_Group1],$B11)/10^5 -> 0 | K11: =-SUMIFS(TB_Kochi[Dec],TB_Kochi[MIS_Group1],$B11)/10^5 -> 0 | L11: =-SUMIFS(TB_Kochi[Jan],TB_Kochi[MIS_Group1],$B11)/10^5 -> 0 | M11: =-SUMIFS(TB_Kochi[Feb],TB_Kochi[MIS_Group1],$B11)/10^5 -> 0 | N11: =-SUMIFS(TB_Kochi[Mar],TB_Kochi[MIS_Group1],$B11)/10^5 -> 0 | O11: =SUM(C11:N11) -> 0 | P11: 0 | R11: =-SUMIFS(TB_Kochi[Apr_26],TB_Kochi[MIS_Group1],$B11)/10^5 -> 0 | S11: =-SUMIFS(TB_Kochi!AB:AB,TB_Kochi!J:J,$B11)/10^5 -> 0 | U11: =IFERROR(R11/C11-1,"-") -> - | V11: =IFERROR(R11/N11-1,"-") -> - | W11: =IFERROR(R11/T11,"-") -> -
B12: Aurveda | C12: =-SUMIFS(TB_Kochi[Apr],TB_Kochi[MIS_Group1],$B12)/10^5 -> 0 | D12: =-SUMIFS(TB_Kochi[May],TB_Kochi[MIS_Group1],$B12)/10^5 -> 0 | E12: =-SUMIFS(TB_Kochi[Jun],TB_Kochi[MIS_Group1],$B12)/10^5 -> 0 | F12: =-SUMIFS(TB_Kochi[Jul],TB_Kochi[MIS_Group1],$B12)/10^5 -> 1.3045 | G12: =-SUMIFS(TB_Kochi[Aug],TB_Kochi[MIS_Group1],$B12)/10^5 -> 1.9655 | H12: =-SUMIFS(TB_Kochi[Sep],TB_Kochi[MIS_Group1],$B12)/10^5 -> 0.281 | I12: =-SUMIFS(TB_Kochi[Oct],TB_Kochi[MIS_Group1],$B12)/10^5 -> 0.49 | J12: =-SUMIFS(TB_Kochi[Nov],TB_Kochi[MIS_Group1],$B12)/10^5 -> 0.415 | K12: =-SUMIFS(TB_Kochi[Dec],TB_Kochi[MIS_Group1],$B12)/10^5 -> 0.469 | L12: =-SUMIFS(TB_Kochi[Jan],TB_Kochi[MIS_Group1],$B12)/10^5 -> 0.238 | M12: =-SUMIFS(TB_Kochi[Feb],TB_Kochi[MIS_Group1],$B12)/10^5 -> 0.23623 | N12: =-SUMIFS(TB_Kochi[Mar],TB_Kochi[MIS_Group1],$B12)/10^5 -> 0.624 | O12: =SUM(C12:N12) -> 6.02323 | P12: 0 | R12: =-SUMIFS(TB_Kochi[Apr_26],TB_Kochi[MIS_Group1],$B12)/10^5 -> 0.0615 | S12: =-SUMIFS(TB_Kochi!AB:AB,TB_Kochi!J:J,$B12)/10^5 -> 0.15 | U12: =IFERROR(R12/C12-1,"-") -> - | V12: =IFERROR(R12/N12-1,"-") -> -0.90144231 | W12: =IFERROR(R12/T12,"-") -> - | X12: =S12 -> 0.15
B13: Revenue From Operation | C13: =SUM(C7:C12) -> 3179.9914 | D13: =SUM(D7:D12) -> 3505.0334 | E13: =SUM(E7:E12) -> 3147.6942 | F13: =SUM(F7:F12) -> 3715.1677 | G13: =SUM(G7:G12) -> 3823.9049 | H13: =SUM(H7:H12) -> 3748.1248 | I13: =SUM(I7:I12) -> 3723.473 | J13: =SUM(J7:J12) -> 3328.3994 | ... P13: =SUM(P7:P12) -> 47599.715 | R13: =SUM(R7:R12) -> 4040.2229 | S13: =SUM(S7:S12) -> 4214.1935 | T13: =SUM(T7:T12) -> 0 | U13: =IFERROR(R13/C13-1,"-") -> 0.27051377 | V13: =IFERROR(R13/N13-1,"-") -> 0.15118116 | W13: =IFERROR(R13/T13,"-") -> - | X13: =PL_FNB!S7 -> 167.08431
B14: Other Income | C14: =-SUMIFS(TB_Kochi[Apr],TB_Kochi[MIS_Group1],$B14)/10^5 -> 22.016991 | D14: =-SUMIFS(TB_Kochi[May],TB_Kochi[MIS_Group1],$B14)/10^5 -> 69.422454 | E14: =-SUMIFS(TB_Kochi[Jun],TB_Kochi[MIS_Group1],$B14)/10^5 -> 62.766434 | F14: =-SUMIFS(TB_Kochi[Jul],TB_Kochi[MIS_Group1],$B14)/10^5 -> 14.721824 | G14: =-SUMIFS(TB_Kochi[Aug],TB_Kochi[MIS_Group1],$B14)/10^5 -> 21.990641 | H14: =-SUMIFS(TB_Kochi[Sep],TB_Kochi[MIS_Group1],$B14)/10^5 -> 25.248849 | I14: =-SUMIFS(TB_Kochi[Oct],TB_Kochi[MIS_Group1],$B14)/10^5 -> 42.587688 | J14: =-SUMIFS(TB_Kochi[Nov],TB_Kochi[MIS_Group1],$B14)/10^5 -> 29.415118 | K14: =-SUMIFS(TB_Kochi[Dec],TB_Kochi[MIS_Group1],$B14)/10^5 -> 13.164296 | L14: =-SUMIFS(TB_Kochi[Jan],TB_Kochi[MIS_Group1],$B14)/10^5 -> 50.157904 | M14: =-SUMIFS(TB_Kochi[Feb],TB_Kochi[MIS_Group1],$B14)/10^5 -> 207.81617 | N14: =-SUMIFS(TB_Kochi[Mar],TB_Kochi[MIS_Group1],$B14)/10^5 -> 352.79043 | O14: =SUM(C14:N14) -> 912.09879 | P14: 493.88162 | R14: =-SUMIFS(TB_Kochi[Apr_26],TB_Kochi[MIS_Group1],$B14)/10^5 -> 49.058138 | S14: =-SUMIFS(TB_Kochi!AB:AB,TB_Kochi!J:J,$B14)/10^5 -> 17.426953 | U14: =IFERROR(R14/C14-1,"-") -> 1.2281945 | V14: =IFERROR(R14/N14-1,"-") -> -0.86094255 | W14: =IFERROR(R14/T14,"-") -> - | X14: =S14+PL_Calicut!S10+PL_FNB!S8 -> 17.637613 | Z14: =S15+PL_Calicut!S11+PL_FNB!S9 -> 4425.9494 | AA14: =Z14-PL_Consol!T15 -> 0
B15: Total Revenue | C15: =C13+C14 -> 3202.0084 | D15: =D13+D14 -> 3574.4558 | E15: =E13+E14 -> 3210.4606 | F15: =F13+F14 -> 3729.8895 | G15: =G13+G14 -> 3845.8955 | H15: =H13+H14 -> 3773.3736 | I15: =I13+I14 -> 3766.0607 | J15: =J13+J14 -> 3357.8145 | ... P15: =P13+P14 -> 48093.596 | R15: =R13+R14 -> 4089.281 | S15: =S13+S14 -> 4231.6205 | T15: =T13+T14 -> 0 | U15: =IFERROR(R15/C15-1,"-") -> 0.27709878 | V15: =IFERROR(R15/N15-1,"-") -> 0.058734639 | W15: =IFERROR(R15/T15,"-") -> - | X15: =S15+PL_Calicut!S11+PL_FNB!S9 -> 4425.9494
P16: =SUMIFS(PL_Consol!Q:Q,PL_Consol!B:B,PL_Kochi!B16)-SUMIFS(PL_Calicut!P:P,PL_Calicut!B:B,PL_Kochi!B16)-SUMIFS(PL_FNB!P:P,PL_FNB!B:B,PL_Kochi!B16) -> 0 | U16: =IFERROR(R16/C16-1,"-") -> - | V16: =IFERROR(R16/N16-1,"-") -> - | W16: =IFERROR(R16/T16,"-") -> -
B17: Material Cost | C17: =SUMIFS(TB_Kochi[Apr],TB_Kochi[MIS_Group1],$B17)/10^5 -> 778.88535 | D17: =SUMIFS(TB_Kochi[May],TB_Kochi[MIS_Group1],$B17)/10^5 -> 1057.039 | E17: =SUMIFS(TB_Kochi[Jun],TB_Kochi[MIS_Group1],$B17)/10^5 -> 1034.0926 | F17: =SUMIFS(TB_Kochi[Jul],TB_Kochi[MIS_Group1],$B17)/10^5 -> 1181.8337 | G17: =SUMIFS(TB_Kochi[Aug],TB_Kochi[MIS_Group1],$B17)/10^5 -> 1121.2558 | H17: =SUMIFS(TB_Kochi[Sep],TB_Kochi[MIS_Group1],$B17)/10^5 -> 1068.9228 | I17: =SUMIFS(TB_Kochi[Oct],TB_Kochi[MIS_Group1],$B17)/10^5 -> 1131.1619 | J17: =SUMIFS(TB_Kochi[Nov],TB_Kochi[MIS_Group1],$B17)/10^5 -> 988.28382 | K17: =SUMIFS(TB_Kochi[Dec],TB_Kochi[MIS_Group1],$B17)/10^5 -> 1050.6063 | L17: =SUMIFS(TB_Kochi[Jan],TB_Kochi[MIS_Group1],$B17)/10^5 -> 1141.1299 | M17: =SUMIFS(TB_Kochi[Feb],TB_Kochi[MIS_Group1],$B17)/10^5 -> 1074.4556 | N17: =SUMIFS(TB_Kochi[Mar],TB_Kochi[MIS_Group1],$B17)/10^5 -> 955.74062 | O17: =SUM(C17:N17) -> 12583.407 | P17: 12704.328 | R17: =SUMIFS(TB_Kochi[Apr_26],TB_Kochi[MIS_Group1],$B17)/10^5 -> 1133.8735 | S17: =SUMIFS(TB_Kochi!AB:AB,TB_Kochi!J:J,$B17)/10^5 -> 1218.4473 | U17: =IFERROR(R17/C17-1,"-") -> 0.45576431 | V17: =IFERROR(R17/N17-1,"-") -> 0.18638203 | W17: =IFERROR(R17/T17,"-") -> -
B18: Doctor Cost | C18: =SUMIFS(TB_Kochi[Apr],TB_Kochi[MIS_Group1],$B18)/10^5 -> 614.33412 | D18: =SUMIFS(TB_Kochi[May],TB_Kochi[MIS_Group1],$B18)/10^5 -> 622.20414 | E18: =SUMIFS(TB_Kochi[Jun],TB_Kochi[MIS_Group1],$B18)/10^5 -> 605.03751 | F18: =SUMIFS(TB_Kochi[Jul],TB_Kochi[MIS_Group1],$B18)/10^5 -> 659.41217 | G18: =SUMIFS(TB_Kochi[Aug],TB_Kochi[MIS_Group1],$B18)/10^5 -> 660.74376 | H18: =SUMIFS(TB_Kochi[Sep],TB_Kochi[MIS_Group1],$B18)/10^5 -> 664.49548 | I18: =SUMIFS(TB_Kochi[Oct],TB_Kochi[MIS_Group1],$B18)/10^5 -> 643.06909 | J18: =SUMIFS(TB_Kochi[Nov],TB_Kochi[MIS_Group1],$B18)/10^5 -> 651.05653 | K18: =SUMIFS(TB_Kochi[Dec],TB_Kochi[MIS_Group1],$B18)/10^5 -> 678.18344 | L18: =SUMIFS(TB_Kochi[Jan],TB_Kochi[MIS_Group1],$B18)/10^5 -> 689.85884 | M18: =SUMIFS(TB_Kochi[Feb],TB_Kochi[MIS_Group1],$B18)/10^5 -> 672.48624 | N18: =SUMIFS(TB_Kochi[Mar],TB_Kochi[MIS_Group1],$B18)/10^5 -> 688.78896 | O18: =SUM(C18:N18) -> 7849.6703 | P18: 9630.14 | R18: =SUMIFS(TB_Kochi[Apr_26],TB_Kochi[MIS_Group1],$B18)/10^5 -> 704.08974 | S18: =SUMIFS(TB_Kochi!AB:AB,TB_Kochi!J:J,$B18)/10^5 -> 679.24983 | U18: =IFERROR(R18/C18-1,"-") -> 0.14610229 | V18: =IFERROR(R18/N18-1,"-") -> 0.022214032 | W18: =IFERROR(R18/T18,"-") -> -
B19: Employee Cost | C19: =SUMIFS(TB_Kochi[Apr],TB_Kochi[MIS_Group1],$B19)/10^5 -> 530.16576 | D19: =SUMIFS(TB_Kochi[May],TB_Kochi[MIS_Group1],$B19)/10^5 -> 602.84982 | E19: =SUMIFS(TB_Kochi[Jun],TB_Kochi[MIS_Group1],$B19)/10^5 -> 592.35521 | F19: =SUMIFS(TB_Kochi[Jul],TB_Kochi[MIS_Group1],$B19)/10^5 -> 602.80903 | G19: =SUMIFS(TB_Kochi[Aug],TB_Kochi[MIS_Group1],$B19)/10^5 -> 597.06983 | H19: =SUMIFS(TB_Kochi[Sep],TB_Kochi[MIS_Group1],$B19)/10^5 -> 656.45017 | I19: =SUMIFS(TB_Kochi[Oct],TB_Kochi[MIS_Group1],$B19)/10^5 -> 618.38475 | J19: =SUMIFS(TB_Kochi[Nov],TB_Kochi[MIS_Group1],$B19)/10^5 -> 570.37167 | K19: =SUMIFS(TB_Kochi[Dec],TB_Kochi[MIS_Group1],$B19)/10^5 -> 595.73767 | L19: =SUMIFS(TB_Kochi[Jan],TB_Kochi[MIS_Group1],$B19)/10^5 -> 583.65839 | M19: =SUMIFS(TB_Kochi[Feb],TB_Kochi[MIS_Group1],$B19)/10^5 -> 616.82495 | N19: =SUMIFS(TB_Kochi[Mar],TB_Kochi[MIS_Group1],$B19)/10^5 -> 642.41283 | O19: =SUM(C19:N19) -> 7209.0901 | P19: 9793.1601 | R19: =SUMIFS(TB_Kochi[Apr_26],TB_Kochi[MIS_Group1],$B19)/10^5 -> 631.91866 | S19: =SUMIFS(TB_Kochi!AB:AB,TB_Kochi!J:J,$B19)/10^5 -> 634.51068 | U19: =IFERROR(R19/C19-1,"-") -> 0.19192659 | V19: =IFERROR(R19/N19-1,"-") -> -0.016335541 | W19: =IFERROR(R19/T19,"-") -> -
B20: Lab Test Charges | C20: =SUMIFS(TB_Kochi[Apr],TB_Kochi[MIS_Group1],$B20)/10^5 -> 16.78037 | D20: =SUMIFS(TB_Kochi[May],TB_Kochi[MIS_Group1],$B20)/10^5 -> 18.60999 | E20: =SUMIFS(TB_Kochi[Jun],TB_Kochi[MIS_Group1],$B20)/10^5 -> 21.43226 | F20: =SUMIFS(TB_Kochi[Jul],TB_Kochi[MIS_Group1],$B20)/10^5 -> 18.37149 | G20: =SUMIFS(TB_Kochi[Aug],TB_Kochi[MIS_Group1],$B20)/10^5 -> 26.54288 | H20: =SUMIFS(TB_Kochi[Sep],TB_Kochi[MIS_Group1],$B20)/10^5 -> 16.76926 | I20: =SUMIFS(TB_Kochi[Oct],TB_Kochi[MIS_Group1],$B20)/10^5 -> 22.78431 | J20: =SUMIFS(TB_Kochi[Nov],TB_Kochi[MIS_Group1],$B20)/10^5 -> 9.21888 | K20: =SUMIFS(TB_Kochi[Dec],TB_Kochi[MIS_Group1],$B20)/10^5 -> 37.61713 | L20: =SUMIFS(TB_Kochi[Jan],TB_Kochi[MIS_Group1],$B20)/10^5 -> 30.036409 | M20: =SUMIFS(TB_Kochi[Feb],TB_Kochi[MIS_Group1],$B20)/10^5 -> 27.38476 | N20: =SUMIFS(TB_Kochi[Mar],TB_Kochi[MIS_Group1],$B20)/10^5 -> 22.10591 | O20: =SUM(C20:N20) -> 267.65365 | P20: 274.99917 | R20: =SUMIFS(TB_Kochi[Apr_26],TB_Kochi[MIS_Group1],$B20)/10^5 -> 24.08023 | S20: =SUMIFS(TB_Kochi!AB:AB,TB_Kochi!J:J,$B20)/10^5 -> 29.50202 | U20: =IFERROR(R20/C20-1,"-") -> 0.43502378 | V20: =IFERROR(R20/N20-1,"-") -> 0.089311863 | W20: =IFERROR(R20/T20,"-") -> -
B21: Utilities-Power, fuel & water charges | C21: =SUMIFS(TB_Kochi[Apr],TB_Kochi[MIS_Group1],$B21)/10^5 -> 80.580869 | D21: =SUMIFS(TB_Kochi[May],TB_Kochi[MIS_Group1],$B21)/10^5 -> 86.939696 | E21: =SUMIFS(TB_Kochi[Jun],TB_Kochi[MIS_Group1],$B21)/10^5 -> 96.876999 | F21: =SUMIFS(TB_Kochi[Jul],TB_Kochi[MIS_Group1],$B21)/10^5 -> 89.210936 | G21: =SUMIFS(TB_Kochi[Aug],TB_Kochi[MIS_Group1],$B21)/10^5 -> 82.562846 | H21: =SUMIFS(TB_Kochi[Sep],TB_Kochi[MIS_Group1],$B21)/10^5 -> 89.570169 | I21: =SUMIFS(TB_Kochi[Oct],TB_Kochi[MIS_Group1],$B21)/10^5 -> 100.60015 | J21: =SUMIFS(TB_Kochi[Nov],TB_Kochi[MIS_Group1],$B21)/10^5 -> 80.310699 | K21: =SUMIFS(TB_Kochi[Dec],TB_Kochi[MIS_Group1],$B21)/10^5 -> 90.216956 | L21: =SUMIFS(TB_Kochi[Jan],TB_Kochi[MIS_Group1],$B21)/10^5 -> 96.482086 | M21: =SUMIFS(TB_Kochi[Feb],TB_Kochi[MIS_Group1],$B21)/10^5 -> 83.417795 | N21: =SUMIFS(TB_Kochi[Mar],TB_Kochi[MIS_Group1],$B21)/10^5 -> 113.50918 | O21: =SUM(C21:N21) -> 1090.2784 | P21: 1207.4028 | R21: =SUMIFS(TB_Kochi[Apr_26],TB_Kochi[MIS_Group1],$B21)/10^5 -> 100.35193 | S21: =SUMIFS(TB_Kochi!AB:AB,TB_Kochi!J:J,$B21)/10^5 -> 95.957067 | U21: =IFERROR(R21/C21-1,"-") -> 0.24535672 | V21: =IFERROR(R21/N21-1,"-") -> -0.11591355 | W21: =IFERROR(R21/T21,"-") -> -
B22: Rent Paid | C22: =SUMIFS(TB_Kochi[Apr],TB_Kochi[MIS_Group1],$B22)/10^5 -> 12.06222 | D22: =SUMIFS(TB_Kochi[May],TB_Kochi[MIS_Group1],$B22)/10^5 -> 10.76928 | E22: =SUMIFS(TB_Kochi[Jun],TB_Kochi[MIS_Group1],$B22)/10^5 -> 12.9562 | F22: =SUMIFS(TB_Kochi[Jul],TB_Kochi[MIS_Group1],$B22)/10^5 -> 6.24876 | G22: =SUMIFS(TB_Kochi[Aug],TB_Kochi[MIS_Group1],$B22)/10^5 -> 15.83935 | H22: =SUMIFS(TB_Kochi[Sep],TB_Kochi[MIS_Group1],$B22)/10^5 -> 15.72184 | I22: =SUMIFS(TB_Kochi[Oct],TB_Kochi[MIS_Group1],$B22)/10^5 -> 9.8071846 | J22: =SUMIFS(TB_Kochi[Nov],TB_Kochi[MIS_Group1],$B22)/10^5 -> 8.2658836 | K22: =SUMIFS(TB_Kochi[Dec],TB_Kochi[MIS_Group1],$B22)/10^5 -> 12.974524 | L22: =SUMIFS(TB_Kochi[Jan],TB_Kochi[MIS_Group1],$B22)/10^5 -> 10.716814 | M22: =SUMIFS(TB_Kochi[Feb],TB_Kochi[MIS_Group1],$B22)/10^5 -> 10.821984 | N22: =SUMIFS(TB_Kochi[Mar],TB_Kochi[MIS_Group1],$B22)/10^5 -> 19.049694 | O22: =SUM(C22:N22) -> 145.23373 | P22: 67.094598 | R22: =SUMIFS(TB_Kochi[Apr_26],TB_Kochi[MIS_Group1],$B22)/10^5 -> 9.2140104 | S22: =SUMIFS(TB_Kochi!AB:AB,TB_Kochi!J:J,$B22)/10^5 -> 11.444164 | U22: =IFERROR(R22/C22-1,"-") -> -0.23612648 | V22: =IFERROR(R22/N22-1,"-") -> -0.51631714 | W22: =IFERROR(R22/T22,"-") -> -
B23: Repair & Maintenance | C23: =SUMIFS(TB_Kochi[Apr],TB_Kochi[MIS_Group1],$B23)/10^5 -> 64.356514 | D23: =SUMIFS(TB_Kochi[May],TB_Kochi[MIS_Group1],$B23)/10^5 -> 82.209474 | E23: =SUMIFS(TB_Kochi[Jun],TB_Kochi[MIS_Group1],$B23)/10^5 -> 115.93859 | F23: =SUMIFS(TB_Kochi[Jul],TB_Kochi[MIS_Group1],$B23)/10^5 -> 117.26712 | G23: =SUMIFS(TB_Kochi[Aug],TB_Kochi[MIS_Group1],$B23)/10^5 -> 126.82324 | H23: =SUMIFS(TB_Kochi[Sep],TB_Kochi[MIS_Group1],$B23)/10^5 -> 145.99992 | I23: =SUMIFS(TB_Kochi[Oct],TB_Kochi[MIS_Group1],$B23)/10^5 -> 151.83994 | J23: =SUMIFS(TB_Kochi[Nov],TB_Kochi[MIS_Group1],$B23)/10^5 -> 120.39281 | K23: =SUMIFS(TB_Kochi[Dec],TB_Kochi[MIS_Group1],$B23)/10^5 -> 92.163137 | L23: =SUMIFS(TB_Kochi[Jan],TB_Kochi[MIS_Group1],$B23)/10^5 -> 80.220752 | M23: =SUMIFS(TB_Kochi[Feb],TB_Kochi[MIS_Group1],$B23)/10^5 -> 181.89487 | N23: =SUMIFS(TB_Kochi[Mar],TB_Kochi[MIS_Group1],$B23)/10^5 -> 175.18003 | O23: =SUM(C23:N23) -> 1454.2864 | P23: 1158.8032 | R23: =SUMIFS(TB_Kochi[Apr_26],TB_Kochi[MIS_Group1],$B23)/10^5 -> 104.13855 | S23: =SUMIFS(TB_Kochi!AB:AB,TB_Kochi!J:J,$B23)/10^5 -> 70.302392 | U23: =IFERROR(R23/C23-1,"-") -> 0.61815086 | V23: =IFERROR(R23/N23-1,"-") -> -0.40553413 | W23: =IFERROR(R23/T23,"-") -> -
B24: Security Expenses | C24: =SUMIFS(TB_Kochi[Apr],TB_Kochi[MIS_Group1],$B24)/10^5 -> 20.41736 | D24: =SUMIFS(TB_Kochi[May],TB_Kochi[MIS_Group1],$B24)/10^5 -> 23.25145 | E24: =SUMIFS(TB_Kochi[Jun],TB_Kochi[MIS_Group1],$B24)/10^5 -> 23.25145 | F24: =SUMIFS(TB_Kochi[Jul],TB_Kochi[MIS_Group1],$B24)/10^5 -> 22.96171 | G24: =SUMIFS(TB_Kochi[Aug],TB_Kochi[MIS_Group1],$B24)/10^5 -> 19.61162 | H24: =SUMIFS(TB_Kochi[Sep],TB_Kochi[MIS_Group1],$B24)/10^5 -> 18.675923 | I24: =SUMIFS(TB_Kochi[Oct],TB_Kochi[MIS_Group1],$B24)/10^5 -> 25.15048 | J24: =SUMIFS(TB_Kochi[Nov],TB_Kochi[MIS_Group1],$B24)/10^5 -> 20.6798 | K24: =SUMIFS(TB_Kochi[Dec],TB_Kochi[MIS_Group1],$B24)/10^5 -> 21.01506 | L24: =SUMIFS(TB_Kochi[Jan],TB_Kochi[MIS_Group1],$B24)/10^5 -> 22.25077 | M24: =SUMIFS(TB_Kochi[Feb],TB_Kochi[MIS_Group1],$B24)/10^5 -> 20.75996 | N24: =SUMIFS(TB_Kochi[Mar],TB_Kochi[MIS_Group1],$B24)/10^5 -> 22.6 | O24: =SUM(C24:N24) -> 260.62558 | P24: 234.68642 | R24: =SUMIFS(TB_Kochi[Apr_26],TB_Kochi[MIS_Group1],$B24)/10^5 -> 23.45755 | S24: =SUMIFS(TB_Kochi!AB:AB,TB_Kochi!J:J,$B24)/10^5 -> 18.42536 | U24: =IFERROR(R24/C24-1,"-") -> 0.14890221 | V24: =IFERROR(R24/N24-1,"-") -> 0.03794469 | W24: =IFERROR(R24/T24,"-") -> -
B25: House Keeping Expenses | C25: =SUMIFS(TB_Kochi[Apr],TB_Kochi[MIS_Group1],$B25)/10^5 -> 63.59328 | D25: =SUMIFS(TB_Kochi[May],TB_Kochi[MIS_Group1],$B25)/10^5 -> 68.970342 | E25: =SUMIFS(TB_Kochi[Jun],TB_Kochi[MIS_Group1],$B25)/10^5 -> 76.137535 | F25: =SUMIFS(TB_Kochi[Jul],TB_Kochi[MIS_Group1],$B25)/10^5 -> 71.090918 | G25: =SUMIFS(TB_Kochi[Aug],TB_Kochi[MIS_Group1],$B25)/10^5 -> 64.630585 | H25: =SUMIFS(TB_Kochi[Sep],TB_Kochi[MIS_Group1],$B25)/10^5 -> 72.412979 | I25: =SUMIFS(TB_Kochi[Oct],TB_Kochi[MIS_Group1],$B25)/10^5 -> 85.337473 | J25: =SUMIFS(TB_Kochi[Nov],TB_Kochi[MIS_Group1],$B25)/10^5 -> 60.379886 | K25: =SUMIFS(TB_Kochi[Dec],TB_Kochi[MIS_Group1],$B25)/10^5 -> 65.103126 | L25: =SUMIFS(TB_Kochi[Jan],TB_Kochi[MIS_Group1],$B25)/10^5 -> 45.841541 | M25: =SUMIFS(TB_Kochi[Feb],TB_Kochi[MIS_Group1],$B25)/10^5 -> 118.05676 | N25: =SUMIFS(TB_Kochi[Mar],TB_Kochi[MIS_Group1],$B25)/10^5 -> 179.92848 | O25: =SUM(C25:N25) -> 971.4829 | P25: 888.04263 | R25: =SUMIFS(TB_Kochi[Apr_26],TB_Kochi[MIS_Group1],$B25)/10^5 -> 86.153207 | S25: =SUMIFS(TB_Kochi!AB:AB,TB_Kochi!J:J,$B25)/10^5 -> 111.12339 | U25: =IFERROR(R25/C25-1,"-") -> 0.35475332 | V25: =IFERROR(R25/N25-1,"-") -> -0.52118082 | W25: =IFERROR(R25/T25,"-") -> -
B26: Printing & Stationery | C26: =SUMIFS(TB_Kochi[Apr],TB_Kochi[MIS_Group1],$B26)/10^5 -> 11.413164 | D26: =SUMIFS(TB_Kochi[May],TB_Kochi[MIS_Group1],$B26)/10^5 -> 17.289713 | E26: =SUMIFS(TB_Kochi[Jun],TB_Kochi[MIS_Group1],$B26)/10^5 -> 13.468636 | F26: =SUMIFS(TB_Kochi[Jul],TB_Kochi[MIS_Group1],$B26)/10^5 -> 16.438968 | G26: =SUMIFS(TB_Kochi[Aug],TB_Kochi[MIS_Group1],$B26)/10^5 -> 13.802424 | H26: =SUMIFS(TB_Kochi[Sep],TB_Kochi[MIS_Group1],$B26)/10^5 -> 14.393906 | I26: =SUMIFS(TB_Kochi[Oct],TB_Kochi[MIS_Group1],$B26)/10^5 -> 17.629972 | J26: =SUMIFS(TB_Kochi[Nov],TB_Kochi[MIS_Group1],$B26)/10^5 -> 11.574042 | K26: =SUMIFS(TB_Kochi[Dec],TB_Kochi[MIS_Group1],$B26)/10^5 -> 13.907571 | L26: =SUMIFS(TB_Kochi[Jan],TB_Kochi[MIS_Group1],$B26)/10^5 -> 14.013111 | M26: =SUMIFS(TB_Kochi[Feb],TB_Kochi[MIS_Group1],$B26)/10^5 -> 17.457754 | N26: =SUMIFS(TB_Kochi[Mar],TB_Kochi[MIS_Group1],$B26)/10^5 -> 19.357531 | O26: =SUM(C26:N26) -> 180.74679 | P26: 176.68482 | R26: =SUMIFS(TB_Kochi[Apr_26],TB_Kochi[MIS_Group1],$B26)/10^5 -> 18.919433 | S26: =SUMIFS(TB_Kochi!AB:AB,TB_Kochi!J:J,$B26)/10^5 -> 17.911197 | U26: =IFERROR(R26/C26-1,"-") -> 0.65768523 | V26: =IFERROR(R26/N26-1,"-") -> -0.022631925 | W26: =IFERROR(R26/T26,"-") -> -
B27: Insurance | C27: =SUMIFS(TB_Kochi[Apr],TB_Kochi[MIS_Group1],$B27)/10^5 -> 2.1328066 | D27: =SUMIFS(TB_Kochi[May],TB_Kochi[MIS_Group1],$B27)/10^5 -> 2.3836815 | E27: =SUMIFS(TB_Kochi[Jun],TB_Kochi[MIS_Group1],$B27)/10^5 -> 1.7857524 | F27: =SUMIFS(TB_Kochi[Jul],TB_Kochi[MIS_Group1],$B27)/10^5 -> 1.84461 | G27: =SUMIFS(TB_Kochi[Aug],TB_Kochi[MIS_Group1],$B27)/10^5 -> 2.63082 | H27: =SUMIFS(TB_Kochi[Sep],TB_Kochi[MIS_Group1],$B27)/10^5 -> 2.6194263 | I27: =SUMIFS(TB_Kochi[Oct],TB_Kochi[MIS_Group1],$B27)/10^5 -> 2.6621797 | J27: =SUMIFS(TB_Kochi[Nov],TB_Kochi[MIS_Group1],$B27)/10^5 -> 2.8790145 | K27: =SUMIFS(TB_Kochi[Dec],TB_Kochi[MIS_Group1],$B27)/10^5 -> 3.106754 | L27: =SUMIFS(TB_Kochi[Jan],TB_Kochi[MIS_Group1],$B27)/10^5 -> 3.1086155 | M27: =SUMIFS(TB_Kochi[Feb],TB_Kochi[MIS_Group1],$B27)/10^5 -> 2.8095307 | N27: =SUMIFS(TB_Kochi[Mar],TB_Kochi[MIS_Group1],$B27)/10^5 -> 3.1139877 | O27: =SUM(C27:N27) -> 31.077179 | P27: 31.212928 | R27: =SUMIFS(TB_Kochi[Apr_26],TB_Kochi[MIS_Group1],$B27)/10^5 -> 2.9571758 | S27: =SUMIFS(TB_Kochi!AB:AB,TB_Kochi!J:J,$B27)/10^5 -> 3.214462 | U27: =IFERROR(R27/C27-1,"-") -> 0.3865185 | V27: =IFERROR(R27/N27-1,"-") -> -0.050357264 | W27: =IFERROR(R27/T27,"-") -> -
B28: Rates & taxes | C28: =SUMIFS(TB_Kochi[Apr],TB_Kochi[MIS_Group1],$B28)/10^5 -> 3.3502372 | D28: =SUMIFS(TB_Kochi[May],TB_Kochi[MIS_Group1],$B28)/10^5 -> 5.880676 | E28: =SUMIFS(TB_Kochi[Jun],TB_Kochi[MIS_Group1],$B28)/10^5 -> 4.333596 | F28: =SUMIFS(TB_Kochi[Jul],TB_Kochi[MIS_Group1],$B28)/10^5 -> 6.08216 | G28: =SUMIFS(TB_Kochi[Aug],TB_Kochi[MIS_Group1],$B28)/10^5 -> 2.982145 | H28: =SUMIFS(TB_Kochi[Sep],TB_Kochi[MIS_Group1],$B28)/10^5 -> 1.555136 | I28: =SUMIFS(TB_Kochi[Oct],TB_Kochi[MIS_Group1],$B28)/10^5 -> 9.4252486 | J28: =SUMIFS(TB_Kochi[Nov],TB_Kochi[MIS_Group1],$B28)/10^5 -> 1.6373285 | K28: =SUMIFS(TB_Kochi[Dec],TB_Kochi[MIS_Group1],$B28)/10^5 -> 2.1742185 | L28: =SUMIFS(TB_Kochi[Jan],TB_Kochi[MIS_Group1],$B28)/10^5 -> 4.4485585 | M28: =SUMIFS(TB_Kochi[Feb],TB_Kochi[MIS_Group1],$B28)/10^5 -> 2.625028 | N28: =SUMIFS(TB_Kochi[Mar],TB_Kochi[MIS_Group1],$B28)/10^5 -> 13.392654 | O28: =SUM(C28:N28) -> 57.886986 | P28: 58.754068 | R28: =SUMIFS(TB_Kochi[Apr_26],TB_Kochi[MIS_Group1],$B28)/10^5 -> 1.0579971 | S28: =SUMIFS(TB_Kochi!AB:AB,TB_Kochi!J:J,$B28)/10^5 -> 1.3032737 | U28: =IFERROR(R28/C28-1,"-") -> -0.68420233 | V28: =IFERROR(R28/N28-1,"-") -> -0.92100168 | W28: =IFERROR(R28/T28,"-") -> -
... B30: Quality & Infection control expense | C30: =SUMIFS(TB_Kochi[Apr],TB_Kochi[MIS_Group1],$B30)/10^5 -> 0 | D30: =SUMIFS(TB_Kochi[May],TB_Kochi[MIS_Group1],$B30)/10^5 -> 0 | E30: =SUMIFS(TB_Kochi[Jun],TB_Kochi[MIS_Group1],$B30)/10^5 -> 0 | F30: =SUMIFS(TB_Kochi[Jul],TB_Kochi[MIS_Group1],$B30)/10^5 -> 0 | G30: =SUMIFS(TB_Kochi[Aug],TB_Kochi[MIS_Group1],$B30)/10^5 -> 0.084 | H30: =SUMIFS(TB_Kochi[Sep],TB_Kochi[MIS_Group1],$B30)/10^5 -> 0.595 | I30: =SUMIFS(TB_Kochi[Oct],TB_Kochi[MIS_Group1],$B30)/10^5 -> 0.4176 | J30: =SUMIFS(TB_Kochi[Nov],TB_Kochi[MIS_Group1],$B30)/10^5 -> 0.424 | K30: =SUMIFS(TB_Kochi[Dec],TB_Kochi[MIS_Group1],$B30)/10^5 -> 0.88136 | L30: =SUMIFS(TB_Kochi[Jan],TB_Kochi[MIS_Group1],$B30)/10^5 -> 0.634 | M30: =SUMIFS(TB_Kochi[Feb],TB_Kochi[MIS_Group1],$B30)/10^5 -> 0.0496 | N30: =SUMIFS(TB_Kochi[Mar],TB_Kochi[MIS_Group1],$B30)/10^5 -> 2.590128 | O30: =SUM(C30:N30) -> 5.675688 | P30: 4.4807815 | R30: =SUMIFS(TB_Kochi[Apr_26],TB_Kochi[MIS_Group1],$B30)/10^5 -> 0 | S30: =SUMIFS(TB_Kochi!AB:AB,TB_Kochi!J:J,$B30)/10^5 -> 0 | U30: =IFERROR(R30/C30-1,"-") -> - | V30: =IFERROR(R30/N30-1,"-") -> -1 | W30: =IFERROR(R30/T30,"-") -> -
B31: Provission for Bad Debts | C31: 18.708139 | D31: =ECL!$M$43/12 -> 1.376742 | E31: =ECL!$M$43/12 -> 1.376742 | F31: =ECL!$M$43/12 -> 1.376742 | G31: =ECL!$M$43/12 -> 1.376742 | H31: =ECL!$M$43/12 -> 1.376742 | I31: =ECL!$M$43/12 -> 1.376742 | J31: =ECL!$M$43/12 -> 1.376742 | K31: =ECL!$M$43/12 -> 1.376742 | ... M31: =ECL!$M$43/12 -> 1.376742 | N31: 18.708139 | O31: =SUM(C31:N31) -> 51.183699 | P31: 370.00734 | R31: =ECL!$M$43/12 -> 1.376742 | S31: 1.376742 | U31: =IFERROR(R31/C31-1,"-") -> -0.92640946 | V31: =IFERROR(R31/N31-1,"-") -> -0.92640946 | W31: =IFERROR(R31/T31,"-") -> -
B32: Marketing Cost | C32: =SUMIFS(TB_Kochi[Apr],TB_Kochi[MIS_Group1],$B32)/10^5 -> 79.777442 | D32: =SUMIFS(TB_Kochi[May],TB_Kochi[MIS_Group1],$B32)/10^5 -> 57.800632 | E32: =SUMIFS(TB_Kochi[Jun],TB_Kochi[MIS_Group1],$B32)/10^5 -> 59.60263 | F32: =SUMIFS(TB_Kochi[Jul],TB_Kochi[MIS_Group1],$B32)/10^5 -> 50.627185 | G32: =SUMIFS(TB_Kochi[Aug],TB_Kochi[MIS_Group1],$B32)/10^5 -> 66.304112 | H32: =SUMIFS(TB_Kochi[Sep],TB_Kochi[MIS_Group1],$B32)/10^5 -> 84.835324 | I32: =SUMIFS(TB_Kochi[Oct],TB_Kochi[MIS_Group1],$B32)/10^5 -> 81.838729 | J32: =SUMIFS(TB_Kochi[Nov],TB_Kochi[MIS_Group1],$B32)/10^5 -> 71.732657 | K32: =SUMIFS(TB_Kochi[Dec],TB_Kochi[MIS_Group1],$B32)/10^5 -> 77.642089 | L32: =SUMIFS(TB_Kochi[Jan],TB_Kochi[MIS_Group1],$B32)/10^5 -> 74.109965 | M32: =SUMIFS(TB_Kochi[Feb],TB_Kochi[MIS_Group1],$B32)/10^5 -> 111.7571 | N32: =SUMIFS(TB_Kochi[Mar],TB_Kochi[MIS_Group1],$B32)/10^5 -> 63.348098 | O32: =SUM(C32:N32) -> 879.37596 | P32: 1209.5726 | R32: =SUMIFS(TB_Kochi[Apr_26],TB_Kochi[MIS_Group1],$B32)/10^5 -> 72.002349 | S32: =SUMIFS(TB_Kochi!AB:AB,TB_Kochi!J:J,$B32)/10^5 -> 51.2837 | U32: =IFERROR(R32/C32-1,"-") -> -0.097459794 | V32: =IFERROR(R32/N32-1,"-") -> 0.13661422 | W32: =IFERROR(R32/T32,"-") -> -
B33: Communication Costs | C33: =SUMIFS(TB_Kochi[Apr],TB_Kochi[MIS_Group1],$B33)/10^5 -> 0.6816408 | D33: =SUMIFS(TB_Kochi[May],TB_Kochi[MIS_Group1],$B33)/10^5 -> 3.401031 | E33: =SUMIFS(TB_Kochi[Jun],TB_Kochi[MIS_Group1],$B33)/10^5 -> 2.3331343 | F33: =SUMIFS(TB_Kochi[Jul],TB_Kochi[MIS_Group1],$B33)/10^5 -> 3.74227 | G33: =SUMIFS(TB_Kochi[Aug],TB_Kochi[MIS_Group1],$B33)/10^5 -> 2.67773 | H33: =SUMIFS(TB_Kochi[Sep],TB_Kochi[MIS_Group1],$B33)/10^5 -> 2.3750443 | I33: =SUMIFS(TB_Kochi[Oct],TB_Kochi[MIS_Group1],$B33)/10^5 -> 2.92807 | J33: =SUMIFS(TB_Kochi[Nov],TB_Kochi[MIS_Group1],$B33)/10^5 -> 4.9159996 | K33: =SUMIFS(TB_Kochi[Dec],TB_Kochi[MIS_Group1],$B33)/10^5 -> 1.8910118 | L33: =SUMIFS(TB_Kochi[Jan],TB_Kochi[MIS_Group1],$B33)/10^5 -> 3.2128392 | M33: =SUMIFS(TB_Kochi[Feb],TB_Kochi[MIS_Group1],$B33)/10^5 -> 1.8980122 | N33: =SUMIFS(TB_Kochi[Mar],TB_Kochi[MIS_Group1],$B33)/10^5 -> 5.00226 | O33: =SUM(C33:N33) -> 35.059043 | P33: 35.696857 | R33: =SUMIFS(TB_Kochi[Apr_26],TB_Kochi[MIS_Group1],$B33)/10^5 -> 0.84087 | S33: =SUMIFS(TB_Kochi!AB:AB,TB_Kochi!J:J,$B33)/10^5 -> 2.40681 | U33: =IFERROR(R33/C33-1,"-") -> 0.23359693 | V33: =IFERROR(R33/N33-1,"-") -> -0.83190198 | W33: =IFERROR(R33/T33,"-") -> -
B34: Business Travel Cost | C34: =SUMIFS(TB_Kochi[Apr],TB_Kochi[MIS_Group1],$B34)/10^5 -> 0.58836 | D34: =SUMIFS(TB_Kochi[May],TB_Kochi[MIS_Group1],$B34)/10^5 -> 2.26307 | E34: =SUMIFS(TB_Kochi[Jun],TB_Kochi[MIS_Group1],$B34)/10^5 -> 2.30149 | F34: =SUMIFS(TB_Kochi[Jul],TB_Kochi[MIS_Group1],$B34)/10^5 -> 3.35502 | G34: =SUMIFS(TB_Kochi[Aug],TB_Kochi[MIS_Group1],$B34)/10^5 -> 5.59574 | H34: =SUMIFS(TB_Kochi[Sep],TB_Kochi[MIS_Group1],$B34)/10^5 -> 1.20231 | I34: =SUMIFS(TB_Kochi[Oct],TB_Kochi[MIS_Group1],$B34)/10^5 -> 3.485781 | J34: =SUMIFS(TB_Kochi[Nov],TB_Kochi[MIS_Group1],$B34)/10^5 -> 1.09571 | K34: =SUMIFS(TB_Kochi[Dec],TB_Kochi[MIS_Group1],$B34)/10^5 -> 2.09376 | L34: =SUMIFS(TB_Kochi[Jan],TB_Kochi[MIS_Group1],$B34)/10^5 -> 1.4586799 | M34: =SUMIFS(TB_Kochi[Feb],TB_Kochi[MIS_Group1],$B34)/10^5 -> 3.4290939 | N34: =SUMIFS(TB_Kochi[Mar],TB_Kochi[MIS_Group1],$B34)/10^5 -> 9.6397573 | O34: =SUM(C34:N34) -> 36.508772 | P34: 34.893018 | R34: =SUMIFS(TB_Kochi[Apr_26],TB_Kochi[MIS_Group1],$B34)/10^5 -> 5.27001 | S34: =SUMIFS(TB_Kochi!AB:AB,TB_Kochi!J:J,$B34)/10^5 -> 1.65998 | U34: =IFERROR(R34/C34-1,"-") -> 7.9571181 | V34: =IFERROR(R34/N34-1,"-") -> -0.4533047 | W34: =IFERROR(R34/T34,"-") -> -
B35: Miscellaneous expenses | C35: =SUMIFS(TB_Kochi[Apr],TB_Kochi[MIS_Group1],$B35)/10^5 -> 2.3950229 | D35: =SUMIFS(TB_Kochi[May],TB_Kochi[MIS_Group1],$B35)/10^5 -> 2.3361631 | E35: =SUMIFS(TB_Kochi[Jun],TB_Kochi[MIS_Group1],$B35)/10^5 -> 3.4022804 | F35: =SUMIFS(TB_Kochi[Jul],TB_Kochi[MIS_Group1],$B35)/10^5 -> 6.8056594 | G35: =SUMIFS(TB_Kochi[Aug],TB_Kochi[MIS_Group1],$B35)/10^5 -> 12.542993 | H35: =SUMIFS(TB_Kochi[Sep],TB_Kochi[MIS_Group1],$B35)/10^5 -> 6.171818 | I35: =SUMIFS(TB_Kochi[Oct],TB_Kochi[MIS_Group1],$B35)/10^5 -> 8.1020856 | J35: =SUMIFS(TB_Kochi[Nov],TB_Kochi[MIS_Group1],$B35)/10^5 -> 25.883638 | K35: =SUMIFS(TB_Kochi[Dec],TB_Kochi[MIS_Group1],$B35)/10^5 -> 11.296049 | L35: =SUMIFS(TB_Kochi[Jan],TB_Kochi[MIS_Group1],$B35)/10^5 -> 9.4450408 | M35: =SUMIFS(TB_Kochi[Feb],TB_Kochi[MIS_Group1],$B35)/10^5 -> 5.6722984 | N35: =SUMIFS(TB_Kochi[Mar],TB_Kochi[MIS_Group1],$B35)/10^5 -> 23.63844 | O35: =SUM(C35:N35) -> 117.69149 | P35: 148.50957 | R35: =SUMIFS(TB_Kochi[Apr_26],TB_Kochi[MIS_Group1],$B35)/10^5 -> 4.4549679 | S35: =SUMIFS(TB_Kochi!AB:AB,TB_Kochi!J:J,$B35)/10^5 -> 6.8408594 | U35: =IFERROR(R35/C35-1,"-") -> 0.86009407 | V35: =IFERROR(R35/N35-1,"-") -> -0.81153714 | W35: =IFERROR(R35/T35,"-") -> -
B36: CSR Activity | C36: =SUMIFS(TB_Kochi[Apr],TB_Kochi[MIS_Group1],$B36)/10^5 -> 7.6233333 | D36: =SUMIFS(TB_Kochi[May],TB_Kochi[MIS_Group1],$B36)/10^5 -> 8.4198233 | E36: =SUMIFS(TB_Kochi[Jun],TB_Kochi[MIS_Group1],$B36)/10^5 -> 10.581563 | F36: =SUMIFS(TB_Kochi[Jul],TB_Kochi[MIS_Group1],$B36)/10^5 -> 10.073333 | G36: =SUMIFS(TB_Kochi[Aug],TB_Kochi[MIS_Group1],$B36)/10^5 -> 8.8683333 | H36: =SUMIFS(TB_Kochi[Sep],TB_Kochi[MIS_Group1],$B36)/10^5 -> 10.170893 | I36: =SUMIFS(TB_Kochi[Oct],TB_Kochi[MIS_Group1],$B36)/10^5 -> 9.0244733 | J36: =SUMIFS(TB_Kochi[Nov],TB_Kochi[MIS_Group1],$B36)/10^5 -> 7.6233333 | K36: =SUMIFS(TB_Kochi[Dec],TB_Kochi[MIS_Group1],$B36)/10^5 -> 30.194143 | L36: =SUMIFS(TB_Kochi[Jan],TB_Kochi[MIS_Group1],$B36)/10^5 -> 7.6233333 | M36: =SUMIFS(TB_Kochi[Feb],TB_Kochi[MIS_Group1],$B36)/10^5 -> 9.6233333 | N36: =SUMIFS(TB_Kochi[Mar],TB_Kochi[MIS_Group1],$B36)/10^5 -> 27.395973 | O36: =SUM(C36:N36) -> 147.22187 | P36: 110.00218 | R36: =SUMIFS(TB_Kochi[Apr_26],TB_Kochi[MIS_Group1],$B36)/10^5 -> 15 | S36: =SUMIFS(TB_Kochi!AB:AB,TB_Kochi!J:J,$B36)/10^5 -> 15 | U36: =IFERROR(R36/C36-1,"-") -> 0.9676432 | V36: =IFERROR(R36/N36-1,"-") -> -0.45247428 | W36: =IFERROR(R36/T36,"-") -> -
B37: Total Expenses | C37: =SUM(C17:C36) -> 2310.981 | D37: =SUM(D17:D36) -> 2684.9052 | E37: =SUM(E17:E36) -> 2688.2237 | F37: =SUM(F17:F36) -> 2890.0434 | G37: =SUM(G17:G36) -> 2839.253 | H37: =SUM(H17:H36) -> 2881.0929 | I37: =SUM(I17:I36) -> 2941.2051 | J37: =SUM(J17:J36) -> 2654.9612 | ... P37: =SUM(P17:P36) -> 38278.698 | R37: =SUM(R17:R36) -> 2953.2182 | S37: =SUM(S17:S36) -> 2984.378 | T37: =SUM(T17:T36) -> 0 | U37: =IFERROR(R37/C37-1,"-") -> 0.27790674 | V37: =IFERROR(R37/N37-1,"-") -> -0.030791587 | W37: =IFERROR(R37/T37,"-") -> -
P38: =SUMIFS(PL_Consol!Q:Q,PL_Consol!B:B,PL_Kochi!B38)-SUMIFS(PL_Calicut!P:P,PL_Calicut!B:B,PL_Kochi!B38)-SUMIFS(PL_FNB!P:P,PL_FNB!B:B,PL_Kochi!B38) -> 0 | U38: =IFERROR(R38/C38-1,"-") -> - | V38: =IFERROR(R38/N38-1,"-") -> - | W38: =IFERROR(R38/T38,"-") -> -
B39: EBITDA | C39: =C15-C37 -> 891.02742 | D39: =D15-D37 -> 889.55064 | E39: =E15-E37 -> 522.23693 | F39: =F15-F37 -> 839.84603 | G39: =G15-G37 -> 1006.6426 | H39: =H15-H37 -> 892.28073 | I39: =I15-I37 -> 824.85563 | J39: =J15-J37 -> 702.8533 | ... P39: =P15-P37 -> 9814.8982 | R39: =R15-R37 -> 1136.0628 | S39: =S15-S37 -> 1247.2425 | T39: =T15-T37 -> 0 | U39: =IFERROR(R39/C39-1,"-") -> 0.27500324 | V39: =IFERROR(R39/N39-1,"-") -> 0.3932898 | W39: =IFERROR(R39/T39,"-") -> -
B40: Depreciation | C40: 216.90151 | D40: =((Depr.!$H$16/PL_Consol!$P$15)*PL_Kochi!$O$15)/12 -> 15.681444 | E40: =((Depr.!$H$16/PL_Consol!$P$15)*PL_Kochi!$O$15)/12 -> 15.681444 | F40: =((Depr.!$H$16/PL_Consol!$P$15)*PL_Kochi!$O$15)/12 -> 15.681444 | G40: =((Depr.!$H$16/PL_Consol!$P$15)*PL_Kochi!$O$15)/12 -> 15.681444 | H40: =((Depr.!$H$16/PL_Consol!$P$15)*PL_Kochi!$O$15)/12 -> 15.681444 | I40: =((Depr.!$H$16/PL_Consol!$P$15)*PL_Kochi!$O$15)/12 -> 15.681444 | J40: =((Depr.!$H$16/PL_Consol!$P$15)*PL_Kochi!$O$15)/12 -> 15.681444 | K40: =((Depr.!$H$16/PL_Consol!$P$15)*PL_Kochi!$O$15)/12 -> 15.681444 | ... M40: =((Depr.!$H$16/PL_Consol!$P$15)*PL_Kochi!$O$15)/12 -> 15.681444 | N40: 216.90151 | O40: =SUM(C40:N40) -> 590.61745 | P40: 2578.2425 | R40: 189.7 | S40: =(Depr.!H16/PL_Consol!T15)*PL_Kochi!S15 -> 188.58235 | U40: =IFERROR(R40/C40-1,"-") -> -0.12540949 | V40: =IFERROR(R40/N40-1,"-") -> -0.12540949 | W40: =IFERROR(R40/T40,"-") -> - | X40: 26383396
B41: EBIT (Operational Profit) | C41: =C39-C40 -> 674.12591 | D41: =D39-D40 -> 873.86919 | E41: =E39-E40 -> 506.55548 | F41: =F39-F40 -> 824.16459 | G41: =G39-G40 -> 990.96113 | H41: =H39-H40 -> 876.59928 | I41: =I39-I40 -> 809.17419 | J41: =J39-J40 -> 687.17186 | ... P41: =P39-P40 -> 7236.6557 | R41: =R39-R40 -> 946.36285 | S41: =S39-S40 -> 1058.6602 | T41: =T39-T40 -> 0 | U41: =IFERROR(R41/C41-1,"-") -> 0.40383692 | V41: =IFERROR(R41/N41-1,"-") -> 0.5812771 | W41: =IFERROR(R41/T41,"-") -> -
B42: Finance Cost | C42: =SUMIFS(TB_Kochi[Apr],TB_Kochi[MIS_Group1],$B42)/10^5 -> 0.3489362 | D42: =SUMIFS(TB_Kochi[May],TB_Kochi[MIS_Group1],$B42)/10^5 -> 5.6549663 | E42: =SUMIFS(TB_Kochi[Jun],TB_Kochi[MIS_Group1],$B42)/10^5 -> 7.3311816 | F42: =SUMIFS(TB_Kochi[Jul],TB_Kochi[MIS_Group1],$B42)/10^5 -> 7.2627232 | G42: =SUMIFS(TB_Kochi[Aug],TB_Kochi[MIS_Group1],$B42)/10^5 -> 7.1569922 | H42: =SUMIFS(TB_Kochi[Sep],TB_Kochi[MIS_Group1],$B42)/10^5 -> 6.4875598 | I42: =SUMIFS(TB_Kochi[Oct],TB_Kochi[MIS_Group1],$B42)/10^5 -> 2.5778316 | J42: =SUMIFS(TB_Kochi[Nov],TB_Kochi[MIS_Group1],$B42)/10^5 -> 3.2429631 | K42: =SUMIFS(TB_Kochi[Dec],TB_Kochi[MIS_Group1],$B42)/10^5 -> 2.6124811 | L42: =SUMIFS(TB_Kochi[Jan],TB_Kochi[MIS_Group1],$B42)/10^5 -> 2.6509742 | M42: =SUMIFS(TB_Kochi[Feb],TB_Kochi[MIS_Group1],$B42)/10^5 -> 2.3908275 | N42: =SUMIFS(TB_Kochi[Mar],TB_Kochi[MIS_Group1],$B42)/10^5 -> 13.231441 | O42: =SUM(C42:N42) -> 60.948878 | P42: 59.969078 | R42: =SUMIFS(TB_Kochi[Apr_26],TB_Kochi[MIS_Group1],$B42)/10^5 -> 1.7556128 | S42: =SUMIFS(TB_Kochi!AB:AB,TB_Kochi!J:J,$B42)/10^5 -> 2.1584159 | U42: =IFERROR(R42/C42-1,"-") -> 4.0313289 | V42: =IFERROR(R42/N42-1,"-") -> -0.86731508 | W42: =IFERROR(R42/T42,"-") -> -
B43: PBT | C43: =C41-C42 -> 673.77698 | D43: =D41-D42 -> 868.21423 | E43: =E41-E42 -> 499.2243 | F43: =F41-F42 -> 816.90187 | G43: =G41-G42 -> 983.80414 | H43: =H41-H42 -> 870.11172 | I43: =I41-I42 -> 806.59636 | J43: =J41-J42 -> 683.9289 | ... P43: =P41-P42 -> 7176.6866 | R43: =R41-R42 -> 944.60723 | S43: =S41-S42 -> 1056.5018 | T43: =T41-T42 -> 0 | U43: =IFERROR(R43/C43-1,"-") -> 0.40195831 | V43: =IFERROR(R43/N43-1,"-") -> 0.61402722 | W43: =IFERROR(R43/T43,"-") -> -
B44: Tax | C44: =IF(C43>0,C43*PL_Consol!$R$44/PL_Consol!$R$43,0) -> 174.35554 | D44: =IF(D43>0,D43*PL_Consol!$R$44/PL_Consol!$R$43,0) -> 224.67072 | E44: =IF(E43>0,E43*PL_Consol!$R$44/PL_Consol!$R$43,0) -> 129.18596 | F44: =IF(F43>0,F43*PL_Consol!$R$44/PL_Consol!$R$43,0) -> 211.39245 | G44: =IF(G43>0,G43*PL_Consol!$R$44/PL_Consol!$R$43,0) -> 254.58231 | H44: =IF(H43>0,H43*PL_Consol!$R$44/PL_Consol!$R$43,0) -> 225.16174 | I44: =IF(I43>0,I43*PL_Consol!$R$44/PL_Consol!$R$43,0) -> 208.72566 | J44: =IF(J43>0,J43*PL_Consol!$R$44/PL_Consol!$R$43,0) -> 176.98259 | ... N44: =IF(N43>0,N43*PL_Consol!$R$44/PL_Consol!$R$43,0) -> 151.44676 | O44: =SUM(C44:N44) -> 2496.2203 | P44: 1758.0089 | R44: =IF(R43>0,R43*PL_Consol!$R$44/PL_Consol!$R$43,0) -> 244.4392 | S44: =IF(S43>0,S43*PL_Consol!$R$44/PL_Consol!$R$43,0) -> 273.39452 | T44: =IF(T43>0,T43*PL_Consol!$R$44/PL_Consol!$R$43,0) -> 0 | U44: =IFERROR(R44/C44-1,"-") -> 0.40195831 | V44: =IFERROR(R44/N44-1,"-") -> 0.61402722 | W44: =IFERROR(R44/T44,"-") -> -
B45: PAT | C45: =C43-C44 -> 499.42144 | D45: =D43-D44 -> 643.5435 | E45: =E43-E44 -> 370.03835 | F45: =F43-F44 -> 605.50942 | G45: =G43-G44 -> 729.22183 | H45: =H43-H44 -> 644.94998 | I45: =I43-I44 -> 597.8707 | J45: =J43-J44 -> 506.94631 | ... P45: =P43-P44 -> 5418.6777 | R45: =R43-R44 -> 700.16804 | S45: =S43-S44 -> 783.10724 | T45: =T43-T44 -> 0 | U45: =IFERROR(R45/C45-1,"-") -> 0.40195831 | V45: =IFERROR(R45/N45-1,"-") -> 0.61402722 | W45: =IFERROR(R45/T45,"-") -> -
R47: =S40+PL_Calicut!S36+PL_FNB!S24 -> 197.24263
B50: Common Size Statement
T51: Bud
B52: Particulars | C52: 45748 | D52: 45778 | E52: 45809 | F52: 45839 | G52: 45870 | H52: 45901 | I52: 45931 | J52: 45962 | K52: 45992 | L52: 46023 | M52: 46054 | N52: 46082 | O52: YTD | P52: Bud | Q52: FY25 | R52: 46113 | T52: 46113
B53: Revenue
B54: IP Revenue | C54: =IFERROR(C7/C$15,0) -> 0.40227138 | D54: =IFERROR(D7/D$15,0) -> 0.38861787 | E54: =IFERROR(E7/E$15,0) -> 0.38708111 | F54: =IFERROR(F7/F$15,0) -> 0.38694216 | G54: =IFERROR(G7/G$15,0) -> 0.41174884 | H54: =IFERROR(H7/H$15,0) -> 0.39882522 | I54: =IFERROR(I7/I$15,0) -> 0.41262125 | J54: =IFERROR(J7/J$15,0) -> 0.41756114 | ... R54: =IFERROR(R7/R$15,0) -> 0.42119132 | T54: =IFERROR(T7/T$15,0) -> 0
B55: IP Pharmacy | C55: =IFERROR(C8/C$15,0) -> 0.30037358 | D55: =IFERROR(D8/D$15,0) -> 0.3166464 | E55: =IFERROR(E8/E$15,0) -> 0.31764886 | F55: =IFERROR(F8/F$15,0) -> 0.32456405 | G55: =IFERROR(G8/G$15,0) -> 0.30429978 | H55: =IFERROR(H8/H$15,0) -> 0.32668698 | I55: =IFERROR(I8/I$15,0) -> 0.30842258 | J55: =IFERROR(J8/J$15,0) -> 0.30258052 | ... R55: =IFERROR(R8/R$15,0) -> 0.33473253 | T55: =IFERROR(T8/T$15,0) -> 0
B56: OP Revenue | C56: =IFERROR(C9/C$15,0) -> 0.19521448 | D56: =IFERROR(D9/D$15,0) -> 0.18298846 | E56: =IFERROR(E9/E$15,0) -> 0.18741399 | F56: =IFERROR(F9/F$15,0) -> 0.19585272 | G56: =IFERROR(G9/G$15,0) -> 0.18215703 | H56: =IFERROR(H9/H$15,0) -> 0.18180186 | I56: =IFERROR(I9/I$15,0) -> 0.18055078 | J56: =IFERROR(J9/J$15,0) -> 0.1847401 | ... R56: =IFERROR(R9/R$15,0) -> 0.15204913 | T56: =IFERROR(T9/T$15,0) -> 0
B57: OP Pharmacy | C57: =IFERROR(C10/C$15,0) -> 0.095264566 | D57: =IFERROR(D10/D$15,0) -> 0.092325439 | E57: =IFERROR(E10/E$15,0) -> 0.08830544 | F57: =IFERROR(F10/F$15,0) -> 0.088344343 | G57: =IFERROR(G10/G$15,0) -> 0.09556533 | H57: =IFERROR(H10/H$15,0) -> 0.085920144 | I57: =IFERROR(I10/I$15,0) -> 0.086966999 | J57: =IFERROR(J10/J$15,0) -> 0.086234454 | ... R57: =IFERROR(R10/R$15,0) -> 0.080015211 | T57: =IFERROR(T10/T$15,0) -> 0
B58: Clinical Studies | C58: =IFERROR(C11/C$15,0) -> 0 | D58: =IFERROR(D11/D$15,0) -> 0 | E58: =IFERROR(E11/E$15,0) -> 0 | F58: =IFERROR(F11/F$15,0) -> 0 | G58: =IFERROR(G11/G$15,0) -> 0 | H58: =IFERROR(H11/H$15,0) -> 0 | I58: =IFERROR(I11/I$15,0) -> 0 | J58: =IFERROR(J11/J$15,0) -> 0 | ... R58: =IFERROR(R11/R$15,0) -> 0 | T58: =IFERROR(T11/T$15,0) -> 0
B59: Aurveda | C59: =IFERROR(C12/C$15,0) -> 0 | D59: =IFERROR(D12/D$15,0) -> 0 | E59: =IFERROR(E12/E$15,0) -> 0 | F59: =IFERROR(F12/F$15,0) -> 0.00034974227 | G59: =IFERROR(G12/G$15,0) -> 0.00051106432 | H59: =IFERROR(H12/H$15,0) -> 7.4469169e-05 | I59: =IFERROR(I12/I$15,0) -> 0.00013010943 | J59: =IFERROR(J12/J$15,0) -> 0.0001235923 | ... R59: =IFERROR(R12/R$15,0) -> 1.5039319e-05 | T59: =IFERROR(T12/T$15,0) -> 0
B60: Revenue From Operation | C60: =IFERROR(C13/C$15,0) -> 0.99312401 | D60: =IFERROR(D13/D$15,0) -> 0.98057818 | E60: =IFERROR(E13/E$15,0) -> 0.9804494 | F60: =IFERROR(F13/F$15,0) -> 0.99605301 | G60: =IFERROR(G13/G$15,0) -> 0.99428205 | H60: =IFERROR(H13/H$15,0) -> 0.99330868 | I60: =IFERROR(I13/I$15,0) -> 0.98869171 | J60: =IFERROR(J13/J$15,0) -> 0.9912398 | ... R60: =IFERROR(R13/R$15,0) -> 0.98800324 | T60: =IFERROR(T13/T$15,0) -> 0
B61: Other Income | C61: =IFERROR(C14/C$15,0) -> 0.0068759941 | D61: =IFERROR(D14/D$15,0) -> 0.019421825 | E61: =IFERROR(E14/E$15,0) -> 0.019550601 | F61: =IFERROR(F14/F$15,0) -> 0.0039469867 | G61: =IFERROR(G14/G$15,0) -> 0.0057179508 | H61: =IFERROR(H14/H$15,0) -> 0.0066913196 | I61: =IFERROR(I14/I$15,0) -> 0.011308285 | J61: =IFERROR(J14/J$15,0) -> 0.0087601976 | ... R61: =IFERROR(R14/R$15,0) -> 0.011996764 | T61: =IFERROR(T14/T$15,0) -> 0
B62: Total Revenue | C62: =IFERROR(C15/C$15,0) -> 1 | D62: =IFERROR(D15/D$15,0) -> 1 | E62: =IFERROR(E15/E$15,0) -> 1 | F62: =IFERROR(F15/F$15,0) -> 1 | G62: =IFERROR(G15/G$15,0) -> 1 | H62: =IFERROR(H15/H$15,0) -> 1 | I62: =IFERROR(I15/I$15,0) -> 1 | J62: =IFERROR(J15/J$15,0) -> 1 | ... R62: =IFERROR(R15/R$15,0) -> 1 | T62: =IFERROR(T15/T$15,0) -> 0
C63: =IFERROR(C16/C$15,0) -> 0 | D63: =IFERROR(D16/D$15,0) -> 0 | E63: =IFERROR(E16/E$15,0) -> 0 | F63: =IFERROR(F16/F$15,0) -> 0 | G63: =IFERROR(G16/G$15,0) -> 0 | H63: =IFERROR(H16/H$15,0) -> 0 | I63: =IFERROR(I16/I$15,0) -> 0 | J63: =IFERROR(J16/J$15,0) -> 0 | ... R63: =IFERROR(R16/R$15,0) -> 0 | T63: =IFERROR(T16/T$15,0) -> 0
B64: Material Cost | C64: =IFERROR(C17/C$15,0) -> 0.243249 | D64: =IFERROR(D17/D$15,0) -> 0.29572026 | E64: =IFERROR(E17/E$15,0) -> 0.32210101 | F64: =IFERROR(F17/F$15,0) -> 0.31685487 | G64: =IFERROR(G17/G$15,0) -> 0.29154609 | H64: =IFERROR(H17/H$15,0) -> 0.2832804 | I64: =IFERROR(I17/I$15,0) -> 0.30035679 | J64: =IFERROR(J17/J$15,0) -> 0.29432353 | ... R64: =IFERROR(R17/R$15,0) -> 0.27727943 | T64: =IFERROR(T17/T$15,0) -> 0
B65: Doctor Cost | C65: =IFERROR(C18/C$15,0) -> 0.191859 | D65: =IFERROR(D18/D$15,0) -> 0.17406961 | E65: =IFERROR(E18/E$15,0) -> 0.18845816 | F65: =IFERROR(F18/F$15,0) -> 0.17679134 | G65: =IFERROR(G18/G$15,0) -> 0.17180492 | H65: =IFERROR(H18/H$15,0) -> 0.17610116 | I65: =IFERROR(I18/I$15,0) -> 0.17075378 | J65: =IFERROR(J18/J$15,0) -> 0.19389294 | ... R65: =IFERROR(R18/R$15,0) -> 0.17217935 | T65: =IFERROR(T18/T$15,0) -> 0
B66: Employee Cost | C66: =IFERROR(C19/C$15,0) -> 0.16557288 | D66: =IFERROR(D19/D$15,0) -> 0.16865499 | E66: =IFERROR(E19/E$15,0) -> 0.18450786 | F66: =IFERROR(F19/F$15,0) -> 0.16161579 | G66: =IFERROR(G19/G$15,0) -> 0.15524858 | H66: =IFERROR(H19/H$15,0) -> 0.17396903 | I66: =IFERROR(I19/I$15,0) -> 0.16419936 | J66: =IFERROR(J19/J$15,0) -> 0.16986396 | ... R66: =IFERROR(R19/R$15,0) -> 0.15453051 | T66: =IFERROR(T19/T$15,0) -> 0
B67: Lab Test Charges | C67: =IFERROR(C20/C$15,0) -> 0.0052405765 | D67: =IFERROR(D20/D$15,0) -> 0.0052063841 | E67: =IFERROR(E20/E$15,0) -> 0.0066757586 | F67: =IFERROR(F20/F$15,0) -> 0.0049254784 | G67: =IFERROR(G20/G$15,0) -> 0.0069016123 | H67: =IFERROR(H20/H$15,0) -> 0.0044441027 | I67: =IFERROR(I20/I$15,0) -> 0.0060499051 | J67: =IFERROR(J20/J$15,0) -> 0.0027455001 | ... R67: =IFERROR(R20/R$15,0) -> 0.005888622 | T67: =IFERROR(T20/T$15,0) -> 0
B68: Utilities-Power, fuel & water charges | C68: =IFERROR(C21/C$15,0) -> 0.025165727 | D68: =IFERROR(D21/D$15,0) -> 0.024322499 | E68: =IFERROR(E21/E$15,0) -> 0.030175421 | F68: =IFERROR(F21/F$15,0) -> 0.02391785 | G68: =IFERROR(G21/G$15,0) -> 0.021467782 | H68: =IFERROR(H21/H$15,0) -> 0.023737424 | I68: =IFERROR(I21/I$15,0) -> 0.026712301 | J68: =IFERROR(J21/J$15,0) -> 0.023917551 | ... R68: =IFERROR(R21/R$15,0) -> 0.024540237 | T68: =IFERROR(T21/T$15,0) -> 0
B69: Rent Paid | C69: =IFERROR(C22/C$15,0) -> 0.0037670794 | D69: =IFERROR(D22/D$15,0) -> 0.0030128446 | E69: =IFERROR(E22/E$15,0) -> 0.0040356203 | F69: =IFERROR(F22/F$15,0) -> 0.0016753204 | G69: =IFERROR(G22/G$15,0) -> 0.0041185076 | H69: =IFERROR(H22/H$15,0) -> 0.0041665209 | I69: =IFERROR(I22/I$15,0) -> 0.0026040962 | J69: =IFERROR(J22/J$15,0) -> 0.0024616856 | ... R69: =IFERROR(R22/R$15,0) -> 0.0022532104 | T69: =IFERROR(T22/T$15,0) -> 0
B70: Repair & Maintenance | C70: =IFERROR(C23/C$15,0) -> 0.020098796 | D70: =IFERROR(D23/D$15,0) -> 0.022999158 | E70: =IFERROR(E23/E$15,0) -> 0.036112758 | F70: =IFERROR(F23/F$15,0) -> 0.031439838 | G70: =IFERROR(G23/G$15,0) -> 0.032976256 | H70: =IFERROR(H23/H$15,0) -> 0.038692146 | I70: =IFERROR(I23/I$15,0) -> 0.040317975 | J70: =IFERROR(J23/J$15,0) -> 0.035854516 | ... R70: =IFERROR(R23/R$15,0) -> 0.025466225 | T70: =IFERROR(T23/T$15,0) -> 0
B71: Security Expenses | C71: =IFERROR(C24/C$15,0) -> 0.006376423 | D71: =IFERROR(D24/D$15,0) -> 0.0065048923 | E71: =IFERROR(E24/E$15,0) -> 0.0072424031 | F71: =IFERROR(F24/F$15,0) -> 0.0061561368 | G71: =IFERROR(G24/G$15,0) -> 0.0050993637 | H71: =IFERROR(H24/H$15,0) -> 0.0049493968 | I71: =IFERROR(I24/I$15,0) -> 0.0066781929 | J71: =IFERROR(J24/J$15,0) -> 0.0061587083 | ... R71: =IFERROR(R24/R$15,0) -> 0.0057363507 | T71: =IFERROR(T24/T$15,0) -> 0
B72: House Keeping Expenses | C72: =IFERROR(C25/C$15,0) -> 0.019860435 | D72: =IFERROR(D25/D$15,0) -> 0.01929534 | E72: =IFERROR(E25/E$15,0) -> 0.023715455 | F72: =IFERROR(F25/F$15,0) -> 0.019059792 | G72: =IFERROR(G25/G$15,0) -> 0.016805081 | H72: =IFERROR(H25/H$15,0) -> 0.019190514 | I72: =IFERROR(I25/I$15,0) -> 0.022659611 | J72: =IFERROR(J25/J$15,0) -> 0.017981901 | ... R72: =IFERROR(R25/R$15,0) -> 0.021068057 | T72: =IFERROR(T25/T$15,0) -> 0
B73: Printing & Stationery | C73: =IFERROR(C26/C$15,0) -> 0.0035643766 | D73: =IFERROR(D26/D$15,0) -> 0.0048370196 | E73: =IFERROR(E26/E$15,0) -> 0.0041952349 | F73: =IFERROR(F26/F$15,0) -> 0.0044073606 | G73: =IFERROR(G26/G$15,0) -> 0.0035888713 | H73: =IFERROR(H26/H$15,0) -> 0.0038145988 | I73: =IFERROR(I26/I$15,0) -> 0.0046812767 | J73: =IFERROR(J26/J$15,0) -> 0.0034468974 | ... R73: =IFERROR(R26/R$15,0) -> 0.0046265915 | T73: =IFERROR(T26/T$15,0) -> 0
B74: Insurance | C74: =IFERROR(C27/C$15,0) -> 0.00066608401 | D74: =IFERROR(D27/D$15,0) -> 0.00066686557 | E74: =IFERROR(E27/E$15,0) -> 0.00055622935 | F74: =IFERROR(F27/F$15,0) -> 0.00049454817 | G74: =IFERROR(G27/G$15,0) -> 0.00068405914 | H74: =IFERROR(H27/H$15,0) -> 0.00069418683 | I74: =IFERROR(I27/I$15,0) -> 0.00070688709 | J74: =IFERROR(J27/J$15,0) -> 0.00085740725 | ... R74: =IFERROR(R27/R$15,0) -> 0.00072315299 | T74: =IFERROR(T27/T$15,0) -> 0
B75: Rates & taxes | C75: =IFERROR(C28/C$15,0) -> 0.0010462924 | D75: =IFERROR(D28/D$15,0) -> 0.0016451948 | E75: =IFERROR(E28/E$15,0) -> 0.0013498362 | F75: =IFERROR(F28/F$15,0) -> 0.0016306542 | G75: =IFERROR(G28/G$15,0) -> 0.00077540977 | H75: =IFERROR(H28/H$15,0) -> 0.00041213411 | I75: =IFERROR(I28/I$15,0) -> 0.002502681 | J75: =IFERROR(J28/J$15,0) -> 0.00048761732 | ... R75: =IFERROR(R28/R$15,0) -> 0.00025872448 | T75: =IFERROR(T28/T$15,0) -> 0
... B84: Total Expenses | C84: =IFERROR(C37/C$15,0) -> 0.72172858 | D84: =IFERROR(D37/D$15,0) -> 0.75113676 | E84: =IFERROR(E37/E$15,0) -> 0.83733271 | F84: =IFERROR(F37/F$15,0) -> 0.77483353 | G84: =IFERROR(G37/G$15,0) -> 0.73825535 | H84: =IFERROR(H37/H$15,0) -> 0.76353237 | I84: =IFERROR(I37/I$15,0) -> 0.78097654 | J84: =IFERROR(J37/J$15,0) -> 0.79068132 | ... R84: =IFERROR(R37/R$15,0) -> 0.72218519 | T84: =IFERROR(T37/T$15,0) -> 0
C85: =IFERROR(C38/C$15,0) -> 0 | D85: =IFERROR(D38/D$15,0) -> 0 | E85: =IFERROR(E38/E$15,0) -> 0 | F85: =IFERROR(F38/F$15,0) -> 0 | G85: =IFERROR(G38/G$15,0) -> 0 | H85: =IFERROR(H38/H$15,0) -> 0 | I85: =IFERROR(I38/I$15,0) -> 0 | J85: =IFERROR(J38/J$15,0) -> 0 | ... R85: =IFERROR(R38/R$15,0) -> 0 | T85: =IFERROR(T38/T$15,0) -> 0
B86: EBITDA | C86: =IFERROR(C39/C$15,0) -> 0.27827142 | D86: =IFERROR(D39/D$15,0) -> 0.24886324 | E86: =IFERROR(E39/E$15,0) -> 0.16266729 | F86: =IFERROR(F39/F$15,0) -> 0.22516647 | G86: =IFERROR(G39/G$15,0) -> 0.26174465 | H86: =IFERROR(H39/H$15,0) -> 0.23646763 | I86: =IFERROR(I39/I$15,0) -> 0.21902346 | J86: =IFERROR(J39/J$15,0) -> 0.20931868 | ... R86: =IFERROR(R39/R$15,0) -> 0.27781481 | T86: =IFERROR(T39/T$15,0) -> 0
B87: Depreciation | C87: =IFERROR(C40/C$15,0) -> 0.067739206 | D87: =IFERROR(D40/D$15,0) -> 0.0043870858 | E87: =IFERROR(E40/E$15,0) -> 0.0048844842 | F87: =IFERROR(F40/F$15,0) -> 0.0042042651 | G87: =IFERROR(G40/G$15,0) -> 0.0040774493 | H87: =IFERROR(H40/H$15,0) -> 0.0041558154 | I87: =IFERROR(I40/I$15,0) -> 0.0041638851 | J87: =IFERROR(J40/J$15,0) -> 0.0046701342 | ... R87: =IFERROR(R40/R$15,0) -> 0.046389573 | T87: =IFERROR(T40/T$15,0) -> 0
B88: EBIT (Operational Profit) | C88: =IFERROR(C41/C$15,0) -> 0.21053221 | D88: =IFERROR(D41/D$15,0) -> 0.24447615 | E88: =IFERROR(E41/E$15,0) -> 0.15778281 | F88: =IFERROR(F41/F$15,0) -> 0.2209622 | G88: =IFERROR(G41/G$15,0) -> 0.2576672 | H88: =IFERROR(H41/H$15,0) -> 0.23231182 | I88: =IFERROR(I41/I$15,0) -> 0.21485957 | J88: =IFERROR(J41/J$15,0) -> 0.20464855 | ... R88: =IFERROR(R41/R$15,0) -> 0.23142524 | T88: =IFERROR(T41/T$15,0) -> 0
B89: Finance Cost | C89: =IFERROR(C42/C$15,0) -> 0.00010897417 | D89: =IFERROR(D42/D$15,0) -> 0.0015820496 | E89: =IFERROR(E42/E$15,0) -> 0.0022835295 | F89: =IFERROR(F42/F$15,0) -> 0.0019471685 | G89: =IFERROR(G42/G$15,0) -> 0.0018609429 | H89: =IFERROR(H42/H$15,0) -> 0.0017192996 | I89: =IFERROR(I42/I$15,0) -> 0.00068449018 | J89: =IFERROR(J42/J$15,0) -> 0.00096579579 | ... R89: =IFERROR(R42/R$15,0) -> 0.00042932065 | T89: =IFERROR(T42/T$15,0) -> 0
B90: PBT | C90: =IFERROR(C43/C$15,0) -> 0.21042324 | D90: =IFERROR(D43/D$15,0) -> 0.2428941 | E90: =IFERROR(E43/E$15,0) -> 0.15549928 | F90: =IFERROR(F43/F$15,0) -> 0.21901503 | G90: =IFERROR(G43/G$15,0) -> 0.25580626 | H90: =IFERROR(H43/H$15,0) -> 0.23059252 | I90: =IFERROR(I43/I$15,0) -> 0.21417508 | J90: =IFERROR(J43/J$15,0) -> 0.20368275 | ... R90: =IFERROR(R43/R$15,0) -> 0.23099592 | T90: =IFERROR(T43/T$15,0) -> 0
B91: Tax | C91: =IFERROR(C44/C$15,0) -> 0.054451931 | D91: =IFERROR(D44/D$15,0) -> 0.062854525 | E91: =IFERROR(E44/E$15,0) -> 0.040239072 | F91: =IFERROR(F44/F$15,0) -> 0.056675258 | G91: =IFERROR(G44/G$15,0) -> 0.066195847 | H91: =IFERROR(H44/H$15,0) -> 0.059671203 | I91: =IFERROR(I44/I$15,0) -> 0.055422808 | J91: =IFERROR(J44/J$15,0) -> 0.052707672 | ... R91: =IFERROR(R44/R$15,0) -> 0.059775593 | T91: =IFERROR(T44/T$15,0) -> 0
B92: PAT | C92: =IFERROR(C45/C$15,0) -> 0.15597131 | D92: =IFERROR(D45/D$15,0) -> 0.18003957 | E92: =IFERROR(E45/E$15,0) -> 0.1152602 | F92: =IFERROR(F45/F$15,0) -> 0.16233977 | G92: =IFERROR(G45/G$15,0) -> 0.18961041 | H92: =IFERROR(H45/H$15,0) -> 0.17092131 | I92: =IFERROR(I45/I$15,0) -> 0.15875227 | J92: =IFERROR(J45/J$15,0) -> 0.15097508 | ... R92: =IFERROR(R45/R$15,0) -> 0.17122033 | T92: =IFERROR(T45/T$15,0) -> 0

Sheet PL_Calicut
B1: LAKESHORE HOSPITAL - CALICUT
B2: Profit and Loss Statement (Amount in Lakhs) | E2: (Amount in Lakhs)
C4: SMLY | D4: SMLY | N4: PM | R4: PM | S4: CM | T4: Budget | U4: Growth & Ach %
B5: Particulars | C5: 45748 | D5: 45778 | E5: 45809 | F5: 45839 | G5: 45870 | H5: 45901 | I5: 45931 | J5: 45962 | K5: 45992 | L5: 46023 | M5: 46054 | N5: 46082 | O5: YTD | P5: Bud | Q5: FY25 | R5: 46113 | S5: 46143 | T5: 46143 | U5: YOY Gr. | V5: MOM Gr. | W5: BUD Ach.
B6: Revenue
B7: OP Revenue | C7: =-SUMIFS(TB_Calicut[Apr],TB_Calicut[MIS_Group1],$B7)/10^5 -> 11.90571 | D7: =-SUMIFS(TB_Calicut[May],TB_Calicut[MIS_Group1],$B7)/10^5 -> 8.92493 | E7: =-SUMIFS(TB_Calicut[Jun],TB_Calicut[MIS_Group1],$B7)/10^5 -> 9.9301599 | F7: =-SUMIFS(TB_Calicut[Jul],TB_Calicut[MIS_Group1],$B7)/10^5 -> 12.46093 | G7: =-SUMIFS(TB_Calicut[Aug],TB_Calicut[MIS_Group1],$B7)/10^5 -> 12.560156 | H7: =-SUMIFS(TB_Calicut[Sep],TB_Calicut[MIS_Group1],$B7)/10^5 -> 12.570122 | I7: =-SUMIFS(TB_Calicut[Oct],TB_Calicut[MIS_Group1],$B7)/10^5 -> 11.879449 | J7: =-SUMIFS(TB_Calicut[Nov],TB_Calicut[MIS_Group1],$B7)/10^5 -> 10.45698 | K7: =-SUMIFS(TB_Calicut[Dec],TB_Calicut[MIS_Group1],$B7)/10^5 -> 10.55704 | L7: =-SUMIFS(TB_Calicut[Jan],TB_Calicut[MIS_Group1],$B7)/10^5 -> 10.14587 | M7: =-SUMIFS(TB_Calicut[Feb],TB_Calicut[MIS_Group1],$B7)/10^5 -> 11.672865 | N7: =-SUMIFS(TB_Calicut[Mar],TB_Calicut[MIS_Group1],$B7)/10^5 -> 10.56666 | O7: =SUM(C7:N7) -> 133.63087 | P7: 168.79424 | R7: =-SUMIFS(TB_Calicut[Apr_26],TB_Calicut[MIS_Group1],$B7)/10^5 -> 9.159555 | S7: =-SUMIFS(TB_Calicut!AB:AB,TB_Calicut!J:J,PL_Calicut!B7)/10^5 -> 10.670718 | U7: =IFERROR(R7/C7-1,"-") -> -0.23065864 | V7: =IFERROR(R7/N7-1,"-") -> -0.1331646 | W7: =IFERROR(R7/T7,"-") -> -
B8: OP Pharmacy | C8: =-SUMIFS(TB_Calicut[Apr],TB_Calicut[MIS_Group1],$B8)/10^5 -> 16.373898 | D8: =-SUMIFS(TB_Calicut[May],TB_Calicut[MIS_Group1],$B8)/10^5 -> 14.143823 | E8: =-SUMIFS(TB_Calicut[Jun],TB_Calicut[MIS_Group1],$B8)/10^5 -> 14.985201 | F8: =-SUMIFS(TB_Calicut[Jul],TB_Calicut[MIS_Group1],$B8)/10^5 -> 18.045853 | G8: =-SUMIFS(TB_Calicut[Aug],TB_Calicut[MIS_Group1],$B8)/10^5 -> 16.696175 | H8: =-SUMIFS(TB_Calicut[Sep],TB_Calicut[MIS_Group1],$B8)/10^5 -> 19.381276 | I8: =-SUMIFS(TB_Calicut[Oct],TB_Calicut[MIS_Group1],$B8)/10^5 -> 20.670919 | J8: =-SUMIFS(TB_Calicut[Nov],TB_Calicut[MIS_Group1],$B8)/10^5 -> 17.948125 | K8: =-SUMIFS(TB_Calicut[Dec],TB_Calicut[MIS_Group1],$B8)/10^5 -> 26.212341 | L8: =-SUMIFS(TB_Calicut[Jan],TB_Calicut[MIS_Group1],$B8)/10^5 -> 18.126335 | M8: =-SUMIFS(TB_Calicut[Feb],TB_Calicut[MIS_Group1],$B8)/10^5 -> 21.759343 | N8: =-SUMIFS(TB_Calicut[Mar],TB_Calicut[MIS_Group1],$B8)/10^5 -> 19.073116 | O8: =SUM(C8:N8) -> 223.4164 | P8: 282.20576 | R8: =-SUMIFS(TB_Calicut[Apr_26],TB_Calicut[MIS_Group1],$B8)/10^5 -> 21.342837 | S8: =-SUMIFS(TB_Calicut!AB:AB,TB_Calicut!J:J,PL_Calicut!B8)/10^5 -> 16.363267 | U8: =IFERROR(R8/C8-1,"-") -> 0.3034671 | V8: =IFERROR(R8/N8-1,"-") -> 0.1190011 | W8: =IFERROR(R8/T8,"-") -> -
B9: Revenue From Operation | C9: =SUM(C7:C8) -> 28.279608 | D9: =SUM(D7:D8) -> 23.068753 | E9: =SUM(E7:E8) -> 24.915361 | F9: =SUM(F7:F8) -> 30.506783 | G9: =SUM(G7:G8) -> 29.256331 | H9: =SUM(H7:H8) -> 31.951398 | I9: =SUM(I7:I8) -> 32.550368 | J9: =SUM(J7:J8) -> 28.405105 | ... S9: =SUM(S7:S8) -> 27.033984 | U9: =IFERROR(R9/C9-1,"-") -> 0.078600259 | V9: =IFERROR(R9/N9-1,"-") -> 0.029103351 | W9: =IFERROR(R9/T9,"-") -> -
B10: Other Income | C10: =-SUMIFS(TB_Calicut[Apr],TB_Calicut[MIS_Group1],$B10)/10^5 -> 0 | D10: =-SUMIFS(TB_Calicut[May],TB_Calicut[MIS_Group1],$B10)/10^5 -> 0 | E10: =-SUMIFS(TB_Calicut[Jun],TB_Calicut[MIS_Group1],$B10)/10^5 -> 0 | F10: =-SUMIFS(TB_Calicut[Jul],TB_Calicut[MIS_Group1],$B10)/10^5 -> 0.67109 | G10: =-SUMIFS(TB_Calicut[Aug],TB_Calicut[MIS_Group1],$B10)/10^5 -> 0.11326 | H10: =-SUMIFS(TB_Calicut[Sep],TB_Calicut[MIS_Group1],$B10)/10^5 -> 0.11461 | I10: =-SUMIFS(TB_Calicut[Oct],TB_Calicut[MIS_Group1],$B10)/10^5 -> 0.12259 | J10: =-SUMIFS(TB_Calicut[Nov],TB_Calicut[MIS_Group1],$B10)/10^5 -> 0.13443 | K10: =-SUMIFS(TB_Calicut[Dec],TB_Calicut[MIS_Group1],$B10)/10^5 -> 0.12834 | L10: =-SUMIFS(TB_Calicut[Jan],TB_Calicut[MIS_Group1],$B10)/10^5 -> 0.09395 | M10: =-SUMIFS(TB_Calicut[Feb],TB_Calicut[MIS_Group1],$B10)/10^5 -> 0.10104 | N10: =-SUMIFS(TB_Calicut[Mar],TB_Calicut[MIS_Group1],$B10)/10^5 -> 0.09618 | O10: =SUM(C10:N10) -> 1.57549 | P10: 7.56e-06 | R10: =-SUMIFS(TB_Calicut[Apr_26],TB_Calicut[MIS_Group1],$B10)/10^5 -> 0.06728 | S10: =-SUMIFS(TB_Calicut!AB:AB,TB_Calicut!J:J,PL_Calicut!B10)/10^5 -> 0.11769 | U10: =IFERROR(R10/C10-1,"-") -> - | V10: =IFERROR(R10/N10-1,"-") -> -0.30047827 | W10: =IFERROR(R10/T10,"-") -> -
B11: Total Revenue | C11: =SUM(C9:C10) -> 28.279608 | D11: =SUM(D9:D10) -> 23.068753 | E11: =SUM(E9:E10) -> 24.915361 | F11: =SUM(F9:F10) -> 31.177873 | G11: =SUM(G9:G10) -> 29.369591 | H11: =SUM(H9:H10) -> 32.066008 | I11: =SUM(I9:I10) -> 32.672958 | J11: =SUM(J9:J10) -> 28.539535 | ... S11: =SUM(S9:S10) -> 27.151674 | U11: =IFERROR(R11/C11-1,"-") -> 0.080979358 | V11: =IFERROR(R11/N11-1,"-") -> 0.02803733 | W11: =IFERROR(R11/T11,"-") -> -
U12: =IFERROR(R12/C12-1,"-") -> - | V12: =IFERROR(R12/N12-1,"-") -> - | W12: =IFERROR(R12/T12,"-") -> -
B13: Material Cost | C13: =SUMIFS(TB_Calicut[Apr],TB_Calicut[MIS_Group1],$B13)/10^5 -> 7.3410719 | D13: =SUMIFS(TB_Calicut[May],TB_Calicut[MIS_Group1],$B13)/10^5 -> 10.26781 | E13: =SUMIFS(TB_Calicut[Jun],TB_Calicut[MIS_Group1],$B13)/10^5 -> 10.483299 | F13: =SUMIFS(TB_Calicut[Jul],TB_Calicut[MIS_Group1],$B13)/10^5 -> 12.919084 | G13: =SUMIFS(TB_Calicut[Aug],TB_Calicut[MIS_Group1],$B13)/10^5 -> 10.564763 | H13: =SUMIFS(TB_Calicut[Sep],TB_Calicut[MIS_Group1],$B13)/10^5 -> 13.330288 | I13: =SUMIFS(TB_Calicut[Oct],TB_Calicut[MIS_Group1],$B13)/10^5 -> 15.671179 | J13: =SUMIFS(TB_Calicut[Nov],TB_Calicut[MIS_Group1],$B13)/10^5 -> 12.886412 | K13: =SUMIFS(TB_Calicut[Dec],TB_Calicut[MIS_Group1],$B13)/10^5 -> 18.539978 | L13: =SUMIFS(TB_Calicut[Jan],TB_Calicut[MIS_Group1],$B13)/10^5 -> 12.403138 | M13: =SUMIFS(TB_Calicut[Feb],TB_Calicut[MIS_Group1],$B13)/10^5 -> 16.044492 | N13: =SUMIFS(TB_Calicut[Mar],TB_Calicut[MIS_Group1],$B13)/10^5 -> 15.665462 | O13: =SUM(C13:N13) -> 156.11698 | P13: 198.45885 | R13: =SUMIFS(TB_Calicut[Apr_26],TB_Calicut[MIS_Group1],$B13)/10^5 -> 15.66163 | S13: =SUMIFS(TB_Calicut!AB:AB,TB_Calicut!J:J,PL_Calicut!B13)/10^5 -> 11.888618 | U13: =IFERROR(R13/C13-1,"-") -> 1.1334255 | V13: =IFERROR(R13/N13-1,"-") -> -0.00024461219 | W13: =IFERROR(R13/T13,"-") -> -
B14: Doctor Cost | C14: =SUMIFS(TB_Calicut[Apr],TB_Calicut[MIS_Group1],$B14)/10^5 -> 10.42993 | D14: =SUMIFS(TB_Calicut[May],TB_Calicut[MIS_Group1],$B14)/10^5 -> 10.3519 | E14: =SUMIFS(TB_Calicut[Jun],TB_Calicut[MIS_Group1],$B14)/10^5 -> 9.92 | F14: =SUMIFS(TB_Calicut[Jul],TB_Calicut[MIS_Group1],$B14)/10^5 -> 11.84557 | G14: =SUMIFS(TB_Calicut[Aug],TB_Calicut[MIS_Group1],$B14)/10^5 -> 11.475 | H14: =SUMIFS(TB_Calicut[Sep],TB_Calicut[MIS_Group1],$B14)/10^5 -> 11.8407 | I14: =SUMIFS(TB_Calicut[Oct],TB_Calicut[MIS_Group1],$B14)/10^5 -> 11.1903 | J14: =SUMIFS(TB_Calicut[Nov],TB_Calicut[MIS_Group1],$B14)/10^5 -> 10.6797 | K14: =SUMIFS(TB_Calicut[Dec],TB_Calicut[MIS_Group1],$B14)/10^5 -> 10.64354 | L14: =SUMIFS(TB_Calicut[Jan],TB_Calicut[MIS_Group1],$B14)/10^5 -> 9.24569 | M14: =SUMIFS(TB_Calicut[Feb],TB_Calicut[MIS_Group1],$B14)/10^5 -> 10.853224 | N14: =SUMIFS(TB_Calicut[Mar],TB_Calicut[MIS_Group1],$B14)/10^5 -> 10.116149 | O14: =SUM(C14:N14) -> 128.5917 | P14: 148.98 | R14: =SUMIFS(TB_Calicut[Apr_26],TB_Calicut[MIS_Group1],$B14)/10^5 -> 10.561936 | S14: =SUMIFS(TB_Calicut!AB:AB,TB_Calicut!J:J,PL_Calicut!B14)/10^5 -> 13.34443 | U14: =IFERROR(R14/C14-1,"-") -> 0.012656413 | V14: =IFERROR(R14/N14-1,"-") -> 0.04406686 | W14: =IFERROR(R14/T14,"-") -> -
B15: Employee Cost | C15: =SUMIFS(TB_Calicut[Apr],TB_Calicut[MIS_Group1],$B15)/10^5 -> 5.2472289 | D15: =SUMIFS(TB_Calicut[May],TB_Calicut[MIS_Group1],$B15)/10^5 -> 5.9149589 | E15: =SUMIFS(TB_Calicut[Jun],TB_Calicut[MIS_Group1],$B15)/10^5 -> 5.8809289 | F15: =SUMIFS(TB_Calicut[Jul],TB_Calicut[MIS_Group1],$B15)/10^5 -> 6.0773489 | G15: =SUMIFS(TB_Calicut[Aug],TB_Calicut[MIS_Group1],$B15)/10^5 -> 6.0624689 | H15: =SUMIFS(TB_Calicut[Sep],TB_Calicut[MIS_Group1],$B15)/10^5 -> 5.9636489 | I15: =SUMIFS(TB_Calicut[Oct],TB_Calicut[MIS_Group1],$B15)/10^5 -> 6.6325889 | J15: =SUMIFS(TB_Calicut[Nov],TB_Calicut[MIS_Group1],$B15)/10^5 -> 6.1059589 | K15: =SUMIFS(TB_Calicut[Dec],TB_Calicut[MIS_Group1],$B15)/10^5 -> 6.3907089 | L15: =SUMIFS(TB_Calicut[Jan],TB_Calicut[MIS_Group1],$B15)/10^5 -> 6.3999489 | M15: =SUMIFS(TB_Calicut[Feb],TB_Calicut[MIS_Group1],$B15)/10^5 -> 6.4000789 | N15: =SUMIFS(TB_Calicut[Mar],TB_Calicut[MIS_Group1],$B15)/10^5 -> 6.3130289 | O15: =SUM(C15:N15) -> 73.388897 | P15: 125.07668 | R15: =SUMIFS(TB_Calicut[Apr_26],TB_Calicut[MIS_Group1],$B15)/10^5 -> 6.2502889 | S15: =SUMIFS(TB_Calicut!AB:AB,TB_Calicut!J:J,PL_Calicut!B15)/10^5 -> 5.9830989 | U15: =IFERROR(R15/C15-1,"-") -> 0.19115995 | V15: =IFERROR(R15/N15-1,"-") -> -0.0099381772 | W15: =IFERROR(R15/T15,"-") -> -
B16: Lab Test Charges | C16: =SUMIFS(TB_Calicut[Apr],TB_Calicut[MIS_Group1],$B16)/10^5 -> 0 | D16: =SUMIFS(TB_Calicut[May],TB_Calicut[MIS_Group1],$B16)/10^5 -> 0 | E16: =SUMIFS(TB_Calicut[Jun],TB_Calicut[MIS_Group1],$B16)/10^5 -> 0 | F16: =SUMIFS(TB_Calicut[Jul],TB_Calicut[MIS_Group1],$B16)/10^5 -> 0 | G16: =SUMIFS(TB_Calicut[Aug],TB_Calicut[MIS_Group1],$B16)/10^5 -> 0 | H16: =SUMIFS(TB_Calicut[Sep],TB_Calicut[MIS_Group1],$B16)/10^5 -> 0 | I16: =SUMIFS(TB_Calicut[Oct],TB_Calicut[MIS_Group1],$B16)/10^5 -> 0 | J16: =SUMIFS(TB_Calicut[Nov],TB_Calicut[MIS_Group1],$B16)/10^5 -> 0 | K16: =SUMIFS(TB_Calicut[Dec],TB_Calicut[MIS_Group1],$B16)/10^5 -> 0 | L16: =SUMIFS(TB_Calicut[Jan],TB_Calicut[MIS_Group1],$B16)/10^5 -> 0.0375 | M16: =SUMIFS(TB_Calicut[Feb],TB_Calicut[MIS_Group1],$B16)/10^5 -> 0 | N16: =SUMIFS(TB_Calicut[Mar],TB_Calicut[MIS_Group1],$B16)/10^5 -> 0 | O16: =SUM(C16:N16) -> 0.0375 | P16: 0 | R16: =SUMIFS(TB_Calicut[Apr_26],TB_Calicut[MIS_Group1],$B16)/10^5 -> 0.015 | S16: =SUMIFS(TB_Calicut!AB:AB,TB_Calicut!J:J,PL_Calicut!B16)/10^5 -> 0 | U16: =IFERROR(R16/C16-1,"-") -> - | V16: =IFERROR(R16/N16-1,"-") -> - | W16: =IFERROR(R16/T16,"-") -> -
B17: Utilities-Power, fuel & water charges | C17: =SUMIFS(TB_Calicut[Apr],TB_Calicut[MIS_Group1],$B17)/10^5 -> 1.5581203 | D17: =SUMIFS(TB_Calicut[May],TB_Calicut[MIS_Group1],$B17)/10^5 -> 1.60753 | E17: =SUMIFS(TB_Calicut[Jun],TB_Calicut[MIS_Group1],$B17)/10^5 -> 1.2912085 | F17: =SUMIFS(TB_Calicut[Jul],TB_Calicut[MIS_Group1],$B17)/10^5 -> 1.52354 | G17: =SUMIFS(TB_Calicut[Aug],TB_Calicut[MIS_Group1],$B17)/10^5 -> 1.40257 | H17: =SUMIFS(TB_Calicut[Sep],TB_Calicut[MIS_Group1],$B17)/10^5 -> 1.4304 | I17: =SUMIFS(TB_Calicut[Oct],TB_Calicut[MIS_Group1],$B17)/10^5 -> 1.53711 | J17: =SUMIFS(TB_Calicut[Nov],TB_Calicut[MIS_Group1],$B17)/10^5 -> 1.5252158 | K17: =SUMIFS(TB_Calicut[Dec],TB_Calicut[MIS_Group1],$B17)/10^5 -> 1.3682462 | L17: =SUMIFS(TB_Calicut[Jan],TB_Calicut[MIS_Group1],$B17)/10^5 -> 1.40558 | M17: =SUMIFS(TB_Calicut[Feb],TB_Calicut[MIS_Group1],$B17)/10^5 -> 1.36916 | N17: =SUMIFS(TB_Calicut[Mar],TB_Calicut[MIS_Group1],$B17)/10^5 -> 1.39039 | O17: =SUM(C17:N17) -> 17.409071 | P17: 17.607413 | R17: =SUMIFS(TB_Calicut[Apr_26],TB_Calicut[MIS_Group1],$B17)/10^5 -> 1.5981005 | S17: =SUMIFS(TB_Calicut!AB:AB,TB_Calicut!J:J,PL_Calicut!B17)/10^5 -> 1.62963 | U17: =IFERROR(R17/C17-1,"-") -> 0.025659251 | V17: =IFERROR(R17/N17-1,"-") -> 0.1493901 | W17: =IFERROR(R17/T17,"-") -> -
B18: Rent Paid | C18: =SUMIFS(TB_Calicut[Apr],TB_Calicut[MIS_Group1],$B18)/10^5 -> 9.27067 | D18: =SUMIFS(TB_Calicut[May],TB_Calicut[MIS_Group1],$B18)/10^5 -> 9.27067 | E18: =SUMIFS(TB_Calicut[Jun],TB_Calicut[MIS_Group1],$B18)/10^5 -> 9.27067 | F18: =SUMIFS(TB_Calicut[Jul],TB_Calicut[MIS_Group1],$B18)/10^5 -> 9.27467 | G18: =SUMIFS(TB_Calicut[Aug],TB_Calicut[MIS_Group1],$B18)/10^5 -> 9.31787 | H18: =SUMIFS(TB_Calicut[Sep],TB_Calicut[MIS_Group1],$B18)/10^5 -> 9.31787 | I18: =SUMIFS(TB_Calicut[Oct],TB_Calicut[MIS_Group1],$B18)/10^5 -> 10.002895 | J18: =SUMIFS(TB_Calicut[Nov],TB_Calicut[MIS_Group1],$B18)/10^5 -> 10.602276 | K18: =SUMIFS(TB_Calicut[Dec],TB_Calicut[MIS_Group1],$B18)/10^5 -> 10.632276 | L18: =SUMIFS(TB_Calicut[Jan],TB_Calicut[MIS_Group1],$B18)/10^5 -> 10.602276 | M18: =SUMIFS(TB_Calicut[Feb],TB_Calicut[MIS_Group1],$B18)/10^5 -> 10.602276 | N18: =SUMIFS(TB_Calicut[Mar],TB_Calicut[MIS_Group1],$B18)/10^5 -> 10.657476 | O18: =SUM(C18:N18) -> 118.8219 | P18: 111.24804 | R18: =SUMIFS(TB_Calicut[Apr_26],TB_Calicut[MIS_Group1],$B18)/10^5 -> 10.602276 | S18: =SUMIFS(TB_Calicut!AB:AB,TB_Calicut!J:J,PL_Calicut!B18)/10^5 -> 10.559076 | U18: =IFERROR(R18/C18-1,"-") -> 0.14363648 | V18: =IFERROR(R18/N18-1,"-") -> -0.0051794626 | W18: =IFERROR(R18/T18,"-") -> -
B19: Repair & Maintenance | C19: =SUMIFS(TB_Calicut[Apr],TB_Calicut[MIS_Group1],$B19)/10^5 -> 0 | D19: =SUMIFS(TB_Calicut[May],TB_Calicut[MIS_Group1],$B19)/10^5 -> 0.10705 | E19: =SUMIFS(TB_Calicut[Jun],TB_Calicut[MIS_Group1],$B19)/10^5 -> 1.274665 | F19: =SUMIFS(TB_Calicut[Jul],TB_Calicut[MIS_Group1],$B19)/10^5 -> 0.98441 | G19: =SUMIFS(TB_Calicut[Aug],TB_Calicut[MIS_Group1],$B19)/10^5 -> 0.13779 | H19: =SUMIFS(TB_Calicut[Sep],TB_Calicut[MIS_Group1],$B19)/10^5 -> 0.31773 | I19: =SUMIFS(TB_Calicut[Oct],TB_Calicut[MIS_Group1],$B19)/10^5 -> 0.34089 | J19: =SUMIFS(TB_Calicut[Nov],TB_Calicut[MIS_Group1],$B19)/10^5 -> 1.4202133 | K19: =SUMIFS(TB_Calicut[Dec],TB_Calicut[MIS_Group1],$B19)/10^5 -> 0.29584 | L19: =SUMIFS(TB_Calicut[Jan],TB_Calicut[MIS_Group1],$B19)/10^5 -> 0.9565348 | M19: =SUMIFS(TB_Calicut[Feb],TB_Calicut[MIS_Group1],$B19)/10^5 -> 0.5966908 | N19: =SUMIFS(TB_Calicut[Mar],TB_Calicut[MIS_Group1],$B19)/10^5 -> 3.5600088 | O19: =SUM(C19:N19) -> 9.9918227 | P19: 13.671564 | R19: =SUMIFS(TB_Calicut[Apr_26],TB_Calicut[MIS_Group1],$B19)/10^5 -> 3.1193831 | S19: =SUMIFS(TB_Calicut!AB:AB,TB_Calicut!J:J,PL_Calicut!B19)/10^5 -> 0.6506866 | U19: =IFERROR(R19/C19-1,"-") -> - | V19: =IFERROR(R19/N19-1,"-") -> -0.12377096 | W19: =IFERROR(R19/T19,"-") -> -
B20: House Keeping Expenses | C20: =SUMIFS(TB_Calicut[Apr],TB_Calicut[MIS_Group1],$B20)/10^5 -> 0.89366 | D20: =SUMIFS(TB_Calicut[May],TB_Calicut[MIS_Group1],$B20)/10^5 -> 0.98822 | E20: =SUMIFS(TB_Calicut[Jun],TB_Calicut[MIS_Group1],$B20)/10^5 -> 0.86074 | F20: =SUMIFS(TB_Calicut[Jul],TB_Calicut[MIS_Group1],$B20)/10^5 -> 1.1517 | G20: =SUMIFS(TB_Calicut[Aug],TB_Calicut[MIS_Group1],$B20)/10^5 -> 1.1262724 | H20: =SUMIFS(TB_Calicut[Sep],TB_Calicut[MIS_Group1],$B20)/10^5 -> 0.990836 | I20: =SUMIFS(TB_Calicut[Oct],TB_Calicut[MIS_Group1],$B20)/10^5 -> 1.017736 | J20: =SUMIFS(TB_Calicut[Nov],TB_Calicut[MIS_Group1],$B20)/10^5 -> 0.993846 | K20: =SUMIFS(TB_Calicut[Dec],TB_Calicut[MIS_Group1],$B20)/10^5 -> 0.987096 | L20: =SUMIFS(TB_Calicut[Jan],TB_Calicut[MIS_Group1],$B20)/10^5 -> 1.49856 | M20: =SUMIFS(TB_Calicut[Feb],TB_Calicut[MIS_Group1],$B20)/10^5 -> 1.09579 | N20: =SUMIFS(TB_Calicut[Mar],TB_Calicut[MIS_Group1],$B20)/10^5 -> 1.702991 | O20: =SUM(C20:N20) -> 13.307447 | P20: 13.766747 | R20: =SUMIFS(TB_Calicut[Apr_26],TB_Calicut[MIS_Group1],$B20)/10^5 -> 0.79214 | S20: =SUMIFS(TB_Calicut!AB:AB,TB_Calicut!J:J,PL_Calicut!B20)/10^5 -> 0.99506 | U20: =IFERROR(R20/C20-1,"-") -> -0.11360025 | V20: =IFERROR(R20/N20-1,"-") -> -0.53485368 | W20: =IFERROR(R20/T20,"-") -> -
B21: Security Expenses | C21: =SUMIFS(TB_Calicut[Apr],TB_Calicut[MIS_Group1],$B21)/10^5 -> 0.36256 | D21: =SUMIFS(TB_Calicut[May],TB_Calicut[MIS_Group1],$B21)/10^5 -> 0.36256 | E21: =SUMIFS(TB_Calicut[Jun],TB_Calicut[MIS_Group1],$B21)/10^5 -> 0.36256 | F21: =SUMIFS(TB_Calicut[Jul],TB_Calicut[MIS_Group1],$B21)/10^5 -> 0.36256 | G21: =SUMIFS(TB_Calicut[Aug],TB_Calicut[MIS_Group1],$B21)/10^5 -> 0.20467 | H21: =SUMIFS(TB_Calicut[Sep],TB_Calicut[MIS_Group1],$B21)/10^5 -> 0.362562 | I21: =SUMIFS(TB_Calicut[Oct],TB_Calicut[MIS_Group1],$B21)/10^5 -> 0.362562 | J21: =SUMIFS(TB_Calicut[Nov],TB_Calicut[MIS_Group1],$B21)/10^5 -> 0.362562 | K21: =SUMIFS(TB_Calicut[Dec],TB_Calicut[MIS_Group1],$B21)/10^5 -> 0.36256 | L21: =SUMIFS(TB_Calicut[Jan],TB_Calicut[MIS_Group1],$B21)/10^5 -> 0.36256 | M21: =SUMIFS(TB_Calicut[Feb],TB_Calicut[MIS_Group1],$B21)/10^5 -> 0.36256 | N21: =SUMIFS(TB_Calicut[Mar],TB_Calicut[MIS_Group1],$B21)/10^5 -> 0.660441 | O21: =SUM(C21:N21) -> 4.490717 | P21: 6.7887355 | R21: =SUMIFS(TB_Calicut[Apr_26],TB_Calicut[MIS_Group1],$B21)/10^5 -> 0.61204 | S21: =SUMIFS(TB_Calicut!AB:AB,TB_Calicut!J:J,PL_Calicut!B21)/10^5 -> 0.36256 | U21: =IFERROR(R21/C21-1,"-") -> 0.6881068 | V21: =IFERROR(R21/N21-1,"-") -> -0.07328588 | W21: =IFERROR(R21/T21,"-") -> -
B22: Printing & Stationery | C22: =SUMIFS(TB_Calicut[Apr],TB_Calicut[MIS_Group1],$B22)/10^5 -> 0 | D22: =SUMIFS(TB_Calicut[May],TB_Calicut[MIS_Group1],$B22)/10^5 -> 0.09533 | E22: =SUMIFS(TB_Calicut[Jun],TB_Calicut[MIS_Group1],$B22)/10^5 -> 0.0435 | F22: =SUMIFS(TB_Calicut[Jul],TB_Calicut[MIS_Group1],$B22)/10^5 -> 0.25163 | G22: =SUMIFS(TB_Calicut[Aug],TB_Calicut[MIS_Group1],$B22)/10^5 -> 0.12301 | H22: =SUMIFS(TB_Calicut[Sep],TB_Calicut[MIS_Group1],$B22)/10^5 -> 0 | I22: =SUMIFS(TB_Calicut[Oct],TB_Calicut[MIS_Group1],$B22)/10^5 -> 0.44728 | J22: =SUMIFS(TB_Calicut[Nov],TB_Calicut[MIS_Group1],$B22)/10^5 -> 0.06374 | K22: =SUMIFS(TB_Calicut[Dec],TB_Calicut[MIS_Group1],$B22)/10^5 -> 0.07369 | L22: =SUMIFS(TB_Calicut[Jan],TB_Calicut[MIS_Group1],$B22)/10^5 -> 0.20561 | M22: =SUMIFS(TB_Calicut[Feb],TB_Calicut[MIS_Group1],$B22)/10^5 -> 0.5747365 | N22: =SUMIFS(TB_Calicut[Mar],TB_Calicut[MIS_Group1],$B22)/10^5 -> 0.0846 | O22: =SUM(C22:N22) -> 1.9631265 | P22: 3.3114111 | R22: =SUMIFS(TB_Calicut[Apr_26],TB_Calicut[MIS_Group1],$B22)/10^5 -> 0 | S22: =SUMIFS(TB_Calicut!AB:AB,TB_Calicut!J:J,PL_Calicut!B22)/10^5 -> 0.0633 | U22: =IFERROR(R22/C22-1,"-") -> - | V22: =IFERROR(R22/N22-1,"-") -> -1 | W22: =IFERROR(R22/T22,"-") -> -
B23: Insurance | C23: =SUMIFS(TB_Calicut[Apr],TB_Calicut[MIS_Group1],$B23)/10^5 -> 0.14727 | D23: =SUMIFS(TB_Calicut[May],TB_Calicut[MIS_Group1],$B23)/10^5 -> 0 | E23: =SUMIFS(TB_Calicut[Jun],TB_Calicut[MIS_Group1],$B23)/10^5 -> 0.15669 | F23: =SUMIFS(TB_Calicut[Jul],TB_Calicut[MIS_Group1],$B23)/10^5 -> 0 | G23: =SUMIFS(TB_Calicut[Aug],TB_Calicut[MIS_Group1],$B23)/10^5 -> 0 | H23: =SUMIFS(TB_Calicut[Sep],TB_Calicut[MIS_Group1],$B23)/10^5 -> 0.7747 | I23: =SUMIFS(TB_Calicut[Oct],TB_Calicut[MIS_Group1],$B23)/10^5 -> 0.0201933 | J23: =SUMIFS(TB_Calicut[Nov],TB_Calicut[MIS_Group1],$B23)/10^5 -> 0.0295 | K23: =SUMIFS(TB_Calicut[Dec],TB_Calicut[MIS_Group1],$B23)/10^5 -> 0.0201933 | L23: =SUMIFS(TB_Calicut[Jan],TB_Calicut[MIS_Group1],$B23)/10^5 -> -0.3963767 | M23: =SUMIFS(TB_Calicut[Feb],TB_Calicut[MIS_Group1],$B23)/10^5 -> 0.0797833 | N23: =SUMIFS(TB_Calicut[Mar],TB_Calicut[MIS_Group1],$B23)/10^5 -> 0.0822233 | O23: =SUM(C23:N23) -> 0.9141765 | P23: 0.78596385 | R23: =SUMIFS(TB_Calicut[Apr_26],TB_Calicut[MIS_Group1],$B23)/10^5 -> 0.07451 | S23: =SUMIFS(TB_Calicut!AB:AB,TB_Calicut!J:J,PL_Calicut!B23)/10^5 -> 0.07512 | U23: =IFERROR(R23/C23-1,"-") -> -0.49405853 | V23: =IFERROR(R23/N23-1,"-") -> -0.093809176 | W23: =IFERROR(R23/T23,"-") -> -
B24: Rates & taxes | C24: =SUMIFS(TB_Calicut[Apr],TB_Calicut[MIS_Group1],$B24)/10^5 -> 0.0648 | D24: =SUMIFS(TB_Calicut[May],TB_Calicut[MIS_Group1],$B24)/10^5 -> 0.00323 | E24: =SUMIFS(TB_Calicut[Jun],TB_Calicut[MIS_Group1],$B24)/10^5 -> 0.0592875 | F24: =SUMIFS(TB_Calicut[Jul],TB_Calicut[MIS_Group1],$B24)/10^5 -> 0.00023 | G24: =SUMIFS(TB_Calicut[Aug],TB_Calicut[MIS_Group1],$B24)/10^5 -> 0.002 | H24: =SUMIFS(TB_Calicut[Sep],TB_Calicut[MIS_Group1],$B24)/10^5 -> 0.0592875 | I24: =SUMIFS(TB_Calicut[Oct],TB_Calicut[MIS_Group1],$B24)/10^5 -> 0.0197625 | J24: =SUMIFS(TB_Calicut[Nov],TB_Calicut[MIS_Group1],$B24)/10^5 -> 0.0197625 | K24: =SUMIFS(TB_Calicut[Dec],TB_Calicut[MIS_Group1],$B24)/10^5 -> 0.0197625 | L24: =SUMIFS(TB_Calicut[Jan],TB_Calicut[MIS_Group1],$B24)/10^5 -> 0.0207625 | M24: =SUMIFS(TB_Calicut[Feb],TB_Calicut[MIS_Group1],$B24)/10^5 -> 0.0197625 | N24: =SUMIFS(TB_Calicut[Mar],TB_Calicut[MIS_Group1],$B24)/10^5 -> 0.0772625 | O24: =SUM(C24:N24) -> 0.36591 | P24: 0.45477401 | R24: =SUMIFS(TB_Calicut[Apr_26],TB_Calicut[MIS_Group1],$B24)/10^5 -> 0.2447625 | S24: =SUMIFS(TB_Calicut!AB:AB,TB_Calicut!J:J,PL_Calicut!B24)/10^5 -> 0.0277625 | U24: =IFERROR(R24/C24-1,"-") -> 2.7771991 | V24: =IFERROR(R24/N24-1,"-") -> 2.167934 | W24: =IFERROR(R24/T24,"-") -> -
B25: Professional Fee | C25: =SUMIFS(TB_Calicut[Apr],TB_Calicut[MIS_Group1],$B25)/10^5 -> 0 | D25: =SUMIFS(TB_Calicut[May],TB_Calicut[MIS_Group1],$B25)/10^5 -> 0 | E25: =SUMIFS(TB_Calicut[Jun],TB_Calicut[MIS_Group1],$B25)/10^5 -> 0 | F25: =SUMIFS(TB_Calicut[Jul],TB_Calicut[MIS_Group1],$B25)/10^5 -> 0 | G25: =SUMIFS(TB_Calicut[Aug],TB_Calicut[MIS_Group1],$B25)/10^5 -> 0.0245 | H25: =SUMIFS(TB_Calicut[Sep],TB_Calicut[MIS_Group1],$B25)/10^5 -> 0 | I25: =SUMIFS(TB_Calicut[Oct],TB_Calicut[MIS_Group1],$B25)/10^5 -> 0.2 | J25: =SUMIFS(TB_Calicut[Nov],TB_Calicut[MIS_Group1],$B25)/10^5 -> 0.2465 | K25: =SUMIFS(TB_Calicut[Dec],TB_Calicut[MIS_Group1],$B25)/10^5 -> 0 | L25: =SUMIFS(TB_Calicut[Jan],TB_Calicut[MIS_Group1],$B25)/10^5 -> 0.048 | M25: =SUMIFS(TB_Calicut[Feb],TB_Calicut[MIS_Group1],$B25)/10^5 -> 0.4 | N25: =SUMIFS(TB_Calicut[Mar],TB_Calicut[MIS_Group1],$B25)/10^5 -> 0 | O25: =SUM(C25:N25) -> 0.919 | P25: 7.7505563 | R25: =SUMIFS(TB_Calicut[Apr_26],TB_Calicut[MIS_Group1],$B25)/10^5 -> 0.2 | S25: =SUMIFS(TB_Calicut!AB:AB,TB_Calicut!J:J,PL_Calicut!B25)/10^5 -> 0 | U25: =IFERROR(R25/C25-1,"-") -> - | V25: =IFERROR(R25/N25-1,"-") -> - | W25: =IFERROR(R25/T25,"-") -> -
B26: Quality & Infection control expense | C26: =SUMIFS(TB_Calicut[Apr],TB_Calicut[MIS_Group1],$B26)/10^5 -> 0 | D26: =SUMIFS(TB_Calicut[May],TB_Calicut[MIS_Group1],$B26)/10^5 -> 0 | E26: =SUMIFS(TB_Calicut[Jun],TB_Calicut[MIS_Group1],$B26)/10^5 -> 0 | F26: =SUMIFS(TB_Calicut[Jul],TB_Calicut[MIS_Group1],$B26)/10^5 -> 0 | G26: =SUMIFS(TB_Calicut[Aug],TB_Calicut[MIS_Group1],$B26)/10^5 -> 0 | H26: =SUMIFS(TB_Calicut[Sep],TB_Calicut[MIS_Group1],$B26)/10^5 -> 0 | I26: =SUMIFS(TB_Calicut[Oct],TB_Calicut[MIS_Group1],$B26)/10^5 -> 0 | J26: =SUMIFS(TB_Calicut[Nov],TB_Calicut[MIS_Group1],$B26)/10^5 -> 0 | K26: =SUMIFS(TB_Calicut[Dec],TB_Calicut[MIS_Group1],$B26)/10^5 -> 0 | L26: =SUMIFS(TB_Calicut[Jan],TB_Calicut[MIS_Group1],$B26)/10^5 -> 0 | M26: =SUMIFS(TB_Calicut[Feb],TB_Calicut[MIS_Group1],$B26)/10^5 -> 0 | N26: =SUMIFS(TB_Calicut[Mar],TB_Calicut[MIS_Group1],$B26)/10^5 -> 0 | O26: =SUM(C26:N26) -> 0 | R26: =SUMIFS(TB_Calicut[Apr_26],TB_Calicut[MIS_Group1],$B26)/10^5 -> 0 | S26: =SUMIFS(TB_Calicut!AB:AB,TB_Calicut!J:J,PL_Calicut!B26)/10^5 -> 0 | U26: =IFERROR(R26/C26-1,"-") -> - | V26: =IFERROR(R26/N26-1,"-") -> - | W26: =IFERROR(R26/T26,"-") -> -
B27: Provission for Bad Debts | C27: =SUMIFS(TB_Calicut[Apr],TB_Calicut[MIS_Group1],$B27)/10^5 -> 0 | D27: =SUMIFS(TB_Calicut[May],TB_Calicut[MIS_Group1],$B27)/10^5 -> 0 | E27: =SUMIFS(TB_Calicut[Jun],TB_Calicut[MIS_Group1],$B27)/10^5 -> 0 | F27: =SUMIFS(TB_Calicut[Jul],TB_Calicut[MIS_Group1],$B27)/10^5 -> 0 | G27: =SUMIFS(TB_Calicut[Aug],TB_Calicut[MIS_Group1],$B27)/10^5 -> 0 | H27: =SUMIFS(TB_Calicut[Sep],TB_Calicut[MIS_Group1],$B27)/10^5 -> 0 | I27: =SUMIFS(TB_Calicut[Oct],TB_Calicut[MIS_Group1],$B27)/10^5 -> 0 | J27: =SUMIFS(TB_Calicut[Nov],TB_Calicut[MIS_Group1],$B27)/10^5 -> 0 | K27: =SUMIFS(TB_Calicut[Dec],TB_Calicut[MIS_Group1],$B27)/10^5 -> 0 | L27: =SUMIFS(TB_Calicut[Jan],TB_Calicut[MIS_Group1],$B27)/10^5 -> 0 | M27: =SUMIFS(TB_Calicut[Feb],TB_Calicut[MIS_Group1],$B27)/10^5 -> 0 | N27: =SUMIFS(TB_Calicut[Mar],TB_Calicut[MIS_Group1],$B27)/10^5 -> 0 | O27: =SUM(C27:N27) -> 0 | R27: =SUMIFS(TB_Calicut[Apr_26],TB_Calicut[MIS_Group1],$B27)/10^5 -> 0 | S27: =SUMIFS(TB_Calicut!AB:AB,TB_Calicut!J:J,PL_Calicut!B27)/10^5 -> 0 | U27: =IFERROR(R27/C27-1,"-") -> - | V27: =IFERROR(R27/N27-1,"-") -> - | W27: =IFERROR(R27/T27,"-") -> -
B28: Marketing Cost | C28: =SUMIFS(TB_Calicut[Apr],TB_Calicut[MIS_Group1],$B28)/10^5 -> 0 | D28: =SUMIFS(TB_Calicut[May],TB_Calicut[MIS_Group1],$B28)/10^5 -> 0 | E28: =SUMIFS(TB_Calicut[Jun],TB_Calicut[MIS_Group1],$B28)/10^5 -> 0 | F28: =SUMIFS(TB_Calicut[Jul],TB_Calicut[MIS_Group1],$B28)/10^5 -> 0.18994 | G28: =SUMIFS(TB_Calicut[Aug],TB_Calicut[MIS_Group1],$B28)/10^5 -> 0.10557 | H28: =SUMIFS(TB_Calicut[Sep],TB_Calicut[MIS_Group1],$B28)/10^5 -> 0 | I28: =SUMIFS(TB_Calicut[Oct],TB_Calicut[MIS_Group1],$B28)/10^5 -> 0 | J28: =SUMIFS(TB_Calicut[Nov],TB_Calicut[MIS_Group1],$B28)/10^5 -> 0.0174 | K28: =SUMIFS(TB_Calicut[Dec],TB_Calicut[MIS_Group1],$B28)/10^5 -> 0 | L28: =SUMIFS(TB_Calicut[Jan],TB_Calicut[MIS_Group1],$B28)/10^5 -> 0.05 | M28: =SUMIFS(TB_Calicut[Feb],TB_Calicut[MIS_Group1],$B28)/10^5 -> 0.0012 | N28: =SUMIFS(TB_Calicut[Mar],TB_Calicut[MIS_Group1],$B28)/10^5 -> 0.1491 | O28: =SUM(C28:N28) -> 0.51321 | P28: 0.42365838 | R28: =SUMIFS(TB_Calicut[Apr_26],TB_Calicut[MIS_Group1],$B28)/10^5 -> 0 | S28: =SUMIFS(TB_Calicut!AB:AB,TB_Calicut!J:J,PL_Calicut!B28)/10^5 -> 0.0009 | U28: =IFERROR(R28/C28-1,"-") -> - | V28: =IFERROR(R28/N28-1,"-") -> -1 | W28: =IFERROR(R28/T28,"-") -> -
B29: Communication Costs | C29: =SUMIFS(TB_Calicut[Apr],TB_Calicut[MIS_Group1],$B29)/10^5 -> 0 | D29: =SUMIFS(TB_Calicut[May],TB_Calicut[MIS_Group1],$B29)/10^5 -> 0.08721 | E29: =SUMIFS(TB_Calicut[Jun],TB_Calicut[MIS_Group1],$B29)/10^5 -> 0.08821 | F29: =SUMIFS(TB_Calicut[Jul],TB_Calicut[MIS_Group1],$B29)/10^5 -> 0.29401 | G29: =SUMIFS(TB_Calicut[Aug],TB_Calicut[MIS_Group1],$B29)/10^5 -> 0.09758 | H29: =SUMIFS(TB_Calicut[Sep],TB_Calicut[MIS_Group1],$B29)/10^5 -> 0.51348 | I29: =SUMIFS(TB_Calicut[Oct],TB_Calicut[MIS_Group1],$B29)/10^5 -> 0.18318 | J29: =SUMIFS(TB_Calicut[Nov],TB_Calicut[MIS_Group1],$B29)/10^5 -> 0.09518 | K29: =SUMIFS(TB_Calicut[Dec],TB_Calicut[MIS_Group1],$B29)/10^5 -> 0.52817 | L29: =SUMIFS(TB_Calicut[Jan],TB_Calicut[MIS_Group1],$B29)/10^5 -> 0.09478 | M29: =SUMIFS(TB_Calicut[Feb],TB_Calicut[MIS_Group1],$B29)/10^5 -> 0.09898 | N29: =SUMIFS(TB_Calicut[Mar],TB_Calicut[MIS_Group1],$B29)/10^5 -> 0.33538 | O29: =SUM(C29:N29) -> 2.41616 | P29: 6.2659919 | R29: =SUMIFS(TB_Calicut[Apr_26],TB_Calicut[MIS_Group1],$B29)/10^5 -> 0.25281 | S29: =SUMIFS(TB_Calicut!AB:AB,TB_Calicut!J:J,PL_Calicut!B29)/10^5 -> 0.2670207 | U29: =IFERROR(R29/C29-1,"-") -> - | V29: =IFERROR(R29/N29-1,"-") -> -0.24619834 | W29: =IFERROR(R29/T29,"-") -> -
B30: Business Travel Cost | C30: =SUMIFS(TB_Calicut[Apr],TB_Calicut[MIS_Group1],$B30)/10^5 -> 0 | D30: =SUMIFS(TB_Calicut[May],TB_Calicut[MIS_Group1],$B30)/10^5 -> 0.28599 | E30: =SUMIFS(TB_Calicut[Jun],TB_Calicut[MIS_Group1],$B30)/10^5 -> 0 | F30: =SUMIFS(TB_Calicut[Jul],TB_Calicut[MIS_Group1],$B30)/10^5 -> 0.31084 | G30: =SUMIFS(TB_Calicut[Aug],TB_Calicut[MIS_Group1],$B30)/10^5 -> 0.25081 | H30: =SUMIFS(TB_Calicut[Sep],TB_Calicut[MIS_Group1],$B30)/10^5 -> 0 | I30: =SUMIFS(TB_Calicut[Oct],TB_Calicut[MIS_Group1],$B30)/10^5 -> 0.31385 | J30: =SUMIFS(TB_Calicut[Nov],TB_Calicut[MIS_Group1],$B30)/10^5 -> 0.25411 | K30: =SUMIFS(TB_Calicut[Dec],TB_Calicut[MIS_Group1],$B30)/10^5 -> 0.09687 | L30: =SUMIFS(TB_Calicut[Jan],TB_Calicut[MIS_Group1],$B30)/10^5 -> 0.05027 | M30: =SUMIFS(TB_Calicut[Feb],TB_Calicut[MIS_Group1],$B30)/10^5 -> 0.61245 | N30: =SUMIFS(TB_Calicut[Mar],TB_Calicut[MIS_Group1],$B30)/10^5 -> 0.31259 | O30: =SUM(C30:N30) -> 2.48778 | P30: 2.8636466 | R30: =SUMIFS(TB_Calicut[Apr_26],TB_Calicut[MIS_Group1],$B30)/10^5 -> 0.176 | S30: =SUMIFS(TB_Calicut!AB:AB,TB_Calicut!J:J,PL_Calicut!B30)/10^5 -> 0.03093 | U30: =IFERROR(R30/C30-1,"-") -> - | V30: =IFERROR(R30/N30-1,"-") -> -0.43696215 | W30: =IFERROR(R30/T30,"-") -> -
B31: Miscellaneous expenses | C31: =SUMIFS(TB_Calicut[Apr],TB_Calicut[MIS_Group1],$B31)/10^5 -> -0.0003732 | D31: =SUMIFS(TB_Calicut[May],TB_Calicut[MIS_Group1],$B31)/10^5 -> 0.0588096 | E31: =SUMIFS(TB_Calicut[Jun],TB_Calicut[MIS_Group1],$B31)/10^5 -> -0.0002533 | F31: =SUMIFS(TB_Calicut[Jul],TB_Calicut[MIS_Group1],$B31)/10^5 -> 0.0743393 | G31: =SUMIFS(TB_Calicut[Aug],TB_Calicut[MIS_Group1],$B31)/10^5 -> 0.0259306 | H31: =SUMIFS(TB_Calicut[Sep],TB_Calicut[MIS_Group1],$B31)/10^5 -> 0.0588118 | I31: =SUMIFS(TB_Calicut[Oct],TB_Calicut[MIS_Group1],$B31)/10^5 -> 0.0025024 | J31: =SUMIFS(TB_Calicut[Nov],TB_Calicut[MIS_Group1],$B31)/10^5 -> 0.0100655 | K31: =SUMIFS(TB_Calicut[Dec],TB_Calicut[MIS_Group1],$B31)/10^5 -> 0.0103422 | L31: =SUMIFS(TB_Calicut[Jan],TB_Calicut[MIS_Group1],$B31)/10^5 -> 0.0050235 | M31: =SUMIFS(TB_Calicut[Feb],TB_Calicut[MIS_Group1],$B31)/10^5 -> 0.006738 | N31: =SUMIFS(TB_Calicut[Mar],TB_Calicut[MIS_Group1],$B31)/10^5 -> 0.0091652 | O31: =SUM(C31:N31) -> 0.2611016 | P31: 1.1279367 | R31: =SUMIFS(TB_Calicut[Apr_26],TB_Calicut[MIS_Group1],$B31)/10^5 -> -0.0005908 | S31: =SUMIFS(TB_Calicut!AB:AB,TB_Calicut!J:J,PL_Calicut!B31)/10^5 -> 0.0029801 | U31: =IFERROR(R31/C31-1,"-") -> 0.58306538 | V31: =IFERROR(R31/N31-1,"-") -> -1.0644612 | W31: =IFERROR(R31/T31,"-") -> -
B32: CSR Activity | C32: =SUMIFS(TB_Calicut[Apr],TB_Calicut[MIS_Group1],$B32)/10^5 -> 0 | D32: =SUMIFS(TB_Calicut[May],TB_Calicut[MIS_Group1],$B32)/10^5 -> 0 | E32: =SUMIFS(TB_Calicut[Jun],TB_Calicut[MIS_Group1],$B32)/10^5 -> 0 | F32: =SUMIFS(TB_Calicut[Jul],TB_Calicut[MIS_Group1],$B32)/10^5 -> 0 | G32: =SUMIFS(TB_Calicut[Aug],TB_Calicut[MIS_Group1],$B32)/10^5 -> 0 | H32: =SUMIFS(TB_Calicut[Sep],TB_Calicut[MIS_Group1],$B32)/10^5 -> 0 | I32: =SUMIFS(TB_Calicut[Oct],TB_Calicut[MIS_Group1],$B32)/10^5 -> 0 | J32: =SUMIFS(TB_Calicut[Nov],TB_Calicut[MIS_Group1],$B32)/10^5 -> 0 | K32: =SUMIFS(TB_Calicut[Dec],TB_Calicut[MIS_Group1],$B32)/10^5 -> 0 | L32: =SUMIFS(TB_Calicut[Jan],TB_Calicut[MIS_Group1],$B32)/10^5 -> 0 | M32: =SUMIFS(TB_Calicut[Feb],TB_Calicut[MIS_Group1],$B32)/10^5 -> 0 | N32: =SUMIFS(TB_Calicut[Mar],TB_Calicut[MIS_Group1],$B32)/10^5 -> 0 | O32: =SUM(C32:N32) -> 0 | R32: =SUMIFS(TB_Calicut[Apr_26],TB_Calicut[MIS_Group1],$B32)/10^5 -> 0 | S32: =SUMIFS(TB_Calicut!AB:AB,TB_Calicut!J:J,PL_Calicut!B32)/10^5 -> 0 | U32: =IFERROR(R32/C32-1,"-") -> - | V32: =IFERROR(R32/N32-1,"-") -> - | W32: =IFERROR(R32/T32,"-") -> -
B33: Total Expenses | C33: =SUM(C13:C32) -> 35.314938 | D33: =SUM(D13:D32) -> 39.401269 | E33: =SUM(E13:E32) -> 39.691506 | F33: =SUM(F13:F32) -> 45.259872 | G33: =SUM(G13:G32) -> 40.920805 | H33: =SUM(H13:H32) -> 44.960314 | I33: =SUM(I13:I32) -> 47.94203 | J33: =SUM(J13:J32) -> 45.312442 | ... S33: =SUM(S13:S32) -> 45.881173 | U33: =IFERROR(R33/C33-1,"-") -> 0.42037022 | V33: =IFERROR(R33/N33-1,"-") -> -0.0187021 | W33: =IFERROR(R33/T33,"-") -> -
U34: =IFERROR(R34/C34-1,"-") -> - | V34: =IFERROR(R34/N34-1,"-") -> - | W34: =IFERROR(R34/T34,"-") -> -
B35: EBITDA | C35: =C11-C33 -> -7.03533 | D35: =D11-D33 -> -16.332516 | E35: =E11-E33 -> -14.776145 | F35: =F11-F33 -> -14.081999 | G35: =G11-G33 -> -11.551214 | H35: =H11-H33 -> -12.894306 | I35: =I11-I33 -> -15.269072 | J35: =J11-J33 -> -16.772908 | ... S35: =S11-S33 -> -18.729499 | U35: =IFERROR(R35/C35-1,"-") -> 1.7846048 | V35: =IFERROR(R35/N35-1,"-") -> -0.083707775 | W35: =IFERROR(R35/T35,"-") -> -
B36: Depreciation | C36: 1.7730821 | D36: =((Depr.!$H$16/PL_Consol!$P$15)*$O$11)/12 -> 0.12818947 | E36: =((Depr.!$H$16/PL_Consol!$P$15)*$O$11)/12 -> 0.12818947 | F36: =((Depr.!$H$16/PL_Consol!$P$15)*$O$11)/12 -> 0.12818947 | G36: =((Depr.!$H$16/PL_Consol!$P$15)*$O$11)/12 -> 0.12818947 | H36: =((Depr.!$H$16/PL_Consol!$P$15)*$O$11)/12 -> 0.12818947 | I36: =((Depr.!$H$16/PL_Consol!$P$15)*$O$11)/12 -> 0.12818947 | J36: =((Depr.!$H$16/PL_Consol!$P$15)*$O$11)/12 -> 0.12818947 | K36: =((Depr.!$H$16/PL_Consol!$P$15)*$O$11)/12 -> 0.12818947 | ... M36: =((Depr.!$H$16/PL_Consol!$P$15)*$O$11)/12 -> 0.12818947 | N36: 1.7730821 | O36: =SUM(C36:N36) -> 4.828059 | P36: 130 | R36: =Depr.!$H$16/(PL_Kochi!$R$15+PL_Calicut!$R$11+PL_FNB!$R$9)*PL_Calicut!R11 -> 1.4101523 | S36: =Depr.!H16/PL_Consol!T15*PL_Calicut!S11 -> 1.2100156 | U36: =IFERROR(R36/C36-1,"-") -> -0.20468871 | V36: =IFERROR(R36/N36-1,"-") -> -0.20468871 | W36: =IFERROR(R36/T36,"-") -> -
B37: EBIT (Operational Profit) | C37: =C35-C36 -> -8.8084121 | D37: =D35-D36 -> -16.460705 | E37: =E35-E36 -> -14.904335 | F37: =F35-F36 -> -14.210189 | G37: =G35-G36 -> -11.679403 | H37: =H35-H36 -> -13.022495 | I37: =I35-I36 -> -15.397261 | J37: =J35-J36 -> -16.901097 | ... S37: =S35-S36 -> -19.939515 | U37: =IFERROR(R37/C37-1,"-") -> 1.3841716 | V37: =IFERROR(R37/N37-1,"-") -> -0.09297247 | W37: =IFERROR(R37/T37,"-") -> -
B38: Finance Cost | C38: =SUMIFS(TB_Calicut[Apr],TB_Calicut[MIS_Group1],$B38)/10^5 -> 0.0046362 | D38: =SUMIFS(TB_Calicut[May],TB_Calicut[MIS_Group1],$B38)/10^5 -> 0.0622942 | E38: =SUMIFS(TB_Calicut[Jun],TB_Calicut[MIS_Group1],$B38)/10^5 -> 0.0581054 | F38: =SUMIFS(TB_Calicut[Jul],TB_Calicut[MIS_Group1],$B38)/10^5 -> 0.0870964 | G38: =SUMIFS(TB_Calicut[Aug],TB_Calicut[MIS_Group1],$B38)/10^5 -> 0.0822476 | H38: =SUMIFS(TB_Calicut[Sep],TB_Calicut[MIS_Group1],$B38)/10^5 -> 0.0840737 | I38: =SUMIFS(TB_Calicut[Oct],TB_Calicut[MIS_Group1],$B38)/10^5 -> 0.0852621 | J38: =SUMIFS(TB_Calicut[Nov],TB_Calicut[MIS_Group1],$B38)/10^5 -> 0.1028739 | K38: =SUMIFS(TB_Calicut[Dec],TB_Calicut[MIS_Group1],$B38)/10^5 -> 0.0781365 | L38: =SUMIFS(TB_Calicut[Jan],TB_Calicut[MIS_Group1],$B38)/10^5 -> 0.0794621 | M38: =SUMIFS(TB_Calicut[Feb],TB_Calicut[MIS_Group1],$B38)/10^5 -> 0.0984125 | N38: =SUMIFS(TB_Calicut[Mar],TB_Calicut[MIS_Group1],$B38)/10^5 -> 0.1301486 | O38: =SUM(C38:N38) -> 0.9527492 | P38: 0 | R38: =SUMIFS(TB_Calicut[Apr_26],TB_Calicut[MIS_Group1],$B38)/10^5 -> 0.0529163 | S38: =SUMIFS(TB_Calicut[Apr_26],TB_Calicut[MIS_Group1],$B38)/10^5 -> 0.0529163 | U38: =IFERROR(R38/C38-1,"-") -> 10.413722 | V38: =IFERROR(R38/N38-1,"-") -> -0.59341629 | W38: =IFERROR(R38/T38,"-") -> -
B39: PBT | C39: =C37-C38 -> -8.8130483 | D39: =D37-D38 -> -16.522999 | E39: =E37-E38 -> -14.96244 | F39: =F37-F38 -> -14.297285 | G39: =G37-G38 -> -11.761651 | H39: =H37-H38 -> -13.106569 | I39: =I37-I38 -> -15.482523 | J39: =J37-J38 -> -17.003971 | ... S39: =S37-S38 -> -19.992431 | U39: =IFERROR(R39/C39-1,"-") -> 1.3889217 | V39: =IFERROR(R39/N39-1,"-") -> -0.095769813 | W39: =IFERROR(R39/T39,"-") -> -
B40: Tax | C40: =IF(C39>0,C39*PL_Consol!$R$44/PL_Consol!$R$43,0) -> 0 | D40: =IF(D39>0,D39*PL_Consol!$R$44/PL_Consol!$R$43,0) -> 0 | E40: =IF(E39>0,E39*PL_Consol!$R$44/PL_Consol!$R$43,0) -> 0 | F40: =IF(F39>0,F39*PL_Consol!$R$44/PL_Consol!$R$43,0) -> 0 | G40: =IF(G39>0,G39*PL_Consol!$R$44/PL_Consol!$R$43,0) -> 0 | H40: =IF(H39>0,H39*PL_Consol!$R$44/PL_Consol!$R$43,0) -> 0 | I40: =IF(I39>0,I39*PL_Consol!$R$44/PL_Consol!$R$43,0) -> 0 | J40: =IF(J39>0,J39*PL_Consol!$R$44/PL_Consol!$R$43,0) -> 0 | ... N40: =IF(N39>0,N39*PL_Consol!$R$44/PL_Consol!$R$43,0) -> 0 | O40: =SUM(C40:N40) -> 0 | P40: =IF(P39>0,P39*PL_Consol!$R$44/PL_Consol!$R$43,0) -> 0 | Q40: =SUMIFS(TB_Calicut[Mar],TB_Calicut[MIS_Group1],$B40)/10^5 -> 0 | R40: =IF(R39>0,R39*PL_Consol!$R$44/PL_Consol!$R$43,0) -> 0 | S40: =IF(S39>0,S39*PL_Consol!$R$44/PL_Consol!$R$43,0) -> 0 | U40: =IFERROR(R40/C40-1,"-") -> - | V40: =IFERROR(R40/N40-1,"-") -> - | W40: =IFERROR(R40/T40,"-") -> -
B41: PAT | C41: =C39-C40 -> -8.8130483 | D41: =D39-D40 -> -16.522999 | E41: =E39-E40 -> -14.96244 | F41: =F39-F40 -> -14.297285 | G41: =G39-G40 -> -11.761651 | H41: =H39-H40 -> -13.106569 | I41: =I39-I40 -> -15.482523 | J41: =J39-J40 -> -17.003971 | ... S41: =S39-S40 -> -19.992431 | U41: =IFERROR(R41/C41-1,"-") -> 1.3889217 | V41: =IFERROR(R41/N41-1,"-") -> -0.095769813 | W41: =IFERROR(R41/T41,"-") -> -
B47: Common Size Statement
T48: Bud
B49: Particulars | C49: 45748 | D49: 45778 | E49: 45809 | F49: 45839 | G49: 45870 | H49: 45901 | I49: 45931 | J49: 45962 | K49: 45992 | L49: 46023 | M49: 46054 | N49: 46082 | O49: YTD | P49: Bud | Q49: FY25 | R49: 46113 | T49: 46113
B50: Revenue
B51: OP Revenue | C51: =IFERROR(C7/C$11,0) -> 0.42099982 | D51: =IFERROR(D7/D$11,0) -> 0.38688393 | E51: =IFERROR(E7/E$11,0) -> 0.39855573 | F51: =IFERROR(F7/F$11,0) -> 0.39967223 | G51: =IFERROR(G7/G$11,0) -> 0.42765853 | H51: =IFERROR(H7/H$11,0) -> 0.3920077 | I51: =IFERROR(I7/I$11,0) -> 0.36358658 | J51: =IFERROR(J7/J$11,0) -> 0.36640331 | ... R51: =IFERROR(R7/R$11,0) -> 0.29962882 | T51: =IFERROR(T7/T$11,0) -> 0
B52: OP Pharmacy | C52: =IFERROR(C8/C$11,0) -> 0.57900018 | D52: =IFERROR(D8/D$11,0) -> 0.61311607 | E52: =IFERROR(E8/E$11,0) -> 0.60144427 | F52: =IFERROR(F8/F$11,0) -> 0.57880321 | G52: =IFERROR(G8/G$11,0) -> 0.5684851 | H52: =IFERROR(H8/H$11,0) -> 0.60441811 | I52: =IFERROR(I8/I$11,0) -> 0.63266139 | J52: =IFERROR(J8/J$11,0) -> 0.62888638 | ... R52: =IFERROR(R8/R$11,0) -> 0.6981703 | T52: =IFERROR(T8/T$11,0) -> 0
B53: Revenue From Operation | C53: =IFERROR(C9/C$11,0) -> 1 | D53: =IFERROR(D9/D$11,0) -> 1 | E53: =IFERROR(E9/E$11,0) -> 1 | F53: =IFERROR(F9/F$11,0) -> 0.97847544 | G53: =IFERROR(G9/G$11,0) -> 0.99614363 | H53: =IFERROR(H9/H$11,0) -> 0.99642581 | I53: =IFERROR(I9/I$11,0) -> 0.99624797 | J53: =IFERROR(J9/J$11,0) -> 0.99528969 | ... R53: =IFERROR(R9/R$11,0) -> 0.99779913 | T53: =IFERROR(T9/T$11,0) -> 0
B54: Other Income | C54: =IFERROR(C10/C$11,0) -> 0 | D54: =IFERROR(D10/D$11,0) -> 0 | E54: =IFERROR(E10/E$11,0) -> 0 | F54: =IFERROR(F10/F$11,0) -> 0.02152456 | G54: =IFERROR(G10/G$11,0) -> 0.0038563697 | H54: =IFERROR(H10/H$11,0) -> 0.0035741898 | I54: =IFERROR(I10/I$11,0) -> 0.0037520325 | J54: =IFERROR(J10/J$11,0) -> 0.004710308 | ... R54: =IFERROR(R10/R$11,0) -> 0.0022008741 | T54: =IFERROR(T10/T$11,0) -> 0
B55: Total Revenue | C55: =IFERROR(C11/C$11,0) -> 1 | D55: =IFERROR(D11/D$11,0) -> 1 | E55: =IFERROR(E11/E$11,0) -> 1 | F55: =IFERROR(F11/F$11,0) -> 1 | G55: =IFERROR(G11/G$11,0) -> 1 | H55: =IFERROR(H11/H$11,0) -> 1 | I55: =IFERROR(I11/I$11,0) -> 1 | J55: =IFERROR(J11/J$11,0) -> 1 | ... R55: =IFERROR(R11/R$11,0) -> 1 | T55: =IFERROR(T11/T$11,0) -> 0
C56: =IFERROR(C12/C$11,0) -> 0 | D56: =IFERROR(D12/D$11,0) -> 0 | E56: =IFERROR(E12/E$11,0) -> 0 | F56: =IFERROR(F12/F$11,0) -> 0 | G56: =IFERROR(G12/G$11,0) -> 0 | H56: =IFERROR(H12/H$11,0) -> 0 | I56: =IFERROR(I12/I$11,0) -> 0 | J56: =IFERROR(J12/J$11,0) -> 0 | ... R56: =IFERROR(R12/R$11,0) -> 0 | T56: =IFERROR(T12/T$11,0) -> 0
B57: Material Cost | C57: =IFERROR(C13/C$11,0) -> 0.25958888 | D57: =IFERROR(D13/D$11,0) -> 0.44509602 | E57: =IFERROR(E13/E$11,0) -> 0.42075648 | F57: =IFERROR(F13/F$11,0) -> 0.41436708 | G57: =IFERROR(G13/G$11,0) -> 0.35971774 | H57: =IFERROR(H13/H$11,0) -> 0.41571398 | I57: =IFERROR(I13/I$11,0) -> 0.4796376 | J57: =IFERROR(J13/J$11,0) -> 0.45152846 | ... R57: =IFERROR(R13/R$11,0) -> 0.51232574 | T57: =IFERROR(T13/T$11,0) -> 0
B58: Doctor Cost | C58: =IFERROR(C14/C$11,0) -> 0.36881452 | D58: =IFERROR(D14/D$11,0) -> 0.4487412 | E58: =IFERROR(E14/E$11,0) -> 0.39814796 | F58: =IFERROR(F14/F$11,0) -> 0.37993516 | G58: =IFERROR(G14/G$11,0) -> 0.39071024 | H58: =IFERROR(H14/H$11,0) -> 0.36926018 | I58: =IFERROR(I14/I$11,0) -> 0.34249424 | J58: =IFERROR(J14/J$11,0) -> 0.37420722 | ... R58: =IFERROR(R14/R$11,0) -> 0.34550372 | T58: =IFERROR(T14/T$11,0) -> 0
B59: Employee Cost | C59: =IFERROR(C15/C$11,0) -> 0.18554815 | D59: =IFERROR(D15/D$11,0) -> 0.25640566 | E59: =IFERROR(E15/E$11,0) -> 0.23603627 | F59: =IFERROR(F15/F$11,0) -> 0.19492507 | G59: =IFERROR(G15/G$11,0) -> 0.20641993 | H59: =IFERROR(H15/H$11,0) -> 0.1859804 | I59: =IFERROR(I15/I$11,0) -> 0.20299934 | J59: =IFERROR(J15/J$11,0) -> 0.21394739 | ... R59: =IFERROR(R15/R$11,0) -> 0.20446045 | T59: =IFERROR(T15/T$11,0) -> 0
B60: Lab Test Charges | C60: =IFERROR(C16/C$11,0) -> 0 | D60: =IFERROR(D16/D$11,0) -> 0 | E60: =IFERROR(E16/E$11,0) -> 0 | F60: =IFERROR(F16/F$11,0) -> 0 | G60: =IFERROR(G16/G$11,0) -> 0 | H60: =IFERROR(H16/H$11,0) -> 0 | I60: =IFERROR(I16/I$11,0) -> 0 | J60: =IFERROR(J16/J$11,0) -> 0 | ... R60: =IFERROR(R16/R$11,0) -> 0.00049068239 | T60: =IFERROR(T16/T$11,0) -> 0
B61: Utilities-Power, fuel & water charges | C61: =IFERROR(C17/C$11,0) -> 0.055096956 | D61: =IFERROR(D17/D$11,0) -> 0.069684303 | E61: =IFERROR(E17/E$11,0) -> 0.051823793 | F61: =IFERROR(F17/F$11,0) -> 0.048866066 | G61: =IFERROR(G17/G$11,0) -> 0.047755857 | H61: =IFERROR(H17/H$11,0) -> 0.044607985 | I61: =IFERROR(I17/I$11,0) -> 0.047045327 | J61: =IFERROR(J17/J$11,0) -> 0.05344221 | ... R61: =IFERROR(R17/R$11,0) -> 0.052277318 | T61: =IFERROR(T17/T$11,0) -> 0
B62: Rent Paid | C62: =IFERROR(C18/C$11,0) -> 0.32782173 | D62: =IFERROR(D18/D$11,0) -> 0.40187131 | E62: =IFERROR(E18/E$11,0) -> 0.37208652 | F62: =IFERROR(F18/F$11,0) -> 0.29747603 | G62: =IFERROR(G18/G$11,0) -> 0.3172625 | H62: =IFERROR(H18/H$11,0) -> 0.29058404 | I62: =IFERROR(I18/I$11,0) -> 0.30615212 | J62: =IFERROR(J18/J$11,0) -> 0.37149437 | ... R62: =IFERROR(R18/R$11,0) -> 0.34682336 | T62: =IFERROR(T18/T$11,0) -> 0
B63: Repair & Maintenance | C63: =IFERROR(C19/C$11,0) -> 0 | D63: =IFERROR(D19/D$11,0) -> 0.0046404762 | E63: =IFERROR(E19/E$11,0) -> 0.051159805 | F63: =IFERROR(F19/F$11,0) -> 0.031573995 | G63: =IFERROR(G19/G$11,0) -> 0.0046915873 | H63: =IFERROR(H19/H$11,0) -> 0.0099086235 | I63: =IFERROR(I19/I$11,0) -> 0.010433399 | J63: =IFERROR(J19/J$11,0) -> 0.049763015 | ... R63: =IFERROR(R19/R$11,0) -> 0.10204176 | T63: =IFERROR(T19/T$11,0) -> 0
B64: House Keeping Expenses | C64: =IFERROR(C20/C$11,0) -> 0.031600862 | D64: =IFERROR(D20/D$11,0) -> 0.042838032 | E64: =IFERROR(E20/E$11,0) -> 0.03454656 | F64: =IFERROR(F20/F$11,0) -> 0.036939659 | G64: =IFERROR(G20/G$11,0) -> 0.038348249 | H64: =IFERROR(H20/H$11,0) -> 0.030899886 | I64: =IFERROR(I20/I$11,0) -> 0.031149185 | J64: =IFERROR(J20/J$11,0) -> 0.034823483 | ... R64: =IFERROR(R20/R$11,0) -> 0.02591261 | T64: =IFERROR(T20/T$11,0) -> 0
B65: Security Expenses | C65: =IFERROR(C21/C$11,0) -> 0.012820546 | D65: =IFERROR(D21/D$11,0) -> 0.015716497 | E65: =IFERROR(E21/E$11,0) -> 0.014551666 | F65: =IFERROR(F21/F$11,0) -> 0.01162876 | G65: =IFERROR(G21/G$11,0) -> 0.0069687726 | H65: =IFERROR(H21/H$11,0) -> 0.01130674 | I65: =IFERROR(I21/I$11,0) -> 0.0110967 | J65: =IFERROR(J21/J$11,0) -> 0.012703851 | ... R65: =IFERROR(R21/R$11,0) -> 0.02002115 | T65: =IFERROR(T21/T$11,0) -> 0
B66: Printing & Stationery | C66: =IFERROR(C22/C$11,0) -> 0 | D66: =IFERROR(D22/D$11,0) -> 0.0041324296 | E66: =IFERROR(E22/E$11,0) -> 0.0017459109 | F66: =IFERROR(F22/F$11,0) -> 0.0080707879 | G66: =IFERROR(G22/G$11,0) -> 0.0041883457 | H66: =IFERROR(H22/H$11,0) -> 0 | I66: =IFERROR(I22/I$11,0) -> 0.013689608 | J66: =IFERROR(J22/J$11,0) -> 0.0022333931 | ... R66: =IFERROR(R22/R$11,0) -> 0 | T66: =IFERROR(T22/T$11,0) -> 0
B67: Insurance | C67: =IFERROR(C23/C$11,0) -> 0.0052076394 | D67: =IFERROR(D23/D$11,0) -> 0 | E67: =IFERROR(E23/E$11,0) -> 0.0062888914 | F67: =IFERROR(F23/F$11,0) -> 0 | G67: =IFERROR(G23/G$11,0) -> 0 | H67: =IFERROR(H23/H$11,0) -> 0.02415954 | I67: =IFERROR(I23/I$11,0) -> 0.00061804321 | J67: =IFERROR(J23/J$11,0) -> 0.0010336539 | ... R67: =IFERROR(R23/R$11,0) -> 0.002437383 | T67: =IFERROR(T23/T$11,0) -> 0
B68: Rates & taxes | C68: =IFERROR(C24/C$11,0) -> 0.0022914038 | D68: =IFERROR(D24/D$11,0) -> 0.00014001624 | E68: =IFERROR(E24/E$11,0) -> 0.0023795561 | F68: =IFERROR(F24/F$11,0) -> 7.3770267e-06 | G68: =IFERROR(G24/G$11,0) -> 6.8097646e-05 | H68: =IFERROR(H24/H$11,0) -> 0.0018489205 | I68: =IFERROR(I24/I$11,0) -> 0.000604858 | J68: =IFERROR(J24/J$11,0) -> 0.00069246048 | ... R68: =IFERROR(R24/R$11,0) -> 0.0080067099 | T68: =IFERROR(T24/T$11,0) -> 0
... B77: Total Expenses | C77: =IFERROR(C33/C$11,0) -> 1.2487775 | D77: =IFERROR(D33/D$11,0) -> 1.707993 | E77: =IFERROR(E33/E$11,0) -> 1.5930536 | F77: =IFERROR(F33/F$11,0) -> 1.4516665 | G77: =IFERROR(G33/G$11,0) -> 1.3933052 | H77: =IFERROR(H33/H$11,0) -> 1.4021176 | I77: =IFERROR(I33/I$11,0) -> 1.4673306 | J77: =IFERROR(J33/J$11,0) -> 1.5877078 | ... R77: =IFERROR(R33/R$11,0) -> 1.6408513 | T77: =IFERROR(T33/T$11,0) -> 0
C78: =IFERROR(C34/C$11,0) -> 0 | D78: =IFERROR(D34/D$11,0) -> 0 | E78: =IFERROR(E34/E$11,0) -> 0 | F78: =IFERROR(F34/F$11,0) -> 0 | G78: =IFERROR(G34/G$11,0) -> 0 | H78: =IFERROR(H34/H$11,0) -> 0 | I78: =IFERROR(I34/I$11,0) -> 0 | J78: =IFERROR(J34/J$11,0) -> 0 | ... R78: =IFERROR(R34/R$11,0) -> 0 | T78: =IFERROR(T34/T$11,0) -> 0
B79: EBITDA | C79: =IFERROR(C35/C$11,0) -> -0.24877749 | D79: =IFERROR(D35/D$11,0) -> -0.70799299 | E79: =IFERROR(E35/E$11,0) -> -0.59305363 | F79: =IFERROR(F35/F$11,0) -> -0.45166646 | G79: =IFERROR(G35/G$11,0) -> -0.39330523 | H79: =IFERROR(H35/H$11,0) -> -0.40211759 | I79: =IFERROR(I35/I$11,0) -> -0.46733056 | J79: =IFERROR(J35/J$11,0) -> -0.58770782 | ... R79: =IFERROR(R35/R$11,0) -> -0.64085128 | T79: =IFERROR(T35/T$11,0) -> 0
B80: Depreciation | C80: =IFERROR(C36/C$11,0) -> 0.062698258 | D80: =IFERROR(D36/D$11,0) -> 0.0055568442 | E80: =IFERROR(E36/E$11,0) -> 0.0051449974 | F80: =IFERROR(F36/F$11,0) -> 0.0041115527 | G80: =IFERROR(G36/G$11,0) -> 0.0043647005 | H80: =IFERROR(H36/H$11,0) -> 0.0039976747 | I80: =IFERROR(I36/I$11,0) -> 0.0039234118 | J80: =IFERROR(J36/J$11,0) -> 0.0044916453 | ... R80: =IFERROR(R36/R$11,0) -> 0.046129125 | T80: =IFERROR(T36/T$11,0) -> 0
B81: EBIT (Operational Profit) | C81: =IFERROR(C37/C$11,0) -> -0.31147575 | D81: =IFERROR(D37/D$11,0) -> -0.71354983 | E81: =IFERROR(E37/E$11,0) -> -0.59819863 | F81: =IFERROR(F37/F$11,0) -> -0.45577801 | G81: =IFERROR(G37/G$11,0) -> -0.39766994 | H81: =IFERROR(H37/H$11,0) -> -0.40611527 | I81: =IFERROR(I37/I$11,0) -> -0.47125397 | J81: =IFERROR(J37/J$11,0) -> -0.59219947 | ... R81: =IFERROR(R37/R$11,0) -> -0.68698041 | T81: =IFERROR(T37/T$11,0) -> 0
B82: Finance Cost | C82: =IFERROR(C38/C$11,0) -> 0.00016394145 | D82: =IFERROR(D38/D$11,0) -> 0.0027003713 | E82: =IFERROR(E38/E$11,0) -> 0.0023321115 | F82: =IFERROR(F38/F$11,0) -> 0.0027935325 | G82: =IFERROR(G38/G$11,0) -> 0.002800434 | H82: =IFERROR(H38/H$11,0) -> 0.0026218948 | I82: =IFERROR(I38/I$11,0) -> 0.0026095617 | J82: =IFERROR(J38/J$11,0) -> 0.0036046103 | ... R82: =IFERROR(R38/R$11,0) -> 0.0017310064 | T82: =IFERROR(T38/T$11,0) -> 0
B83: PBT | C83: =IFERROR(C39/C$11,0) -> -0.31163969 | D83: =IFERROR(D39/D$11,0) -> -0.7162502 | E83: =IFERROR(E39/E$11,0) -> -0.60053074 | F83: =IFERROR(F39/F$11,0) -> -0.45857154 | G83: =IFERROR(G39/G$11,0) -> -0.40047037 | H83: =IFERROR(H39/H$11,0) -> -0.40873716 | I83: =IFERROR(I39/I$11,0) -> -0.47386354 | J83: =IFERROR(J39/J$11,0) -> -0.59580408 | ... R83: =IFERROR(R39/R$11,0) -> -0.68871142 | T83: =IFERROR(T39/T$11,0) -> 0
B84: Tax | C84: =IFERROR(C40/C$11,0) -> 0 | D84: =IFERROR(D40/D$11,0) -> 0 | E84: =IFERROR(E40/E$11,0) -> 0 | F84: =IFERROR(F40/F$11,0) -> 0 | G84: =IFERROR(G40/G$11,0) -> 0 | H84: =IFERROR(H40/H$11,0) -> 0 | I84: =IFERROR(I40/I$11,0) -> 0 | J84: =IFERROR(J40/J$11,0) -> 0 | ... R84: =IFERROR(R40/R$11,0) -> 0 | T84: =IFERROR(T40/T$11,0) -> 0
B85: PAT | C85: =IFERROR(C41/C$11,0) -> -0.31163969 | D85: =IFERROR(D41/D$11,0) -> -0.7162502 | E85: =IFERROR(E41/E$11,0) -> -0.60053074 | F85: =IFERROR(F41/F$11,0) -> -0.45857154 | G85: =IFERROR(G41/G$11,0) -> -0.40047037 | H85: =IFERROR(H41/H$11,0) -> -0.40873716 | I85: =IFERROR(I41/I$11,0) -> -0.47386354 | J85: =IFERROR(J41/J$11,0) -> -0.59580408 | ... R85: =IFERROR(R41/R$11,0) -> -0.68871142 | T85: =IFERROR(T41/T$11,0) -> 0

Sheet PL_FNB
B1: LAKESHORE - FOOD AND BEVERAGE
B2: Profit and Loss Statement (Amount in Lakhs) | E2: (Amount in Lakhs)
C4: SMLY | N4: PM | R4: PM | S4: CM | T4: Budget | U4: Growth & Ach %
B5: Particulars | C5: 45748 | D5: 45778 | E5: 45809 | F5: 45839 | G5: 45870 | H5: 45901 | I5: 45931 | J5: 45962 | K5: 45992 | L5: 46023 | M5: 46054 | N5: 46082 | O5: YTD | P5: Bud | Q5: FY25 | R5: 46113 | S5: 46143 | T5: 46113 | U5: YOY Gr. | V5: MOM Gr. | W5: BUD Ach.
B6: Revenue
B7: F & B Revenue | C7: =-SUMIFS(TB_FNB[Apr],TB_FNB[MIS_Group1],$B7)/10^5 -> 133.45512 | D7: =-SUMIFS(TB_FNB[May],TB_FNB[MIS_Group1],$B7)/10^5 -> 141.66725 | E7: =-SUMIFS(TB_FNB[Jun],TB_FNB[MIS_Group1],$B7)/10^5 -> 131.13537 | F7: =-SUMIFS(TB_FNB[Jul],TB_FNB[MIS_Group1],$B7)/10^5 -> 153.33094 | G7: =-SUMIFS(TB_FNB[Aug],TB_FNB[MIS_Group1],$B7)/10^5 -> 152.96558 | H7: =-SUMIFS(TB_FNB[Sep],TB_FNB[MIS_Group1],$B7)/10^5 -> 147.75529 | I7: =-SUMIFS(TB_FNB[Oct],TB_FNB[MIS_Group1],$B7)/10^5 -> 146.87833 | J7: =-SUMIFS(TB_FNB[Nov],TB_FNB[MIS_Group1],$B7)/10^5 -> 137.58937 | K7: =-SUMIFS(TB_FNB[Dec],TB_FNB[MIS_Group1],$B7)/10^5 -> 141.79663 | L7: =-SUMIFS(TB_FNB[Jan],TB_FNB[MIS_Group1],$B7)/10^5 -> 155.47462 | M7: =-SUMIFS(TB_FNB[Feb],TB_FNB[MIS_Group1],$B7)/10^5 -> 142.10076 | N7: =-SUMIFS(TB_FNB[Mar],TB_FNB[MIS_Group1],$B7)/10^5 -> 134.02744 | O7: =SUM(C7:N7) -> 1718.1767 | P7: 1848.3621 | R7: =-SUMIFS(TB_FNB[Apr_26],TB_FNB[MIS_Group1],$B7)/10^5 -> 156.02992 | S7: =-SUMIFS(TB_FNB!AA:AA,TB_FNB!J:J,PL_FNB!B7)/10^5 -> 167.08431 | U7: =IFERROR(R7/C7-1,"-") -> 0.16915651 | V7: =IFERROR(R7/N7-1,"-") -> 0.16416404 | W7: =IFERROR(R7/T7,"-") -> -
B8: Other Income | C8: =-SUMIFS(TB_FNB[Apr],TB_FNB[MIS_Group1],$B8)/10^5 -> 0 | D8: =-SUMIFS(TB_FNB[May],TB_FNB[MIS_Group1],$B8)/10^5 -> 0 | E8: =-SUMIFS(TB_FNB[Jun],TB_FNB[MIS_Group1],$B8)/10^5 -> 0.11656 | F8: =-SUMIFS(TB_FNB[Jul],TB_FNB[MIS_Group1],$B8)/10^5 -> 0.05678 | G8: =-SUMIFS(TB_FNB[Aug],TB_FNB[MIS_Group1],$B8)/10^5 -> 0 | H8: =-SUMIFS(TB_FNB[Sep],TB_FNB[MIS_Group1],$B8)/10^5 -> 0.17786 | I8: =-SUMIFS(TB_FNB[Oct],TB_FNB[MIS_Group1],$B8)/10^5 -> 0 | J8: =-SUMIFS(TB_FNB[Nov],TB_FNB[MIS_Group1],$B8)/10^5 -> 0.08712 | K8: =-SUMIFS(TB_FNB[Dec],TB_FNB[MIS_Group1],$B8)/10^5 -> 0 | L8: =-SUMIFS(TB_FNB[Jan],TB_FNB[MIS_Group1],$B8)/10^5 -> 0.0983 | M8: =-SUMIFS(TB_FNB[Feb],TB_FNB[MIS_Group1],$B8)/10^5 -> 0 | N8: =-SUMIFS(TB_FNB[Mar],TB_FNB[MIS_Group1],$B8)/10^5 -> 0.0878 | O8: =SUM(C8:N8) -> 0.62442 | P8: 4.9413574 | R8: =-SUMIFS(TB_FNB[Apr_26],TB_FNB[MIS_Group1],$B8)/10^5 -> 0 | S8: =-SUMIFS(TB_FNB!AA:AA,TB_FNB!J:J,PL_FNB!B8)/10^5 -> 0.09297 | U8: =IFERROR(R8/C8-1,"-") -> - | V8: =IFERROR(R8/N8-1,"-") -> -1 | W8: =IFERROR(R8/T8,"-") -> -
B9: Total Revenue | C9: =SUM(C7:C8) -> 133.45512 | D9: =SUM(D7:D8) -> 141.66725 | E9: =SUM(E7:E8) -> 131.25193 | F9: =SUM(F7:F8) -> 153.38772 | G9: =SUM(G7:G8) -> 152.96558 | H9: =SUM(H7:H8) -> 147.93315 | I9: =SUM(I7:I8) -> 146.87833 | J9: =SUM(J7:J8) -> 137.67649 | ... S9: =SUM(S7:S8) -> 167.17728 | U9: =IFERROR(R9/C9-1,"-") -> 0.16915651 | V9: =IFERROR(R9/N9-1,"-") -> 0.16340191 | W9: =IFERROR(R9/T9,"-") -> -
