Workbook

Sheet Assumptions
A3: When revenue is projected only variable kept is OP count, rest OP to IP conversion, ARPP-op, ARPP-IP all kept constant
A4: The opex - one time and recurring are only evaluated.
A5: The capex are mentioned but need an independent evaluation and it will be useful to determine cash flow
A10: Bequip Comments
A11: Bringing in new age specialities
A12: Improving OP to IP conversion
J13: {=+_xlfn.UNIQUE('Initiative Register'!C:C)} -> 0
J14: Initiative ID
J15: R-01 | K15: =+SUMIFS('Initiative Register'!AA:AA,'Initiative Register'!C:C,Assumptions!J15) -> 0
J16: R-02 | K16: =+SUMIFS('Initiative Register'!AA:AA,'Initiative Register'!C:C,Assumptions!J16) -> 2.335
J17: R-03 | K17: =+SUMIFS('Initiative Register'!AA:AA,'Initiative Register'!C:C,Assumptions!J17) -> 0
J18: R-04 | K18: =+SUMIFS('Initiative Register'!AA:AA,'Initiative Register'!C:C,Assumptions!J18) -> 0
J19: R-05 | K19: =+SUMIFS('Initiative Register'!AA:AA,'Initiative Register'!C:C,Assumptions!J19) -> 0
J20: R-06 | K20: =+SUMIFS('Initiative Register'!AA:AA,'Initiative Register'!C:C,Assumptions!J20) -> 0
J21: R-07 | K21: =+SUMIFS('Initiative Register'!AA:AA,'Initiative Register'!C:C,Assumptions!J21) -> 0
J22: R-08 | K22: =+SUMIFS('Initiative Register'!AA:AA,'Initiative Register'!C:C,Assumptions!J22) -> 0
J23: R-09 | K23: =+SUMIFS('Initiative Register'!AA:AA,'Initiative Register'!C:C,Assumptions!J23) -> 0
J24: R-10 | K24: =+SUMIFS('Initiative Register'!AA:AA,'Initiative Register'!C:C,Assumptions!J24) -> 425.09111
J25: R-11 | K25: =+SUMIFS('Initiative Register'!AA:AA,'Initiative Register'!C:C,Assumptions!J25) -> 42.822427
J26: R-12 | K26: =+SUMIFS('Initiative Register'!AA:AA,'Initiative Register'!C:C,Assumptions!J26) -> 0
... J49: Cost New 1 | K49: =+SUMIFS('Initiative Register'!AA:AA,'Initiative Register'!C:C,Assumptions!J49) -> 61.800787
K50: =+SUMIFS('Initiative Register'!AA:AA,'Initiative Register'!C:C,Assumptions!J50) -> 0

Sheet Initiative Register
K1: =+K3-K5 -> 0 | L1: =+L3-L5 -> 0 | AA1: =+M3-M4 -> 115.09
A2: VPS LAKESHORE HOSPITAL — AOP INITIATIVE REGISTER | FY 2026–27 | 33 Initiatives | K2: =+K4-K6 -> 0 | L2: =+L4-L6 -> 0 | AA2: =+AA1-AA3 -> -472.47104
K3: 1087.5 | L3: 109 | M3: 125.6 | O3: =SUM(O8:O460) -> 39.572417 | P3: =SUM(P8:P460) -> 40.54019 | Q3: =SUM(Q8:Q460) -> 41.303689 | R3: =SUM(R8:R460) -> 48.384232 | S3: =SUM(S8:S460) -> 47.846026 | T3: =SUM(T8:T460) -> 49.017426 | U3: =SUM(U8:U460) -> 52.021551 | V3: =SUM(V8:V460) -> 49.829776 | ... AA3: =SUM(AA8:AA460) -> 587.56104
L4: 100 | M4: 10.51
A5: TOTAL REVENUE IMPACT | G5: Sum of 15 revenue initiatives (R-01 to R-15) — opex, capex, and revenue impact | K5: =SUM(K8:K26) -> 1087.5 | L5: =SUM(L8:L26) -> 109 | M5: =SUM(M8:M26) -> 125.6
A6: TOTAL COST SAVING | G6: Sum of 13 cost initiatives (C-01 to C-13) — opex, capex, and cost saving | L6: =SUM(L28:L40) -> 100 | M6: =SUM(M28:M40) -> 10.51 | O6: All Rs. In Crores
A7: Type | B7: # | C7: Initiative ID | D7: Sub Initiative | E7: Initiative Name | F7: Category | G7: Description | H7: Start Month | I7: Est. Cost | J7: Est. Cost Detailed | K7: Opex (₹L/yr) | L7: Capex (₹L) | M7: Est. Impact (₹ Cr) | N7: P&L Head to Link | O7: 46113 | P7: 46143 | Q7: 46174 | R7: 46204 | S7: 46235 | T7: 46266 | U7: 46296 | V7: 46327 | W7: 46357 | X7: 46388 | Y7: 46419 | Z7: 46447 | AA7: Total
A8: REVENUE — PRICING & YIELD | B8: 1 | C8: R-01 | E8: Annual Rate Revision Policy | F8: Revenue — Pricing & Yield | G8: Revise all IP room, nursing, and procedure rates for cash/self-pay patients effective May-26. Room & nursing tariffs benchmarked against Aster, Welcare, Rajagiri, and Sunrise across 19 bed categories (avg increase ~12%). Top 50 revenue procedures repriced to midpoint of Lakeshore and highest competitor rate. TPA/insurer tariff renegotiation under R-03. | H8: 46113 | I8: Nil — internal process; CFO time only | K8: 0 | L8: 0 | M8: 9.6 | AA8: =SUM(O8:Z8) -> 0
A9: REVENUE — PRICING & YIELD | B9: 2 | C9: R-02 | D9: 1 | E9: Procedure Contribution Framework | F9: Revenue — Pricing & Yield | G9: Launch a contribution framework for all IP procedures. Cost out top 50 procedures by revenue — include doctor fees, team costs, consumables, and overhead allocation. Identify low-contribution procedures (<50% margin). Reprice for both cash AND insurance. Flag insurer tariff renegotiation list. Build sustainable contribution model: target 58% average contribution for 26% EBITDA. | H9: 46113 | I9: ₹1.5L one-time (costing consultant or internal CFO + pharmacy time) | K9: 1.5 | L9: 0 | M9: 2.5 | O9: =+'R-02'!E4/10^7 -> 0 | P9: =+'R-02'!F4/10^7 -> 0 | Q9: =+'R-02'!G4/10^7 -> 0 | R9: =+'R-02'!H4/10^7 -> 0.075 | S9: =+'R-02'!I4/10^7 -> 0.125 | T9: =+'R-02'!J4/10^7 -> 0.175 | U9: =+'R-02'!K4/10^7 -> 0.225 | V9: =+'R-02'!L4/10^7 -> 0.275 | ... Z9: =+'R-02'!P4/10^7 -> 0.5 | AA9: =SUM(O9:Z9) -> 2.5
A10: REVENUE — PRICING & YIELD | B10: 2 | C10: R-02 | D10: 2 | E10: Procedure Contribution Framework | F10: Revenue — Pricing & Yield | G10: Launch a contribution framework for all IP procedures. Cost out top 50 procedures by revenue — include doctor fees, team costs, consumables, and overhead allocation. Identify low-contribution procedures (<50% margin). Reprice for both cash AND insurance. Flag insurer tariff renegotiation list. Build sustainable contribution model: target 58% average contribution for 26% EBITDA. | H10: 46113 | O10: =+'R-02'!E6/10^7 -> 0 | P10: =-+'R-02'!F6/10^7 -> -0.015 | Q10: =-+'R-02'!G6/10^7 -> -0.015 | R10: =-+'R-02'!H6/10^7 -> -0.015 | S10: =-+'R-02'!I6/10^7 -> -0.015 | T10: =-+'R-02'!J6/10^7 -> -0.015 | U10: =-+'R-02'!K6/10^7 -> -0.015 | V10: =-+'R-02'!L6/10^7 -> -0.015 | W10: =-+'R-02'!M6/10^7 -> -0.015 | ... Z10: =-+'R-02'!P6/10^7 -> -0.015 | AA10: =SUM(O10:Z10) -> -0.165
A11: REVENUE — PRICING & YIELD | B11: 3 | C11: R-03 | E11: Insurance Renegotiation & Empanelment | F11: Revenue — Pricing & Yield | G11: Three-pronged insurance revenue initiative: (A) Charge Capture Audit — audit IP bills against TPA tariff schedules; fix charge master for covered-but-unbilled items (nursing, monitoring, physio, ICU); train nursing on charge initiation. (B) TPA/Insurer Tariff Renegotiation — formal annual revision with all empanelled TPAs (most agreements 2–3 yrs old vs 12–15% cost inflation); target 8–12% rate improvement. (C) Competitive Empanelment Analysis — compare gap insurers vs Aster/Rajagiri/KIMS (Star Health, Go Digit, Navi, SBI General, TATA AIG etc.); pursue new empanelments with incremental revenue impact. | H11: 46113 | I11: ₹4L one-time (billing audit + legal + data prep; internal CFO time) | K11: 4 | L11: 0 | M11: 9 | AA11: =SUM(O11:Z11) -> 0
A12: REVENUE — NETWORK EXPANSION | B12: 4 | C12: R-04 | E12: Distributed Healthcare Network (DHCN) | F12: Revenue — Network Expansion | G12: Deploy two network prototypes across Kerala: (a) Satellite clinics — Lakeshore-branded OPD in suburban/district locations with VPS surgeons running weekly clinics; target 10 clinics. (b) Risk Assessment Centres (RACs) — cancer screening + cardiac/metabolic risk triage at high-footfall locations; target 25 RACs. Both funnel referrals to Kochi main campus. Project referral revenue, revenue share models, and spare capacity utilisation (doctor OP consult analysis). Includes oncology hub-and-spoke scope. | H12: 46143 | I12: ₹65L/yr (10 satellite clinics fit-out + 25 RAC stations + oncology consultant travel + partner MOUs + admin) | K12: 65 | L12: 0 | M12: 13 | AA12: =SUM(O12:Z12) -> 0
A13: REVENUE — NETWORK EXPANSION | B13: 5 | C13: R-05 | E13: Corporate Health Programme | F13: Revenue — Network Expansion | G13: Build a structured corporate health programme targeting top 50 corporates (PSU + private) within 20km of Kochi campus. | H13: 46143 | I13: ₹17L/yr (2 corporate RMs + package design + billing desk) | K13: 17 | L13: 0 | M13: 5 | AA13: =SUM(O13:Z13) -> 0
A14: REVENUE — NETWORK EXPANSION | B14: 6 | C14: R-06 | E14: Residential & Community Outreach | F14: Revenue — Network Expansion | G14: Partner with major gated communities and apartment complexes within 15km for on-site health camps, resident doctor visits, and emergency response agreements. Handled by dedicated corporate/residential team within BD organisation. Includes community health camps: monthly programmes in schools, temples/mosques, and residential complexes. | H14: 46143 | I14: ₹30L/yr (logistics, portable diagnostic equipment, community coordinator + camp logistics) | K14: 30 | L14: 0 | M14: 3 | AA14: =SUM(O14:Z14) -> 0
A15: REVENUE — REFERRAL DEVELOPMENT | B15: 7 | C15: R-07 | E15: International Medical Value Travel | F15: Revenue — Referral Development | G15: Expand medical value travel (MVT) beyond Middle East to all viable source markets for Kerala. Score countries on multi-parameter framework: flight connectivity to Kochi, diaspora size, healthcare gap vs local system, insurance/reimbursement coverage, competitor presence, and VPS Healthcare group synergies (Abu Dhabi, Oman network). Map ecosystem: HCF agents, embassy health attachés, corporate medical evacuation contracts, international insurance TPAs. Build online reputation (Arabic/Bengali/Dhivehi Google Business, Practo international, Vaidam/Bookimed/Medical Departures). Sign clinical referral MOUs with 2–3 Maldives + 2 Gulf hospitals. Target: 200+ MVT patients Year 1, scaling to 500 by Year 3. | H15: 46143 | I15: ₹25L/yr (MVT coordinator + content + aggregator onboarding) | K15: 25 | L15: 0 | M15: 6 | AA15: =SUM(O15:Z15) -> 0
A16: REVENUE — REFERRAL DEVELOPMENT | B16: 8 | C16: R-08 | E16: Government Scheme Empanelment Optimisation | F16: Revenue — Referral Development | G16: Review PMJAY, KASP, CGHS, ECHS, and ESI empanelments — kept separate from insurance (R-03). Ensure all eligible complex procedures (transplant, cardiac interventions, cancer treatments) are listed. Renegotiate rates for high-volume procedures. | H16: 46143 | I16: ₹6L/yr (dedicated scheme coordinator, 1 FTE) | K16: 6 | L16: 0 | M16: 3 | AA16: =SUM(O16:Z16) -> 0
A17: REVENUE — REFERRAL DEVELOPMENT | B17: 9 | C17: R-09 | E17: Scaled BD Organisation & Referral Programme | F17: Revenue — Referral Development | G17: Expand to a full-spectrum BD function with three verticals: (A) Referral Development (3 zones — North/Central/South Kerala): map referring doctors within 50km; A/B/C tier classification; BD field executives on A-tier (top 100) with monthly visit cadence; 500+ registered referring doctors; 24-hr discharge summary SOP. (B) Institutional & Partnerships: corporate accounts (R-05), MVT (R-07), satellite clinics (R-04), government schemes (R-08). (C) Communications & Branding: CME calendar — monthly specialty CMEs across suburban/district locations; dedicated CME Coordinator; MCI accreditation; digital CME platform. 27-person BD organisation under BD Head reporting to CEO. | H17: 46113 | I17: ₹3.5 Cr/yr total BD function (6 open roles + CRM + CME events + FE travel) | K17: 350 | L17: 0 | M17: 25 | AA17: =SUM(O17:Z17) -> 0
A18: REVENUE — REFERRAL DEVELOPMENT | B18: 10 | C18: R-10 | D18: 1 | E18: OP-IP Conversion & Follow-Up | F18: Revenue — Referral Development | G18: OP-to-IP conversion initiative with two tracks: (A) Surgical OPD Counselling — deploy trained financial counsellors at surgical OPD (ortho, cardiac, neurosurgery, oncology, transplant); explain package costs; initiate insurance pre-auth on day of consultation; arrange EMI/loan tie-ups for self-pay. (B) Follow-Up & Dropout Prevention — analyse OP follow-up calls to curtail dropouts; appointment reminders; 48-hour post-consult callbacks; treatment plan adherence tracking; lapsed patient re-engagement. Target: +5pp conversion = ~2,000 incremental IP admissions/yr. | H18: 46143 | I18: ₹17L/yr (3–4 counsellor salaries + TPA training + NBFC onboarding) | O18: =-'R-10'!J5/10^7 -> -0.014 | P18: =-'R-10'!K5/10^7 -> -0.014 | Q18: =-'R-10'!L5/10^7 -> -0.014 | R18: =-'R-10'!M5/10^7 -> -0.014 | S18: =-'R-10'!N5/10^7 -> -0.014 | T18: =-'R-10'!O5/10^7 -> -0.014 | U18: =-'R-10'!P5/10^7 -> -0.014 | V18: =-'R-10'!Q5/10^7 -> -0.014 | ... Z18: =-'R-10'!U5/10^7 -> -0.014 | AA18: =SUM(O18:Z18) -> -0.168
A19: REVENUE — REFERRAL DEVELOPMENT | B19: 10 | C19: R-10 | D19: 2 | E19: OP-IP Conversion & Follow-Up | F19: Revenue — Referral Development | G19: OP-to-IP conversion initiative with two tracks: (A) Surgical OPD Counselling — deploy trained financial counsellors at surgical OPD (ortho, cardiac, neurosurgery, oncology, transplant); explain package costs; initiate insurance pre-auth on day of consultation; arrange EMI/loan tie-ups for self-pay. (B) Follow-Up & Dropout Prevention — analyse OP follow-up calls to curtail dropouts; appointment reminders; 48-hour post-consult callbacks; treatment plan adherence tracking; lapsed patient re-engagement. Target: +5pp conversion = ~2,000 incremental IP admissions/yr. | H19: 46143 | I19: ₹17L/yr (3–4 counsellor salaries + TPA training + NBFC onboarding) | K19: 17 | L19: 0 | M19: 4 | O19: 32.437148 | P19: 32.437148 | Q19: 32.240848 | R19: 38.367325 | S19: 36.651286 | T19: 36.651286 | U19: 36.827255 | V19: 33.596443 | W19: 35.83597 | X19: 39.476666 | Y19: 34.608664 | Z19: 36.129073 | AA19: =SUM(O19:Z19) -> 425.25911
A20: REVENUE — HIGH-VALUE SERVICES | B20: 11 | C20: R-11 | E20: Departmental Organic Growth Initiative | F20: Revenue — High-Value Services | G20: Monthly department review: each clinical department presents its growth plan, infrastructure needs, staffing gaps, and volume targets. | H20: 46143 | I20: Nil — internal process; dept-level investment decisions routed through normal capex approval | K20: 0 | L20: 0 | M20: 8 | O20: =+'R-11'!T4/10000000 -> 0 | P20: =+'R-11'!U4/10000000 -> 0.31394309 | Q20: =+'R-11'!V4/10000000 -> 1.0036637 | R20: =+'R-11'!W4/10000000 -> 1.8401196 | S20: =+'R-11'!X4/10000000 -> 2.4398645 | T20: =+'R-11'!Y4/10000000 -> 3.1779269 | U20: =+'R-11'!Z4/10000000 -> 3.9264253 | V20: =+'R-11'!AA4/10000000 -> 4.215596 | ... Z20: =+'R-11'!AE4/10000000 -> 7.3996918 | AA20: =SUM(O20:Z20) -> 42.822427
A21: REVENUE — HIGH-VALUE SERVICES | B21: 12 | C21: R-12 | E21: New Specialties, Procedures & Packages | F21: Revenue — High-Value Services | G21: Launch new high-end, high-value specialties and packages based on Kochi/Kerala market dynamics: (A) Structural Heart & EP — TAVR/MitraClip/LAAO programme. (B) Orthopaedics — all-inclusive joint replacement packages, sports medicine. (C) Additional specialties/packages identified from market analysis. Focus on high-end procedures with unmet demand and strong uptake potential. | H21: 46143 | I21: ₹19L one-time capex (device partnerships + package design + billing config + marketing collateral) | K21: 0 | L21: 19 | M21: 11 | AA21: =SUM(O21:Z21) -> 0
A22: REVENUE — HIGH-VALUE SERVICES | B22: 13 | C22: R-13 | E22: Clinician Recruitment & Specialty Team Building | F22: Revenue — High-Value Services | G22: Recruit senior clinicians and clinical teams in 6 specialties where Lakeshore is underweight vs competitors: (A) Women’s Health & Obstetrics, (B) Paediatrics & Neonatology, (C) Pulmonology, (D) Endocrinology, (E) Rheumatology, (F) ENT & Head-Neck Surgery. Each senior consultant brings ₹3–5 Cr/yr IP revenue with established referral network. | H22: 46143 | I22: ₹4 Cr/yr opex (7–8 senior consultants @ ₹60L–1 Cr each incl. relocation + 12-mo practice guarantee top-up); ₹90L one-time capex (NICU upgrade + sleep lab + maternity branding). Year 1 practice-guarantee exposure may add ₹1–2 Cr one-time. | K22: 400 | L22: 90 | M22: 20 | AA22: =SUM(O22:Z22) -> 0
A23: REVENUE — MARKETING & PATIENT ACQUISITION | B23: 14 | C23: R-14 | D23: 0 | E23: Quarterly Health Events Calendar | F23: Revenue — Marketing & Patient Acquisition | G23: Rebrand from single Heart Run to a structured quarterly events calendar. Four flagship events per year: (1) Lakeshore Heart Run (Q2 — cardiac awareness, half-marathon/10K), (2) Liver Week (Q3 — liver health screenings, transplant awareness), (3) Cancer Awareness Drive (Q4 — aligned with Breast Cancer/World Cancer Day), (4) Diabetes & Metabolic Health Camp (Q1 — aligned with World Diabetes Day). Each event: 3,000–5,000 participants, health screenings, OPD follow-ups, media coverage, sponsorship. Entry fees + pharma/device sponsorship partially offset costs. | H23: 46266 | I23: ₹1.1 Cr/yr (5 events × ₹10–12L + media ₹40–50L; partial sponsorship recovery) Actual cost per eveny around Rs. 30L estimated | J23: 5*22L | K23: 110 | L23: 0 | M23: 1.5 | O23: =+'R-14'!F5/10000000 -> 0 | P23: =+'R-14'!G5/10000000 -> 0 | Q23: =+'R-14'!H5/10000000 -> -0.3 | R23: =+'R-14'!I5/10000000 -> 0 | S23: =+'R-14'!J5/10000000 -> -0.3 | T23: =+'R-14'!K5/10000000 -> 0 | U23: =+'R-14'!L5/10000000 -> 0 | V23: =+'R-14'!M5/10000000 -> -0.3 | ... Z23: =+'R-14'!Q5/10000000 -> -0.3 | AA23: =SUM(O23:Z23) -> -1.5
A24: REVENUE — MARKETING & PATIENT ACQUISITION | B24: 14 | C24: =+C23 -> R-14 | D24: =+D23+1 -> 1 | E24: Quarterly Health Events Calendar | F24: Revenue — Marketing & Patient Acquisition | G24: Rebrand from single Heart Run to a structured quarterly events calendar. Four flagship events per year: (1) Lakeshore Heart Run (Q2 — cardiac awareness, half-marathon/10K), (2) Liver Week (Q3 — liver health screenings, transplant awareness), (3) Cancer Awareness Drive (Q4 — aligned with Breast Cancer/World Cancer Day), (4) Diabetes & Metabolic Health Camp (Q1 — aligned with World Diabetes Day). Each event: 3,000–5,000 participants, health screenings, OPD follow-ups, media coverage, sponsorship. Entry fees + pharma/device sponsorship partially offset costs. | H24: 46266 | I24: Total Estiamted Cost of each program including media coverage Rs. 30L. Out of this 25% sponsorship revenue approx. Rs. 7 lakhs | J24: 5*7L each | O24: =+'R-14'!F6/10000000 -> 0 | P24: =+'R-14'!G6/10000000 -> 0 | Q24: =+'R-14'!H6/10000000 -> 0.07 | R24: =+'R-14'!I6/10000000 -> 0 | S24: =+'R-14'!J6/10000000 -> 0.07 | T24: =+'R-14'!K6/10000000 -> 0 | U24: =+'R-14'!L6/10000000 -> 0 | V24: =+'R-14'!M6/10000000 -> 0.07 | ... Z24: =+'R-14'!Q6/10000000 -> 0.07 | AA24: =SUM(O24:Z24) -> 0.35
A25: REVENUE — MARKETING & PATIENT ACQUISITION | B25: 14 | C25: =+C24 -> R-14 | D25: =+D24+1 -> 2 | E25: Quarterly Health Events Calendar | F25: Revenue — Marketing & Patient Acquisition | G25: Rebrand from single Heart Run to a structured quarterly events calendar. Four flagship events per year: (1) Lakeshore Heart Run (Q2 — cardiac awareness, half-marathon/10K), (2) Liver Week (Q3 — liver health screenings, transplant awareness), (3) Cancer Awareness Drive (Q4 — aligned with Breast Cancer/World Cancer Day), (4) Diabetes & Metabolic Health Camp (Q1 — aligned with World Diabetes Day). Each event: 3,000–5,000 participants, health screenings, OPD follow-ups, media coverage, sponsorship. Entry fees + pharma/device sponsorship partially offset costs. | H25: 46266 | I25: Estimated Revenue Increase | O25: =+'R-14'!F7/10000000 -> 0 | P25: =+'R-14'!G7/10000000 -> 0 | Q25: =+'R-14'!H7/10000000 -> 0.22761 | R25: =+'R-14'!I7/10000000 -> 0 | S25: =+'R-14'!J7/10000000 -> 0.377912 | T25: =+'R-14'!K7/10000000 -> 0 | U25: =+'R-14'!L7/10000000 -> 0 | V25: =+'R-14'!M7/10000000 -> 0.450904 | ... Z25: =+'R-14'!Q7/10000000 -> 0.145978 | AA25: =SUM(O25:Z25) -> 1.503006
A26: REVENUE — MARKETING & PATIENT ACQUISITION | B26: 15 | C26: R-15 | D26: 0 | E26: Patient Acquisition & Digital Platform | F26: Revenue — Marketing & Patient Acquisition | G26: Comprehensive patient acquisition analysis: How do patients find us vs competition? Marketing spend ~₹7Cr = 10–15% commission → only ₹50–70Cr revenue through referral channel. Remaining patients walked in — understand why. Magnify the strongest channels. Digital platform: 3 health videos/week, SEO, Google Ads, doctor online reputation management (Google Business, Practo, Doctorundi), post-OPD review collection. Track digital-to-enquiry conversion. Includes online reputation management scope. | H26: 46113 | I26: ₹62L/yr (2 content staff + Malayalam agency + Google Ads + SEO + platform management) | K26: 62 | L26: 0 | M26: 5 | O26: =+-'R-15'!H3/10000000 -> 0 | P26: =+-'R-15'!I3/10000000 -> -0.0905 | Q26: =+-'R-15'!J3/10000000 -> -0.0555 | R26: =+-'R-15'!K3/10000000 -> -0.0505 | S26: =+-'R-15'!L3/10000000 -> -0.0555 | T26: =+-'R-15'!M3/10000000 -> -0.0505 | U26: =+-'R-15'!N3/10000000 -> -0.0505 | V26: =+-'R-15'!O3/10000000 -> -0.0555 | ... Z26: =+-'R-15'!S3/10000000 -> -0.0555 | AA26: =SUM(O26:Z26) -> -0.6205
A27: =+A26 -> REVENUE — MARKETING & PATIENT ACQUISITION | B27: 15 | C27: R-15 | D27: =+D26+1 -> 1 | E27: Patient Acquisition & Digital Platform | F27: Revenue — Marketing & Patient Acquisition | G27: Comprehensive patient acquisition analysis: How do patients find us vs competition? Marketing spend ~₹7Cr = 10–15% commission → only ₹50–70Cr revenue through referral channel. Remaining patients walked in — understand why. Magnify the strongest channels. Digital platform: 3 health videos/week, SEO, Google Ads, doctor online reputation management (Google Business, Practo, Doctorundi), post-OPD review collection. Track digital-to-enquiry conversion. Includes online reputation management scope. | H27: 46113 | I27: Increase in Overall Revenue through footfall increase | O27: =+'R-15'!H13/10000000 -> 0 | P27: =+'R-15'!I13/10000000 -> 0.010161 | Q27: =+'R-15'!J13/10000000 -> 0.018753 | R27: =+'R-15'!K13/10000000 -> 0.051312 | S27: =+'R-15'!L13/10000000 -> 0.21845 | T27: =+'R-15'!M13/10000000 -> 0.314556 | U27: =+'R-15'!N13/10000000 -> 0.467231 | V27: =+'R-15'!O13/10000000 -> 0.541018 | ... Z27: =+'R-15'!S13/10000000 -> 0.989893 | AA27: =SUM(O27:Z27) -> 5.020543
A28: COST — MATERIALS / COGS | B28: 16 | C28: C-01 | E28: Drug Brand Substitution | F28: Cost — Materials / COGS | G28: Substitute 16 high-spend branded drugs with clinically equivalent alternatives at lower procurement cost. Formulary analysis identifies ₹38.8L/month (₹4.66 Cr/year) incremental profit at full compliance. | H28: 46113 | I28: Nil — formulary committee process; HMIS alert = existing config | L28: 0 | M28: 3 | O28: 0.18714138 | P28: 0.25397285 | Q28: 0.24845956 | R28: 0.28395704 | S28: 0.26940211 | T28: 0.25682815 | U28: 0.27178223 | V28: 0.23745317 | W28: 0.25242729 | X28: 0.27417722 | Y28: 0.2581575 | Z28: 0.22963407 | AA28: =SUM(O28:Z28) -> 3.0233926
A29: COST — MATERIALS / COGS | B29: 17 | C29: C-02 | E29: Manufacturer Rate Contract | F29: Cost — Materials / COGS | G29: MD/CEO-level engagement with top 20 manufacturers. Negotiate higher discounts via volume commitment. Replace spot purchase with 12-month rate contracts. | H29: 46113 | I29: Nil — internal negotiation | L29: 0 | M29: 1.3 | O29: 0.081094597 | P29: 0.1100549 | Q29: 0.10766581 | R29: 0.12304805 | S29: 0.11674091 | T29: 0.1112922 | U29: 0.1177723 | V29: 0.10289637 | W29: 0.10938516 | X29: 0.11881013 | Y29: 0.11186825 | Z29: 0.099508099 | AA29: =SUM(O29:Z29) -> 1.3101368
A30: COST — MATERIALS / COGS | B30: 18 | C30: C-03 | E30: Distributor Consolidation | F30: Cost — Materials / COGS | G30: Reduce to 3 core distributors. Extract volume-linked discounts. Eliminate margin leakage from fragmented procurement. | H30: 46113 | I30: Nil — procurement process change only | L30: 0 | M30: 0.8 | O30: 0.049904367 | P30: 0.067726095 | Q30: 0.066255884 | R30: 0.075721877 | S30: 0.071840563 | T30: 0.068487507 | U30: 0.072475261 | V30: 0.063320845 | W30: 0.067313944 | X30: 0.073113925 | Y30: 0.068842 | Z30: 0.061235753 | AA30: =SUM(O30:Z30) -> 0.80623802
A31: COST — MATERIALS / COGS | B31: 19 | C31: C-04 | E31: Surgical BOQ Standardisation | F31: Cost — Materials / COGS | G31: Standardise preference cards and consumable kits per procedure. Eliminate inter-surgeon variation. | H31: 46174 | I31: ₹2.5L one-time (OT audit, preference card redesign, store system config) | L31: 0 | M31: 0.575 | O31: 0.037428275 | P31: 0.050794571 | Q31: 0.049691913 | R31: 0.056791408 | S31: 0.053880422 | T31: 0.05136563 | U31: 0.054356446 | V31: 0.047490634 | W31: 0.050485458 | X31: 0.054835444 | Y31: 0.0516315 | Z31: 0.045926815 | AA31: =SUM(O31:Z31) -> 0.60467852
A32: COST — MATERIALS / COGS | B32: 20 | C32: C-05 | E32: Inventory, Expiry & Wastage Control | F32: Cost — Materials / COGS | G32: Comprehensive wastage reduction across all material categories: (A) Drug Inventory & Expiry — reduce drug inventory holding to <20 days; eliminate expiry write-offs; vendor return clauses in all new supply contracts; HMIS-enforced FEFO dispensing + reorder-point alerts. (B) F&B Meal Wastage — reduce cost per patient meal via menu standardisation and order accuracy; cut wastage 20% through demand forecasting + plate return analysis; dietitian-driven menu. (C) Consumables & Surgical Wastage — cut-strip wastage, opened-but-unused consumables, OT preference card over-ordering; monthly wastage reporting by department. | H32: 46113 | I32: Nil — HMIS config + pharmacy/F&B process change | L32: 0 | M32: 0.7 | O32: 0.043666321 | P32: 0.059260333 | Q32: 0.057973898 | R32: 0.066256643 | S32: 0.062860493 | T32: 0.059926568 | U32: 0.063415854 | V32: 0.05540574 | W32: 0.058899701 | X32: 0.063974684 | Y32: 0.06023675 | Z32: 0.053581284 | AA32: =SUM(O32:Z32) -> 0.70545827
A33: COST — MATERIALS / COGS | B33: 21 | C33: C-06 | E33: Laundry Cost Reduction | F33: Cost — Materials / COGS | G33: Reduce cost per kg of linen processing. Outsourcing optimisation and linen tagging/RFID to reduce loss. | H33: 46113 | I33: ₹1.5L one-time (linen tagging/RFID if required) | L33: 0 | M33: 0.135 | O33: =+'C-06'!H5/10^7 -> 0.010778138 | P33: =+'C-06'!I5/10^7 -> 0.010776414 | Q33: =+'C-06'!J5/10^7 -> 0.010222622 | R33: =+'C-06'!K5/10^7 -> 0.011179147 | S33: =+'C-06'!L5/10^7 -> 0.015679308 | T33: =+'C-06'!M5/10^7 -> 0.0064171674 | U33: =+'C-06'!N5/10^7 -> 0.010553442 | V33: =+'C-06'!O5/10^7 -> 0.012022228 | ... Z33: =+'C-06'!S5/10^7 -> 0.02604834 | AA33: =SUM(O33:Z33) -> 0.15
A34: COST — MATERIALS / COGS | B34: 22 | C34: C-07 | E34: AMC Renegotiation | F34: Cost — Materials / COGS | G34: Replace OEM AMC with third-party maintenance for non-critical equipment. Renegotiate using competitive quotes. | H34: 46143 | I34: ₹2.5L one-time (biomedical vendor empanelment + criticality classification) | L34: 0 | M34: 0.275 | O34: =+'C-07'!F6/10^7 -> 0.066868793 | P34: =+'C-07'!G6/10^7 -> -0.35229928 | Q34: =+'C-07'!H6/10^7 -> 0.020288969 | R34: =+'C-07'!I6/10^7 -> -0.7414554 | S34: =+'C-07'!J6/10^7 -> -0.68174847 | T34: =+'C-07'!K6/10^7 -> -1.1148352 | U34: =+'C-07'!L6/10^7 -> 0.7629488 | V34: =+'C-07'!M6/10^7 -> 1.6039326 | ... Z34: =+'C-07'!Q6/10^7 -> 0.79849147 | AA34: =SUM(O34:Z34) -> -1.0995505
A35: COST — PAYROLL | B35: 23 | C35: C-08 | E35: Nursing Headcount to Occupied-Bed Norm | F35: Cost — Payroll | G35: Align nursing strength to occupied bed norm (1:3 general, 1:1 ICU). Reduce ~97 surplus via natural attrition. | H35: 46113 | I35: Nil — attrition-based; hiring freeze only | L35: 0 | M35: 1.5 | O35: 0.73981207 | P35: 0.83780464 | Q35: 0.82399179 | R35: 0.83842656 | S35: 0.83034662 | T35: 0.90894849 | U35: 0.86150935 | V35: 0.79498983 | W35: 0.82753294 | X35: 0.81319568 | Y35: 0.85709359 | Z35: 0.89100905 | AA35: =SUM(O35:Z35) -> 10.024661
A36: COST — PAYROLL | B36: 24 | C36: C-09 | E36: Pharmacy Headcount Post-Automation | F36: Cost — Payroll | G36: Reduce pharmacy staff 93→86 post barcode dispensing. Hard dependency: barcode capex first. | H36: 46174 | I36: ₹1 Cr one-time capex (barcode dispensing system — hard dependency before savings) | L36: 100 | M36: 1 | O36: 0.49320805 | P36: 0.55853643 | Q36: 0.54932786 | R36: 0.55895104 | S36: 0.55356441 | T36: 0.60596566 | U36: 0.57433957 | V36: 0.52999322 | W36: 0.55168863 | X36: 0.54213046 | Y36: 0.57139573 | Z36: 0.59400604 | AA36: =SUM(O36:Z36) -> 6.6831071
A37: COST — PAYROLL | B37: 25 | C37: C-10 | E37: PCS Reduction via EMR | F37: Cost — Payroll | G37: Eliminate ward secretary roles made redundant by EMR. Target: 97→80. Natural attrition post-EMR. | H37: 46174 | I37: Nil incremental — dependent on EMR go-live (separate capital project) | L37: 0 | M37: 0.5 | O37: 0.24660402 | P37: 0.27926821 | Q37: 0.27466393 | R37: 0.27947552 | S37: 0.27678221 | T37: 0.30298283 | U37: 0.28716978 | V37: 0.26499661 | W37: 0.27584431 | X37: 0.27106523 | Y37: 0.28569786 | Z37: 0.29700302 | AA37: =SUM(O37:Z37) -> 3.3415535
A38: COST — PAYROLL | B38: 26 | C38: C-11 | E38: Contract Staff Rebid | F38: Cost — Payroll | G38: Competitive rebidding of outsourced staffing contracts. 416 contracted staff, ₹1,290L annual spend. Structured RFQ with SLAs. | H38: 46143 | I38: ₹2.5L one-time (RFQ/tender + legal review of existing contracts) | J38: No scope seen for cost optimisation | L38: 0 | M38: 0.375 | O38: 0 | P38: 0 | Q38: 0 | R38: 0 | S38: 0 | T38: 0 | U38: 0 | V38: 0 | W38: 0 | X38: 0 | Y38: 0 | Z38: 0 | AA38: =SUM(O38:Z38) -> 0
A39: COST — MISCELLANEOUS | B39: 27 | C39: C-12 | E39: Creditor Days Extension | F39: Cost — Miscellaneous | G39: Extend creditor payment days with top vendors. Each 15-day extension on ₹1,000Cr payables = ₹40Cr working capital freed. | H39: 46143 | I39: Nil — CFO-led vendor negotiation | J39: Need a periodic analysis cannot estimate now | L39: 0 | M39: 0.2 | O39: 0 | P39: 0 | Q39: 0 | R39: 0 | S39: 0 | T39: 0 | U39: 0 | V39: 0 | W39: 0 | X39: 0 | Y39: 0 | Z39: 0 | AA39: =SUM(O39:Z39) -> 0
A40: COST — MISCELLANEOUS | B40: 28 | C40: C-13 | E40: Expense Analysis & Financial Discipline | F40: Cost — Miscellaneous | G40: Establish a structured expense governance programme across the hospital: (A) Hidden Expense Identification — map all recurring payments (professional fees, retainers, subscriptions, AMCs, memberships) against active deliverables; eliminate spend with no demonstrable ROI. (B) IT & Software Licence Rationalisation — audit active licences, SaaS subscriptions, IT AMCs; identify unused seats, duplicate tools, open-source alternatives; bandwidth optimisation. (C) Contract Review — systematic review of active contracts; surface expired auto-renewals, favourable-to-vendor terms, renegotiation opportunities. (D) Financial Discipline — PO compliance, monthly budget variance reporting, cost centre accountability, quarterly cost reviews. (E) Material Cost Programme — COGS 28.5%→26.5% target via rate contracts, BOQ standardisation, volume consolidation (strategic umbrella over C-01 to C-12). | H40: 46113 | I40: Nil — CFO + Procurement Head review; possible ₹1L legal advisory for contract exits | L40: 0 | M40: 0.15 | O40: =+'C-13'!E4/10^5 -> 0 | P40: =+'C-13'!F4/10^5 -> 0 | Q40: =+'C-13'!G4/10^5 -> 0 | R40: =+'C-13'!H4/10^5 -> 0.45 | S40: =+'C-13'!I4/10^5 -> 0.75 | T40: =+'C-13'!J4/10^5 -> 1.05 | U40: =+'C-13'!K4/10^5 -> 1.35 | V40: =+'C-13'!L4/10^5 -> 1.65 | ... Z40: =+'C-13'!P4/10^5 -> 3 | AA40: =SUM(O40:Z40) -> 15
A41: CLINICAL EXCELLENCE | B41: 29 | C41: CL-01 | E41: Research & Publications | F41: Clinical Excellence | G41: Four integrated workstreams: (A) Clinical Trials — expand from 8 to 20+ active studies with dedicated CRCs. (B) Publications — 10 indexed publications/yr from top 20 unpublished case series. (C) Grant Applications — ICMR/DBT/DST, target 1 funded grant/yr. (D) Ethics Committee — scale to 8-10 meetings/yr, CDSCO registration. | H41: 46143 | I41: Nil — internal process | K41: 0 | L41: 0 | O41: 0 | P41: 0 | Q41: 0 | R41: 0 | S41: 0 | T41: 0 | U41: 0 | V41: 0 | W41: 0 | X41: 0 | Y41: 0 | Z41: 0 | AA41: =SUM(O41:Z41) -> 0
A42: CLINICAL EXCELLENCE | B42: 30 | C42: CL-02 | E42: Patient Care & Experience | F42: Clinical Excellence | G42: Integrated patient experience programme with four pillars: (A) NPS & real-time feedback — Net Promoter Score at OPD checkout, discharge, and 7-day post-discharge via SMS; department dashboard visible to HODs; monthly review. (B) Discharge & follow-up protocol — 24-hr discharge summary, 48-hr post-discharge nurse call for surgical patients, next appointment booked at discharge. (C) Patient support groups — structured groups for transplant, cancer, and cardiac patients; monthly meetings; annual reunion. (D) Annual clinical outcomes report — published for top 5 programmes, distributed to 1,000+ referring physicians; quarterly clinical-firsts press releases. | H42: 46143 | I42: Nil — internal process | K42: 0 | L42: 0 | O42: 0 | P42: 0 | Q42: 0 | R42: 0 | S42: 0 | T42: 0 | U42: 0 | V42: 0 | W42: 0 | X42: 0 | Y42: 0 | Z42: 0 | AA42: =SUM(O42:Z42) -> 0
A43: CLINICAL EXCELLENCE | B43: 31 | C43: CL-03 | E43: Academic Excellence & Medical Education | F43: Clinical Excellence | G43: Two-track medical education expansion: (A) DNB programme expansion — apply for additional DNB seats in cardiology, gastroenterology, neurology, and surgical oncology; structured curriculum with log book and supervision. (B) Fellowship & observership programme — structured 1-week to 3-month fellowships in robotic surgery, transplant, structural heart, and head & neck oncology; offset by fellowship fees; target cohort of 20+ fellows/yr. | H43: 46143 | I43: Nil — internal process | K43: 0 | L43: 0 | O43: 0 | P43: 0 | Q43: 0 | R43: 0 | S43: 0 | T43: 0 | U43: 0 | V43: 0 | W43: 0 | X43: 0 | Y43: 0 | Z43: 0 | AA43: =SUM(O43:Z43) -> 0
A44: CLINICAL EXCELLENCE | B44: 32 | C44: CL-04 | E44: Rare & Complex Care | F44: Clinical Excellence | G44: Three centres of clinical differentiation: (A) Robotic Surgery Centre of Excellence — formalise centre, prospective case registry, 1-week observership, industry training partnership. (B) Rare Disease & Complex Case Programme — weekly MDT for rare presentations, registration with ORDI and ICMR Rare Disease Registry, annual case series publication, genetic testing tie-up. (C) Structural Heart & EP Sub-Specialty — formalise TAVR/MitraClip/LAAO programme, complex EP development, outcomes publication, integration with cardiac imaging. | H44: 46143 | I44: Nil — internal process | K44: 0 | L44: 0 | O44: 0 | P44: 0 | Q44: 0 | R44: 0 | S44: 0 | T44: 0 | U44: 0 | V44: 0 | W44: 0 | X44: 0 | Y44: 0 | Z44: 0 | AA44: =SUM(O44:Z44) -> 0
A45: CLINICAL EXCELLENCE | B45: 33 | C45: CL-05 | E45: Awards & Accreditations | F45: Clinical Excellence | G45: Systematic pursuit of accreditations and awards. Accreditations: JCI (competitors Aster/KIMS already accredited), NABH Nursing Excellence, NABH Green OT, NABL, NOTTO, MTQUA, GHA. Awards: FICCI Healthcare Excellence, AHPI, ET Healthworld, Asian Hospital Management, Times Health Excellence, BMJ India, IHF. Target: JCI by Sep-27, 5+ award submissions/yr. | H45: 46143 | I45: ₹20L one-time capex (JCI consultant + application fees + documentation support) | K45: 0 | L45: 20 | O45: 0 | P45: 0 | Q45: 0 | R45: 0 | S45: 0 | T45: 0 | U45: 0 | V45: 0 | W45: 0 | X45: 0 | Y45: 0 | Z45: 0 | AA45: =SUM(O45:Z45) -> 0
AA46: =SUM(O46:Z46) -> 0
C48: Cost New | G48: Historically in FY 22-23 and FY 2021-22 the Consumption % was tried to be kept below 30% and hence having a cost control inititaive for being midnful in usage of department consumables and maximising patient billing will help to bring in this impact | O48: 0.63191405 | P48: 0.85758167 | Q48: 0.83896513 | R48: 0.95882827 | S48: 0.90968113 | T48: 0.86722305 | U48: 0.91771799 | V48: 0.8018002 | W48: 0.85236281 | X48: 0.92580508 | Y48: 0.87171182 | Z48: 0.77539772 | AA48: 10.208989
C49: Cost New 1 | G49: Inorder to achive the EBITDA a further hair cut of Rs. 9.24 is required which has to be identified department wise. | O49: 4.5608495 | P49: 5.1649615 | Q49: 5.079807 | R49: 5.1687956 | S49: 5.1189837 | T49: 5.6035545 | U49: 5.3110981 | V49: 4.9010136 | W49: 5.1016378 | X49: 5.0132504 | Y49: 5.2838755 | Z49: 5.4929601 | AA49: =SUM(O49:Z49) -> 61.800787

Sheet R-01
A1: R-01 | Annual Rate Revision Policy
A2: Revenue — Pricing & Yield
A3: OVERVIEW
A4: Description / Objective | B4: Revise all IP room, nursing, and procedure rates for cash/self-pay patients effective May-26. Room & nursing tariffs benchmarked against Aster, Welcare, Rajagiri, and Sunrise across 19 bed categories (avg increase ~12%). Top 50 revenue procedures repriced to midpoint of Lakeshore and highest competitor rate.
A5: Start Month | B5: 46113
A6: Estimated Cost | B6: Nil — internal process; CFO time only
A7: Expected Impact | B7: ₹9.6 Cr (Room & Nursing ₹3.5 Cr + Procedure repricing ₹6.1 Cr)
A9: BASIS FOR THIS INITIATIVE
A10: • Room & nursing tariffs benchmarked across 19 bed categories against Aster, Welcare, Rajagiri, and Sunrise • Revised tariff effective May-26 applies to cash/self-pay patients; avg increase ~12% (wards 11–25%, rooms 4–13%, suites 10–11%, critical care 10–16%) • Lakeshore remains below Aster post-revision — AC Room ₹6,500 vs ₹7,500 (−13%); Deluxe ₹7,500 vs ₹12,500 (−40%) • Chemo Ward held flat at ₹1,700 to protect oncology volume • Top 50 revenue procedures benchmarked against estimated Aster, Rajagiri, and Welcare rates; proposed hike to midpoint of Lakeshore and highest competitor • Competitor procedure rates are estimates from room tariff premium patterns — to be validated with actual competitor rate sheets • Note: Lakeshore is already priced above Rajagiri (40 of 50 procedures) and Welcare (all 50). Proposed hikes widen this gap further. Consider selective restraint on procedures where the gap to Rajagiri/Welcare exceeds 15–20%
A11: EXECUTION TRACKING (to be completed)
A12: Owner | B12: CFO
A13: Key Milestones / Actions | B13: 1. Tariff card signed off with 19-category rate grid (done) 2. Update HIS billing master with new rates by 30-Apr 3. Front-office and billing-counter staff briefing by 30-Apr 4. Monitor first-month revenue per occupied bed vs baseline (Jun review)
A14: Risks / Dependencies | B14: 1. Patient pushback on ward categories with >20% increase (General Ward +25%, Triple Sharing +22%) — front-desk scripts and patient counsellors needed 2. Cash patient share may vary seasonally; monsoon months see higher insurance utilisation 3. HIS billing-master update must be error-free to avoid under-billing cash patients at old rates
A15: Remarks | B15: Competitor benchmarking confirms room for increase vs Aster, but Lakeshore is already above Rajagiri and Welcare on most procedures — hikes should be selective. Chemo Ward held flat to protect oncology volumes. Diet and F&B service charges unchanged.
A18: ANALYSIS 1 : Room & Nursing Tariff Revision — Nursing Increment Pass-Through
A19: All rates are all-inclusive daily rates (room rent + nursing charges + diet + F&B service). Revision effective May-26, cash/self-pay patients only.
A21: Bed Category | B21: Existing (₹/day) | C21: Proposed (₹/day) | D21: Increase % | E21: Aster (₹/day) | F21: Welcare (₹/day) | G21: Rajagiri (₹/day) | H21: Sunrise (₹/day) | I21: vs Aster
A22: SINGLE ROOM NON A/C. | B22: 3400 | C22: 3750 | D22: =(C22-B22)/B22 -> 0.10294118 | E22: — | F22: — | G22: 4000 | H22: 3500 | I22: —
A23: GENERAL WARD | B23: 1200 | C23: 1500 | D23: =(C23-B23)/B23 -> 0.25 | E23: 2250 | F23: — | G23: — | H23: — | I23: =(C23-E23)/E23 -> -0.33333333
A24: GENERAL WARD A/C. | B24: 1800 | C24: 2000 | D24: =(C24-B24)/B24 -> 0.11111111 | E24: — | F24: — | G24: — | H24: — | I24: —
A25: TWIN SHARING A/C | B25: 3100 | C25: 3500 | D25: =(C25-B25)/B25 -> 0.12903226 | E25: 4500 | F25: 3150 | G25: — | H25: — | I25: =(C25-E25)/E25 -> -0.22222222
A26: TRIPLE SHARING A/C | B26: 2450 | C26: 3000 | D26: =(C26-B26)/B26 -> 0.2244898 | E26: — | F26: — | G26: — | H26: — | I26: —
A27: AC ROOM | B27: 6250 | C27: 6500 | D27: =(C27-B27)/B27 -> 0.04 | E27: 7500 | F27: 4900 | G27: 4500 | H27: 4500 | I27: =(C27-E27)/E27 -> -0.13333333
A28: DELUXE A/C. | B28: 6760 | C28: 7500 | D28: =(C28-B28)/B28 -> 0.10946746 | E28: 12500 | F28: 5800 | G28: 7300 | H28: — | I28: =(C28-E28)/E28 -> -0.4
A29: EXECUTIVE ROOM | B29: 9175 | C29: 10100 | D29: =(C29-B29)/B29 -> 0.10081744 | E29: 16000 | F29: — | G29: — | H29: 6000 | I29: =(C29-E29)/E29 -> -0.36875
A30: EXECUTIVE SUITE | B30: 30200 | C30: 33500 | D30: =(C30-B30)/B30 -> 0.10927152 | E30: — | F30: 11000 | G30: — | H30: — | I30: —
A31: PRESIDENTIAL SUITE | B31: 42200 | C31: 46500 | D31: =(C31-B31)/B31 -> 0.10189573 | E31: 75000 | F31: — | G31: — | H31: — | I31: =(C31-E31)/E31 -> -0.38
A32: CHEMO WARD | B32: 1700 | C32: 1700 | D32: =(C32-B32)/B32 -> 0 | E32: 1250 | F32: — | G32: — | H32: — | I32: =(C32-E32)/E32 -> 0.36
A33: DAY CARE | B33: 1800 | C33: 2000 | D33: =(C33-B33)/B33 -> 0.11111111 | E33: 1250 | F33: — | G33: — | H33: — | I33: =(C33-E33)/E33 -> 0.6
A34: LABOUR ROOM | B34: 5200 | C34: 6000 | D34: =(C34-B34)/B34 -> 0.15384615 | E34: — | F34: — | G34: — | H34: — | I34: —
A35: HDU | B35: 5650 | C35: 6500 | D35: =(C35-B35)/B35 -> 0.15044248 | E35: — | F35: — | G35: — | H35: — | I35: —
A36: ICU | B36: 7300 | C36: 8000 | D36: =(C36-B36)/B36 -> 0.095890411 | E36: — | F36: — | G36: — | H36: — | I36: —
A37: ISOLATION ICU | B37: 7500 | C37: 8500 | D37: =(C37-B37)/B37 -> 0.13333333 | E37: — | F37: — | G37: — | H37: — | I37: —
A38: ICCU / KTXICU | B38: 8650 | C38: 10000 | D38: =(C38-B38)/B38 -> 0.15606936 | E38: — | F38: — | G38: — | H38: — | I38: —
A39: LIVERTX ICU / CSICU | B39: 13000 | C39: 14500 | D39: =(C39-B39)/B39 -> 0.11538462 | E39: — | F39: — | G39: — | H39: — | I39: —
A40: PRIVATE ICU | B40: 21000 | C40: 23500 | D40: =(C40-B40)/B40 -> 0.11904762 | E40: — | F40: — | G40: — | H40: — | I40: —
A44: ANALYSIS 2 : Top 50 Revenue Procedures — Competitor Benchmarking & Repricing Impact
A45: Lakeshore rate card (PDN rate) for top 50 clinical procedures by FY26 revenue. Competitor rates estimated from room tariff premium patterns. Cleaned list: excludes diet, bystander, oxygen, CSSD, equipment, anaesthetist, MRD, registration.
A47: # | B47: Procedure | C47: Group | D47: FY26 Rev (₹L) | E47: Qty | F47: Lakeshore Rate (₹) | G47: Aster (est.) | H47: Rajagiri (est.) | I47: Welcare (est.) | J47: Proposed Rate (₹) | K47: Hike % | L47: Annual Impact (₹L)
A48: 1 | B48: PET CT WHOLE BODY SCAN | C48: PET CT | D48: 355 | E48: 1846 | F48: 19000 | G48: 23750 | H48: 18050 | I48: 15200 | J48: =ROUND((F48+MAX(G48,H48,I48))/2,0) -> 21375 | K48: =(J48-F48)/F48 -> 0.125 | L48: =(J48-F48)*E48/100000 -> 43.8425
A49: 2 | B49: 2 D ECHO WITH COLOR DOPLER | C49: CARDIOLOGY | D49: 333 | E49: 16375 | F49: 2040 | G49: 2448 | H49: 1938 | I49: 1734 | J49: =ROUND((F49+MAX(G49,H49,I49))/2,0) -> 2244 | K49: =(J49-F49)/F49 -> 0.1 | L49: =(J49-F49)*E49/100000 -> 33.405
A50: 3 | B50: LIVER FUNCTION TEST | C50: BIOCHEMISTRY | D50: 329 | E50: 37375 | F50: 810 | G50: 931 | H50: 770 | I50: 689 | J50: =ROUND((F50+MAX(G50,H50,I50))/2,0) -> 871 | K50: =(J50-F50)/F50 -> 0.075308642 | L50: =(J50-F50)*E50/100000 -> 22.79875
A51: 4 | B51: HEMODIALYSIS | C51: NEPHROLOGY | D51: 287 | E51: 18803 | F51: 1440 | G51: 1584 | H51: 1368 | I51: 1296 | J51: =ROUND((F51+MAX(G51,H51,I51))/2,0) -> 1512 | K51: =(J51-F51)/F51 -> 0.05 | L51: =(J51-F51)*E51/100000 -> 13.53816
A52: 5 | B52: RFT | C52: BIOCHEMISTRY | D52: 264 | E52: 78254 | F52: 290 | G52: 334 | H52: 276 | I52: 247 | J52: =ROUND((F52+MAX(G52,H52,I52))/2,0) -> 312 | K52: =(J52-F52)/F52 -> 0.075862069 | L52: =(J52-F52)*E52/100000 -> 17.21588
A53: 6 | B53: BLOOD SUGAR (GLUCOMETER- W/OUT STRIP) | C53: BIOCHEMISTRY | D53: 242 | E53: 171088 | F53: 110 | G53: 126 | H53: 105 | I53: 94 | J53: =ROUND((F53+MAX(G53,H53,I53))/2,0) -> 118 | K53: =(J53-F53)/F53 -> 0.072727273 | L53: =(J53-F53)*E53/100000 -> 13.68704
A54: 7 | B54: US ABDOMEN | C54: ULTRASOUND | D54: 239 | E54: 21531 | F54: 1250 | G54: 1563 | H54: 1188 | I54: 1000 | J54: =ROUND((F54+MAX(G54,H54,I54))/2,0) -> 1407 | K54: =(J54-F54)/F54 -> 0.1256 | L54: =(J54-F54)*E54/100000 -> 33.80367
A55: 8 | B55: PTCA (PERCUTANEOUS TRANSLUMINAL CORONARY ANGIOPLASTY) | C55: INTERVENTIONAL CARDIOLOGY | D55: 217 | E55: 272 | F55: 99710 | G55: 129623 | H55: 99710 | I55: 84754 | J55: =ROUND((F55+MAX(G55,H55,I55))/2,0) -> 114667 | K55: =(J55-F55)/F55 -> 0.15000501 | L55: =(J55-F55)*E55/100000 -> 40.68304
A56: 9 | B56: MRI BRAIN | C56: M R I | D56: 201 | E56: 1974 | F56: 9500 | G56: 11875 | H56: 9025 | I56: 7600 | J56: =ROUND((F56+MAX(G56,H56,I56))/2,0) -> 10688 | K56: =(J56-F56)/F56 -> 0.12505263 | L56: =(J56-F56)*E56/100000 -> 23.45112
A57: 10 | B57: RADICAL RT PER FRACTION | C57: TELETHERAPY | D57: 172 | E57: 4420 | F57: 4000 | G57: 4800 | H57: 4000 | I57: 3400 | J57: =ROUND((F57+MAX(G57,H57,I57))/2,0) -> 4400 | K57: =(J57-F57)/F57 -> 0.1 | L57: =(J57-F57)*E57/100000 -> 17.68
A58: 11 | B58: TAC - LEVEL | C58: BIOCHEMISTRY | D58: 172 | E58: 4489 | F58: 3540 | G58: 4071 | H58: 3363 | I58: 3009 | J58: =ROUND((F58+MAX(G58,H58,I58))/2,0) -> 3806 | K58: =(J58-F58)/F58 -> 0.075141243 | L58: =(J58-F58)*E58/100000 -> 11.94074
A59: 12 | B59: C-REACTIVE PROTEIN / CRP | C59: MICROBIOLOGY | D59: 159 | E59: 26048 | F59: 560 | G59: 644 | H59: 532 | I59: 476 | J59: =ROUND((F59+MAX(G59,H59,I59))/2,0) -> 602 | K59: =(J59-F59)/F59 -> 0.075 | L59: =(J59-F59)*E59/100000 -> 10.94016
... A97: 50 | B97: TFT | C97: BIOCHEMISTRY | D97: 56 | E97: 3323 | F97: 950 | G97: 1093 | H97: 903 | I97: 808 | J97: =ROUND((F97+MAX(G97,H97,I97))/2,0) -> 1022 | K97: =(J97-F97)/F97 -> 0.075789474 | L97: =(J97-F97)*E97/100000 -> 2.39256
I98: TOTAL | L98: =SUM(L48:L97) -> 607.6586
A99: ESTIMATION METHODOLOGY
A100: Competitor procedure rates are ESTIMATES derived from room tariff premium patterns (Analysis 1). Category-specific multipliers: Labs ×1.15, Imaging ×1.25, Interventional ×1.30, Dialysis ×1.10 (Aster); Rajagiri ×0.95–1.0; Welcare ×0.80–0.90. Validated: Aster PET CT est ₹23,750 matches Vaidam range ₹22–30K. Replace with actual competitor rates from TPA sheets when available.
A101: COMBINED RATE REVISION IMPACT — FY27
A103: Component | B103: Estimated Impact | D103: Basis
A104: Room & Nursing tariff hike (cash patients) | B104: ₹3.5 Cr | D104: 35–45% cash share × 12% avg increase × 11 months (conservative estimate)
A105: Procedure repricing (top 50 by revenue) | B105: ₹6.1 Cr | D105: Hike to midpoint of Lakeshore & highest competitor
A106: TOTAL | B106: ₹9.6 Cr
A108: Proposed rates (blue) are conservative — midpoint between current Lakeshore rate and highest of 3 competitor estimates. All quantities are FY26 actual volumes; impact assumes no volume loss from repricing. Competitor estimates derived from room tariff premium patterns — see Estimation Methodology.

Sheet R-02
A1: R-02 | Procedure Contribution Framework
A2: Revenue — Pricing & Yield | H2: 0.03 | I2: 0.05 | J2: 0.07 | K2: 0.09 | L2: 0.11 | M2: 0.13 | N2: 0.15 | O2: 0.17 | P2: 0.2 | Q2: =SUM(H2:P2) -> 1
A3: OVERVIEW | D3: YTD | E3: Apr | F3: May | G3: Jun | H3: Jul | I3: Aug | J3: Sep | K3: Oct | L3: Nov | M3: Dec | N3: Jan | O3: Feb | P3: Mar
A4: Description / Objective | B4: Launch a contribution framework for all IP procedures — for both cash and insurance patients. Cost out top 50 procedures by revenue: include doctor fees, team costs (OT staff, anaesthesia, nursing), consumables, and overhead allocation per procedure. Identify low-contribution procedures (<50% contribution). Reprice cash rates and flag insurer tariff renegotiation list. Target: 58% average contribution for 26% EBITDA. This is a per-procedure P&L that reveals which services make money and which don't after fully loading doctor and team costs. | C4: Rev Impact overall by bringing cost measurements | D4: 25000000 | E4: 0 | F4: 0 | G4: 0 | H4: =+H$2*$D$4 -> 750000 | I4: =+I$2*$D$4 -> 1250000 | J4: =+J$2*$D$4 -> 1750000 | K4: =+K$2*$D$4 -> 2250000 | L4: =+L$2*$D$4 -> 2750000 | M4: =+M$2*$D$4 -> 3250000 | N4: =+N$2*$D$4 -> 3750000 | O4: =+O$2*$D$4 -> 4250000 | P4: =+P$2*$D$4 -> 5000000
A5: Start Month | B5: 46113 | C5: Cost Impact for the above
A6: Estimated Cost | B6: ₹1.5L one-time (costing consultant or internal CFO + pharmacy time) | C6: Costing Consultant | D6: =+SUM(E6:P6) -> 1650000 | F6: 150000 | G6: 150000 | H6: 150000 | I6: 150000 | J6: 150000 | K6: 150000 | L6: 150000 | M6: 150000 | N6: 150000 | O6: 150000 | P6: 150000
A7: Expected Impact | B7: ₹2.5 Cr | C7: Costing Staff
A9: BASIS FOR THIS INITIATIVE
A10: Current pricing is set without systematic visibility into per-procedure profitability. A contribution framework reveals per-procedure P&L after fully loading doctor fees, team costs, consumables, and overhead. IMPACT BUILD-UP (₹2.5 Cr conservative): (A) Cash rate correction (top 25 procedures): • Build per-procedure P&L for top 50 revenue procedures • Identify cash-patient procedures where current rate sits below competitive benchmark and contribution floor • Cardiology (PTCA + Coronary Angiography): largest single opportunity • Achievable rate correction on cash patients: ~60% of identified opportunity (rest constrained by market pricing / volume elasticity) • Estimated recovery: ₹2 Cr (B) Contribution-based repricing (low-margin procedures): • Target: identify procedures below 50% contribution after full cost loading • Reprice or restructure bottom 20 procedures → estimated ₹50L incremental Total conservative: ₹2 Cr (cash rate correction) + ₹0.5 Cr (contribution repricing) = ₹2.5 Cr
A11: EXECUTION TRACKING (to be completed)
A12: Owner | B12: CFO / Operations Manager
A13: Key Milestones / Actions | B13: 1. Build per-procedure P&L for top 50 procedures: include doctor fees, OT team costs, consumables, overhead allocation by Jul-26 2. Identify all procedures below 50% contribution margin — reprice or discontinue by Aug-26 3. Cardiology: PTCA and Coronary Angiography to be reviewed with department head 4. Lab/Biochemistry: review rate card — bulk revision through LIS update by Jun-26 5. MRI/Ultrasound: review radiology tariff card by Jun-26 6. Flag insurance-specific procedures for R-03 tariff renegotiation 7. Target: 58% average contribution for 26% EBITDA
A14: Risks / Dependencies | B14: 1. Doctor fee data is sensitive and may face resistance from Finance/HR in sharing 2. Some surgeons may resist transparency on per-procedure profitability 3. Contribution analysis depends on accurate consumable BOQ data (C-05 must deliver) 4. Repricing low-contribution insured procedures requires TPA renegotiation (R-03 dependency) 5. Risk of volume loss if cash prices are raised too aggressively on price-sensitive procedures
A15: Remarks | B15: Contribution framework is the analytical foundation for downstream pricing decisions. Feeds R-03 (insurance renegotiation priority list) and informs R-10 (new package design).
A16: Bequip Remarks | B16: Intrduce back the Billing Department wise and the Procedure Department wise P&L with maximum cost allcoation to direct, allocated and absorbed costs
A17: Bequip Remarks | B17: 1. Cost Consultant 1 time cost seems to be low, either have an in house staff 2. need to work out department PL of top 15 and bottom 15 and renegotiate the doctor payouts, low fixed pay and high variable pay, also sensitise the doctor and the administrative representative of the need to focus on procedures that we list, OP to IP ocnversion and Lab and Radiology counts that we propose.

Sheet R-03
A1: R-03 | Insurance Renegotiation & Empanelment
A2: Revenue — Pricing & Yield
A3: OVERVIEW
A4: Description / Objective | B4: Three-pronged insurance revenue initiative: (A) Charge Capture Audit: Audit current insurance bills against TPA tariff schedules. Identify covered items (nursing charges, monitoring, clinical charges, physiotherapy, ICU charges) not systematically billed. Fix charge master. Train nursing on charge initiation. (B) TPA/Insurer Tariff Renegotiation: Formal annual tariff revision with all empanelled TPAs and insurers. Most agreements not revised in 2–3 years while costs rose 12–15%. Leverage volume and case complexity data. Target: 8–12% rate improvement. (C) Competitive Empanelment Analysis: Compare insurer MoU package/reimbursement rates. Top 50 procedures by value. Identify which schemes/insurers competitors (Aster, Rajagiri, KIMS) have that we don’t. Recommend new empanelments with incremental revenue impact.
A5: Start Month | B5: 46113
A6: Estimated Cost | B6: ₹4L one-time (billing audit + legal + data prep; internal CFO time)
A7: Expected Impact | B7: ₹9 Cr
A9: BASIS FOR THIS INITIATIVE
A10: Multiple billable line items are covered under standard TPA tariffs but not raised due to charge master gaps or nursing documentation failures. Simultaneously, TPA/insurer rates have not been renegotiated in 2–3 years while costs rose 12–15%. IMPACT BUILD-UP (₹9 Cr conservative): (A) Charge Capture — ₹3 Cr: • Insurance IP admissions: ~12,000/yr • Avg missed billable items per admission: ₹2,500 (nursing charges, monitoring, physio, clinical charges) • Recovery: 12,000 × ₹2,500 = ₹3 Cr (B) TPA Tariff Renegotiation — ₹4 Cr: • Current insurance IP revenue: ~₹160 Cr/yr (est. 40% of ₹399 Cr total IP) • Target rate increase: 8–12% across empanelled TPAs (most agreements 2–3 yrs old) • Conservative 2.5% effective blended increase (some TPAs will resist): ₹160 Cr × 2.5% = ₹4 Cr (C) New Empanelments (gap insurers from comparison table) — ₹2 Cr: • 10 gap insurers identified (Star Health, Go Digit, Navi, SBI General, etc.) • Avg incremental volume per new empanelment: 100 IP cases/yr × ₹1.5L avg ticket • 10 insurers × 100 cases × ₹1.5L = ₹1.5 Cr, rounded to ₹2 Cr with OP Total: ₹3 + ₹4 + ₹2 = ₹9 Cr
A11: EXECUTION TRACKING (to be completed)
A12: Owner | B12: CFO / Head Insurance & TPA
A13: Key Milestones / Actions | B13: 1. Audit 50 representative IP bills against TPA tariff schedules for missing items by May-26 2. Update charge master with all covered-but-unbilled items by Jun-26 3. Train nursing on charge initiation protocols (monitoring, physio, ICU charges) by Jun-26 4. Compile insurer-wise tariff comparison matrix — top 50 procedures by value by Jun-26 5. Identify which insurers/schemes Aster, Rajagiri, KIMS have that we don’t by Jun-26 6. Submit formal tariff revision requests to top 10 TPAs by Jul-26 (target: 8–12% improvement) 7. Prepare new empanelment applications for identified gaps by Aug-26 8. Track charge capture uplift monthly from Jul-26
A14: Risks / Dependencies | B14: 1. TPA tariff renegotiation has 60–90 day contract cycle lag 2. Some TPAs may push back or threaten delisting — need volume data to negotiate from strength 3. New empanelments take 3–6 months for processing 4. Charge master update requires IT + billing coordination
A15: Remarks | B15: This is the single largest revenue opportunity after rate revision. Combines charge capture (immediate), tariff renegotiation (medium-term), and new empanelments (strategic). Feeds from R-02 contribution framework data for evidence-based renegotiation.
A17: COMPETITOR EMPANELMENT ANALYSIS
A18: Source: Hospital websites (asterhospitals.in, vpslakeshorehospital.com, kimshospitals.com). Lists are dynamic — confirm with Insurance Help Desk before acting.
A20: Insurer / TPA | B20: VPS Lakeshore | C20: Aster Medcity | D20: KIMS | E20: Action
A21: Aditya Birla Health Insurance | B21: — | C21: ✓ | D21: ✓ | E21: Pursue — large retail insurer, growing Kerala presence
A22: SBI General Insurance | B22: — | C22: ✓ | D22: ? | E22: Pursue — PSU bank-linked, high volume potential
A23: TATA AIG General Insurance | B23: — | C23: ✓ | D23: ? | E23: Pursue — major corporate insurer
A24: Go Digit General Insurance | B24: — | C24: ✓ | D24: ? | E24: Pursue — fast-growing digital-first insurer
A25: Navi General Insurance | B25: — | C25: ✓ | D25: ? | E25: Pursue — digital insurer, younger demographics
A26: Niva Bupa Health Insurance | B26: — | C26: ✓ | D26: ? | E26: Pursue — standalone health insurer, high claim volumes
A27: Star Health & Allied Insurance | B27: — | C27: ✓ | D27: ? | E27: High priority — India's largest standalone health insurer
A28: Liberty General Insurance | B28: — | C28: ✓ | D28: ? | E28: Evaluate — niche but growing
A29: Galaxy Health Insurance | B29: — | C29: ✓ | D29: ? | E29: Evaluate — TPA with growing network
A30: Volo Health / East West Assist | B30: — | C30: ✓ | D30: ? | E30: Evaluate — TPA serving multiple insurers
A32: INTERNATIONAL INSURANCE GAPS
A33: Aster Medcity has 14 international insurers (Gulf + Maldives) that VPS Lakeshore likely lacks. Key gaps:
A34: Aasandha Insurance (Maldives), Allied Insurance (Maldives), Amana Takaful (Maldives), Daman Insurance (UAE), Almadalla (UAE), Alkoot (Qatar), Dubai Insurance Co, NowHealth, MSH Insurance, NLGI, Union Insurance, Health 360, Dar-Takaful, Allianz International
A35: VPS Lakeshore benefits from VPS Healthcare group presence in UAE/Oman. Internal VPS referral pathways may already exist outside formal insurance empanelment. International patient cell to confirm which Gulf/Maldives insurers are currently active.

Sheet R-04
A1: R-04 | Distributed Healthcare Network (DHCN)
A2: Revenue — Network Expansion
A3: OVERVIEW
A4: Description / Objective | B4: Deploy two network prototypes across Kerala: (A) Satellite Clinics (Prototype 4 — Partner Hospital model): Dedicated Lakeshore-branded floor or wing within partner hospitals (MBMMH Kothamangalam, Malankara Mission Kunnamkulam, VPS Calicut), with VPS clinical staff, protocols, and full EMR integration. Phase 1 target: 10 satellite clinic locations across Kerala. (B) Risk Assessment Centres (Prototype 5 — RAC): Structured risk-assessment and triage stations at high-footfall locations. 5-cancer screening (oral, breast, cervical, colorectal, lung), cardiac/metabolic risk profiling, genomic risk assessment. Phase 1 target: 25 RAC stations. All nodes funnel diagnosed/complex cases to Lakeshore Kochi for surgery, radiation, transplant, and complex chemotherapy. Revenue share models define economics at each node. Oncology hub-and-spoke (screening → Lakeshore radiation/surgery) is a core use case within this network.
A5: Start Month | B5: 46143
A6: Estimated Cost | B6: ₹65L/yr (10 satellite clinics fit-out + 25 RAC stations + oncology consultant travel + partner MOUs + admin)
A7: Expected Impact | B7: ₹13 Cr
A9: BASIS FOR THIS INITIATIVE
A10: Over 60% of Lakeshore’s addressable catchment lives beyond 20km. Patients in Thrissur, Muvattupuzha, and North Ernakulam default to local hospitals because the first consult is inconvenient. A weekly surgeon-run OPD brings Lakeshore’s clinical brand to the patient. IP referral back to main campus is the primary financial lever. PHASED REVENUE MODEL (Year 1, conservative): Satellite Clinics (10 locations, phased: 2 in Q1, +3 in Q2, +3 in Q3, +2 in Q4): • Per clinic at steady state: 30 consults/wk → 10% IP conversion = 3 admissions/wk × ₹1.5L avg ticket = ₹4.5L/wk gross • After partner revenue share and ramp-up: net ₹2.7L/wk per clinic • Utilisation ramp: Q1 50%, Q2 65%, Q3 80%, Q4 90% • Q1: 2 clinics × ₹1.4L/wk × 13 wks = ₹35L • Q2: 5 clinics × ₹1.8L/wk × 13 wks = ₹114L • Q3: 8 clinics × ₹2.2L/wk × 13 wks = ₹224L • Q4: 10 clinics × ₹2.4L/wk × 13 wks = ₹316L • Clinic Year 1 total: ₹689L = ₹6.9 Cr RAC Stations (25 locations, phased: 0 in Q1, 5 in Q2, +5 in Q3, +15 in Q4): • Per RAC at steady state: 60 screens/wk × ₹1,500 = ₹0.9L/wk screening + 1 IP referral/wk × ₹2L = ₹2L/wk → total ₹2.9L/wk gross • After ramp-up: net ₹1.6L/wk per RAC • Utilisation ramp: Q2 50%, Q3 65%, Q4 80% • Q1: 0 RACs = ₹0 • Q2: 5 RACs × ₹0.8L/wk × 13 wks = ₹52L • Q3: 10 RACs × ₹1.0L/wk × 13 wks = ₹135L • Q4: 25 RACs × ₹1.3L/wk × 13 wks = ₹416L • RAC Year 1 total: ₹603L = ₹6.0 Cr Total Year 1 conservative: ₹6.9 + ₹6.0 = ₹12.9 Cr ≈ ₹13 Cr (heavily weighted to H2 as network matures)
A11: EXECUTION TRACKING (to be completed)
A12: Owner | B12: Head BD / Head of DHCN
A13: Key Milestones / Actions | B13: 1. Finalise MOUs with 3 existing partner hospitals (Kothamangalam, Kunnamkulam, Calicut) by May-26 2. Identify 7 additional satellite locations — Thrissur, Muvattupuzha, Perumbavoor, Angamaly, Aluva, Thodupuzha, Palakkad by Jun-26 3. Build per-location financial model: lease + fit-out + 2 consultants/wk + admin = break-even at ~40 consults/week 4. RAC pilot at Kochi campus (Jul-26), then MBMMH & Calicut (Aug–Sep-26), then suburban roll-out 5. Analyse doctor OP consult data to identify surgeons with spare OPD capacity for satellite deployment 6. Define revenue share model per prototype: satellite = Lakeshore 70%/Partner 30% vs RAC = Lakeshore retains screening revenue, referral conversion = main campus revenue 7. Project referral revenue: 10 clinics × 40 consults/wk × 15% IP conversion × ₹2L avg ticket = ₹62L/yr conservative; 25 RACs × 100 screens/wk × 5% positive × ₹3L avg = ₹19.5L/yr 8. Phase 2 targets: scale to 25 clinics + 50 RACs by FY28
A14: Risks / Dependencies | B14: 1. Partner hospital clinical standards may not match Lakeshore protocols — clinical audit required before co-branding 2. RAC regulatory clearance required for screening equipment at non-hospital locations 3. Satellite OPD days reduce surgeon availability at main campus — scheduling discipline required 4. EMR integration with partner hospitals requires IT investment (₹5–10L per site) 5. Break-even at <40 consults/week is achievable only in high-density catchments
A15: Remarks | B15: Hub-and-spoke model: satellite clinics and RACs serve as referral funnels to the Kochi main campus. Partner MOU quality should take precedence over clinic count; prioritise locations with limited existing tertiary access. Dependencies: R-09 (BD referral programme) for partner doctor onboarding and R-12 (new specialties) for onco/cardiac referral capture.

Sheet R-05
A1: R-05 | Corporate Health Programme
A2: Revenue — Network Expansion
A3: OVERVIEW
A4: Description / Objective | B4: Build a structured corporate health programme targeting top 50 corporates (PSU + private) within 20km of Kochi campus. Tiered offering: (a) Executive Health Check packages — cardiac, oncology, and metabolic risk profiling; (b) Company insurance tie-ups — negotiate group mediclaim with preferential IP rates; (c) On-premises multispecialty OP clinics — deploy VPS consultants to corporate campuses for weekly/fortnightly clinics. Deduplicate against existing corporate accounts to avoid channel conflict. Assign 2 dedicated corporate relationship managers. Track conversion: health check → OPD follow-up → IP admission.
A5: Start Month | B5: 46143
A6: Estimated Cost | B6: ₹17L/yr (2 corporate RMs + package design + billing desk)
A7: Expected Impact | B7: ₹5 Cr
A9: BASIS FOR THIS INITIATIVE
A10: Corporate volumes are captive, predictable, and have very low acquisition cost once contracted. Kochi's industrial and IT belt represents 100,000+ covered lives within 15km. Anchor accounts (BPCL, Cochin Port, FACT alone = ~15,000 employees) can seed significant IP volume through health check conversions. TARGET CORPORATE LIST (Top 50, representative): PSU (15): BPCL Kochi Refinery (~4,500), Cochin Shipyard (~3,000), FACT (~2,500), Cochin Port Trust (~2,000), KSEB Ernakulam (~1,500), Naval Base Kochi (~3,000), Southern Air Command, HMT, BHEL, CIAL, Kochi Metro Rail, KITCO, BSNL, FCI, LIC Regional IT/ITES (20): TCS Infopark (~5,000), Wipro, Cognizant, UST Global (~3,500), IBS Software (~2,000), QBurst (~2,000), Ernst & Young GDS, NeST, NIC, Envestnet, Nissan Digital Hub, SunTec, Litmus7, TechM, HCL, Fingent, Baker Hughes, Teleperformance, Byju's, Muthoot Private/MNC (15): Federal Bank, South Indian Bank, Muthoot Finance, GCDA, Lulu Group, Le Meridien/Marriott/Taj, V-Guard, Kitex, Nitta Gelatin, Synthite, SFO Technologies, Century Metal, Geojit, Manorama, Asianet REVENUE BASIS (₹5 Cr conservative): • Target: 25 signed corporates in Year 1 (50% of target list) • Executive health checks: 25 cos × 200 avg employees screened × ₹5,000 avg package = ₹2.5 Cr • IP conversion from health checks: 3% positive finding rate × 5,000 screened × ₹1.5L avg ticket = ₹2.25 Cr • On-premises OP clinics: 10 active clients × 50 consults/mo × ₹500 × 12 mo = ₹3L = ~₹30L • Total: ~₹5 Cr
A11: EXECUTION TRACKING (to be completed)
A12: Owner | B12: Head BD / Corporate Marketing team
A13: Key Milestones / Actions | B13: 1. Compile target list of top 50 corporates with employee strength, current health partner, and insurance status by May-26 2. Audit existing 20 corporate accounts — revenue per account, services used, upsell potential by May-26 3. Design 3-tier health check packages (Basic ₹3,500 / Premium ₹8,000 / Executive ₹15,000) by Jun-26 4. Pilot on-premises OP clinic at 3 anchor corporates (1 IT, 1 PSU, 1 hospitality) by Jul-26 5. Assign 2 dedicated corporate RMs — target 15 new accounts in Year 1 6. Build conversion tracking: health check → abnormal finding → OPD follow-up → IP admission 7. Target: 5,000 health checks Year 1 × ₹8,000 avg = ₹4 Cr direct; 8% IP conversion × ₹2L avg = ₹8 Cr indirect
A14: Risks / Dependencies | B14: 1. On-premises clinics require regulatory clearance for off-site consultations 2. Corporate decision cycles typically run 3–6 months, tied to annual budget planning 3. Established corporate sales teams at Aster and existing PSU relationships at AIMS present competitive resistance 4. Health check package pricing must be competitive against standalone diagnostic centres (SRL, Metropolis) 5. Insurance tie-ups depend on TPA cooperation (dependency on R-03)
A15: Remarks | B15: Health check volume is the funnel metric; IP conversion is the revenue metric. Target ratio: ₹5–8 of downstream IP revenue for every ₹1 of health check fee. Suggested sequencing: secure 3–5 PSU/IT anchor accounts first to support reference-based selling. Dependencies: R-03 (corporate TPAs) and R-09 (Corporate-Residential RM team).

Sheet R-06
A1: R-06 | Residential & Community Outreach
A2: Revenue — Network Expansion
A3: OVERVIEW
A4: Description / Objective | B4: Partner with major gated communities and apartment complexes within 15km (Sobha, Prestige, Purva in Kakkanad, Edapally, Thrippunithura) for on-site health camps, resident doctor visits, and emergency response agreements. Handled by dedicated corporate/residential team within BD organisation. Includes community health camps: two monthly health awareness programmes in schools (adolescent health, vision, nutrition), temples and mosques (senior citizen camps, post-Ramadan diabetes/cardiac screening), and residential complexes. Low cost, high community trust. | F4: Apr | G4: May | H4: Jun | I4: Jul | J4: Aug | K4: Sep | L4: Oct | M4: Nov | N4: Dec | O4: Jan | P4: Feb | Q4: Mar
A5: Start Month | B5: 46143 | H5: 3000000 | K5: 3000000 | N5: 3000000 | Q5: 3000000
A6: Estimated Cost | B6: ₹30L/yr (logistics, portable diagnostic equipment, community coordinator + camp logistics)
A7: Expected Impact | B7: ₹3 Cr
A9: BASIS FOR THIS INITIATIVE
A10: Gated communities represent high-income, high-compliance patient segments. Emergency tie-ups create first-call advantage. Health camps drive diagnostics, OPD footfall, and early detection conversions. Acquisition cost is far lower than digital advertising for this segment. TARGET RESIDENTIAL COMMUNITIES (20+, within 15km): Kakkanad: DLF New Town Heights (~1,200 units), Prestige Hillside Gateway (~800), Joyalukkas Gold Tower (~400), Confident Group properties, Mather projects Edapally: SFS Grandville (~600 units), Skyline Apartments, Asset Homes projects, Desai Homes DD Kings Square/Queens Square Thrippunithura: Sobha projects (~500 units), Purva Eternity Maradu/Nettoor: Waterfront communities (proximity to Lakeshore), DD Sunset Island Aluva: CIAL township housing, Rajagiri Valley Other: Panangad communities, Vyttila premium apartments, Marine Drive high-rises Total addressable: ~8,000–10,000 households = 25,000–30,000 residents REVENUE BASIS (₹3 Cr conservative): • Target: 15 active community partnerships in Year 1 • Health camps: 15 communities × 4 camps/yr × 200 screens/camp × ₹2,000 avg = ₹2.4 Cr • Emergency response tie-ups: 15 communities × ~5 emergency transfers/yr × ₹2L avg IP ticket = ₹1.5 Cr (but discounted for overlap) • OPD follow-up from camps: 10% of 12,000 screened = 1,200 OPD visits × ₹1,500 = ₹18L • Conservative total (camps + follow-up + emergency): ~₹3 Cr
A11: EXECUTION TRACKING (to be completed)
A12: Owner | B12: Head BD / Community Health Coordinator / Corporate-Residential RM team
A13: Key Milestones / Actions | B13: 1. Map all gated communities >200 units within 15km — with RWA contact, population estimate by May-26 2. Design 3 camp formats: (a) Senior wellness, (b) Women's health, (c) General screening — standardised protocols 3. Pilot 4 camps in May–Jun-26: 1 school, 1 temple/mosque, 2 residential complexes 4. Negotiate emergency response MOUs with top 10 RWAs by Jun-26 (ambulance SLA, doctor-on-call) 5. Launch monthly camp calendar (4–6 camps/month) from Jul-26 onwards 6. Track camp → OPD → IP conversion funnel monthly 7. Target Year 1: 60 camps, 8,000 screenings, 800 OPD conversions, 120 IP admissions
A14: Risks / Dependencies | B14: 1. RWA cooperation varies; some associations restrict commercial health activities in common areas 2. Regulatory clearance required for portable diagnostic equipment at off-site locations 3. Overlap with R-04 community outreach in satellite clinic catchments — territory mapping required to avoid duplication 4. Consistent camp quality is required; a single substandard experience can affect brand perception across a community
A15: Remarks | B15: Targets the 15km catchment around the Kochi campus. Economics depend on rigorous IP conversion tracking (health check → abnormal finding → OPD → IP). Shares RM team with R-05. Patient data flows into R-15 (digital platform records). Emphasis on repeat engagement rather than one-off camps.

Sheet R-07
A1: R-07 | International Medical Value Travel
A2: Revenue — Referral Development
A3: OVERVIEW
A4: Description / Objective | B4: Expand medical value travel (MVT) beyond Middle East to all viable source markets for Kerala. Score countries on multi-parameter framework: flight connectivity to Kochi, diaspora size, healthcare gap vs local system, insurance/reimbursement coverage, competitor presence , and VPS Healthcare group synergies (Abu Dhabi, Oman network). Map the ecosystem: HCF agents/agencies, embassy health attachés, corporate medical evacuation contracts, international insurance TPAs. Build online reputation in recommended countries: Google Business profiles in Arabic/Bengali/Dhivehi, Practo international, hospital aggregator listings (Medical Departures, Bookimed, Vaidam). Target 200+ MVT patients Year 1, scaling to 500 by Year 3. CLINICAL REFERRAL PARTNERSHIPS: Sign clinical referral MOUs with 2–3 Maldives hospitals and 2 Gulf hospitals. Telemedicine protocol for pre-visit assessment. Joint case reviews.
A5: Start Month | B5: 46143
A6: Estimated Cost | B6: ₹25L/yr (MVT coordinator + content + aggregator onboarding)
A7: Expected Impact | B7: ₹6 Cr
A9: BASIS FOR THIS INITIATIVE
A10: Lakeshore is already on the Kerala Medical Value Travel Society registry and has multilingual staff and international patient services — the infrastructure exists. MVT patients have 3–5× higher ARPOB than domestic IP. Gulf demand for cardiac, orthopaedic, and transplant services is structurally strong due to limited local tertiary capacity in Tier-2 GCC cities. COMPETITOR INTERNATIONAL PRESENCE: • Aster Medcity: Strongest position — parent VPS Healthcare operates 14 hospitals in UAE/Oman/Bahrain. Has 14 international insurance partners (Daman, Aasandha-Maldives, Allied-Maldives, Alkoot, Allianz, Almadalla, Amana Takaful, Dubai Insurance, Health 360, MSH, NLGI, NowHealth, Union Insurance, Dar-Takaful). Direct referral pipeline from group hospitals. • KIMS Health: Majority of international patients from GCC countries. Has international patient services in Trivandrum and coordinates patients from 50+ countries. • Amrita (AIMS): Airport help desk at CIAL for international arrivals. Partnership with 60+ medical entities in US, Canada, Europe. Faculty exchange with 30+ countries. • Rajagiri: JCI accredited. International Patient Care Helpdesk. Accepts foreign currency, wire transfers, embassy sponsorship. SOURCE MARKET PRIORITY (scoring: flight connectivity, diaspora size, healthcare gap, insurance coverage, VPS synergy): Tier 1: UAE, Saudi Arabia, Oman, Maldives (direct flights, VPS Group presence, established insurance pathways) Tier 2: Kuwait, Bahrain, Qatar (growing demand, limited direct flights) Tier 3: Bangladesh, East Africa (high healthcare gap, growing medical tourism, limited competition)
A11: EXECUTION TRACKING (to be completed)
A12: Owner | B12: Head BD / MVT Coordinator (to hire) / International Patient Services
A13: Key Milestones / Actions | B13: 1. Complete multi-parameter source market scoring by May-26 — rank top 10 countries by opportunity 2. Map competitor international offices and aggregator partnerships by May-26 3. Hire dedicated MVT Coordinator (bilingual Arabic/English preferred) by Jun-26 4. Apply for Maldives Aasandha empanelment by Jun-26 5. Onboard with 3 international aggregators (Vaidam, Medical Departures, Bookimed) by Jul-26 6. Develop Arabic + Bengali digital content: website landing pages, Google Business, video testimonials by Jul-26 7. Attend 2 international health tourism conferences (Arab Health, MERCY Malaysia) in FY27 8. Establish referral corridor with VPS Healthcare Abu Dhabi/Oman — reciprocal patient transfer protocol by Aug-26 9. Target: 200 MVT patients Year 1 × ₹3L avg ticket = ₹6 Cr conservative; 500 patients by Year 3 10.
A14: Risks / Dependencies | B14: 1. Maldives Aasandha empanelment is a 6–12 month bureaucratic process 2. Gulf patients often have employer-directed hospital choices — corporate-level MOUs with major Gulf employers are required 3. VPS group internal referral dynamics: Abu Dhabi facilities may prioritise retaining patients locally 4. Aggregator commission rates of 15–25% compress net margins 5. Visa facilitation and medical visa processing delays affect Bangladesh and African source markets
A15: Remarks | B15: VPS Healthcare group presence in UAE and Oman provides existing internal referral pathways that are currently under-utilised. Suggested sequencing: Gulf markets first (group leverage), followed by CIS and Maldives (existing Kerala corridor), with African markets as a longer-horizon step. The MVT Coordinator hire is a prerequisite for aggregator empanelment execution.

Sheet R-08
A1: R-08 | Government Scheme Empanelment Optimisation
A2: Revenue — Referral Development
A3: OVERVIEW
A4: Description / Objective | B4: Review PMJAY, KASP, CGHS, ECHS, and ESI empanelments — kept separate from insurance (R-03). Ensure all eligible complex procedures (transplant, cardiac interventions, cancer treatments) are listed. Renegotiate rates for high-volume procedures. Assess feasibility of each scheme — PMJAY may not be viable at current rates; CGHS/ECHS are typically positive margin. Recommend new empanelments with incremental revenue impact. Assign dedicated scheme coordinator.
A5: Start Month | B5: 46143
A6: Estimated Cost | B6: ₹6L/yr (dedicated scheme coordinator, 1 FTE)
A7: Expected Impact | B7: ₹3 Cr
A9: BASIS FOR THIS INITIATIVE
A10: Government schemes are volume-stable revenue streams. ECHS alone covers ~50,000 ex-servicemen families in Ernakulam district. CGHS covers central government employees. Each empanelment takes 3–6 months, so early start is critical. IMPACT BUILD-UP (₹3 Cr conservative): (A) Existing empanelments — rate revision + specialty expansion: ₹1.5 Cr • ECHS: currently empanelled but not all specialties listed. Adding transplant, oncology, cardiac surgery packages → ~200 additional cases/yr × ₹1.5L avg = ₹3 Cr gross, net incremental ~₹1 Cr • CGHS/ECHS rate revision (rates 3+ yrs old): 10% uplift on existing ~₹5 Cr scheme revenue = ₹50L (B) New empanelments — CGHS, ESI, MEDISEP: ₹1.5 Cr • CGHS (if not current): ~15,000 central govt employees in Ernakulam → est. 300 IP cases/yr × ₹1.2L avg = ₹3.6 Cr potential, conservative 20% market share = ₹72L • ESI: ~100,000 covered workers in Ernakulam district → est. 500 IP referrals/yr × ₹80K avg = ₹4 Cr potential, 10% share = ₹40L • MEDISEP (state employees): ~50,000 state govt staff → est. 200 IP cases/yr × ₹1L = ₹2 Cr potential, 15% share = ₹30L • Total new: ₹72L + ₹40L + ₹30L = ₹1.4 Cr, rounded to ₹1.5 Cr Total: ₹1.5 + ₹1.5 = ₹3 Cr SCHEME EMPANELMENT COMPARISON (Kochi hospitals): • ECHS: Aster ✓, KIMS ✓, Amrita ✓, Rajagiri ✓, Lakeshore ✓ — confirm all specialties listed • CGHS: Aster ✓, KIMS ✓, Amrita ✓, Rajagiri ✓, Lakeshore — status to be confirmed • PMJAY/KASP: Aster ✓, KIMS ✓, Amrita ✓ — Lakeshore feasibility depends on procedure-level rate adequacy • ESI: Aster ✓, Amrita ✓ — Lakeshore not currently empanelled • MEDISEP: Aster ✓ (select specialties), Lakeshore status to be confirmed • Railway Health: Amrita ✓ — Lakeshore not empanelled Competitor data is indicative based on publicly listed insurance/TPA panels. Insurance desk to complete with actual data by May-26.
A11: EXECUTION TRACKING (to be completed)
A12: Owner | B12: Head BD / Scheme Coordinator (1 FTE, to designate) / Insurance & TPA Head
A13: Key Milestones / Actions | B13: 1. Map all current empanelments — scheme, specialties covered, rate structure, last revision date by May-26 2. Compile competitor empanelment matrix — where are Aster, KIMS, AIMS, Rajagiri empanelled and not us by May-26 3. Shortlist 3-5 new empanelments with highest incremental revenue by Jun-26 4. Submit empanelment applications for shortlisted schemes by Jun-26 5. Renegotiate rates for ECHS and CGHS (top 20 procedures by volume) by Jul-26 6. Assess PMJAY viability: run breakeven analysis on top 10 PMJAY procedures at current rates by Jun-26 7. Assign dedicated scheme coordinator by May-26 8. Target: 2 new empanelments live by Sep-26; 3Cr incremental scheme revenue Year 1
A14: Risks / Dependencies | B14: 1. PMJAY rates may be below cost for several complex procedures — empanelment would attract volume at a loss 2. Government empanelment processes are bureaucratic — 3-6 month lag 3. Claims processing delays with government schemes can reach 90-180 days, impacting cash flow 4. Some schemes require dedicated infrastructure (e.g., ECHS counters)
A15: Remarks | B15: Scheme economics are fundamentally different from private insurance — volume-driven, rate-constrained, administratively heavy. Kept separate from R-03 (insurance) for this reason. The dedicated coordinator is critical; this cannot be a part-time add-on to existing TPA staff.

Sheet R-09
A1: R-09 | Scaled BD Organisation & Referral Programme
A2: Revenue — Referral Development
A3: OVERVIEW
A4: Description / Objective | B4: Expand to a full-spectrum BD function with three verticals: (A) Referral Development (3 zones — North/Central/South Kerala): Map all referring doctors within 50km by specialty and volume; classify A/B/C tiers; assign BD field executives to A-tier (top 100) with monthly visit cadence. Build registered community of 500+ referring doctors. Implement 24-hour discharge summary SOP as non-negotiable feedback loop. Revisit referral commission rates vs market. (B) Institutional & Partnerships: Corporate accounts (R-05), MVT (R-07), satellite clinics (R-04), government schemes (R-08). (C) Communications & Branding: CME calendar — monthly specialty-specific CMEs rotating across suburban/district locations (Thrissur, Kottayam, Alappuzha, Ernakulam suburbs). Appoint CME Coordinator (MBBS/BAMS/BDS, reports to Med Supt & Head BD). MCI accreditation. Digital CME platform (webinar + on-demand library). Innovative engagement: case-based discussions, tumour boards, masterclasses. Structured under BD Head reporting to CEO. 27-person organisation with distinct verticals.
A5: Start Month | B5: 46113
A6: Estimated Cost | B6: ₹3.5 Cr/yr total BD function (6 open roles + CRM + CME events + FE travel)
A7: Expected Impact | B7: ₹25 Cr
A9: BASIS FOR THIS INITIATIVE
A10: Revenue growth at the scale required by the transformation programme (₹100–200Cr over 3 years) cannot be delivered by a lean referral-focused team. A 27-person BD organisation with distinct verticals (referral, institutional, communications) mirrors the structure of peer hospitals generating 15–20% annual revenue growth. The BD org is the execution engine for multiple revenue initiatives: • R-04 (DHCN / Satellite Clinics): BD team manages partner hospital relationships and RAC site selection • R-05 (Corporate Health): Institutional BD vertical owns corporate account acquisition and health check contracting • R-06 (Residential Colony): Same institutional BD vertical manages RWA relationships and camp logistics • R-07 (International MVT): Dedicated MVT coordinator within BD handles HCF agents, insurance tie-ups, international marketing • R-08 (Govt Schemes): BD team drives empanelment applications and scheme coordinator role • R-14 (Events): Communications vertical organises quarterly events and CME calendar • R-15 (Patient Acquisition): Digital marketing and content platform sit under communications vertical Without the scaled BD org, initiatives R-04 through R-15 lack a dedicated execution team and revert to ad-hoc effort by clinical/admin staff.
A11: EXECUTION TRACKING (to be completed)
A12: Owner | B12: Head BD / CME Coordinator (to hire) / Medical Superintendent / CEO
A13: Key Milestones / Actions | B13: 1. Finalise BD org chart — 27 roles across 3 verticals; fill 6 open positions by Jun-26 2. Compile referral physician database — current active referrers + target list within 50km by May-26 3. Classify A/B/C tiers: A = top 100 by IP referral volume, B = next 200, C = all others 4. Recruit CME Coordinator per approved JD by Jun-26 5. Design annual CME calendar — 12 in-hospital + 6 outreach (Thrissur, Kottayam, Alappuzha) by Jun-26 6. Deploy CRM system for referral tracking (Salesforce Health or similar) by Jul-26 7. Mandate 24-hour discharge summary SOP — CNO + Medical Superintendent to enforce by May-26 8. Launch first CME and case-based discussion by Jul-26 9. Pilot digital CME platform (webinar + on-demand library) by Aug-26 10. Complete referral commission rate benchmarking vs competitors by Jun-26 11. Target: 500 registered referring doctors by Mar-27; 15% of new IP volume from tracked referrals
A14: Risks / Dependencies | B14: 1. MCI/NMC guidelines on referral fees — must be structured as professional fees, not volume-linked commissions 2. CME accreditation process with Kerala Medical Council takes 2–3 months lead time 3. CRM system integration with existing HMIS/billing for referral attribution 4. Consultant buy-in for discharge summary SOP — enforcement requires Medical Superintendent backing 5. BD org build-out depends on finding qualified candidates for 6 open roles — recruitment may take 3–6 months 6. Some referring doctors may be actively sending to competitors — need competitive intelligence on rival programmes
A15: Remarks | B15: Combines the Referral Physician Programme & CME scope with the broader BD Organisation build. References: JD Manager Medical Affairs (CME). The investment is ~3–4Cr — the return is a multiplier across every other revenue initiative. The LPMC New Block's capacity expansion makes a scaled BD organisation both necessary and viable.

Sheet R-10
A1: R-10 | OP-IP Conversion & Follow-Up
A2: Revenue — Referral Development
A3: OVERVIEW | H3: OP TO IP% | J3: Apr | K3: May | L3: Jun | M3: Jul | N3: Aug | O3: Sep | P3: Oct | Q3: Nov | R3: Dec | S3: Jan | T3: Feb | U3: Mar
A4: Description / Objective | B4: OP-to-IP conversion initiative with two tracks: (A) Surgical OPD Counselling: Deploy trained financial counsellors at surgical OPD (ortho, cardiac, neurosurgery, oncology, transplant). Explain package costs, initiate insurance pre-auth on day of consultation, arrange EMI/loan tie-ups for self-pay. (B) Follow-Up & Dropout Prevention: Analyse OP follow-up calls to curtail dropouts. Proactive actions: appointment reminders, post-consult callbacks within 48 hours, treatment plan adherence tracking, lapsed patient re-engagement campaigns. | E4: Manpower Cost
A5: Start Month | B5: 46143 | E5: 4 financial counsellors @ 35000 | J5: =35000*4 -> 140000 | K5: =35000*4 -> 140000 | L5: =35000*4 -> 140000 | M5: =35000*4 -> 140000 | N5: =35000*4 -> 140000 | O5: =35000*4 -> 140000 | P5: =35000*4 -> 140000 | Q5: =35000*4 -> 140000 | ... U5: =35000*4 -> 140000
A6: Estimated Cost | B6: ₹17L/yr (3–4 counsellor salaries + TPA training + NBFC onboarding) | I6: =SUM(I8:I30) -> 178468 | J6: 0.076812097 | K6: 0.077329359 | L6: 0.076557659 | M6: 0.089827542 | N6: 0.085669869 | O6: 0.085516088 | P6: 0.086564594 | Q6: 0.079879324 | R6: 0.084291434 | S6: 0.092083925 | T6: 0.083019248 | U6: 0.082448861
A7: Expected Impact | B7: ₹4 Cr | E7: Medical | F7: EXISTING | G7: Increase to | H7: Incremental | I7: OP COUNT IN 25-26 | V7: =SUM(V8:V39) -> 2057 | W7: ARPPIP Incremental
E8: NEPHROLOGY | F8: 0.068685245 | G8: =+F8 -> 0.068685245 | H8: =+G8-F8 -> 0 | I8: 25620 | J8: =ROUND($V8*J$6,0) -> 0 | K8: =ROUND($V8*K$6,0) -> 0 | L8: =ROUND($V8*L$6,0) -> 0 | M8: =ROUND($V8*M$6,0) -> 0 | N8: =ROUND($V8*N$6,0) -> 0 | O8: =ROUND($V8*O$6,0) -> 0 | P8: =ROUND($V8*P$6,0) -> 0 | Q8: =ROUND($V8*Q$6,0) -> 0 | ... T8: =ROUND($V8*T$6,0) -> 0 | U8: =+V8-SUM(J8:T8) -> 0 | V8: =ROUND(+I8*H8,0) -> 0 | W8: 0.1
A9: BASIS FOR THIS INITIATIVE | E9: MEDICAL ONCOLOGY | F9: 0.16295328 | G9: =+F9 -> 0.16295328 | H9: =+G9-F9 -> 0 | I9: 35190 | J9: =ROUND($V9*J$6,0) -> 0 | K9: =ROUND($V9*K$6,0) -> 0 | L9: =ROUND($V9*L$6,0) -> 0 | M9: =ROUND($V9*M$6,0) -> 0 | N9: =ROUND($V9*N$6,0) -> 0 | O9: =ROUND($V9*O$6,0) -> 0 | P9: =ROUND($V9*P$6,0) -> 0 | Q9: =ROUND($V9*Q$6,0) -> 0 | ... T9: =ROUND($V9*T$6,0) -> 0 | U9: =+V9-SUM(J9:T9) -> 0 | V9: =ROUND(+I9*H9,0) -> 0 | W9: 0.1
A10: A significant number of patients who receive a surgical recommendation in OPD do not convert to IP admission. Common barriers: cost uncertainty, insurance confusion, fear, competing hospital opinions. Financial counselling addresses the first two barriers on the spot. Follow-up callbacks address the rest. IMPACT BASIS (₹4 Cr conservative): • Lakeshore surgical OPD volume: ~800 consults/week across cardiac, ortho, neuro, onco, transplant • Current estimated OP-to-IP conversion: ~25–30% • Target with counsellors + follow-up: 33–35% (i.e., +5 percentage points) • Incremental IP admissions: 800 × 5% = 40/week = ~2,000/year • Average IP ticket for surgical patients: ₹2L • Gross incremental revenue: 2,000 × ₹2L = ₹40 Cr • BUT most of this is existing capacity utilisation (beds, OTs, staff already in place) — true incremental revenue after accounting for realistic ramp-up and variable costs: conservative ₹4 Cr in Year 1 • Counsellor cost: 3–4 counsellors × ₹4–5L/yr = ₹15–20L + TPA training + NBFC onboarding = total ₹25–30L investment • ROI: 13–16× on direct investment | E10: ORTHOPEDICS | F10: 0.058978873 | G10: =+F10+4% -> 0.098978873 | H10: =+G10-F10 -> 0.04 | I10: 4312 | J10: =ROUND($V10*J$6,0) -> 13 | K10: =ROUND($V10*K$6,0) -> 13 | L10: =ROUND($V10*L$6,0) -> 13 | M10: =ROUND($V10*M$6,0) -> 15 | N10: =ROUND($V10*N$6,0) -> 15 | O10: =ROUND($V10*O$6,0) -> 15 | P10: =ROUND($V10*P$6,0) -> 15 | Q10: =ROUND($V10*Q$6,0) -> 14 | ... T10: =ROUND($V10*T$6,0) -> 14 | U10: =+V10-SUM(J10:T10) -> 15 | V10: =ROUND(+I10*H10,0) -> 172 | W10: 0.1
A11: EXECUTION TRACKING (to be completed) | E11: NEURO SURGERY | F11: 0.10117146 | G11: =+F11+3% -> 0.13117146 | H11: =+G11-F11 -> 0.03 | I11: 9378 | J11: =ROUND($V11*J$6,0) -> 22 | K11: =ROUND($V11*K$6,0) -> 22 | L11: =ROUND($V11*L$6,0) -> 22 | M11: =ROUND($V11*M$6,0) -> 25 | N11: =ROUND($V11*N$6,0) -> 24 | O11: =ROUND($V11*O$6,0) -> 24 | P11: =ROUND($V11*P$6,0) -> 24 | Q11: =ROUND($V11*Q$6,0) -> 22 | ... T11: =ROUND($V11*T$6,0) -> 23 | U11: =+V11-SUM(J11:T11) -> 23 | V11: =ROUND(+I11*H11,0) -> 281 | W11: 0.1
A12: Owner | B12: Head BD / Call Centre Manager / CFO | E12: GI SURGERY | F12: 0.043478261 | G12: =+F12+1% -> 0.053478261 | H12: =+G12-F12 -> 0.01 | I12: 13651 | J12: =ROUND($V12*J$6,0) -> 11 | K12: =ROUND($V12*K$6,0) -> 11 | L12: =ROUND($V12*L$6,0) -> 10 | M12: =ROUND($V12*M$6,0) -> 12 | N12: =ROUND($V12*N$6,0) -> 12 | O12: =ROUND($V12*O$6,0) -> 12 | P12: =ROUND($V12*P$6,0) -> 12 | Q12: =ROUND($V12*Q$6,0) -> 11 | ... T12: =ROUND($V12*T$6,0) -> 11 | U12: =+V12-SUM(J12:T12) -> 10 | V12: =ROUND(+I12*H12,0) -> 137 | W12: 0.1
A13: Key Milestones / Actions | B13: 1. Analyse current OP-to-IP conversion rates by department (cardiac, ortho, neuro, onco, transplant) by May-26 2. Identify top 5 dropout reasons from surgical OPD — survey 100 patients who did not proceed by Jun-26 3. Recruit 3-4 financial counsellors and station at surgical OPD counters by Jun-26 4. Build insurance pre-auth initiation protocol: counsellor starts pre-auth on day of consultation 5. Onboard 2-3 NBFC/EMI partners (Bajaj Finance, HDB) for self-pay patient financing by Jul-26 6. Implement 48-hour post-consult callback protocol for all surgical OPD patients by Jun-26 7. Launch lapsed patient re-engagement: automated SMS/call for patients with pending surgical recommendations older than 30 days 8. Track conversion rate monthly — target: 5% improvement in OP-IP conversion within 6 months | E13: GASTROENTEROLOGY | F13: 0.032544379 | G13: =+F13+1% -> 0.042544379 | H13: =+G13-F13 -> 0.01 | I13: 22007 | J13: =ROUND($V13*J$6,0) -> 17 | K13: =ROUND($V13*K$6,0) -> 17 | L13: =ROUND($V13*L$6,0) -> 17 | M13: =ROUND($V13*M$6,0) -> 20 | N13: =ROUND($V13*N$6,0) -> 19 | O13: =ROUND($V13*O$6,0) -> 19 | P13: =ROUND($V13*P$6,0) -> 19 | Q13: =ROUND($V13*Q$6,0) -> 18 | ... T13: =ROUND($V13*T$6,0) -> 18 | U13: =+V13-SUM(J13:T13) -> 17 | V13: =ROUND(+I13*H13,0) -> 220 | W13: 0.1
A14: Risks / Dependencies | B14: 1. Financial counsellors need deep product knowledge — training on all surgical packages and insurance products 2. Patient financing (EMI) carries compliance and collection risk 3. Callback protocols require integration with OPD scheduling system 4. Dropout patients may have gone to competitors — re-engagement must be tactful, not aggressive | E14: CARDIOLOGY | F14: 0.087200599 | G14: =+F14+1% -> 0.097200599 | H14: =+G14-F14 -> 0.01 | I14: 16627 | J14: =ROUND($V14*J$6,0) -> 13 | K14: =ROUND($V14*K$6,0) -> 13 | L14: =ROUND($V14*L$6,0) -> 13 | M14: =ROUND($V14*M$6,0) -> 15 | N14: =ROUND($V14*N$6,0) -> 14 | O14: =ROUND($V14*O$6,0) -> 14 | P14: =ROUND($V14*P$6,0) -> 14 | Q14: =ROUND($V14*Q$6,0) -> 13 | ... T14: =ROUND($V14*T$6,0) -> 14 | U14: =+V14-SUM(J14:T14) -> 14 | V14: =ROUND(+I14*H14,0) -> 166 | W14: 0.1
A15: Remarks | B15: This is one of the highest-ROI initiatives — the patient has already arrived, seen the doctor, and received a recommendation. The only gap is conversion support. Financial counselling + follow-up closes this gap at very low marginal cost. | E15: UROLOGY | F15: 0.06056338 | G15: =+F15+2% -> 0.08056338 | H15: =+G15-F15 -> 0.02 | I15: 13810 | J15: =ROUND($V15*J$6,0) -> 21 | K15: =ROUND($V15*K$6,0) -> 21 | L15: =ROUND($V15*L$6,0) -> 21 | M15: =ROUND($V15*M$6,0) -> 25 | N15: =ROUND($V15*N$6,0) -> 24 | O15: =ROUND($V15*O$6,0) -> 24 | P15: =ROUND($V15*P$6,0) -> 24 | Q15: =ROUND($V15*Q$6,0) -> 22 | ... T15: =ROUND($V15*T$6,0) -> 23 | U15: =+V15-SUM(J15:T15) -> 23 | V15: =ROUND(+I15*H15,0) -> 276 | W15: 0.1
E16: SURGICAL ONCOLOGY | F16: 0.041666667 | G16: =+F16+2% -> 0.061666667 | H16: =+G16-F16 -> 0.02 | I16: 12863 | J16: =ROUND($V16*J$6,0) -> 20 | K16: =ROUND($V16*K$6,0) -> 20 | L16: =ROUND($V16*L$6,0) -> 20 | M16: =ROUND($V16*M$6,0) -> 23 | N16: =ROUND($V16*N$6,0) -> 22 | O16: =ROUND($V16*O$6,0) -> 22 | P16: =ROUND($V16*P$6,0) -> 22 | Q16: =ROUND($V16*Q$6,0) -> 21 | ... T16: =ROUND($V16*T$6,0) -> 21 | U16: =+V16-SUM(J16:T16) -> 20 | V16: =ROUND(+I16*H16,0) -> 257 | W16: 0.1
E17: MINIMALLY INVASIVE SURGERY | F17: 0.18642005 | G17: =+F17+5% -> 0.23642005 | H17: =+G17-F17 -> 0.05 | I17: 4110 | J17: =ROUND($V17*J$6,0) -> 16 | K17: =ROUND($V17*K$6,0) -> 16 | L17: =ROUND($V17*L$6,0) -> 16 | M17: =ROUND($V17*M$6,0) -> 19 | N17: =ROUND($V17*N$6,0) -> 18 | O17: =ROUND($V17*O$6,0) -> 18 | P17: =ROUND($V17*P$6,0) -> 18 | Q17: =ROUND($V17*Q$6,0) -> 16 | ... T17: =ROUND($V17*T$6,0) -> 17 | U17: =+V17-SUM(J17:T17) -> 16 | V17: =ROUND(+I17*H17,0) -> 206 | W17: 0.1
E18: COMPREHENSIVE LIVER CARE | F18: 0 | G18: =+F18+5% -> 0.05 | H18: =+G18-F18 -> 0.05 | I18: 364 | J18: =ROUND($V18*J$6,0) -> 1 | K18: =ROUND($V18*K$6,0) -> 1 | L18: =ROUND($V18*L$6,0) -> 1 | M18: =ROUND($V18*M$6,0) -> 2 | N18: =ROUND($V18*N$6,0) -> 2 | O18: =ROUND($V18*O$6,0) -> 2 | P18: =ROUND($V18*P$6,0) -> 2 | Q18: =ROUND($V18*Q$6,0) -> 1 | ... T18: =ROUND($V18*T$6,0) -> 1 | U18: =+V18-SUM(J18:T18) -> 1 | V18: =ROUND(+I18*H18,0) -> 18 | W18: 0.1
W19: 0.1
W20: 0.1
W21: 0.1
W22: 0.1
E23: JOINT REPLACEMENT & SPORTS MED | F23: 0.087692308 | G23: =+F23+1% -> 0.097692308 | H23: =+G23-F23 -> 0.01 | I23: 9336 | J23: =ROUND($V23*J$6,0) -> 7 | K23: =ROUND($V23*K$6,0) -> 7 | L23: =ROUND($V23*L$6,0) -> 7 | M23: =ROUND($V23*M$6,0) -> 8 | N23: =ROUND($V23*N$6,0) -> 8 | O23: =ROUND($V23*O$6,0) -> 8 | P23: =ROUND($V23*P$6,0) -> 8 | Q23: =ROUND($V23*Q$6,0) -> 7 | ... T23: =ROUND($V23*T$6,0) -> 8 | U23: =+V23-SUM(J23:T23) -> 8 | V23: =ROUND(+I23*H23,0) -> 93 | W23: 0.1
E24: ORTHOPEDICS - DIVISION OF FOOT ANKLE & PODIATRY | F24: 0 | G24: =+F24+1% -> 0.01 | H24: =+G24-F24 -> 0.01 | I24: 7701 | J24: =ROUND($V24*J$6,0) -> 6 | K24: =ROUND($V24*K$6,0) -> 6 | L24: =ROUND($V24*L$6,0) -> 6 | M24: =ROUND($V24*M$6,0) -> 7 | N24: =ROUND($V24*N$6,0) -> 7 | O24: =ROUND($V24*O$6,0) -> 7 | P24: =ROUND($V24*P$6,0) -> 7 | Q24: =ROUND($V24*Q$6,0) -> 6 | ... T24: =ROUND($V24*T$6,0) -> 6 | U24: =+V24-SUM(J24:T24) -> 6 | V24: =ROUND(+I24*H24,0) -> 77 | W24: 0.1
E25: ORTHOPEDICS - DIVISION OF ORTHOPEDIC ONCOLOGY | F25: 0 | G25: =+F25+1% -> 0.01 | H25: =+G25-F25 -> 0.01 | I25: 516 | J25: =ROUND($V25*J$6,0) -> 0 | K25: =ROUND($V25*K$6,0) -> 0 | L25: =ROUND($V25*L$6,0) -> 0 | M25: =ROUND($V25*M$6,0) -> 0 | N25: =ROUND($V25*N$6,0) -> 0 | O25: =ROUND($V25*O$6,0) -> 0 | P25: =ROUND($V25*P$6,0) -> 0 | Q25: =ROUND($V25*Q$6,0) -> 0 | ... T25: =ROUND($V25*T$6,0) -> 0 | U25: =+V25-SUM(J25:T25) -> 5 | V25: =ROUND(+I25*H25,0) -> 5 | W25: 0.1
E26: COMPREHENSIVE LIVER CARE - SUR | F26: 0 | G26: =+F26+5% -> 0.05 | H26: =+G26-F26 -> 0.05 | I26: 1925 | J26: =ROUND($V26*J$6,0) -> 7 | K26: =ROUND($V26*K$6,0) -> 7 | L26: =ROUND($V26*L$6,0) -> 7 | M26: =ROUND($V26*M$6,0) -> 9 | N26: =ROUND($V26*N$6,0) -> 8 | O26: =ROUND($V26*O$6,0) -> 8 | P26: =ROUND($V26*P$6,0) -> 8 | Q26: =ROUND($V26*Q$6,0) -> 8 | ... T26: =ROUND($V26*T$6,0) -> 8 | U26: =+V26-SUM(J26:T26) -> 9 | V26: =ROUND(+I26*H26,0) -> 96 | W26: 0.1
W27: 0.1
E28: GYNAECOLOGY | F28: 0 | G28: =+F28+5% -> 0.05 | H28: =+G28-F28 -> 0.05 | I28: 22 | J28: =ROUND($V28*J$6,0) -> 0 | K28: =ROUND($V28*K$6,0) -> 0 | L28: =ROUND($V28*L$6,0) -> 0 | M28: =ROUND($V28*M$6,0) -> 0 | N28: =ROUND($V28*N$6,0) -> 0 | O28: =ROUND($V28*O$6,0) -> 0 | P28: =ROUND($V28*P$6,0) -> 0 | Q28: =ROUND($V28*Q$6,0) -> 0 | ... T28: =ROUND($V28*T$6,0) -> 0 | U28: =+V28-SUM(J28:T28) -> 1 | V28: =ROUND(+I28*H28,0) -> 1 | W28: 0.1
E29: HEAD AND NECK ONCOLOGY | F29: 0 | G29: =+F29+5% -> 0.05 | H29: =+G29-F29 -> 0.05 | I29: 1036 | J29: =ROUND($V29*J$6,0) -> 4 | K29: =ROUND($V29*K$6,0) -> 4 | L29: =ROUND($V29*L$6,0) -> 4 | M29: =ROUND($V29*M$6,0) -> 5 | N29: =ROUND($V29*N$6,0) -> 4 | O29: =ROUND($V29*O$6,0) -> 4 | P29: =ROUND($V29*P$6,0) -> 5 | Q29: =ROUND($V29*Q$6,0) -> 4 | ... T29: =ROUND($V29*T$6,0) -> 4 | U29: =+V29-SUM(J29:T29) -> 5 | V29: =ROUND(+I29*H29,0) -> 52 | W29: 0.1

Sheet R-11
A1: R-11 | Departmental Organic Growth Initiative
A2: Revenue — High-Value Services
A3: OVERVIEW
A4: Description / Objective | B4: Monthly department review: each clinical department presents its growth plan, infrastructure needs, staffing gaps, and volume targets. Process = structured departmental consultations where clinicians articulate what they need to grow volumes (equipment, beds, OT time, staff, referral support). Cover all specialties systematically across the year. Focus on removing bottlenecks and enabling organic volume growth. | E4: Total | T4: =+T5+T54 -> 0 | U4: =+U5+U54 -> 3139430.9 | V4: =+V5+V54 -> 10036637 | W4: =+W5+W54 -> 18401196 | X4: =+X5+X54 -> 24398645 | Y4: =+Y5+Y54 -> 31779269 | Z4: =+Z5+Z54 -> 39264253 | AA4: =+AA5+AA54 -> 42155960 | ... AE4: =+AE5+AE54 -> 73996918
A5: Start Month | B5: 46143 | T5: =SUM(T8:T51) -> 0 | U5: =SUM(U8:U51) -> 858987.93 | V5: =SUM(V8:V51) -> 2592190.1 | W5: =SUM(W8:W51) -> 4980080.7 | X5: =SUM(X8:X51) -> 6494690.8 | Y5: =SUM(Y8:Y51) -> 8383562.2 | Z5: =SUM(Z8:Z51) -> 10508926 | AA5: =SUM(AA8:AA51) -> 11081716 | ... AE5: =SUM(AE8:AE51) -> 19793711
A6: Estimated Cost | B6: Nil — internal process; dept-level investment decisions routed through normal capex approval | G6: OP | T6: OP
A7: Expected Impact | B7: ₹8 Cr | E7: Medical | G7: Apr | H7: May | I7: June | J7: Jul | K7: Aug | L7: Sep | M7: Oct | N7: Nov | O7: Dec | P7: Jan | Q7: Feb | R7: Mar | S7: ARPP-OP | T7: Apr | U7: May | V7: June | W7: Jul | X7: Aug | Y7: Sep | Z7: Oct | AA7: Nov | AB7: Dec | AC7: Jan | AD7: Feb | AE7: Mar
E8: NEPHROLOGY | G8: 0 | H8: 16 | I8: 61 | J8: 112 | K8: 126 | L8: 175 | M8: 232 | N8: 256 | O8: 362 | P8: 479 | Q8: 468 | R8: 564 | S8: 7661.9249 | T8: =+G8*$S8 -> 0 | U8: =+H8*$S8 -> 122590.8 | V8: =+I8*$S8 -> 467377.42 | W8: =+J8*$S8 -> 858135.58 | X8: =+K8*$S8 -> 965402.53 | Y8: =+L8*$S8 -> 1340836.8 | Z8: =+M8*$S8 -> 1777566.6 | AA8: =+N8*$S8 -> 1961452.8 | ... AE8: =+R8*$S8 -> 4321325.6
A9: BASIS FOR THIS INITIATIVE | E9: MEDICAL ONCOLOGY | G9: 0 | H9: 30 | I9: 88 | J9: 157 | K9: 198 | L9: 266 | M9: 345 | N9: 345 | O9: 440 | P9: 504 | Q9: 523 | R9: 601 | S9: 6302.7976 | T9: =+G9*$S9 -> 0 | U9: =+H9*$S9 -> 189083.93 | V9: =+I9*$S9 -> 554646.19 | W9: =+J9*$S9 -> 989539.22 | X9: =+K9*$S9 -> 1247953.9 | Y9: =+L9*$S9 -> 1676544.2 | Z9: =+M9*$S9 -> 2174465.2 | AA9: =+N9*$S9 -> 2174465.2 | ... AE9: =+R9*$S9 -> 3787981.4
A10: Most hospital revenue growth comes from existing departments doing more of what they already do well. The constraint is rarely clinical capability — it is OT scheduling, bed availability, equipment downtime, staffing gaps, or marketing support. A systematic department-by-department review identifies and removes these bottlenecks. Monthly reviews create accountability and visibility. IMPACT BUILD-UP (₹8 Cr conservative): Lakeshore IP revenue: ~₹399 Cr (FY27 budget) across ~20 clinical departments. • Target: 2% organic volume uplift across departments through bottleneck removal • ₹399 Cr × 2% = ₹8 Cr This is achievable because: • Cardiac Sciences (current ~₹80 Cr): 1 additional OT slot/day = ~200 cases/yr × ₹2L = ₹4 Cr; 2% = ₹1.6 Cr • Orthopaedics (~₹40 Cr): faster implant procurement + dedicated physio = 3% uplift = ₹1.2 Cr • Oncology (~₹45 Cr): reduced chemo chair wait time + 1 additional radiation slot = 2% = ₹0.9 Cr • Nephrology (~₹30 Cr): additional dialysis shifts + transplant volume = 3% = ₹0.9 Cr • Gastro/Liver (~₹35 Cr): endoscopy scheduling optimisation = 2% = ₹0.7 Cr • Remaining 15 depts (~₹169 Cr combined): even 1.5% blended uplift = ₹2.5 Cr Total: ₹1.6 + ₹1.2 + ₹0.9 + ₹0.9 + ₹0.7 + ₹2.5 = ₹7.8 Cr ≈ ₹8 Cr Note: department-level revenue splits above are indicative. Actual splits to be confirmed during first round of reviews. | E10: ORTHOPEDICS | G10: 0 | H10: 3 | I10: 8 | J10: 15 | K10: 16 | L10: 28 | M10: 41 | N10: 48 | O10: 67 | P10: 84 | Q10: 87 | R10: 99 | S10: 2232.036 | T10: =+G10*$S10 -> 0 | U10: =+H10*$S10 -> 6696.108 | V10: =+I10*$S10 -> 17856.288 | W10: =+J10*$S10 -> 33480.54 | X10: =+K10*$S10 -> 35712.576 | Y10: =+L10*$S10 -> 62497.008 | Z10: =+M10*$S10 -> 91513.475 | AA10: =+N10*$S10 -> 107137.73 | ... AE10: =+R10*$S10 -> 220971.56
A11: EXECUTION TRACKING (to be completed) | E11: NEURO SURGERY | G11: 0 | H11: 7 | I11: 20 | J11: 39 | K11: 62 | L11: 79 | M11: 88 | N11: 95 | O11: 112 | P11: 152 | Q11: 146 | R11: 161 | S11: 3008.9909 | T11: =+G11*$S11 -> 0 | U11: =+H11*$S11 -> 21062.936 | V11: =+I11*$S11 -> 60179.818 | W11: =+J11*$S11 -> 117350.65 | X11: =+K11*$S11 -> 186557.44 | Y11: =+L11*$S11 -> 237710.28 | Z11: =+M11*$S11 -> 264791.2 | AA11: =+N11*$S11 -> 285854.14 | ... AE11: =+R11*$S11 -> 484447.54
A12: Owner | B12: Head BD / Individual Department HODs | E12: GI SURGERY | G12: 0 | H12: 12 | I12: 35 | J12: 59 | K12: 80 | L12: 104 | M12: 148 | N12: 125 | O12: 156 | P12: 212 | Q12: 207 | R12: 219 | S12: 1810.4889 | T12: =+G12*$S12 -> 0 | U12: =+H12*$S12 -> 21725.867 | V12: =+I12*$S12 -> 63367.113 | W12: =+J12*$S12 -> 106818.85 | X12: =+K12*$S12 -> 144839.12 | Y12: =+L12*$S12 -> 188290.85 | Z12: =+M12*$S12 -> 267952.36 | AA12: =+N12*$S12 -> 226311.12 | ... AE12: =+R12*$S12 -> 396497.08
A13: Key Milestones / Actions | B13: 1. Schedule first 3 departmental growth reviews: Cardiac Sciences (Jun-26), Orthopaedics (Jul-26), Nephrology (Aug-26) 2. Each review must include: current volumes, 3-year trend, capacity utilisation, bottleneck analysis, growth plan with specific asks 3. Head BD to compile action tracker — infrastructure/equipment/staffing decisions within 2 weeks of each review 4. Rotate all departments through the cycle by Mar-27 (12 departments minimum) 5. Track volume growth per department quarterly vs baseline 6. Identify 3 quick-win bottleneck removals per department (e.g., additional OT slot, equipment repair, dedicated nurse) | E13: GASTROENTEROLOGY | G13: 0 | H13: 19 | I13: 51 | J13: 107 | K13: 150 | L13: 177 | M13: 211 | N13: 203 | O13: 248 | P13: 320 | Q13: 322 | R13: 316 | S13: 3813.2544 | T13: =+G13*$S13 -> 0 | U13: =+H13*$S13 -> 72451.834 | V13: =+I13*$S13 -> 194475.98 | W13: =+J13*$S13 -> 408018.22 | X13: =+K13*$S13 -> 571988.16 | Y13: =+L13*$S13 -> 674946.03 | Z13: =+M13*$S13 -> 804596.68 | AA13: =+N13*$S13 -> 774090.65 | ... AE13: =+R13*$S13 -> 1204988.4
A14: Risks / Dependencies | B14: 1. Department HODs may treat reviews as compliance rather than genuine growth planning 2. Capital requests from reviews may exceed available budget — a prioritisation framework is required 3. Some departments are capacity-constrained (ICU beds, OT slots) where growth requires capex 4. Risk of setting expectations that all requests will be funded | E14: CARDIOLOGY | G14: 0 | H14: 12 | I14: 37 | J14: 73 | K14: 99 | L14: 138 | M14: 165 | N14: 181 | O14: 204 | P14: 263 | Q14: 252 | R14: 298 | S14: 2618.3826 | T14: =+G14*$S14 -> 0 | U14: =+H14*$S14 -> 31420.591 | V14: =+I14*$S14 -> 96880.157 | W14: =+J14*$S14 -> 191141.93 | X14: =+K14*$S14 -> 259219.88 | Y14: =+L14*$S14 -> 361336.8 | Z14: =+M14*$S14 -> 432033.13 | AA14: =+N14*$S14 -> 473927.26 | ... AE14: =+R14*$S14 -> 780278.02
A15: Remarks | B15: Governance layer rather than a standalone growth initiative. Ensures each clinical department has a reviewed, approved growth plan with tracked bottlenecks. Outputs feed capex prioritisation and identify specialties requiring R-13 (clinician recruitment) support. Effectiveness depends on Head BD chairing reviews and HODs providing accurate capacity and constraint data. | E15: UROLOGY | G15: 0 | H15: 11 | I15: 31 | J15: 65 | K15: 82 | L15: 107 | M15: 133 | N15: 141 | O15: 172 | P15: 213 | Q15: 212 | R15: 233 | S15: 2548.7509 | T15: =+G15*$S15 -> 0 | U15: =+H15*$S15 -> 28036.26 | V15: =+I15*$S15 -> 79011.278 | W15: =+J15*$S15 -> 165668.81 | X15: =+K15*$S15 -> 208997.57 | Y15: =+L15*$S15 -> 272716.35 | Z15: =+M15*$S15 -> 338983.87 | AA15: =+N15*$S15 -> 359373.88 | ... AE15: =+R15*$S15 -> 593858.96
E16: SURGICAL ONCOLOGY | G16: 0 | H16: 12 | I16: 35 | J16: 70 | K16: 87 | L16: 110 | M16: 108 | N16: 101 | O16: 128 | P16: 170 | Q16: 171 | R16: 175 | S16: 2465.6794 | T16: =+G16*$S16 -> 0 | U16: =+H16*$S16 -> 29588.153 | V16: =+I16*$S16 -> 86298.78 | W16: =+J16*$S16 -> 172597.56 | X16: =+K16*$S16 -> 214514.11 | Y16: =+L16*$S16 -> 271224.74 | Z16: =+M16*$S16 -> 266293.38 | AA16: =+N16*$S16 -> 249033.62 | ... AE16: =+R16*$S16 -> 431493.9
E17: MINIMALLY INVASIVE SURGERY | G17: 0 | H17: 3 | I17: 8 | J17: 21 | K17: 23 | L17: 29 | M17: 39 | N17: 44 | O17: 65 | P17: 64 | Q17: 54 | R17: 71 | S17: 2200.2123 | T17: =+G17*$S17 -> 0 | U17: =+H17*$S17 -> 6600.6369 | V17: =+I17*$S17 -> 17601.698 | W17: =+J17*$S17 -> 46204.458 | X17: =+K17*$S17 -> 50604.883 | Y17: =+L17*$S17 -> 63806.157 | Z17: =+M17*$S17 -> 85808.28 | AA17: =+N17*$S17 -> 96809.341 | ... AE17: =+R17*$S17 -> 156215.07
E18: COMPREHENSIVE LIVER CARE | G18: 0 | H18: 0 | I18: 0 | J18: 0 | K18: 0 | L18: 1 | M18: 3 | N18: 3 | O18: 10 | P18: 11 | Q18: 13 | R18: 21 | S18: 5942.9578 | T18: =+G18*$S18 -> 0 | U18: =+H18*$S18 -> 0 | V18: =+I18*$S18 -> 0 | W18: =+J18*$S18 -> 0 | X18: =+K18*$S18 -> 0 | Y18: =+L18*$S18 -> 5942.9578 | Z18: =+M18*$S18 -> 17828.874 | AA18: =+N18*$S18 -> 17828.874 | ... AE18: =+R18*$S18 -> 124802.11
E19: NEUROLOGY | G19: 0 | H19: 12 | I19: 33 | J19: 57 | K19: 85 | L19: 103 | M19: 139 | N19: 151 | O19: 154 | P19: 235 | Q19: 208 | R19: 222 | S19: 2228.7649 | T19: =+G19*$S19 -> 0 | U19: =+H19*$S19 -> 26745.179 | V19: =+I19*$S19 -> 73549.241 | W19: =+J19*$S19 -> 127039.6 | X19: =+K19*$S19 -> 189445.01 | Y19: =+L19*$S19 -> 229562.78 | Z19: =+M19*$S19 -> 309798.32 | AA19: =+N19*$S19 -> 336543.5 | ... AE19: =+R19*$S19 -> 494785.8
E20: GENERAL MEDICINE | G20: 0 | H20: 8 | I20: 25 | J20: 48 | K20: 61 | L20: 83 | M20: 101 | N20: 116 | O20: 132 | P20: 169 | Q20: 173 | R20: 164 | S20: 2680.675 | T20: =+G20*$S20 -> 0 | U20: =+H20*$S20 -> 21445.4 | V20: =+I20*$S20 -> 67016.874 | W20: =+J20*$S20 -> 128672.4 | X20: =+K20*$S20 -> 163521.17 | Y20: =+L20*$S20 -> 222496.02 | Z20: =+M20*$S20 -> 270748.17 | AA20: =+N20*$S20 -> 310958.3 | ... AE20: =+R20*$S20 -> 439630.7
E21: OB & GYNEC. | G21: 0 | H21: 8 | I21: 27 | J21: 53 | K21: 70 | L21: 89 | M21: 127 | N21: 124 | O21: 145 | P21: 190 | Q21: 176 | R21: 200 | S21: 1611.834 | T21: =+G21*$S21 -> 0 | U21: =+H21*$S21 -> 12894.672 | V21: =+I21*$S21 -> 43519.517 | W21: =+J21*$S21 -> 85427.201 | X21: =+K21*$S21 -> 112828.38 | Y21: =+L21*$S21 -> 143453.22 | Z21: =+M21*$S21 -> 204702.91 | AA21: =+N21*$S21 -> 199867.41 | ... AE21: =+R21*$S21 -> 322366.79
E22: PEDIATRICS | G22: 0 | H22: 14 | I22: 51 | J22: 122 | K22: 175 | L22: 221 | M22: 246 | N22: 304 | O22: 363 | P22: 359 | Q22: 467 | R22: 435 | S22: 810.70795 | T22: =+G22*$S22 -> 0 | U22: =+H22*$S22 -> 11349.911 | V22: =+I22*$S22 -> 41346.105 | W22: =+J22*$S22 -> 98906.37 | X22: =+K22*$S22 -> 141873.89 | Y22: =+L22*$S22 -> 179166.46 | Z22: =+M22*$S22 -> 199434.16 | AA22: =+N22*$S22 -> 246455.22 | ... AE22: =+R22*$S22 -> 352657.96
G23: 0 | H23: 0 | I23: 0 | J23: 0 | K23: 0 | L23: 0 | M23: 0 | N23: 0 | O23: 0 | P23: 0 | Q23: 0 | R23: 0 | T23: =+G23*$S23 -> 0 | U23: =+H23*$S23 -> 0 | V23: =+I23*$S23 -> 0 | W23: =+J23*$S23 -> 0 | X23: =+K23*$S23 -> 0 | Y23: =+L23*$S23 -> 0 | Z23: =+M23*$S23 -> 0 | AA23: =+N23*$S23 -> 0 | ... AE23: =+R23*$S23 -> 0
E24: RADIATION ONCOLOGY | G24: 0 | H24: 5 | I24: 12 | J24: 25 | K24: 32 | L24: 40 | M24: 49 | N24: 49 | O24: 51 | P24: 69 | Q24: 75 | R24: 77 | S24: 11146.989 | T24: =+G24*$S24 -> 0 | U24: =+H24*$S24 -> 55734.945 | V24: =+I24*$S24 -> 133763.87 | W24: =+J24*$S24 -> 278674.73 | X24: =+K24*$S24 -> 356703.65 | Y24: =+L24*$S24 -> 445879.56 | Z24: =+M24*$S24 -> 546202.47 | AA24: =+N24*$S24 -> 546202.47 | ... AE24: =+R24*$S24 -> 858318.16
E25: CARDIO THORACIC SURGERY | G25: 0 | H25: 1 | I25: 3 | J25: 4 | K25: 8 | L25: 10 | M25: 11 | N25: 10 | O25: 11 | P25: 23 | Q25: 18 | R25: 18 | S25: 4156.6513 | T25: =+G25*$S25 -> 0 | U25: =+H25*$S25 -> 4156.6513 | V25: =+I25*$S25 -> 12469.954 | W25: =+J25*$S25 -> 16626.605 | X25: =+K25*$S25 -> 33253.211 | Y25: =+L25*$S25 -> 41566.513 | Z25: =+M25*$S25 -> 45723.165 | AA25: =+N25*$S25 -> 41566.513 | ... AE25: =+R25*$S25 -> 74819.724
E26: PULMONOLOGY | G26: 0 | H26: 2 | I26: 9 | J26: 15 | K26: 21 | L26: 36 | M26: 38 | N26: 50 | O26: 55 | P26: 86 | Q26: 69 | R26: 80 | S26: 1758.3157 | T26: =+G26*$S26 -> 0 | U26: =+H26*$S26 -> 3516.6314 | V26: =+I26*$S26 -> 15824.841 | W26: =+J26*$S26 -> 26374.735 | X26: =+K26*$S26 -> 36924.63 | Y26: =+L26*$S26 -> 63299.365 | Z26: =+M26*$S26 -> 66815.996 | AA26: =+N26*$S26 -> 87915.785 | ... AE26: =+R26*$S26 -> 140665.26
E27: PLASTIC SURGERY | G27: 0 | H27: 3 | I27: 8 | J27: 14 | K27: 21 | L27: 26 | M27: 28 | N27: 39 | O27: 50 | P27: 52 | Q27: 55 | R27: 72 | S27: 1558.4114 | T27: =+G27*$S27 -> 0 | U27: =+H27*$S27 -> 4675.2342 | V27: =+I27*$S27 -> 12467.291 | W27: =+J27*$S27 -> 21817.76 | X27: =+K27*$S27 -> 32726.639 | Y27: =+L27*$S27 -> 40518.696 | Z27: =+M27*$S27 -> 43635.519 | AA27: =+N27*$S27 -> 60778.045 | ... AE27: =+R27*$S27 -> 112205.62
E28: ENT | G28: 0 | H28: 7 | I28: 18 | J28: 39 | K28: 52 | L28: 66 | M28: 77 | N28: 97 | O28: 122 | P28: 134 | Q28: 128 | R28: 136 | S28: 1069.3562 | T28: =+G28*$S28 -> 0 | U28: =+H28*$S28 -> 7485.4931 | V28: =+I28*$S28 -> 19248.411 | W28: =+J28*$S28 -> 41704.89 | X28: =+K28*$S28 -> 55606.52 | Y28: =+L28*$S28 -> 70577.506 | Z28: =+M28*$S28 -> 82340.424 | AA28: =+N28*$S28 -> 103727.55 | ... AE28: =+R28*$S28 -> 145432.44
E29: FAMILY MEDICINE | G29: 0 | H29: 3 | I29: 10 | J29: 23 | K29: 36 | L29: 40 | M29: 48 | N29: 45 | O29: 61 | P29: 89 | Q29: 62 | R29: 121 | S29: 9606.9619 | T29: =+G29*$S29 -> 0 | U29: =+H29*$S29 -> 28820.886 | V29: =+I29*$S29 -> 96069.619 | W29: =+J29*$S29 -> 220960.12 | X29: =+K29*$S29 -> 345850.63 | Y29: =+L29*$S29 -> 384278.48 | Z29: =+M29*$S29 -> 461134.17 | AA29: =+N29*$S29 -> 432313.29 | ... AE29: =+R29*$S29 -> 1162442.4
E30: DERMATOLOGY & V D | G30: 0 | H30: 9 | I30: 32 | J30: 65 | K30: 83 | L30: 96 | M30: 120 | N30: 138 | O30: 148 | P30: 193 | Q30: 188 | R30: 192 | S30: 1955.5935 | T30: =+G30*$S30 -> 0 | U30: =+H30*$S30 -> 17600.342 | V30: =+I30*$S30 -> 62578.993 | W30: =+J30*$S30 -> 127113.58 | X30: =+K30*$S30 -> 162314.26 | Y30: =+L30*$S30 -> 187736.98 | Z30: =+M30*$S30 -> 234671.22 | AA30: =+N30*$S30 -> 269871.91 | ... AE30: =+R30*$S30 -> 375473.96
E31: ENDOCRINOLOGY | G31: 0 | H31: 11 | I31: 31 | J31: 59 | K31: 79 | L31: 107 | M31: 130 | N31: 143 | O31: 167 | P31: 243 | Q31: 236 | R31: 228 | S31: 1908.0374 | T31: =+G31*$S31 -> 0 | U31: =+H31*$S31 -> 20988.411 | V31: =+I31*$S31 -> 59149.159 | W31: =+J31*$S31 -> 112574.21 | X31: =+K31*$S31 -> 150734.95 | Y31: =+L31*$S31 -> 204160 | Z31: =+M31*$S31 -> 248044.86 | AA31: =+N31*$S31 -> 272849.34 | ... AE31: =+R31*$S31 -> 435032.52
E32: Spine surgery | G32: 0 | H32: 2 | I32: 7 | J32: 13 | K32: 18 | L32: 22 | M32: 28 | N32: 40 | O32: 36 | P32: 50 | Q32: 40 | R32: 45 | S32: 3217.1108 | T32: =+G32*$S32 -> 0 | U32: =+H32*$S32 -> 6434.2216 | V32: =+I32*$S32 -> 22519.776 | W32: =+J32*$S32 -> 41822.441 | X32: =+K32*$S32 -> 57907.995 | Y32: =+L32*$S32 -> 70776.438 | Z32: =+M32*$S32 -> 90079.103 | AA32: =+N32*$S32 -> 128684.43 | ... AE32: =+R32*$S32 -> 144769.99
E33: EMERGENCY DEPARTMENT | G33: 0 | H33: 15 | I33: 45 | J33: 89 | K33: 126 | L33: 151 | M33: 171 | N33: 203 | O33: 250 | P33: 295 | Q33: 299 | R33: 338 | S33: 1407.5019 | T33: =+G33*$S33 -> 0 | U33: =+H33*$S33 -> 21112.529 | V33: =+I33*$S33 -> 63337.588 | W33: =+J33*$S33 -> 125267.67 | X33: =+K33*$S33 -> 177345.25 | Y33: =+L33*$S33 -> 212532.79 | Z33: =+M33*$S33 -> 240682.83 | AA33: =+N33*$S33 -> 285722.9 | ... AE33: =+R33*$S33 -> 475735.66
E34: PSYCHIATRY | G34: 0 | H34: 5 | I34: 15 | J34: 28 | K34: 38 | L34: 49 | M34: 59 | N34: 66 | O34: 72 | P34: 98 | Q34: 93 | R34: 113 | S34: 1293.6688 | T34: =+G34*$S34 -> 0 | U34: =+H34*$S34 -> 6468.344 | V34: =+I34*$S34 -> 19405.032 | W34: =+J34*$S34 -> 36222.727 | X34: =+K34*$S34 -> 49159.415 | Y34: =+L34*$S34 -> 63389.772 | Z34: =+M34*$S34 -> 76326.46 | AA34: =+N34*$S34 -> 85382.141 | ... AE34: =+R34*$S34 -> 146184.58
E35: DENTAL | G35: 0 | H35: 6 | I35: 16 | J35: 26 | K35: 36 | L35: 46 | M35: 58 | N35: 63 | O35: 70 | P35: 82 | Q35: 92 | R35: 89 | S35: 2285.0631 | T35: =+G35*$S35 -> 0 | U35: =+H35*$S35 -> 13710.379 | V35: =+I35*$S35 -> 36561.01 | W35: =+J35*$S35 -> 59411.641 | X35: =+K35*$S35 -> 82262.272 | Y35: =+L35*$S35 -> 105112.9 | Z35: =+M35*$S35 -> 132533.66 | AA35: =+N35*$S35 -> 143958.98 | ... AE35: =+R35*$S35 -> 203370.62
... E42: PEDIATRIC SURGERY | G42: 0 | H42: 0 | I42: 0 | J42: 0 | K42: 0 | L42: 0 | M42: 0 | N42: 0 | O42: 0 | P42: 0 | Q42: 0 | R42: 0 | S42: 0 | T42: =+G42*$S42 -> 0 | U42: =+H42*$S42 -> 0 | V42: =+I42*$S42 -> 0 | W42: =+J42*$S42 -> 0 | X42: =+K42*$S42 -> 0 | Y42: =+L42*$S42 -> 0 | Z42: =+M42*$S42 -> 0 | AA42: =+N42*$S42 -> 0 | ... AE42: =+R42*$S42 -> 0
G43: 0 | H43: 0 | I43: 0 | J43: 0 | K43: 0 | L43: 0 | M43: 0 | N43: 0 | O43: 0 | P43: 0 | Q43: 0 | R43: 0 | T43: =+G43*$S43 -> 0 | U43: =+H43*$S43 -> 0 | V43: =+I43*$S43 -> 0 | W43: =+J43*$S43 -> 0 | X43: =+K43*$S43 -> 0 | Y43: =+L43*$S43 -> 0 | Z43: =+M43*$S43 -> 0 | AA43: =+N43*$S43 -> 0 | ... AE43: =+R43*$S43 -> 0
E44: JOINT REPLACEMENT & SPORTS MED | G44: 0 | H44: 8 | I44: 21 | J44: 41 | K44: 60 | L44: 68 | M44: 88 | N44: 89 | O44: 120 | P44: 138 | Q44: 139 | R44: 156 | S44: 2232.036 | T44: =+G44*$S44 -> 0 | U44: =+H44*$S44 -> 17856.288 | V44: =+I44*$S44 -> 46872.756 | W44: =+J44*$S44 -> 91513.475 | X44: =+K44*$S44 -> 133922.16 | Y44: =+L44*$S44 -> 151778.45 | Z44: =+M44*$S44 -> 196419.17 | AA44: =+N44*$S44 -> 198651.2 | ... AE44: =+R44*$S44 -> 348197.61
E45: ORTHOPEDICS - DIVISION OF FOOT ANKLE & PODIATRY | G45: 0 | H45: 6 | I45: 18 | J45: 36 | K45: 43 | L45: 58 | M45: 63 | N45: 81 | O45: 104 | P45: 114 | Q45: 127 | R45: 146 | S45: 2232.036 | T45: =+G45*$S45 -> 0 | U45: =+H45*$S45 -> 13392.216 | V45: =+I45*$S45 -> 40176.648 | W45: =+J45*$S45 -> 80353.295 | X45: =+K45*$S45 -> 95977.547 | Y45: =+L45*$S45 -> 129458.09 | Z45: =+M45*$S45 -> 140618.27 | AA45: =+N45*$S45 -> 180794.91 | ... AE45: =+R45*$S45 -> 325877.25
E46: ORTHOPEDICS - DIVISION OF ORTHOPEDIC ONCOLOGY | G46: 0 | H46: 1 | I46: 2 | J46: 3 | K46: 4 | L46: 4 | M46: 4 | N46: 4 | O46: 5 | P46: 6 | Q46: 7 | R46: 10 | S46: 2232.036 | T46: =+G46*$S46 -> 0 | U46: =+H46*$S46 -> 2232.036 | V46: =+I46*$S46 -> 4464.072 | W46: =+J46*$S46 -> 6696.108 | X46: =+K46*$S46 -> 8928.1439 | Y46: =+L46*$S46 -> 8928.1439 | Z46: =+M46*$S46 -> 8928.1439 | AA46: =+N46*$S46 -> 8928.1439 | ... AE46: =+R46*$S46 -> 22320.36
E47: COMPREHENSIVE LIVER CARE - SUR | G47: 0 | H47: 2 | I47: 5 | J47: 9 | K47: 12 | L47: 13 | M47: 17 | N47: 22 | O47: 24 | P47: 29 | Q47: 25 | R47: 33 | S47: 5942.9578 | T47: =+G47*$S47 -> 0 | U47: =+H47*$S47 -> 11885.916 | V47: =+I47*$S47 -> 29714.789 | W47: =+J47*$S47 -> 53486.621 | X47: =+K47*$S47 -> 71315.494 | Y47: =+L47*$S47 -> 77258.452 | Z47: =+M47*$S47 -> 101030.28 | AA47: =+N47*$S47 -> 130745.07 | ... AE47: =+R47*$S47 -> 196117.61
E48: PULMONARY CRITICAL CARE AND SLEEP MEDICINE | G48: 0 | H48: 3 | I48: 4 | J48: 13 | K48: 15 | L48: 23 | M48: 30 | N48: 21 | O48: 41 | P48: 44 | Q48: 37 | R48: 49 | S48: 1758.3157 | T48: =+G48*$S48 -> 0 | U48: =+H48*$S48 -> 5274.9471 | V48: =+I48*$S48 -> 7033.2628 | W48: =+J48*$S48 -> 22858.104 | X48: =+K48*$S48 -> 26374.735 | Y48: =+L48*$S48 -> 40441.261 | Z48: =+M48*$S48 -> 52749.471 | AA48: =+N48*$S48 -> 36924.63 | ... AE48: =+R48*$S48 -> 86157.469
E49: GYNAECOLOGY | G49: 0 | H49: 0 | I49: 0 | J49: 0 | K49: 0 | L49: 0 | M49: 0 | N49: 0 | O49: 0 | P49: 0 | Q49: 1 | R49: 0 | S49: 1611.834 | T49: =+G49*$S49 -> 0 | U49: =+H49*$S49 -> 0 | V49: =+I49*$S49 -> 0 | W49: =+J49*$S49 -> 0 | X49: =+K49*$S49 -> 0 | Y49: =+L49*$S49 -> 0 | Z49: =+M49*$S49 -> 0 | AA49: =+N49*$S49 -> 0 | ... AE49: =+R49*$S49 -> 0
E50: HEAD AND NECK ONCOLOGY | G50: 0 | H50: 0 | I50: 0 | J50: 0 | K50: 0 | L50: 0 | M50: 15 | N50: 19 | O50: 25 | P50: 34 | Q50: 36 | R50: 43 | S50: 2465.6794 | T50: =+G50*$S50 -> 0 | U50: =+H50*$S50 -> 0 | V50: =+I50*$S50 -> 0 | W50: =+J50*$S50 -> 0 | X50: =+K50*$S50 -> 0 | Y50: =+L50*$S50 -> 0 | Z50: =+M50*$S50 -> 36985.192 | AA50: =+N50*$S50 -> 46847.909 | ... AE50: =+R50*$S50 -> 106024.22
E51: NEONATAL ICU | G51: 0 | H51: 0 | I51: 0 | J51: 0 | K51: 0 | L51: 0 | M51: 0 | N51: 0 | O51: 0 | P51: 0 | Q51: 0 | R51: 7 | S51: 810.70795 | T51: =+G51*$S51 -> 0 | U51: =+H51*$S51 -> 0 | V51: =+I51*$S51 -> 0 | W51: =+J51*$S51 -> 0 | X51: =+K51*$S51 -> 0 | Y51: =+L51*$S51 -> 0 | Z51: =+M51*$S51 -> 0 | AA51: =+N51*$S51 -> 0 | ... AE51: =+R51*$S51 -> 5674.9556
G53: IP | T53: IP
T54: =SUM(T55:T98) -> 0 | U54: =SUM(U55:U98) -> 2280443 | V54: =SUM(V55:V98) -> 7444446.5 | W54: =SUM(W55:W98) -> 13421115 | X54: =SUM(X55:X98) -> 17903955 | Y54: =SUM(Y55:Y98) -> 23395707 | Z54: =SUM(Z55:Z98) -> 28755326 | AA54: =SUM(AA55:AA98) -> 31074244 | ... AE54: =SUM(AE55:AE98) -> 54203208
E55: NEPHROLOGY | G55: 0 | H55: 1 | I55: 3 | J55: 5 | K55: 6 | L55: 8 | M55: 11 | N55: 12 | O55: 17 | P55: 23 | Q55: 23 | R55: 27 | S55: 303609.13 | T55: =+G55*$S55 -> 0 | U55: =+H55*$S55 -> 303609.13 | V55: =+I55*$S55 -> 910827.39 | W55: =+J55*$S55 -> 1518045.7 | X55: =+K55*$S55 -> 1821654.8 | Y55: =+L55*$S55 -> 2428873 | Z55: =+M55*$S55 -> 3339700.4 | AA55: =+N55*$S55 -> 3643309.6 | ... AE55: =+R55*$S55 -> 8197446.5
E56: MEDICAL ONCOLOGY | G56: 0 | H56: 5 | I56: 14 | J56: 26 | K56: 32 | L56: 43 | M56: 56 | N56: 56 | O56: 72 | P56: 82 | Q56: 86 | R56: 98 | S56: 60454.843 | T56: =+G56*$S56 -> 0 | U56: =+H56*$S56 -> 302274.22 | V56: =+I56*$S56 -> 846367.81 | W56: =+J56*$S56 -> 1571825.9 | X56: =+K56*$S56 -> 1934555 | Y56: =+L56*$S56 -> 2599558.3 | Z56: =+M56*$S56 -> 3385471.2 | AA56: =+N56*$S56 -> 3385471.2 | ... AE56: =+R56*$S56 -> 5924574.6
E57: ORTHOPEDICS | G57: 0 | H57: 0 | I57: 1 | J57: 1 | K57: 1 | L57: 2 | M57: 3 | N57: 3 | O57: 5 | P57: 6 | Q57: 6 | R57: 7 | S57: 233914.61 | T57: =+G57*$S57 -> 0 | U57: =+H57*$S57 -> 0 | V57: =+I57*$S57 -> 233914.61 | W57: =+J57*$S57 -> 233914.61 | X57: =+K57*$S57 -> 233914.61 | Y57: =+L57*$S57 -> 467829.21 | Z57: =+M57*$S57 -> 701743.82 | AA57: =+N57*$S57 -> 701743.82 | ... AE57: =+R57*$S57 -> 1637402.2
E58: NEURO SURGERY | G58: 0 | H58: 1 | I58: 3 | J58: 5 | K58: 8 | L58: 10 | M58: 11 | N58: 12 | O58: 14 | P58: 19 | Q58: 18 | R58: 20 | S58: 269243.95 | T58: =+G58*$S58 -> 0 | U58: =+H58*$S58 -> 269243.95 | V58: =+I58*$S58 -> 807731.86 | W58: =+J58*$S58 -> 1346219.8 | X58: =+K58*$S58 -> 2153951.6 | Y58: =+L58*$S58 -> 2692439.5 | Z58: =+M58*$S58 -> 2961683.5 | AA58: =+N58*$S58 -> 3230927.5 | ... AE58: =+R58*$S58 -> 5384879.1
E59: GI SURGERY | G59: 0 | H59: 1 | I59: 3 | J59: 5 | K59: 7 | L59: 9 | M59: 13 | N59: 11 | O59: 14 | P59: 19 | Q59: 18 | R59: 19 | S59: 196299.55 | T59: =+G59*$S59 -> 0 | U59: =+H59*$S59 -> 196299.55 | V59: =+I59*$S59 -> 588898.65 | W59: =+J59*$S59 -> 981497.74 | X59: =+K59*$S59 -> 1374096.8 | Y59: =+L59*$S59 -> 1766695.9 | Z59: =+M59*$S59 -> 2551894.1 | AA59: =+N59*$S59 -> 2159295 | ... AE59: =+R59*$S59 -> 3729691.4
E60: GASTROENTEROLOGY | G60: 0 | H60: 1 | I60: 3 | J60: 6 | K60: 9 | L60: 10 | M60: 12 | N60: 12 | O60: 15 | P60: 19 | Q60: 19 | R60: 19 | S60: 98304.556 | T60: =+G60*$S60 -> 0 | U60: =+H60*$S60 -> 98304.556 | V60: =+I60*$S60 -> 294913.67 | W60: =+J60*$S60 -> 589827.34 | X60: =+K60*$S60 -> 884741 | Y60: =+L60*$S60 -> 983045.56 | Z60: =+M60*$S60 -> 1179654.7 | AA60: =+N60*$S60 -> 1179654.7 | ... AE60: =+R60*$S60 -> 1867786.6
E61: CARDIOLOGY | G61: 0 | H61: 1 | I61: 3 | J61: 6 | K61: 8 | L61: 11 | M61: 13 | N61: 14 | O61: 16 | P61: 21 | Q61: 20 | R61: 23 | S61: 161575.61 | T61: =+G61*$S61 -> 0 | U61: =+H61*$S61 -> 161575.61 | V61: =+I61*$S61 -> 484726.83 | W61: =+J61*$S61 -> 969453.66 | X61: =+K61*$S61 -> 1292604.9 | Y61: =+L61*$S61 -> 1777331.7 | Z61: =+M61*$S61 -> 2100482.9 | AA61: =+N61*$S61 -> 2262058.5 | ... AE61: =+R61*$S61 -> 3716239
E62: UROLOGY | G62: 0 | H62: 1 | I62: 2 | J62: 5 | K62: 6 | L62: 8 | M62: 9 | N62: 10 | O62: 12 | P62: 15 | Q62: 15 | R62: 17 | S62: 163617.48 | T62: =+G62*$S62 -> 0 | U62: =+H62*$S62 -> 163617.48 | V62: =+I62*$S62 -> 327234.95 | W62: =+J62*$S62 -> 818087.39 | X62: =+K62*$S62 -> 981704.86 | Y62: =+L62*$S62 -> 1308939.8 | Z62: =+M62*$S62 -> 1472557.3 | AA62: =+N62*$S62 -> 1636174.8 | ... AE62: =+R62*$S62 -> 2781497.1
E63: SURGICAL ONCOLOGY | G63: 0 | H63: 1 | I63: 2 | J63: 5 | K63: 6 | L63: 8 | M63: 8 | N63: 7 | O63: 9 | P63: 12 | Q63: 12 | R63: 12 | S63: 175968.72 | T63: =+G63*$S63 -> 0 | U63: =+H63*$S63 -> 175968.72 | V63: =+I63*$S63 -> 351937.44 | W63: =+J63*$S63 -> 879843.6 | X63: =+K63*$S63 -> 1055812.3 | Y63: =+L63*$S63 -> 1407749.8 | Z63: =+M63*$S63 -> 1407749.8 | AA63: =+N63*$S63 -> 1231781 | ... AE63: =+R63*$S63 -> 2111624.6
E64: MINIMALLY INVASIVE SURGERY | G64: 0 | H64: 1 | I64: 1 | J64: 4 | K64: 4 | L64: 5 | M64: 7 | N64: 8 | O64: 12 | P64: 12 | Q64: 10 | R64: 13 | S64: 183869.55 | T64: =+G64*$S64 -> 0 | U64: =+H64*$S64 -> 183869.55 | V64: =+I64*$S64 -> 183869.55 | W64: =+J64*$S64 -> 735478.19 | X64: =+K64*$S64 -> 735478.19 | Y64: =+L64*$S64 -> 919347.74 | Z64: =+M64*$S64 -> 1287086.8 | AA64: =+N64*$S64 -> 1470956.4 | ... AE64: =+R64*$S64 -> 2390304.1
E65: COMPREHENSIVE LIVER CARE | G65: 0 | H65: 0 | I65: 0 | J65: 0 | K65: 0 | L65: 0 | M65: 0 | N65: 0 | O65: 1 | P65: 1 | Q65: 1 | R65: 1 | S65: 487489.56 | T65: =+G65*$S65 -> 0 | U65: =+H65*$S65 -> 0 | V65: =+I65*$S65 -> 0 | W65: =+J65*$S65 -> 0 | X65: =+K65*$S65 -> 0 | Y65: =+L65*$S65 -> 0 | Z65: =+M65*$S65 -> 0 | AA65: =+N65*$S65 -> 0 | ... AE65: =+R65*$S65 -> 487489.56
E66: NEUROLOGY | G66: 0 | H66: 1 | I66: 2 | J66: 4 | K66: 6 | L66: 7 | M66: 10 | N66: 11 | O66: 11 | P66: 17 | Q66: 15 | R66: 16 | S66: 89841.225 | T66: =+G66*$S66 -> 0 | U66: =+H66*$S66 -> 89841.225 | V66: =+I66*$S66 -> 179682.45 | W66: =+J66*$S66 -> 359364.9 | X66: =+K66*$S66 -> 539047.35 | Y66: =+L66*$S66 -> 628888.58 | Z66: =+M66*$S66 -> 898412.25 | AA66: =+N66*$S66 -> 988253.48 | ... AE66: =+R66*$S66 -> 1437459.6
... E69: PEDIATRICS | G69: 0 | H69: 1 | I69: 3 | J69: 7 | K69: 9 | L69: 12 | M69: 13 | N69: 16 | O69: 19 | P69: 19 | Q69: 25 | R69: 23 | S69: 33256.565 | T69: =+G69*$S69 -> 0 | U69: =+H69*$S69 -> 33256.565 | V69: =+I69*$S69 -> 99769.696 | W69: =+J69*$S69 -> 232795.96 | X69: =+K69*$S69 -> 299309.09 | Y69: =+L69*$S69 -> 399078.78 | Z69: =+M69*$S69 -> 432335.35 | AA69: =+N69*$S69 -> 532105.05 | ... AE69: =+R69*$S69 -> 764901
T70: =+G70*$S70 -> 0 | U70: =+H70*$S70 -> 0 | V70: =+I70*$S70 -> 0 | W70: =+J70*$S70 -> 0 | X70: =+K70*$S70 -> 0 | Y70: =+L70*$S70 -> 0 | Z70: =+M70*$S70 -> 0 | AA70: =+N70*$S70 -> 0 | ... AE70: =+R70*$S70 -> 0
E71: RADIATION ONCOLOGY | G71: 0 | H71: 0 | I71: 0 | J71: 0 | K71: 0 | L71: 0 | M71: 0 | N71: 0 | O71: 0 | P71: 0 | Q71: 0 | R71: 0 | S71: 48428.881 | T71: =+G71*$S71 -> 0 | U71: =+H71*$S71 -> 0 | V71: =+I71*$S71 -> 0 | W71: =+J71*$S71 -> 0 | X71: =+K71*$S71 -> 0 | Y71: =+L71*$S71 -> 0 | Z71: =+M71*$S71 -> 0 | AA71: =+N71*$S71 -> 0 | ... AE71: =+R71*$S71 -> 0
E72: CARDIO THORACIC SURGERY | G72: 0 | H72: 0 | I72: 1 | J72: 1 | K72: 1 | L72: 2 | M72: 2 | N72: 2 | O72: 2 | P72: 4 | Q72: 3 | R72: 3 | S72: 309349.33 | T72: =+G72*$S72 -> 0 | U72: =+H72*$S72 -> 0 | V72: =+I72*$S72 -> 309349.33 | W72: =+J72*$S72 -> 309349.33 | X72: =+K72*$S72 -> 309349.33 | Y72: =+L72*$S72 -> 618698.67 | Z72: =+M72*$S72 -> 618698.67 | AA72: =+N72*$S72 -> 618698.67 | ... AE72: =+R72*$S72 -> 928048
E73: PULMONOLOGY | G73: 0 | H73: 0 | I73: 1 | J73: 1 | K73: 2 | L73: 3 | M73: 3 | N73: 4 | O73: 4 | P73: 6 | Q73: 5 | R73: 6 | S73: 98026.1 | T73: =+G73*$S73 -> 0 | U73: =+H73*$S73 -> 0 | V73: =+I73*$S73 -> 98026.1 | W73: =+J73*$S73 -> 98026.1 | X73: =+K73*$S73 -> 196052.2 | Y73: =+L73*$S73 -> 294078.3 | Z73: =+M73*$S73 -> 294078.3 | AA73: =+N73*$S73 -> 392104.4 | ... AE73: =+R73*$S73 -> 588156.6
E74: PLASTIC SURGERY | G74: 0 | H74: 0 | I74: 1 | J74: 1 | K74: 1 | L74: 2 | M74: 2 | N74: 3 | O74: 3 | P74: 3 | Q74: 4 | R74: 5 | S74: 145519.83 | T74: =+G74*$S74 -> 0 | U74: =+H74*$S74 -> 0 | V74: =+I74*$S74 -> 145519.83 | W74: =+J74*$S74 -> 145519.83 | X74: =+K74*$S74 -> 145519.83 | Y74: =+L74*$S74 -> 291039.67 | Z74: =+M74*$S74 -> 291039.67 | AA74: =+N74*$S74 -> 436559.5 | ... AE74: =+R74*$S74 -> 727599.17
E75: ENT | G75: 0 | H75: 0 | I75: 1 | J75: 1 | K75: 2 | L75: 2 | M75: 3 | N75: 3 | O75: 4 | P75: 5 | Q75: 4 | R75: 5 | S75: 92348.217 | T75: =+G75*$S75 -> 0 | U75: =+H75*$S75 -> 0 | V75: =+I75*$S75 -> 92348.217 | W75: =+J75*$S75 -> 92348.217 | X75: =+K75*$S75 -> 184696.43 | Y75: =+L75*$S75 -> 184696.43 | Z75: =+M75*$S75 -> 277044.65 | AA75: =+N75*$S75 -> 277044.65 | ... AE75: =+R75*$S75 -> 461741.09
E76: FAMILY MEDICINE | G76: 0 | H76: 0 | I76: 0 | J76: 0 | K76: 0 | L76: 0 | M76: 0 | N76: 0 | O76: 0 | P76: 0 | Q76: 0 | R76: 0 | S76: 0 | T76: =+G76*$S76 -> 0 | U76: =+H76*$S76 -> 0 | V76: =+I76*$S76 -> 0 | W76: =+J76*$S76 -> 0 | X76: =+K76*$S76 -> 0 | Y76: =+L76*$S76 -> 0 | Z76: =+M76*$S76 -> 0 | AA76: =+N76*$S76 -> 0 | ... AE76: =+R76*$S76 -> 0
E77: DERMATOLOGY & V D | G77: 0 | H77: 0 | I77: 0 | J77: 0 | K77: 1 | L77: 1 | M77: 1 | N77: 1 | O77: 1 | P77: 1 | Q77: 1 | R77: 1 | S77: 44020.502 | T77: =+G77*$S77 -> 0 | U77: =+H77*$S77 -> 0 | V77: =+I77*$S77 -> 0 | W77: =+J77*$S77 -> 0 | X77: =+K77*$S77 -> 44020.502 | Y77: =+L77*$S77 -> 44020.502 | Z77: =+M77*$S77 -> 44020.502 | AA77: =+N77*$S77 -> 44020.502 | ... AE77: =+R77*$S77 -> 44020.502
E78: ENDOCRINOLOGY | G78: 0 | H78: 0 | I78: 0 | J78: 0 | K78: 1 | L78: 1 | M78: 1 | N78: 1 | O78: 1 | P78: 2 | Q78: 2 | R78: 2 | S78: 46036.704 | T78: =+G78*$S78 -> 0 | U78: =+H78*$S78 -> 0 | V78: =+I78*$S78 -> 0 | W78: =+J78*$S78 -> 0 | X78: =+K78*$S78 -> 46036.704 | Y78: =+L78*$S78 -> 46036.704 | Z78: =+M78*$S78 -> 46036.704 | AA78: =+N78*$S78 -> 46036.704 | ... AE78: =+R78*$S78 -> 92073.408
E79: Spine surgery | G79: 0 | H79: 0 | I79: 0 | J79: 1 | K79: 1 | L79: 1 | M79: 1 | N79: 2 | O79: 2 | P79: 2 | Q79: 2 | R79: 2 | S79: 307760.22 | T79: =+G79*$S79 -> 0 | U79: =+H79*$S79 -> 0 | V79: =+I79*$S79 -> 0 | W79: =+J79*$S79 -> 307760.22 | X79: =+K79*$S79 -> 307760.22 | Y79: =+L79*$S79 -> 307760.22 | Z79: =+M79*$S79 -> 307760.22 | AA79: =+N79*$S79 -> 615520.44 | ... AE79: =+R79*$S79 -> 615520.44
E80: EMERGENCY DEPARTMENT | G80: 0 | H80: 0 | I80: 0 | J80: 0 | K80: 0 | L80: 0 | M80: 0 | N80: 0 | O80: 0 | P80: 0 | Q80: 0 | R80: 0 | S80: 3367.9563 | T80: =+G80*$S80 -> 0 | U80: =+H80*$S80 -> 0 | V80: =+I80*$S80 -> 0 | W80: =+J80*$S80 -> 0 | X80: =+K80*$S80 -> 0 | Y80: =+L80*$S80 -> 0 | Z80: =+M80*$S80 -> 0 | AA80: =+N80*$S80 -> 0 | ... AE80: =+R80*$S80 -> 0
E81: PSYCHIATRY | G81: 0 | H81: 0 | I81: 1 | J81: 1 | K81: 1 | L81: 2 | M81: 2 | N81: 3 | O81: 3 | P81: 4 | Q81: 4 | R81: 4 | S81: 54853.656 | T81: =+G81*$S81 -> 0 | U81: =+H81*$S81 -> 0 | V81: =+I81*$S81 -> 54853.656 | W81: =+J81*$S81 -> 54853.656 | X81: =+K81*$S81 -> 54853.656 | Y81: =+L81*$S81 -> 109707.31 | Z81: =+M81*$S81 -> 109707.31 | AA81: =+N81*$S81 -> 164560.97 | ... AE81: =+R81*$S81 -> 219414.62
E82: DENTAL | G82: 0 | H82: 0 | I82: 0 | J82: 0 | K82: 0 | L82: 0 | M82: 0 | N82: 0 | O82: 0 | P82: 0 | Q82: 0 | R82: 0 | S82: 103057.29 | T82: =+G82*$S82 -> 0 | U82: =+H82*$S82 -> 0 | V82: =+I82*$S82 -> 0 | W82: =+J82*$S82 -> 0 | X82: =+K82*$S82 -> 0 | Y82: =+L82*$S82 -> 0 | Z82: =+M82*$S82 -> 0 | AA82: =+N82*$S82 -> 0 | ... AE82: =+R82*$S82 -> 0
... E89: PEDIATRIC SURGERY | G89: 0 | H89: 0 | I89: 0 | J89: 0 | K89: 0 | L89: 0 | M89: 0 | N89: 0 | O89: 0 | P89: 0 | Q89: 0 | R89: 0 | S89: 0 | T89: =+G89*$S89 -> 0 | U89: =+H89*$S89 -> 0 | V89: =+I89*$S89 -> 0 | W89: =+J89*$S89 -> 0 | X89: =+K89*$S89 -> 0 | Y89: =+L89*$S89 -> 0 | Z89: =+M89*$S89 -> 0 | AA89: =+N89*$S89 -> 0 | ... AE89: =+R89*$S89 -> 0
T90: =+G90*$S90 -> 0 | U90: =+H90*$S90 -> 0 | V90: =+I90*$S90 -> 0 | W90: =+J90*$S90 -> 0 | X90: =+K90*$S90 -> 0 | Y90: =+L90*$S90 -> 0 | Z90: =+M90*$S90 -> 0 | AA90: =+N90*$S90 -> 0 | ... AE90: =+R90*$S90 -> 0
E91: JOINT REPLACEMENT & SPORTS MED | G91: 0 | H91: 1 | I91: 2 | J91: 3 | K91: 4 | L91: 5 | M91: 7 | N91: 7 | O91: 9 | P91: 10 | Q91: 10 | R91: 12 | S91: 233914.61 | T91: =+G91*$S91 -> 0 | U91: =+H91*$S91 -> 233914.61 | V91: =+I91*$S91 -> 467829.21 | W91: =+J91*$S91 -> 701743.82 | X91: =+K91*$S91 -> 935658.42 | Y91: =+L91*$S91 -> 1169573 | Z91: =+M91*$S91 -> 1637402.2 | AA91: =+N91*$S91 -> 1637402.2 | ... AE91: =+R91*$S91 -> 2806975.3
E92: ORTHOPEDICS - DIVISION OF FOOT ANKLE & PODIATRY | G92: 0 | H92: 0 | I92: 1 | J92: 2 | K92: 3 | L92: 4 | M92: 4 | N92: 5 | O92: 7 | P92: 7 | Q92: 8 | R92: 9 | S92: 233914.61 | T92: =+G92*$S92 -> 0 | U92: =+H92*$S92 -> 0 | V92: =+I92*$S92 -> 233914.61 | W92: =+J92*$S92 -> 467829.21 | X92: =+K92*$S92 -> 701743.82 | Y92: =+L92*$S92 -> 935658.42 | Z92: =+M92*$S92 -> 935658.42 | AA92: =+N92*$S92 -> 1169573 | ... AE92: =+R92*$S92 -> 2105231.5
E93: ORTHOPEDICS - DIVISION OF ORTHOPEDIC ONCOLOGY | G93: 0 | H93: 0 | I93: 0 | J93: 0 | K93: 0 | L93: 0 | M93: 0 | N93: 0 | O93: 0 | P93: 1 | Q93: 1 | R93: 1 | S93: 233914.61 | T93: =+G93*$S93 -> 0 | U93: =+H93*$S93 -> 0 | V93: =+I93*$S93 -> 0 | W93: =+J93*$S93 -> 0 | X93: =+K93*$S93 -> 0 | Y93: =+L93*$S93 -> 0 | Z93: =+M93*$S93 -> 0 | AA93: =+N93*$S93 -> 0 | ... AE93: =+R93*$S93 -> 233914.61
E94: COMPREHENSIVE LIVER CARE - SUR | G94: 0 | H94: 0 | I94: 1 | J94: 1 | K94: 2 | L94: 2 | M94: 2 | N94: 3 | O94: 3 | P94: 4 | Q94: 3 | R94: 4 | S94: 487489.56 | T94: =+G94*$S94 -> 0 | U94: =+H94*$S94 -> 0 | V94: =+I94*$S94 -> 487489.56 | W94: =+J94*$S94 -> 487489.56 | X94: =+K94*$S94 -> 974979.12 | Y94: =+L94*$S94 -> 974979.12 | Z94: =+M94*$S94 -> 974979.12 | AA94: =+N94*$S94 -> 1462468.7 | ... AE94: =+R94*$S94 -> 1949958.2
E95: PULMONARY CRITICAL CARE AND SLEEP MEDICINE | G95: 0 | H95: 0 | I95: 0 | J95: 1 | K95: 1 | L95: 2 | M95: 2 | N95: 2 | O95: 3 | P95: 3 | Q95: 3 | R95: 4 | S95: 98026.1 | T95: =+G95*$S95 -> 0 | U95: =+H95*$S95 -> 0 | V95: =+I95*$S95 -> 0 | W95: =+J95*$S95 -> 98026.1 | X95: =+K95*$S95 -> 98026.1 | Y95: =+L95*$S95 -> 196052.2 | Z95: =+M95*$S95 -> 196052.2 | AA95: =+N95*$S95 -> 196052.2 | ... AE95: =+R95*$S95 -> 392104.4
E96: GYNAECOLOGY | G96: 0 | H96: 0 | I96: 0 | J96: 0 | K96: 0 | L96: 0 | M96: 0 | N96: 0 | O96: 0 | P96: 0 | Q96: 0 | R96: 0 | S96: 107905.47 | T96: =+G96*$S96 -> 0 | U96: =+H96*$S96 -> 0 | V96: =+I96*$S96 -> 0 | W96: =+J96*$S96 -> 0 | X96: =+K96*$S96 -> 0 | Y96: =+L96*$S96 -> 0 | Z96: =+M96*$S96 -> 0 | AA96: =+N96*$S96 -> 0 | ... AE96: =+R96*$S96 -> 0
E97: HEAD AND NECK ONCOLOGY | G97: 0 | H97: 0 | I97: 0 | J97: 0 | K97: 0 | L97: 0 | M97: 1 | N97: 2 | O97: 2 | P97: 3 | Q97: 3 | R97: 4 | S97: 175968.72 | T97: =+G97*$S97 -> 0 | U97: =+H97*$S97 -> 0 | V97: =+I97*$S97 -> 0 | W97: =+J97*$S97 -> 0 | X97: =+K97*$S97 -> 0 | Y97: =+L97*$S97 -> 0 | Z97: =+M97*$S97 -> 175968.72 | AA97: =+N97*$S97 -> 351937.44 | ... AE97: =+R97*$S97 -> 703874.88
E98: NEONATAL ICU | G98: 0 | H98: 0 | I98: 0 | J98: 0 | K98: 0 | L98: 0 | M98: 0 | N98: 0 | O98: 0 | P98: 0 | Q98: 0 | R98: 4 | S98: 33256.565 | T98: =+G98*$S98 -> 0 | U98: =+H98*$S98 -> 0 | V98: =+I98*$S98 -> 0 | W98: =+J98*$S98 -> 0 | X98: =+K98*$S98 -> 0 | Y98: =+L98*$S98 -> 0 | Z98: =+M98*$S98 -> 0 | AA98: =+N98*$S98 -> 0 | ... AE98: =+R98*$S98 -> 133026.26

Sheet R-12
A1: R-12 | New Specialties, Procedures & Packages
A2: Revenue — High-Value Services
A3: OVERVIEW
A4: Description / Objective | B4: Launch new high-end, high-value specialties and packages based on Kochi/Kerala market dynamics and existing infrastructure strengths: (A) Structural Heart & EP: TAVR/MitraClip/LAAO programme with device company partnership; grow EP lab utilisation; expand paediatric cardiac volumes. Each TAVR = ₹6–10L revenue. (B) Orthopaedics & Joint Replacement Packages: All-inclusive fixed-price joint replacement. Sports medicine programme. Leverage India-first digitally integrated orthopaedic OT and first bilateral total hip (ceramic/metal liner) in Asia. (C) Comprehensive Cancer Packages: All-inclusive chemotherapy cycles (per protocol), radiation therapy packages (IMRT/IGRT per course), and surgical oncology bundles (breast, colorectal, head & neck) with upfront pricing. (D) Liver & Multi-Organ Transplant Packages: Fixed-price living-donor liver transplant and kidney transplant bundles including 90-day post-op immunosuppression. Leverage Lakeshore’s transplant leadership. (E) Bariatric & Metabolic Surgery: All-inclusive sleeve gastrectomy and gastric bypass packages. Kerala has rising obesity and diabetes prevalence; few hospitals offer structured bariatric programmes. (F) Advanced Neurosurgery: Stereotactic radiosurgery (Gamma Knife/CyberKnife referral pathway), deep brain stimulation for Parkinson’s, minimally invasive spine packages. (G) Fertility & Reproductive Medicine: IVF packages with transparent per-cycle pricing. Growing demand from 30–40 age group; competitors (CIMAR, KJK) are standalone clinics — hospital-backed IVF has a trust advantage. (H) Executive & Preventive Health Packages: Premium 2-day comprehensive health checks (cardiac risk, cancer screening, metabolic profiling, genomic risk assessment). Targets NRIs, corporate executives, Gulf returnees.
A5: Start Month | B5: 46143
A6: Estimated Cost | B6: ₹19L one-time capex (device partnerships + package design + billing config + marketing collateral)
A7: Expected Impact | B7: ₹11 Cr
A9: BASIS FOR THIS INITIATIVE
A10: Kerala has strong demand for high-end cardiac procedures (TAVR market growing 30%+ annually in India), sports medicine is underserved, and all-inclusive joint replacement packages are proven volume drivers at Apollo and Manipal. Lakeshore has the infrastructure and clinical talent — the gap is commercial packaging and active marketing of these capabilities. PACKAGE REVENUE ESTIMATES (Year 1 conservative): • TAVR/MitraClip: 50 cases × ₹8L avg = ₹4 Cr • Joint Replacement (TKR/THR/Bilateral): 200 packages × ₹3L avg = ₹6 Cr — partially cannibalises existing volumes, net incremental ~₹2 Cr • Cancer Packages: 100 new bundled patients × ₹4L avg = ₹4 Cr — partially existing, net incremental ~₹1.5 Cr • Transplant Packages: 15 incremental transplants × ₹15L avg = ₹2.25 Cr — net ~₹1 Cr • Bariatric: 40 cases × ₹3L = ₹1.2 Cr • Neurosurgery: 30 cases × ₹5L = ₹1.5 Cr — net ~₹0.5 Cr • Fertility: 80 IVF cycles × ₹2L = ₹1.6 Cr • Executive Health: 500 packages × ₹25K = ₹1.25 Cr Total gross: ~₹22 Cr | Net incremental (after cannibalisation): ~₹11 Cr conservative
A11: EXECUTION TRACKING (to be completed)
A12: Owner | B12: Medical Superintendent / Chief Medical Officer / Head BD
A13: Key Milestones / Actions | B13: 1. Finalise TAVR/MitraClip programme with device partner (Medtronic or Edwards) by Jun-26 2. Design 3 all-inclusive joint replacement packages (Total Knee, Total Hip, Bilateral) with published prices by May-26 3. Launch sports medicine programme: dedicated clinic, physio integration, athlete partnerships by Jul-26 4. Design comprehensive cancer packages (chemo cycle, radiation course, surgical bundles) with oncology team by Jun-26 5. Structure fixed-price transplant packages (liver, kidney) with 90-day post-op inclusion by Jul-26 6. Launch bariatric surgery programme: surgeon recruitment or upskilling, dietitian integration, support group by Aug-26 7. Evaluate advanced neurosurgery packages (DBS, stereotactic) and referral pathways by Sep-26 8. Assess IVF programme feasibility: infrastructure needs, regulatory, embryologist recruitment by Jul-26 9. Design 3-tier executive health packages (Standard/Premium/Platinum) by May-26 10. Publish clinical outcomes data for all packaged procedures (infection rate, LOS, readmission) by Sep-26 11. Marketing campaign for each new package: digital + referring doctor outreach 12. Target Year 1: 50 TAVR, 200 joint replacements, 100 cancer bundles, 15 transplants, 40 bariatric, 80 IVF, 500 executive health checks
A14: Risks / Dependencies | B14: 1. TAVR requires significant device inventory investment and trained cath lab team 2. Fixed-price packages carry cost risk if complications increase LOS 3. New specialty launches depend on recruiting or retaining key clinicians 4. Competition from AIMS and KIMS on cardiac interventions is strong
A15: Remarks | B15: Orthopaedics and joint replacement packaging is consolidated into this initiative alongside structural heart and new specialty launches. Packages should be published on the website with transparent pricing — this is a major differentiator in the Kerala market where pricing is typically opaque.

Sheet R-13
A1: R-13 | Clinician Recruitment & Specialty Team Building
A2: Revenue — High-Value Services
A3: OVERVIEW
A4: Description / Objective | B4: Recruit senior clinicians in 6 specialties where Lakeshore is underweight vs Aster / KIMS / Amrita. A top consultant with an established referral network brings ₹3–5 Cr/yr in IP revenue within 12–18 months. SPECIALTY GAPS: (A) Women's Health & Obstetrics — HIGH GAP. Target: 2 OB-GYN + 1 foetal medicine; branded maternity unit. (B) Paediatrics & Neonatology — HIGH GAP. Target: 1 neonatologist + 1 paed surgeon; NICU upgrade to Level III. (C) Pulmonology — MODERATE GAP. Target: 1 interventional pulmonologist; launch sleep lab. (D) Endocrinology — MODERATE GAP. Target: 1 endocrinologist; structured diabetes programme. (E) Rheumatology — MODERATE GAP. Target: 1 rheumatologist; cross-refer with ortho/nephro. (F) ENT & Head-Neck — STRATEGIC GAP. Target: 1 senior ENT (cochlear + skull base); link to H&N cancer centre.
A5: Start Month | B5: 46143
A6: Estimated Cost | B6: ₹4 Cr/yr opex — 7–8 senior consultant packages (₹60L–1 Cr each fixed/minimum-guaranteed) + relocation + 12-mo practice guarantee top-up. Year 1 may include additional ₹1–2 Cr one-time practice-guarantee exposure before ramp-up. ₹90L one-time capex (NICU Level III upgrade + sleep lab + maternity branding).
A7: Expected Impact | B7: ₹20 Cr
A9: BASIS FOR THIS INITIATIVE
A10: Rationale | B10: Hospital revenue follows clinical talent — a senior consultant with an established referral base brings volume from Day 1. A productive senior surgeon generates ₹3–5 Cr/yr IP; a high-volume medical specialist generates ₹1.5–2.5 Cr/yr OP + downstream IP. IMPACT BUILD-UP (₹20 Cr conservative, Year 2 run-rate): (A) Women's Health: ₹5 Cr — 300–400 deliveries Yr2 × ₹1.5L + gynae surgery + fertility. (B) Paed & NICU: ₹4 Cr — 200 NICU admits × ₹1.5L + 100 paed surgeries × ₹1L. (C) Pulmonology: ₹3 Cr — OP + interventional (EBUS) + sleep studies + IP referrals (COPD, ILD, lung ca). (D) Endocrinology: ₹2 Cr — diabetes programme: 2,000 pts × ₹10K/yr value. (E) Rheumatology: ₹1.5 Cr — high-loyalty OP + biologics infusion + IP referrals. (F) ENT: ₹4.5 Cr — cochlear implants 30/yr × ₹6L + skull base 50/yr × ₹2L + general ENT. Total Yr2 run-rate: ₹20 Cr. Yr1 (ramp): ~₹10–12 Cr (staggered joins Q1–Q3; 6–12 month practice build).
A11: EXECUTION TRACKING (to be completed)
A12: Owner | B12: Head HR / Respective Specialty HODs
A13: Key Milestones / Actions | B13: 1. Finalise target profiles and compensation benchmarks for all 6 specialties by May-26 2. Engage medical recruitment firm (or CEO direct outreach) by May-26 3. Priority 1 (Women's Health — 2 OB-GYN + 1 foetal medicine): offers Jul-26, onboard Sep-26 4. Priority 2 (ENT skull base + Neonatologist): offers Aug-26, onboard Oct-26 5. Priority 3 (Pulm + Endo + Rheum): offers Sep-26, onboard Nov-26 6. Paed surgeon: recruit by Dec-26 (6-mo notice likely) 7. NICU Level III upgrade: RFQ Jun-26, complete Oct-26 8. Sleep lab: procurement Jul-26, operational Sep-26 9. Maternity branding/renovation: design Jun-26, complete Aug-26 10. Each hire: 12-month practice guarantee + BD support (top-50 referrer introductions within 30 days; digital profiles within 2 weeks) 11. Track monthly OP/IP volumes per clinician; quarterly review with Medical Sup.
A14: Risks / Dependencies | B14: 1. Talent availability — top Kerala clinicians settled at Aster/Amrita/KIMS; may need to recruit from outside state 2. Compensation escalation — bidding war risk; need ceiling per role 3. Practice ramp slower than expected — mitigated by 12-mo guarantee + BD 4. Infrastructure delays (NICU, sleep lab) could delay dependent hires 5. Cultural integration with existing department heads — needs CEO-level onboarding Dependencies: NICU capex, sleep lab setup, maternity renovation, board-approved comp packages.
A15: Remarks | B15: Feeds R-12 (New Specialties) by providing clinical talent for bariatric, IVF etc. Feeds R-09 (BD Org) by creating referral magnets. ₹20 Cr is additive — new capabilities, not cannibalisation of existing volumes.
A16: Bequip Remarks | B16: This can be better planned after looking into the capacity each doctor in the department can handle

Sheet R-14
A1: R-14 | Quarterly Health Events Calendar
A2: Revenue — Marketing & Patient Acquisition | T2: Count Increase- OP
A3: OVERVIEW | D3: Particulars | F3: Apr | G3: May | H3: Jun | I3: Jul | J3: Aug | K3: Sep | L3: Oct | M3: Nov | N3: Dec | O3: Jan | P3: Feb | Q3: Mar | R3: Total | T3: Apr | U3: May | V3: Jun | W3: Jul | X3: Aug | Y3: Sep | Z3: Oct | AA3: Nov | AB3: Dec | AC3: Jan | AD3: Feb | AE3: Mar
A4: Description / Objective | B4: Rebrand from single Heart Run to a structured quarterly events calendar. Four flagship events per year: (1) Lakeshore Heart Run (Q2 — cardiac awareness, half-marathon/10K), (2) Liver Week (Q3 — liver health screenings, transplant awareness), (3) Cancer Awareness Drive (Q4 — aligned with Breast Cancer/World Cancer Day), (4) Diabetes & Metabolic Health Camp (Q1 — aligned with World Diabetes Day). Each event: 3,000-5,000 participants, health screenings, OPD follow-ups, media coverage, sponsorship. Entry fees + pharma/device sponsorship cover costs. | H4: To plan a run | J4: Heart Run | M4: Liver Week | O4: Cancer Awareness | Q4: Diabetes Camp
A5: Start Month | B5: 46266 | D5: Cost of Events | H5: -3000000 | J5: -3000000 | M5: -3000000 | O5: -3000000 | Q5: -3000000 | R5: =SUM(F5:Q5) -> -15000000
A6: Estimated Cost | B6: ₹1.1 Cr/yr (5 events × ₹10–12L + media ₹40–50L; partial sponsorship recovery) | D6: Sponsorship Expected Minimum | H6: 700000 | J6: 700000 | M6: 700000 | O6: 700000 | Q6: 700000 | R6: =SUM(F6:Q6) -> 3500000
A7: Expected Impact | B7: ₹1.5 Cr | D7: Revenue Expected | F7: =SUM(F8:F29) -> 0 | G7: =SUM(G8:G29) -> 0 | H7: =SUM(H8:H29) -> 2276100 | I7: =SUM(I8:I29) -> 0 | J7: =SUM(J8:J29) -> 3779120 | K7: =SUM(K8:K29) -> 0 | L7: =SUM(L8:L29) -> 0 | M7: =SUM(M8:M29) -> 4509040 | ... R7: =SUM(R8:R29) -> 15030060
D8: OP | R8: =SUM(F8:Q8) -> 0 | S8: ARPP-OP
A9: BASIS FOR THIS INITIATIVE | D9: NEPHROLOGY | F9: =ROUND(+$S9*T9,-1) -> 0 | G9: =ROUND(+$S9*U9,-1) -> 0 | H9: =ROUND(+$S9*V9,-1) -> 528670 | I9: =ROUND(+$S9*W9,-1) -> 0 | J9: =ROUND(+$S9*X9,-1) -> 881120 | K9: =ROUND(+$S9*Y9,-1) -> 0 | L9: =ROUND(+$S9*Z9,-1) -> 0 | M9: =ROUND(+$S9*AA9,-1) -> 1057350 | ... Q9: =ROUND(+$S9*AE9,-1) -> 352450 | R9: =SUM(F9:Q9) -> 3524490 | S9: 7661.9249 | V9: 69 | X9: 115 | AA9: 138 | AC9: 92 | AE9: 46
A10: Events create mass awareness, generate screening leads (5–8% of abnormal findings convert to OPD), build community trust, and generate significant PR value. Scaling to 4–5 events/year with proper media activation creates a sustained brand presence calendar and a steady stream of screening-to-OPD-to-IP conversions. | D10: MEDICAL ONCOLOGY | F10: =ROUND(+$S10*T10,-1) -> 0 | G10: =ROUND(+$S10*U10,-1) -> 0 | H10: =ROUND(+$S10*V10,-1) -> 598770 | I10: =ROUND(+$S10*W10,-1) -> 0 | J10: =ROUND(+$S10*X10,-1) -> 995840 | K10: =ROUND(+$S10*Y10,-1) -> 0 | L10: =ROUND(+$S10*Z10,-1) -> 0 | M10: =ROUND(+$S10*AA10,-1) -> 1191230 | ... Q10: =ROUND(+$S10*AE10,-1) -> 390770 | R10: =SUM(F10:Q10) -> 3970760 | S10: 6302.7976 | V10: 95 | X10: 158 | AA10: 189 | AC10: 126 | AE10: 62
A11: EXECUTION TRACKING (to be completed) | D11: ORTHOPEDICS | F11: =ROUND(+$S11*T11,-1) -> 0 | G11: =ROUND(+$S11*U11,-1) -> 0 | H11: =ROUND(+$S11*V11,-1) -> 26780 | I11: =ROUND(+$S11*W11,-1) -> 0 | J11: =ROUND(+$S11*X11,-1) -> 44640 | K11: =ROUND(+$S11*Y11,-1) -> 0 | L11: =ROUND(+$S11*Z11,-1) -> 0 | M11: =ROUND(+$S11*AA11,-1) -> 53570 | ... Q11: =ROUND(+$S11*AE11,-1) -> 17860 | R11: =SUM(F11:Q11) -> 178560 | S11: 2232.036 | V11: 12 | X11: 20 | AA11: 24 | AC11: 16 | AE11: 8
A12: Owner | B12: Head BD / Head Communications / Event Coordinator / Relevant Department HODs | D12: NEURO SURGERY | F12: =ROUND(+$S12*T12,-1) -> 0 | G12: =ROUND(+$S12*U12,-1) -> 0 | H12: =ROUND(+$S12*V12,-1) -> 78230 | I12: =ROUND(+$S12*W12,-1) -> 0 | J12: =ROUND(+$S12*X12,-1) -> 129390 | K12: =ROUND(+$S12*Y12,-1) -> 0 | L12: =ROUND(+$S12*Z12,-1) -> 0 | M12: =ROUND(+$S12*AA12,-1) -> 153460 | ... Q12: =ROUND(+$S12*AE12,-1) -> 48140 | R12: =SUM(F12:Q12) -> 511530 | S12: 3008.9909 | V12: 26 | X12: 43 | AA12: 51 | AC12: 34 | AE12: 16
A13: Key Milestones / Actions | B13: 1. Lock FY27 events calendar: Heart Run (Aug-26), Liver Week (Nov-26), Cancer Awareness (Jan-27), Diabetes Camp (Mar-27) 2. Secure title sponsor and 3-5 co-sponsors for Heart Run by Jun-26 3. Design standardised event format: screening stations, consultation booths, registration desk, follow-up workflow 4. Mandate department participation: Cardiology leads Heart Run, Gastro/Transplant leads Liver Week, Oncology leads Cancer, Endocrinology leads Diabetes 5. Build post-event conversion funnel: abnormal finding > 24-hr callback > OPD appointment > IP admission 6. Target per event: 3,000 participants, 500 screenings, 50 OPD conversions, 8-10 IP admissions 7. Media coverage target: 3 print + 2 TV + social media reach 50K per event | D13: GI SURGERY | F13: =ROUND(+$S13*T13,-1) -> 0 | G13: =ROUND(+$S13*U13,-1) -> 0 | H13: =ROUND(+$S13*V13,-1) -> 65180 | I13: =ROUND(+$S13*W13,-1) -> 0 | J13: =ROUND(+$S13*X13,-1) -> 108630 | K13: =ROUND(+$S13*Y13,-1) -> 0 | L13: =ROUND(+$S13*Z13,-1) -> 0 | M13: =ROUND(+$S13*AA13,-1) -> 130360 | ... Q13: =ROUND(+$S13*AE13,-1) -> 43450 | R13: =SUM(F13:Q13) -> 434520 | S13: 1810.4889 | V13: 36 | X13: 60 | AA13: 72 | AC13: 48 | AE13: 24
A14: Risks / Dependencies | B14: 1. Event execution quality is critical — one poorly run event damages brand for all future events 2. Weather/monsoon risk for outdoor events (Heart Run) 3. Sponsorship revenue depends on pharma/device company marketing budgets which are cyclical 4. Screening follow-up requires dedicated coordination — lost leads are wasted screening cost | D14: GASTROENTEROLOGY | F14: =ROUND(+$S14*T14,-1) -> 0 | G14: =ROUND(+$S14*U14,-1) -> 0 | H14: =ROUND(+$S14*V14,-1) -> 224980 | I14: =ROUND(+$S14*W14,-1) -> 0 | J14: =ROUND(+$S14*X14,-1) -> 373700 | K14: =ROUND(+$S14*Y14,-1) -> 0 | L14: =ROUND(+$S14*Z14,-1) -> 0 | M14: =ROUND(+$S14*AA14,-1) -> 446150 | ... Q14: =ROUND(+$S14*AE14,-1) -> 144900 | R14: =SUM(F14:Q14) -> 1487160 | S14: 3813.2544 | V14: 59 | X14: 98 | AA14: 117 | AC14: 78 | AE14: 38
A15: Remarks | B15: Replaces the single Heart Run with a full-year calendar. Each event aligns with a clinical department, creating natural ownership. Events double as community engagement (R-06 synergy) and digital content opportunities (R-15 synergy). | D15: CARDIOLOGY | F15: =ROUND(+$S15*T15,-1) -> 0 | G15: =ROUND(+$S15*U15,-1) -> 0 | H15: =ROUND(+$S15*V15,-1) -> 117830 | I15: =ROUND(+$S15*W15,-1) -> 0 | J15: =ROUND(+$S15*X15,-1) -> 196380 | K15: =ROUND(+$S15*Y15,-1) -> 0 | L15: =ROUND(+$S15*Z15,-1) -> 0 | M15: =ROUND(+$S15*AA15,-1) -> 235650 | ... Q15: =ROUND(+$S15*AE15,-1) -> 78550 | R15: =SUM(F15:Q15) -> 785510 | S15: 2618.3826 | V15: 45 | X15: 75 | AA15: 90 | AC15: 60 | AE15: 30
D16: UROLOGY | F16: =ROUND(+$S16*T16,-1) -> 0 | G16: =ROUND(+$S16*U16,-1) -> 0 | H16: =ROUND(+$S16*V16,-1) -> 96850 | I16: =ROUND(+$S16*W16,-1) -> 0 | J16: =ROUND(+$S16*X16,-1) -> 160570 | K16: =ROUND(+$S16*Y16,-1) -> 0 | L16: =ROUND(+$S16*Z16,-1) -> 0 | M16: =ROUND(+$S16*AA16,-1) -> 191160 | ... Q16: =ROUND(+$S16*AE16,-1) -> 61170 | R16: =SUM(F16:Q16) -> 637190 | S16: 2548.7509 | V16: 38 | X16: 63 | AA16: 75 | AC16: 50 | AE16: 24
D17: SURGICAL ONCOLOGY | F17: =ROUND(+$S17*T17,-1) -> 0 | G17: =ROUND(+$S17*U17,-1) -> 0 | H17: =ROUND(+$S17*V17,-1) -> 86300 | I17: =ROUND(+$S17*W17,-1) -> 0 | J17: =ROUND(+$S17*X17,-1) -> 143010 | K17: =ROUND(+$S17*Y17,-1) -> 0 | L17: =ROUND(+$S17*Z17,-1) -> 0 | M17: =ROUND(+$S17*AA17,-1) -> 170130 | ... Q17: =ROUND(+$S17*AE17,-1) -> 54240 | R17: =SUM(F17:Q17) -> 567100 | S17: 2465.6794 | V17: 35 | X17: 58 | AA17: 69 | AC17: 46 | AE17: 22
D18: MINIMALLY INVASIVE SURGERY | F18: =ROUND(+$S18*T18,-1) -> 0 | G18: =ROUND(+$S18*U18,-1) -> 0 | H18: =ROUND(+$S18*V18,-1) -> 24200 | I18: =ROUND(+$S18*W18,-1) -> 0 | J18: =ROUND(+$S18*X18,-1) -> 39600 | K18: =ROUND(+$S18*Y18,-1) -> 0 | L18: =ROUND(+$S18*Z18,-1) -> 0 | M18: =ROUND(+$S18*AA18,-1) -> 46200 | ... Q18: =ROUND(+$S18*AE18,-1) -> 13200 | R18: =SUM(F18:Q18) -> 154000 | S18: 2200.2123 | V18: 11 | X18: 18 | AA18: 21 | AC18: 14 | AE18: 6
D19: COMPREHENSIVE LIVER CARE | F19: =ROUND(+$S19*T19,-1) -> 0 | G19: =ROUND(+$S19*U19,-1) -> 0 | H19: =ROUND(+$S19*V19,-1) -> 11890 | I19: =ROUND(+$S19*W19,-1) -> 0 | J19: =ROUND(+$S19*X19,-1) -> 17830 | K19: =ROUND(+$S19*Y19,-1) -> 0 | L19: =ROUND(+$S19*Z19,-1) -> 0 | M19: =ROUND(+$S19*AA19,-1) -> 17830 | ... Q19: =ROUND(+$S19*AE19,-1) -> 0 | R19: =SUM(F19:Q19) -> 59440 | S19: 5942.9578 | V19: 2 | X19: 3 | AA19: 3 | AC19: 2 | AE19: 0
D20: NEUROLOGY | F20: =ROUND(+$S20*T20,-1) -> 0 | G20: =ROUND(+$S20*U20,-1) -> 0 | H20: =ROUND(+$S20*V20,-1) -> 84690 | I20: =ROUND(+$S20*W20,-1) -> 0 | J20: =ROUND(+$S20*X20,-1) -> 140410 | K20: =ROUND(+$S20*Y20,-1) -> 0 | L20: =ROUND(+$S20*Z20,-1) -> 0 | M20: =ROUND(+$S20*AA20,-1) -> 167160 | ... Q20: =ROUND(+$S20*AE20,-1) -> 53490 | R20: =SUM(F20:Q20) -> 557190 | S20: 2228.7649 | V20: 38 | X20: 63 | AA20: 75 | AC20: 50 | AE20: 24
D21: GENERAL MEDICINE | F21: =ROUND(+$S21*T21,-1) -> 0 | G21: =ROUND(+$S21*U21,-1) -> 0 | H21: =ROUND(+$S21*V21,-1) -> 77740 | I21: =ROUND(+$S21*W21,-1) -> 0 | J21: =ROUND(+$S21*X21,-1) -> 128670 | K21: =ROUND(+$S21*Y21,-1) -> 0 | L21: =ROUND(+$S21*Z21,-1) -> 0 | M21: =ROUND(+$S21*AA21,-1) -> 152800 | ... Q21: =ROUND(+$S21*AE21,-1) -> 48250 | R21: =SUM(F21:Q21) -> 509330 | S21: 2680.675 | V21: 29 | X21: 48 | AA21: 57 | AC21: 38 | AE21: 18
D22: OB & GYNEC. | F22: =ROUND(+$S22*T22,-1) -> 0 | G22: =ROUND(+$S22*U22,-1) -> 0 | H22: =ROUND(+$S22*V22,-1) -> 51580 | I22: =ROUND(+$S22*W22,-1) -> 0 | J22: =ROUND(+$S22*X22,-1) -> 85430 | K22: =ROUND(+$S22*Y22,-1) -> 0 | L22: =ROUND(+$S22*Z22,-1) -> 0 | M22: =ROUND(+$S22*AA22,-1) -> 101550 | ... Q22: =ROUND(+$S22*AE22,-1) -> 32240 | R22: =SUM(F22:Q22) -> 338500 | S22: 1611.834 | V22: 32 | X22: 53 | AA22: 63 | AC22: 42 | AE22: 20
D23: PEDIATRICS | F23: =ROUND(+$S23*T23,-1) -> 0 | G23: =ROUND(+$S23*U23,-1) -> 0 | H23: =ROUND(+$S23*V23,-1) -> 55940 | I23: =ROUND(+$S23*W23,-1) -> 0 | J23: =ROUND(+$S23*X23,-1) -> 93230 | K23: =ROUND(+$S23*Y23,-1) -> 0 | L23: =ROUND(+$S23*Z23,-1) -> 0 | M23: =ROUND(+$S23*AA23,-1) -> 111880 | ... Q23: =ROUND(+$S23*AE23,-1) -> 37290 | R23: =SUM(F23:Q23) -> 372930 | S23: 810.70795 | V23: 69 | X23: 115 | AA23: 138 | AC23: 92 | AE23: 46
D25: JOINT REPLACEMENT & SPORTS MED | F25: =ROUND(+$S25*T25,-1) -> 0 | G25: =ROUND(+$S25*U25,-1) -> 0 | H25: =ROUND(+$S25*V25,-1) -> 58030 | I25: =ROUND(+$S25*W25,-1) -> 0 | J25: =ROUND(+$S25*X25,-1) -> 95980 | K25: =ROUND(+$S25*Y25,-1) -> 0 | L25: =ROUND(+$S25*Z25,-1) -> 0 | M25: =ROUND(+$S25*AA25,-1) -> 113830 | ... Q25: =ROUND(+$S25*AE25,-1) -> 35710 | R25: =SUM(F25:Q25) -> 379440 | S25: 2232.036 | V25: 26 | X25: 43 | AA25: 51 | AC25: 34 | AE25: 16
D26: ORTHOPEDICS - DIVISION OF FOOT ANKLE & PODIATRY | F26: =ROUND(+$S26*T26,-1) -> 0 | G26: =ROUND(+$S26*U26,-1) -> 0 | H26: =ROUND(+$S26*V26,-1) -> 46870 | I26: =ROUND(+$S26*W26,-1) -> 0 | J26: =ROUND(+$S26*X26,-1) -> 78120 | K26: =ROUND(+$S26*Y26,-1) -> 0 | L26: =ROUND(+$S26*Z26,-1) -> 0 | M26: =ROUND(+$S26*AA26,-1) -> 93750 | ... Q26: =ROUND(+$S26*AE26,-1) -> 31250 | R26: =SUM(F26:Q26) -> 312490 | S26: 2232.036 | V26: 21 | X26: 35 | AA26: 42 | AC26: 28 | AE26: 14
D27: ORTHOPEDICS - DIVISION OF ORTHOPEDIC ONCOLOGY | F27: =ROUND(+$S27*T27,-1) -> 0 | G27: =ROUND(+$S27*U27,-1) -> 0 | H27: =ROUND(+$S27*V27,-1) -> 4460 | I27: =ROUND(+$S27*W27,-1) -> 0 | J27: =ROUND(+$S27*X27,-1) -> 6700 | K27: =ROUND(+$S27*Y27,-1) -> 0 | L27: =ROUND(+$S27*Z27,-1) -> 0 | M27: =ROUND(+$S27*AA27,-1) -> 6700 | ... Q27: =ROUND(+$S27*AE27,-1) -> 0 | R27: =SUM(F27:Q27) -> 22320 | S27: 2232.036 | V27: 2 | X27: 3 | AA27: 3 | AC27: 2 | AE27: 0
D28: COMPREHENSIVE LIVER CARE - SUR | F28: =ROUND(+$S28*T28,-1) -> 0 | G28: =ROUND(+$S28*U28,-1) -> 0 | H28: =ROUND(+$S28*V28,-1) -> 29710 | I28: =ROUND(+$S28*W28,-1) -> 0 | J28: =ROUND(+$S28*X28,-1) -> 47540 | K28: =ROUND(+$S28*Y28,-1) -> 0 | L28: =ROUND(+$S28*Z28,-1) -> 0 | M28: =ROUND(+$S28*AA28,-1) -> 53490 | ... Q28: =ROUND(+$S28*AE28,-1) -> 11890 | R28: =SUM(F28:Q28) -> 178290 | S28: 5942.9578 | V28: 5 | X28: 8 | AA28: 9 | AC28: 6 | AE28: 2
D29: HEAD AND NECK ONCOLOGY | F29: =ROUND(+$S29*T29,-1) -> 0 | G29: =ROUND(+$S29*U29,-1) -> 0 | H29: =ROUND(+$S29*V29,-1) -> 7400 | I29: =ROUND(+$S29*W29,-1) -> 0 | J29: =ROUND(+$S29*X29,-1) -> 12330 | K29: =ROUND(+$S29*Y29,-1) -> 0 | L29: =ROUND(+$S29*Z29,-1) -> 0 | M29: =ROUND(+$S29*AA29,-1) -> 14790 | ... Q29: =ROUND(+$S29*AE29,-1) -> 4930 | R29: =SUM(F29:Q29) -> 49310 | S29: 2465.6794 | V29: 3 | X29: 5 | AA29: 6 | AC29: 4 | AE29: 2

Sheet R-15
A1: R-15 | Patient Acquisition & Digital Platform
A2: Revenue — Marketing & Patient Acquisition
A3: OVERVIEW | G3: =SUM(H3:S3) -> 6205000 | H3: =SUM(H5:H11) -> 0 | I3: =SUM(I5:I11) -> 905000 | J3: =SUM(J5:J11) -> 555000 | K3: =SUM(K5:K11) -> 505000 | L3: =SUM(L5:L11) -> 555000 | M3: =SUM(M5:M11) -> 505000 | N3: =SUM(N5:N11) -> 505000 | O3: =SUM(O5:O11) -> 555000 | ... S3: =SUM(S5:S11) -> 555000
A4: Description / Objective | B4: Comprehensive patient acquisition analysis + digital platform: (A) Channel Analysis: Marketing spend ~₹7 Cr = 10–15% commission, yet only ₹50–70 Cr revenue through referral channel. The other 70%+ of patients walked in via family recommendation (35%), other/direct (38%), or friends (16%). (B) Content Platform: 3 health videos/week (Malayalam + English) across YouTube, Facebook, Instagram, hospital website. SEO-optimised. Procedure explainers, doctor Q&As, patient testimonials. Track digital-to-enquiry conversion. (C) Doctor Online Reputation: Optimise Google Business, Practo, Doctorundi for all senior consultants. Post-OPD SMS review collection (NPS currently 60 from 60,000+ responses). Online reputation management consolidated here. | G4: Hiring | H4: Apr | I4: May | J4: Jun | K4: Jul | L4: Aug | M4: Sep | N4: Oct | O4: Nov | P4: Dec | Q4: Jan | R4: Feb | S4: Mar
A5: Start Month | B5: 46113 | G5: 1 video producer | I5: 50000 | J5: 50000 | K5: 50000 | L5: 50000 | M5: 50000 | N5: 50000 | O5: 50000 | P5: 50000 | Q5: 50000 | R5: 50000 | S5: 50000
A6: Estimated Cost | B6: ₹62L/yr (2 content staff + Malayalam agency + Google Ads + SEO + platform management) | G6: 1 content writer | I6: 30000 | J6: 30000 | K6: 30000 | L6: 30000 | M6: 30000 | N6: 30000 | O6: 30000 | P6: 30000 | Q6: 30000 | R6: 30000 | S6: 30000
A7: Expected Impact | B7: ₹5 Cr | G7: 1 social media | I7: 25000 | J7: 25000 | K7: 25000 | L7: 25000 | M7: 25000 | N7: 25000 | O7: 25000 | P7: 25000 | Q7: 25000 | R7: 25000 | S7: 25000
G8: Google Ads | I8: 150000 | J8: 150000 | K8: 150000 | L8: 150000 | M8: 150000 | N8: 150000 | O8: 150000 | P8: 150000 | Q8: 150000 | R8: 150000 | S8: 150000
A9: BASIS FOR THIS INITIATIVE | G9: Seo/ other digital spend | I9: 150000 | J9: =150000+50000 -> 200000 | K9: 150000 | L9: =150000+50000 -> 200000 | M9: 150000 | N9: 150000 | O9: =150000+50000 -> 200000 | P9: 150000 | Q9: =150000+50000 -> 200000 | R9: 150000 | S9: =150000+50000 -> 200000
A10: OP feedback data (60,307 responses, Jun 2023-Apr 2026) shows: NPS 60, mean 8.6/10, 70% promoters. Top source is Other/walk-in (38%) and Family recommendation (35%) — only 4.4% come via doctor referral. This means word-of-mouth and reputation are the dominant acquisition channels. Digital amplifies both. Marketing ROI analysis suggests the 7Cr marketing spend has low attribution — most patients arrive through organic/trust channels. | G10: Malayalam Agency | I10: 100000 | J10: 100000 | K10: 100000 | L10: 100000 | M10: 100000 | N10: 100000 | O10: 100000 | P10: 100000 | Q10: 100000 | R10: 100000 | S10: 100000
A11: EXECUTION TRACKING (to be completed) | G11: Initial Efforts | I11: 400000
A12: Owner | B12: Head Communications / Head BD | V12: Apr | W12: May | X12: Jun | Y12: Jul | Z12: Aug | AA12: Sep | AB12: Oct | AC12: Nov | AD12: Dec | AE12: Jan | AF12: Feb | AG12: Mar
A13: Key Milestones / Actions | B13: 1. Complete patient acquisition channel analysis: map all new patient sources for last 12 months by May-26 2. Calculate cost-per-acquisition by channel: referral, digital, walk-in, corporate, scheme by May-26 3. Hire/assign digital content team: 1 video producer + 1 content writer + 1 social media manager by Jun-26 4. Launch 3 videos/week production schedule by Jul-26 5. Optimise Google Business profiles for top 30 consultants (reviews, photos, specialisations) by Jun-26 6. Implement post-OPD automated SMS review request by Jun-26 7. Set up digital conversion tracking: website visit > enquiry > OPD appointment > IP admission 8. Monthly digital marketing dashboard: impressions, enquiries, cost-per-lead, conversion rate 9. Target: 500 digital-sourced OPD appointments/month by Dec-26 | G13: Revenue Expected | H13: =+H14+H36 -> 0 | I13: =+I14+I36 -> 101610 | J13: =+J14+J36 -> 187530 | K13: =+K14+K36 -> 513120 | L13: =+L14+L36 -> 2184500 | M13: =+M14+M36 -> 3145560 | N13: =+N14+N36 -> 4672310 | O13: =+O14+O36 -> 5410180 | ... T13: =+T14+T36 -> 50205430
A14: Risks / Dependencies | B14: 1. Video content requires consultant cooperation — some doctors may resist on-camera appearances 2. SEO results take 3-6 months to materialise 3. Review management: negative reviews need rapid response protocols 4. Attribution is imperfect — many patients interact with multiple channels before booking | G14: OP | H14: =SUM(H15:H34) -> 0 | I14: =SUM(I15:I34) -> 101610 | J14: =SUM(J15:J34) -> 187530 | K14: =SUM(K15:K34) -> 392210 | L14: =SUM(L15:L34) -> 511420 | M14: =SUM(M15:M34) -> 696750 | N14: =SUM(N15:N34) -> 806390 | O14: =SUM(O15:O34) -> 993930 | ... S14: =SUM(S15:S34) -> 1871840 | T14: =SUM(H14:S14) -> 9939120 | U14: ARPP OP
A15: Remarks | B15: Online reputation management is consolidated into this initiative. OP feedback data (60,000+ responses over 3 years) confirms that trust-based channels (family, friends) dominate patient acquisition. Digital strategy should amplify these organic channels, not replace them with paid advertising. | G15: NEPHROLOGY | H15: =ROUND(+$U15*V15,-1) -> 0 | I15: =ROUND(+$U15*W15,-1) -> 22990 | J15: =ROUND(+$U15*X15,-1) -> 45970 | K15: =ROUND(+$U15*Y15,-1) -> 91940 | L15: =ROUND(+$U15*Z15,-1) -> 122590 | M15: =ROUND(+$U15*AA15,-1) -> 168560 | N15: =ROUND(+$U15*AB15,-1) -> 191550 | O15: =ROUND(+$U15*AC15,-1) -> 237520 | ... S15: =ROUND(+$U15*AG15,-1) -> 444390 | U15: 7661.9249 | V15: 0 | W15: 3 | X15: 6 | Y15: 12 | Z15: 16 | AA15: 22 | AB15: 25 | AC15: 31 | AD15: 37 | AE15: 47 | AF15: 53 | AG15: 58
A16: Bequip Remarks | B16: We want an additional data collection of how the customer came to know us so that we can actually understand the response and build our digital marketing strategy accordingly. | G16: MEDICAL ONCOLOGY | H16: =ROUND(+$U16*V16,-1) -> 0 | I16: =ROUND(+$U16*W16,-1) -> 25210 | J16: =ROUND(+$U16*X16,-1) -> 50420 | K16: =ROUND(+$U16*Y16,-1) -> 107150 | L16: =ROUND(+$U16*Z16,-1) -> 132360 | M16: =ROUND(+$U16*AA16,-1) -> 182780 | N16: =ROUND(+$U16*AB16,-1) -> 214300 | O16: =ROUND(+$U16*AC16,-1) -> 264720 | ... S16: =ROUND(+$U16*AG16,-1) -> 510530 | U16: 6302.7976 | V16: 0 | W16: 4 | X16: 8 | Y16: 17 | Z16: 21 | AA16: 29 | AB16: 34 | AC16: 42 | AD16: 50 | AE16: 63 | AF16: 71 | AG16: 81
G17: ORTHOPEDICS | H17: =ROUND(+$U17*V17,-1) -> 0 | I17: =ROUND(+$U17*W17,-1) -> 2230 | J17: =ROUND(+$U17*X17,-1) -> 2230 | K17: =ROUND(+$U17*Y17,-1) -> 4460 | L17: =ROUND(+$U17*Z17,-1) -> 6700 | M17: =ROUND(+$U17*AA17,-1) -> 8930 | N17: =ROUND(+$U17*AB17,-1) -> 8930 | O17: =ROUND(+$U17*AC17,-1) -> 11160 | ... S17: =ROUND(+$U17*AG17,-1) -> 15620 | U17: 2232.036 | V17: 0 | W17: 1 | X17: 1 | Y17: 2 | Z17: 3 | AA17: 4 | AB17: 4 | AC17: 5 | AD17: 6 | AE17: 8 | AF17: 9 | AG17: 7
G18: NEURO SURGERY | H18: =ROUND(+$U18*V18,-1) -> 0 | I18: =ROUND(+$U18*W18,-1) -> 3010 | J18: =ROUND(+$U18*X18,-1) -> 6020 | K18: =ROUND(+$U18*Y18,-1) -> 12040 | L18: =ROUND(+$U18*Z18,-1) -> 18050 | M18: =ROUND(+$U18*AA18,-1) -> 24070 | N18: =ROUND(+$U18*AB18,-1) -> 27080 | O18: =ROUND(+$U18*AC18,-1) -> 33100 | ... S18: =ROUND(+$U18*AG18,-1) -> 60180 | U18: 3008.9909 | V18: 0 | W18: 1 | X18: 2 | Y18: 4 | Z18: 6 | AA18: 8 | AB18: 9 | AC18: 11 | AD18: 13 | AE18: 17 | AF18: 19 | AG18: 20
G19: GI SURGERY | H19: =ROUND(+$U19*V19,-1) -> 0 | I19: =ROUND(+$U19*W19,-1) -> 3620 | J19: =ROUND(+$U19*X19,-1) -> 5430 | K19: =ROUND(+$U19*Y19,-1) -> 10860 | L19: =ROUND(+$U19*Z19,-1) -> 14480 | M19: =ROUND(+$U19*AA19,-1) -> 19920 | N19: =ROUND(+$U19*AB19,-1) -> 23540 | O19: =ROUND(+$U19*AC19,-1) -> 28970 | ... S19: =ROUND(+$U19*AG19,-1) -> 56130 | U19: 1810.4889 | V19: 0 | W19: 2 | X19: 3 | Y19: 6 | Z19: 8 | AA19: 11 | AB19: 13 | AC19: 16 | AD19: 19 | AE19: 24 | AF19: 27 | AG19: 31
G20: GASTROENTEROLOGY | H20: =ROUND(+$U20*V20,-1) -> 0 | I20: =ROUND(+$U20*W20,-1) -> 11440 | J20: =ROUND(+$U20*X20,-1) -> 19070 | K20: =ROUND(+$U20*Y20,-1) -> 38130 | L20: =ROUND(+$U20*Z20,-1) -> 49570 | M20: =ROUND(+$U20*AA20,-1) -> 68640 | N20: =ROUND(+$U20*AB20,-1) -> 80080 | O20: =ROUND(+$U20*AC20,-1) -> 99140 | ... S20: =ROUND(+$U20*AG20,-1) -> 190660 | U20: 3813.2544 | V20: 0 | W20: 3 | X20: 5 | Y20: 10 | Z20: 13 | AA20: 18 | AB20: 21 | AC20: 26 | AD20: 31 | AE20: 39 | AF20: 44 | AG20: 50
G21: CARDIOLOGY | H21: =ROUND(+$U21*V21,-1) -> 0 | I21: =ROUND(+$U21*W21,-1) -> 5240 | J21: =ROUND(+$U21*X21,-1) -> 10470 | K21: =ROUND(+$U21*Y21,-1) -> 20950 | L21: =ROUND(+$U21*Z21,-1) -> 26180 | M21: =ROUND(+$U21*AA21,-1) -> 36660 | N21: =ROUND(+$U21*AB21,-1) -> 41890 | O21: =ROUND(+$U21*AC21,-1) -> 52370 | ... S21: =ROUND(+$U21*AG21,-1) -> 99500 | U21: 2618.3826 | V21: 0 | W21: 2 | X21: 4 | Y21: 8 | Z21: 10 | AA21: 14 | AB21: 16 | AC21: 20 | AD21: 24 | AE21: 30 | AF21: 34 | AG21: 38
G22: UROLOGY | H22: =ROUND(+$U22*V22,-1) -> 0 | I22: =ROUND(+$U22*W22,-1) -> 5100 | J22: =ROUND(+$U22*X22,-1) -> 7650 | K22: =ROUND(+$U22*Y22,-1) -> 15290 | L22: =ROUND(+$U22*Z22,-1) -> 20390 | M22: =ROUND(+$U22*AA22,-1) -> 28040 | N22: =ROUND(+$U22*AB22,-1) -> 33130 | O22: =ROUND(+$U22*AC22,-1) -> 40780 | ... S22: =ROUND(+$U22*AG22,-1) -> 79010 | U22: 2548.7509 | V22: 0 | W22: 2 | X22: 3 | Y22: 6 | Z22: 8 | AA22: 11 | AB22: 13 | AC22: 16 | AD22: 19 | AE22: 24 | AF22: 27 | AG22: 31
G23: SURGICAL ONCOLOGY | H23: =ROUND(+$U23*V23,-1) -> 0 | I23: =ROUND(+$U23*W23,-1) -> 4930 | J23: =ROUND(+$U23*X23,-1) -> 7400 | K23: =ROUND(+$U23*Y23,-1) -> 14790 | L23: =ROUND(+$U23*Z23,-1) -> 19730 | M23: =ROUND(+$U23*AA23,-1) -> 27120 | N23: =ROUND(+$U23*AB23,-1) -> 29590 | O23: =ROUND(+$U23*AC23,-1) -> 36990 | ... S23: =ROUND(+$U23*AG23,-1) -> 64110 | U23: 2465.6794 | V23: 0 | W23: 2 | X23: 3 | Y23: 6 | Z23: 8 | AA23: 11 | AB23: 12 | AC23: 15 | AD23: 18 | AE23: 23 | AF23: 26 | AG23: 26
G24: MINIMALLY INVASIVE SURGERY | H24: =ROUND(+$U24*V24,-1) -> 0 | I24: =ROUND(+$U24*W24,-1) -> 2200 | J24: =ROUND(+$U24*X24,-1) -> 2200 | K24: =ROUND(+$U24*Y24,-1) -> 4400 | L24: =ROUND(+$U24*Z24,-1) -> 6600 | M24: =ROUND(+$U24*AA24,-1) -> 8800 | N24: =ROUND(+$U24*AB24,-1) -> 8800 | O24: =ROUND(+$U24*AC24,-1) -> 11000 | ... S24: =ROUND(+$U24*AG24,-1) -> 15400 | U24: 2200.2123 | V24: 0 | W24: 1 | X24: 1 | Y24: 2 | Z24: 3 | AA24: 4 | AB24: 4 | AC24: 5 | AD24: 6 | AE24: 8 | AF24: 9 | AG24: 7
G25: COMPREHENSIVE LIVER CARE | H25: =ROUND(+$U25*V25,-1) -> 0 | I25: =ROUND(+$U25*W25,-1) -> 0 | J25: =ROUND(+$U25*X25,-1) -> 0 | K25: =ROUND(+$U25*Y25,-1) -> 0 | L25: =ROUND(+$U25*Z25,-1) -> 0 | M25: =ROUND(+$U25*AA25,-1) -> 0 | N25: =ROUND(+$U25*AB25,-1) -> 0 | O25: =ROUND(+$U25*AC25,-1) -> 0 | ... S25: =ROUND(+$U25*AG25,-1) -> 0 | U25: 5942.9578 | V25: 0 | W25: 0 | X25: 0 | Y25: 0 | Z25: 0 | AA25: 0 | AB25: 0 | AC25: 0 | AD25: 0 | AE25: 0 | AF25: 0 | AG25: 0
G26: NEUROLOGY | H26: =ROUND(+$U26*V26,-1) -> 0 | I26: =ROUND(+$U26*W26,-1) -> 4460 | J26: =ROUND(+$U26*X26,-1) -> 6690 | K26: =ROUND(+$U26*Y26,-1) -> 15600 | L26: =ROUND(+$U26*Z26,-1) -> 20060 | M26: =ROUND(+$U26*AA26,-1) -> 26750 | N26: =ROUND(+$U26*AB26,-1) -> 31200 | O26: =ROUND(+$U26*AC26,-1) -> 37890 | ... S26: =ROUND(+$U26*AG26,-1) -> 69090 | U26: 2228.7649 | V26: 0 | W26: 2 | X26: 3 | Y26: 7 | Z26: 9 | AA26: 12 | AB26: 14 | AC26: 17 | AD26: 20 | AE26: 26 | AF26: 29 | AG26: 31
G27: GENERAL MEDICINE | H27: =ROUND(+$U27*V27,-1) -> 0 | I27: =ROUND(+$U27*W27,-1) -> 2680 | J27: =ROUND(+$U27*X27,-1) -> 5360 | K27: =ROUND(+$U27*Y27,-1) -> 13400 | L27: =ROUND(+$U27*Z27,-1) -> 16080 | M27: =ROUND(+$U27*AA27,-1) -> 21450 | N27: =ROUND(+$U27*AB27,-1) -> 26810 | O27: =ROUND(+$U27*AC27,-1) -> 32170 | ... S27: =ROUND(+$U27*AG27,-1) -> 64340 | U27: 2680.675 | V27: 0 | W27: 1 | X27: 2 | Y27: 5 | Z27: 6 | AA27: 8 | AB27: 10 | AC27: 12 | AD27: 14 | AE27: 18 | AF27: 20 | AG27: 24
G28: OB & GYNEC. | H28: =ROUND(+$U28*V28,-1) -> 0 | I28: =ROUND(+$U28*W28,-1) -> 1610 | J28: =ROUND(+$U28*X28,-1) -> 4840 | K28: =ROUND(+$U28*Y28,-1) -> 9670 | L28: =ROUND(+$U28*Z28,-1) -> 11280 | M28: =ROUND(+$U28*AA28,-1) -> 16120 | N28: =ROUND(+$U28*AB28,-1) -> 17730 | O28: =ROUND(+$U28*AC28,-1) -> 22570 | ... S28: =ROUND(+$U28*AG28,-1) -> 41910 | U28: 1611.834 | V28: 0 | W28: 1 | X28: 3 | Y28: 6 | Z28: 7 | AA28: 10 | AB28: 11 | AC28: 14 | AD28: 17 | AE28: 21 | AF28: 24 | AG28: 26
... G34: HEAD AND NECK ONCOLOGY | H34: =ROUND(+$U34*V34,-1) -> 0 | I34: =ROUND(+$U34*W34,-1) -> 0 | J34: =ROUND(+$U34*X34,-1) -> 0 | K34: =ROUND(+$U34*Y34,-1) -> 0 | L34: =ROUND(+$U34*Z34,-1) -> 2470 | M34: =ROUND(+$U34*AA34,-1) -> 2470 | N34: =ROUND(+$U34*AB34,-1) -> 2470 | O34: =ROUND(+$U34*AC34,-1) -> 2470 | ... S34: =ROUND(+$U34*AG34,-1) -> 2470 | U34: 2465.6794 | V34: 0 | W34: 0 | X34: 0 | Y34: 0 | Z34: 1 | AA34: 1 | AB34: 1 | AC34: 1 | AD34: 1 | AE34: 2 | AF34: 2 | AG34: 1
G36: IP | H36: =SUM(H37:H56) -> 0 | I36: =SUM(I37:I56) -> 0 | J36: =SUM(J37:J56) -> 0 | K36: =SUM(K37:K56) -> 120910 | L36: =SUM(L37:L56) -> 1673080 | M36: =SUM(M37:M56) -> 2448810 | N36: =SUM(N37:N56) -> 3865920 | O36: =SUM(O37:O56) -> 4416250 | ... S36: =SUM(S37:S56) -> 8027090 | T36: =SUM(H36:S36) -> 40266310 | U36: ARPP-IP
G37: NEPHROLOGY | H37: =ROUND(+$U37*V37,-1) -> 0 | I37: =ROUND(+$U37*W37,-1) -> 0 | J37: =ROUND(+$U37*X37,-1) -> 0 | K37: =ROUND(+$U37*Y37,-1) -> 0 | L37: =ROUND(+$U37*Z37,-1) -> 303610 | M37: =ROUND(+$U37*AA37,-1) -> 303610 | N37: =ROUND(+$U37*AB37,-1) -> 607220 | O37: =ROUND(+$U37*AC37,-1) -> 607220 | ... S37: =ROUND(+$U37*AG37,-1) -> 910830 | U37: 303609.13 | V37: 0 | W37: 0 | X37: 0 | Y37: 0 | Z37: 1 | AA37: 1 | AB37: 2 | AC37: 2 | AD37: 3 | AE37: 3 | AF37: 3 | AG37: 3
G38: MEDICAL ONCOLOGY | H38: =ROUND(+$U38*V38,-1) -> 0 | I38: =ROUND(+$U38*W38,-1) -> 0 | J38: =ROUND(+$U38*X38,-1) -> 0 | K38: =ROUND(+$U38*Y38,-1) -> 120910 | L38: =ROUND(+$U38*Z38,-1) -> 181360 | M38: =ROUND(+$U38*AA38,-1) -> 362730 | N38: =ROUND(+$U38*AB38,-1) -> 483640 | O38: =ROUND(+$U38*AC38,-1) -> 604550 | ... S38: =ROUND(+$U38*AG38,-1) -> 906820 | U38: 60454.843 | V38: 0 | W38: 0 | X38: 0 | Y38: 2 | Z38: 3 | AA38: 6 | AB38: 8 | AC38: 10 | AD38: 11 | AE38: 12 | AF38: 14 | AG38: 15
G39: ORTHOPEDICS | H39: =ROUND(+$U39*V39,-1) -> 0 | I39: =ROUND(+$U39*W39,-1) -> 0 | J39: =ROUND(+$U39*X39,-1) -> 0 | K39: =ROUND(+$U39*Y39,-1) -> 0 | L39: =ROUND(+$U39*Z39,-1) -> 0 | M39: =ROUND(+$U39*AA39,-1) -> 0 | N39: =ROUND(+$U39*AB39,-1) -> 0 | O39: =ROUND(+$U39*AC39,-1) -> 0 | ... S39: =ROUND(+$U39*AG39,-1) -> 233910 | U39: 233914.61 | V39: 0 | W39: 0 | X39: 0 | Y39: 0 | Z39: 0 | AA39: 0 | AB39: 0 | AC39: 0 | AD39: 1 | AE39: 1 | AF39: 1 | AG39: 1
G40: NEURO SURGERY | H40: =ROUND(+$U40*V40,-1) -> 0 | I40: =ROUND(+$U40*W40,-1) -> 0 | J40: =ROUND(+$U40*X40,-1) -> 0 | K40: =ROUND(+$U40*Y40,-1) -> 0 | L40: =ROUND(+$U40*Z40,-1) -> 269240 | M40: =ROUND(+$U40*AA40,-1) -> 269240 | N40: =ROUND(+$U40*AB40,-1) -> 538490 | O40: =ROUND(+$U40*AC40,-1) -> 538490 | ... S40: =ROUND(+$U40*AG40,-1) -> 807730 | U40: 269243.95 | V40: 0 | W40: 0 | X40: 0 | Y40: 0 | Z40: 1 | AA40: 1 | AB40: 2 | AC40: 2 | AD40: 2 | AE40: 3 | AF40: 3 | AG40: 3
G41: GI SURGERY | H41: =ROUND(+$U41*V41,-1) -> 0 | I41: =ROUND(+$U41*W41,-1) -> 0 | J41: =ROUND(+$U41*X41,-1) -> 0 | K41: =ROUND(+$U41*Y41,-1) -> 0 | L41: =ROUND(+$U41*Z41,-1) -> 196300 | M41: =ROUND(+$U41*AA41,-1) -> 196300 | N41: =ROUND(+$U41*AB41,-1) -> 392600 | O41: =ROUND(+$U41*AC41,-1) -> 392600 | ... S41: =ROUND(+$U41*AG41,-1) -> 588900 | U41: 196299.55 | V41: 0 | W41: 0 | X41: 0 | Y41: 0 | Z41: 1 | AA41: 1 | AB41: 2 | AC41: 2 | AD41: 2 | AE41: 3 | AF41: 3 | AG41: 3
G42: GASTROENTEROLOGY | H42: =ROUND(+$U42*V42,-1) -> 0 | I42: =ROUND(+$U42*W42,-1) -> 0 | J42: =ROUND(+$U42*X42,-1) -> 0 | K42: =ROUND(+$U42*Y42,-1) -> 0 | L42: =ROUND(+$U42*Z42,-1) -> 98300 | M42: =ROUND(+$U42*AA42,-1) -> 98300 | N42: =ROUND(+$U42*AB42,-1) -> 196610 | O42: =ROUND(+$U42*AC42,-1) -> 196610 | ... S42: =ROUND(+$U42*AG42,-1) -> 294910 | U42: 98304.556 | V42: 0 | W42: 0 | X42: 0 | Y42: 0 | Z42: 1 | AA42: 1 | AB42: 2 | AC42: 2 | AD42: 3 | AE42: 3 | AF42: 3 | AG42: 3
G43: CARDIOLOGY | H43: =ROUND(+$U43*V43,-1) -> 0 | I43: =ROUND(+$U43*W43,-1) -> 0 | J43: =ROUND(+$U43*X43,-1) -> 0 | K43: =ROUND(+$U43*Y43,-1) -> 0 | L43: =ROUND(+$U43*Z43,-1) -> 161580 | M43: =ROUND(+$U43*AA43,-1) -> 161580 | N43: =ROUND(+$U43*AB43,-1) -> 323150 | O43: =ROUND(+$U43*AC43,-1) -> 323150 | ... S43: =ROUND(+$U43*AG43,-1) -> 484730 | U43: 161575.61 | V43: 0 | W43: 0 | X43: 0 | Y43: 0 | Z43: 1 | AA43: 1 | AB43: 2 | AC43: 2 | AD43: 3 | AE43: 3 | AF43: 3 | AG43: 3
G44: UROLOGY | H44: =ROUND(+$U44*V44,-1) -> 0 | I44: =ROUND(+$U44*W44,-1) -> 0 | J44: =ROUND(+$U44*X44,-1) -> 0 | K44: =ROUND(+$U44*Y44,-1) -> 0 | L44: =ROUND(+$U44*Z44,-1) -> 163620 | M44: =ROUND(+$U44*AA44,-1) -> 163620 | N44: =ROUND(+$U44*AB44,-1) -> 163620 | O44: =ROUND(+$U44*AC44,-1) -> 327230 | ... S44: =ROUND(+$U44*AG44,-1) -> 490850 | U44: 163617.48 | V44: 0 | W44: 0 | X44: 0 | Y44: 0 | Z44: 1 | AA44: 1 | AB44: 1 | AC44: 2 | AD44: 2 | AE44: 2 | AF44: 2 | AG44: 3
G45: SURGICAL ONCOLOGY | H45: =ROUND(+$U45*V45,-1) -> 0 | I45: =ROUND(+$U45*W45,-1) -> 0 | J45: =ROUND(+$U45*X45,-1) -> 0 | K45: =ROUND(+$U45*Y45,-1) -> 0 | L45: =ROUND(+$U45*Z45,-1) -> 175970 | M45: =ROUND(+$U45*AA45,-1) -> 175970 | N45: =ROUND(+$U45*AB45,-1) -> 175970 | O45: =ROUND(+$U45*AC45,-1) -> 351940 | ... S45: =ROUND(+$U45*AG45,-1) -> 351940 | U45: 175968.72 | V45: 0 | W45: 0 | X45: 0 | Y45: 0 | Z45: 1 | AA45: 1 | AB45: 1 | AC45: 2 | AD45: 2 | AE45: 2 | AF45: 2 | AG45: 2
G46: MINIMALLY INVASIVE SURGERY | H46: =ROUND(+$U46*V46,-1) -> 0 | I46: =ROUND(+$U46*W46,-1) -> 0 | J46: =ROUND(+$U46*X46,-1) -> 0 | K46: =ROUND(+$U46*Y46,-1) -> 0 | L46: =ROUND(+$U46*Z46,-1) -> 0 | M46: =ROUND(+$U46*AA46,-1) -> 183870 | N46: =ROUND(+$U46*AB46,-1) -> 183870 | O46: =ROUND(+$U46*AC46,-1) -> 183870 | ... S46: =ROUND(+$U46*AG46,-1) -> 367740 | U46: 183869.55 | V46: 0 | W46: 0 | X46: 0 | Y46: 0 | Z46: 0 | AA46: 1 | AB46: 1 | AC46: 1 | AD46: 2 | AE46: 2 | AF46: 2 | AG46: 2
G47: COMPREHENSIVE LIVER CARE | H47: =ROUND(+$U47*V47,-1) -> 0 | I47: =ROUND(+$U47*W47,-1) -> 0 | J47: =ROUND(+$U47*X47,-1) -> 0 | K47: =ROUND(+$U47*Y47,-1) -> 0 | L47: =ROUND(+$U47*Z47,-1) -> 0 | M47: =ROUND(+$U47*AA47,-1) -> 0 | N47: =ROUND(+$U47*AB47,-1) -> 0 | O47: =ROUND(+$U47*AC47,-1) -> 0 | ... S47: =ROUND(+$U47*AG47,-1) -> 0 | U47: 487489.56 | V47: 0 | W47: 0 | X47: 0 | Y47: 0 | Z47: 0 | AA47: 0 | AB47: 0 | AC47: 0 | AD47: 0 | AE47: 0 | AF47: 0 | AG47: 0
G48: NEUROLOGY | H48: =ROUND(+$U48*V48,-1) -> 0 | I48: =ROUND(+$U48*W48,-1) -> 0 | J48: =ROUND(+$U48*X48,-1) -> 0 | K48: =ROUND(+$U48*Y48,-1) -> 0 | L48: =ROUND(+$U48*Z48,-1) -> 89840 | M48: =ROUND(+$U48*AA48,-1) -> 89840 | N48: =ROUND(+$U48*AB48,-1) -> 89840 | O48: =ROUND(+$U48*AC48,-1) -> 179680 | ... S48: =ROUND(+$U48*AG48,-1) -> 269520 | U48: 89841.225 | V48: 0 | W48: 0 | X48: 0 | Y48: 0 | Z48: 1 | AA48: 1 | AB48: 1 | AC48: 2 | AD48: 2 | AE48: 2 | AF48: 2 | AG48: 3
... G56: HEAD AND NECK ONCOLOGY | H56: =ROUND(+$U56*V56,-1) -> 0 | I56: =ROUND(+$U56*W56,-1) -> 0 | J56: =ROUND(+$U56*X56,-1) -> 0 | K56: =ROUND(+$U56*Y56,-1) -> 0 | L56: =ROUND(+$U56*Z56,-1) -> 0 | M56: =ROUND(+$U56*AA56,-1) -> 0 | N56: =ROUND(+$U56*AB56,-1) -> 0 | O56: =ROUND(+$U56*AC56,-1) -> 0 | ... S56: =ROUND(+$U56*AG56,-1) -> 175970 | U56: 175968.72 | V56: 0 | W56: 0 | X56: 0 | Y56: 0 | Z56: 0 | AA56: 0 | AB56: 0 | AC56: 0 | AD56: 0 | AE56: 0 | AF56: 0 | AG56: 1

Sheet C-01
A1: C-01 | Drug Brand Substitution | D1: PC | E1: 0.07591616 | F1: 0.077724757 | G1: 0.085973356
A2: Cost — Materials / COGS | D2: DC | E2: 0.13139166 | F2: 0.061925468 | G2: 0.0659017
A3: OVERVIEW
A4: Description / Objective | B4: Substitute 16 high-spend branded drugs with clinically equivalent alternatives at lower procurement cost. Formulary analysis identifies ₹38.8L/month (₹4.66 Cr/year) incremental profit at full compliance. Top 5 candidates alone account for ₹30L/month: Paracetamol IV (KABIMOL→DOLO IV), Meropenem 1GM (MERONEM→MEROTROL), IV Infusion Sets (SAFESET→TRANSFLOW), Ceftazidime-Avibactam (ZAVIECFTA→PRE ULTRA), Meropenem-Sulbactam (MEROWAK→MERFAITH). Formulary committee with binding authority enforced via HMIS hard-stop at dispensing point.
A5: Start Month | B5: 46113
A6: Estimated Cost | B6: Nil — formulary committee process; HMIS alert = existing config
A7: Expected Impact | B7: ₹300L saving
A9: BASIS FOR THIS INITIATIVE
A10: Pharmacy formulary analysis of 16 high-value drug groups shows current procurement is concentrated with premium brands (Pfizer, Fresenius, Abbott, B Braun) where equivalent molecules from Lupin, Micro Labs, Cipla, Intas, Mylan, and Reliance offer 50–300% higher margin at the same MRP. The substitution is margin-accretive with no change to patient billing — the hospital buys cheaper and retains the MRP spread. Monthly consumption data confirms volumes are sufficient for meaningful impact. See table below for the full 16-drug candidate list with current vs. proposed brands, suppliers, and monthly/annual savings.
A11: EXECUTION TRACKING (to be completed)
A12: Owner | B12: Chief Pharmacist / CMO / Formulary Committee
A13: Key Milestones / Actions | B13: 1. Formulary committee to ratify top 20 substitution candidates — present to Medical Superintendent by May-26 2. Phase 1 (May-Jun-26): Switch top 5 by incremental profit — Paracetamol IV (₹10L/mo), Meropenem 1GM (₹8.3L/mo), IV Infusion Sets (₹4.3L/mo), Ceftazidime-Avibactam (₹3.8L/mo), Meropenem-Sulbactam (₹3.4L/mo) 3. Phase 2 (Jul-Aug-26): Next 5 — Cefoperazone-Sulbactam, Human Albumin 20%, Piperacillin-Tazobactam, Anidulafungin, Sevoflurane 4. Phase 3 (Sep-Oct-26): Remaining 10 items including Luprolide, Sodium Chloride, Amphotericin B, Immunoglobulin, Darbepoetin, Ursodeoxycholic Acid 5. HMIS hard-stop enforcement: prescribers must select from approved formulary list or enter clinical justification override 6. Formulary compliance tracking: monthly report on compliance rate by prescriber and department — target 90%+ compliance by Q3 FY27 7. Monthly pharmacy report: brand-vs-generic ratio, override frequency, incremental savings vs baseline 8. Target: ₹300L annual saving (₹38.8L/month × 80% compliance) 9. Quarterly formulary review — add/remove based on new rate contracts and clinical feedback
A14: Risks / Dependencies | B14: 1. Clinician resistance where consultants prefer existing premium brands (Pfizer, Fresenius, Abbott) due to familiarity or perceived quality 2. Patient perception risk if substitution is visible on itemised bills — mitigated through package pricing 3. Supplier reliability — Micro Labs, Lupin, Cipla must guarantee supply continuity; stock-out risk on critical molecules (Meropenem, Albumin) 4. Formulary committee alignment required across 16 substitutions and 8 suppliers 5. HMIS hard-stop configuration depends on IT bandwidth; slippage delays compliance
A15: Remarks | B15: Represents the largest single cost-saving line item (~₹3 Cr/yr), with the top 5 molecules contributing approximately ₹30L/month. Enforcement via HMIS hard-stop is required; without it, override rates typically drift to 40–60% within six months. Monthly brand-vs-generic ratio is the primary operational KPI. Dependencies: C-02 (rate contracts may further improve generic pricing) and C-05 (inventory discipline for new SKUs).
A16: TOP 16 DRUG SUBSTITUTION CANDIDATES (from formulary analysis)
A17: # | B17: Current Brand | C17: Generic Name | D17: Proposed Substitute | E17: Supplier | F17: Monthly Saving (₹) | G17: Annual Saving (₹)
A18: 1 | B18: KABIMOL INJ | C18: Paracetamol IV | D18: DOLO IV | E18: Micro Labs | F18: 998688 | G18: 11984256
A19: 2 | B19: MERONEM 1GM | C19: Meropenem 1GM | D19: MEROTROL 1GM | E19: Lupin | F19: 825346 | G19: 9904153
A20: 3 | B20: SAFESET IV SET | C20: IV Infusion Set | D20: IV SET TRANSFLOW | E20: Romsons | F20: 431438 | G20: 5177255
A21: 4 | B21: ZAVIECFTA INJ | C21: Ceftazidime+Avibactam | D21: PRE ULTRA INJ | E21: BDR | F21: 379748 | G21: 4556970
A22: 5 | B22: MEROWAK S 1.5 INJ | C22: Meropenem+Sulbactam | D22: MERFAITH S 1.5 INJ | E22: Unifaith | F22: 335162 | G22: 4021948
A23: 6 | B23: FLEXBUMIN 20% INJ | C23: Human Albumin 20% | D23: ALBUREL 20% INJ | E23: Reliance | F23: 246412 | G23: 2956945
A24: 7 | B24: ERAXIS 100MG INJ | C24: Anidulafungin 100 | D24: ANIDULAN INJ | E24: Mylan | F24: 148331 | G24: 1779975
A25: 8 | B25: MAGNEX FORTE 1.5GM | C25: Cefoperazone+Sulbactam | D25: CEFGLOBE S FORTE | E25: Micro Labs | F25: 125444 | G25: 1505331
A26: 9 | B26: GAMMAREN 5GM INJ | C26: Immunoglobulin | D26: IMMUNOREL 5GM INJ | E26: Reliance | F26: 117070 | G26: 1404840
A27: 10 | B27: SEVITRUE 250ML | C27: Sevoflurane | D27: SEVOTROY 250ML | E27: Troika | F27: 84436 | G27: 1013230
A28: 11 | B28: ABHOPE INJ | C28: Liposomal Amphotericin B | D28: AMBISOME INJ | E28: Mylan | F28: 56435 | G28: 677223
A29: 12 | B29: DARNESP 40 INJ | C29: Darbepoetin Alfa | D29: CRESP 40 INJ | E29: Dr Reddys | F29: 49678 | G29: 596131
... A33: 16 | B33: TAZACT 4.5 INJ | C33: Piperacillin+Tazobactam | D33: PICZAR 4.5 INJ | E33: Intas | F33: 5377 | G33: 64525
B34: TOTAL | F34: =SUM(F18:F33) -> 3882148 | G34: =SUM(G18:G33) -> 46585774
A36: Monthly incremental profit at 100% compliance: ₹38.8L | At 80% compliance: ₹31L | Annual target (conservative): ₹300L

Sheet C-02
A1: C-02 | Manufacturer Rate Contract
A2: Cost — Materials / COGS
A3: OVERVIEW
A4: Description / Objective | B4: MD/CEO-level engagement with top 20 manufacturers. Negotiate higher percentage discount via volume commitment letters. Replace spot purchase with 12-month rate contracts.
A5: Start Month | B5: 46113
A6: Estimated Cost | B6: Nil — internal negotiation
A7: Expected Impact | B7: ₹130L saving
A9: BASIS FOR THIS INITIATIVE
A10: Volume commitment letters with manufacturers routinely generate 5–15% additional discount over standard trade terms. MD/CEO-level engagement changes the negotiation dynamic from procurement to institutional partnership. This is standard practice in large hospital networks — Lakeshore operates at sufficient scale to access these rates.
A11: EXECUTION TRACKING (to be completed)
A12: Owner | B12: Procurement Head / Chief Pharmacist / CFO
A13: Key Milestones / Actions | B13: 1. Identify top 10 manufacturers by spend — prepare volume data and benchmarks by May-26 2. CEO/MD to lead initial meetings with 3 largest suppliers by Jun-26 3. Negotiate minimum 8–10% rate reduction on top 5 categories by Jul-26 4. Execute revised rate contracts with lock-in period (12–24 months) by Aug-26 5. Implement new rates in HIS procurement module 6. Monitor monthly purchase prices vs contracted rates — flag deviations
A14: Risks / Dependencies | B14: 1. Manufacturers will resist volume commitments without credible 12-month forecasts 2. Existing distributors may lose margin and resist replacement commercial terms (interacts with C-03) 3. Manufacturer direct contracts may require letters of credit or working capital commitments — CFO alignment required 4. Supply continuity risk where single-source manufacturer relationships replace distributor redundancy 5. Price benchmarking data may be dated; fresh quotes from three alternatives should be obtained before renegotiation
A15: Remarks | B15: To be sequenced with C-03 (distributor consolidation); manufacturer contracts and distributor consolidation address two sides of the same procurement strategy. Suggested starting point: highest-spend molecules (Meropenem, Albumin, Piperacillin). MD/CEO-level engagement typically unlocks a larger discount band (5–8%) than CFO-level discussions (2–3%).

Sheet C-03
A1: C-03 | Distributor Consolidation
A2: Cost — Materials / COGS
A3: OVERVIEW
A4: Description / Objective | B4: Reduce to 3 core distributors. Extract volume-linked discounts from consolidated spend. Eliminate the margin leakage from fragmented procurement across 10–15 distributors.
A5: Start Month | B5: 46113
A6: Estimated Cost | B6: Nil — procurement process change only
A7: Expected Impact | B7: ₹80L saving
A9: BASIS FOR THIS INITIATIVE
A10: Distributor fragmentation eliminates volume leverage. Consolidation to 3 distributors concentrates annual spend into relationships where 3–5% incremental discount is achievable. The process change is administrative — no capital required.
A11: EXECUTION TRACKING (to be completed)
A12: Owner | B12: Procurement Head / Chief Pharmacist / CFO
A13: Key Milestones / Actions | B13: 1. Map current distributor landscape — number of active distributors, categories, credit terms by May-26 2. Shortlist 3 core distributors based on range, reliability, credit, and pricing 3. Negotiate consolidated volume discounts with shortlisted distributors by Jun-26 4. Transition procurement to 3 core distributors over 3 months (Jul–Sep-26) 5. Monitor fill rates, delivery times, and pricing compliance monthly
A14: Risks / Dependencies | B14: 1. Existing distributors losing partnership may respond with service-level reductions during the transition 2. Over-consolidation creates single-point-of-failure risk; a minimum of three distributors should be retained for redundancy 3. Credit term renegotiation complexity — new distributors may seek tighter terms initially 4. Stock-out risk during transition; structured cutover planning required 5. Volume leverage depends on C-02 rate contracts; the two initiatives should move in parallel
A15: Remarks | B15: Distributor consolidation on its own yields modest savings; paired with C-02 manufacturer contracts it supports the full 5–8% improvement. Suggested structure: three core distributors with category specialisation (critical care, generics, surgical consumables), with a small backup panel retained for emergency sourcing.

Sheet C-04
A1: C-04 | Surgical BOQ Standardisation
A2: Cost — Materials / COGS
A3: OVERVIEW
A4: Description / Objective | B4: Three-layer consumable optimisation across OT and clinical departments: (A) Standardise preference cards and BOQ per procedure — eliminate inter-surgeon variation for top 20 procedures. (B) De-specify non-critical consumables — e.g., non-sterile exam gloves in OPD, basic-grade sutures where clinical outcome unaffected, standard (non-premium) IV sets for routine cases. (C) Harmonise consumable specifications across departments — glove types/sizes, suture brands, syringe specs. Consolidate high-value SKUs to 2–3 vendors per category (cath-lab balloons, orthopaedic implants, endo-surgery accessories).
A5: Start Month | B5: 46174
A6: Estimated Cost | B6: ₹2.5L one-time (OT audit, preference card redesign, store system config)
A7: Expected Impact | B7: ₹60L saving
A9: BASIS FOR THIS INITIATIVE
A10: Inter-surgeon variation in consumable use for identical procedures is one of the largest sources of materials cost inflation in OTs. A single procedure can have 3–5× cost variation between surgeons. Standardised BOQs based on clinical consensus reduce this variation without compromising outcomes. This is the prerequisite for meaningful consumable tendering.
A11: EXECUTION TRACKING (to be completed)
A12: Owner | B12: OT In-Charge / Procurement Head / CFO
A13: Key Milestones / Actions | B13: 1. Compile current BOQ variations across surgeons for top 20 procedures by May-26 2. Identify de-specification candidates — non-critical consumables where premium grade is not clinically required (OPD gloves, routine sutures, standard IV sets) by Jun-26 3. Clinical committee to agree standardised BOQ per procedure and de-specification list by Jun-26 4. Map consumable specs across departments — identify harmonisation opportunities (glove types, syringe specs, suture brands) 5. High-value consumable vendor consolidation: run price benchmarking on balloon catheters, orthopaedic implants, endo-surgery accessories. Target 2–3 vendors per category 6. Update HIS with standard BOQ templates — auto-populate per procedure type 7. Negotiate bulk pricing for standardised consumable kits and de-specified SKUs with suppliers by Jul-26 8. Monitor BOQ compliance and variance reporting monthly
A14: Risks / Dependencies | B14: 1. Surgeon resistance, as preference cards reflect individual surgical styles; standardisation may be perceived as an intrusion on clinical autonomy 2. Pack design must cover approximately 80% of cases without excess waste 3. OT store system reconfiguration required; may require HMIS support 4. Training burden on OT staff during cutover; a short-term efficiency dip is expected 5. Clinical quality risk if substitute consumables underperform; validation with clinical leads is required before switching
A15: Remarks | B15: Cardiac and orthopaedic specialties have the highest consumable variance and offer the largest impact. Rather than a single standardised pack, 2–3 preference card variants per procedure provide a better balance of standardisation and clinical acceptability. Dependencies: C-01 (consumable substitution choices) and C-05 (inventory discipline). OT In-Charge buy-in is required for adoption.

Sheet C-05
A1: C-05 | Inventory, Expiry & Wastage Control
A2: Cost — Materials / COGS
A3: OVERVIEW
A4: Description / Objective | B4: Comprehensive wastage reduction across all material categories: (A) Drug Inventory & Expiry: Reduce drug inventory holding days to <20. Eliminate expiry-related write-offs. Negotiate vendor return clauses in all new supply contracts. HMIS-enforced FIFO dispensing and reorder-point alerts. (B) F&B Meal Wastage: Reduce cost per patient meal through menu standardisation and order accuracy. Reduce wastage by 20% through demand forecasting and plate return analysis. Dietitian-driven menu standardisation. (C) Consumables & Surgical Wastage: Cut-strip wastage, opened-but-unused consumables, OT preference card over-ordering. Track and report wastage by department monthly.
A5: Start Month | B5: 46113
A6: Estimated Cost | B6: Nil — HMIS config + pharmacy/F&B process change
A7: Expected Impact | B7: ₹70L saving
A9: BASIS FOR THIS INITIATIVE
A10: Expiry write-offs in hospital pharmacies average 1–3% of drug spend annually. Inventory days above 25 represent tied-up working capital and expiry risk. HMIS-enforced FIFO dispensing and reorder-point alerts are standard system features that are often under-configured. Vendor return clauses shift expiry risk to the supplier for slow-moving molecules.
A11: EXECUTION TRACKING (to be completed)
A12: Owner | B12: Chief Pharmacist / F&B Manager / Central Stores In-Charge / CFO
A13: Key Milestones / Actions | B13: 1. Conduct full pharmacy and consumable inventory audit — identify slow-moving and near-expiry stock by May-26 2. Implement FEFO (First Expiry First Out) protocol in HMIS by Jun-26 3. Set reorder points and safety stock levels for top 200 SKUs 4. Monthly expiry write-off tracking — target <0.5% of inventory value 5. Quarterly dead stock review — return or dispose items with <3 month shelf life 6. F&B wastage audit — implement portion control and daily consumption tracking
A14: Risks / Dependencies | B14: 1. Savings depend on both HMIS configuration and prescriber behaviour change; slippage on either reduces realised savings 2. F&B waste reduction requires kitchen process change, which intersects with F&B Manager operational autonomy 3. Expiry tracking requires end-to-end batch discipline; weak links reduce savings 4. Over-tight inventory levels create stock-out risk; demand forecasting accuracy is required 5. Central stores staffing may require upskilling on FIFO/FEFO discipline
A15: Remarks | B15: Composed of 15–20 sub-process improvements totalling approximately ₹70L/yr, with no single large line item. Pharmacy expiry is the largest bucket (~40% of wastage value), followed by F&B and consumables. Dependencies: C-01 (new SKU discipline) and C-04 (standardised BOQs reduce variance). Central Stores In-Charge is the operational owner; CFO provides governance cadence.

Sheet C-06
A1: C-06 | Laundry Cost Reduction
A2: Cost — Materials / COGS
A3: OVERVIEW | H3: Apr | I3: May | J3: Jun | K3: Jul | L3: Aug | M3: Sep | N3: Oct | O3: Nov | P3: Dec | Q3: Jan | R3: Feb | S3: Mar
A4: Description / Objective | B4: Reduce cost per kg of linen processing and write-offs through outsourcing optimisation and linen tracking. Implement linen tagging to reduce loss. | H4: 0.071854255 | I4: 0.071842762 | J4: 0.068150812 | K4: 0.074527645 | L4: 0.10452872 | M4: 0.042781116 | N4: 0.070356279 | O4: 0.080148189 | P4: 0.072635038 | Q4: 0.080234505 | R4: 0.089285081 | S4: 0.1736556
A5: Start Month | B5: 46113 | F5: Laundry | G5: 1500000 | H5: =+$G$5*H4 -> 107781.38 | I5: =+$G$5*I4 -> 107764.14 | J5: =+$G$5*J4 -> 102226.22 | K5: =+$G$5*K4 -> 111791.47 | L5: =+$G$5*L4 -> 156793.08 | M5: =+$G$5*M4 -> 64171.674 | N5: =+$G$5*N4 -> 105534.42 | O5: =+$G$5*O4 -> 120222.28 | ... S5: =+$G$5*S4 -> 260483.4
A6: Estimated Cost | B6: ₹1.5L one-time (linen tagging/RFID if required)
A7: Expected Impact | B7: ₹15L saving
A9: BASIS FOR THIS INITIATIVE
A10: Linen loss and high-cost in-house laundry are pervasive inefficiencies in hospitals that have not benchmarked against outsourced alternatives. SAVINGS BUILD-UP (₹15L/yr conservative): • Current in-house laundry cost (est.): staff (4–5 FTEs × ₹2.5L CTC) + utilities + chemicals + equipment maintenance = ~₹18–20L/yr • Linen loss/damage: est. 8–10% annual replacement on ₹15L linen inventory = ₹1.2–1.5L/yr • Total current cost: ~₹20–22L/yr • Outsourced laundry (per-kg model): est. ₹8–10/kg × ~500 kg/day × 365 days = ₹15–18L/yr • Linen loss reduction with RFID tracking: 50% reduction = ₹0.6–0.8L/yr saved • Net saving: (₹20–22L) – (₹15–18L) + ₹0.6L linen savings = ₹3–5L/yr from outsourcing • Additional: renegotiate existing contract if already outsourced → 10–15% rate reduction = ₹1.5–2L • Conservative total: ₹15L (accounts for partial outsourcing + linen loss reduction + rate renegotiation)
A11: EXECUTION TRACKING (to be completed)
A12: Owner | B12: Housekeeping/Linen In-Charge / Procurement Head
A13: Key Milestones / Actions | B13: 1. Benchmark current in-house laundry cost per kg vs 3 outsourced providers by May-26 2. Pilot RFID linen tagging on 2 floors — measure loss reduction over 60 days (Jun–Jul-26) 3. If outsourcing viable: issue RFQ to 3 industrial laundry providers by Jul-26 4. If in-house: renegotiate chemical and equipment maintenance contracts 5. Target: 15–20% cost reduction on current laundry spend by Sep-26
A14: Risks / Dependencies | B14: 1. Linen vendor resistance to lower cost-per-kg rates; potential reduction in service levels or frequency 2. RFID / barcode tagging capex required upfront for loss tracking (₹1–2L) 3. In-house laundry alternative requires space, equipment, and labour; a larger analysis is needed before any switch 4. Seasonal linen demand variance may affect flat-rate contract economics 5. Infection control standards must be preserved under any vendor change
A15: Remarks | B15: Modest scale (~₹15L/yr) but benchmarks indicate Lakeshore is paying above the Kerala market rate. Suggested dual track: (a) renegotiate existing vendor through a competitive RFP, and (b) pilot linen tagging to quantify actual loss. Housekeeping/Linen In-Charge leads operational rollout; Procurement Head manages commercial terms.
A16: Bequip Remarks | B16: This Initiative is not take up as the agreement alreaady signed with new rates

Sheet C-07
A1: C-07 | AMC Renegotiation
A2: Cost — Materials / COGS
A3: OVERVIEW | F3: Apr | G3: May | H3: Jun | I3: Jul | J3: Aug | K3: Sep | L3: Oct | M3: Nov | N3: Dec | O3: Jan | P3: Feb | Q3: Mar | R3: YTD
A4: Description / Objective | B4: Classify all equipment into three tiers and match maintenance model to criticality: (A) Critical equipment (OT, ICU, cath-lab, MRI, CT, dialysis) — retain OEM CMC but renegotiate using competitive quotes as leverage. (B) Mid-tier equipment (ward monitors, X-ray, ultrasound, ventilators) — shift from OEM AMC to third-party AMC. (C) Low-cost equipment — move from scheduled AMC to pay-per-visit / breakdown-based service, with insurance cover on asset value where economical. Biomedical vendor empanelment and preventive-maintenance discipline underpin the shift. | D4: FY 2025-26 | F4: 4653353.9 | G4: 4618295.1 | H4: 8597700 | I4: 8080824.9 | J4: 7537976 | K4: 11680041 | L4: 8184021 | M4: 6696564.8 | N4: 6470070.2 | O4: 5028388.5 | P4: 14886145 | Q4: 9718269.9 | R4: =SUM(F4:Q4) -> 96151650
A5: Start Month | B5: 46143 | D5: FY 2026-27 | F5: =+AMC!D63 -> 5322041.8 | G5: =+AMC!E63 -> 1095302.3 | H5: =+AMC!F63 -> 8800589.7 | I5: =+AMC!G63 -> 666270.85 | J5: =+AMC!H63 -> 720491.35 | K5: =+AMC!I63 -> 531688.8 | L5: =+AMC!J63 -> 15813509 | M5: =+AMC!K63 -> 22735891 | ... Q5: =+AMC!O63 -> 17703185 | R5: =SUM(F5:Q5) -> 85156144
A6: Estimated Cost | B6: ₹2.5L one-time (biomedical vendor empanelment + criticality classification) | D6: Savings | F6: =+F5-F4 -> 668687.93 | G6: =+G5-G4 -> -3522992.8 | H6: =+H5-H4 -> 202889.69 | I6: =+I5-I4 -> -7414554 | J6: =+J5-J4 -> -6817484.7 | K6: =+K5-K4 -> -11148352 | L6: =+L5-L4 -> 7629488 | M6: =+M5-M4 -> 16039326 | ... S6: =+S5-S4 -> 0
A7: Expected Impact | B7: ₹30L saving
A9: BASIS FOR THIS INITIATIVE
A10: OEM AMC contracts are systematically overpriced — OEMs charge 8–15% of equipment capital value annually when third-party alternatives deliver equivalent uptime at 4–6%. Criticality classification ensures the trade-off between uptime risk and cost savings is made rationally: non-critical equipment goes third-party; critical imaging and life support stays on OEM with renegotiated rates.
A11: EXECUTION TRACKING (to be completed)
A12: Owner | B12: Biomedical Engineering Head / Procurement Head / CFO
A13: Key Milestones / Actions | B13: 1. Compile all active AMC/CMC contracts — equipment, terms, expiry dates, annual cost by May-26 2. Classify all equipment by criticality tier (critical / mid-tier / low-cost) and match target maintenance model (CMC / AMC / pay-per-visit + insurance) by May-26 3. Identify contracts expiring in next 6 months — prioritise for renegotiation 4. Empanel 2–3 third-party biomedical service providers per equipment category; obtain competitive quotes 5. Evaluate insurance-cover economics for low-cost equipment (asset value cap vs AMC premium) 6. Renegotiate or switch to target maintenance model for top 10 contracts by value by Aug-26 7. Implement preventive maintenance schedule to reduce breakdown-based dependency 8. Quarterly review: tier classification, contract status, cost per equipment tier
A14: Risks / Dependencies | B14: 1. OEM-only service requirements on warranty-sensitive equipment (imaging, cath lab) limit third-party switching 2. Third-party AMC providers may lack parts access, creating downtime risk on critical equipment 3. Biomedical team capacity is constrained; criticality classification takes 4–6 weeks 4. Contract exit penalties on existing OEM AMCs may affect the timing of realised savings 5. Quality monitoring is required; a lower-cost AMC with poor service can exceed the cost of the savings through downtime
A15: Remarks | B15: Criticality tiering is the gating step. Tier 1 (cath lab, imaging, ventilators) remains under OEM AMC; Tier 2 and Tier 3 (peripheral, lab, non-critical) opens to third-party bids. Typical savings on Tier 2/3 AMCs range 20–40%. Biomedical Engineering Head owns technical fit; Procurement Head runs the RFQ.

Sheet C-08
A1: C-08 | Nursing Headcount to Occupied-Bed Norm
A2: Cost — Payroll
A3: OVERVIEW
A4: Description / Objective | B4: Align nursing strength to occupied bed norm (1:3 general ward, 1:1 ICU). Reduce estimated ~97 surplus staff over 9–12 months through natural attrition and hiring freeze.
A5: Start Month | B5: 46113
A6: Estimated Cost | B6: Nil — attrition-based; hiring freeze only
A7: Expected Impact | B7: ₹150L saving
A9: BASIS FOR THIS INITIATIVE
A10: Nursing payroll is the single largest controllable cost line in the hospital. Current nursing strength is calibrated to peak occupancy, but average occupancy runs at 55–68%. Linking nursing deployment to actual occupancy unlocks savings through attrition-based right-sizing. SAVINGS BUILD-UP (₹150L/yr conservative): • Total nursing staff: ~800 FTEs (est.) • Avg CTC per nurse: ~₹4L/yr • Total nursing payroll: ~₹3,200L/yr (₹32 Cr) • Current nurse-to-occupied-bed ratio: ~3.5:1 (staffed for 470 beds at peak) • Target ratio at avg occupancy (60% = 282 beds): 3.0:1 = 846 nurses needed vs ~800 (already slightly lean) • Savings mechanism: not headcount reduction but shift optimisation — Reduce agency/overtime nurses during low-occupancy periods (monsoon, post-festival) — Est. agency nurse spend: ₹200–250L/yr; 40% reduction = ₹80–100L — Overtime reduction: est. ₹50–70L/yr saved • Conservative total: ₹150L (agency reduction + overtime optimisation, no permanent headcount cuts)
A11: EXECUTION TRACKING (to be completed)
A12: Owner | B12: CNO (Chief Nursing Officer) / Head HR
A13: Key Milestones / Actions | B13: 1. Map current nursing deployment by ward, shift, and occupancy level by May-26 2. Quantify agency/overtime nurse spend by month — identify peak vs low-occupancy patterns 3. Implement occupancy-linked shift scheduling — reduce agency nurses during low-occupancy months (monsoon, post-festival) 4. Freeze new permanent nursing hires — fill gaps through internal redeployment 5. Target: 40% reduction in agency nurse spend by Dec-26 6. Monthly dashboard: occupancy vs nursing hours vs agency spend
A14: Risks / Dependencies | B14: 1. Regulated patient-to-nurse ratios (1:3 general, 1:1 ICU) cannot be breached under any scenario 2. Attrition rate variability; slower attrition extends the savings timeline 3. Clinical risk during peak occupancy if wards are understaffed; a floating pool buffer is required 4. Potential union / nursing council concern if reductions are perceived as targeted 5. Case-mix judgement required; high-acuity wards cannot flex to the same extent as low-acuity wards
A15: Remarks | B15: Attrition-based approach; avoids union exposure and severance cost. Approximately 97 surplus FTEs identified from occupancy norm mapping; natural attrition at 18–22% annually covers the reduction within ~18 months. Hiring freeze is the primary lever, with CNO approving all backfills. Interaction with C-10 (EMR reduces nursing admin load) provides a secondary efficiency contribution.

Sheet C-09
A1: C-09 | Pharmacy Headcount Post-Automation
A2: Cost — Payroll
A3: OVERVIEW
A4: Description / Objective | B4: Reduce pharmacy staff headcount (target: 93→86) once barcode dispensing system goes live. Phased reduction via attrition. Hard dependency: barcode dispensing capex project must precede savings.
A5: Start Month | B5: 46174
A6: Estimated Cost | B6: ₹1 Cr one-time capex (barcode dispensing system — hard dependency before savings)
A7: Expected Impact | B7: ₹100L saving
A9: BASIS FOR THIS INITIATIVE
A10: Barcode dispensing and unit-dose systems eliminate multiple manual dispensing and verification steps. In peer pharmacies, automation has reduced headcount by 15–25% with simultaneous improvement in dispensing accuracy. The savings are contingent on the barcode dispensing system going live — this initiative is the downstream benefit of that capital investment.
A11: EXECUTION TRACKING (to be completed)
A12: Owner | B12: Chief Pharmacist / Head IT / Head HR
A13: Key Milestones / Actions | B13: 1. Complete pharmacy workflow automation assessment — identify manual tasks that EMR/HMIS can replace by Jun-26 2. Map current pharmacy FTE allocation by function (dispensing, billing, inventory, compounding) 3. Post-EMR automation: reduce 8–10 FTEs through attrition over 12 months 4. Redeploy surplus staff to clinical pharmacy roles (ward-based medication review) 5. Target: ₹100L annual saving from headcount optimisation by Mar-27
