Workbook

Sheet Dashboard
A1: AOP EXECUTION DASHBOARD — FY 2026-27 | VPS Lakeshore Hospital
A2: FY 2026-27 | Auto-linked from all sheets | Refresh after actuals entry each month
A4: INITIATIVE STATUS
A5: Total Initiatives | C5: Completed | E5: In Progress | G5: Delayed | I5: On Hold | K5: Not Started
A6: =COUNTIF('Initiative Register'!C5:C55,"<>") -> 50 | C6: =COUNTIF('Initiative Register'!R5:R55,"Completed") -> 1 | E6: =COUNTIF('Initiative Register'!R5:R55,"In Progress") -> 1 | G6: =COUNTIF('Initiative Register'!R5:R55,"Delayed") -> 0 | I6: =COUNTIF('Initiative Register'!R5:R55,"On Hold") -> 0 | K6: =COUNTIF('Initiative Register'!R5:R55,"Not Started") -> 48
A9: FINANCIAL SUMMARY (Rs Lakhs)
A10: Metric | B10: AOP Budget | C10: YTD Actual | D10: Variance (Rs) | E10: Variance % | F10: Status
A11: Revenue from Initiatives | B11: ='Revenue Impact'!P71 -> 0 | C11: ='Monthly Actuals'!P73 -> 0 | D11: =C11-B11 -> 0 | E11: =IFERROR(D11/B11,"") | F11: =IF(E11="","",IF(E11<0,"▼ BEHIND","▲ AHEAD"))
A12: Cost of Initiatives | B12: ='Cost Plan'!P55 -> 0 | C12: ='Monthly Actuals'!P127 -> 0 | D12: =C12-B12 -> 0 | E12: =IFERROR(D12/B12,"") | F12: =IF(E12="","",IF(E12<0,"▼ BEHIND","▲ AHEAD"))
A13: Net EBITDA Impact | B13: =B11-B12 -> 0 | C13: =C11-C12 -> 0 | D13: =C13-B13 -> 0 | E13: =IFERROR(D13/B13,"") | F13: =IF(E13="","",IF(E13<0,"▼ BEHIND","▲ AHEAD"))
A15: MONTHLY TREND (Rs Lakhs)
A16: Month | B16: Bdg Revenue | C16: Act Revenue | D16: Rev Var | E16: Bdg Cost | F16: Act Cost | G16: Cost Var | H16: Net EBITDA (Bdg) | I16: Net EBITDA (Act)
A17: Apr | B17: ='Revenue Impact'!D71 -> 0 | C17: ='Monthly Actuals'!D73 -> 0 | D17: =C17-B17 -> 0 | E17: ='Cost Plan'!D55 -> 0 | F17: ='Monthly Actuals'!D127 -> 0 | G17: =F17-E17 -> 0 | H17: =B17-E17 -> 0 | I17: =C17-F17 -> 0
A18: May | B18: ='Revenue Impact'!E71 -> 0 | C18: ='Monthly Actuals'!E73 -> 0 | D18: =C18-B18 -> 0 | E18: ='Cost Plan'!E55 -> 0 | F18: ='Monthly Actuals'!E127 -> 0 | G18: =F18-E18 -> 0 | H18: =B18-E18 -> 0 | I18: =C18-F18 -> 0
A19: Jun | B19: ='Revenue Impact'!F71 -> 0 | C19: ='Monthly Actuals'!F73 -> 0 | D19: =C19-B19 -> 0 | E19: ='Cost Plan'!F55 -> 0 | F19: ='Monthly Actuals'!F127 -> 0 | G19: =F19-E19 -> 0 | H19: =B19-E19 -> 0 | I19: =C19-F19 -> 0
A20: Jul | B20: ='Revenue Impact'!G71 -> 0 | C20: ='Monthly Actuals'!G73 -> 0 | D20: =C20-B20 -> 0 | E20: ='Cost Plan'!G55 -> 0 | F20: ='Monthly Actuals'!G127 -> 0 | G20: =F20-E20 -> 0 | H20: =B20-E20 -> 0 | I20: =C20-F20 -> 0
A21: Aug | B21: ='Revenue Impact'!H71 -> 0 | C21: ='Monthly Actuals'!H73 -> 0 | D21: =C21-B21 -> 0 | E21: ='Cost Plan'!H55 -> 0 | F21: ='Monthly Actuals'!H127 -> 0 | G21: =F21-E21 -> 0 | H21: =B21-E21 -> 0 | I21: =C21-F21 -> 0
A22: Sep | B22: ='Revenue Impact'!I71 -> 0 | C22: ='Monthly Actuals'!I73 -> 0 | D22: =C22-B22 -> 0 | E22: ='Cost Plan'!I55 -> 0 | F22: ='Monthly Actuals'!I127 -> 0 | G22: =F22-E22 -> 0 | H22: =B22-E22 -> 0 | I22: =C22-F22 -> 0
A23: Oct | B23: ='Revenue Impact'!J71 -> 0 | C23: ='Monthly Actuals'!J73 -> 0 | D23: =C23-B23 -> 0 | E23: ='Cost Plan'!J55 -> 0 | F23: ='Monthly Actuals'!J127 -> 0 | G23: =F23-E23 -> 0 | H23: =B23-E23 -> 0 | I23: =C23-F23 -> 0
A24: Nov | B24: ='Revenue Impact'!K71 -> 0 | C24: ='Monthly Actuals'!K73 -> 0 | D24: =C24-B24 -> 0 | E24: ='Cost Plan'!K55 -> 0 | F24: ='Monthly Actuals'!K127 -> 0 | G24: =F24-E24 -> 0 | H24: =B24-E24 -> 0 | I24: =C24-F24 -> 0
A25: Dec | B25: ='Revenue Impact'!L71 -> 0 | C25: ='Monthly Actuals'!L73 -> 0 | D25: =C25-B25 -> 0 | E25: ='Cost Plan'!L55 -> 0 | F25: ='Monthly Actuals'!L127 -> 0 | G25: =F25-E25 -> 0 | H25: =B25-E25 -> 0 | I25: =C25-F25 -> 0
A26: Jan | B26: ='Revenue Impact'!M71 -> 0 | C26: ='Monthly Actuals'!M73 -> 0 | D26: =C26-B26 -> 0 | E26: ='Cost Plan'!M55 -> 0 | F26: ='Monthly Actuals'!M127 -> 0 | G26: =F26-E26 -> 0 | H26: =B26-E26 -> 0 | I26: =C26-F26 -> 0
A27: Feb | B27: ='Revenue Impact'!N71 -> 0 | C27: ='Monthly Actuals'!N73 -> 0 | D27: =C27-B27 -> 0 | E27: ='Cost Plan'!N55 -> 0 | F27: ='Monthly Actuals'!N127 -> 0 | G27: =F27-E27 -> 0 | H27: =B27-E27 -> 0 | I27: =C27-F27 -> 0
A28: Mar | B28: ='Revenue Impact'!O71 -> 0 | C28: ='Monthly Actuals'!O73 -> 0 | D28: =C28-B28 -> 0 | E28: ='Cost Plan'!O55 -> 0 | F28: ='Monthly Actuals'!O127 -> 0 | G28: =F28-E28 -> 0 | H28: =B28-E28 -> 0 | I28: =C28-F28 -> 0
A30: EXCEPTION LOG — Initiatives Flagged
A31: # | B31: Initiative ID | C31: Initiative Name | D31: Status | E31: Ann Budget (Rs) | F31: Ann Actual (Rs) | G31: Variance (Rs) | H31: Var % | I31: Exception Flag
A32: 1 | B32: ='Initiative Register'!B5 -> INI-001 | C32: ='Initiative Register'!C5 -> Campaign- Patient experience improvement | D32: ='Initiative Register'!R5 -> Completed | E32: ='Cost Plan'!P5 -> 0 | F32: ='Monthly Actuals'!P77 -> 0 | G32: =F32-E32 -> 0 | H32: =IFERROR(IF(E32=0,"",G32/E32),"" ) | I32: ='Variance Analysis'!X5
A33: 2 | B33: ='Initiative Register'!B6 | C33: ='Initiative Register'!C6 -> 0 | D33: ='Initiative Register'!R6 -> 0 | E33: ='Cost Plan'!P6 -> 0 | F33: ='Monthly Actuals'!P78 -> 0 | G33: =F33-E33 -> 0 | H33: =IFERROR(IF(E33=0,"",G33/E33),"" ) | I33: ='Variance Analysis'!X6
A34: 3 | B34: ='Initiative Register'!B7 -> INI-003 | C34: ='Initiative Register'!C7 -> Geriatric ward | D34: ='Initiative Register'!R7 -> Not Started | E34: ='Cost Plan'!P7 -> 0 | F34: ='Monthly Actuals'!P79 -> 0 | G34: =F34-E34 -> 0 | H34: =IFERROR(IF(E34=0,"",G34/E34),"" ) | I34: ='Variance Analysis'!X7
A35: 4 | B35: ='Initiative Register'!B8 -> INI-004 | C35: ='Initiative Register'!C8 -> Appointment of Specialized Doctors and development of existing department | D35: ='Initiative Register'!R8 -> Not Started | E35: ='Cost Plan'!P8 -> 0 | F35: ='Monthly Actuals'!P80 -> 0 | G35: =F35-E35 -> 0 | H35: =IFERROR(IF(E35=0,"",G35/E35),"" ) | I35: ='Variance Analysis'!X8
A36: 5 | B36: ='Initiative Register'!B9 -> INI-005 | C36: ='Initiative Register'!C9 -> Patient companion | D36: ='Initiative Register'!R9 -> Not Started | E36: ='Cost Plan'!P9 -> 0 | F36: ='Monthly Actuals'!P81 -> 0 | G36: =F36-E36 -> 0 | H36: =IFERROR(IF(E36=0,"",G36/E36),"" ) | I36: ='Variance Analysis'!X9
A37: 6 | B37: ='Initiative Register'!B10 -> INI-006 | C37: ='Initiative Register'!C10 -> Newborn Care Enhancement | D37: ='Initiative Register'!R10 -> Not Started | E37: ='Cost Plan'!P10 -> 0 | F37: ='Monthly Actuals'!P82 -> 0 | G37: =F37-E37 -> 0 | H37: =IFERROR(IF(E37=0,"",G37/E37),"" ) | I37: ='Variance Analysis'!X10
A38: 7 | B38: ='Initiative Register'!B11 -> INI-007 | C38: ='Initiative Register'!C11 -> Digital Patient Acquisition Funnel | D38: ='Initiative Register'!R11 -> Not Started | E38: ='Cost Plan'!P11 -> 0 | F38: ='Monthly Actuals'!P83 -> 0 | G38: =F38-E38 -> 0 | H38: =IFERROR(IF(E38=0,"",G38/E38),"" ) | I38: ='Variance Analysis'!X11
A39: 8 | B39: ='Initiative Register'!B12 -> INI-008 | C39: ='Initiative Register'!C12 -> Development of KPI for Doctors | D39: ='Initiative Register'!R12 -> Not Started | E39: ='Cost Plan'!P12 -> 0 | F39: ='Monthly Actuals'!P84 -> 0 | G39: =F39-E39 -> 0 | H39: =IFERROR(IF(E39=0,"",G39/E39),"" ) | I39: ='Variance Analysis'!X12
A40: 9 | B40: ='Initiative Register'!B13 -> INI-009 | C40: ='Initiative Register'!C13 -> Daycare and Minimaly Invasive Shift | D40: ='Initiative Register'!R13 -> Not Started | E40: ='Cost Plan'!P13 -> 0 | F40: ='Monthly Actuals'!P85 -> 0 | G40: =F40-E40 -> 0 | H40: =IFERROR(IF(E40=0,"",G40/E40),"" ) | I40: ='Variance Analysis'!X13
A41: 10 | B41: ='Initiative Register'!B14 -> INI-010 | C41: ='Initiative Register'!C14 -> Consumables standardization model | D41: ='Initiative Register'!R14 -> Not Started | E41: ='Cost Plan'!P14 -> 0 | F41: ='Monthly Actuals'!P86 -> 0 | G41: =F41-E41 -> 0 | H41: =IFERROR(IF(E41=0,"",G41/E41),"" ) | I41: ='Variance Analysis'!X14
A42: 11 | B42: ='Initiative Register'!B15 -> INI-011 | C42: ='Initiative Register'!C15 -> Collaboration with other Hospitals | D42: ='Initiative Register'!R15 -> Not Started | E42: ='Cost Plan'!P15 -> 0 | F42: ='Monthly Actuals'!P87 -> 0 | G42: =F42-E42 -> 0 | H42: =IFERROR(IF(E42=0,"",G42/E42),"" ) | I42: ='Variance Analysis'!X15
A43: 12 | B43: ='Initiative Register'!B16 -> INI-012 | C43: ='Initiative Register'!C16 -> ANNUAL RATE REVISION POLICY | D43: ='Initiative Register'!R16 -> Not Started | E43: ='Cost Plan'!P16 -> 0 | F43: ='Monthly Actuals'!P88 -> 0 | G43: =F43-E43 -> 0 | H43: =IFERROR(IF(E43=0,"",G43/E43),"" ) | I43: ='Variance Analysis'!X16
... A51: 20 | B51: ='Initiative Register'!B24 -> INI-020 | C51: ='Initiative Register'!C24 -> CME AND CLINICAL CONNECT PROGRAMME | D51: ='Initiative Register'!R24 -> Not Started | E51: ='Cost Plan'!P24 -> 0 | F51: ='Monthly Actuals'!P96 -> 0 | G51: =F51-E51 -> 0 | H51: =IFERROR(IF(E51=0,"",G51/E51),"" ) | I51: ='Variance Analysis'!X24

Sheet Initiative Register
A1: AOP INITIATIVE REGISTER — FY 2026-27
A3: IDENTIFICATION | C3: DESCRIPTION | F3: OWNERSHIP | H3: TIMELINE | K3: COST | M3: SUCCESS CRITERIA | O3: FINANCIAL IMPACT | Q3: STATUS | S3: REMARKS
A4: # | B4: Initiative ID | C4: Initiative Name | D4: Function / Dept | E4: Description / Objective | F4: Owner | G4: Designation | H4: Start Month | I4: End Month | J4: Duration (Mths) | K4: Cost Type | L4: Est. Cost (Rs Lkh) | M4: KRA | N4: KPI / Metric | O4: Est. Revenue Impact (Rs Lkh) | P4: Benefit Month | Q4: Priority | R4: Status | S4: Remarks / Dependencies
A5: 1 | B5: =IF(C5<>"","INI-"&TEXT(A5,"000"),"") -> INI-001 | C5: Campaign- Patient experience improvement | D5: Marketing | E5: To enhance overall patient satisfaction by collecting structured feedback, identifying service gaps, and implementing improvement initiatives across departments. | F5: Marketing Head | G5: Manager – Marketing | H5: Mar | I5: Mar | J5: =IFERROR(IF(AND(H5<>"",I5<>""),MATCH(I5,{"Apr","May","Jun","Jul","Aug","Sep","Oct","Nov","Dec","Jan","Feb","Mar"},0)-MATCH(H5,{"Apr","May","Jun","Jul","Aug","Sep","Oct","Nov","Dec","Jan","Feb","Mar"},0)+1,""),"" ) -> 1 | L5: 0 | O5: 0 | R5: Completed | S5: No direct financial implication points | T5: final report to receive
A6: =+A5+1 -> 2 | B6: =IF(C6<>"","INI-"&TEXT(A6,"000"),"")
A7: =+A6+1 -> 3 | B7: =IF(C7<>"","INI-"&TEXT(A7,"000"),"") -> INI-003 | C7: Geriatric ward | D7: HR & Admin | E7: To establish and operationalize a dedicated geriatric care unit aimed at improving clinical outcomes, patient comfort, and specialized services for elderly patients. | F7: Admin Head | G7: Manager – HR & Administration | J7: =IFERROR(IF(AND(H7<>"",I7<>""),MATCH(I7,{"Apr","May","Jun","Jul","Aug","Sep","Oct","Nov","Dec","Jan","Feb","Mar"},0)-MATCH(H7,{"Apr","May","Jun","Jul","Aug","Sep","Oct","Nov","Dec","Jan","Feb","Mar"},0)+1,""),"" ) | R7: Not Started | S7: Set up a meeting with Kancare a senior care startup (SVP suggestion)
A8: =+A7+1 -> 4 | B8: =IF(C8<>"","INI-"&TEXT(A8,"000"),"") -> INI-004 | C8: Appointment of Specialized Doctors and development of existing department | D8: HR & Admin | E8: To strengthen clinical capabilities by onboarding specialized doctors and enhancing existing departments to improve service quality and increase patient inflow. | F8: Medical Director | G8: Head – Clinical Services | J8: =IFERROR(IF(AND(H8<>"",I8<>""),MATCH(I8,{"Apr","May","Jun","Jul","Aug","Sep","Oct","Nov","Dec","Jan","Feb","Mar"},0)-MATCH(H8,{"Apr","May","Jun","Jul","Aug","Sep","Oct","Nov","Dec","Jan","Feb","Mar"},0)+1,""),"" ) | R8: Not Started
A9: =+A8+1 -> 5 | B9: =IF(C9<>"","INI-"&TEXT(A9,"000"),"") -> INI-005 | C9: Patient companion | D9: HR & Admin | E9: To enhance patient experience and continuity of care by providing dedicated patient companions to assist throughout the hospital journey, including admission, in-hospital support, discharge coordination, and periodic follow-up, thereby improving patient satisfaction and retention. | F9: HR Head | G9: Manager | J9: =IFERROR(IF(AND(H9<>"",I9<>""),MATCH(I9,{"Apr","May","Jun","Jul","Aug","Sep","Oct","Nov","Dec","Jan","Feb","Mar"},0)-MATCH(H9,{"Apr","May","Jun","Jul","Aug","Sep","Oct","Nov","Dec","Jan","Feb","Mar"},0)+1,""),"" ) | R9: Not Started | S9: Set up a meeting with Healtheease a Health Startup (SVP suggestion)
A10: =+A9+1 -> 6 | B10: =IF(C10<>"","INI-"&TEXT(A10,"000"),"") -> INI-006 | C10: Newborn Care Enhancement | D10: Operations | E10: To enhance maternal and neonatal care services by providing comprehensive post-delivery support, including newborn care, mother care, lactation guidance, and structured follow-up programs, thereby improving clinical outcomes and patient satisfaction. | F10: Operations Head | G10: Manager – Operations / Head – Nursing | J10: =IFERROR(IF(AND(H10<>"",I10<>""),MATCH(I10,{"Apr","May","Jun","Jul","Aug","Sep","Oct","Nov","Dec","Jan","Feb","Mar"},0)-MATCH(H10,{"Apr","May","Jun","Jul","Aug","Sep","Oct","Nov","Dec","Jan","Feb","Mar"},0)+1,""),"" ) | R10: Not Started
A11: =+A10+1 -> 7 | B11: =IF(C11<>"","INI-"&TEXT(A11,"000"),"") -> INI-007 | C11: Digital Patient Acquisition Funnel | D11: Business Development | E11: To strengthen digital patient acquisition by leveraging teleconsultation, digital marketing channels, and conversion optimization strategies to increase OP footfall and IP admissions. | F11: Business Development Head | G11: Manager – Business Development | H11: May | I11: Mar | J11: =IFERROR(IF(AND(H11<>"",I11<>""),MATCH(I11,{"Apr","May","Jun","Jul","Aug","Sep","Oct","Nov","Dec","Jan","Feb","Mar"},0)-MATCH(H11,{"Apr","May","Jun","Jul","Aug","Sep","Oct","Nov","Dec","Jan","Feb","Mar"},0)+1,""),"" ) -> 11 | O11: 0 | R11: Not Started
A12: =+A11+1 -> 8 | B12: =IF(C12<>"","INI-"&TEXT(A12,"000"),"") -> INI-008 | C12: Development of KPI for Doctors | D12: HR & Admin | E12: To establish a structured performance management framework for doctors by defining key performance indicators (KPIs) aligned with revenue, clinical outcomes, and patient engagement. | F12: HR Head | G12: Manager – HR | J12: =IFERROR(IF(AND(H12<>"",I12<>""),MATCH(I12,{"Apr","May","Jun","Jul","Aug","Sep","Oct","Nov","Dec","Jan","Feb","Mar"},0)-MATCH(H12,{"Apr","May","Jun","Jul","Aug","Sep","Oct","Nov","Dec","Jan","Feb","Mar"},0)+1,""),"" ) | R12: Not Started
A13: =+A12+1 -> 9 | B13: =IF(C13<>"","INI-"&TEXT(A13,"000"),"") -> INI-009 | C13: Daycare and Minimaly Invasive Shift | D13: Operations | E13: To improve operational efficiency and reduce average length of stay (ALOS) by promoting daycare procedures and minimally invasive surgical techniques. | F13: Operations Head | G13: Manager – Operations | J13: =IFERROR(IF(AND(H13<>"",I13<>""),MATCH(I13,{"Apr","May","Jun","Jul","Aug","Sep","Oct","Nov","Dec","Jan","Feb","Mar"},0)-MATCH(H13,{"Apr","May","Jun","Jul","Aug","Sep","Oct","Nov","Dec","Jan","Feb","Mar"},0)+1,""),"" ) | R13: Not Started
A14: =+A13+1 -> 10 | B14: =IF(C14<>"","INI-"&TEXT(A14,"000"),"") -> INI-010 | C14: Consumables standardization model | D14: Supply Chain / Purchase | E14: To optimize cost efficiency by standardizing consumable usage through procedure-wise bundling and reducing wastage across departments. | F14: Purchase Head | G14: Manager – Supply Chain | J14: =IFERROR(IF(AND(H14<>"",I14<>""),MATCH(I14,{"Apr","May","Jun","Jul","Aug","Sep","Oct","Nov","Dec","Jan","Feb","Mar"},0)-MATCH(H14,{"Apr","May","Jun","Jul","Aug","Sep","Oct","Nov","Dec","Jan","Feb","Mar"},0)+1,""),"" ) | R14: Not Started
A15: =+A14+1 -> 11 | B15: =IF(C15<>"","INI-"&TEXT(A15,"000"),"") -> INI-011 | C15: Collaboration with other Hospitals | D15: Business Development | E15: To expand patient inflow and service capabilities through strategic partnerships and referral networks with other hospitals and specialty centers. | F15: Business Development Head | G15: Manager – Business Development | J15: =IFERROR(IF(AND(H15<>"",I15<>""),MATCH(I15,{"Apr","May","Jun","Jul","Aug","Sep","Oct","Nov","Dec","Jan","Feb","Mar"},0)-MATCH(H15,{"Apr","May","Jun","Jul","Aug","Sep","Oct","Nov","Dec","Jan","Feb","Mar"},0)+1,""),"" ) | R15: Not Started
A16: =+A15+1 -> 12 | B16: =IF(C16<>"","INI-"&TEXT(A16,"000"),"") -> INI-012 | C16: ANNUAL RATE REVISION POLICY | D16: Finance | E16: Institutionalise a pricing committee meeting every April. Revise all IP rates (room, procedures, OT charges, nursing, clinical charges) by CPI+2% for cash patients. Simultaneously renegotiate TPA/insurance tariffs annually. Prevents multi-year price stagnation — the single biggest structural margin leak in private hospitals. | F16: Finance Head | G16: CFO + CEO | H16: May | I16: May | J16: =IFERROR(IF(AND(H16<>"",I16<>""),MATCH(I16,{"Apr","May","Jun","Jul","Aug","Sep","Oct","Nov","Dec","Jan","Feb","Mar"},0)-MATCH(H16,{"Apr","May","Jun","Jul","Aug","Sep","Oct","Nov","Dec","Jan","Feb","Mar"},0)+1,""),"" ) -> 1 | L16: 0 | O16: 634.84 | P16: May | Q16: High | R16: Not Started | S16: Revenue impact starts from May 2026 onwards- Only the annual impact shown.
A17: =+A16+1 -> 13 | B17: =IF(C17<>"","INI-"&TEXT(A17,"000"),"") -> INI-013 | C17: PROCEDURE CONTRIBUTION AUDIT AND REPRICING | D17: Finance | E17: Cost out the top 50 procedures by revenue value. For 26% EBITDA, procedure-level contribution must average 58%. Identify all procedures where contribution is below 50%. Revise cash rates. Flag TPA tariff renegotiation list separately. | F17: Finance Head | G17: CFO + Medical Director | H17: May | I17: Jun | J17: =IFERROR(IF(AND(H17<>"",I17<>""),MATCH(I17,{"Apr","May","Jun","Jul","Aug","Sep","Oct","Nov","Dec","Jan","Feb","Mar"},0)-MATCH(H17,{"Apr","May","Jun","Jul","Aug","Sep","Oct","Nov","Dec","Jan","Feb","Mar"},0)+1,""),"" ) -> 2 | L17: 0 | O17: 9.35 | P17: Jun | Q17: High | R17: Not Started
A18: =+A17+1 -> 14 | B18: =IF(C18<>"","INI-"&TEXT(A18,"000"),"") -> INI-014 | C18: INSURANCE CHARGE CAPTURE — BILL WHAT IS COVERED | D18: Finance | E18: Audit current insurance bills against TPA tariff schedules. Multiple line items (nursing charges, monitoring, clinical charges, physiotherapy, ICU-specific charges) are covered under TPA tariffs but not systematically raised in bills. Fix charge master. Immediate revenue recovery with no new service needed. | F18: Accounts Head | G18: Billing Head | H18: May | I18: May | J18: =IFERROR(IF(AND(H18<>"",I18<>""),MATCH(I18,{"Apr","May","Jun","Jul","Aug","Sep","Oct","Nov","Dec","Jan","Feb","Mar"},0)-MATCH(H18,{"Apr","May","Jun","Jul","Aug","Sep","Oct","Nov","Dec","Jan","Feb","Mar"},0)+1,""),"" ) -> 1 | L18: 0 | R18: Not Started | S18: Detailes pending | T18: TPA agreements list
A19: =+A18+1 -> 15 | B19: =IF(C19<>"","INI-"&TEXT(A19,"000"),"") -> INI-015 | C19: SATELLITE CLINIC NETWORK — SURGEON-LED OFF-CAMPUS OPDs | D19: Business Development | E19: Deploy 6–8 surgeons to run weekly OPD clinics in suburban and district locations (Aluva, Angamaly, Muvattupuzha, Thrippunithura, Kakkanad, Thrissur). Hospital provides space, admin, and branding. Surgeon does one day per week off-campus. Consults convert to admissions at main campus. | F19: Operations Head | G19: COO | H19: May | I19: Oct | J19: =IFERROR(IF(AND(H19<>"",I19<>""),MATCH(I19,{"Apr","May","Jun","Jul","Aug","Sep","Oct","Nov","Dec","Jan","Feb","Mar"},0)-MATCH(H19,{"Apr","May","Jun","Jul","Aug","Sep","Oct","Nov","Dec","Jan","Feb","Mar"},0)+1,""),"" ) -> 6 | O19: 4320 | Q19: High | R19: Not Started | S19: List of surgical doctors prepared, management to speak to these doctors
A20: =+A19+1 -> 16 | B20: =IF(C20<>"","INI-"&TEXT(A20,"000"),"") -> INI-016 | C20: CORPORATE HEALTH PROGRAMME | D20: Business Development | E20: Approach top 50 corporates in Kochi (Infopark, Smartcity, BPCL, Cochin Port, FACT, Kochi Metro, KSEB, major hotel chains) for tiered employee health packages: annual health check + OPD benefit + preferential IP rates. Assign dedicated corporate relationship managers. Volume is captive and predictable. | F20: Finance Head | G20: Business Development Head | H20: May | I20: Aug | J20: =IFERROR(IF(AND(H20<>"",I20<>""),MATCH(I20,{"Apr","May","Jun","Jul","Aug","Sep","Oct","Nov","Dec","Jan","Feb","Mar"},0)-MATCH(H20,{"Apr","May","Jun","Jul","Aug","Sep","Oct","Nov","Dec","Jan","Feb","Mar"},0)+1,""),"" ) -> 4 | O20: 354.52 | P20: Aug | Q20: High | R20: Not Started | S20: List of corporate received, grouping has to be done
A21: =+A20+1 -> 17 | B21: =IF(C21<>"","INI-"&TEXT(A21,"000"),"") -> INI-017 | C21: RESIDENTIAL COLONY AND COMMUNITY HEALTH PROGRAMMES | D21: Business Development | E21: Partner with major gated communities and apartment complexes in Kochi (Sobha, Prestige, Purva in Kakkanad, Edapally, Thrippunithura) for on-site health camps, resident doctor visits, and emergency response agreements. Low acquisition cost. Drives OPD footfall and diagnostics. | F21: Operations Head | G21: Marketing Head | H21: May | I21: Jul | J21: =IFERROR(IF(AND(H21<>"",I21<>""),MATCH(I21,{"Apr","May","Jun","Jul","Aug","Sep","Oct","Nov","Dec","Jan","Feb","Mar"},0)-MATCH(H21,{"Apr","May","Jun","Jul","Aug","Sep","Oct","Nov","Dec","Jan","Feb","Mar"},0)+1,""),"" ) -> 3 | O21: 0 | P21: May | Q21: High | R21: Not Started | S21: General measure already covered in campaign programme
A22: =+A21+1 -> 18 | B22: =IF(C22<>"","INI-"&TEXT(A22,"000"),"") -> INI-018 | C22: INTERNATIONAL MEDICAL VALUE TOURISM — GULF, MALDIVES, BANGLADESH | D22: Business Development | E22: Kochi airport has direct flights to 12+ Middle East cities. Lakeshore is already on the Kerala Medical Value Travel Society registry and has multilingual (Arabic, Hindi, English, Malayalam) staff and international patient services. Formalise MVT as a growth vertical: empanel with aggregators, assign dedicated MVT coordinator, develop Arabic-language digital content. | F22: Strategy Head | G22: Business Development Head | H22: May | I22: Oct | J22: =IFERROR(IF(AND(H22<>"",I22<>""),MATCH(I22,{"Apr","May","Jun","Jul","Aug","Sep","Oct","Nov","Dec","Jan","Feb","Mar"},0)-MATCH(H22,{"Apr","May","Jun","Jul","Aug","Sep","Oct","Nov","Dec","Jan","Feb","Mar"},0)+1,""),"" ) -> 6 | O22: 614.82 | P22: Oct | Q22: High | R22: Not Started
A23: =+A22+1 -> 19 | B23: =IF(C23<>"","INI-"&TEXT(A23,"000"),"") -> INI-019 | C23: STRUCTURED REFERRAL DOCTOR PROGRAMME | D23: Business Development | E23: Map all referring doctors within 50km by specialty and volume. Classify as A/B/C tiers. Assign BD field executives to A-tier (top 100 referrers) with monthly visit cadence. Implement 24-hour discharge summary SOP as a non-negotiable feedback loop for referrers. Track referral volume monthly by doctor. | F23: Finance Head | G23: Business Development Head | H23: May | I23: Aug | J23: =IFERROR(IF(AND(H23<>"",I23<>""),MATCH(I23,{"Apr","May","Jun","Jul","Aug","Sep","Oct","Nov","Dec","Jan","Feb","Mar"},0)-MATCH(H23,{"Apr","May","Jun","Jul","Aug","Sep","Oct","Nov","Dec","Jan","Feb","Mar"},0)+1,""),"" ) -> 4 | Q23: Medium | R23: Not Started | S23: Data collected from website
A24: =+A23+1 -> 20 | B24: =IF(C24<>"","INI-"&TEXT(A24,"000"),"") -> INI-020 | C24: CME AND CLINICAL CONNECT PROGRAMME | D24: Business Development | E24: Run monthly CMEs for referring doctors — specialty-specific, with Lakeshore faculty. Rotate across suburban and district locations (Thrissur, Kottayam, Alappuzha, Ernakulam suburbs). Build a registered community of 500+ referring doctors. CMEs generate clinical credibility and direct referral uplift. | F24: Finance Head | G24: Marketing Head | H24: May | I24: Jun | J24: =IFERROR(IF(AND(H24<>"",I24<>""),MATCH(I24,{"Apr","May","Jun","Jul","Aug","Sep","Oct","Nov","Dec","Jan","Feb","Mar"},0)-MATCH(H24,{"Apr","May","Jun","Jul","Aug","Sep","Oct","Nov","Dec","Jan","Feb","Mar"},0)+1,""),"" ) -> 2 | Q24: Medium | R24: Not Started | S24: CME has to be conducted
A25: =+A24+1 -> 21 | B25: =IF(C25<>"","INI-"&TEXT(A25,"000"),"") -> INI-021 | C25: GOVERNMENT SCHEME EMPANELMENT OPTIMISATION | D25: Finance | E25: Review PMJAY, KASP, CGHS, ECHS, and ESI empanelments. Ensure all eligible procedures — including complex ones like transplant components, cardiac interventions, cancer treatments — are listed. Renegotiate rates for high-volume procedures. At current occupancy levels, scheme patients fill beds that would otherwise be vacant. | F25: Finance Head | G25: Finance Head | H25: May | I25: Jul | J25: =IFERROR(IF(AND(H25<>"",I25<>""),MATCH(I25,{"Apr","May","Jun","Jul","Aug","Sep","Oct","Nov","Dec","Jan","Feb","Mar"},0)-MATCH(H25,{"Apr","May","Jun","Jul","Aug","Sep","Oct","Nov","Dec","Jan","Feb","Mar"},0)+1,""),"" ) -> 3 | O25: 108.39 | P25: Jul | Q25: Medium | R25: Not Started
A26: =+A25+1 -> 22 | B26: =IF(C26<>"","INI-"&TEXT(A26,"000"),"") -> INI-022 | C26: TRANSPLANT CENTRE — VOLUME GROWTH AND DONOR PROGRAMME ACTIVATION | D26: Operations | E26: Multi-organ transplant (liver, kidney, pancreas, combined) is Lakeshore's signature clinical programme. Levers: increase deceased donor programme activity, expand living donor evaluation capacity, grow pre- and post-transplant outpatient care, develop dedicated transplant coordinator network. | F26: Operations Head | G26: COO + CEO | H26: May | I26: Jan | J26: =IFERROR(IF(AND(H26<>"",I26<>""),MATCH(I26,{"Apr","May","Jun","Jul","Aug","Sep","Oct","Nov","Dec","Jan","Feb","Mar"},0)-MATCH(H26,{"Apr","May","Jun","Jul","Aug","Sep","Oct","Nov","Dec","Jan","Feb","Mar"},0)+1,""),"" ) -> 9 | O26: 0 | P26: May | Q26: High | R26: Not Started
A27: =+A26+1 -> 23 | B27: =IF(C27<>"","INI-"&TEXT(A27,"000"),"") -> INI-023 | C27: CARDIAC SCIENCES — STRUCTURAL HEART AND ELECTROPHYSIOLOGY VOLUME BUILD | D27: Marketing | E27: Lakeshore is recognised for comprehensive cardiac care including interventional cardiology, paediatric cardiology, electrophysiology, structural heart disease, CABG, and LVAD implantation. Growth levers: increase EP lab utilisation, develop structural heart disease programme (TAVR, MitraClip), grow paediatric cardiac surgical volume. | F27: Operations Head | G27: COO + CEO | H27: May | I27: Oct | J27: =IFERROR(IF(AND(H27<>"",I27<>""),MATCH(I27,{"Apr","May","Jun","Jul","Aug","Sep","Oct","Nov","Dec","Jan","Feb","Mar"},0)-MATCH(H27,{"Apr","May","Jun","Jul","Aug","Sep","Oct","Nov","Dec","Jan","Feb","Mar"},0)+1,""),"" ) -> 6 | R27: Not Started
A28: =+A27+1 -> 24 | B28: =IF(C28<>"","INI-"&TEXT(A28,"000"),"") -> INI-024 | C28: ONCOLOGY — EARLY DETECTION, SATELLITE CLINICS AND SURGICAL VOLUME GROWTH | D28: Business Development | E28: Build a hub-and-spoke oncology model. Hub: Lakeshore for radiation oncology and complex cancer surgery. Spokes: satellite oncology clinics embedded within partner general hospitals and diagnostic centres across Kerala. Spokes drive early detection (oral, breast, cervical, colorectal screening) and funnel diagnosed cases to Lakeshore for surgery and radiation. Chemotherapy delivery at partner sites where appropriate. | F28: Operations Head | G28: COO + CEO | H28: May | I28: Jan | J28: =IFERROR(IF(AND(H28<>"",I28<>""),MATCH(I28,{"Apr","May","Jun","Jul","Aug","Sep","Oct","Nov","Dec","Jan","Feb","Mar"},0)-MATCH(H28,{"Apr","May","Jun","Jul","Aug","Sep","Oct","Nov","Dec","Jan","Feb","Mar"},0)+1,""),"" ) -> 9 | O28: 2126.88 | P28: Feb | Q28: High | R28: Not Started
A29: =+A28+1 -> 25 | B29: =IF(C29<>"","INI-"&TEXT(A29,"000"),"") -> INI-025 | C29: ORTHOPAEDICS AND JOINT REPLACEMENT — VOLUME AND PACKAGE PROGRAMME | D29: Business Development | E29: Lakeshore has India's first digitally integrated orthopaedic OT with guided airflow. Performed first bilateral total hip replacement using ceramic head with metal liner in Asia. Growth levers: fixed-price joint replacement packages, sports medicine programme, fracture care and trauma protocols, robotic-assisted joint replacement. | F29: Operations Head | G29: COO + CEO | H29: May | I29: Aug | J29: =IFERROR(IF(AND(H29<>"",I29<>""),MATCH(I29,{"Apr","May","Jun","Jul","Aug","Sep","Oct","Nov","Dec","Jan","Feb","Mar"},0)-MATCH(H29,{"Apr","May","Jun","Jul","Aug","Sep","Oct","Nov","Dec","Jan","Feb","Mar"},0)+1,""),"" ) -> 4 | O29: 1284.97 | Q29: High | R29: Not Started
A30: =+A29+1 -> 26 | B30: =IF(C30<>"","INI-"&TEXT(A30,"000"),"") -> INI-026 | C30: LAKESHORE HEART RUN — ANNUAL CARDIAC HEALTH EVENT | D30: Business Development | E30: Organise annual half-marathon or 10K run branded around cardiac health awareness. 3,000–5,000 participants. Entry fee plus sponsorship covers cost. Generates: brand visibility, cardiac health screenings at event (ECG, BP, lipid), OPD follow-ups, cardiologist consultations, and media coverage. | F30: Strategy Head | G30: Business Development Head | H30: Sep | I30: Sep | J30: =IFERROR(IF(AND(H30<>"",I30<>""),MATCH(I30,{"Apr","May","Jun","Jul","Aug","Sep","Oct","Nov","Dec","Jan","Feb","Mar"},0)-MATCH(H30,{"Apr","May","Jun","Jul","Aug","Sep","Oct","Nov","Dec","Jan","Feb","Mar"},0)+1,""),"" ) -> 1 | K30: Opex - One Time | R30: Not Started
A31: =+A30+1 -> 27 | B31: =IF(C31<>"","INI-"&TEXT(A31,"000"),"") -> INI-027 | C31: PREVENTIVE HEALTH + LIVER SCREENING CAMPAIGN | D31: Business Development | E31: Promote preventive healthcare during World Health Day through full body checkups, LFT packages, and fatty liver screening to increase early diagnosis and package conversions.April 19th Liver Day | F31: Marketing Head | G31: Business Development Head | H31: Apr | I31: Apr | J31: =IFERROR(IF(AND(H31<>"",I31<>""),MATCH(I31,{"Apr","May","Jun","Jul","Aug","Sep","Oct","Nov","Dec","Jan","Feb","Mar"},0)-MATCH(H31,{"Apr","May","Jun","Jul","Aug","Sep","Oct","Nov","Dec","Jan","Feb","Mar"},0)+1,""),"" ) -> 1 | K31: Opex - One Time | L31: 1.12 | O31: 34.25 | P31: Apr | Q31: High | R31: Not Started
A32: =+A31+1 -> 28 | B32: =IF(C32<>"","INI-"&TEXT(A32,"000"),"") -> INI-028 | C32: DIGITAL CONTENT PLATFORM — MALAYALAM AND ENGLISH | D32: Business Development | E32: Build a sustained health content library across specialties: YouTube, Facebook, Instagram, hospital website. Procedure explainers, doctor Q&As, patient testimonials, disease awareness. Prioritise Lakeshore's clinical differentiators: transplant journeys, cardiac interventions, robotic surgery, cancer care. Malayalam is significantly underserved on health content platforms. | F32: Strategy Head | G32: Business Development Head | H32: Apr | I32: Jun | J32: =IFERROR(IF(AND(H32<>"",I32<>""),MATCH(I32,{"Apr","May","Jun","Jul","Aug","Sep","Oct","Nov","Dec","Jan","Feb","Mar"},0)-MATCH(H32,{"Apr","May","Jun","Jul","Aug","Sep","Oct","Nov","Dec","Jan","Feb","Mar"},0)+1,""),"" ) -> 3 | K32: Opex - Recurring Monthly | O32: 0 | Q32: High | R32: Not Started
A33: =+A32+1 -> 29 | B33: =IF(C33<>"","INI-"&TEXT(A33,"000"),"") -> INI-029 | C33: COMMUNITY HEALTH CAMPS — SCHOOLS, PLACES OF WORSHIP, RESIDENTIAL AREAS | D33: Business Development | E33: Run monthly health awareness programmes in schools (adolescent health, vision, nutrition), temples and mosques (senior citizen camps during festivals, post-Ramadan diabetes and cardiac screening), and residential complexes. Low cost. High community trust. Converts to OPD footfall. | F33: Strategy Head | G33: Business Development Head | H33: May | I33: Jun | J33: =IFERROR(IF(AND(H33<>"",I33<>""),MATCH(I33,{"Apr","May","Jun","Jul","Aug","Sep","Oct","Nov","Dec","Jan","Feb","Mar"},0)-MATCH(H33,{"Apr","May","Jun","Jul","Aug","Sep","Oct","Nov","Dec","Jan","Feb","Mar"},0)+1,""),"" ) -> 2 | R33: Not Started | T33: get the list
A34: =+A33+1 -> 30 | B34: =IF(C34<>"","INI-"&TEXT(A34,"000"),"") -> INI-030 | C34: DOCTOR ONLINE REPUTATION AND DIGITAL DISCOVERABILITY | D34: Marketing | E34: Ensure all senior consultants have optimised Google Business profiles, Practo and Doctorundi listings, and detailed hospital website profiles with specialisation, publications, clinical firsts, and patient reviews. Over 60% of new OP patients in urban Kerala search online before choosing a doctor. | F34: Strategy Head | G34: Business Development Head | H34: May | I34: May | J34: =IFERROR(IF(AND(H34<>"",I34<>""),MATCH(I34,{"Apr","May","Jun","Jul","Aug","Sep","Oct","Nov","Dec","Jan","Feb","Mar"},0)-MATCH(H34,{"Apr","May","Jun","Jul","Aug","Sep","Oct","Nov","Dec","Jan","Feb","Mar"},0)+1,""),"" ) -> 1 | R34: Not Started | S34: social media capacity building and give a startegy
A35: =+A34+1 -> 31 | B35: =IF(C35<>"","INI-"&TEXT(A35,"000"),"") -> INI-031 | C35: TPA AND INSURER TARIFF RENEGOTIATION | D35: Finance | E35: Formal annual tariff revision with all empanelled TPAs and insurers. Most hospital-insurer agreements have not been revised in 2–3 years while costs have risen 12–15%. Engage each TPA separately. Leverage volume and case complexity data. Target: 8–12% rate improvement. | F35: Finance Head | G35: CFO | H35: May | I35: Jul | J35: =IFERROR(IF(AND(H35<>"",I35<>""),MATCH(I35,{"Apr","May","Jun","Jul","Aug","Sep","Oct","Nov","Dec","Jan","Feb","Mar"},0)-MATCH(H35,{"Apr","May","Jun","Jul","Aug","Sep","Oct","Nov","Dec","Jan","Feb","Mar"},0)+1,""),"" ) -> 3 | R35: Not Started | S35: As informed by the croproate manager, many are at cash rate itself.
A36: =+A35+1 -> 32 | B36: =IF(C36<>"","INI-"&TEXT(A36,"000"),"") -> INI-032 | C36: FINANCIAL COUNSELLING AND PRE-AUTHORISATION AT SURGICAL OPD | D36: Operations | E36: Deploy trained financial counsellors at surgical OPD (orthopaedics, cardiac, neurosurgery, oncology, transplant). Role: explain package costs, initiate insurance pre-auth on day of consultation, arrange EMI/loan tie-ups for self-pay patients. Converts deferred decisions to same-week admissions. | F36: Finance Head | G36: CFO | H36: May | I36: Jun | J36: =IFERROR(IF(AND(H36<>"",I36<>""),MATCH(I36,{"Apr","May","Jun","Jul","Aug","Sep","Oct","Nov","Dec","Jan","Feb","Mar"},0)-MATCH(H36,{"Apr","May","Jun","Jul","Aug","Sep","Oct","Nov","Dec","Jan","Feb","Mar"},0)+1,""),"" ) -> 2 | R36: Not Started | S36: Currently we have financial counsellors who look into all IP | T36: How many additional finance councellors would be required?
A37: =+A36+1 -> 33 | B37: =IF(C37<>"","INI-"&TEXT(A37,"000"),"") -> INI-033 | C37: BUILD A SCALED BD ORGANISATION | D37: Business Development | E37: Expand from the current referral-focused BD team to a 27-person full-spectrum function covering: referral development across 3 zones (North, Central, South Kerala); institutional and partnerships (corporate accounts, MVT, satellite clinics, CME); and communications and branding (Arogyam digital platform, PR). Structured under BD Head (Rosh Mohan) reporting to CEO. | F37: Strategy Head | G37: Business Development Head | H37: Apr | I37: Dec | J37: =IFERROR(IF(AND(H37<>"",I37<>""),MATCH(I37,{"Apr","May","Jun","Jul","Aug","Sep","Oct","Nov","Dec","Jan","Feb","Mar"},0)-MATCH(H37,{"Apr","May","Jun","Jul","Aug","Sep","Oct","Nov","Dec","Jan","Feb","Mar"},0)+1,""),"" ) -> 9 | R37: Not Started
A38: =+A37+1 -> 34 | B38: =IF(C38<>"","INI-"&TEXT(A38,"000"),"") -> INI-034 | C38: MATERIALS / DRUG COST & CONSUMABLES | D38: Supply Chain / Purchase | E38: Replace branded drugs with equivalent generics/lower-cost brands ensuring same clinical outcome; focus on high-value molecules | F38: Medical Director + Pharmacy Head | G38: Pharmacy Head | H38: Apr | I38: Jun | J38: =IFERROR(IF(AND(H38<>"",I38<>""),MATCH(I38,{"Apr","May","Jun","Jul","Aug","Sep","Oct","Nov","Dec","Jan","Feb","Mar"},0)-MATCH(H38,{"Apr","May","Jun","Jul","Aug","Sep","Oct","Nov","Dec","Jan","Feb","Mar"},0)+1,""),"" ) -> 3 | R38: In Progress
A39: =+A38+1 -> 35 | B39: =IF(C39<>"","INI-"&TEXT(A39,"000"),"") -> INI-035 | C39: MATERIALS / DRUG COST & CONSUMABLES | D39: Supply Chain / Purchase | E39: Negotiate higher discounts from manufacturers through volume commitment and MD-level engagement | F39: Purchase Head + MD | G39: Purchase Manager | H39: Apr | I39: May | J39: =IFERROR(IF(AND(H39<>"",I39<>""),MATCH(I39,{"Apr","May","Jun","Jul","Aug","Sep","Oct","Nov","Dec","Jan","Feb","Mar"},0)-MATCH(H39,{"Apr","May","Jun","Jul","Aug","Sep","Oct","Nov","Dec","Jan","Feb","Mar"},0)+1,""),"" ) -> 2 | R39: Not Started
A40: =+A39+1 -> 36 | B40: =IF(C40<>"","INI-"&TEXT(A40,"000"),"") -> INI-036 | C40: MATERIALS / DRUG COST & CONSUMABLES | D40: Supply Chain / Purchase | E40: Reduce distributor base and consolidate procurement to extract volume-linked discounts | F40: Purchase Head | G40: Purchase Manager | H40: Apr | I40: Jun | J40: =IFERROR(IF(AND(H40<>"",I40<>""),MATCH(I40,{"Apr","May","Jun","Jul","Aug","Sep","Oct","Nov","Dec","Jan","Feb","Mar"},0)-MATCH(H40,{"Apr","May","Jun","Jul","Aug","Sep","Oct","Nov","Dec","Jan","Feb","Mar"},0)+1,""),"" ) -> 3 | R40: Not Started
A41: =+A40+1 -> 37 | B41: =IF(C41<>"","INI-"&TEXT(A41,"000"),"") -> INI-037 | C41: MATERIALS / DRUG COST & CONSUMABLES | D41: Supply Chain / Purchase | E41: Implement competitive tendering and rate contracts for high-value consumables replacing spot purchase | F41: Purchase Head + Medical Director | G41: Purchase Manager | H41: May | I41: Aug | J41: =IFERROR(IF(AND(H41<>"",I41<>""),MATCH(I41,{"Apr","May","Jun","Jul","Aug","Sep","Oct","Nov","Dec","Jan","Feb","Mar"},0)-MATCH(H41,{"Apr","May","Jun","Jul","Aug","Sep","Oct","Nov","Dec","Jan","Feb","Mar"},0)+1,""),"" ) -> 4 | R41: Not Started
A42: =+A41+1 -> 38 | B42: =IF(C42<>"","INI-"&TEXT(A42,"000"),"") -> INI-038 | C42: MATERIALS / DRUG COST & CONSUMABLES | D42: Supply Chain / Purchase | E42: Standardise consumable usage across surgeons using procedure-based BOQs and preference cards | F42: Medical Director + OT Head | G42: OT Head | H42: Jun | I42: Sep | J42: =IFERROR(IF(AND(H42<>"",I42<>""),MATCH(I42,{"Apr","May","Jun","Jul","Aug","Sep","Oct","Nov","Dec","Jan","Feb","Mar"},0)-MATCH(H42,{"Apr","May","Jun","Jul","Aug","Sep","Oct","Nov","Dec","Jan","Feb","Mar"},0)+1,""),"" ) -> 4 | R42: Not Started
A43: =+A42+1 -> 39 | B43: =IF(C43<>"","INI-"&TEXT(A43,"000"),"") -> INI-039 | C43: MATERIALS / DRUG COST & CONSUMABLES | D43: Supply Chain / Purchase | E43: Reduce inventory holding days and eliminate expiry-related write-offs through stock optimisation | F43: Pharmacy Head + Purchase | G43: Pharmacy Head | H43: Apr | I43: Jun | J43: =IFERROR(IF(AND(H43<>"",I43<>""),MATCH(I43,{"Apr","May","Jun","Jul","Aug","Sep","Oct","Nov","Dec","Jan","Feb","Mar"},0)-MATCH(H43,{"Apr","May","Jun","Jul","Aug","Sep","Oct","Nov","Dec","Jan","Feb","Mar"},0)+1,""),"" ) -> 3 | R43: Not Started
A44: =+A43+1 -> 40 | B44: =IF(C44<>"","INI-"&TEXT(A44,"000"),"") -> INI-040 | C44: MATERIALS / DRUG COST & CONSUMABLES | D44: HR & Admin | E44: Reduce linen processing cost and loss through outsourcing optimisation and tracking systems | F44: Admin Head | G44: Housekeeping Head | H44: Apr | I44: Jun | J44: =IFERROR(IF(AND(H44<>"",I44<>""),MATCH(I44,{"Apr","May","Jun","Jul","Aug","Sep","Oct","Nov","Dec","Jan","Feb","Mar"},0)-MATCH(H44,{"Apr","May","Jun","Jul","Aug","Sep","Oct","Nov","Dec","Jan","Feb","Mar"},0)+1,""),"" ) -> 3 | R44: Not Started
A45: =+A44+1 -> 41 | B45: =IF(C45<>"","INI-"&TEXT(A45,"000"),"") -> INI-041 | C45: MATERIALS / DRUG COST & CONSUMABLES | D45: Operations | E45: Shift non-critical AMC to third-party vendors and renegotiate OEM contracts for critical equipment | F45: Biomedical Head + Purchase | G45: Biomedical Head | H45: May | I45: Aug | J45: =IFERROR(IF(AND(H45<>"",I45<>""),MATCH(I45,{"Apr","May","Jun","Jul","Aug","Sep","Oct","Nov","Dec","Jan","Feb","Mar"},0)-MATCH(H45,{"Apr","May","Jun","Jul","Aug","Sep","Oct","Nov","Dec","Jan","Feb","Mar"},0)+1,""),"" ) -> 4 | R45: Not Started
A46: =+A45+1 -> 42 | B46: =IF(C46<>"","INI-"&TEXT(A46,"000"),"") -> INI-042 | C46: PAYROLL – NURSING OPTIMISATION | D46: Operations | E46: Align nursing headcount to occupied bed norms through attrition and hiring freeze | F46: COO + Nursing Head | G46: Nursing Head | H46: Apr | I46: Dec | J46: =IFERROR(IF(AND(H46<>"",I46<>""),MATCH(I46,{"Apr","May","Jun","Jul","Aug","Sep","Oct","Nov","Dec","Jan","Feb","Mar"},0)-MATCH(H46,{"Apr","May","Jun","Jul","Aug","Sep","Oct","Nov","Dec","Jan","Feb","Mar"},0)+1,""),"" ) -> 9 | R46: Not Started
A47: =+A46+1 -> 43 | B47: =IF(C47<>"","INI-"&TEXT(A47,"000"),"") -> INI-043 | C47: PAYROLL – PHARMACY OPTIMISATION | D47: Operations | E47: Reduce pharmacy headcount post barcode dispensing and unit-dose system implementation | F47: Pharmacy Head + IT | G47: Pharmacy Head | H47: Apr | I47: Oct | J47: =IFERROR(IF(AND(H47<>"",I47<>""),MATCH(I47,{"Apr","May","Jun","Jul","Aug","Sep","Oct","Nov","Dec","Jan","Feb","Mar"},0)-MATCH(H47,{"Apr","May","Jun","Jul","Aug","Sep","Oct","Nov","Dec","Jan","Feb","Mar"},0)+1,""),"" ) -> 7 | R47: Not Started
A48: =+A47+1 -> 44 | B48: =IF(C48<>"","INI-"&TEXT(A48,"000"),"") -> INI-044 | C48: PAYROLL – ADMIN (PCS) OPTIMISATION | D48: HR & Admin | E48: Eliminate manual documentation roles after full EMR implementation in IP wards | F48: COO + IT Head | G48: IT Head | H48: Apr | I48: Mar | J48: =IFERROR(IF(AND(H48<>"",I48<>""),MATCH(I48,{"Apr","May","Jun","Jul","Aug","Sep","Oct","Nov","Dec","Jan","Feb","Mar"},0)-MATCH(H48,{"Apr","May","Jun","Jul","Aug","Sep","Oct","Nov","Dec","Jan","Feb","Mar"},0)+1,""),"" ) -> 12 | R48: Not Started
... A57: =+A56+1 -> 53 | B57: =IF(C57<>"","INI-"&TEXT(A57,"000"),"") -> INI-053 | C57: PROFESSIONAL FEE RATIONALISATION | D57: Finance / Admin | E57: Eliminate redundant retainers and renegotiate professional and subscription contracts | F57: CFO + COO | G57: CFO | H57: Apr | I57: May | J57: =IFERROR(IF(AND(H57<>"",I57<>""),MATCH(I57,{"Apr","May","Jun","Jul","Aug","Sep","Oct","Nov","Dec","Jan","Feb","Mar"},0)-MATCH(H57,{"Apr","May","Jun","Jul","Aug","Sep","Oct","Nov","Dec","Jan","Feb","Mar"},0)+1,""),"" ) -> 2 | R57: Not Started
A58: =+A57+1 -> 54 | B58: =IF(C58<>"","INI-"&TEXT(A58,"000"),"") | J58: =IFERROR(IF(AND(H58<>"",I58<>""),MATCH(I58,{"Apr","May","Jun","Jul","Aug","Sep","Oct","Nov","Dec","Jan","Feb","Mar"},0)-MATCH(H58,{"Apr","May","Jun","Jul","Aug","Sep","Oct","Nov","Dec","Jan","Feb","Mar"},0)+1,""),"" )
A59: =+A58+1 -> 55 | B59: =IF(C59<>"","INI-"&TEXT(A59,"000"),"") | J59: =IFERROR(IF(AND(H59<>"",I59<>""),MATCH(I59,{"Apr","May","Jun","Jul","Aug","Sep","Oct","Nov","Dec","Jan","Feb","Mar"},0)-MATCH(H59,{"Apr","May","Jun","Jul","Aug","Sep","Oct","Nov","Dec","Jan","Feb","Mar"},0)+1,""),"" )
A60: =+A59+1 -> 56
A61: =+A60+1 -> 57
A62: =+A61+1 -> 58
A63: =+A62+1 -> 59
A64: =+A63+1 -> 60
A65: =+A64+1 -> 61
A66: =+A65+1 -> 62
A67: =+A66+1 -> 63
A68: =+A67+1 -> 64
A69: =+A68+1 -> 65
A70: =+A69+1 -> 66
A71: =+A70+1 -> 67
... A75: =+A74+1 -> 71
A76: =+A75+1 -> 72 | B76: =IF(C76<>"","INI-"&TEXT(A76,"000"),"") | J76: =IFERROR(IF(AND(H76<>"",I76<>""),MATCH(I76,{"Apr","May","Jun","Jul","Aug","Sep","Oct","Nov","Dec","Jan","Feb","Mar"},0)-MATCH(H76,{"Apr","May","Jun","Jul","Aug","Sep","Oct","Nov","Dec","Jan","Feb","Mar"},0)+1,""),"" )
J77: =IFERROR(IF(AND(H77<>"",I77<>""),MATCH(I77,{"Apr","May","Jun","Jul","Aug","Sep","Oct","Nov","Dec","Jan","Feb","Mar"},0)-MATCH(H77,{"Apr","May","Jun","Jul","Aug","Sep","Oct","Nov","Dec","Jan","Feb","Mar"},0)+1,""),"" )
A78: TOTALS | L78: =SUM(L5:L55) -> 1.12 | O78: =SUM(O5:O55) -> 9488.02

Sheet Monthly Plan
A1: MONTHLY EXECUTION PLAN — Activity Grid (1=Active, 0=Inactive)
A2: Enter 1 in months when the initiative is active. Linked from Initiative Register.
A4: # | B4: Initiative ID | C4: Initiative Name | D4: Apr | E4: May | F4: Jun | G4: Jul | H4: Aug | I4: Sep | J4: Oct | K4: Nov | L4: Dec | M4: Jan | N4: Feb | O4: Mar | P4: Active Months
A5: 1 | B5: ='Initiative Register'!B5 -> INI-001 | C5: ='Initiative Register'!C5 -> Campaign- Patient experience improvement | D5: 0 | E5: 0 | F5: 0 | G5: 0 | H5: 0 | I5: 0 | J5: 0 | K5: 0 | L5: 0 | M5: 0 | N5: 0 | O5: 0 | P5: =SUM(D5:O5) -> 0
A6: 2 | B6: ='Initiative Register'!B6 | C6: ='Initiative Register'!C6 -> 0 | D6: 0 | E6: 0 | F6: 0 | G6: 0 | H6: 0 | I6: 0 | J6: 0 | K6: 0 | L6: 0 | M6: 0 | N6: 0 | O6: 0 | P6: =SUM(D6:O6) -> 0
A7: 3 | B7: ='Initiative Register'!B7 -> INI-003 | C7: ='Initiative Register'!C7 -> Geriatric ward | D7: 0 | E7: 0 | F7: 0 | G7: 0 | H7: 0 | I7: 0 | J7: 0 | K7: 0 | L7: 0 | M7: 0 | N7: 0 | O7: 0 | P7: =SUM(D7:O7) -> 0
A8: 4 | B8: ='Initiative Register'!B8 -> INI-004 | C8: ='Initiative Register'!C8 -> Appointment of Specialized Doctors and development of existing department | D8: 0 | E8: 0 | F8: 0 | G8: 0 | H8: 0 | I8: 0 | J8: 0 | K8: 0 | L8: 0 | M8: 0 | N8: 0 | O8: 0 | P8: =SUM(D8:O8) -> 0
A9: 5 | B9: ='Initiative Register'!B9 -> INI-005 | C9: ='Initiative Register'!C9 -> Patient companion | D9: 0 | E9: 0 | F9: 0 | G9: 0 | H9: 0 | I9: 0 | J9: 0 | K9: 0 | L9: 0 | M9: 0 | N9: 0 | O9: 0 | P9: =SUM(D9:O9) -> 0
A10: 6 | B10: ='Initiative Register'!B10 -> INI-006 | C10: ='Initiative Register'!C10 -> Newborn Care Enhancement | D10: 0 | E10: 0 | F10: 0 | G10: 0 | H10: 0 | I10: 0 | J10: 0 | K10: 0 | L10: 0 | M10: 0 | N10: 0 | O10: 0 | P10: =SUM(D10:O10) -> 0
A11: 7 | B11: ='Initiative Register'!B11 -> INI-007 | C11: ='Initiative Register'!C11 -> Digital Patient Acquisition Funnel | D11: 0 | E11: 0 | F11: 0 | G11: 0 | H11: 0 | I11: 0 | J11: 0 | K11: 0 | L11: 0 | M11: 0 | N11: 0 | O11: 0 | P11: =SUM(D11:O11) -> 0
A12: 8 | B12: ='Initiative Register'!B12 -> INI-008 | C12: ='Initiative Register'!C12 -> Development of KPI for Doctors | D12: 0 | E12: 0 | F12: 0 | G12: 0 | H12: 0 | I12: 0 | J12: 0 | K12: 0 | L12: 0 | M12: 0 | N12: 0 | O12: 0 | P12: =SUM(D12:O12) -> 0
A13: 9 | B13: ='Initiative Register'!B13 -> INI-009 | C13: ='Initiative Register'!C13 -> Daycare and Minimaly Invasive Shift | D13: 0 | E13: 0 | F13: 0 | G13: 0 | H13: 0 | I13: 0 | J13: 0 | K13: 0 | L13: 0 | M13: 0 | N13: 0 | O13: 0 | P13: =SUM(D13:O13) -> 0
A14: 10 | B14: ='Initiative Register'!B14 -> INI-010 | C14: ='Initiative Register'!C14 -> Consumables standardization model | D14: 0 | E14: 0 | F14: 0 | G14: 0 | H14: 0 | I14: 0 | J14: 0 | K14: 0 | L14: 0 | M14: 0 | N14: 0 | O14: 0 | P14: =SUM(D14:O14) -> 0
A15: 11 | B15: ='Initiative Register'!B15 -> INI-011 | C15: ='Initiative Register'!C15 -> Collaboration with other Hospitals | D15: 0 | E15: 0 | F15: 0 | G15: 0 | H15: 0 | I15: 0 | J15: 0 | K15: 0 | L15: 0 | M15: 0 | N15: 0 | O15: 0 | P15: =SUM(D15:O15) -> 0
A16: 12 | B16: ='Initiative Register'!B16 -> INI-012 | C16: ='Initiative Register'!C16 -> ANNUAL RATE REVISION POLICY | D16: 0 | E16: 0 | F16: 0 | G16: 0 | H16: 0 | I16: 0 | J16: 0 | K16: 0 | L16: 0 | M16: 0 | N16: 0 | O16: 0 | P16: =SUM(D16:O16) -> 0
... A30: 26 | B30: ='Initiative Register'!B30 -> INI-026 | C30: ='Initiative Register'!C30 -> LAKESHORE HEART RUN — ANNUAL CARDIAC HEALTH EVENT | D30: 0 | E30: 0 | F30: 0 | G30: 0 | H30: 0 | I30: 0 | J30: 0 | K30: 0 | L30: 0 | M30: 0 | N30: 0 | O30: 0 | P30: =SUM(D30:O30) -> 0
A31: 27 | B31: ='Initiative Register'!B32 -> INI-028 | C31: ='Initiative Register'!C32 -> DIGITAL CONTENT PLATFORM — MALAYALAM AND ENGLISH | D31: 0 | E31: 0 | F31: 0 | G31: 0 | H31: 0 | I31: 0 | J31: 0 | K31: 0 | L31: 0 | M31: 0 | N31: 0 | O31: 0 | P31: =SUM(D31:O31) -> 0
A32: 28 | B32: ='Initiative Register'!B33 -> INI-029 | C32: ='Initiative Register'!C33 -> COMMUNITY HEALTH CAMPS — SCHOOLS, PLACES OF WORSHIP, RESIDENTIAL AREAS | D32: 0 | E32: 0 | F32: 0 | G32: 0 | H32: 0 | I32: 0 | J32: 0 | K32: 0 | L32: 0 | M32: 0 | N32: 0 | O32: 0 | P32: =SUM(D32:O32) -> 0
A33: 29 | B33: ='Initiative Register'!B34 -> INI-030 | C33: ='Initiative Register'!C34 -> DOCTOR ONLINE REPUTATION AND DIGITAL DISCOVERABILITY | D33: 0 | E33: 0 | F33: 0 | G33: 0 | H33: 0 | I33: 0 | J33: 0 | K33: 0 | L33: 0 | M33: 0 | N33: 0 | O33: 0 | P33: =SUM(D33:O33) -> 0
A34: 30 | B34: ='Initiative Register'!B35 -> INI-031 | C34: ='Initiative Register'!C35 -> TPA AND INSURER TARIFF RENEGOTIATION | D34: 0 | E34: 0 | F34: 0 | G34: 0 | H34: 0 | I34: 0 | J34: 0 | K34: 0 | L34: 0 | M34: 0 | N34: 0 | O34: 0 | P34: =SUM(D34:O34) -> 0
A35: 31 | B35: ='Initiative Register'!B36 -> INI-032 | C35: ='Initiative Register'!C36 -> FINANCIAL COUNSELLING AND PRE-AUTHORISATION AT SURGICAL OPD | D35: 0 | E35: 0 | F35: 0 | G35: 0 | H35: 0 | I35: 0 | J35: 0 | K35: 0 | L35: 0 | M35: 0 | N35: 0 | O35: 0 | P35: =SUM(D35:O35) -> 0
A36: 32 | B36: ='Initiative Register'!B37 -> INI-033 | C36: ='Initiative Register'!C37 -> BUILD A SCALED BD ORGANISATION | D36: 0 | E36: 0 | F36: 0 | G36: 0 | H36: 0 | I36: 0 | J36: 0 | K36: 0 | L36: 0 | M36: 0 | N36: 0 | O36: 0 | P36: =SUM(D36:O36) -> 0
A37: 33 | B37: ='Initiative Register'!B38 -> INI-034 | C37: ='Initiative Register'!C38 -> MATERIALS / DRUG COST & CONSUMABLES | D37: 0 | E37: 0 | F37: 0 | G37: 0 | H37: 0 | I37: 0 | J37: 0 | K37: 0 | L37: 0 | M37: 0 | N37: 0 | O37: 0 | P37: =SUM(D37:O37) -> 0
A38: 34 | B38: ='Initiative Register'!B39 -> INI-035 | C38: ='Initiative Register'!C39 -> MATERIALS / DRUG COST & CONSUMABLES | D38: 0 | E38: 0 | F38: 0 | G38: 0 | H38: 0 | I38: 0 | J38: 0 | K38: 0 | L38: 0 | M38: 0 | N38: 0 | O38: 0 | P38: =SUM(D38:O38) -> 0
A39: 35 | B39: ='Initiative Register'!B40 -> INI-036 | C39: ='Initiative Register'!C40 -> MATERIALS / DRUG COST & CONSUMABLES | D39: 0 | E39: 0 | F39: 0 | G39: 0 | H39: 0 | I39: 0 | J39: 0 | K39: 0 | L39: 0 | M39: 0 | N39: 0 | O39: 0 | P39: =SUM(D39:O39) -> 0
A40: 36 | B40: ='Initiative Register'!B41 -> INI-037 | C40: ='Initiative Register'!C41 -> MATERIALS / DRUG COST & CONSUMABLES | D40: 0 | E40: 0 | F40: 0 | G40: 0 | H40: 0 | I40: 0 | J40: 0 | K40: 0 | L40: 0 | M40: 0 | N40: 0 | O40: 0 | P40: =SUM(D40:O40) -> 0
A41: 37 | B41: ='Initiative Register'!B42 -> INI-038 | C41: ='Initiative Register'!C42 -> MATERIALS / DRUG COST & CONSUMABLES | D41: 0 | E41: 0 | F41: 0 | G41: 0 | H41: 0 | I41: 0 | J41: 0 | K41: 0 | L41: 0 | M41: 0 | N41: 0 | O41: 0 | P41: =SUM(D41:O41) -> 0
A42: 38 | B42: ='Initiative Register'!B43 -> INI-039 | C42: ='Initiative Register'!C43 -> MATERIALS / DRUG COST & CONSUMABLES | D42: 0 | E42: 0 | F42: 0 | G42: 0 | H42: 0 | I42: 0 | J42: 0 | K42: 0 | L42: 0 | M42: 0 | N42: 0 | O42: 0 | P42: =SUM(D42:O42) -> 0
... A54: 50 | B54: ='Initiative Register'!B55 -> INI-051 | C54: ='Initiative Register'!C55 -> OVERHEAD – REVENUE LEAKAGE RECOVERY | D54: 0 | E54: 0 | F54: 0 | G54: 0 | H54: 0 | I54: 0 | J54: 0 | K54: 0 | L54: 0 | M54: 0 | N54: 0 | O54: 0 | P54: =SUM(D54:O54) -> 0

Sheet Cost Plan
A1: COST PLAN — FY 2026-27 | Monthly Budgeted Cost per Initiative (Rs Lakhs)
A4: # | B4: Initiative ID | C4: Initiative Name | D4: Apr | E4: May | F4: Jun | G4: Jul | H4: Aug | I4: Sep | J4: Oct | K4: Nov | L4: Dec | M4: Jan | N4: Feb | O4: Mar | P4: Annual Total
A5: 1 | B5: ='Initiative Register'!B5 -> INI-001 | C5: ='Initiative Register'!C5 -> Campaign- Patient experience improvement | D5: 0 | E5: 0 | F5: 0 | G5: 0 | H5: 0 | I5: 0 | J5: 0 | K5: 0 | L5: 0 | M5: 0 | N5: 0 | O5: 0 | P5: =SUM(D5:O5) -> 0
A6: 2 | B6: ='Initiative Register'!B6 | C6: ='Initiative Register'!C6 -> 0 | D6: 0 | E6: 0 | F6: 0 | G6: 0 | H6: 0 | I6: 0 | J6: 0 | K6: 0 | L6: 0 | M6: 0 | N6: 0 | O6: 0 | P6: =SUM(D6:O6) -> 0
A7: 3 | B7: ='Initiative Register'!B7 -> INI-003 | C7: ='Initiative Register'!C7 -> Geriatric ward | D7: 0 | E7: 0 | F7: 0 | G7: 0 | H7: 0 | I7: 0 | J7: 0 | K7: 0 | L7: 0 | M7: 0 | N7: 0 | O7: 0 | P7: =SUM(D7:O7) -> 0
A8: 4 | B8: ='Initiative Register'!B8 -> INI-004 | C8: ='Initiative Register'!C8 -> Appointment of Specialized Doctors and development of existing department | D8: 0 | E8: 0 | F8: 0 | G8: 0 | H8: 0 | I8: 0 | J8: 0 | K8: 0 | L8: 0 | M8: 0 | N8: 0 | O8: 0 | P8: =SUM(D8:O8) -> 0
A9: 5 | B9: ='Initiative Register'!B9 -> INI-005 | C9: ='Initiative Register'!C9 -> Patient companion | D9: 0 | E9: 0 | F9: 0 | G9: 0 | H9: 0 | I9: 0 | J9: 0 | K9: 0 | L9: 0 | M9: 0 | N9: 0 | O9: 0 | P9: =SUM(D9:O9) -> 0
A10: 6 | B10: ='Initiative Register'!B10 -> INI-006 | C10: ='Initiative Register'!C10 -> Newborn Care Enhancement | D10: 0 | E10: 0 | F10: 0 | G10: 0 | H10: 0 | I10: 0 | J10: 0 | K10: 0 | L10: 0 | M10: 0 | N10: 0 | O10: 0 | P10: =SUM(D10:O10) -> 0
A11: 7 | B11: ='Initiative Register'!B11 -> INI-007 | C11: ='Initiative Register'!C11 -> Digital Patient Acquisition Funnel | D11: 0 | E11: 0 | F11: 0 | G11: 0 | H11: 0 | I11: 0 | J11: 0 | K11: 0 | L11: 0 | M11: 0 | N11: 0 | O11: 0 | P11: =SUM(D11:O11) -> 0
A12: 8 | B12: ='Initiative Register'!B12 -> INI-008 | C12: ='Initiative Register'!C12 -> Development of KPI for Doctors | D12: 0 | E12: 0 | F12: 0 | G12: 0 | H12: 0 | I12: 0 | J12: 0 | K12: 0 | L12: 0 | M12: 0 | N12: 0 | O12: 0 | P12: =SUM(D12:O12) -> 0
A13: 9 | B13: ='Initiative Register'!B13 -> INI-009 | C13: ='Initiative Register'!C13 -> Daycare and Minimaly Invasive Shift | D13: 0 | E13: 0 | F13: 0 | G13: 0 | H13: 0 | I13: 0 | J13: 0 | K13: 0 | L13: 0 | M13: 0 | N13: 0 | O13: 0 | P13: =SUM(D13:O13) -> 0
A14: 10 | B14: ='Initiative Register'!B14 -> INI-010 | C14: ='Initiative Register'!C14 -> Consumables standardization model | D14: 0 | E14: 0 | F14: 0 | G14: 0 | H14: 0 | I14: 0 | J14: 0 | K14: 0 | L14: 0 | M14: 0 | N14: 0 | O14: 0 | P14: =SUM(D14:O14) -> 0
A15: 11 | B15: ='Initiative Register'!B15 -> INI-011 | C15: ='Initiative Register'!C15 -> Collaboration with other Hospitals | D15: 0 | E15: 0 | F15: 0 | G15: 0 | H15: 0 | I15: 0 | J15: 0 | K15: 0 | L15: 0 | M15: 0 | N15: 0 | O15: 0 | P15: =SUM(D15:O15) -> 0
A16: 12 | B16: ='Initiative Register'!B16 -> INI-012 | C16: ='Initiative Register'!C16 -> ANNUAL RATE REVISION POLICY | D16: 0 | E16: 0 | F16: 0 | G16: 0 | H16: 0 | I16: 0 | J16: 0 | K16: 0 | L16: 0 | M16: 0 | N16: 0 | O16: 0 | P16: =SUM(D16:O16) -> 0
... A30: 26 | B30: ='Initiative Register'!B30 -> INI-026 | C30: ='Initiative Register'!C30 -> LAKESHORE HEART RUN — ANNUAL CARDIAC HEALTH EVENT | D30: 0 | E30: 0 | F30: 0 | G30: 0 | H30: 0 | I30: 0 | J30: 0 | K30: 0 | L30: 0 | M30: 0 | N30: 0 | O30: 0 | P30: =SUM(D30:O30) -> 0
A31: 27 | B31: ='Initiative Register'!B32 -> INI-028 | C31: ='Initiative Register'!C32 -> DIGITAL CONTENT PLATFORM — MALAYALAM AND ENGLISH | D31: 0 | E31: 0 | F31: 0 | G31: 0 | H31: 0 | I31: 0 | J31: 0 | K31: 0 | L31: 0 | M31: 0 | N31: 0 | O31: 0 | P31: =SUM(D31:O31) -> 0
A32: 28 | B32: ='Initiative Register'!B33 -> INI-029 | C32: ='Initiative Register'!C33 -> COMMUNITY HEALTH CAMPS — SCHOOLS, PLACES OF WORSHIP, RESIDENTIAL AREAS | D32: 0 | E32: 0 | F32: 0 | G32: 0 | H32: 0 | I32: 0 | J32: 0 | K32: 0 | L32: 0 | M32: 0 | N32: 0 | O32: 0 | P32: =SUM(D32:O32) -> 0
A33: 29 | B33: ='Initiative Register'!B34 -> INI-030 | C33: ='Initiative Register'!C34 -> DOCTOR ONLINE REPUTATION AND DIGITAL DISCOVERABILITY | D33: 0 | E33: 0 | F33: 0 | G33: 0 | H33: 0 | I33: 0 | J33: 0 | K33: 0 | L33: 0 | M33: 0 | N33: 0 | O33: 0 | P33: =SUM(D33:O33) -> 0
A34: 30 | B34: ='Initiative Register'!B35 -> INI-031 | C34: ='Initiative Register'!C35 -> TPA AND INSURER TARIFF RENEGOTIATION | D34: 0 | E34: 0 | F34: 0 | G34: 0 | H34: 0 | I34: 0 | J34: 0 | K34: 0 | L34: 0 | M34: 0 | N34: 0 | O34: 0 | P34: =SUM(D34:O34) -> 0
A35: 31 | B35: ='Initiative Register'!B36 -> INI-032 | C35: ='Initiative Register'!C36 -> FINANCIAL COUNSELLING AND PRE-AUTHORISATION AT SURGICAL OPD | D35: 0 | E35: 0 | F35: 0 | G35: 0 | H35: 0 | I35: 0 | J35: 0 | K35: 0 | L35: 0 | M35: 0 | N35: 0 | O35: 0 | P35: =SUM(D35:O35) -> 0
A36: 32 | B36: ='Initiative Register'!B37 -> INI-033 | C36: ='Initiative Register'!C37 -> BUILD A SCALED BD ORGANISATION | D36: 0 | E36: 0 | F36: 0 | G36: 0 | H36: 0 | I36: 0 | J36: 0 | K36: 0 | L36: 0 | M36: 0 | N36: 0 | O36: 0 | P36: =SUM(D36:O36) -> 0
A37: 33 | B37: ='Initiative Register'!B38 -> INI-034 | C37: ='Initiative Register'!C38 -> MATERIALS / DRUG COST & CONSUMABLES | D37: 0 | E37: 0 | F37: 0 | G37: 0 | H37: 0 | I37: 0 | J37: 0 | K37: 0 | L37: 0 | M37: 0 | N37: 0 | O37: 0 | P37: =SUM(D37:O37) -> 0
A38: 34 | B38: ='Initiative Register'!B39 -> INI-035 | C38: ='Initiative Register'!C39 -> MATERIALS / DRUG COST & CONSUMABLES | D38: 0 | E38: 0 | F38: 0 | G38: 0 | H38: 0 | I38: 0 | J38: 0 | K38: 0 | L38: 0 | M38: 0 | N38: 0 | O38: 0 | P38: =SUM(D38:O38) -> 0
A39: 35 | B39: ='Initiative Register'!B40 -> INI-036 | C39: ='Initiative Register'!C40 -> MATERIALS / DRUG COST & CONSUMABLES | D39: 0 | E39: 0 | F39: 0 | G39: 0 | H39: 0 | I39: 0 | J39: 0 | K39: 0 | L39: 0 | M39: 0 | N39: 0 | O39: 0 | P39: =SUM(D39:O39) -> 0
A40: 36 | B40: ='Initiative Register'!B41 -> INI-037 | C40: ='Initiative Register'!C41 -> MATERIALS / DRUG COST & CONSUMABLES | D40: 0 | E40: 0 | F40: 0 | G40: 0 | H40: 0 | I40: 0 | J40: 0 | K40: 0 | L40: 0 | M40: 0 | N40: 0 | O40: 0 | P40: =SUM(D40:O40) -> 0
A41: 37 | B41: ='Initiative Register'!B42 -> INI-038 | C41: ='Initiative Register'!C42 -> MATERIALS / DRUG COST & CONSUMABLES | D41: 0 | E41: 0 | F41: 0 | G41: 0 | H41: 0 | I41: 0 | J41: 0 | K41: 0 | L41: 0 | M41: 0 | N41: 0 | O41: 0 | P41: =SUM(D41:O41) -> 0
A42: 38 | B42: ='Initiative Register'!B43 -> INI-039 | C42: ='Initiative Register'!C43 -> MATERIALS / DRUG COST & CONSUMABLES | D42: 0 | E42: 0 | F42: 0 | G42: 0 | H42: 0 | I42: 0 | J42: 0 | K42: 0 | L42: 0 | M42: 0 | N42: 0 | O42: 0 | P42: =SUM(D42:O42) -> 0
... A54: 50 | B54: ='Initiative Register'!B55 -> INI-051 | C54: ='Initiative Register'!C55 -> OVERHEAD – REVENUE LEAKAGE RECOVERY | D54: 0 | E54: 0 | F54: 0 | G54: 0 | H54: 0 | I54: 0 | J54: 0 | K54: 0 | L54: 0 | M54: 0 | N54: 0 | O54: 0 | P54: =SUM(D54:O54) -> 0
A55: TOTAL | D55: =SUM(D5:D54) -> 0 | E55: =SUM(E5:E54) -> 0 | F55: =SUM(F5:F54) -> 0 | G55: =SUM(G5:G54) -> 0 | H55: =SUM(H5:H54) -> 0 | I55: =SUM(I5:I54) -> 0 | J55: =SUM(J5:J54) -> 0 | K55: =SUM(K5:K54) -> 0 | ... P55: =SUM(P5:P54) -> 0

Sheet Revenue Impact
A1: REVENUE IMPACT PLAN — FY 2026-27 | Expected Revenue Uplift per Initiative (Rs Lakhs)
A4: # | B4: Initiative ID | C4: Initiative Name | D4: Apr | E4: May | F4: Jun | G4: Jul | H4: Aug | I4: Sep | J4: Oct | K4: Nov | L4: Dec | M4: Jan | N4: Feb | O4: Mar | P4: Annual Total
A5: 1 | B5: ='Initiative Register'!B5 -> INI-001 | C5: ='Initiative Register'!C5 -> Campaign- Patient experience improvement | D5: 0 | E5: 0 | F5: 0 | G5: 0 | H5: 0 | I5: 0 | J5: 0 | K5: 0 | L5: 0 | M5: 0 | N5: 0 | O5: 0 | P5: =SUM(D5:O5) -> 0
A6: 2 | B6: ='Initiative Register'!B6 | C6: ='Initiative Register'!C6 -> 0 | D6: 0 | E6: 0 | F6: 0 | G6: 0 | H6: 0 | I6: 0 | J6: 0 | K6: 0 | L6: 0 | M6: 0 | N6: 0 | O6: 0 | P6: =SUM(D6:O6) -> 0
A7: 3 | B7: ='Initiative Register'!B7 -> INI-003 | C7: ='Initiative Register'!C7 -> Geriatric ward | D7: 0 | E7: 0 | F7: 0 | G7: 0 | H7: 0 | I7: 0 | J7: 0 | K7: 0 | L7: 0 | M7: 0 | N7: 0 | O7: 0 | P7: =SUM(D7:O7) -> 0
A8: 4 | B8: ='Initiative Register'!B8 -> INI-004 | C8: ='Initiative Register'!C8 -> Appointment of Specialized Doctors and development of existing department | D8: 0 | E8: 0 | F8: 0 | G8: 0 | H8: 0 | I8: 0 | J8: 0 | K8: 0 | L8: 0 | M8: 0 | N8: 0 | O8: 0 | P8: =SUM(D8:O8) -> 0
A9: 5 | B9: ='Initiative Register'!B9 -> INI-005 | C9: ='Initiative Register'!C9 -> Patient companion | D9: 0 | E9: 0 | F9: 0 | G9: 0 | H9: 0 | I9: 0 | J9: 0 | K9: 0 | L9: 0 | M9: 0 | N9: 0 | O9: 0 | P9: =SUM(D9:O9) -> 0
A10: 6 | B10: ='Initiative Register'!B10 -> INI-006 | C10: ='Initiative Register'!C10 -> Newborn Care Enhancement | D10: 0 | E10: 0 | F10: 0 | G10: 0 | H10: 0 | I10: 0 | J10: 0 | K10: 0 | L10: 0 | M10: 0 | N10: 0 | O10: 0 | P10: =SUM(D10:O10) -> 0
A11: 7 | B11: ='Initiative Register'!B11 -> INI-007 | C11: ='Initiative Register'!C11 -> Digital Patient Acquisition Funnel | D11: 0 | E11: 0 | F11: 0 | G11: 0 | H11: 0 | I11: 0 | J11: 0 | K11: 0 | L11: 0 | M11: 0 | N11: 0 | O11: 0 | P11: =SUM(D11:O11) -> 0
A12: 8 | B12: ='Initiative Register'!B12 -> INI-008 | C12: ='Initiative Register'!C12 -> Development of KPI for Doctors | D12: 0 | E12: 0 | F12: 0 | G12: 0 | H12: 0 | I12: 0 | J12: 0 | K12: 0 | L12: 0 | M12: 0 | N12: 0 | O12: 0 | P12: =SUM(D12:O12) -> 0
A13: 9 | B13: ='Initiative Register'!B13 -> INI-009 | C13: ='Initiative Register'!C13 -> Daycare and Minimaly Invasive Shift | D13: 0 | E13: 0 | F13: 0 | G13: 0 | H13: 0 | I13: 0 | J13: 0 | K13: 0 | L13: 0 | M13: 0 | N13: 0 | O13: 0 | P13: =SUM(D13:O13) -> 0
A14: 10 | B14: ='Initiative Register'!B14 -> INI-010 | C14: ='Initiative Register'!C14 -> Consumables standardization model | D14: 0 | E14: 0 | F14: 0 | G14: 0 | H14: 0 | I14: 0 | J14: 0 | K14: 0 | L14: 0 | M14: 0 | N14: 0 | O14: 0 | P14: =SUM(D14:O14) -> 0
A15: 11 | B15: ='Initiative Register'!B15 -> INI-011 | C15: ='Initiative Register'!C15 -> Collaboration with other Hospitals | D15: 0 | E15: 0 | F15: 0 | G15: 0 | H15: 0 | I15: 0 | J15: 0 | K15: 0 | L15: 0 | M15: 0 | N15: 0 | O15: 0 | P15: =SUM(D15:O15) -> 0
A16: 12 | B16: ='Initiative Register'!B16 -> INI-012 | C16: ='Initiative Register'!C16 -> ANNUAL RATE REVISION POLICY | D16: 0 | E16: 0 | F16: 0 | G16: 0 | H16: 0 | I16: 0 | J16: 0 | K16: 0 | L16: 0 | M16: 0 | N16: 0 | O16: 0 | P16: =SUM(D16:O16) -> 0
... A70: 66 | B70: ='Initiative Register'!B70 -> 0 | C70: ='Initiative Register'!C70 -> 0 | D70: 0 | E70: 0 | F70: 0 | G70: 0 | H70: 0 | I70: 0 | J70: 0 | K70: 0 | L70: 0 | M70: 0 | N70: 0 | O70: 0 | P70: =SUM(D70:O70) -> 0
A71: TOTAL | D71: =SUM(D5:D55) -> 0 | E71: =SUM(E5:E55) -> 0 | F71: =SUM(F5:F55) -> 0 | G71: =SUM(G5:G55) -> 0 | H71: =SUM(H5:H55) -> 0 | I71: =SUM(I5:I55) -> 0 | J71: =SUM(J5:J55) -> 0 | K71: =SUM(K5:K55) -> 0 | ... P71: =SUM(P5:P55) -> 0

Sheet Monthly Actuals
A1: MONTHLY ACTUALS — FY 2026-27 | Enter after each month close (Rs Lakhs)
A2: Section A = Actual Revenue Realised | Section B = Actual Cost Incurred
A3: SECTION A — ACTUAL REVENUE REALISED
A4: # | B4: Initiative ID | C4: Initiative Name | D4: Apr | E4: May | F4: Jun | G4: Jul | H4: Aug | I4: Sep | J4: Oct | K4: Nov | L4: Dec | M4: Jan | N4: Feb | O4: Mar | P4: YTD Total
A5: 1 | B5: ='Initiative Register'!B5 -> INI-001 | C5: ='Initiative Register'!C5 -> Campaign- Patient experience improvement | D5: 0 | E5: 0 | F5: 0 | G5: 0 | H5: 0 | I5: 0 | J5: 0 | K5: 0 | L5: 0 | M5: 0 | N5: 0 | O5: 0 | P5: =SUM(D5:O5) -> 0
A6: 2 | B6: ='Initiative Register'!B6 | C6: ='Initiative Register'!C6 -> 0 | D6: 0 | E6: 0 | F6: 0 | G6: 0 | H6: 0 | I6: 0 | J6: 0 | K6: 0 | L6: 0 | M6: 0 | N6: 0 | O6: 0 | P6: =SUM(D6:O6) -> 0
A7: 3 | B7: ='Initiative Register'!B7 -> INI-003 | C7: ='Initiative Register'!C7 -> Geriatric ward | D7: 0 | E7: 0 | F7: 0 | G7: 0 | H7: 0 | I7: 0 | J7: 0 | K7: 0 | L7: 0 | M7: 0 | N7: 0 | O7: 0 | P7: =SUM(D7:O7) -> 0
A8: 4 | B8: ='Initiative Register'!B8 -> INI-004 | C8: ='Initiative Register'!C8 -> Appointment of Specialized Doctors and development of existing department | D8: 0 | E8: 0 | F8: 0 | G8: 0 | H8: 0 | I8: 0 | J8: 0 | K8: 0 | L8: 0 | M8: 0 | N8: 0 | O8: 0 | P8: =SUM(D8:O8) -> 0
A9: 5 | B9: ='Initiative Register'!B9 -> INI-005 | C9: ='Initiative Register'!C9 -> Patient companion | D9: 0 | E9: 0 | F9: 0 | G9: 0 | H9: 0 | I9: 0 | J9: 0 | K9: 0 | L9: 0 | M9: 0 | N9: 0 | O9: 0 | P9: =SUM(D9:O9) -> 0
A10: 6 | B10: ='Initiative Register'!B10 -> INI-006 | C10: ='Initiative Register'!C10 -> Newborn Care Enhancement | D10: 0 | E10: 0 | F10: 0 | G10: 0 | H10: 0 | I10: 0 | J10: 0 | K10: 0 | L10: 0 | M10: 0 | N10: 0 | O10: 0 | P10: =SUM(D10:O10) -> 0
A11: 7 | B11: ='Initiative Register'!B11 -> INI-007 | C11: ='Initiative Register'!C11 -> Digital Patient Acquisition Funnel | D11: 0 | E11: 0 | F11: 0 | G11: 0 | H11: 0 | I11: 0 | J11: 0 | K11: 0 | L11: 0 | M11: 0 | N11: 0 | O11: 0 | P11: =SUM(D11:O11) -> 0
A12: 8 | B12: ='Initiative Register'!B12 -> INI-008 | C12: ='Initiative Register'!C12 -> Development of KPI for Doctors | D12: 0 | E12: 0 | F12: 0 | G12: 0 | H12: 0 | I12: 0 | J12: 0 | K12: 0 | L12: 0 | M12: 0 | N12: 0 | O12: 0 | P12: =SUM(D12:O12) -> 0
A13: 9 | B13: ='Initiative Register'!B13 -> INI-009 | C13: ='Initiative Register'!C13 -> Daycare and Minimaly Invasive Shift | D13: 0 | E13: 0 | F13: 0 | G13: 0 | H13: 0 | I13: 0 | J13: 0 | K13: 0 | L13: 0 | M13: 0 | N13: 0 | O13: 0 | P13: =SUM(D13:O13) -> 0
A14: 10 | B14: ='Initiative Register'!B14 -> INI-010 | C14: ='Initiative Register'!C14 -> Consumables standardization model | D14: 0 | E14: 0 | F14: 0 | G14: 0 | H14: 0 | I14: 0 | J14: 0 | K14: 0 | L14: 0 | M14: 0 | N14: 0 | O14: 0 | P14: =SUM(D14:O14) -> 0
A15: 11 | B15: ='Initiative Register'!B15 -> INI-011 | C15: ='Initiative Register'!C15 -> Collaboration with other Hospitals | D15: 0 | E15: 0 | F15: 0 | G15: 0 | H15: 0 | I15: 0 | J15: 0 | K15: 0 | L15: 0 | M15: 0 | N15: 0 | O15: 0 | P15: =SUM(D15:O15) -> 0
A16: 12 | B16: ='Initiative Register'!B16 -> INI-012 | C16: ='Initiative Register'!C16 -> ANNUAL RATE REVISION POLICY | D16: 0 | E16: 0 | F16: 0 | G16: 0 | H16: 0 | I16: 0 | J16: 0 | K16: 0 | L16: 0 | M16: 0 | N16: 0 | O16: 0 | P16: =SUM(D16:O16) -> 0
... A72: 68 | B72: ='Initiative Register'!B72 -> 0 | C72: ='Initiative Register'!C72 -> 0 | D72: 0 | E72: 0 | F72: 0 | G72: 0 | H72: 0 | I72: 0 | J72: 0 | K72: 0 | L72: 0 | M72: 0 | N72: 0 | O72: 0 | P72: =SUM(D72:O72) -> 0
A73: TOTAL | D73: =SUM(D5:D54) -> 0 | E73: =SUM(E5:E54) -> 0 | F73: =SUM(F5:F54) -> 0 | G73: =SUM(G5:G54) -> 0 | H73: =SUM(H5:H54) -> 0 | I73: =SUM(I5:I54) -> 0 | J73: =SUM(J5:J54) -> 0 | K73: =SUM(K5:K54) -> 0 | ... P73: =SUM(P5:P54) -> 0
A75: SECTION B — ACTUAL COST INCURRED
A76: # | B76: Initiative ID | C76: Initiative Name | D76: Apr | E76: May | F76: Jun | G76: Jul | H76: Aug | I76: Sep | J76: Oct | K76: Nov | L76: Dec | M76: Jan | N76: Feb | O76: Mar | P76: YTD Total
A77: 1 | B77: ='Initiative Register'!B5 -> INI-001 | C77: ='Initiative Register'!C5 -> Campaign- Patient experience improvement | D77: 0 | E77: 0 | F77: 0 | G77: 0 | H77: 0 | I77: 0 | J77: 0 | K77: 0 | L77: 0 | M77: 0 | N77: 0 | O77: 0 | P77: =SUM(D77:O77) -> 0
A78: 2 | B78: ='Initiative Register'!B6 | C78: ='Initiative Register'!C6 -> 0 | D78: 0 | E78: 0 | F78: 0 | G78: 0 | H78: 0 | I78: 0 | J78: 0 | K78: 0 | L78: 0 | M78: 0 | N78: 0 | O78: 0 | P78: =SUM(D78:O78) -> 0
A79: 3 | B79: ='Initiative Register'!B7 -> INI-003 | C79: ='Initiative Register'!C7 -> Geriatric ward | D79: 0 | E79: 0 | F79: 0 | G79: 0 | H79: 0 | I79: 0 | J79: 0 | K79: 0 | L79: 0 | M79: 0 | N79: 0 | O79: 0 | P79: =SUM(D79:O79) -> 0
A80: 4 | B80: ='Initiative Register'!B8 -> INI-004 | C80: ='Initiative Register'!C8 -> Appointment of Specialized Doctors and development of existing department | D80: 0 | E80: 0 | F80: 0 | G80: 0 | H80: 0 | I80: 0 | J80: 0 | K80: 0 | L80: 0 | M80: 0 | N80: 0 | O80: 0 | P80: =SUM(D80:O80) -> 0
A81: 5 | B81: ='Initiative Register'!B9 -> INI-005 | C81: ='Initiative Register'!C9 -> Patient companion | D81: 0 | E81: 0 | F81: 0 | G81: 0 | H81: 0 | I81: 0 | J81: 0 | K81: 0 | L81: 0 | M81: 0 | N81: 0 | O81: 0 | P81: =SUM(D81:O81) -> 0
A82: 6 | B82: ='Initiative Register'!B10 -> INI-006 | C82: ='Initiative Register'!C10 -> Newborn Care Enhancement | D82: 0 | E82: 0 | F82: 0 | G82: 0 | H82: 0 | I82: 0 | J82: 0 | K82: 0 | L82: 0 | M82: 0 | N82: 0 | O82: 0 | P82: =SUM(D82:O82) -> 0
A83: 7 | B83: ='Initiative Register'!B11 -> INI-007 | C83: ='Initiative Register'!C11 -> Digital Patient Acquisition Funnel | D83: 0 | E83: 0 | F83: 0 | G83: 0 | H83: 0 | I83: 0 | J83: 0 | K83: 0 | L83: 0 | M83: 0 | N83: 0 | O83: 0 | P83: =SUM(D83:O83) -> 0
A84: 8 | B84: ='Initiative Register'!B12 -> INI-008 | C84: ='Initiative Register'!C12 -> Development of KPI for Doctors | D84: 0 | E84: 0 | F84: 0 | G84: 0 | H84: 0 | I84: 0 | J84: 0 | K84: 0 | L84: 0 | M84: 0 | N84: 0 | O84: 0 | P84: =SUM(D84:O84) -> 0
A85: 9 | B85: ='Initiative Register'!B13 -> INI-009 | C85: ='Initiative Register'!C13 -> Daycare and Minimaly Invasive Shift | D85: 0 | E85: 0 | F85: 0 | G85: 0 | H85: 0 | I85: 0 | J85: 0 | K85: 0 | L85: 0 | M85: 0 | N85: 0 | O85: 0 | P85: =SUM(D85:O85) -> 0
A86: 10 | B86: ='Initiative Register'!B14 -> INI-010 | C86: ='Initiative Register'!C14 -> Consumables standardization model | D86: 0 | E86: 0 | F86: 0 | G86: 0 | H86: 0 | I86: 0 | J86: 0 | K86: 0 | L86: 0 | M86: 0 | N86: 0 | O86: 0 | P86: =SUM(D86:O86) -> 0
A87: 11 | B87: ='Initiative Register'!B15 -> INI-011 | C87: ='Initiative Register'!C15 -> Collaboration with other Hospitals | D87: 0 | E87: 0 | F87: 0 | G87: 0 | H87: 0 | I87: 0 | J87: 0 | K87: 0 | L87: 0 | M87: 0 | N87: 0 | O87: 0 | P87: =SUM(D87:O87) -> 0
A88: 12 | B88: ='Initiative Register'!B16 -> INI-012 | C88: ='Initiative Register'!C16 -> ANNUAL RATE REVISION POLICY | D88: 0 | E88: 0 | F88: 0 | G88: 0 | H88: 0 | I88: 0 | J88: 0 | K88: 0 | L88: 0 | M88: 0 | N88: 0 | O88: 0 | P88: =SUM(D88:O88) -> 0
... A102: 26 | B102: ='Initiative Register'!B30 -> INI-026 | C102: ='Initiative Register'!C30 -> LAKESHORE HEART RUN — ANNUAL CARDIAC HEALTH EVENT | D102: 0 | E102: 0 | F102: 0 | G102: 0 | H102: 0 | I102: 0 | J102: 0 | K102: 0 | L102: 0 | M102: 0 | N102: 0 | O102: 0 | P102: =SUM(D102:O102) -> 0
A103: 27 | B103: ='Initiative Register'!B32 -> INI-028 | C103: ='Initiative Register'!C32 -> DIGITAL CONTENT PLATFORM — MALAYALAM AND ENGLISH | D103: 0 | E103: 0 | F103: 0 | G103: 0 | H103: 0 | I103: 0 | J103: 0 | K103: 0 | L103: 0 | M103: 0 | N103: 0 | O103: 0 | P103: =SUM(D103:O103) -> 0
A104: 28 | B104: ='Initiative Register'!B33 -> INI-029 | C104: ='Initiative Register'!C33 -> COMMUNITY HEALTH CAMPS — SCHOOLS, PLACES OF WORSHIP, RESIDENTIAL AREAS | D104: 0 | E104: 0 | F104: 0 | G104: 0 | H104: 0 | I104: 0 | J104: 0 | K104: 0 | L104: 0 | M104: 0 | N104: 0 | O104: 0 | P104: =SUM(D104:O104) -> 0
A105: 29 | B105: ='Initiative Register'!B34 -> INI-030 | C105: ='Initiative Register'!C34 -> DOCTOR ONLINE REPUTATION AND DIGITAL DISCOVERABILITY | D105: 0 | E105: 0 | F105: 0 | G105: 0 | H105: 0 | I105: 0 | J105: 0 | K105: 0 | L105: 0 | M105: 0 | N105: 0 | O105: 0 | P105: =SUM(D105:O105) -> 0
A106: 30 | B106: ='Initiative Register'!B35 -> INI-031 | C106: ='Initiative Register'!C35 -> TPA AND INSURER TARIFF RENEGOTIATION | D106: 0 | E106: 0 | F106: 0 | G106: 0 | H106: 0 | I106: 0 | J106: 0 | K106: 0 | L106: 0 | M106: 0 | N106: 0 | O106: 0 | P106: =SUM(D106:O106) -> 0
A107: 31 | B107: ='Initiative Register'!B36 -> INI-032 | C107: ='Initiative Register'!C36 -> FINANCIAL COUNSELLING AND PRE-AUTHORISATION AT SURGICAL OPD | D107: 0 | E107: 0 | F107: 0 | G107: 0 | H107: 0 | I107: 0 | J107: 0 | K107: 0 | L107: 0 | M107: 0 | N107: 0 | O107: 0 | P107: =SUM(D107:O107) -> 0
A108: 32 | B108: ='Initiative Register'!B37 -> INI-033 | C108: ='Initiative Register'!C37 -> BUILD A SCALED BD ORGANISATION | D108: 0 | E108: 0 | F108: 0 | G108: 0 | H108: 0 | I108: 0 | J108: 0 | K108: 0 | L108: 0 | M108: 0 | N108: 0 | O108: 0 | P108: =SUM(D108:O108) -> 0
A109: 33 | B109: ='Initiative Register'!B38 -> INI-034 | C109: ='Initiative Register'!C38 -> MATERIALS / DRUG COST & CONSUMABLES | D109: 0 | E109: 0 | F109: 0 | G109: 0 | H109: 0 | I109: 0 | J109: 0 | K109: 0 | L109: 0 | M109: 0 | N109: 0 | O109: 0 | P109: =SUM(D109:O109) -> 0
A110: 34 | B110: ='Initiative Register'!B39 -> INI-035 | C110: ='Initiative Register'!C39 -> MATERIALS / DRUG COST & CONSUMABLES | D110: 0 | E110: 0 | F110: 0 | G110: 0 | H110: 0 | I110: 0 | J110: 0 | K110: 0 | L110: 0 | M110: 0 | N110: 0 | O110: 0 | P110: =SUM(D110:O110) -> 0
A111: 35 | B111: ='Initiative Register'!B40 -> INI-036 | C111: ='Initiative Register'!C40 -> MATERIALS / DRUG COST & CONSUMABLES | D111: 0 | E111: 0 | F111: 0 | G111: 0 | H111: 0 | I111: 0 | J111: 0 | K111: 0 | L111: 0 | M111: 0 | N111: 0 | O111: 0 | P111: =SUM(D111:O111) -> 0
A112: 36 | B112: ='Initiative Register'!B41 -> INI-037 | C112: ='Initiative Register'!C41 -> MATERIALS / DRUG COST & CONSUMABLES | D112: 0 | E112: 0 | F112: 0 | G112: 0 | H112: 0 | I112: 0 | J112: 0 | K112: 0 | L112: 0 | M112: 0 | N112: 0 | O112: 0 | P112: =SUM(D112:O112) -> 0
A113: 37 | B113: ='Initiative Register'!B42 -> INI-038 | C113: ='Initiative Register'!C42 -> MATERIALS / DRUG COST & CONSUMABLES | D113: 0 | E113: 0 | F113: 0 | G113: 0 | H113: 0 | I113: 0 | J113: 0 | K113: 0 | L113: 0 | M113: 0 | N113: 0 | O113: 0 | P113: =SUM(D113:O113) -> 0
A114: 38 | B114: ='Initiative Register'!B43 -> INI-039 | C114: ='Initiative Register'!C43 -> MATERIALS / DRUG COST & CONSUMABLES | D114: 0 | E114: 0 | F114: 0 | G114: 0 | H114: 0 | I114: 0 | J114: 0 | K114: 0 | L114: 0 | M114: 0 | N114: 0 | O114: 0 | P114: =SUM(D114:O114) -> 0
... A126: 50 | B126: ='Initiative Register'!B55 -> INI-051 | C126: ='Initiative Register'!C55 -> OVERHEAD – REVENUE LEAKAGE RECOVERY | D126: 0 | E126: 0 | F126: 0 | G126: 0 | H126: 0 | I126: 0 | J126: 0 | K126: 0 | L126: 0 | M126: 0 | N126: 0 | O126: 0 | P126: =SUM(D126:O126) -> 0
A127: TOTAL | D127: =SUM(D77:D126) -> 0 | E127: =SUM(E77:E126) -> 0 | F127: =SUM(F77:F126) -> 0 | G127: =SUM(G77:G126) -> 0 | H127: =SUM(H77:H126) -> 0 | I127: =SUM(I77:I126) -> 0 | J127: =SUM(J77:J126) -> 0 | K127: =SUM(K77:K126) -> 0 | ... P127: =SUM(P77:P126) -> 0

Sheet Variance Analysis
A1: VARIANCE ANALYSIS — FY 2026-27 | Budget vs Actual | RED = Exception over threshold
A3: COST VARIANCE (Quarterly + Annual)
A4: # | B4: Initiative ID | C4: Initiative Name | D4: Q1 Bdg | E4: Q1 Act | F4: Q1 Var | G4: Q1 Var% | H4: Q2 Bdg | I4: Q2 Act | J4: Q2 Var | K4: Q2 Var% | L4: Q3 Bdg | M4: Q3 Act | N4: Q3 Var | O4: Q3 Var% | P4: Q4 Bdg | Q4: Q4 Act | R4: Q4 Var | S4: Q4 Var% | T4: Ann Bdg | U4: Ann Act | V4: Ann Var | W4: Ann Var% | X4: Exception
A5: 1 | B5: ='Initiative Register'!B5 -> INI-001 | C5: ='Initiative Register'!C5 -> Campaign- Patient experience improvement | D5: =SUM('Cost Plan'!D5:F5) -> 0 | E5: =SUM('Monthly Actuals'!D77:F77) -> 0 | F5: =E5-D5 -> 0 | G5: =IFERROR(IF(D5=0,"",F5/D5),"" ) | H5: =SUM('Cost Plan'!G5:I5) -> 0 | I5: =SUM('Monthly Actuals'!G77:I77) -> 0 | J5: =I5-H5 -> 0 | K5: =IFERROR(IF(H5=0,"",J5/H5),"" ) | L5: =SUM('Cost Plan'!J5:L5) -> 0 | M5: =SUM('Monthly Actuals'!J77:L77) -> 0 | N5: =M5-L5 -> 0 | O5: =IFERROR(IF(L5=0,"",N5/L5),"" ) | P5: =SUM('Cost Plan'!M5:O5) -> 0 | Q5: =SUM('Monthly Actuals'!M77:O77) -> 0 | R5: =Q5-P5 -> 0 | S5: =IFERROR(IF(P5=0,"",R5/P5),"" ) | T5: ='Cost Plan'!P5 -> 0 | U5: ='Monthly Actuals'!P77 -> 0 | V5: =U5-T5 -> 0 | W5: =IFERROR(IF(T5=0,"",V5/T5),"" ) | X5: =IF(ISNUMBER(W5),IF(W5>(Config!B7/100),"OVER BUDGET",IF(W5<-(Config!B7/100),"UNDER BUDGET","ON TRACK")),"" )
A6: 2 | B6: ='Initiative Register'!B6 | C6: ='Initiative Register'!C6 -> 0 | D6: =SUM('Cost Plan'!D6:F6) -> 0 | E6: =SUM('Monthly Actuals'!D78:F78) -> 0 | F6: =E6-D6 -> 0 | G6: =IFERROR(IF(D6=0,"",F6/D6),"" ) | H6: =SUM('Cost Plan'!G6:I6) -> 0 | I6: =SUM('Monthly Actuals'!G78:I78) -> 0 | J6: =I6-H6 -> 0 | K6: =IFERROR(IF(H6=0,"",J6/H6),"" ) | L6: =SUM('Cost Plan'!J6:L6) -> 0 | M6: =SUM('Monthly Actuals'!J78:L78) -> 0 | N6: =M6-L6 -> 0 | O6: =IFERROR(IF(L6=0,"",N6/L6),"" ) | P6: =SUM('Cost Plan'!M6:O6) -> 0 | Q6: =SUM('Monthly Actuals'!M78:O78) -> 0 | R6: =Q6-P6 -> 0 | S6: =IFERROR(IF(P6=0,"",R6/P6),"" ) | T6: ='Cost Plan'!P6 -> 0 | U6: ='Monthly Actuals'!P78 -> 0 | V6: =U6-T6 -> 0 | W6: =IFERROR(IF(T6=0,"",V6/T6),"" ) | X6: =IF(ISNUMBER(W6),IF(W6>(Config!B7/100),"OVER BUDGET",IF(W6<-(Config!B7/100),"UNDER BUDGET","ON TRACK")),"" )
A7: 3 | B7: ='Initiative Register'!B7 -> INI-003 | C7: ='Initiative Register'!C7 -> Geriatric ward | D7: =SUM('Cost Plan'!D7:F7) -> 0 | E7: =SUM('Monthly Actuals'!D79:F79) -> 0 | F7: =E7-D7 -> 0 | G7: =IFERROR(IF(D7=0,"",F7/D7),"" ) | H7: =SUM('Cost Plan'!G7:I7) -> 0 | I7: =SUM('Monthly Actuals'!G79:I79) -> 0 | J7: =I7-H7 -> 0 | K7: =IFERROR(IF(H7=0,"",J7/H7),"" ) | L7: =SUM('Cost Plan'!J7:L7) -> 0 | M7: =SUM('Monthly Actuals'!J79:L79) -> 0 | N7: =M7-L7 -> 0 | O7: =IFERROR(IF(L7=0,"",N7/L7),"" ) | P7: =SUM('Cost Plan'!M7:O7) -> 0 | Q7: =SUM('Monthly Actuals'!M79:O79) -> 0 | R7: =Q7-P7 -> 0 | S7: =IFERROR(IF(P7=0,"",R7/P7),"" ) | T7: ='Cost Plan'!P7 -> 0 | U7: ='Monthly Actuals'!P79 -> 0 | V7: =U7-T7 -> 0 | W7: =IFERROR(IF(T7=0,"",V7/T7),"" ) | X7: =IF(ISNUMBER(W7),IF(W7>(Config!B7/100),"OVER BUDGET",IF(W7<-(Config!B7/100),"UNDER BUDGET","ON TRACK")),"" )
A8: 4 | B8: ='Initiative Register'!B8 -> INI-004 | C8: ='Initiative Register'!C8 -> Appointment of Specialized Doctors and development of existing department | D8: =SUM('Cost Plan'!D8:F8) -> 0 | E8: =SUM('Monthly Actuals'!D80:F80) -> 0 | F8: =E8-D8 -> 0 | G8: =IFERROR(IF(D8=0,"",F8/D8),"" ) | H8: =SUM('Cost Plan'!G8:I8) -> 0 | I8: =SUM('Monthly Actuals'!G80:I80) -> 0 | J8: =I8-H8 -> 0 | K8: =IFERROR(IF(H8=0,"",J8/H8),"" ) | L8: =SUM('Cost Plan'!J8:L8) -> 0 | M8: =SUM('Monthly Actuals'!J80:L80) -> 0 | N8: =M8-L8 -> 0 | O8: =IFERROR(IF(L8=0,"",N8/L8),"" ) | P8: =SUM('Cost Plan'!M8:O8) -> 0 | Q8: =SUM('Monthly Actuals'!M80:O80) -> 0 | R8: =Q8-P8 -> 0 | S8: =IFERROR(IF(P8=0,"",R8/P8),"" ) | T8: ='Cost Plan'!P8 -> 0 | U8: ='Monthly Actuals'!P80 -> 0 | V8: =U8-T8 -> 0 | W8: =IFERROR(IF(T8=0,"",V8/T8),"" ) | X8: =IF(ISNUMBER(W8),IF(W8>(Config!B7/100),"OVER BUDGET",IF(W8<-(Config!B7/100),"UNDER BUDGET","ON TRACK")),"" )
A9: 5 | B9: ='Initiative Register'!B9 -> INI-005 | C9: ='Initiative Register'!C9 -> Patient companion | D9: =SUM('Cost Plan'!D9:F9) -> 0 | E9: =SUM('Monthly Actuals'!D81:F81) -> 0 | F9: =E9-D9 -> 0 | G9: =IFERROR(IF(D9=0,"",F9/D9),"" ) | H9: =SUM('Cost Plan'!G9:I9) -> 0 | I9: =SUM('Monthly Actuals'!G81:I81) -> 0 | J9: =I9-H9 -> 0 | K9: =IFERROR(IF(H9=0,"",J9/H9),"" ) | L9: =SUM('Cost Plan'!J9:L9) -> 0 | M9: =SUM('Monthly Actuals'!J81:L81) -> 0 | N9: =M9-L9 -> 0 | O9: =IFERROR(IF(L9=0,"",N9/L9),"" ) | P9: =SUM('Cost Plan'!M9:O9) -> 0 | Q9: =SUM('Monthly Actuals'!M81:O81) -> 0 | R9: =Q9-P9 -> 0 | S9: =IFERROR(IF(P9=0,"",R9/P9),"" ) | T9: ='Cost Plan'!P9 -> 0 | U9: ='Monthly Actuals'!P81 -> 0 | V9: =U9-T9 -> 0 | W9: =IFERROR(IF(T9=0,"",V9/T9),"" ) | X9: =IF(ISNUMBER(W9),IF(W9>(Config!B7/100),"OVER BUDGET",IF(W9<-(Config!B7/100),"UNDER BUDGET","ON TRACK")),"" )
A10: 6 | B10: ='Initiative Register'!B10 -> INI-006 | C10: ='Initiative Register'!C10 -> Newborn Care Enhancement | D10: =SUM('Cost Plan'!D10:F10) -> 0 | E10: =SUM('Monthly Actuals'!D82:F82) -> 0 | F10: =E10-D10 -> 0 | G10: =IFERROR(IF(D10=0,"",F10/D10),"" ) | H10: =SUM('Cost Plan'!G10:I10) -> 0 | I10: =SUM('Monthly Actuals'!G82:I82) -> 0 | J10: =I10-H10 -> 0 | K10: =IFERROR(IF(H10=0,"",J10/H10),"" ) | L10: =SUM('Cost Plan'!J10:L10) -> 0 | M10: =SUM('Monthly Actuals'!J82:L82) -> 0 | N10: =M10-L10 -> 0 | O10: =IFERROR(IF(L10=0,"",N10/L10),"" ) | P10: =SUM('Cost Plan'!M10:O10) -> 0 | Q10: =SUM('Monthly Actuals'!M82:O82) -> 0 | R10: =Q10-P10 -> 0 | S10: =IFERROR(IF(P10=0,"",R10/P10),"" ) | T10: ='Cost Plan'!P10 -> 0 | U10: ='Monthly Actuals'!P82 -> 0 | V10: =U10-T10 -> 0 | W10: =IFERROR(IF(T10=0,"",V10/T10),"" ) | X10: =IF(ISNUMBER(W10),IF(W10>(Config!B7/100),"OVER BUDGET",IF(W10<-(Config!B7/100),"UNDER BUDGET","ON TRACK")),"" )
A11: 7 | B11: ='Initiative Register'!B11 -> INI-007 | C11: ='Initiative Register'!C11 -> Digital Patient Acquisition Funnel | D11: =SUM('Cost Plan'!D11:F11) -> 0 | E11: =SUM('Monthly Actuals'!D83:F83) -> 0 | F11: =E11-D11 -> 0 | G11: =IFERROR(IF(D11=0,"",F11/D11),"" ) | H11: =SUM('Cost Plan'!G11:I11) -> 0 | I11: =SUM('Monthly Actuals'!G83:I83) -> 0 | J11: =I11-H11 -> 0 | K11: =IFERROR(IF(H11=0,"",J11/H11),"" ) | L11: =SUM('Cost Plan'!J11:L11) -> 0 | M11: =SUM('Monthly Actuals'!J83:L83) -> 0 | N11: =M11-L11 -> 0 | O11: =IFERROR(IF(L11=0,"",N11/L11),"" ) | P11: =SUM('Cost Plan'!M11:O11) -> 0 | Q11: =SUM('Monthly Actuals'!M83:O83) -> 0 | R11: =Q11-P11 -> 0 | S11: =IFERROR(IF(P11=0,"",R11/P11),"" ) | T11: ='Cost Plan'!P11 -> 0 | U11: ='Monthly Actuals'!P83 -> 0 | V11: =U11-T11 -> 0 | W11: =IFERROR(IF(T11=0,"",V11/T11),"" ) | X11: =IF(ISNUMBER(W11),IF(W11>(Config!B7/100),"OVER BUDGET",IF(W11<-(Config!B7/100),"UNDER BUDGET","ON TRACK")),"" )
A12: 8 | B12: ='Initiative Register'!B12 -> INI-008 | C12: ='Initiative Register'!C12 -> Development of KPI for Doctors | D12: =SUM('Cost Plan'!D12:F12) -> 0 | E12: =SUM('Monthly Actuals'!D84:F84) -> 0 | F12: =E12-D12 -> 0 | G12: =IFERROR(IF(D12=0,"",F12/D12),"" ) | H12: =SUM('Cost Plan'!G12:I12) -> 0 | I12: =SUM('Monthly Actuals'!G84:I84) -> 0 | J12: =I12-H12 -> 0 | K12: =IFERROR(IF(H12=0,"",J12/H12),"" ) | L12: =SUM('Cost Plan'!J12:L12) -> 0 | M12: =SUM('Monthly Actuals'!J84:L84) -> 0 | N12: =M12-L12 -> 0 | O12: =IFERROR(IF(L12=0,"",N12/L12),"" ) | P12: =SUM('Cost Plan'!M12:O12) -> 0 | Q12: =SUM('Monthly Actuals'!M84:O84) -> 0 | R12: =Q12-P12 -> 0 | S12: =IFERROR(IF(P12=0,"",R12/P12),"" ) | T12: ='Cost Plan'!P12 -> 0 | U12: ='Monthly Actuals'!P84 -> 0 | V12: =U12-T12 -> 0 | W12: =IFERROR(IF(T12=0,"",V12/T12),"" ) | X12: =IF(ISNUMBER(W12),IF(W12>(Config!B7/100),"OVER BUDGET",IF(W12<-(Config!B7/100),"UNDER BUDGET","ON TRACK")),"" )
A13: 9 | B13: ='Initiative Register'!B13 -> INI-009 | C13: ='Initiative Register'!C13 -> Daycare and Minimaly Invasive Shift | D13: =SUM('Cost Plan'!D13:F13) -> 0 | E13: =SUM('Monthly Actuals'!D85:F85) -> 0 | F13: =E13-D13 -> 0 | G13: =IFERROR(IF(D13=0,"",F13/D13),"" ) | H13: =SUM('Cost Plan'!G13:I13) -> 0 | I13: =SUM('Monthly Actuals'!G85:I85) -> 0 | J13: =I13-H13 -> 0 | K13: =IFERROR(IF(H13=0,"",J13/H13),"" ) | L13: =SUM('Cost Plan'!J13:L13) -> 0 | M13: =SUM('Monthly Actuals'!J85:L85) -> 0 | N13: =M13-L13 -> 0 | O13: =IFERROR(IF(L13=0,"",N13/L13),"" ) | P13: =SUM('Cost Plan'!M13:O13) -> 0 | Q13: =SUM('Monthly Actuals'!M85:O85) -> 0 | R13: =Q13-P13 -> 0 | S13: =IFERROR(IF(P13=0,"",R13/P13),"" ) | T13: ='Cost Plan'!P13 -> 0 | U13: ='Monthly Actuals'!P85 -> 0 | V13: =U13-T13 -> 0 | W13: =IFERROR(IF(T13=0,"",V13/T13),"" ) | X13: =IF(ISNUMBER(W13),IF(W13>(Config!B7/100),"OVER BUDGET",IF(W13<-(Config!B7/100),"UNDER BUDGET","ON TRACK")),"" )
A14: 10 | B14: ='Initiative Register'!B14 -> INI-010 | C14: ='Initiative Register'!C14 -> Consumables standardization model | D14: =SUM('Cost Plan'!D14:F14) -> 0 | E14: =SUM('Monthly Actuals'!D86:F86) -> 0 | F14: =E14-D14 -> 0 | G14: =IFERROR(IF(D14=0,"",F14/D14),"" ) | H14: =SUM('Cost Plan'!G14:I14) -> 0 | I14: =SUM('Monthly Actuals'!G86:I86) -> 0 | J14: =I14-H14 -> 0 | K14: =IFERROR(IF(H14=0,"",J14/H14),"" ) | L14: =SUM('Cost Plan'!J14:L14) -> 0 | M14: =SUM('Monthly Actuals'!J86:L86) -> 0 | N14: =M14-L14 -> 0 | O14: =IFERROR(IF(L14=0,"",N14/L14),"" ) | P14: =SUM('Cost Plan'!M14:O14) -> 0 | Q14: =SUM('Monthly Actuals'!M86:O86) -> 0 | R14: =Q14-P14 -> 0 | S14: =IFERROR(IF(P14=0,"",R14/P14),"" ) | T14: ='Cost Plan'!P14 -> 0 | U14: ='Monthly Actuals'!P86 -> 0 | V14: =U14-T14 -> 0 | W14: =IFERROR(IF(T14=0,"",V14/T14),"" ) | X14: =IF(ISNUMBER(W14),IF(W14>(Config!B7/100),"OVER BUDGET",IF(W14<-(Config!B7/100),"UNDER BUDGET","ON TRACK")),"" )
A15: 11 | B15: ='Initiative Register'!B15 -> INI-011 | C15: ='Initiative Register'!C15 -> Collaboration with other Hospitals | D15: =SUM('Cost Plan'!D15:F15) -> 0 | E15: =SUM('Monthly Actuals'!D87:F87) -> 0 | F15: =E15-D15 -> 0 | G15: =IFERROR(IF(D15=0,"",F15/D15),"" ) | H15: =SUM('Cost Plan'!G15:I15) -> 0 | I15: =SUM('Monthly Actuals'!G87:I87) -> 0 | J15: =I15-H15 -> 0 | K15: =IFERROR(IF(H15=0,"",J15/H15),"" ) | L15: =SUM('Cost Plan'!J15:L15) -> 0 | M15: =SUM('Monthly Actuals'!J87:L87) -> 0 | N15: =M15-L15 -> 0 | O15: =IFERROR(IF(L15=0,"",N15/L15),"" ) | P15: =SUM('Cost Plan'!M15:O15) -> 0 | Q15: =SUM('Monthly Actuals'!M87:O87) -> 0 | R15: =Q15-P15 -> 0 | S15: =IFERROR(IF(P15=0,"",R15/P15),"" ) | T15: ='Cost Plan'!P15 -> 0 | U15: ='Monthly Actuals'!P87 -> 0 | V15: =U15-T15 -> 0 | W15: =IFERROR(IF(T15=0,"",V15/T15),"" ) | X15: =IF(ISNUMBER(W15),IF(W15>(Config!B7/100),"OVER BUDGET",IF(W15<-(Config!B7/100),"UNDER BUDGET","ON TRACK")),"" )
A16: 12 | B16: ='Initiative Register'!B16 -> INI-012 | C16: ='Initiative Register'!C16 -> ANNUAL RATE REVISION POLICY | D16: =SUM('Cost Plan'!D16:F16) -> 0 | E16: =SUM('Monthly Actuals'!D88:F88) -> 0 | F16: =E16-D16 -> 0 | G16: =IFERROR(IF(D16=0,"",F16/D16),"" ) | H16: =SUM('Cost Plan'!G16:I16) -> 0 | I16: =SUM('Monthly Actuals'!G88:I88) -> 0 | J16: =I16-H16 -> 0 | K16: =IFERROR(IF(H16=0,"",J16/H16),"" ) | L16: =SUM('Cost Plan'!J16:L16) -> 0 | M16: =SUM('Monthly Actuals'!J88:L88) -> 0 | N16: =M16-L16 -> 0 | O16: =IFERROR(IF(L16=0,"",N16/L16),"" ) | P16: =SUM('Cost Plan'!M16:O16) -> 0 | Q16: =SUM('Monthly Actuals'!M88:O88) -> 0 | R16: =Q16-P16 -> 0 | S16: =IFERROR(IF(P16=0,"",R16/P16),"" ) | T16: ='Cost Plan'!P16 -> 0 | U16: ='Monthly Actuals'!P88 -> 0 | V16: =U16-T16 -> 0 | W16: =IFERROR(IF(T16=0,"",V16/T16),"" ) | X16: =IF(ISNUMBER(W16),IF(W16>(Config!B7/100),"OVER BUDGET",IF(W16<-(Config!B7/100),"UNDER BUDGET","ON TRACK")),"" )
A17: 13 | B17: ='Initiative Register'!B17 -> INI-013 | C17: ='Initiative Register'!C17 -> PROCEDURE CONTRIBUTION AUDIT AND REPRICING | D17: =SUM('Cost Plan'!D17:F17) -> 0 | E17: =SUM('Monthly Actuals'!D89:F89) -> 0 | F17: =E17-D17 -> 0 | G17: =IFERROR(IF(D17=0,"",F17/D17),"" ) | H17: =SUM('Cost Plan'!G17:I17) -> 0 | I17: =SUM('Monthly Actuals'!G89:I89) -> 0 | J17: =I17-H17 -> 0 | K17: =IFERROR(IF(H17=0,"",J17/H17),"" ) | L17: =SUM('Cost Plan'!J17:L17) -> 0 | M17: =SUM('Monthly Actuals'!J89:L89) -> 0 | N17: =M17-L17 -> 0 | O17: =IFERROR(IF(L17=0,"",N17/L17),"" ) | P17: =SUM('Cost Plan'!M17:O17) -> 0 | Q17: =SUM('Monthly Actuals'!M89:O89) -> 0 | R17: =Q17-P17 -> 0 | S17: =IFERROR(IF(P17=0,"",R17/P17),"" ) | T17: ='Cost Plan'!P17 -> 0 | U17: ='Monthly Actuals'!P89 -> 0 | V17: =U17-T17 -> 0 | W17: =IFERROR(IF(T17=0,"",V17/T17),"" ) | X17: =IF(ISNUMBER(W17),IF(W17>(Config!B7/100),"OVER BUDGET",IF(W17<-(Config!B7/100),"UNDER BUDGET","ON TRACK")),"" )
A18: 14 | B18: ='Initiative Register'!B18 -> INI-014 | C18: ='Initiative Register'!C18 -> INSURANCE CHARGE CAPTURE — BILL WHAT IS COVERED | D18: =SUM('Cost Plan'!D18:F18) -> 0 | E18: =SUM('Monthly Actuals'!D90:F90) -> 0 | F18: =E18-D18 -> 0 | G18: =IFERROR(IF(D18=0,"",F18/D18),"" ) | H18: =SUM('Cost Plan'!G18:I18) -> 0 | I18: =SUM('Monthly Actuals'!G90:I90) -> 0 | J18: =I18-H18 -> 0 | K18: =IFERROR(IF(H18=0,"",J18/H18),"" ) | L18: =SUM('Cost Plan'!J18:L18) -> 0 | M18: =SUM('Monthly Actuals'!J90:L90) -> 0 | N18: =M18-L18 -> 0 | O18: =IFERROR(IF(L18=0,"",N18/L18),"" ) | P18: =SUM('Cost Plan'!M18:O18) -> 0 | Q18: =SUM('Monthly Actuals'!M90:O90) -> 0 | R18: =Q18-P18 -> 0 | S18: =IFERROR(IF(P18=0,"",R18/P18),"" ) | T18: ='Cost Plan'!P18 -> 0 | U18: ='Monthly Actuals'!P90 -> 0 | V18: =U18-T18 -> 0 | W18: =IFERROR(IF(T18=0,"",V18/T18),"" ) | X18: =IF(ISNUMBER(W18),IF(W18>(Config!B7/100),"OVER BUDGET",IF(W18<-(Config!B7/100),"UNDER BUDGET","ON TRACK")),"" )
A19: 15 | B19: ='Initiative Register'!B19 -> INI-015 | C19: ='Initiative Register'!C19 -> SATELLITE CLINIC NETWORK — SURGEON-LED OFF-CAMPUS OPDs | D19: =SUM('Cost Plan'!D19:F19) -> 0 | E19: =SUM('Monthly Actuals'!D91:F91) -> 0 | F19: =E19-D19 -> 0 | G19: =IFERROR(IF(D19=0,"",F19/D19),"" ) | H19: =SUM('Cost Plan'!G19:I19) -> 0 | I19: =SUM('Monthly Actuals'!G91:I91) -> 0 | J19: =I19-H19 -> 0 | K19: =IFERROR(IF(H19=0,"",J19/H19),"" ) | L19: =SUM('Cost Plan'!J19:L19) -> 0 | M19: =SUM('Monthly Actuals'!J91:L91) -> 0 | N19: =M19-L19 -> 0 | O19: =IFERROR(IF(L19=0,"",N19/L19),"" ) | P19: =SUM('Cost Plan'!M19:O19) -> 0 | Q19: =SUM('Monthly Actuals'!M91:O91) -> 0 | R19: =Q19-P19 -> 0 | S19: =IFERROR(IF(P19=0,"",R19/P19),"" ) | T19: ='Cost Plan'!P19 -> 0 | U19: ='Monthly Actuals'!P91 -> 0 | V19: =U19-T19 -> 0 | W19: =IFERROR(IF(T19=0,"",V19/T19),"" ) | X19: =IF(ISNUMBER(W19),IF(W19>(Config!B7/100),"OVER BUDGET",IF(W19<-(Config!B7/100),"UNDER BUDGET","ON TRACK")),"" )
A20: 16 | B20: ='Initiative Register'!B20 -> INI-016 | C20: ='Initiative Register'!C20 -> CORPORATE HEALTH PROGRAMME | D20: =SUM('Cost Plan'!D20:F20) -> 0 | E20: =SUM('Monthly Actuals'!D92:F92) -> 0 | F20: =E20-D20 -> 0 | G20: =IFERROR(IF(D20=0,"",F20/D20),"" ) | H20: =SUM('Cost Plan'!G20:I20) -> 0 | I20: =SUM('Monthly Actuals'!G92:I92) -> 0 | J20: =I20-H20 -> 0 | K20: =IFERROR(IF(H20=0,"",J20/H20),"" ) | L20: =SUM('Cost Plan'!J20:L20) -> 0 | M20: =SUM('Monthly Actuals'!J92:L92) -> 0 | N20: =M20-L20 -> 0 | O20: =IFERROR(IF(L20=0,"",N20/L20),"" ) | P20: =SUM('Cost Plan'!M20:O20) -> 0 | Q20: =SUM('Monthly Actuals'!M92:O92) -> 0 | R20: =Q20-P20 -> 0 | S20: =IFERROR(IF(P20=0,"",R20/P20),"" ) | T20: ='Cost Plan'!P20 -> 0 | U20: ='Monthly Actuals'!P92 -> 0 | V20: =U20-T20 -> 0 | W20: =IFERROR(IF(T20=0,"",V20/T20),"" ) | X20: =IF(ISNUMBER(W20),IF(W20>(Config!B7/100),"OVER BUDGET",IF(W20<-(Config!B7/100),"UNDER BUDGET","ON TRACK")),"" )
A21: 17 | B21: ='Initiative Register'!B21 -> INI-017 | C21: ='Initiative Register'!C21 -> RESIDENTIAL COLONY AND COMMUNITY HEALTH PROGRAMMES | D21: =SUM('Cost Plan'!D21:F21) -> 0 | E21: =SUM('Monthly Actuals'!D93:F93) -> 0 | F21: =E21-D21 -> 0 | G21: =IFERROR(IF(D21=0,"",F21/D21),"" ) | H21: =SUM('Cost Plan'!G21:I21) -> 0 | I21: =SUM('Monthly Actuals'!G93:I93) -> 0 | J21: =I21-H21 -> 0 | K21: =IFERROR(IF(H21=0,"",J21/H21),"" ) | L21: =SUM('Cost Plan'!J21:L21) -> 0 | M21: =SUM('Monthly Actuals'!J93:L93) -> 0 | N21: =M21-L21 -> 0 | O21: =IFERROR(IF(L21=0,"",N21/L21),"" ) | P21: =SUM('Cost Plan'!M21:O21) -> 0 | Q21: =SUM('Monthly Actuals'!M93:O93) -> 0 | R21: =Q21-P21 -> 0 | S21: =IFERROR(IF(P21=0,"",R21/P21),"" ) | T21: ='Cost Plan'!P21 -> 0 | U21: ='Monthly Actuals'!P93 -> 0 | V21: =U21-T21 -> 0 | W21: =IFERROR(IF(T21=0,"",V21/T21),"" ) | X21: =IF(ISNUMBER(W21),IF(W21>(Config!B7/100),"OVER BUDGET",IF(W21<-(Config!B7/100),"UNDER BUDGET","ON TRACK")),"" )
A22: 18 | B22: ='Initiative Register'!B22 -> INI-018 | C22: ='Initiative Register'!C22 -> INTERNATIONAL MEDICAL VALUE TOURISM — GULF, MALDIVES, BANGLADESH | D22: =SUM('Cost Plan'!D22:F22) -> 0 | E22: =SUM('Monthly Actuals'!D94:F94) -> 0 | F22: =E22-D22 -> 0 | G22: =IFERROR(IF(D22=0,"",F22/D22),"" ) | H22: =SUM('Cost Plan'!G22:I22) -> 0 | I22: =SUM('Monthly Actuals'!G94:I94) -> 0 | J22: =I22-H22 -> 0 | K22: =IFERROR(IF(H22=0,"",J22/H22),"" ) | L22: =SUM('Cost Plan'!J22:L22) -> 0 | M22: =SUM('Monthly Actuals'!J94:L94) -> 0 | N22: =M22-L22 -> 0 | O22: =IFERROR(IF(L22=0,"",N22/L22),"" ) | P22: =SUM('Cost Plan'!M22:O22) -> 0 | Q22: =SUM('Monthly Actuals'!M94:O94) -> 0 | R22: =Q22-P22 -> 0 | S22: =IFERROR(IF(P22=0,"",R22/P22),"" ) | T22: ='Cost Plan'!P22 -> 0 | U22: ='Monthly Actuals'!P94 -> 0 | V22: =U22-T22 -> 0 | W22: =IFERROR(IF(T22=0,"",V22/T22),"" ) | X22: =IF(ISNUMBER(W22),IF(W22>(Config!B7/100),"OVER BUDGET",IF(W22<-(Config!B7/100),"UNDER BUDGET","ON TRACK")),"" )
A23: 19 | B23: ='Initiative Register'!B23 -> INI-019 | C23: ='Initiative Register'!C23 -> STRUCTURED REFERRAL DOCTOR PROGRAMME | D23: =SUM('Cost Plan'!D23:F23) -> 0 | E23: =SUM('Monthly Actuals'!D95:F95) -> 0 | F23: =E23-D23 -> 0 | G23: =IFERROR(IF(D23=0,"",F23/D23),"" ) | H23: =SUM('Cost Plan'!G23:I23) -> 0 | I23: =SUM('Monthly Actuals'!G95:I95) -> 0 | J23: =I23-H23 -> 0 | K23: =IFERROR(IF(H23=0,"",J23/H23),"" ) | L23: =SUM('Cost Plan'!J23:L23) -> 0 | M23: =SUM('Monthly Actuals'!J95:L95) -> 0 | N23: =M23-L23 -> 0 | O23: =IFERROR(IF(L23=0,"",N23/L23),"" ) | P23: =SUM('Cost Plan'!M23:O23) -> 0 | Q23: =SUM('Monthly Actuals'!M95:O95) -> 0 | R23: =Q23-P23 -> 0 | S23: =IFERROR(IF(P23=0,"",R23/P23),"" ) | T23: ='Cost Plan'!P23 -> 0 | U23: ='Monthly Actuals'!P95 -> 0 | V23: =U23-T23 -> 0 | W23: =IFERROR(IF(T23=0,"",V23/T23),"" ) | X23: =IF(ISNUMBER(W23),IF(W23>(Config!B7/100),"OVER BUDGET",IF(W23<-(Config!B7/100),"UNDER BUDGET","ON TRACK")),"" )
A24: 20 | B24: ='Initiative Register'!B24 -> INI-020 | C24: ='Initiative Register'!C24 -> CME AND CLINICAL CONNECT PROGRAMME | D24: =SUM('Cost Plan'!D24:F24) -> 0 | E24: =SUM('Monthly Actuals'!D96:F96) -> 0 | F24: =E24-D24 -> 0 | G24: =IFERROR(IF(D24=0,"",F24/D24),"" ) | H24: =SUM('Cost Plan'!G24:I24) -> 0 | I24: =SUM('Monthly Actuals'!G96:I96) -> 0 | J24: =I24-H24 -> 0 | K24: =IFERROR(IF(H24=0,"",J24/H24),"" ) | L24: =SUM('Cost Plan'!J24:L24) -> 0 | M24: =SUM('Monthly Actuals'!J96:L96) -> 0 | N24: =M24-L24 -> 0 | O24: =IFERROR(IF(L24=0,"",N24/L24),"" ) | P24: =SUM('Cost Plan'!M24:O24) -> 0 | Q24: =SUM('Monthly Actuals'!M96:O96) -> 0 | R24: =Q24-P24 -> 0 | S24: =IFERROR(IF(P24=0,"",R24/P24),"" ) | T24: ='Cost Plan'!P24 -> 0 | U24: ='Monthly Actuals'!P96 -> 0 | V24: =U24-T24 -> 0 | W24: =IFERROR(IF(T24=0,"",V24/T24),"" ) | X24: =IF(ISNUMBER(W24),IF(W24>(Config!B7/100),"OVER BUDGET",IF(W24<-(Config!B7/100),"UNDER BUDGET","ON TRACK")),"" )
A25: 21 | B25: ='Initiative Register'!B25 -> INI-021 | C25: ='Initiative Register'!C25 -> GOVERNMENT SCHEME EMPANELMENT OPTIMISATION | D25: =SUM('Cost Plan'!D25:F25) -> 0 | E25: =SUM('Monthly Actuals'!D97:F97) -> 0 | F25: =E25-D25 -> 0 | G25: =IFERROR(IF(D25=0,"",F25/D25),"" ) | H25: =SUM('Cost Plan'!G25:I25) -> 0 | I25: =SUM('Monthly Actuals'!G97:I97) -> 0 | J25: =I25-H25 -> 0 | K25: =IFERROR(IF(H25=0,"",J25/H25),"" ) | L25: =SUM('Cost Plan'!J25:L25) -> 0 | M25: =SUM('Monthly Actuals'!J97:L97) -> 0 | N25: =M25-L25 -> 0 | O25: =IFERROR(IF(L25=0,"",N25/L25),"" ) | P25: =SUM('Cost Plan'!M25:O25) -> 0 | Q25: =SUM('Monthly Actuals'!M97:O97) -> 0 | R25: =Q25-P25 -> 0 | S25: =IFERROR(IF(P25=0,"",R25/P25),"" ) | T25: ='Cost Plan'!P25 -> 0 | U25: ='Monthly Actuals'!P97 -> 0 | V25: =U25-T25 -> 0 | W25: =IFERROR(IF(T25=0,"",V25/T25),"" ) | X25: =IF(ISNUMBER(W25),IF(W25>(Config!B7/100),"OVER BUDGET",IF(W25<-(Config!B7/100),"UNDER BUDGET","ON TRACK")),"" )
A26: 22 | B26: ='Initiative Register'!B26 -> INI-022 | C26: ='Initiative Register'!C26 -> TRANSPLANT CENTRE — VOLUME GROWTH AND DONOR PROGRAMME ACTIVATION | D26: =SUM('Cost Plan'!D26:F26) -> 0 | E26: =SUM('Monthly Actuals'!D98:F98) -> 0 | F26: =E26-D26 -> 0 | G26: =IFERROR(IF(D26=0,"",F26/D26),"" ) | H26: =SUM('Cost Plan'!G26:I26) -> 0 | I26: =SUM('Monthly Actuals'!G98:I98) -> 0 | J26: =I26-H26 -> 0 | K26: =IFERROR(IF(H26=0,"",J26/H26),"" ) | L26: =SUM('Cost Plan'!J26:L26) -> 0 | M26: =SUM('Monthly Actuals'!J98:L98) -> 0 | N26: =M26-L26 -> 0 | O26: =IFERROR(IF(L26=0,"",N26/L26),"" ) | P26: =SUM('Cost Plan'!M26:O26) -> 0 | Q26: =SUM('Monthly Actuals'!M98:O98) -> 0 | R26: =Q26-P26 -> 0 | S26: =IFERROR(IF(P26=0,"",R26/P26),"" ) | T26: ='Cost Plan'!P26 -> 0 | U26: ='Monthly Actuals'!P98 -> 0 | V26: =U26-T26 -> 0 | W26: =IFERROR(IF(T26=0,"",V26/T26),"" ) | X26: =IF(ISNUMBER(W26),IF(W26>(Config!B7/100),"OVER BUDGET",IF(W26<-(Config!B7/100),"UNDER BUDGET","ON TRACK")),"" )
A27: 23 | B27: ='Initiative Register'!B27 -> INI-023 | C27: ='Initiative Register'!C27 -> CARDIAC SCIENCES — STRUCTURAL HEART AND ELECTROPHYSIOLOGY VOLUME BUILD | D27: =SUM('Cost Plan'!D27:F27) -> 0 | E27: =SUM('Monthly Actuals'!D99:F99) -> 0 | F27: =E27-D27 -> 0 | G27: =IFERROR(IF(D27=0,"",F27/D27),"" ) | H27: =SUM('Cost Plan'!G27:I27) -> 0 | I27: =SUM('Monthly Actuals'!G99:I99) -> 0 | J27: =I27-H27 -> 0 | K27: =IFERROR(IF(H27=0,"",J27/H27),"" ) | L27: =SUM('Cost Plan'!J27:L27) -> 0 | M27: =SUM('Monthly Actuals'!J99:L99) -> 0 | N27: =M27-L27 -> 0 | O27: =IFERROR(IF(L27=0,"",N27/L27),"" ) | P27: =SUM('Cost Plan'!M27:O27) -> 0 | Q27: =SUM('Monthly Actuals'!M99:O99) -> 0 | R27: =Q27-P27 -> 0 | S27: =IFERROR(IF(P27=0,"",R27/P27),"" ) | T27: ='Cost Plan'!P27 -> 0 | U27: ='Monthly Actuals'!P99 -> 0 | V27: =U27-T27 -> 0 | W27: =IFERROR(IF(T27=0,"",V27/T27),"" ) | X27: =IF(ISNUMBER(W27),IF(W27>(Config!B7/100),"OVER BUDGET",IF(W27<-(Config!B7/100),"UNDER BUDGET","ON TRACK")),"" )
A28: 24 | B28: ='Initiative Register'!B28 -> INI-024 | C28: ='Initiative Register'!C28 -> ONCOLOGY — EARLY DETECTION, SATELLITE CLINICS AND SURGICAL VOLUME GROWTH | D28: =SUM('Cost Plan'!D28:F28) -> 0 | E28: =SUM('Monthly Actuals'!D100:F100) -> 0 | F28: =E28-D28 -> 0 | G28: =IFERROR(IF(D28=0,"",F28/D28),"" ) | H28: =SUM('Cost Plan'!G28:I28) -> 0 | I28: =SUM('Monthly Actuals'!G100:I100) -> 0 | J28: =I28-H28 -> 0 | K28: =IFERROR(IF(H28=0,"",J28/H28),"" ) | L28: =SUM('Cost Plan'!J28:L28) -> 0 | M28: =SUM('Monthly Actuals'!J100:L100) -> 0 | N28: =M28-L28 -> 0 | O28: =IFERROR(IF(L28=0,"",N28/L28),"" ) | P28: =SUM('Cost Plan'!M28:O28) -> 0 | Q28: =SUM('Monthly Actuals'!M100:O100) -> 0 | R28: =Q28-P28 -> 0 | S28: =IFERROR(IF(P28=0,"",R28/P28),"" ) | T28: ='Cost Plan'!P28 -> 0 | U28: ='Monthly Actuals'!P100 -> 0 | V28: =U28-T28 -> 0 | W28: =IFERROR(IF(T28=0,"",V28/T28),"" ) | X28: =IF(ISNUMBER(W28),IF(W28>(Config!B7/100),"OVER BUDGET",IF(W28<-(Config!B7/100),"UNDER BUDGET","ON TRACK")),"" )
A29: 25 | B29: ='Initiative Register'!B29 -> INI-025 | C29: ='Initiative Register'!C29 -> ORTHOPAEDICS AND JOINT REPLACEMENT — VOLUME AND PACKAGE PROGRAMME | D29: =SUM('Cost Plan'!D29:F29) -> 0 | E29: =SUM('Monthly Actuals'!D101:F101) -> 0 | F29: =E29-D29 -> 0 | G29: =IFERROR(IF(D29=0,"",F29/D29),"" ) | H29: =SUM('Cost Plan'!G29:I29) -> 0 | I29: =SUM('Monthly Actuals'!G101:I101) -> 0 | J29: =I29-H29 -> 0 | K29: =IFERROR(IF(H29=0,"",J29/H29),"" ) | L29: =SUM('Cost Plan'!J29:L29) -> 0 | M29: =SUM('Monthly Actuals'!J101:L101) -> 0 | N29: =M29-L29 -> 0 | O29: =IFERROR(IF(L29=0,"",N29/L29),"" ) | P29: =SUM('Cost Plan'!M29:O29) -> 0 | Q29: =SUM('Monthly Actuals'!M101:O101) -> 0 | R29: =Q29-P29 -> 0 | S29: =IFERROR(IF(P29=0,"",R29/P29),"" ) | T29: ='Cost Plan'!P29 -> 0 | U29: ='Monthly Actuals'!P101 -> 0 | V29: =U29-T29 -> 0 | W29: =IFERROR(IF(T29=0,"",V29/T29),"" ) | X29: =IF(ISNUMBER(W29),IF(W29>(Config!B7/100),"OVER BUDGET",IF(W29<-(Config!B7/100),"UNDER BUDGET","ON TRACK")),"" )
A30: 26 | B30: ='Initiative Register'!B30 -> INI-026 | C30: ='Initiative Register'!C30 -> LAKESHORE HEART RUN — ANNUAL CARDIAC HEALTH EVENT | D30: =SUM('Cost Plan'!D30:F30) -> 0 | E30: =SUM('Monthly Actuals'!D102:F102) -> 0 | F30: =E30-D30 -> 0 | G30: =IFERROR(IF(D30=0,"",F30/D30),"" ) | H30: =SUM('Cost Plan'!G30:I30) -> 0 | I30: =SUM('Monthly Actuals'!G102:I102) -> 0 | J30: =I30-H30 -> 0 | K30: =IFERROR(IF(H30=0,"",J30/H30),"" ) | L30: =SUM('Cost Plan'!J30:L30) -> 0 | M30: =SUM('Monthly Actuals'!J102:L102) -> 0 | N30: =M30-L30 -> 0 | O30: =IFERROR(IF(L30=0,"",N30/L30),"" ) | P30: =SUM('Cost Plan'!M30:O30) -> 0 | Q30: =SUM('Monthly Actuals'!M102:O102) -> 0 | R30: =Q30-P30 -> 0 | S30: =IFERROR(IF(P30=0,"",R30/P30),"" ) | T30: ='Cost Plan'!P30 -> 0 | U30: ='Monthly Actuals'!P102 -> 0 | V30: =U30-T30 -> 0 | W30: =IFERROR(IF(T30=0,"",V30/T30),"" ) | X30: =IF(ISNUMBER(W30),IF(W30>(Config!B7/100),"OVER BUDGET",IF(W30<-(Config!B7/100),"UNDER BUDGET","ON TRACK")),"" )
A31: 27 | B31: ='Initiative Register'!B32 -> INI-028 | C31: ='Initiative Register'!C32 -> DIGITAL CONTENT PLATFORM — MALAYALAM AND ENGLISH | D31: =SUM('Cost Plan'!D31:F31) -> 0 | E31: =SUM('Monthly Actuals'!D103:F103) -> 0 | F31: =E31-D31 -> 0 | G31: =IFERROR(IF(D31=0,"",F31/D31),"" ) | H31: =SUM('Cost Plan'!G31:I31) -> 0 | I31: =SUM('Monthly Actuals'!G103:I103) -> 0 | J31: =I31-H31 -> 0 | K31: =IFERROR(IF(H31=0,"",J31/H31),"" ) | L31: =SUM('Cost Plan'!J31:L31) -> 0 | M31: =SUM('Monthly Actuals'!J103:L103) -> 0 | N31: =M31-L31 -> 0 | O31: =IFERROR(IF(L31=0,"",N31/L31),"" ) | P31: =SUM('Cost Plan'!M31:O31) -> 0 | Q31: =SUM('Monthly Actuals'!M103:O103) -> 0 | R31: =Q31-P31 -> 0 | S31: =IFERROR(IF(P31=0,"",R31/P31),"" ) | T31: ='Cost Plan'!P31 -> 0 | U31: ='Monthly Actuals'!P103 -> 0 | V31: =U31-T31 -> 0 | W31: =IFERROR(IF(T31=0,"",V31/T31),"" ) | X31: =IF(ISNUMBER(W31),IF(W31>(Config!B7/100),"OVER BUDGET",IF(W31<-(Config!B7/100),"UNDER BUDGET","ON TRACK")),"" )
A32: 28 | B32: ='Initiative Register'!B33 -> INI-029 | C32: ='Initiative Register'!C33 -> COMMUNITY HEALTH CAMPS — SCHOOLS, PLACES OF WORSHIP, RESIDENTIAL AREAS | D32: =SUM('Cost Plan'!D32:F32) -> 0 | E32: =SUM('Monthly Actuals'!D104:F104) -> 0 | F32: =E32-D32 -> 0 | G32: =IFERROR(IF(D32=0,"",F32/D32),"" ) | H32: =SUM('Cost Plan'!G32:I32) -> 0 | I32: =SUM('Monthly Actuals'!G104:I104) -> 0 | J32: =I32-H32 -> 0 | K32: =IFERROR(IF(H32=0,"",J32/H32),"" ) | L32: =SUM('Cost Plan'!J32:L32) -> 0 | M32: =SUM('Monthly Actuals'!J104:L104) -> 0 | N32: =M32-L32 -> 0 | O32: =IFERROR(IF(L32=0,"",N32/L32),"" ) | P32: =SUM('Cost Plan'!M32:O32) -> 0 | Q32: =SUM('Monthly Actuals'!M104:O104) -> 0 | R32: =Q32-P32 -> 0 | S32: =IFERROR(IF(P32=0,"",R32/P32),"" ) | T32: ='Cost Plan'!P32 -> 0 | U32: ='Monthly Actuals'!P104 -> 0 | V32: =U32-T32 -> 0 | W32: =IFERROR(IF(T32=0,"",V32/T32),"" ) | X32: =IF(ISNUMBER(W32),IF(W32>(Config!B7/100),"OVER BUDGET",IF(W32<-(Config!B7/100),"UNDER BUDGET","ON TRACK")),"" )
A33: 29 | B33: ='Initiative Register'!B34 -> INI-030 | C33: ='Initiative Register'!C34 -> DOCTOR ONLINE REPUTATION AND DIGITAL DISCOVERABILITY | D33: =SUM('Cost Plan'!D33:F33) -> 0 | E33: =SUM('Monthly Actuals'!D105:F105) -> 0 | F33: =E33-D33 -> 0 | G33: =IFERROR(IF(D33=0,"",F33/D33),"" ) | H33: =SUM('Cost Plan'!G33:I33) -> 0 | I33: =SUM('Monthly Actuals'!G105:I105) -> 0 | J33: =I33-H33 -> 0 | K33: =IFERROR(IF(H33=0,"",J33/H33),"" ) | L33: =SUM('Cost Plan'!J33:L33) -> 0 | M33: =SUM('Monthly Actuals'!J105:L105) -> 0 | N33: =M33-L33 -> 0 | O33: =IFERROR(IF(L33=0,"",N33/L33),"" ) | P33: =SUM('Cost Plan'!M33:O33) -> 0 | Q33: =SUM('Monthly Actuals'!M105:O105) -> 0 | R33: =Q33-P33 -> 0 | S33: =IFERROR(IF(P33=0,"",R33/P33),"" ) | T33: ='Cost Plan'!P33 -> 0 | U33: ='Monthly Actuals'!P105 -> 0 | V33: =U33-T33 -> 0 | W33: =IFERROR(IF(T33=0,"",V33/T33),"" ) | X33: =IF(ISNUMBER(W33),IF(W33>(Config!B7/100),"OVER BUDGET",IF(W33<-(Config!B7/100),"UNDER BUDGET","ON TRACK")),"" )
A34: 30 | B34: ='Initiative Register'!B35 -> INI-031 | C34: ='Initiative Register'!C35 -> TPA AND INSURER TARIFF RENEGOTIATION | D34: =SUM('Cost Plan'!D34:F34) -> 0 | E34: =SUM('Monthly Actuals'!D106:F106) -> 0 | F34: =E34-D34 -> 0 | G34: =IFERROR(IF(D34=0,"",F34/D34),"" ) | H34: =SUM('Cost Plan'!G34:I34) -> 0 | I34: =SUM('Monthly Actuals'!G106:I106) -> 0 | J34: =I34-H34 -> 0 | K34: =IFERROR(IF(H34=0,"",J34/H34),"" ) | L34: =SUM('Cost Plan'!J34:L34) -> 0 | M34: =SUM('Monthly Actuals'!J106:L106) -> 0 | N34: =M34-L34 -> 0 | O34: =IFERROR(IF(L34=0,"",N34/L34),"" ) | P34: =SUM('Cost Plan'!M34:O34) -> 0 | Q34: =SUM('Monthly Actuals'!M106:O106) -> 0 | R34: =Q34-P34 -> 0 | S34: =IFERROR(IF(P34=0,"",R34/P34),"" ) | T34: ='Cost Plan'!P34 -> 0 | U34: ='Monthly Actuals'!P106 -> 0 | V34: =U34-T34 -> 0 | W34: =IFERROR(IF(T34=0,"",V34/T34),"" ) | X34: =IF(ISNUMBER(W34),IF(W34>(Config!B7/100),"OVER BUDGET",IF(W34<-(Config!B7/100),"UNDER BUDGET","ON TRACK")),"" )
A35: 31 | B35: ='Initiative Register'!B36 -> INI-032 | C35: ='Initiative Register'!C36 -> FINANCIAL COUNSELLING AND PRE-AUTHORISATION AT SURGICAL OPD | D35: =SUM('Cost Plan'!D35:F35) -> 0 | E35: =SUM('Monthly Actuals'!D107:F107) -> 0 | F35: =E35-D35 -> 0 | G35: =IFERROR(IF(D35=0,"",F35/D35),"" ) | H35: =SUM('Cost Plan'!G35:I35) -> 0 | I35: =SUM('Monthly Actuals'!G107:I107) -> 0 | J35: =I35-H35 -> 0 | K35: =IFERROR(IF(H35=0,"",J35/H35),"" ) | L35: =SUM('Cost Plan'!J35:L35) -> 0 | M35: =SUM('Monthly Actuals'!J107:L107) -> 0 | N35: =M35-L35 -> 0 | O35: =IFERROR(IF(L35=0,"",N35/L35),"" ) | P35: =SUM('Cost Plan'!M35:O35) -> 0 | Q35: =SUM('Monthly Actuals'!M107:O107) -> 0 | R35: =Q35-P35 -> 0 | S35: =IFERROR(IF(P35=0,"",R35/P35),"" ) | T35: ='Cost Plan'!P35 -> 0 | U35: ='Monthly Actuals'!P107 -> 0 | V35: =U35-T35 -> 0 | W35: =IFERROR(IF(T35=0,"",V35/T35),"" ) | X35: =IF(ISNUMBER(W35),IF(W35>(Config!B7/100),"OVER BUDGET",IF(W35<-(Config!B7/100),"UNDER BUDGET","ON TRACK")),"" )
A36: 32 | B36: ='Initiative Register'!B37 -> INI-033 | C36: ='Initiative Register'!C37 -> BUILD A SCALED BD ORGANISATION | D36: =SUM('Cost Plan'!D36:F36) -> 0 | E36: =SUM('Monthly Actuals'!D108:F108) -> 0 | F36: =E36-D36 -> 0 | G36: =IFERROR(IF(D36=0,"",F36/D36),"" ) | H36: =SUM('Cost Plan'!G36:I36) -> 0 | I36: =SUM('Monthly Actuals'!G108:I108) -> 0 | J36: =I36-H36 -> 0 | K36: =IFERROR(IF(H36=0,"",J36/H36),"" ) | L36: =SUM('Cost Plan'!J36:L36) -> 0 | M36: =SUM('Monthly Actuals'!J108:L108) -> 0 | N36: =M36-L36 -> 0 | O36: =IFERROR(IF(L36=0,"",N36/L36),"" ) | P36: =SUM('Cost Plan'!M36:O36) -> 0 | Q36: =SUM('Monthly Actuals'!M108:O108) -> 0 | R36: =Q36-P36 -> 0 | S36: =IFERROR(IF(P36=0,"",R36/P36),"" ) | T36: ='Cost Plan'!P36 -> 0 | U36: ='Monthly Actuals'!P108 -> 0 | V36: =U36-T36 -> 0 | W36: =IFERROR(IF(T36=0,"",V36/T36),"" ) | X36: =IF(ISNUMBER(W36),IF(W36>(Config!B7/100),"OVER BUDGET",IF(W36<-(Config!B7/100),"UNDER BUDGET","ON TRACK")),"" )
A37: 33 | B37: ='Initiative Register'!B38 -> INI-034 | C37: ='Initiative Register'!C38 -> MATERIALS / DRUG COST & CONSUMABLES | D37: =SUM('Cost Plan'!D37:F37) -> 0 | E37: =SUM('Monthly Actuals'!D109:F109) -> 0 | F37: =E37-D37 -> 0 | G37: =IFERROR(IF(D37=0,"",F37/D37),"" ) | H37: =SUM('Cost Plan'!G37:I37) -> 0 | I37: =SUM('Monthly Actuals'!G109:I109) -> 0 | J37: =I37-H37 -> 0 | K37: =IFERROR(IF(H37=0,"",J37/H37),"" ) | L37: =SUM('Cost Plan'!J37:L37) -> 0 | M37: =SUM('Monthly Actuals'!J109:L109) -> 0 | N37: =M37-L37 -> 0 | O37: =IFERROR(IF(L37=0,"",N37/L37),"" ) | P37: =SUM('Cost Plan'!M37:O37) -> 0 | Q37: =SUM('Monthly Actuals'!M109:O109) -> 0 | R37: =Q37-P37 -> 0 | S37: =IFERROR(IF(P37=0,"",R37/P37),"" ) | T37: ='Cost Plan'!P37 -> 0 | U37: ='Monthly Actuals'!P109 -> 0 | V37: =U37-T37 -> 0 | W37: =IFERROR(IF(T37=0,"",V37/T37),"" ) | X37: =IF(ISNUMBER(W37),IF(W37>(Config!B7/100),"OVER BUDGET",IF(W37<-(Config!B7/100),"UNDER BUDGET","ON TRACK")),"" )
A38: 34 | B38: ='Initiative Register'!B39 -> INI-035 | C38: ='Initiative Register'!C39 -> MATERIALS / DRUG COST & CONSUMABLES | D38: =SUM('Cost Plan'!D38:F38) -> 0 | E38: =SUM('Monthly Actuals'!D110:F110) -> 0 | F38: =E38-D38 -> 0 | G38: =IFERROR(IF(D38=0,"",F38/D38),"" ) | H38: =SUM('Cost Plan'!G38:I38) -> 0 | I38: =SUM('Monthly Actuals'!G110:I110) -> 0 | J38: =I38-H38 -> 0 | K38: =IFERROR(IF(H38=0,"",J38/H38),"" ) | L38: =SUM('Cost Plan'!J38:L38) -> 0 | M38: =SUM('Monthly Actuals'!J110:L110) -> 0 | N38: =M38-L38 -> 0 | O38: =IFERROR(IF(L38=0,"",N38/L38),"" ) | P38: =SUM('Cost Plan'!M38:O38) -> 0 | Q38: =SUM('Monthly Actuals'!M110:O110) -> 0 | R38: =Q38-P38 -> 0 | S38: =IFERROR(IF(P38=0,"",R38/P38),"" ) | T38: ='Cost Plan'!P38 -> 0 | U38: ='Monthly Actuals'!P110 -> 0 | V38: =U38-T38 -> 0 | W38: =IFERROR(IF(T38=0,"",V38/T38),"" ) | X38: =IF(ISNUMBER(W38),IF(W38>(Config!B7/100),"OVER BUDGET",IF(W38<-(Config!B7/100),"UNDER BUDGET","ON TRACK")),"" )
A39: 35 | B39: ='Initiative Register'!B40 -> INI-036 | C39: ='Initiative Register'!C40 -> MATERIALS / DRUG COST & CONSUMABLES | D39: =SUM('Cost Plan'!D39:F39) -> 0 | E39: =SUM('Monthly Actuals'!D111:F111) -> 0 | F39: =E39-D39 -> 0 | G39: =IFERROR(IF(D39=0,"",F39/D39),"" ) | H39: =SUM('Cost Plan'!G39:I39) -> 0 | I39: =SUM('Monthly Actuals'!G111:I111) -> 0 | J39: =I39-H39 -> 0 | K39: =IFERROR(IF(H39=0,"",J39/H39),"" ) | L39: =SUM('Cost Plan'!J39:L39) -> 0 | M39: =SUM('Monthly Actuals'!J111:L111) -> 0 | N39: =M39-L39 -> 0 | O39: =IFERROR(IF(L39=0,"",N39/L39),"" ) | P39: =SUM('Cost Plan'!M39:O39) -> 0 | Q39: =SUM('Monthly Actuals'!M111:O111) -> 0 | R39: =Q39-P39 -> 0 | S39: =IFERROR(IF(P39=0,"",R39/P39),"" ) | T39: ='Cost Plan'!P39 -> 0 | U39: ='Monthly Actuals'!P111 -> 0 | V39: =U39-T39 -> 0 | W39: =IFERROR(IF(T39=0,"",V39/T39),"" ) | X39: =IF(ISNUMBER(W39),IF(W39>(Config!B7/100),"OVER BUDGET",IF(W39<-(Config!B7/100),"UNDER BUDGET","ON TRACK")),"" )
A40: 36 | B40: ='Initiative Register'!B41 -> INI-037 | C40: ='Initiative Register'!C41 -> MATERIALS / DRUG COST & CONSUMABLES | D40: =SUM('Cost Plan'!D40:F40) -> 0 | E40: =SUM('Monthly Actuals'!D112:F112) -> 0 | F40: =E40-D40 -> 0 | G40: =IFERROR(IF(D40=0,"",F40/D40),"" ) | H40: =SUM('Cost Plan'!G40:I40) -> 0 | I40: =SUM('Monthly Actuals'!G112:I112) -> 0 | J40: =I40-H40 -> 0 | K40: =IFERROR(IF(H40=0,"",J40/H40),"" ) | L40: =SUM('Cost Plan'!J40:L40) -> 0 | M40: =SUM('Monthly Actuals'!J112:L112) -> 0 | N40: =M40-L40 -> 0 | O40: =IFERROR(IF(L40=0,"",N40/L40),"" ) | P40: =SUM('Cost Plan'!M40:O40) -> 0 | Q40: =SUM('Monthly Actuals'!M112:O112) -> 0 | R40: =Q40-P40 -> 0 | S40: =IFERROR(IF(P40=0,"",R40/P40),"" ) | T40: ='Cost Plan'!P40 -> 0 | U40: ='Monthly Actuals'!P112 -> 0 | V40: =U40-T40 -> 0 | W40: =IFERROR(IF(T40=0,"",V40/T40),"" ) | X40: =IF(ISNUMBER(W40),IF(W40>(Config!B7/100),"OVER BUDGET",IF(W40<-(Config!B7/100),"UNDER BUDGET","ON TRACK")),"" )
A41: 37 | B41: ='Initiative Register'!B42 -> INI-038 | C41: ='Initiative Register'!C42 -> MATERIALS / DRUG COST & CONSUMABLES | D41: =SUM('Cost Plan'!D41:F41) -> 0 | E41: =SUM('Monthly Actuals'!D113:F113) -> 0 | F41: =E41-D41 -> 0 | G41: =IFERROR(IF(D41=0,"",F41/D41),"" ) | H41: =SUM('Cost Plan'!G41:I41) -> 0 | I41: =SUM('Monthly Actuals'!G113:I113) -> 0 | J41: =I41-H41 -> 0 | K41: =IFERROR(IF(H41=0,"",J41/H41),"" ) | L41: =SUM('Cost Plan'!J41:L41) -> 0 | M41: =SUM('Monthly Actuals'!J113:L113) -> 0 | N41: =M41-L41 -> 0 | O41: =IFERROR(IF(L41=0,"",N41/L41),"" ) | P41: =SUM('Cost Plan'!M41:O41) -> 0 | Q41: =SUM('Monthly Actuals'!M113:O113) -> 0 | R41: =Q41-P41 -> 0 | S41: =IFERROR(IF(P41=0,"",R41/P41),"" ) | T41: ='Cost Plan'!P41 -> 0 | U41: ='Monthly Actuals'!P113 -> 0 | V41: =U41-T41 -> 0 | W41: =IFERROR(IF(T41=0,"",V41/T41),"" ) | X41: =IF(ISNUMBER(W41),IF(W41>(Config!B7/100),"OVER BUDGET",IF(W41<-(Config!B7/100),"UNDER BUDGET","ON TRACK")),"" )
A42: 38 | B42: ='Initiative Register'!B43 -> INI-039 | C42: ='Initiative Register'!C43 -> MATERIALS / DRUG COST & CONSUMABLES | D42: =SUM('Cost Plan'!D42:F42) -> 0 | E42: =SUM('Monthly Actuals'!D114:F114) -> 0 | F42: =E42-D42 -> 0 | G42: =IFERROR(IF(D42=0,"",F42/D42),"" ) | H42: =SUM('Cost Plan'!G42:I42) -> 0 | I42: =SUM('Monthly Actuals'!G114:I114) -> 0 | J42: =I42-H42 -> 0 | K42: =IFERROR(IF(H42=0,"",J42/H42),"" ) | L42: =SUM('Cost Plan'!J42:L42) -> 0 | M42: =SUM('Monthly Actuals'!J114:L114) -> 0 | N42: =M42-L42 -> 0 | O42: =IFERROR(IF(L42=0,"",N42/L42),"" ) | P42: =SUM('Cost Plan'!M42:O42) -> 0 | Q42: =SUM('Monthly Actuals'!M114:O114) -> 0 | R42: =Q42-P42 -> 0 | S42: =IFERROR(IF(P42=0,"",R42/P42),"" ) | T42: ='Cost Plan'!P42 -> 0 | U42: ='Monthly Actuals'!P114 -> 0 | V42: =U42-T42 -> 0 | W42: =IFERROR(IF(T42=0,"",V42/T42),"" ) | X42: =IF(ISNUMBER(W42),IF(W42>(Config!B7/100),"OVER BUDGET",IF(W42<-(Config!B7/100),"UNDER BUDGET","ON TRACK")),"" )
A43: 39 | B43: ='Initiative Register'!B44 -> INI-040 | C43: ='Initiative Register'!C44 -> MATERIALS / DRUG COST & CONSUMABLES | D43: =SUM('Cost Plan'!D43:F43) -> 0 | E43: =SUM('Monthly Actuals'!D115:F115) -> 0 | F43: =E43-D43 -> 0 | G43: =IFERROR(IF(D43=0,"",F43/D43),"" ) | H43: =SUM('Cost Plan'!G43:I43) -> 0 | I43: =SUM('Monthly Actuals'!G115:I115) -> 0 | J43: =I43-H43 -> 0 | K43: =IFERROR(IF(H43=0,"",J43/H43),"" ) | L43: =SUM('Cost Plan'!J43:L43) -> 0 | M43: =SUM('Monthly Actuals'!J115:L115) -> 0 | N43: =M43-L43 -> 0 | O43: =IFERROR(IF(L43=0,"",N43/L43),"" ) | P43: =SUM('Cost Plan'!M43:O43) -> 0 | Q43: =SUM('Monthly Actuals'!M115:O115) -> 0 | R43: =Q43-P43 -> 0 | S43: =IFERROR(IF(P43=0,"",R43/P43),"" ) | T43: ='Cost Plan'!P43 -> 0 | U43: ='Monthly Actuals'!P115 -> 0 | V43: =U43-T43 -> 0 | W43: =IFERROR(IF(T43=0,"",V43/T43),"" ) | X43: =IF(ISNUMBER(W43),IF(W43>(Config!B7/100),"OVER BUDGET",IF(W43<-(Config!B7/100),"UNDER BUDGET","ON TRACK")),"" )
A44: 40 | B44: ='Initiative Register'!B45 -> INI-041 | C44: ='Initiative Register'!C45 -> MATERIALS / DRUG COST & CONSUMABLES | D44: =SUM('Cost Plan'!D44:F44) -> 0 | E44: =SUM('Monthly Actuals'!D116:F116) -> 0 | F44: =E44-D44 -> 0 | G44: =IFERROR(IF(D44=0,"",F44/D44),"" ) | H44: =SUM('Cost Plan'!G44:I44) -> 0 | I44: =SUM('Monthly Actuals'!G116:I116) -> 0 | J44: =I44-H44 -> 0 | K44: =IFERROR(IF(H44=0,"",J44/H44),"" ) | L44: =SUM('Cost Plan'!J44:L44) -> 0 | M44: =SUM('Monthly Actuals'!J116:L116) -> 0 | N44: =M44-L44 -> 0 | O44: =IFERROR(IF(L44=0,"",N44/L44),"" ) | P44: =SUM('Cost Plan'!M44:O44) -> 0 | Q44: =SUM('Monthly Actuals'!M116:O116) -> 0 | R44: =Q44-P44 -> 0 | S44: =IFERROR(IF(P44=0,"",R44/P44),"" ) | T44: ='Cost Plan'!P44 -> 0 | U44: ='Monthly Actuals'!P116 -> 0 | V44: =U44-T44 -> 0 | W44: =IFERROR(IF(T44=0,"",V44/T44),"" ) | X44: =IF(ISNUMBER(W44),IF(W44>(Config!B7/100),"OVER BUDGET",IF(W44<-(Config!B7/100),"UNDER BUDGET","ON TRACK")),"" )
A45: 41 | B45: ='Initiative Register'!B46 -> INI-042 | C45: ='Initiative Register'!C46 -> PAYROLL – NURSING OPTIMISATION | D45: =SUM('Cost Plan'!D45:F45) -> 0 | E45: =SUM('Monthly Actuals'!D117:F117) -> 0 | F45: =E45-D45 -> 0 | G45: =IFERROR(IF(D45=0,"",F45/D45),"" ) | H45: =SUM('Cost Plan'!G45:I45) -> 0 | I45: =SUM('Monthly Actuals'!G117:I117) -> 0 | J45: =I45-H45 -> 0 | K45: =IFERROR(IF(H45=0,"",J45/H45),"" ) | L45: =SUM('Cost Plan'!J45:L45) -> 0 | M45: =SUM('Monthly Actuals'!J117:L117) -> 0 | N45: =M45-L45 -> 0 | O45: =IFERROR(IF(L45=0,"",N45/L45),"" ) | P45: =SUM('Cost Plan'!M45:O45) -> 0 | Q45: =SUM('Monthly Actuals'!M117:O117) -> 0 | R45: =Q45-P45 -> 0 | S45: =IFERROR(IF(P45=0,"",R45/P45),"" ) | T45: ='Cost Plan'!P45 -> 0 | U45: ='Monthly Actuals'!P117 -> 0 | V45: =U45-T45 -> 0 | W45: =IFERROR(IF(T45=0,"",V45/T45),"" ) | X45: =IF(ISNUMBER(W45),IF(W45>(Config!B7/100),"OVER BUDGET",IF(W45<-(Config!B7/100),"UNDER BUDGET","ON TRACK")),"" )
A46: 42 | B46: ='Initiative Register'!B47 -> INI-043 | C46: ='Initiative Register'!C47 -> PAYROLL – PHARMACY OPTIMISATION | D46: =SUM('Cost Plan'!D46:F46) -> 0 | E46: =SUM('Monthly Actuals'!D118:F118) -> 0 | F46: =E46-D46 -> 0 | G46: =IFERROR(IF(D46=0,"",F46/D46),"" ) | H46: =SUM('Cost Plan'!G46:I46) -> 0 | I46: =SUM('Monthly Actuals'!G118:I118) -> 0 | J46: =I46-H46 -> 0 | K46: =IFERROR(IF(H46=0,"",J46/H46),"" ) | L46: =SUM('Cost Plan'!J46:L46) -> 0 | M46: =SUM('Monthly Actuals'!J118:L118) -> 0 | N46: =M46-L46 -> 0 | O46: =IFERROR(IF(L46=0,"",N46/L46),"" ) | P46: =SUM('Cost Plan'!M46:O46) -> 0 | Q46: =SUM('Monthly Actuals'!M118:O118) -> 0 | R46: =Q46-P46 -> 0 | S46: =IFERROR(IF(P46=0,"",R46/P46),"" ) | T46: ='Cost Plan'!P46 -> 0 | U46: ='Monthly Actuals'!P118 -> 0 | V46: =U46-T46 -> 0 | W46: =IFERROR(IF(T46=0,"",V46/T46),"" ) | X46: =IF(ISNUMBER(W46),IF(W46>(Config!B7/100),"OVER BUDGET",IF(W46<-(Config!B7/100),"UNDER BUDGET","ON TRACK")),"" )
A47: 43 | B47: ='Initiative Register'!B48 -> INI-044 | C47: ='Initiative Register'!C48 -> PAYROLL – ADMIN (PCS) OPTIMISATION | D47: =SUM('Cost Plan'!D47:F47) -> 0 | E47: =SUM('Monthly Actuals'!D119:F119) -> 0 | F47: =E47-D47 -> 0 | G47: =IFERROR(IF(D47=0,"",F47/D47),"" ) | H47: =SUM('Cost Plan'!G47:I47) -> 0 | I47: =SUM('Monthly Actuals'!G119:I119) -> 0 | J47: =I47-H47 -> 0 | K47: =IFERROR(IF(H47=0,"",J47/H47),"" ) | L47: =SUM('Cost Plan'!J47:L47) -> 0 | M47: =SUM('Monthly Actuals'!J119:L119) -> 0 | N47: =M47-L47 -> 0 | O47: =IFERROR(IF(L47=0,"",N47/L47),"" ) | P47: =SUM('Cost Plan'!M47:O47) -> 0 | Q47: =SUM('Monthly Actuals'!M119:O119) -> 0 | R47: =Q47-P47 -> 0 | S47: =IFERROR(IF(P47=0,"",R47/P47),"" ) | T47: ='Cost Plan'!P47 -> 0 | U47: ='Monthly Actuals'!P119 -> 0 | V47: =U47-T47 -> 0 | W47: =IFERROR(IF(T47=0,"",V47/T47),"" ) | X47: =IF(ISNUMBER(W47),IF(W47>(Config!B7/100),"OVER BUDGET",IF(W47<-(Config!B7/100),"UNDER BUDGET","ON TRACK")),"" )
A48: 44 | B48: ='Initiative Register'!B49 -> INI-045 | C48: ='Initiative Register'!C49 -> PAYROLL – LAB OPTIMISATION | D48: =SUM('Cost Plan'!D48:F48) -> 0 | E48: =SUM('Monthly Actuals'!D120:F120) -> 0 | F48: =E48-D48 -> 0 | G48: =IFERROR(IF(D48=0,"",F48/D48),"" ) | H48: =SUM('Cost Plan'!G48:I48) -> 0 | I48: =SUM('Monthly Actuals'!G120:I120) -> 0 | J48: =I48-H48 -> 0 | K48: =IFERROR(IF(H48=0,"",J48/H48),"" ) | L48: =SUM('Cost Plan'!J48:L48) -> 0 | M48: =SUM('Monthly Actuals'!J120:L120) -> 0 | N48: =M48-L48 -> 0 | O48: =IFERROR(IF(L48=0,"",N48/L48),"" ) | P48: =SUM('Cost Plan'!M48:O48) -> 0 | Q48: =SUM('Monthly Actuals'!M120:O120) -> 0 | R48: =Q48-P48 -> 0 | S48: =IFERROR(IF(P48=0,"",R48/P48),"" ) | T48: ='Cost Plan'!P48 -> 0 | U48: ='Monthly Actuals'!P120 -> 0 | V48: =U48-T48 -> 0 | W48: =IFERROR(IF(T48=0,"",V48/T48),"" ) | X48: =IF(ISNUMBER(W48),IF(W48>(Config!B7/100),"OVER BUDGET",IF(W48<-(Config!B7/100),"UNDER BUDGET","ON TRACK")),"" )
A49: 45 | B49: ='Initiative Register'!B50 -> INI-046 | C49: ='Initiative Register'!C50 -> PAYROLL – OT COST CONTROL | D49: =SUM('Cost Plan'!D49:F49) -> 0 | E49: =SUM('Monthly Actuals'!D121:F121) -> 0 | F49: =E49-D49 -> 0 | G49: =IFERROR(IF(D49=0,"",F49/D49),"" ) | H49: =SUM('Cost Plan'!G49:I49) -> 0 | I49: =SUM('Monthly Actuals'!G121:I121) -> 0 | J49: =I49-H49 -> 0 | K49: =IFERROR(IF(H49=0,"",J49/H49),"" ) | L49: =SUM('Cost Plan'!J49:L49) -> 0 | M49: =SUM('Monthly Actuals'!J121:L121) -> 0 | N49: =M49-L49 -> 0 | O49: =IFERROR(IF(L49=0,"",N49/L49),"" ) | P49: =SUM('Cost Plan'!M49:O49) -> 0 | Q49: =SUM('Monthly Actuals'!M121:O121) -> 0 | R49: =Q49-P49 -> 0 | S49: =IFERROR(IF(P49=0,"",R49/P49),"" ) | T49: ='Cost Plan'!P49 -> 0 | U49: ='Monthly Actuals'!P121 -> 0 | V49: =U49-T49 -> 0 | W49: =IFERROR(IF(T49=0,"",V49/T49),"" ) | X49: =IF(ISNUMBER(W49),IF(W49>(Config!B7/100),"OVER BUDGET",IF(W49<-(Config!B7/100),"UNDER BUDGET","ON TRACK")),"" )
A50: 46 | B50: ='Initiative Register'!B51 -> INI-047 | C50: ='Initiative Register'!C51 -> PAYROLL – OUTSOURCED CONTRACT OPTIMISATION | D50: =SUM('Cost Plan'!D50:F50) -> 0 | E50: =SUM('Monthly Actuals'!D122:F122) -> 0 | F50: =E50-D50 -> 0 | G50: =IFERROR(IF(D50=0,"",F50/D50),"" ) | H50: =SUM('Cost Plan'!G50:I50) -> 0 | I50: =SUM('Monthly Actuals'!G122:I122) -> 0 | J50: =I50-H50 -> 0 | K50: =IFERROR(IF(H50=0,"",J50/H50),"" ) | L50: =SUM('Cost Plan'!J50:L50) -> 0 | M50: =SUM('Monthly Actuals'!J122:L122) -> 0 | N50: =M50-L50 -> 0 | O50: =IFERROR(IF(L50=0,"",N50/L50),"" ) | P50: =SUM('Cost Plan'!M50:O50) -> 0 | Q50: =SUM('Monthly Actuals'!M122:O122) -> 0 | R50: =Q50-P50 -> 0 | S50: =IFERROR(IF(P50=0,"",R50/P50),"" ) | T50: ='Cost Plan'!P50 -> 0 | U50: ='Monthly Actuals'!P122 -> 0 | V50: =U50-T50 -> 0 | W50: =IFERROR(IF(T50=0,"",V50/T50),"" ) | X50: =IF(ISNUMBER(W50),IF(W50>(Config!B7/100),"OVER BUDGET",IF(W50<-(Config!B7/100),"UNDER BUDGET","ON TRACK")),"" )
A51: 47 | B51: ='Initiative Register'!B52 -> INI-048 | C51: ='Initiative Register'!C52 -> OVERHEAD – ENERGY COST OPTIMISATION | D51: =SUM('Cost Plan'!D51:F51) -> 0 | E51: =SUM('Monthly Actuals'!D123:F123) -> 0 | F51: =E51-D51 -> 0 | G51: =IFERROR(IF(D51=0,"",F51/D51),"" ) | H51: =SUM('Cost Plan'!G51:I51) -> 0 | I51: =SUM('Monthly Actuals'!G123:I123) -> 0 | J51: =I51-H51 -> 0 | K51: =IFERROR(IF(H51=0,"",J51/H51),"" ) | L51: =SUM('Cost Plan'!J51:L51) -> 0 | M51: =SUM('Monthly Actuals'!J123:L123) -> 0 | N51: =M51-L51 -> 0 | O51: =IFERROR(IF(L51=0,"",N51/L51),"" ) | P51: =SUM('Cost Plan'!M51:O51) -> 0 | Q51: =SUM('Monthly Actuals'!M123:O123) -> 0 | R51: =Q51-P51 -> 0 | S51: =IFERROR(IF(P51=0,"",R51/P51),"" ) | T51: ='Cost Plan'!P51 -> 0 | U51: ='Monthly Actuals'!P123 -> 0 | V51: =U51-T51 -> 0 | W51: =IFERROR(IF(T51=0,"",V51/T51),"" ) | X51: =IF(ISNUMBER(W51),IF(W51>(Config!B7/100),"OVER BUDGET",IF(W51<-(Config!B7/100),"UNDER BUDGET","ON TRACK")),"" )
A52: 48 | B52: ='Initiative Register'!B53 -> INI-049 | C52: ='Initiative Register'!C53 -> OVERHEAD – F&B COST OPTIMISATION | D52: =SUM('Cost Plan'!D52:F52) -> 0 | E52: =SUM('Monthly Actuals'!D124:F124) -> 0 | F52: =E52-D52 -> 0 | G52: =IFERROR(IF(D52=0,"",F52/D52),"" ) | H52: =SUM('Cost Plan'!G52:I52) -> 0 | I52: =SUM('Monthly Actuals'!G124:I124) -> 0 | J52: =I52-H52 -> 0 | K52: =IFERROR(IF(H52=0,"",J52/H52),"" ) | L52: =SUM('Cost Plan'!J52:L52) -> 0 | M52: =SUM('Monthly Actuals'!J124:L124) -> 0 | N52: =M52-L52 -> 0 | O52: =IFERROR(IF(L52=0,"",N52/L52),"" ) | P52: =SUM('Cost Plan'!M52:O52) -> 0 | Q52: =SUM('Monthly Actuals'!M124:O124) -> 0 | R52: =Q52-P52 -> 0 | S52: =IFERROR(IF(P52=0,"",R52/P52),"" ) | T52: ='Cost Plan'!P52 -> 0 | U52: ='Monthly Actuals'!P124 -> 0 | V52: =U52-T52 -> 0 | W52: =IFERROR(IF(T52=0,"",V52/T52),"" ) | X52: =IF(ISNUMBER(W52),IF(W52>(Config!B7/100),"OVER BUDGET",IF(W52<-(Config!B7/100),"UNDER BUDGET","ON TRACK")),"" )
A53: 49 | B53: ='Initiative Register'!B54 -> INI-050 | C53: ='Initiative Register'!C54 -> OVERHEAD – CLAIM DENIAL REDUCTION | D53: =SUM('Cost Plan'!D53:F53) -> 0 | E53: =SUM('Monthly Actuals'!D125:F125) -> 0 | F53: =E53-D53 -> 0 | G53: =IFERROR(IF(D53=0,"",F53/D53),"" ) | H53: =SUM('Cost Plan'!G53:I53) -> 0 | I53: =SUM('Monthly Actuals'!G125:I125) -> 0 | J53: =I53-H53 -> 0 | K53: =IFERROR(IF(H53=0,"",J53/H53),"" ) | L53: =SUM('Cost Plan'!J53:L53) -> 0 | M53: =SUM('Monthly Actuals'!J125:L125) -> 0 | N53: =M53-L53 -> 0 | O53: =IFERROR(IF(L53=0,"",N53/L53),"" ) | P53: =SUM('Cost Plan'!M53:O53) -> 0 | Q53: =SUM('Monthly Actuals'!M125:O125) -> 0 | R53: =Q53-P53 -> 0 | S53: =IFERROR(IF(P53=0,"",R53/P53),"" ) | T53: ='Cost Plan'!P53 -> 0 | U53: ='Monthly Actuals'!P125 -> 0 | V53: =U53-T53 -> 0 | W53: =IFERROR(IF(T53=0,"",V53/T53),"" ) | X53: =IF(ISNUMBER(W53),IF(W53>(Config!B7/100),"OVER BUDGET",IF(W53<-(Config!B7/100),"UNDER BUDGET","ON TRACK")),"" )
A54: 50 | B54: ='Initiative Register'!B55 -> INI-051 | C54: ='Initiative Register'!C55 -> OVERHEAD – REVENUE LEAKAGE RECOVERY | D54: =SUM('Cost Plan'!D54:F54) -> 0 | E54: =SUM('Monthly Actuals'!D126:F126) -> 0 | F54: =E54-D54 -> 0 | G54: =IFERROR(IF(D54=0,"",F54/D54),"" ) | H54: =SUM('Cost Plan'!G54:I54) -> 0 | I54: =SUM('Monthly Actuals'!G126:I126) -> 0 | J54: =I54-H54 -> 0 | K54: =IFERROR(IF(H54=0,"",J54/H54),"" ) | L54: =SUM('Cost Plan'!J54:L54) -> 0 | M54: =SUM('Monthly Actuals'!J126:L126) -> 0 | N54: =M54-L54 -> 0 | O54: =IFERROR(IF(L54=0,"",N54/L54),"" ) | P54: =SUM('Cost Plan'!M54:O54) -> 0 | Q54: =SUM('Monthly Actuals'!M126:O126) -> 0 | R54: =Q54-P54 -> 0 | S54: =IFERROR(IF(P54=0,"",R54/P54),"" ) | T54: ='Cost Plan'!P54 -> 0 | U54: ='Monthly Actuals'!P126 -> 0 | V54: =U54-T54 -> 0 | W54: =IFERROR(IF(T54=0,"",V54/T54),"" ) | X54: =IF(ISNUMBER(W54),IF(W54>(Config!B7/100),"OVER BUDGET",IF(W54<-(Config!B7/100),"UNDER BUDGET","ON TRACK")),"" )

Sheet KPI Tracker
A1: KPI TRACKER — FY 2026-27 | Monthly Operational & Financial KPIs vs Target
A2: Enter Annual Target in col D. Enter monthly Actuals in cols F-Q. Benchmark in col E.
A3: # | B3: KPI / Metric | C3: Unit | D3: Annual Target | E3: Benchmark | F3: Apr | G3: May | H3: Jun | I3: Jul | J3: Aug | K3: Sep | L3: Oct | M3: Nov | N3: Dec | O3: Jan | P3: Feb | Q3: Mar | R3: YTD Avg
A4: REVENUE & VOLUME
A5: 1 | B5: Total Revenue (Rs Lakhs) | C5: Rs Lkh | R5: =IFERROR(AVERAGEIF(F5:Q5,"<>0"),"" )
A6: 2 | B6: OP Footfall | C6: Nos | R6: =IFERROR(AVERAGEIF(F6:Q6,"<>0"),"" )
A7: 3 | B7: IP Admissions | C7: Nos | R7: =IFERROR(AVERAGEIF(F7:Q7,"<>0"),"" )
A8: 4 | B8: ARPOB (Rs) | C8: Rs | R8: =IFERROR(AVERAGEIF(F8:Q8,"<>0"),"" )
A9: 5 | B9: ALOS (Days) | C9: Days | R9: =IFERROR(AVERAGEIF(F9:Q9,"<>0"),"" )
A10: 6 | B10: Bed Occupancy % | C10: % | R10: =IFERROR(AVERAGEIF(F10:Q10,"<>0"),"" )
A11: 7 | B11: OT Utilisation % | C11: % | R11: =IFERROR(AVERAGEIF(F11:Q11,"<>0"),"" )
A12: 8 | B12: Surgery Volume | C12: Nos | R12: =IFERROR(AVERAGEIF(F12:Q12,"<>0"),"" )
A13: COST & EFFICIENCY
A14: 9 | B14: Employee Cost % of Revenue | C14: % | R14: =IFERROR(AVERAGEIF(F14:Q14,"<>0"),"" )
A15: 10 | B15: Drug & Consumable % of Revenue | C15: % | R15: =IFERROR(AVERAGEIF(F15:Q15,"<>0"),"" )
A16: 11 | B16: Power Cost (Rs Lakhs) | C16: Rs Lkh | R16: =IFERROR(AVERAGEIF(F16:Q16,"<>0"),"" )
A17: 12 | B17: Revenue per Employee (Rs Lkh) | C17: Rs Lkh | R17: =IFERROR(AVERAGEIF(F17:Q17,"<>0"),"" )
A18: 13 | B18: Cost per Bed per Day (Rs) | C18: Rs | R18: =IFERROR(AVERAGEIF(F18:Q18,"<>0"),"" )
A19: FINANCIAL PERFORMANCE
A20: 14 | B20: EBITDA (Rs Lakhs) | C20: Rs Lkh | R20: =IFERROR(AVERAGEIF(F20:Q20,"<>0"),"" )
A21: 15 | B21: EBITDA Margin % | C21: % | R21: =IFERROR(AVERAGEIF(F21:Q21,"<>0"),"" )
A22: 16 | B22: Gross Margin % | C22: % | R22: =IFERROR(AVERAGEIF(F22:Q22,"<>0"),"" )
A23: 17 | B23: Collection Efficiency % | C23: % | R23: =IFERROR(AVERAGEIF(F23:Q23,"<>0"),"" )
A24: 18 | B24: Debtors Days | C24: Days | R24: =IFERROR(AVERAGEIF(F24:Q24,"<>0"),"" )
A25: QUALITY & PATIENT
A26: 19 | B26: Patient Satisfaction Score | C26: Score/10 | R26: =IFERROR(AVERAGEIF(F26:Q26,"<>0"),"" )
A27: 20 | B27: Readmission Rate % | C27: % | R27: =IFERROR(AVERAGEIF(F27:Q27,"<>0"),"" )
A28: 21 | B28: Infection Rate % | C28: % | R28: =IFERROR(AVERAGEIF(F28:Q28,"<>0"),"" )
A29: CUSTOM KPIs
A30: 22 | R30: =IFERROR(AVERAGEIF(F30:Q30,"<>0"),"" )
A31: 23 | R31: =IFERROR(AVERAGEIF(F31:Q31,"<>0"),"" )
A32: 24 | R32: =IFERROR(AVERAGEIF(F32:Q32,"<>0"),"" )
A33: 25 | R33: =IFERROR(AVERAGEIF(F33:Q33,"<>0"),"" )
A34: 26 | R34: =IFERROR(AVERAGEIF(F34:Q34,"<>0"),"" )

Sheet Initiative Detail Card
A1: INITIATIVE DETAIL CARD — Mini Business Case Template | FY 2026-27
A2: Fill BLUE input cells. Use before entering into Initiative Register.
A3: Initiative Name
A4: Initiative ID | B4: Auto-generated in Register
A5: Function / Department
A6: Owner
A7: Priority | B7: High / Medium / Low
A9: PROBLEM / OPPORTUNITY STATEMENT
A10: What problem does this solve?
A11: What opportunity does this capture?
A13: CURRENT STATE
A14: Current Metric / KPI Value
A15: Source of Data
A17: TARGET STATE
A18: Target KPI Value
A19: Target Timeline
A21: INITIATIVE ACTION PLAN
A22: Key Action Steps
A23: Dependencies / Pre-conditions
... A46: Approved By

Sheet Instructions
A1: AOP EXECUTION WORKBOOK — FY 2026-27 | VPS Lakeshore Hospital
A2: Set up | Step up | Scale up — Workbook is intentionally blank. Team fills in initiatives.
A4: HOW TO USE THIS WORKBOOK
A5: STEP | B5: SHEET | C5: ACTION | D5: BY WHOM
A6: 1 | B6: Config | C6: Set company name, FY, currency, variance threshold. FY27 Budget targets from Budget_AOP_FY27_UC (WB1). | D6: CFO / Admin
A7: 2 | B7: Initiative Register | C7: Functional heads enter their own initiatives. Blank by design. Must cover the EBITDA gap identified in AOP_ReconciliationBridge_FY2627 (WB5). | D7: Functional Heads
A8: 3 | B8: Monthly Plan | C8: For each initiative, mark months Active (1) or Inactive (0). Timeline must align with Grey-Zone resource deployment in AOP_AnalyticsEngine_FY2627 (WB2). | D8: Initiative Owner
A9: 4 | B9: Cost Plan | C9: Enter budgeted cost (Rs Lakhs) per initiative per month. Totals must reconcile with WB5 Cost_Recon_Summary. | D9: Finance / Owner
A10: 5 | B10: Revenue Impact | C10: Enter expected revenue uplift per initiative per month. Totals must reconcile with WB5 Revenue_Recon. | D10: Finance / Owner
A11: 6 | B11: Monthly Actuals | C11: Section A = Actual Revenue Realised | Section B = Actual Cost Incurred. Enter after each month close. | D11: Finance
A12: 7 | B12: Variance Analysis | C12: Auto-calculated. RED = exception over threshold. Review and escalate per governance protocol. | D12: CFO
A13: 8 | B13: KPI Tracker | C13: Track 25+ operational KPIs vs target monthly. Aligned with MPL dept P&L (WB4 / Layer 4). | D13: Operations / Finance
A14: 9 | B14: Dashboard | C14: Executive dashboard — scorecards, financial summary, monthly trend, exception log. Board-ready. | D14: CFO / Board
A15: 10 | B15: Initiative Detail Card | C15: Mini business case + Progress Card per initiative. Row # selector loads live planned vs actual data. | D15: All Initiative Owners
A17: COLOUR CODING LEGEND
A18: BLUE TEXT = Input cells — fill these in
A19: BLACK TEXT = Formula cells — do not overwrite
A20: GREEN TEXT = Values linked from other sheets
A21: RED BACKGROUND = Exception / adverse variance over threshold
A22: YELLOW BACKGROUND = Input required / needs attention

Sheet Config
A1: WORKBOOK CONFIGURATION
A2: Parameter | B2: Value | C2: Notes
A3: Company Name | B3: VPS Lakeshore | C3: Enter organisation name
A4: Financial Year | B4: FY 2026-27 | C4: e.g. FY 2026-27
A5: Currency | B5: INR | C5: INR / USD / AED etc.
A6: Currency Unit | B6: Lakhs | C6: Lakhs / Crores / Thousands
A7: Variance Alert Threshold (%) | B7: 10 | C7: % over budget that triggers RED exception flag
A8: AOP Prepared By
A9: AOP Approved By
A10: Date of Preparation | C10: dd-mmm-yyyy
A13: FUNCTIONAL DEPARTMENTS
A14: Operations
A15: HR & Admin
A16: Finance
A17: IT / Systems
A18: Business Development
A19: Marketing
A20: Clinical Services
A21: Supply Chain / Purchase
A22: Quality & Compliance
